Workbook
Name ActitudinalBAK: 'Taxonomias para RA'!$AC$3:$AG$3
Name Áreasprofesionales: #REF!
Name Bloom: 'Taxonomias para RA'!$G$3:$I$3
Name CognitivoBAK: 'Taxonomias para RA'!$S$3:$X$3
Name ComponentesCompetencias: 'Paso1 Analisis perfil egreso'!$E$2:$G$2
Name ComponentesCompetencias: #REF!
Name ComprenderLK: 'Taxonomias para RA'!$AM$5:$AM$27
Name Creditos: #REF!,#REF!,#REF!,#REF!,#REF!,#REF!,#REF!,#REF!,#REF!
Name EvaluarLK: 'Taxonomias para RA'!$AP$5:$AP$46
Name FACULTADES: #REF!
Name Ocupación: #REF!
Name PercepciónBAK: 'Taxonomias para RA'!$AC$4:$AC$40
Name PrecisiónBAK: Tabla4170[PrecisiónBAK]
Name ProcedimentalB: Tabla5684[ProcedimentalB]
Name ProcedimentalBAK: 'Taxonomias para RA'!$Y$3:$AB$3
Name ProcedimientosLK: Tabla92[ProcedimientosLK]
Name ProcesosAK: Tabla95[ProcesosAK]
Name RA: #REF!
Name RecordarLK: 'Taxonomias para RA'!$AL$5:$AL$27
Name RecuperaciónAK: 'Taxonomias para RA'!$AT$4:$AT$27
Name resultadoaprendizaje: #REF!
Name SíntesisB: Tabla395381[SíntesisB]
Name SíntesisBAK: Tabla3966[SíntesisBAK]
Name taxonomiasra: Tabla1715[Taxonomías]
Name UsoConocimientoAK: 'Taxonomias para RA'!$AW$4:$AW$70
Name ValorarBAK: Tabla4574[ValorarBAK]

Sheet Paso1 Analisis perfil egreso
A1: [Escribir el nombre del programa] | B1: [Escribir la modalidad: presencial o virtual] | C1: [Escribir el perfil profesional del egresado.] | D1: [Escribir el perfil ocupacional del egresado.] | E1: Componentes fundamentales aplicables a la solución de problemas en la vida profesional [Listar, según lo escrito en el perfil profesional, qué debe saber el egresado en las categorías de Saber -conocimientos, hechos, teorías-, Saber hacer -técnicas, procedimientos, metodologías-, y Saber ser -valores, condiciones, etc.] | H1: Componentes fundamentales de la ocupación laboral del profesional [Listar, según lo escrito en el perfil ocupacional, en qué áreas, qué tareas potenciales y en qué poblaciones o contextos podrá laborar el profesional.] | K1: Diferencial (valor agregado) del profesional [Listar, según lo escrito en los perfiles, los elementos que son diferenciales y generan un valor agregado al egresado.]
A2: Programa | B2: Modalidad | C2: Perfil profesional | D2: Perfil ocupacional | E2: Saber | F2: SaberHacer | G2: SaberSer | H2: Áreas profesionales | I2: Tareas profesionales | J2: Poblaciones actuación | K2: Valor agregado
A3: Técnica Profesional Judicial | B3: Virtual | C3: El Técnico Profesional Judicial aplica con visión crítica, ética e integral, los procedimientos y las técnicas jurídicas asociadas a las diferentes áreas del derecho, para asistir al abogado en la resolución de conflictos, de acuerdo con la realidad de la zona geográfica en la que se encuentre, aprovechando diversas tecnologías en los entornos virtuales o presenciales y caracterizándose por su capacidad oral, elaboración de textos jurídicos, así como por la implementación de técnicas archivísticas, de gestión documental, derecho inmobiliario y digitalización del derecho. | D3: El Técnico Profesional Judicial del Politécnico Grancolombiano está en capacidad de: - Ejercer cargos auxiliares o asistenciales con conocimientos legales claros y prácticos en asuntos sustanciales, procedimentales y logísticos tanto en el sector público como en el privado. - Desempeñar actividades que requieran el uso de tecnologías de la información y la comunicación, implementando sistemas de información documental de acuerdo con las técnicas archivísticas, y de elaboración de textos jurídicos y contractuales asignados en sus labores operativas dentro del área judicial, en cargos tales como escribientes, de secretariado, asistentes, sustanciadores, archivistas, entre otros. | E3: Procesos y procedimientos en derecho penal, laboral, civil, público y mercantil | F3: gestionar una correcta administración de justicia | G3: con un criterio ético y responsable en la aplicación de las normas | H3: Asistente jurídico / Auxiliar judicial / Auxiliar de tribunales / Secretario jurídico / Redactor jurídico / Técnico sustanciador / Citador sustanciador / Técnico en documentación procesal / Auxiliar de archivo jurídico / Gestor de gestión documental / Documentalista legal / Operador de digitalización jurídica / Gestor de información jurídica / Técnico administrativo jurídico / Técnico en seguimiento normativo / Asistente administrativo jurídico / Facilitador de resolución de conflictos / Asistente de conciliación / Técnico en mediación legal / Analista auxiliar de riesgos legales / Coordinador de agenda jurídica / Secretario ejecutivo judicial / Técnico investigador judicial / Investigador judicial / Gestor de proyectos de justicia digital / Auxiliar jurídico en entidades judiciales públicas o privadas / Técnico o asistente en derecho de consumo y competencia / Auxiliar en derecho registral e inmobiliario / Técnico en derecho laboral y seguridad social / Auxiliar de apoyo en derecho empresarial y societario / Técnico o gestor en acciones constitucionales / Auxiliar de análisis de datos jurídicos y estadística judicial / Técnico en procedimientos administrativos y control de términos / Apoyo técnico en investigación penal y criminalística básica. | I3: Elaborar escritos jurídicos como demandas, memoriales y oficios según lineamientos procesales / Apoyar en la organización y seguimiento de procesos judiciales y administrativos / Recopilar información normativa y jurisprudencial para apoyar sustanciaciones / Redactar contratos, actas, poderes y minutas con base en modelos normativos vigentes / Revisar la coherencia y la estructura legal de documentos antes de su firma o radicación / Clasificar expedientes judiciales según su naturaleza y fase procesal / Cargar, actualizar y consultar información jurídica en sistemas de gestión documental / Digitalizar expedientes físicos asegurando calidad de imagen y respaldo en la nube / Apoyar la elaboración de actas de audiencia de conciliación y acuerdos logrados / Orientar a las partes en los pasos para acceder a mecanismos alternativos de resolución / Sistematizar casos atendidos en centros de conciliación mediante bases de datos / Elaborar oficios, comunicaciones internas y reportes para entidades jurídicas / Coordinar el uso de recursos logísticos para el desarrollo de actividades legales / Participar en la recopilación de datos legales para análisis de riesgos normativos / Apoyar la implementación de herramientas tecnológicas para la transformación digital en entornos jurídicos / Elaborar reportes técnicos sobre cumplimiento documental y normativo / Tramitar y registrar documentos de propiedad y actos de comercio ante cámaras de comercio y notarías / Gestionar trámites relacionados con compraventa, arrendamiento y sociedades / Apoyar la preparación de acciones constitucionales (tutelas, habeas corpus, habeas data) / Realizar seguimiento al cumplimiento de fallos constitucionales o administrativos / Tramitar solicitudes ante entidades públicas y realizar control de términos legales / Apoyar la radicación y seguimiento de denuncias penales / Colaborar en la organización de expedientes y pruebas en procesos penales / Gestionar citaciones y notificaciones en procedimientos penales / Elaborar liquidaciones básicas de prestaciones sociales y nómina / Tramitar afiliaciones, novedades y reportes ante el sistema de seguridad social / Gestionar reclamaciones laborales ante el Ministerio de Trabajo o juzgados laborales / Realizar estudios de títulos básicos y verificación de certificados de tradición y libertad / Tramitar inscripciones, cancelaciones e hipotecas ante oficinas de registro / Gestionar licencias o autorizaciones para actos jurídicos sobre inmuebles / Implementar bases de datos para análisis de procesos judiciales y administrativos / Elaborar visualizaciones y reportes estadísticos sobre la gestión jurídica / Administrar repositorios digitales de información legal con control de acceso / Facilitar procesos de mediación comunitaria o empresarial / Tramitar reclamaciones de consumidores ante autoridades competentes / Apoyar en investigaciones sobre prácticas restrictivas de la competencia / Elaborar informes de cumplimiento de normas de protección al consumidor / Apoyar en la constitución, modificación y disolución de sociedades / Elaborar actas de asambleas y juntas de socios / Gestionar registros y renovaciones de matrícula mercantil / Diseñar y presentar propuestas de servicios jurídicos para emprendimientos / Elaborar planes de negocio para empresas del sector legal / Coordinar alianzas estratégicas con otras entidades o profesionales. | J3: Juzgados, tribunales y altas cortes / Fiscalías y procuradurías/ Contralorías y personerías municipales o departamentales / Centros de conciliación y arbitraje / Ministerios y secretarías con áreas jurídicas /Alcaldías y gobernaciones / Entidades descentralizadas con gestión legal (superintendencias, institutos, agencias) / Empresas y corporaciones con unidades legales internas / Firmas de abogados y consultoras jurídicas / Cámaras de comercio y gremios empresariales/Compañías de seguros y bancos en gestión legal y de contratos / Notarías urbanas y rurales/Oficinas de registro de instrumentos públicos / Dependencias de registro mercantil / Empresas de custodia y digitalización de archivos / Dependencias archivísticas de entidades públicas o privadas con alto volumen documental jurídico / Organizaciones no gubernamentales con proyectos de acceso a la justicia. | K3: El egresado de la Técnica Profesional Judicial del Politécnico Grancolombiano se forma con una combinación de fundamentos jurídicos en las diferentes áreas del derecho y herramientas tecnológicas aplicadas al ejercicio legal, que incluyen digitalización del derecho, análisis de datos jurídicos y prácticas en ambientes simulados que replican escenarios reales de la administración de justicia. Esta formación le permite desenvolverse con solvencia en la gestión de expedientes y procesos tanto en entornos físicos como virtuales, responder a los retos de transformación digital en el sector legal y adaptarse a diferentes contextos de trabajo. La articulación de estos elementos con las exigencias actuales del mercado fortalece su proyección laboral en notarías, despachos judiciales, áreas jurídicas corporativas y organismos de control, generando una preparación alineada con las tendencias de modernización y eficiencia en la administración de justicia.
E4: Procesos archivísticos y de digitalización del derecho | F4: categorizar la información judicial de los expedientes | G4: de acuerdo con las necesidades de la organización
E5: Textos jurídicos y contractuales en las diferentes áreas del derecho | F5: documentar la voluntad de las partes | G5: teniendo en cuenta el orden y las etapas necesarias de los actos jurídicos.
E6: Conflictos objeto de negociación | F6: apoyar en su resolución | G6: a través de métodos alternativos hetero compositivos y autocompositivos
E7: Fenómenos contemporáneos | F7: reconocer sus afectaciones o contribuciones en el marco de las ciudadanías globales y de una sociedad responsable y sostenible | G7: desde una perspectiva glocal, soportada en datos, con una mirada ética y crítica

Sheet Paso 2 Redacción competen
A1: Elementos para redactar las competencias que desarrollará el programa
A2: [Enumerar las competencias que se van a declarar.] | B2: [A partir de la celda B2 dar clic sobre el ícono de lista desplegable y elegir el verbo que considere adecuado.] | C2: [A partir de la celda C2 dar clic sobre la lista desplegable y elegir el saber extraído del perfil de egreso.] | D2: [Escribir para qué se abordará el saber elegido. Se sugiere apoyarse en el saber hacer.] | E2: [Escribir la condición describiendo los referentes, parámetros, principios, requerimientos o retos que se necesitan para alcanzar las características del perfil en el contexto donde el egresado se desenvolverá.] | F2: [Articular los componentes. Iniciar con el verbo, continuar con el objeto conceptual, luego la finalidad y condición de contexto o referencia; estos últimos no requieren un orden particular.] | G2: [Escribir el tipo de competencia del perfil: Específica (si es del bloque Disciplinar para pregrado o de los componentes para el caso de posgrado) o Genérica (si aplica bloque institucional pregrado)]
A3: No. | B3: VerboCompetencia | C3: Objeto conceptual | D3: Finalidad | E3: Condición de contexto o referencia | F3: RedacciónCompetencia | G3: Tipo de Competencia
A4: 1 | B4: Desarrollar | C4: Procesos y procedimientos en derecho penal, laboral, civil, público y mercantil | D4: gestionar una correcta administración de justicia, | E4: con un criterio ético y responsable en la aplicación de las normas | F4: Desarrollar procesos y procedimientos en derecho penal, laboral, civil, público y mercantil para gestionar una correcta administración de justicia, con un criterio ético y responsable en la aplicación de las normas. | G4: Específica
A5: 2 | B5: Implementar | C5: Procesos archivísticos y de digitalización del derecho | D5: categorizar la información judicial de los expedientes | E5: de acuerdo con las necesidades de la organización | F5: Implementar procesos archivísticos y de digitalización del derecho de acuerdo con las necesidades de la organización, para categorizar la información judicial de los expedientes. | G5: Específica
A6: 3 | B6: Elaborar | C6: Textos jurídicos y contractuales en las diferentes áreas del derecho | D6: documentar la voluntad de las partes | E6: teniendo en cuenta el orden y las etapas necesarias de los actos jurídicos. | F6: Elaborar textos jurídicos y contractuales en las diferentes áreas del derecho para documentar la voluntad de las partes, teniendo en cuenta el orden y las etapas necesarias de los actos jurídicos. | G6: Específica
A7: 4 | B7: Conocer | C7: Conflictos objeto de negociación | D7: apoyar en su resolución | E7: a través de métodos alternativos hetero compositivos y autocompositivos | F7: Conocer los conflictos objeto de negociación para apoyar en su resolución a través de métodos alternativos hetero compositivos y autocompositivos. | G7: Específica
A8: 5 | B8: Analizar | C8: Fenómenos contemporáneos | D8: reconocer sus afectaciones o contribuciones en el marco de las ciudadanías globales y de una sociedad responsable y sostenible | E8: desde una perspectiva glocal, soportada en datos, con una mirada ética y crítica | F8: Analizar los fenómenos contemporáneos desde una perspectiva glocal, soportada en datos, con una mirada ética y crítica, para reconocer sus afectaciones o contribuciones en el marco de las ciudadanías globales y de una sociedad responsable y sostenible. | G8: Genérica

Sheet Paso 3 Redacción RA 
A1: [A partir de la celda A2 dar clic en la lista desplegable y seleccionar la competencia redactada en el paso 2.] | B1: [Enumerar los resultados de aprendizaje que se van a declarar.] | C1: [A partir de la celda C2, dar clic en la lista desplegable y elegir el tipo de dominio a tratar en el resultado de aprendizaje.] | D1: [A partir de la cela D2, dar clic en la lista desplegable y elegir el saber correspondiente al dominio.] | E1: [A partir de la celda E2, dar clic en la lista desplegable y elegir la taxonomía que se considere adecuada, solo se elige una para todos los saberes.] | F1: [A partir de la celda F2, dar clic en la lista desplegable y elegir el dominio que se considera adecuado.] | G1: [A partir de la celda G2, dar clic en la lista desplegable y elegir el nivel del dominio que se considera adecuado.] | H1: [A partir de la celda H2, dar clic en la lista desplegable y elegir el verbo que se considera adecuado.] | I1: [Iniciar con el verbo elegido (columna H), en infinitivo, luego el objeto sobre el cual recae la acción (columna D) y finalmente la condición de contexto (académico, disciplinar, social u otro).]
A2: Competencia por desarrollar | B2: Número de resultado | C2: TipoSaber | D2: SaberAsociado | E2: Taxonomía | F2: Dominio Asociado | G2: Nivel Dominio | H2: Verbo RA | I2: Resultados Aprendizaje
A3: Desarrollar procesos y procedimientos en derecho penal, laboral, civil, público y mercantil para gestionar una correcta administración de justicia, con un criterio ético y responsable en la aplicación de las normas. | B3: 1 | C3: Saber | D3: Procesos y procedimientos en derecho penal, laboral, civil, público y mercantil | E3: Bloom | F3: CognitivoB | G3: ComprensiónB | H3: Identificar | I3: Identifica los procesos y procedimientos asociados a las diferentes áreas del derecho para estructurar las etapas necesarias y lo que de ellas se deriva, en la resolución de conflictos judiciales y extra judiciales.
A4: Desarrollar procesos y procedimientos en derecho penal, laboral, civil, público y mercantil para gestionar una correcta administración de justicia, con un criterio ético y responsable en la aplicación de las normas. | B4: 4 | C4: Saberhacer | D4: gestionar una correcta administración de justicia, | E4: Bloom | F4: ProcedimentalB | G4: AplicaciónB | H4: Emplear | I4: Emplea los procesos y procedimientos que permiten gestionar una correcta administración de justicia, para generar los soportes documentales o verbales que apoyan la resolución de conflictos objeto de negociación, en las diferentes áreas del derecho.
A5: Desarrollar procesos y procedimientos en derecho penal, laboral, civil, público y mercantil para gestionar una correcta administración de justicia, con un criterio ético y responsable en la aplicación de las normas. | B5: 6 | C5: Saberser | D5: con un criterio ético y responsable en la aplicación de las normas. | E5: Bloom | F5: ActitudinalB | G5: AplicaciónB | H5: Aplicar | I5: Aplica adecuadamente técnicas, procesos, procedimientos y métodos propios del actuar jurídico y de la gestión documental judicial, para plantear soluciones acordes con la normatividad y con las necesidades identificadas en el contexto o en el objeto de negociación en la etapa judicial o extra judicial, según corresponda.
A6: Implementar procesos archivísticos y de digitalización del derecho de acuerdo con las necesidades de la organización, para categorizar la información judicial de los expedientes. | B6: 2 | C6: Saber | D6: Procesos archivísticos y de digitalización del derecho | E6: Bloom | F6: CognitivoB | G6: ConocimientoB | H6: Reconocer | I6: Reconoce los textos jurídicos y contractuales que se deben generar en las diferentes áreas del derecho, para determinar el proceso archivístico o de digitalización que permite organizar y gestionar la documentación de información en las entidades.
A7: Implementar procesos archivísticos y de digitalización del derecho de acuerdo con las necesidades de la organización, para categorizar la información judicial de los expedientes. | B7: 5 | C7: Saberhacer | D7: categorizar la información judicial de los expedientes | E7: Bloom | F7: ProcedimentalB | G7: AplicaciónB | H7: Aplicar | I7: Aplica técnicas para categorizar o documentar información acatando los requisitos establecidos en la normatividad sustancial y procesal, así como de la voluntad de los intervinientes.
A8: Implementar procesos archivísticos y de digitalización del derecho de acuerdo con las necesidades de la organización, para categorizar la información judicial de los expedientes. | B8: 6 | C8: Saberser | D8: de acuerdo con las necesidades de la organización | E8: Bloom | F8: ActitudinalB | G8: AplicaciónB | H8: Aplicar | I8: Aplica adecuadamente técnicas, procesos, procedimientos y métodos propios del actuar jurídico y de la gestión documental judicial, para plantear soluciones acordes con la normatividad y con las necesidades identificadas en el contexto o en el objeto de negociación en la etapa judicial o extra judicial, según corresponda.
A9: Elaborar textos jurídicos y contractuales en las diferentes áreas del derecho para documentar la voluntad de las partes, teniendo en cuenta el orden y las etapas necesarias de los actos jurídicos. | B9: 2 | C9: Saber | D9: Textos jurídicos y contractuales en las diferentes áreas del derecho | E9: Bloom | F9: CognitivoB | G9: Conocimientos | H9: Reconocer | I9: Reconoce los textos jurídicos y contractuales que se deben generar en las diferentes áreas del derecho, para determinar el proceso archivístico o de digitalización que permite organizar y gestionar la documentación de información en las entidades.
A10: Elaborar textos jurídicos y contractuales en las diferentes áreas del derecho para documentar la voluntad de las partes, teniendo en cuenta el orden y las etapas necesarias de los actos jurídicos. | B10: 5 | C10: Saberhacer | D10: documentar la voluntad de las partes, | E10: Bloom | F10: ProcedimentalB | G10: AplicaciónB | H10: Aplicar | I10: Aplica técnicas para categorizar o documentar información acatando los requisitos establecidos en la normatividad sustancial y procesal, así como de la voluntad de los intervinientes.
A11: Elaborar textos jurídicos y contractuales en las diferentes áreas del derecho para documentar la voluntad de las partes, teniendo en cuenta el orden y las etapas necesarias de los actos jurídicos. | B11: 6 | C11: Saberser | D11: teniendo en cuenta el orden y las etapas necesarias de los actos jurídicos. | E11: Bloom | F11: ActitudinalB | G11: AplicaciónB | H11: Aplicar | I11: Aplica adecuadamente técnicas, procesos, procedimientos y métodos propios del actuar jurídico y de la gestión documental judicial, para plantear soluciones acordes con la normatividad y con las necesidades identificadas en el contexto o en el objeto de negociación en la etapa judicial o extra judicial, según corresponda.
A12: Conocer los conflictos objeto de negociación para apoyar en su resolución a través de métodos alternativos hetero compositivos y autocompositivos. | B12: 1 | C12: Saber | D12: Conflictos objeto de negociación | E12: Bloom | F12: CognitivoB | G12: ComprensiónB | H12: Identificar | I12: Identifica los procesos y procedimientos asociados a las diferentes áreas del derecho para estructurar las etapas necesarias y lo que de ellas se deriva, en la resolución de conflictos judiciales y extra judiciales.
A13: Conocer los conflictos objeto de negociación para apoyar en su resolución a través de métodos alternativos hetero compositivos y autocompositivos. | B13: 4 | C13: Saberhacer | D13: apoyar en su resolución | E13: Bloom | F13: ProcedimentalB | G13: AplicaciónB | H13: Emplear | I13: Emplea los procesos y procedimientos que permiten gestionar una correcta administración de justicia, para generar los soportes documentales o verbales que apoyan la resolución de conflictos objeto de negociación, en las diferentes áreas del derecho.
A14: Conocer los conflictos objeto de negociación para apoyar en su resolución a través de métodos alternativos hetero compositivos y autocompositivos. | B14: 6 | C14: Saberser | D14: a través de métodos alternativos hetero compositivos y autocompositivos. | E14: Bloom | F14: ActitudinalB | G14: AplicaciónB | H14: Aplicar | I14: Aplica adecuadamente técnicas, procesos, procedimientos y métodos propios del actuar jurídico y de la gestión documental judicial, para plantear soluciones acordes con la normatividad y con las necesidades identificadas en el contexto o en el objeto de negociación en la etapa judicial o extra judicial, según corresponda.
A15: Analizar los fenómenos contemporáneos desde una perspectiva glocal, soportada en datos, con una mirada ética y crítica, para reconocer sus afectaciones o contribuciones en el marco de las ciudadanías globales y de una sociedad responsable y sostenible. | B15: 3 | C15: Saber | D15: Fenómenos contemporáneos | E15: Bloom | F15: CognitivoB | G15: ComprensiónB | H15: Identificar | I15: Identifica fenómenos contemporáneos y su relación con la profesión, para determinar sus impactos e influencia en la sociedad, de forma responsable y crítica.

Sheet Paso 4 Estrategias mesocurricu
A1: [A partir de la celda A3 despliegue el(los) resultado(s) de aprendizaje y elegir aquel (aquellos) al(a los) que se contribuye desde la estrategia.] | B1: [Escribir el nombre de la estrategia a desarrollar. Participación de los estudiantes en cursos, talleres, seminarios, conferencias, pruebas estandarizadas, investigaciones, actividades o experiencias, cuerpos académicos, redes, comunidades, la elaboración de textos y materiales, así como las publicaciones, entre otros.] | C1: [Describir la(s) estrategia(s) definidas por el programa.] | D1: [Escribir los indicadores de impacto de la estrategia. Se sugieren indicadores como: Valora el nivel de contribución de la estrategia a los resultados de aprendizaje; Número de estudiantes que participan en la estrategia; Número de veces que se realiza la estrategia, entre otros.] | E1: [Escribir las acciones de retroalimentación que usará el programa para comunicar a los estudiantes sobre el alcance de sus resultados de aprendizaje.] | F1: [Escribir, para cada indicador con qué instrumento se recogerá información para evidenciar el (los) impacto (s) declarados. Encuesta, lista de asistencia, informe, entre otros.]
A2: Resultado de aprendizaje | B2: Estrategia del programa | C2: Descripción | D2: Indicador de Impacto de la Estrategia | E2: Acciones de retroalimentación para los estudiantes | F2: Instrumentos de medición
A3: Identifica los procesos y procedimientos asociados al derecho penal, laboral, civil, público y mercantil, para estructurar su forma de uso en el desarrollo de conflictos objeto de negociación. | B3: Eventos académicos nacionales e internacionales | C3: Organización de encuentros con expertos nacionales e internacionales del ámbito jurídico, orientados a la actualización en tendencias, análisis en derecho comparado, cambios normativos y buenas prácticas del derecho. Estos espacios fortalecen el pensamiento crítico, amplían la perspectiva profesional y fomentan redes de contacto en el sector legal. | D3: Número de estudiantes del programa que participan en la estrategia. | E3: Informar y formar sobre las tendencias, cambios normativos y buenas prácticas compartidas por expertos, promoviendo su apropiación y aplicación en contextos jurídicos reales. | F3: Listado de participación
A4: Aplica las técnicas para categorizar o documentar información acatando los requisitos establecidos en la normatividad sustancial y procesal, así como de la voluntad de los intervinientes. | D4: Valoración de los estudiantes de la contribución que da la estrategia a los resultados de aprendizaje asociados. | F4: Encuesta
A5: Emplea los procesos y procedimientos que permiten gestionar una correcta administración de justicia, para generar los soportes documentales o verbales que apoyan la resolución de conflictos objeto de negociación, en las diferentes áreas del derecho. | D5: Número de eventos realizados en el periodo de tiempo que establezca el programa. | F5: Reporte o Informe
A6: Emplea los procesos y procedimientos que permiten gestionar una correcta administración de justicia, para generar los soportes documentales o verbales que apoyan la resolución de conflictos objeto de negociación, en las diferentes áreas del derecho. | B6: Misiones internacionales | C6: Experiencias académicas y culturales con entidades, organismos o expertos disciplinares del exterior que incluyen congresos, seminarios, diplomados y encuentros, permitiendo ampliar el conocimiento de diversos sistemas jurídicos con análisis en derecho comparado y el intercambio de buenas prácticas en la administración de justicia. | D6: Número de estudiantes del programa que participan en la estrategia. | E6: Formar y ayudar a decidir sobre la participación en experiencias académicas internacionales, orientando al estudiante en la valoración de beneficios académicos y profesionales. | F6: Listado de participación
A7: Aplica adecuadamente técnicas, procesos y métodos propios del actuar jurídico y de la gestión documental judicial, para plantear soluciones acordes a las necesidades identificadas en el contexto o al objeto de negociación cuando corresponda. | D7: Valoración de los estudiantes de la contribución que da la estrategia a los resultados de aprendizaje asociados. | F7: Encuesta
A8: Aplica adecuadamente técnicas, procesos y métodos propios del actuar jurídico y de la gestión documental judicial, para plantear soluciones acordes a las necesidades identificadas en el contexto o al objeto de negociación cuando corresponda. | D8: Número de misiones realizadas en el periodo de tiempo que establezca el programa. | F8: Reporte o Informe
A9: Identifica los procesos y procedimientos asociados al derecho penal, laboral, civil, público y mercantil, para estructurar su forma de uso en el desarrollo de conflictos objeto de negociación. | B9: Análisis de empleabilidad y proyección de impacto como egresados hacia las comunidades | C9: Revisión sistemática de la demanda laboral de técnicos judiciales en el sector público y privado, identificando oportunidades de inserción laboral y áreas de impacto social, con el propósito de retroalimentar el plan de estudios y fortalecer la pertinencia del perfil profesional. | D9: Número de estudiantes que participan en las convocatorias a concursos de la rama judicial o que están vinculados laboralmente en actividades jurídicas. | E9: Informar y prevenir respecto a las tendencias del mercado laboral para técnicos judiciales, anticipando competencias y habilidades requeridas por el sector público y privado. | F9: Listado de participación
A10: Aplica las técnicas para categorizar o documentar información acatando los requisitos establecidos en la normatividad sustancial y procesal, así como de la voluntad de los intervinientes. | D10: Número de veces que se participa en las convocatorias a concursos de la rama judicial. | F10: Reporte o Informe
A11: Emplea los procesos y procedimientos que permiten gestionar una correcta administración de justicia, para generar los soportes documentales o verbales que apoyan la resolución de conflictos objeto de negociación, en las diferentes áreas del derecho.
A12: Reconoce los textos jurídicos y contractuales que se deben generar en las situaciones jurídicas de las diferentes áreas del derecho, para determinar el proceso archivístico y de gestión documental que permite organizar la información en las entidades judiciales.
A13: Aplica adecuadamente técnicas, procesos y métodos propios del actuar jurídico y de la gestión documental judicial, para plantear soluciones acordes a las necesidades identificadas en el contexto o al objeto de negociación cuando corresponda.
A14: Identifica los procesos y procedimientos asociados al derecho penal, laboral, civil, público y mercantil, para estructurar su forma de uso en el desarrollo de conflictos objeto de negociación. | B14: Elaboración de textos jurídicos | C14: Desarrollo de talleres y ejercicios prácticos enfocados en la producción de documentos jurídicos contractuales y procedimentales, con énfasis en la estructura normativa, el rigor técnico y el uso preciso del lenguaje jurídico para contextos reales. | D14: Número de estudiantes del programa que participan en la estrategia. | E14: Formar y prevenir sobre errores comunes en la redacción de documentos jurídicos, fortaleciendo la precisión técnica en materia de elementos esenciales y de validez y el uso correcto del lenguaje jurídico. | F14: Listado de participación
A15: Emplea los procesos y procedimientos que permiten gestionar una correcta administración de justicia, para generar los soportes documentales o verbales que apoyan la resolución de conflictos objeto de negociación, en las diferentes áreas del derecho. | D15: Número de documentos y situaciones simuladas generados en el curso de práctica simulada. | F15: Reporte o Informe
A16: Aplica adecuadamente técnicas, procesos y métodos propios del actuar jurídico y de la gestión documental judicial, para plantear soluciones acordes a las necesidades identificadas en el contexto o al objeto de negociación cuando corresponda. | D16: Número de documentos publicados producto de proyectos de semilleros. | F16: Registros en Alejandría u otros repositorios
A17: Reconoce los textos jurídicos y contractuales que se deben generar en las situaciones jurídicas de las diferentes áreas del derecho, para determinar el proceso archivístico y de gestión documental que permite organizar la información en las entidades judiciales.
A18: Aplica las técnicas para categorizar o documentar información acatando los requisitos establecidos en la normatividad sustancial y procesal, así como de la voluntad de los intervinientes.
A19: Identifica los procesos y procedimientos asociados al derecho penal, laboral, civil, público y mercantil, para estructurar su forma de uso en el desarrollo de conflictos objeto de negociación. | B19: Clases espejo nacional e internacional | C19: Implementación de sesiones académicas sincrónicas en modalidad de una o doble vía, donde docentes y estudiantes interactúan con grupos de universidades nacionales e internacionales para contrastar enfoques jurídicos, conocer postulados internacionales y reforzar el aprendizaje en disciplinas del derecho sustancial. | D19: Participación de los estudiantes en las clases espejo en doble vía a las que son convocados. | E19: Formar e informar sobre enfoques y postulados jurídicos nacionales e internacionales, incentivando la comparación crítica normativa y la aplicación contextualizada del conocimiento. | F19: Listados de participación
A20: Emplea los procesos y procedimientos que permiten gestionar una correcta administración de justicia, para generar los soportes documentales o verbales que apoyan la resolución de conflictos objeto de negociación, en las diferentes áreas del derecho. | D20: Número de tutores del programa que participan en la estrategia. | F20: Listados de participación
A21: Aplica adecuadamente técnicas, procesos y métodos propios del actuar jurídico y de la gestión documental judicial, para plantear soluciones acordes a las necesidades identificadas en el contexto o al objeto de negociación cuando corresponda. | D21: Número de veces que se implementa la estrategia semestralmente. | F21: Reporte o Informe
A22: Reconoce los textos jurídicos y contractuales que se deben generar en las situaciones jurídicas de las diferentes áreas del derecho, para determinar el proceso archivístico y de gestión documental que permite organizar la información en las entidades judiciales.
A23: Aplica las técnicas para categorizar o documentar información acatando los requisitos establecidos en la normatividad sustancial y procesal, así como de la voluntad de los intervinientes.
A24: Identifica los procesos y procedimientos asociados al derecho penal, laboral, civil, público y mercantil, para estructurar su forma de uso en el desarrollo de conflictos objeto de negociación. | B24: Socialización prácticas simuladas del programa | C24: Presentación de casos y textos jurídicos elaborados en el módulo virtual de prácticas simuladas, evidenciando la aplicación práctica de procedimientos judiciales y la suficiencia en el manejo de las diferentes áreas del derecho, con retroalimentación académica entre pares y docentes. | D24: Valoración de los estudiantes de la contribución que da la estrategia a los resultados de aprendizaje asociados. | E24: Formar a los estudiantes en temas disciplinares y en su aplicación dentro de contextos procedimentales. Informar y formar mediante la apropiación social del conocimiento, compartiendo las experiencias de prácticas en ambientes simulados y el saber generado por los estudiantes del programa. | F24: Reporte o Informe
A25: Emplea los procesos y procedimientos que permiten gestionar una correcta administración de justicia, para generar los soportes documentales o verbales que apoyan la resolución de conflictos objeto de negociación, en las diferentes áreas del derecho. | D25: Presenta la fundamentación jurídica en la sustentación de argumentos verbales que permitan resolver un caso ante jurados, desde los diferentes énfasis del derecho con uso de MASC en primera instancia. | F25: Reporte o Informe participación en eventos de proyección social con las comunidades
A26: Aplica adecuadamente técnicas, procesos y métodos propios del actuar jurídico y de la gestión documental judicial, para plantear soluciones acordes a las necesidades identificadas en el contexto o al objeto de negociación cuando corresponda. | D26: Desarrolla la solución de problemas formulados a partir de un cuestionario que integra todas las áreas el derecho y los MASC. | F26: Reporte o Informe resultado de las pruebas Saber TyT
A27: Reconoce los textos jurídicos y contractuales que se deben generar en las situaciones jurídicas de las diferentes áreas del derecho, para determinar el proceso archivístico y de gestión documental que permite organizar la información en las entidades judiciales. | D27: Estudiantes que aprueban con promedio superior a 450 puntos de 500, el módulo de practica en ambiente simulados. | F27: Reporte o Informe
A28: Aplica las técnicas para categorizar o documentar información acatando los requisitos establecidos en la normatividad sustancial y procesal, así como de la voluntad de los intervinientes.
A29: Identifica los procesos y procedimientos asociados al derecho penal, laboral, civil, público y mercantil, para estructurar su forma de uso en el desarrollo de conflictos objeto de negociación. | B29: Curso de preparación para el examen Saber TyT | C29: Programa de formación virtual semestral tipo MOOC orientado a reforzar las competencias genéricas evaluadas en el examen Saber TyT, que incluye caja de herramientas, cápsulas de formación, guías de orientación Saber TyT ICFES, sesiones sincrónicas con expertos en competencias ciudadanas, inglés, razonamiento cuantitativo, comunicación escrita y lectura crítica. | D29: Número de estudiantes del programa que participan en la estrategia. | E29: Formar a los estudiantes en contenidos y competencias clave de la profesión evaluadas en las pruebas Saber TyT. Prevenir dificultades y orientar la toma de decisiones académicas a partir del análisis de los resultados obtenidos durante el proceso de preparación y simulación del examen. | F29: Listados de participación
A30: Emplea los procesos y procedimientos que permiten gestionar una correcta administración de justicia, para generar los soportes documentales o verbales que apoyan la resolución de conflictos objeto de negociación, en las diferentes áreas del derecho. | D30: Número de veces que se implementa la estrategia semestralmente. | F30: Reporte o Informe
A31: Aplica adecuadamente técnicas, procesos y métodos propios del actuar jurídico y de la gestión documental judicial, para plantear soluciones acordes a las necesidades identificadas en el contexto o al objeto de negociación cuando corresponda. | D31: Resultados de las pruebas Saber TyT en comparación con la media de resultados institucional y nacional. | F31: Reporte o Informe
A32: Reconoce los textos jurídicos y contractuales que se deben generar en las situaciones jurídicas de las diferentes áreas del derecho, para determinar el proceso archivístico y de gestión documental que permite organizar la información en las entidades judiciales. | D32: Puntaje superior en la solución de problemas formulados para la redacción del texto argumentativo que se requieren en la prueba general de Saber TyT. | F32: Reporte o Informe

Sheet Paso 5 Estrategias micro
A1: [Estas celdas se diligencian automáticamente. No ajustar.] | B1: [A partir de la celda A3 despliegue el(los) resultado(s) de aprendizaje y elija aquel (aquellos) al(a los) que se contribuye desde la asignatura o módulo).] | C1: [Escribir el semestre en el que se cursa la asignatura o módulo.] | D1: [Escribir el nombre de la asignatura o módulo que contribuye al logro del resultado de aprendizaje.] | E1: [Redactar los indicadores iniciando con el verbo en presente indicativo, luego el objeto conceptual y finalmente el complemento de oración (que indique una condición o finalidad, con, para, de, entre otros conectores).] | F1: [Escribir la tipología: T (teórico), P (Práctico), TP (Teórico Práctico)] | G1: [Marcar con X el bloque o componente al que pertenece la asignatura o módulo. Por favor ajustar para posgrado, eliminar una columna y ubicar los títulos C.Fundamentación y C.Profundización.] | J1: [Escribir el número de créditos de la asignatura o módulo] | K1: [Escribir el número de horas de trabajo directo: 16*# o 12*#, para presencial o virtual, según sea el caso.] | L1: [Escribir el número de horas de trabajo independiente: 32*# columna J o 36*# columna J, para presencial o virtual, respectivamente.] | M1: [Escribir la suma de los números de horas de las dos celdas anteriores.] | N1: [Escribir el nombre de los cuatro núcleos temáticos que abordará la asignatura o el módulo.] | O1: [Escribir las lecturas, talleres, análisis, referentes, etc., que realiza el estudiante, clasificadas en trabajo directo e independiente.] | P1: [Escribir las actividades de evaluación que se emplean para identificar el alcance del (de los) indicador(es) de logro(s).] | Q1: [Escribir las acciones de retroalimentación que se emplearán en la asignatura o módulo, para retroalimentar a los estudiantes respecto al alcance de los indicadores de logro. Recordar que son cuatro acciones: informar, formar, prevenir y ayudar a tomar decisiones e indique cómo.]
A2: Tipo de Saber | B2: Resultado de aprendizaje | C2: Semestre | D2: Nombre de la asignatura o módulo | E2: Indicadores de logro de la asignatura y/o módulo | F2: Tipología | G2: B.Institucional | H2: B.Disciplinar | I2: B.Electivo | J2: Créditos | K2: Número de horas de trabajo directo | L2: Número de horas de trabajo independiente | M2: Total de horas | N2: Núcleos temáticos | O2: Actividades de aprendizaje | P2: Actividades de evaluación | Q2: Acciones de retroalimentación
A3: {=_xlfn.XLOOKUP(B3,'Paso 3 Redacción RA '!$I$3:$I$15,'Paso 3 Redacción RA '!$C$3:$C$15,,0,1)} -> Saber | B3: Identifica los procesos y procedimientos asociados a las diferentes áreas del derecho para estructurar las etapas necesarias y lo que de ellas se deriva, en la resolución de conflictos judiciales y extra judiciales. | C3: 1 | D3: Introducción al Derecho | E3: Analiza las concepciones del derecho, sus escuelas y corrientes, así como los principios y fuentes del derecho para establecer el derecho en la resolución de casos mediante la argumentación. | F3: T | H3: X | J3: 3 | K3: =12*J3 -> 36 | L3: =36*J3 -> 108 | M3: =SUM(K3:L7) -> 144 | N3: 1. Nociones fundamentales de Derecho. 2. Introducción a la filosofía del Derecho. 3. Fuentes del Derecho. 4. Principios generales del Derecho. | O3: Trabajo directo: Encuentros sincrónicos Mensajería interna Anuncios Trabajo independiente: Lecturas fundamentales y complementarias Recursos de apoyo Trabajo Colaborativo Foros de discusión grupal | P3: Quiz (semana 2 - Cuestionario de 5 preguntas). Entrega inicial (semana 3 – Ensayo, artículo, cuadro comparativo, revisión documental, entre otros). Foro analítico o argumentativo (semanas 5 y 6 – Participación en el espacio correspondiente del aula). Entrega final (semana 7 – Ensayo, artículo, cuadro comparativo, revisión documental, entre otros). Evaluación final (semana 8 – Cuestionario de entre 15 y 20 preguntas). | Q3: Las acciones de retroalimentación giran en torno a las siguientes. Formar: donde se crean las condiciones para que los estudiantes adquieran conocimientos, habilidades, actitudes, aptitudes y destrezas. Además, debe promover su desarrollo integral y debe acompañarlos en las situaciones académicas que enfrenten durante el desarrollo de un módulo o una asignatura. Informar: para que los estudiantes identifiquen los cambios que pueden afectarlos directa o indirectamente tanto en el aula de clase como en otros espacios. Prevenir: con el fin de anticiparse a las situaciones académicas que pueden representar dificultad para los estudiantes. Esto se logra a través de la interacción individual con los estudiantes y del completo conocimiento del contexto educativo en que el tutor se desenvuelve. Ayudar a decidir: donde se orienta a los estudiantes para que tomen la mejor decisión ante una situación concreta. El objetivo es que el estudiante fortalezca su autonomía y la toma de decisiones responsable.
A4: {=_xlfn.XLOOKUP(B4,'Paso 3 Redacción RA '!$I$3:$I$15,'Paso 3 Redacción RA '!$C$3:$C$15,,0,1)} -> Saberhacer | B4: Emplea los procesos y procedimientos que permiten gestionar una correcta administración de justicia, para generar los soportes documentales o verbales que apoyan la resolución de conflictos objeto de negociación, en las diferentes áreas del derecho.
A5: {=_xlfn.XLOOKUP(B5,'Paso 3 Redacción RA '!$I$3:$I$15,'Paso 3 Redacción RA '!$C$3:$C$15,,0,1)} -> Saberser | B5: Aplica adecuadamente técnicas, procesos, procedimientos y métodos propios del actuar jurídico y de la gestión documental judicial, para plantear soluciones acordes con la normatividad y con las necesidades identificadas en el contexto o en el objeto de negociación en la etapa judicial o extra judicial, según corresponda.
A6: {=_xlfn.XLOOKUP(B6,'Paso 3 Redacción RA '!$I$3:$I$15,'Paso 3 Redacción RA '!$C$3:$C$15,,0,1)} -> Saber | B6: Reconoce los textos jurídicos y contractuales que se deben generar en las diferentes áreas del derecho, para determinar el proceso archivístico o de digitalización que permite organizar y gestionar la documentación de información en las entidades.
A7: {=_xlfn.XLOOKUP(B7,'Paso 3 Redacción RA '!$I$3:$I$15,'Paso 3 Redacción RA '!$C$3:$C$15,,0,1)} -> Saberhacer | B7: Aplica técnicas para categorizar o documentar información acatando los requisitos establecidos en la normatividad sustancial y procesal, así como de la voluntad de los intervinientes.
A8: {=_xlfn.XLOOKUP(B8,'Paso 3 Redacción RA '!$I$3:$I$15,'Paso 3 Redacción RA '!$C$3:$C$15,,0,1)} -> Saber | B8: Identifica fenómenos contemporáneos y su relación con la profesión, para determinar sus impactos e influencia en la sociedad, de forma responsable y crítica. | C8: 1 | D8: Razonamiento Cuantitativo | E8: Analiza datos numéricos presentados en tablas, gráficos o textos para proponer soluciones informadas a situaciones problema del contexto. | F8: TP | G8: X | J8: 3 | K8: =12*J8 -> 36 | L8: =36*J8 -> 108 | M8: =SUM(K8:L8) -> 144 | N8: 1. Pensamiento numérico. Interpretación y representación de información numérica. 2. Pensamiento algebraico desde la representación de regularidades y patrones. 3. Pensamiento algebraico desde las relaciones de comparación entre cantidades o expresiones numéricas. 4. Pensamiento geométrico. Propiedades, formas y relaciones espaciales. | O8: Trabajo Directo: Desarrollo de encuentros sincrónicos Acompañamiento en foros Mensajería interna con la reflexión o síntesis de los resultados alcanzados por el grupo Trabajo Independiente: Revisión de lecturas fundamentales Revisión y desarrollo del material de trabajo Participación en foros de discusión, de actividades formativas o de resolución de dudas Revisión de material complementario | P8: Evaluación diagnóstica (semana 1- Cuestionario inicial de, mínimo, cinco preguntas, que recopila información sobre el conocimiento previo y las habilidades del estudiante. ) Actividad formativa (semana 2 - Foro individual o grupal, creado para que el estudiante participe activamente en la construcción de su conocimiento y desarrollo de habilidades. Varía entre una actividad entregable y la participación en un foro.) Actividades de entrega (semana 4 - Actividad individual o grupal, diseñada para evaluar de manera integral el nivel de conocimiento, comprensión y el desempeño de los indicadores de logro. Varía entre entregas independientes o secuenciales. Al ser un módulo teórico, ésta es la única actividad de entrega. ) Actividad formativa (semana 5 - Foro individual o grupal, creado para que el estudiante participe activamente en la construcción de su conocimiento y desarrollo de habilidades. Varía entre una actividad entregable y la participación en un foro.) Actividad evaluativa (semana 6 - Cuestionario de, mínimo, cinco preguntas, que da cuenta del desarrollo total o parcial de los indicadores de logro y el desarrollo de los temas vistos hasta la unidad 3. ) Examen final (semana 8 - Cuestionario de, mínimo, quince preguntas, que da cuenta del desarrollo total o parcial de los indicadores de logro y el desarrollo de los temas vistos en el módulo. ) Autoevaluación (semana 8 - Cuestionario final de, mínimo, cinco preguntas, en el cual el estudiante reflexiona sobre su propio desempeño, habilidades y resultados en un contexto específico. ) | Q8: Las acciones de retroalimentación giran en torno a las siguientes. Formar: donde se crean las condiciones para que los estudiantes adquieran conocimientos, habilidades, actitudes, aptitudes y destrezas. Además, debe promover su desarrollo integral y debe acompañarlos en las situaciones académicas que enfrenten durante el desarrollo de un módulo o una asignatura. Informar: para que los estudiantes identifiquen los cambios que pueden afectarlos directa o indirectamente tanto en el aula de clase como en otros espacios. Prevenir: con el fin de anticiparse a las situaciones académicas que pueden representar dificultad para los estudiantes. Esto se logra a través de la interacción individual con los estudiantes y del completo conocimiento del contexto educativo en que el tutor se desenvuelve. Ayudar a decidir: donde se orienta a los estudiantes para que tomen la mejor decisión ante una situación concreta. El objetivo es que el estudiante fortalezca su autonomía y la toma de decisiones responsable.
A9: {=_xlfn.XLOOKUP(B9,'Paso 3 Redacción RA '!$I$3:$I$15,'Paso 3 Redacción RA '!$C$3:$C$15,,0,1)} -> Saber | B9: Identifica los procesos y procedimientos asociados a las diferentes áreas del derecho para estructurar las etapas necesarias y lo que de ellas se deriva, en la resolución de conflictos judiciales y extra judiciales. | C9: 1 | D9: Habilidades de Negociación y Manejo de Conflictos | E9: Analiza las nociones de conflicto, negociación, así como los diferentes mecanismos que componen la resolución de conflictos para establecer la mejor estrategia de solución desde la perspectiva jurídica y socio humanística. | F9: TP | H9: X | J9: 3 | K9: =12*J9 -> 36 | L9: =36*J9 -> 108 | M9: =SUM(K9:L14) -> 144 | N9: 1. El conflicto y las controversias jurídicas. 2. Técnicas y habilidades de negociación. 3. Mecanismos alternativos de solución de conflictos autocompositivos. 4. Mecanismos alternativos de solución de conflictos hetero compositivos. | O9: Trabajo directo: Encuentros sincrónicos Mensajería interna Anuncios Trabajo independiente: Lecturas fundamentales y complementarias Recursos de apoyo Trabajo Colaborativo Foros de discusión grupal | P9: Actividad de puntos evaluables (semana 2 – Cuestionario de 5 preguntas). Entrega previa 1 (semana 3 - Laboratorio, taller, ejercicios, resolución de casos o de problemas, desarrollo de procesos o ejecución de propuestas. Entrega de forma individual o grupal, según indicaciones del profesor). Parcial (semana 4 - Cuestionarios de entre 15 y 20 preguntas). Entrega previa 2 (semana 5 - Laboratorio, taller, ejercicios, resolución de casos o de problemas, desarrollo de procesos o ejecución de propuestas. Entrega de forma individual o grupal, según indicaciones dadas por el profesor). Entrega final (semana 7 - Laboratorio, taller, ejercicios, resolución de casos o de problemas, desarrollo de procesos o ejecución de propuestas. Entrega de forma individual o grupal, según indicaciones dadas por el profesor). Evaluación final (semana 8 - Cuestionario de entre 15 y 20 preguntas). | Q9: Las acciones de retroalimentación giran en torno a las siguientes. Formar: donde se crean las condiciones para que los estudiantes adquieran conocimientos, habilidades, actitudes, aptitudes y destrezas. Además, debe promover su desarrollo integral y debe acompañarlos en las situaciones académicas que enfrenten durante el desarrollo de un módulo o una asignatura. Informar: para que los estudiantes identifiquen los cambios que pueden afectarlos directa o indirectamente tanto en el aula de clase como en otros espacios. Prevenir: con el fin de anticiparse a las situaciones académicas que pueden representar dificultad para los estudiantes. Esto se logra a través de la interacción individual con los estudiantes y del completo conocimiento del contexto educativo en que el tutor se desenvuelve. Ayudar a decidir: donde se orienta a los estudiantes para que tomen la mejor decisión ante una situación concreta. El objetivo es que el estudiante fortalezca su autonomía y la toma de decisiones responsable.
A10: {=_xlfn.XLOOKUP(B10,'Paso 3 Redacción RA '!$I$3:$I$15,'Paso 3 Redacción RA '!$C$3:$C$15,,0,1)} -> Saberhacer | B10: Emplea los procesos y procedimientos que permiten gestionar una correcta administración de justicia, para generar los soportes documentales o verbales que apoyan la resolución de conflictos objeto de negociación, en las diferentes áreas del derecho.
A11: {=_xlfn.XLOOKUP(B11,'Paso 3 Redacción RA '!$I$3:$I$15,'Paso 3 Redacción RA '!$C$3:$C$15,,0,1)} -> Saberser | B11: Aplica adecuadamente técnicas, procesos, procedimientos y métodos propios del actuar jurídico y de la gestión documental judicial, para plantear soluciones acordes con la normatividad y con las necesidades identificadas en el contexto o en el objeto de negociación en la etapa judicial o extra judicial, según corresponda.
A12: {=_xlfn.XLOOKUP(B12,'Paso 3 Redacción RA '!$I$3:$I$15,'Paso 3 Redacción RA '!$C$3:$C$15,,0,1)} -> Saber | B12: Reconoce los textos jurídicos y contractuales que se deben generar en las diferentes áreas del derecho, para determinar el proceso archivístico o de digitalización que permite organizar y gestionar la documentación de información en las entidades.
A13: {=_xlfn.XLOOKUP(B13,'Paso 3 Redacción RA '!$I$3:$I$15,'Paso 3 Redacción RA '!$C$3:$C$15,,0,1)} -> Saber | B13: Identifica fenómenos contemporáneos y su relación con la profesión, para determinar sus impactos e influencia en la sociedad, de forma responsable y crítica.
A14: {=_xlfn.XLOOKUP(B14,'Paso 3 Redacción RA '!$I$3:$I$15,'Paso 3 Redacción RA '!$C$3:$C$15,,0,1)} -> Saberhacer | B14: Aplica técnicas para categorizar o documentar información acatando los requisitos establecidos en la normatividad sustancial y procesal, así como de la voluntad de los intervinientes.
A15: {=_xlfn.XLOOKUP(B15,'Paso 3 Redacción RA '!$I$3:$I$15,'Paso 3 Redacción RA '!$C$3:$C$15,,0,1)} -> Saber | B15: Identifica fenómenos contemporáneos y su relación con la profesión, para determinar sus impactos e influencia en la sociedad, de forma responsable y crítica. | C15: 1 | D15: Cultura, Política y Sociedad | E15: Reconoce las problemáticas, escenarios y mecanismos de participación ciudadana en el marco de sociedades de información y digitales para abordarlas desde iniciativas investigativas. Identifica los objetivos de desarrollo sostenible para llevar a cabo análisis de problemáticas sociales, ambientales y culturales. Reflexiona sobre los impactos de los avances tecnológicos en el ámbito profesional y ciudadano para generar análisis alrededor de éstos, en contextos situados. | F15: TP | G15: X | J15: 3 | K15: =12*J15 -> 36 | L15: =36*J15 -> 108 | M15: =SUM(K15:L15) -> 144 | N15: 1. ODS, problemas locales: una mirada a Colombia, territorio en búsqueda de la consolidación de la Paz. 2. Ciudadanía y su lugar: relaciones, dinámicas, construcción, expresión y mecanismos de participación. 3. Ecosistemas digitales: relaciones, dinámicas, construcción, expresión e impactos en el contexto profesional. 4. Narrativas y contenidos digitales: análisis de contextos situados. | O15: Trabajo Directo: Desarrollo de encuentros sincrónicos Acompañamiento en foros Mensajería interna con la reflexión o síntesis de los resultados alcanzados por el grupo Trabajo Independiente: Revisión de lecturas fundamentales Revisión y desarrollo del material de trabajo Participación en foros de discusión, de actividades formativas o de resolución de dudas Revisión de material complementario | P15: Evaluación diagnóstica (semana 1- Cuestionario inicial de, mínimo, cinco preguntas, que recopila información sobre el conocimiento previo y las habilidades del estudiante. ) Actividad formativa (semana 2 - Foro individual o grupal, creado para que el estudiante participe activamente en la construcción de su conocimiento y desarrollo de habilidades. Varía entre una actividad entregable y la participación en un foro.) Actividades de entrega I (semana 4 - Actividad individual o grupal, diseñada para evaluar de manera integral el nivel de conocimiento, comprensión y el desempeño de los indicadores de logro. Varía entre entregas independientes o secuenciales. Al ser un módulo teórico, ésta es la única actividad de entrega. ) Actividad formativa (semana 5 - Foro individual o grupal, creado para que el estudiante participe activamente en la construcción de su conocimiento y desarrollo de habilidades. Varía entre una actividad entregable y la participación en un foro.) Actividades de entrega 2 (semana 6 - Actividad individual o grupal, diseñada para evaluar de manera integral el nivel de conocimiento, comprensión y el desempeño de los indicadores de logro. Varía entre entregas independientes o secuenciales. Al ser un módulo teórico, ésta es la única actividad de entrega. ) Autoevaluación (semana 8 - Cuestionario final de, mínimo, cinco preguntas, en el cual el estudiante reflexiona sobre su propio desempeño, habilidades y resultados en un contexto específico. ) | Q15: Las acciones de retroalimentación giran en torno a las siguientes. Formar: donde se crean las condiciones para que los estudiantes adquieran conocimientos, habilidades, actitudes, aptitudes y destrezas. Además, debe promover su desarrollo integral y debe acompañarlos en las situaciones académicas que enfrenten durante el desarrollo de un módulo o una asignatura. Informar: para que los estudiantes identifiquen los cambios que pueden afectarlos directa o indirectamente tanto en el aula de clase como en otros espacios. Prevenir: con el fin de anticiparse a las situaciones académicas que pueden representar dificultad para los estudiantes. Esto se logra a través de la interacción individual con los estudiantes y del completo conocimiento del contexto educativo en que el tutor se desenvuelve. Ayudar a decidir: donde se orienta a los estudiantes para que tomen la mejor decisión ante una situación concreta. El objetivo es que el estudiante fortalezca su autonomía y la toma de decisiones responsable.
A16: {=_xlfn.XLOOKUP(B16,'Paso 3 Redacción RA '!$I$3:$I$15,'Paso 3 Redacción RA '!$C$3:$C$15,,0,1)} -> Saber | B16: Identifica fenómenos contemporáneos y su relación con la profesión, para determinar sus impactos e influencia en la sociedad, de forma responsable y crítica. | C16: 1 | D16: Derecho Civil Personas | E16: Emplea el derecho civil y de personas, las nociones fundamentales, los derechos y obligaciones, para implementar los atributos de la personalidad desde la existencia hasta la extinción, en el análisis de casos. | F16: TP | H16: X | J16: 3 | K16: =12*J16 -> 36 | L16: =36*J16 -> 108 | M16: =SUM(K16:L20) -> 144 | N16: 1. Historia del Derecho Civil. 2. Contenido y estructura del código civil. 3. De las personas. 4. Derechos de las personas. | O16: Trabajo directo: Encuentros sincrónicos Mensajería interna Anuncios Trabajo independiente: Lecturas fundamentales y complementarias Recursos de apoyo Trabajo Colaborativo Foros de discusión grupal | P16: Actividad de puntos evaluables (semana 2 – Cuestionario de 5 preguntas). Entrega previa 1 (semana 3 - Laboratorio, taller, ejercicios, resolución de casos o de problemas, desarrollo de procesos o ejecución de propuestas. Entrega de forma individual o grupal, según indicaciones del profesor). Parcial (semana 4 - Cuestionarios de entre 15 y 20 preguntas). Entrega previa 2 (semana 5 - Laboratorio, taller, ejercicios, resolución de casos o de problemas, desarrollo de procesos o ejecución de propuestas. Entrega de forma individual o grupal, según indicaciones dadas por el profesor). Entrega final (semana 7 - Laboratorio, taller, ejercicios, resolución de casos o de problemas, desarrollo de procesos o ejecución de propuestas. Entrega de forma individual o grupal, según indicaciones dadas por el profesor). Evaluación final (semana 8 - Cuestionario de entre 15 y 20 preguntas). | Q16: Las acciones de retroalimentación giran en torno a las siguientes. Formar: donde se crean las condiciones para que los estudiantes adquieran conocimientos, habilidades, actitudes, aptitudes y destrezas. Además, debe promover su desarrollo integral y debe acompañarlos en las situaciones académicas que enfrenten durante el desarrollo de un módulo o una asignatura. Informar: para que los estudiantes identifiquen los cambios que pueden afectarlos directa o indirectamente tanto en el aula de clase como en otros espacios. Prevenir: con el fin de anticiparse a las situaciones académicas que pueden representar dificultad para los estudiantes. Esto se logra a través de la interacción individual con los estudiantes y del completo conocimiento del contexto educativo en que el tutor se desenvuelve. Ayudar a decidir: donde se orienta a los estudiantes para que tomen la mejor decisión ante una situación concreta. El objetivo es que el estudiante fortalezca su autonomía y la toma de decisiones responsable.
A17: {=_xlfn.XLOOKUP(B17,'Paso 3 Redacción RA '!$I$3:$I$15,'Paso 3 Redacción RA '!$C$3:$C$15,,0,1)} -> Saberhacer | B17: Emplea los procesos y procedimientos que permiten gestionar una correcta administración de justicia, para generar los soportes documentales o verbales que apoyan la resolución de conflictos objeto de negociación, en las diferentes áreas del derecho.
A18: {=_xlfn.XLOOKUP(B18,'Paso 3 Redacción RA '!$I$3:$I$15,'Paso 3 Redacción RA '!$C$3:$C$15,,0,1)} -> Saberser | B18: Aplica adecuadamente técnicas, procesos, procedimientos y métodos propios del actuar jurídico y de la gestión documental judicial, para plantear soluciones acordes con la normatividad y con las necesidades identificadas en el contexto o en el objeto de negociación en la etapa judicial o extra judicial, según corresponda.
A19: {=_xlfn.XLOOKUP(B19,'Paso 3 Redacción RA '!$I$3:$I$15,'Paso 3 Redacción RA '!$C$3:$C$15,,0,1)} -> Saber | B19: Reconoce los textos jurídicos y contractuales que se deben generar en las diferentes áreas del derecho, para determinar el proceso archivístico o de digitalización que permite organizar y gestionar la documentación de información en las entidades.
A20: {=_xlfn.XLOOKUP(B20,'Paso 3 Redacción RA '!$I$3:$I$15,'Paso 3 Redacción RA '!$C$3:$C$15,,0,1)} -> Saberhacer | B20: Aplica técnicas para categorizar o documentar información acatando los requisitos establecidos en la normatividad sustancial y procesal, así como de la voluntad de los intervinientes.
A21: {=_xlfn.XLOOKUP(B21,'Paso 3 Redacción RA '!$I$3:$I$15,'Paso 3 Redacción RA '!$C$3:$C$15,,0,1)} -> Saber | B21: Identifica los procesos y procedimientos asociados a las diferentes áreas del derecho para estructurar las etapas necesarias y lo que de ellas se deriva, en la resolución de conflictos judiciales y extra judiciales. | C21: I | D21: Derecho Constitucional | E21: Identifica la estructura del poder público en Colombia en atención a las tareas específicas del Estado, así como el régimen económico y de hacienda pública para determinar las responsabilidades del Estado como garante de derechos fundamentales. Reconoce los mecanismos de exigibilidad de derechos, e instrumentos de participación ciudadana para proyectar soluciones en el ejercicio de la protección de derechos. | F21: TP | H21: X | J21: 3 | K21: =12*J21 -> 36 | L21: =36*J21 -> 108 | M21: =SUM(K21:L26) -> 144 | N21: 1. Supremacía constitucional en la Constitución de 1991, mecanismos de control constitucional. Configuración y alcance del catálogo de derechos fundamentales, económicos, sociales y culturales, e instrumentos para su exigibilidad y protección. Mecanismos de participación ciudadana como manifestación del principio democrático en el Estado Social de Derecho. 2. Mecanismos de control constitucional, alcance del catálogo de derechos fundamentales, económicos, sociales y culturales, e instrumentos para su exigibilidad y protección. Mecanismos de participación ciudadana como manifestación del principio democrático en el Estado Social de Derecho. 3. Rasgos distintivos del modelo de Estado derivado del proceso de constitucionalización en Colombia, considerando sus causas y efectos jurídico-políticos. Configuración conceptual y estructural de la forma de Estado vigente, así como las características del sistema de gobierno, organización territorial, régimen político, y el modelo electoral consagrado en la Constitución de 1991. 4. Organización del poder público en la Constitución de 1991, a partir de la distribución funcional y orgánica de sus ramas y competencias. Régimen económico y de Hacienda Pública. Mecanismos y límites de la reforma constitucional y el concepto de sustitución de la Constitución. | O21: Trabajo directo: Encuentros sincrónicos Mensajería interna Anuncios Trabajo independiente: Lecturas fundamentales y complementarias Recursos de apoyo Trabajo Colaborativo Foros de discusión grupal | P21: Evaluación diagnóstica (semana 1- Cuestionario inicial de, mínimo, cinco preguntas, que recopila información sobre el conocimiento previo o las habilidades del estudiante). Actividad formativa (semana 2 - Foro individual o grupal, creado para que el estudiante participe activamente en la construcción de su conocimiento y desarrollo de habilidades. Varía entre una actividad entregable y la participación en un foro). Actividad de entrega 1 (semana 4 - Actividad individual o grupal, diseñada para evaluar de manera integral el nivel de conocimiento, comprensión y el desempeño de los indicadores de logro. Varía entre entregas independientes o secuenciales). Actividad formativa (semana 5 - Foro individual o grupal, creado para que el estudiante participe activamente en la construcción de su conocimiento y desarrollo de habilidades. Varía entre una actividad entregable y la participación en un foro). Actividad evaluativa (semana 6 - Cuestionario de mínimo cinco preguntas, que da cuenta del desarrollo total o parcial de los indicadores de logro y el desarrollo de los temas vistos hasta la unidad 3). Actividad de entrega 2 (semana 7 - Actividad individual o grupal, diseñada para evaluar de manera integral el nivel de conocimiento, comprensión y el desempeño de los indicadores de logro. Varía entre entregas independientes o secuenciales). Autoevaluación (semana 8 - Cuestionario final de, mínimo, cinco preguntas, en el cual el estudiante reflexiona sobre su propio desempeño, habilidades y resultados en un contexto específico). | Q21: Las acciones de retroalimentación giran en torno a las siguientes. Formar: donde se crean las condiciones para que los estudiantes adquieran conocimientos, habilidades, actitudes, aptitudes y destrezas. Además, debe promover su desarrollo integral y debe acompañarlos en las situaciones académicas que enfrenten durante el desarrollo de un módulo o una asignatura. Informar: para que los estudiantes identifiquen los cambios que pueden afectarlos directa o indirectamente tanto en el aula de clase como en otros espacios. Prevenir: con el fin de anticiparse a las situaciones académicas que pueden representar dificultad para los estudiantes. Esto se logra a través de la interacción individual con los estudiantes y del completo conocimiento del contexto educativo en que el tutor se desenvuelve. Ayudar a decidir: donde se orienta a los estudiantes para que tomen la mejor decisión ante una situación concreta. El objetivo es que el estudiante fortalezca su autonomía y la toma de decisiones responsable.
A22: {=_xlfn.XLOOKUP(B22,'Paso 3 Redacción RA '!$I$3:$I$15,'Paso 3 Redacción RA '!$C$3:$C$15,,0,1)} -> Saberhacer | B22: Emplea los procesos y procedimientos que permiten gestionar una correcta administración de justicia, para generar los soportes documentales o verbales que apoyan la resolución de conflictos objeto de negociación, en las diferentes áreas del derecho.
A23: {=_xlfn.XLOOKUP(B23,'Paso 3 Redacción RA '!$I$3:$I$15,'Paso 3 Redacción RA '!$C$3:$C$15,,0,1)} -> Saberser | B23: Aplica adecuadamente técnicas, procesos, procedimientos y métodos propios del actuar jurídico y de la gestión documental judicial, para plantear soluciones acordes con la normatividad y con las necesidades identificadas en el contexto o en el objeto de negociación en la etapa judicial o extra judicial, según corresponda.
A24: {=_xlfn.XLOOKUP(B24,'Paso 3 Redacción RA '!$I$3:$I$15,'Paso 3 Redacción RA '!$C$3:$C$15,,0,1)} -> Saber | B24: Reconoce los textos jurídicos y contractuales que se deben generar en las diferentes áreas del derecho, para determinar el proceso archivístico o de digitalización que permite organizar y gestionar la documentación de información en las entidades.
A25: {=_xlfn.XLOOKUP(B25,'Paso 3 Redacción RA '!$I$3:$I$15,'Paso 3 Redacción RA '!$C$3:$C$15,,0,1)} -> Saber | B25: Identifica fenómenos contemporáneos y su relación con la profesión, para determinar sus impactos e influencia en la sociedad, de forma responsable y crítica.
A26: {=_xlfn.XLOOKUP(B26,'Paso 3 Redacción RA '!$I$3:$I$15,'Paso 3 Redacción RA '!$C$3:$C$15,,0,1)} -> Saberhacer | B26: Aplica técnicas para categorizar o documentar información acatando los requisitos establecidos en la normatividad sustancial y procesal, así como de la voluntad de los intervinientes.
A27: {=_xlfn.XLOOKUP(B27,'Paso 3 Redacción RA '!$I$3:$I$15,'Paso 3 Redacción RA '!$C$3:$C$15,,0,1)} -> Saber | B27: Identifica los procesos y procedimientos asociados a las diferentes áreas del derecho para estructurar las etapas necesarias y lo que de ellas se deriva, en la resolución de conflictos judiciales y extra judiciales. | C27: 2 | D27: Trámites en Derecho Inmobiliario | E27: Diferencia los conceptos de bien y cosa en términos jurídicos para determinar las relaciones jurídicas que existen entre una persona y un bien, a través del ordenamiento jurídico colombiano. Establece los requisitos legales, sustanciales y procedimentales de adquirir el derecho real de dominio dentro del ordenamiento jurídico colombiano, para documentar trámites en la adquisición de propiedad y uso. Determina los tipos de contratos necesarios para elaborar documentos en los cuales se trasmita el derecho de dominio o usufructo de los bienes, a la luz de la legislación colombiana vigente. | F27: TP | H27: X | J27: 2 | K27: =12*J27 -> 24 | L27: =36*J27 -> 72 | M27: =SUM(K27:L32) -> 96 | N27: 1. Derecho de los bienes y su contenido jurídico. 2. Modos de adquirir el derecho real de dominio. 3. Principales contratos del derecho de los bienes. 4. Planificación Urbana y la gestión inmobiliaria. | O27: Trabajo directo: Encuentros sincrónicos Mensajería interna Anuncios Trabajo independiente: Lecturas fundamentales y complementarias Recursos de apoyo Trabajo Colaborativo Foros de discusión grupal | P27: Evaluación diagnóstica (semana 1- Cuestionario inicial de, mínimo, cinco preguntas, que recopila información sobre el conocimiento previo o las habilidades del estudiante). Actividad formativa (semana 2 - Foro individual o grupal, creado para que el estudiante participe activamente en la construcción de su conocimiento y desarrollo de habilidades. Varía entre una actividad entregable y la participación en un foro). Actividad de entrega 1 (semana 4 - Actividad individual o grupal, diseñada para evaluar de manera integral el nivel de conocimiento, comprensión y el desempeño de los indicadores de logro. Varía entre entregas independientes o secuenciales). Actividad formativa (semana 5 - Foro individual o grupal, creado para que el estudiante participe activamente en la construcción de su conocimiento y desarrollo de habilidades. Varía entre una actividad entregable y la participación en un foro). Actividad evaluativa (semana 6 - Cuestionario de mínimo cinco preguntas, que da cuenta del desarrollo total o parcial de los indicadores de logro y el desarrollo de los temas vistos hasta la unidad 3). Actividad de entrega 2 (semana 7 - Actividad individual o grupal, diseñada para evaluar de manera integral el nivel de conocimiento, comprensión y el desempeño de los indicadores de logro. Varía entre entregas independientes o secuenciales). Autoevaluación (semana 8 - Cuestionario final de, mínimo, cinco preguntas, en el cual el estudiante reflexiona sobre su propio desempeño, habilidades y resultados en un contexto específico). | Q27: Las acciones de retroalimentación giran en torno a las siguientes. Formar: donde se crean las condiciones para que los estudiantes adquieran conocimientos, habilidades, actitudes, aptitudes y destrezas. Además, debe promover su desarrollo integral y debe acompañarlos en las situaciones académicas que enfrenten durante el desarrollo de un módulo o una asignatura. Informar: para que los estudiantes identifiquen los cambios que pueden afectarlos directa o indirectamente tanto en el aula de clase como en otros espacios. Prevenir: con el fin de anticiparse a las situaciones académicas que pueden representar dificultad para los estudiantes. Esto se logra a través de la interacción individual con los estudiantes y del completo conocimiento del contexto educativo en que el tutor se desenvuelve. Ayudar a decidir: donde se orienta a los estudiantes para que tomen la mejor decisión ante una situación concreta. El objetivo es que el estudiante fortalezca su autonomía y la toma de decisiones responsable.
A28: {=_xlfn.XLOOKUP(B28,'Paso 3 Redacción RA '!$I$3:$I$15,'Paso 3 Redacción RA '!$C$3:$C$15,,0,1)} -> Saberhacer | B28: Emplea los procesos y procedimientos que permiten gestionar una correcta administración de justicia, para generar los soportes documentales o verbales que apoyan la resolución de conflictos objeto de negociación, en las diferentes áreas del derecho.
A29: {=_xlfn.XLOOKUP(B29,'Paso 3 Redacción RA '!$I$3:$I$15,'Paso 3 Redacción RA '!$C$3:$C$15,,0,1)} -> Saberser | B29: Aplica adecuadamente técnicas, procesos, procedimientos y métodos propios del actuar jurídico y de la gestión documental judicial, para plantear soluciones acordes con la normatividad y con las necesidades identificadas en el contexto o en el objeto de negociación en la etapa judicial o extra judicial, según corresponda.
A30: {=_xlfn.XLOOKUP(B30,'Paso 3 Redacción RA '!$I$3:$I$15,'Paso 3 Redacción RA '!$C$3:$C$15,,0,1)} -> Saber | B30: Reconoce los textos jurídicos y contractuales que se deben generar en las diferentes áreas del derecho, para determinar el proceso archivístico o de digitalización que permite organizar y gestionar la documentación de información en las entidades.
A31: {=_xlfn.XLOOKUP(B31,'Paso 3 Redacción RA '!$I$3:$I$15,'Paso 3 Redacción RA '!$C$3:$C$15,,0,1)} -> Saberhacer | B31: Aplica técnicas para categorizar o documentar información acatando los requisitos establecidos en la normatividad sustancial y procesal, así como de la voluntad de los intervinientes.
A32: {=_xlfn.XLOOKUP(B32,'Paso 3 Redacción RA '!$I$3:$I$15,'Paso 3 Redacción RA '!$C$3:$C$15,,0,1)} -> Saberhacer | B32: Aplica técnicas para categorizar o documentar información acatando los requisitos establecidos en la normatividad sustancial y procesal, así como de la voluntad de los intervinientes.
A33: {=_xlfn.XLOOKUP(B33,'Paso 3 Redacción RA '!$I$3:$I$15,'Paso 3 Redacción RA '!$C$3:$C$15,,0,1)} -> Saber | B33: Identifica los procesos y procedimientos asociados a las diferentes áreas del derecho para estructurar las etapas necesarias y lo que de ellas se deriva, en la resolución de conflictos judiciales y extra judiciales. | C33: 2 | D33: Fundamentos de Derecho Procesal | E33: Analiza el requisito de procedibilidad, la jurisdicción, la competencia, los sujetos y presupuestos procesales para estructurar el procedimiento, la demanda, contestación de la demanda y audiencias propias de una actuación judicial. | F33: TP | H33: X | J33: 3 | K33: =12*J33 -> 36 | L33: =36*J33 -> 108 | M33: =SUM(K33:L38) -> 144 | N33: 1. Temas introductorios, contextualización del derecho procesal. 2. Mecanismos alternativos de resolución de conflictos, actos, presupuestos y sujetos. 3. La demanda, su admisión, reforma y adición. 4. La contestación de la demanda y audiencias. | O33: Trabajo directo: Encuentros sincrónicos Mensajería interna Anuncios Trabajo independiente: Lecturas fundamentales y complementarias Recursos de apoyo Trabajo Colaborativo Foros de discusión grupal | P33: Actividad de puntos evaluables (semana 2 – Cuestionario de 5 preguntas). Entrega previa 1 (semana 3 - Laboratorio, taller, ejercicios, resolución de casos o de problemas, desarrollo de procesos o ejecución de propuestas. Entrega de forma individual o grupal, según indicaciones del profesor). Parcial (semana 4 - Cuestionarios de entre 15 y 20 preguntas). Entrega previa 2 (semana 5 - Laboratorio, taller, ejercicios, resolución de casos o de problemas, desarrollo de procesos o ejecución de propuestas. Entrega de forma individual o grupal, según indicaciones dadas por el profesor). Entrega final (semana 7 - Laboratorio, taller, ejercicios, resolución de casos o de problemas, desarrollo de procesos o ejecución de propuestas. Entrega de forma individual o grupal, según indicaciones dadas por el profesor). Evaluación final (semana 8 - Cuestionario de entre 15 y 20 preguntas). | Q33: Las acciones de retroalimentación giran en torno a las siguientes. Formar: donde se crean las condiciones para que los estudiantes adquieran conocimientos, habilidades, actitudes, aptitudes y destrezas. Además, debe promover su desarrollo integral y debe acompañarlos en las situaciones académicas que enfrenten durante el desarrollo de un módulo o una asignatura. Informar: para que los estudiantes identifiquen los cambios que pueden afectarlos directa o indirectamente tanto en el aula de clase como en otros espacios. Prevenir: con el fin de anticiparse a las situaciones académicas que pueden representar dificultad para los estudiantes. Esto se logra a través de la interacción individual con los estudiantes y del completo conocimiento del contexto educativo en que el tutor se desenvuelve. Ayudar a decidir: donde se orienta a los estudiantes para que tomen la mejor decisión ante una situación concreta. El objetivo es que el estudiante fortalezca su autonomía y la toma de decisiones responsable.
A34: {=_xlfn.XLOOKUP(B34,'Paso 3 Redacción RA '!$I$3:$I$15,'Paso 3 Redacción RA '!$C$3:$C$15,,0,1)} -> Saberhacer | B34: Emplea los procesos y procedimientos que permiten gestionar una correcta administración de justicia, para generar los soportes documentales o verbales que apoyan la resolución de conflictos objeto de negociación, en las diferentes áreas del derecho.
A35: {=_xlfn.XLOOKUP(B35,'Paso 3 Redacción RA '!$I$3:$I$15,'Paso 3 Redacción RA '!$C$3:$C$15,,0,1)} -> Saberser | B35: Aplica adecuadamente técnicas, procesos, procedimientos y métodos propios del actuar jurídico y de la gestión documental judicial, para plantear soluciones acordes con la normatividad y con las necesidades identificadas en el contexto o en el objeto de negociación en la etapa judicial o extra judicial, según corresponda.
A36: {=_xlfn.XLOOKUP(B36,'Paso 3 Redacción RA '!$I$3:$I$15,'Paso 3 Redacción RA '!$C$3:$C$15,,0,1)} -> Saber | B36: Reconoce los textos jurídicos y contractuales que se deben generar en las diferentes áreas del derecho, para determinar el proceso archivístico o de digitalización que permite organizar y gestionar la documentación de información en las entidades.
A37: {=_xlfn.XLOOKUP(B37,'Paso 3 Redacción RA '!$I$3:$I$15,'Paso 3 Redacción RA '!$C$3:$C$15,,0,1)} -> Saber | B37: Identifica fenómenos contemporáneos y su relación con la profesión, para determinar sus impactos e influencia en la sociedad, de forma responsable y crítica.
A38: {=_xlfn.XLOOKUP(B38,'Paso 3 Redacción RA '!$I$3:$I$15,'Paso 3 Redacción RA '!$C$3:$C$15,,0,1)} -> Saberhacer | B38: Aplica técnicas para categorizar o documentar información acatando los requisitos establecidos en la normatividad sustancial y procesal, así como de la voluntad de los intervinientes.
A39: {=_xlfn.XLOOKUP(B39,'Paso 3 Redacción RA '!$I$3:$I$15,'Paso 3 Redacción RA '!$C$3:$C$15,,0,1)} -> Saber | B39: Identifica los procesos y procedimientos asociados a las diferentes áreas del derecho para estructurar las etapas necesarias y lo que de ellas se deriva, en la resolución de conflictos judiciales y extra judiciales. | C39: 2 | D39: Contratos Civiles | E39: Reconoce los diferentes tipos de contratos civiles para determinar los elementos constitutivos y de validez que les corresponden, según sus características. | F39: TP | H39: X | J39: 3 | K39: =12*J39 -> 36 | L39: =36*J39 -> 108 | M39: =SUM(K39:L44) -> 144 | N39: 1. Principios Generales del Derecho de Contratos. 2. Contrato de Compraventa y Contrato de Arrendamiento. 3. Contratos de Préstamo (Mutuo y Comodato) y Contrato de Mandato. 4. Contrato de Promesa, Contrato de Depósito y Fiducia y MASC en materia contractual. | O39: Trabajo directo: Encuentros sincrónicos Mensajería interna Anuncios Trabajo independiente: Lecturas fundamentales y complementarias Recursos de apoyo Trabajo Colaborativo Foros de discusión grupal | P39: Actividad de puntos evaluables (semana 2 – Cuestionario de 5 preguntas). Entrega previa 1 (semana 3 - Laboratorio, taller, ejercicios, resolución de casos o de problemas, desarrollo de procesos o ejecución de propuestas. Entrega de forma individual o grupal, según indicaciones del profesor). Parcial (semana 4 - Cuestionarios de entre 15 y 20 preguntas). Entrega previa 2 (semana 5 - Laboratorio, taller, ejercicios, resolución de casos o de problemas, desarrollo de procesos o ejecución de propuestas. Entrega de forma individual o grupal, según indicaciones dadas por el profesor). Entrega final (semana 7 - Laboratorio, taller, ejercicios, resolución de casos o de problemas, desarrollo de procesos o ejecución de propuestas. Entrega de forma individual o grupal, según indicaciones dadas por el profesor). Evaluación final (semana 8 - Cuestionario de entre 15 y 20 preguntas). | Q39: Las acciones de retroalimentación giran en torno a las siguientes. Formar: donde se crean las condiciones para que los estudiantes adquieran conocimientos, habilidades, actitudes, aptitudes y destrezas. Además, debe promover su desarrollo integral y debe acompañarlos en las situaciones académicas que enfrenten durante el desarrollo de un módulo o una asignatura. Informar: para que los estudiantes identifiquen los cambios que pueden afectarlos directa o indirectamente tanto en el aula de clase como en otros espacios. Prevenir: con el fin de anticiparse a las situaciones académicas que pueden representar dificultad para los estudiantes. Esto se logra a través de la interacción individual con los estudiantes y del completo conocimiento del contexto educativo en que el tutor se desenvuelve. Ayudar a decidir: donde se orienta a los estudiantes para que tomen la mejor decisión ante una situación concreta. El objetivo es que el estudiante fortalezca su autonomía y la toma de decisiones responsable.
A40: {=_xlfn.XLOOKUP(B40,'Paso 3 Redacción RA '!$I$3:$I$15,'Paso 3 Redacción RA '!$C$3:$C$15,,0,1)} -> Saberhacer | B40: Emplea los procesos y procedimientos que permiten gestionar una correcta administración de justicia, para generar los soportes documentales o verbales que apoyan la resolución de conflictos objeto de negociación, en las diferentes áreas del derecho.
A41: {=_xlfn.XLOOKUP(B41,'Paso 3 Redacción RA '!$I$3:$I$15,'Paso 3 Redacción RA '!$C$3:$C$15,,0,1)} -> Saberser | B41: Aplica adecuadamente técnicas, procesos, procedimientos y métodos propios del actuar jurídico y de la gestión documental judicial, para plantear soluciones acordes con la normatividad y con las necesidades identificadas en el contexto o en el objeto de negociación en la etapa judicial o extra judicial, según corresponda.
A42: {=_xlfn.XLOOKUP(B42,'Paso 3 Redacción RA '!$I$3:$I$15,'Paso 3 Redacción RA '!$C$3:$C$15,,0,1)} -> Saber | B42: Reconoce los textos jurídicos y contractuales que se deben generar en las diferentes áreas del derecho, para determinar el proceso archivístico o de digitalización que permite organizar y gestionar la documentación de información en las entidades.
A43: {=_xlfn.XLOOKUP(B43,'Paso 3 Redacción RA '!$I$3:$I$15,'Paso 3 Redacción RA '!$C$3:$C$15,,0,1)} -> Saber | B43: Identifica fenómenos contemporáneos y su relación con la profesión, para determinar sus impactos e influencia en la sociedad, de forma responsable y crítica.
A44: {=_xlfn.XLOOKUP(B44,'Paso 3 Redacción RA '!$I$3:$I$15,'Paso 3 Redacción RA '!$C$3:$C$15,,0,1)} -> Saberhacer | B44: Aplica técnicas para categorizar o documentar información acatando los requisitos establecidos en la normatividad sustancial y procesal, así como de la voluntad de los intervinientes.
A45: {=_xlfn.XLOOKUP(B45,'Paso 3 Redacción RA '!$I$3:$I$15,'Paso 3 Redacción RA '!$C$3:$C$15,,0,1)} -> Saber | B45: Identifica fenómenos contemporáneos y su relación con la profesión, para determinar sus impactos e influencia en la sociedad, de forma responsable y crítica. | C45: 2 | D45: Análisis y Visualización de Datos | E45: Identifica conceptos básicos relacionados con el análisis y visualización de datos con el propósito de comunicar información relevante de manera efectiva en diversos contextos. Utiliza herramientas para realizar análisis y transformación de datos que garanticen una visualización sencilla y eficiente. Utiliza asistentes virtuales para realizar tareas prácticas y resolver problemas en su campo de estudio. Evalúa la presencia de sesgos y cuestiones éticas en el análisis y tratamiento de dato para garantizar que su uso esté desprovisto de efectos negativos en el entorno. | F45: TP | G45: X | J45: 3 | K45: =12*J45 -> 36 | L45: =36*J45 -> 108 | M45: =SUM(K45:L45) -> 144 | N45: 1. Contextualización. 2. Análisis de Datos y Visualización. 3. Usos de la Inteligencia Artificial. 4. Casos de Estudio. | O45: Trabajo Directo: Desarrollo de encuentros sincrónicos Acompañamiento en foros Mensajería interna con la reflexión o síntesis de los resultados alcanzados por el grupo Trabajo Independiente: Revisión de lecturas fundamentales Revisión y desarrollo del material de trabajo Participación en foros de discusión, de actividades formativas o de resolución de dudas Revisión de material complementario | P45: Evaluación diagnóstica (semana 1- Cuestionario inicial de, mínimo, cinco preguntas, que recopila información sobre el conocimiento previo y las habilidades del estudiante. ) Actividad formativa (semana 2 - Foro individual o grupal, creado para que el estudiante participe activamente en la construcción de su conocimiento y desarrollo de habilidades. Varía entre una actividad entregable y la participación en un foro.) Actividades de entrega I (semana 4 - Actividad individual o grupal, diseñada para evaluar de manera integral el nivel de conocimiento, comprensión y el desempeño de los indicadores de logro. Varía entre entregas independientes o secuenciales. Al ser un módulo teórico, ésta es la única actividad de entrega. ) Actividad formativa (semana 5 - Foro individual o grupal, creado para que el estudiante participe activamente en la construcción de su conocimiento y desarrollo de habilidades. Varía entre una actividad entregable y la participación en un foro.) Actividades de entrega 2 (semana 6 - Actividad individual o grupal, diseñada para evaluar de manera integral el nivel de conocimiento, comprensión y el desempeño de los indicadores de logro. Varía entre entregas independientes o secuenciales. Al ser un módulo teórico, ésta es la única actividad de entrega. ) Autoevaluación (semana 8 - Cuestionario final de, mínimo, cinco preguntas, en el cual el estudiante reflexiona sobre su propio desempeño, habilidades y resultados en un contexto específico. ) | Q45: Las acciones de retroalimentación giran en torno a las siguientes. Formar: donde se crean las condiciones para que los estudiantes adquieran conocimientos, habilidades, actitudes, aptitudes y destrezas. Además, debe promover su desarrollo integral y debe acompañarlos en las situaciones académicas que enfrenten durante el desarrollo de un módulo o una asignatura. Informar: para que los estudiantes identifiquen los cambios que pueden afectarlos directa o indirectamente tanto en el aula de clase como en otros espacios. Prevenir: con el fin de anticiparse a las situaciones académicas que pueden representar dificultad para los estudiantes. Esto se logra a través de la interacción individual con los estudiantes y del completo conocimiento del contexto educativo en que el tutor se desenvuelve. Ayudar a decidir: donde se orienta a los estudiantes para que tomen la mejor decisión ante una situación concreta. El objetivo es que el estudiante fortalezca su autonomía y la toma de decisiones responsable.
A46: {=_xlfn.XLOOKUP(B46,'Paso 3 Redacción RA '!$I$3:$I$15,'Paso 3 Redacción RA '!$C$3:$C$15,,0,1)} -> Saber | B46: Identifica los procesos y procedimientos asociados a las diferentes áreas del derecho para estructurar las etapas necesarias y lo que de ellas se deriva, en la resolución de conflictos judiciales y extra judiciales. | C46: 2 | D46: Administrativo General | E46: Explica la función administrativa y la función pública, en la organización del estado desde su fundamentación normativa, para diferenciar los procedimientos contenciosos administrativos, así como los conceptos básicos de la contratación estatal a partir del estatuto de la contratación pública. | F46: TP | H46: X | J46: 3 | K46: =12*J46 -> 36 | L46: =36*J46 -> 108 | M46: =SUM(K46:L51) -> 144 | N46: 1. Fundamentos constitucionales y administrativos del derecho administrativo. 2. Función administrativa y función pública, su noción y fundamentación normativa. 3. Teoría del acto administrativo, y actuaciones administrativas. 4. Procedimientos contenciosos administrativos y conceptos básicos de la contratación estatal. | O46: Trabajo directo: Encuentros sincrónicos Mensajería interna Anuncios Trabajo independiente: Lecturas fundamentales y complementarias Recursos de apoyo Trabajo Colaborativo Foros de discusión grupal | P46: Actividad de puntos evaluables (semana 2 – Cuestionario de 5 preguntas). Entrega previa 1 (semana 3 - Laboratorio, taller, ejercicios, resolución de casos o de problemas, desarrollo de procesos o ejecución de propuestas. Entrega de forma individual o grupal, según indicaciones del profesor). Parcial (semana 4 - Cuestionarios de entre 15 y 20 preguntas). Entrega previa 2 (semana 5 - Laboratorio, taller, ejercicios, resolución de casos o de problemas, desarrollo de procesos o ejecución de propuestas. Entrega de forma individual o grupal, según indicaciones dadas por el profesor). Entrega final (semana 7 - Laboratorio, taller, ejercicios, resolución de casos o de problemas, desarrollo de procesos o ejecución de propuestas. Entrega de forma individual o grupal, según indicaciones dadas por el profesor). Evaluación final (semana 8 - Cuestionario de entre 15 y 20 preguntas). | Q46: Las acciones de retroalimentación giran en torno a las siguientes. Formar: donde se crean las condiciones para que los estudiantes adquieran conocimientos, habilidades, actitudes, aptitudes y destrezas. Además, debe promover su desarrollo integral y debe acompañarlos en las situaciones académicas que enfrenten durante el desarrollo de un módulo o una asignatura. Informar: para que los estudiantes identifiquen los cambios que pueden afectarlos directa o indirectamente tanto en el aula de clase como en otros espacios. Prevenir: con el fin de anticiparse a las situaciones académicas que pueden representar dificultad para los estudiantes. Esto se logra a través de la interacción individual con los estudiantes y del completo conocimiento del contexto educativo en que el tutor se desenvuelve. Ayudar a decidir: donde se orienta a los estudiantes para que tomen la mejor decisión ante una situación concreta. El objetivo es que el estudiante fortalezca su autonomía y la toma de decisiones responsable.
A47: {=_xlfn.XLOOKUP(B47,'Paso 3 Redacción RA '!$I$3:$I$15,'Paso 3 Redacción RA '!$C$3:$C$15,,0,1)} -> Saberhacer | B47: Emplea los procesos y procedimientos que permiten gestionar una correcta administración de justicia, para generar los soportes documentales o verbales que apoyan la resolución de conflictos objeto de negociación, en las diferentes áreas del derecho.
A48: {=_xlfn.XLOOKUP(B48,'Paso 3 Redacción RA '!$I$3:$I$15,'Paso 3 Redacción RA '!$C$3:$C$15,,0,1)} -> Saberser | B48: Aplica adecuadamente técnicas, procesos, procedimientos y métodos propios del actuar jurídico y de la gestión documental judicial, para plantear soluciones acordes con la normatividad y con las necesidades identificadas en el contexto o en el objeto de negociación en la etapa judicial o extra judicial, según corresponda.
A49: {=_xlfn.XLOOKUP(B49,'Paso 3 Redacción RA '!$I$3:$I$15,'Paso 3 Redacción RA '!$C$3:$C$15,,0,1)} -> Saber | B49: Reconoce los textos jurídicos y contractuales que se deben generar en las diferentes áreas del derecho, para determinar el proceso archivístico o de digitalización que permite organizar y gestionar la documentación de información en las entidades.
A50: {=_xlfn.XLOOKUP(B50,'Paso 3 Redacción RA '!$I$3:$I$15,'Paso 3 Redacción RA '!$C$3:$C$15,,0,1)} -> Saber | B50: Identifica fenómenos contemporáneos y su relación con la profesión, para determinar sus impactos e influencia en la sociedad, de forma responsable y crítica.
A51: {=_xlfn.XLOOKUP(B51,'Paso 3 Redacción RA '!$I$3:$I$15,'Paso 3 Redacción RA '!$C$3:$C$15,,0,1)} -> Saberhacer | B51: Aplica técnicas para categorizar o documentar información acatando los requisitos establecidos en la normatividad sustancial y procesal, así como de la voluntad de los intervinientes.
A52: {=_xlfn.XLOOKUP(B52,'Paso 3 Redacción RA '!$I$3:$I$15,'Paso 3 Redacción RA '!$C$3:$C$15,,0,1)} -> Saber | B52: Identifica los procesos y procedimientos asociados a las diferentes áreas del derecho para estructurar las etapas necesarias y lo que de ellas se deriva, en la resolución de conflictos judiciales y extra judiciales. | C52: 2 | D52: Procedimiento en Derecho Penal | E52: Reconoce los fundamentos generales, principios y fuentes normativas del derecho penal y procesal penal, así como las instituciones procesales, partes e intervinientes, para aplicar conceptos y procedimientos en el análisis de casos y en el desarrollo de las etapas estructurales del proceso penal colombiano. | F52: TP | H52: X | J52: 3 | K52: =12*J52 -> 36 | L52: =36*J52 -> 108 | M52: =SUM(K52:L57) -> 144 | N52: 1. Generalidades del Derecho penal y del procedimiento penal. 2. Principios del Derecho penal y del Derecho procesal penal, la pena y la acción civil en el proceso penal. 3. Generalidades de los tipos penales, delitos y tipos penales. 4. Etapas del proceso penal. | O52: Trabajo directo: Encuentros sincrónicos Mensajería interna Anuncios Trabajo independiente: Lecturas fundamentales y complementarias Recursos de apoyo Trabajo Colaborativo Foros de discusión grupal | P52: Evaluación diagnóstica (semana 1- Cuestionario inicial de, mínimo, cinco preguntas, que recopila información sobre el conocimiento previo o las habilidades del estudiante). Actividad formativa (semana 2 - Foro individual o grupal, creado para que el estudiante participe activamente en la construcción de su conocimiento y desarrollo de habilidades. Varía entre una actividad entregable y la participación en un foro). Actividad de entrega 1 (semana 4 - Actividad individual o grupal, diseñada para evaluar de manera integral el nivel de conocimiento, comprensión y el desempeño de los indicadores de logro. Varía entre entregas independientes o secuenciales). Actividad formativa (semana 5 - Foro individual o grupal, creado para que el estudiante participe activamente en la construcción de su conocimiento y desarrollo de habilidades. Varía entre una actividad entregable y la participación en un foro). Actividad evaluativa (semana 6 - Cuestionario de mínimo cinco preguntas, que da cuenta del desarrollo total o parcial de los indicadores de logro y el desarrollo de los temas vistos hasta la unidad 3). Actividad de entrega 2 (semana 7 - Actividad individual o grupal, diseñada para evaluar de manera integral el nivel de conocimiento, comprensión y el desempeño de los indicadores de logro. Varía entre entregas independientes o secuenciales). Autoevaluación (semana 8 - Cuestionario final de, mínimo, cinco preguntas, en el cual el estudiante reflexiona sobre su propio desempeño, habilidades y resultados en un contexto específico). | Q52: Las acciones de retroalimentación giran en torno a las siguientes. Formar: donde se crean las condiciones para que los estudiantes adquieran conocimientos, habilidades, actitudes, aptitudes y destrezas. Además, debe promover su desarrollo integral y debe acompañarlos en las situaciones académicas que enfrenten durante el desarrollo de un módulo o una asignatura. Informar: para que los estudiantes identifiquen los cambios que pueden afectarlos directa o indirectamente tanto en el aula de clase como en otros espacios. Prevenir: con el fin de anticiparse a las situaciones académicas que pueden representar dificultad para los estudiantes. Esto se logra a través de la interacción individual con los estudiantes y del completo conocimiento del contexto educativo en que el tutor se desenvuelve. Ayudar a decidir: donde se orienta a los estudiantes para que tomen la mejor decisión ante una situación concreta. El objetivo es que el estudiante fortalezca su autonomía y la toma de decisiones responsable.
A53: {=_xlfn.XLOOKUP(B53,'Paso 3 Redacción RA '!$I$3:$I$15,'Paso 3 Redacción RA '!$C$3:$C$15,,0,1)} -> Saberhacer | B53: Emplea los procesos y procedimientos que permiten gestionar una correcta administración de justicia, para generar los soportes documentales o verbales que apoyan la resolución de conflictos objeto de negociación, en las diferentes áreas del derecho.
A54: {=_xlfn.XLOOKUP(B54,'Paso 3 Redacción RA '!$I$3:$I$15,'Paso 3 Redacción RA '!$C$3:$C$15,,0,1)} -> Saberser | B54: Aplica adecuadamente técnicas, procesos, procedimientos y métodos propios del actuar jurídico y de la gestión documental judicial, para plantear soluciones acordes con la normatividad y con las necesidades identificadas en el contexto o en el objeto de negociación en la etapa judicial o extra judicial, según corresponda.
A55: {=_xlfn.XLOOKUP(B55,'Paso 3 Redacción RA '!$I$3:$I$15,'Paso 3 Redacción RA '!$C$3:$C$15,,0,1)} -> Saber | B55: Reconoce los textos jurídicos y contractuales que se deben generar en las diferentes áreas del derecho, para determinar el proceso archivístico o de digitalización que permite organizar y gestionar la documentación de información en las entidades.
A56: {=_xlfn.XLOOKUP(B56,'Paso 3 Redacción RA '!$I$3:$I$15,'Paso 3 Redacción RA '!$C$3:$C$15,,0,1)} -> Saber | B56: Identifica fenómenos contemporáneos y su relación con la profesión, para determinar sus impactos e influencia en la sociedad, de forma responsable y crítica.
A57: {=_xlfn.XLOOKUP(B57,'Paso 3 Redacción RA '!$I$3:$I$15,'Paso 3 Redacción RA '!$C$3:$C$15,,0,1)} -> Saberhacer | B57: Aplica técnicas para categorizar o documentar información acatando los requisitos establecidos en la normatividad sustancial y procesal, así como de la voluntad de los intervinientes.
A58: {=_xlfn.XLOOKUP(B58,'Paso 3 Redacción RA '!$I$3:$I$15,'Paso 3 Redacción RA '!$C$3:$C$15,,0,1)} -> Saber | B58: Identifica fenómenos contemporáneos y su relación con la profesión, para determinar sus impactos e influencia en la sociedad, de forma responsable y crítica. | C58: 3 | D58: Pensamiento Crítico y Ciudadanías Activas | E58: Identifica los Derechos y Deberes consignados en la Constitución 1991 en relación con la ciudadanía de manera local y global para la comprensión de inmersiones sociales éticas. Reflexiona los impactos de la investigación- acción sin daño en los espacios académicos y los territorios para el abordaje desde proyectos de investigación formativa. Elabora el diseño de planes detallados desde abordajes investigativos e inmersiones creativas para divulgar hallazgos en el ámbito académico. | F58: TP | G58: X | J58: 3 | K58: =12*J58 -> 36 | L58: =36*J58 -> 108 | M58: =SUM(K58:L58) -> 144 | N58: 1. Pacto social colombiano y marco de referencias de DDHH internacionales. 2. Planes detallados e inmersiones sociales desde procesos participativos, acciones sociales e iniciativas ciudadanas como respuesta a problemas glocales. 3. Perspectivas para la participación ciudadana en los territorios. 4. Los avances tecnológicos y su impacto en lo social, cultural y ambiental en el marco de las sociedades de información. | O58: Trabajo Directo: Desarrollo de encuentros sincrónicos Acompañamiento en foros Mensajería interna con la reflexión o síntesis de los resultados alcanzados por el grupo Trabajo Independiente: Revisión de lecturas fundamentales Revisión y desarrollo del material de trabajo Participación en foros de discusión, de actividades formativas o de resolución de dudas Revisión de material complementario | P58: Evaluación diagnóstica (semana 1- Cuestionario inicial de, mínimo, cinco preguntas, que recopila información sobre el conocimiento previo y las habilidades del estudiante. ) Actividad formativa (semana 2 - Foro individual o grupal, creado para que el estudiante participe activamente en la construcción de su conocimiento y desarrollo de habilidades. Varía entre una actividad entregable y la participación en un foro.) Actividades de entrega I (semana 4 - Actividad individual o grupal, diseñada para evaluar de manera integral el nivel de conocimiento, comprensión y el desempeño de los indicadores de logro. Varía entre entregas independientes o secuenciales. Al ser un módulo teórico, ésta es la única actividad de entrega. ) Actividad formativa (semana 5 - Foro individual o grupal, creado para que el estudiante participe activamente en la construcción de su conocimiento y desarrollo de habilidades. Varía entre una actividad entregable y la participación en un foro.) Actividades de entrega 2 (semana 6 - Actividad individual o grupal, diseñada para evaluar de manera integral el nivel de conocimiento, comprensión y el desempeño de los indicadores de logro. Varía entre entregas independientes o secuenciales. Al ser un módulo teórico, ésta es la única actividad de entrega. ) Autoevaluación (semana 8 - Cuestionario final de, mínimo, cinco preguntas, en el cual el estudiante reflexiona sobre su propio desempeño, habilidades y resultados en un contexto específico. ) | Q58: Las acciones de retroalimentación giran en torno a las siguientes. Formar: donde se crean las condiciones para que los estudiantes adquieran conocimientos, habilidades, actitudes, aptitudes y destrezas. Además, debe promover su desarrollo integral y debe acompañarlos en las situaciones académicas que enfrenten durante el desarrollo de un módulo o una asignatura. Informar: para que los estudiantes identifiquen los cambios que pueden afectarlos directa o indirectamente tanto en el aula de clase como en otros espacios. Prevenir: con el fin de anticiparse a las situaciones académicas que pueden representar dificultad para los estudiantes. Esto se logra a través de la interacción individual con los estudiantes y del completo conocimiento del contexto educativo en que el tutor se desenvuelve. Ayudar a decidir: donde se orienta a los estudiantes para que tomen la mejor decisión ante una situación concreta. El objetivo es que el estudiante fortalezca su autonomía y la toma de decisiones responsable.
A59: {=_xlfn.XLOOKUP(B59,'Paso 3 Redacción RA '!$I$3:$I$15,'Paso 3 Redacción RA '!$C$3:$C$15,,0,1)} -> Saber | B59: Identifica los procesos y procedimientos asociados a las diferentes áreas del derecho para estructurar las etapas necesarias y lo que de ellas se deriva, en la resolución de conflictos judiciales y extra judiciales. | C59: 3 | D59: Digitalización del Derecho | E59: Identifica las nociones básicas de la cibernética jurídica y su relación con el derecho para caracterizar su uso en los procesos del ámbito judicial, según la necesidad del contexto. Aplica los conceptos fundamentales del Derecho Digital para analizar asuntos judiciales relacionados con las tecnologías de la información y la comunicación. Implementa sistemas de gestión documental haciendo uso de las TIC, para documentar y digitalizar información de procesos o trámites en las entidades, de acuerdo con las condiciones y necesidades de estas. | F59: T | H59: X | J59: 3 | K59: =12*J59 -> 36 | L59: =36*J59 -> 108 | M59: =SUM(K59:L64) -> 144 | N59: 1. Generalidades de la digitalización del Derecho. 2. Conceptualización de la cibernética jurídica. 3. La archivística. 4. Gestión documental y aplicación de las nuevas tecnologías. | O59: Trabajo directo: Encuentros sincrónicos Mensajería interna Anuncios Trabajo independiente: Lecturas fundamentales y complementarias Recursos de apoyo Trabajo Colaborativo Foros de discusión grupal | P59: Evaluación diagnóstica (semana 1- Cuestionario inicial de, mínimo, cinco preguntas, que recopila información sobre el conocimiento previo y las habilidades del estudiante). Actividad formativa (semana 2 - Foro individual o grupal, creado para que el estudiante participe activamente en la construcción de su conocimiento y desarrollo de habilidades. Varía entre una actividad entregable y la participación en un foro). Actividades de entrega (semana 4 - Actividad individual o grupal, diseñada para evaluar de manera integral el nivel de conocimiento, comprensión y el desempeño de los indicadores de logro. Varía entre entregas independientes o secuenciales. Al ser un módulo teórico, ésta es la única actividad de entrega). Actividad formativa (semana 5 - Foro individual o grupal, creado para que el estudiante participe activamente en la construcción de su conocimiento y desarrollo de habilidades. Varía entre una actividad entregable y la participación en un foro). Actividad evaluativa (semana 6 - Cuestionario de, mínimo, cinco preguntas, que da cuenta del desarrollo total o parcial de los indicadores de logro y el desarrollo de los temas vistos hasta la unidad 3). Examen final (semana 8 - Cuestionario de, mínimo, quince preguntas, que da cuenta del desarrollo total o parcial de los indicadores de logro y el desarrollo de los temas vistos en el módulo). Autoevaluación (semana 8 - Cuestionario final de, mínimo, cinco preguntas, en el cual el estudiante reflexiona sobre su propio desempeño, habilidades y resultados en un contexto específico). | Q59: Las acciones de retroalimentación giran en torno a las siguientes. Formar: donde se crean las condiciones para que los estudiantes adquieran conocimientos, habilidades, actitudes, aptitudes y destrezas. Además, debe promover su desarrollo integral y debe acompañarlos en las situaciones académicas que enfrenten durante el desarrollo de un módulo o una asignatura. Informar: para que los estudiantes identifiquen los cambios que pueden afectarlos directa o indirectamente tanto en el aula de clase como en otros espacios. Prevenir: con el fin de anticiparse a las situaciones académicas que pueden representar dificultad para los estudiantes. Esto se logra a través de la interacción individual con los estudiantes y del completo conocimiento del contexto educativo en que el tutor se desenvuelve. Ayudar a decidir: donde se orienta a los estudiantes para que tomen la mejor decisión ante una situación concreta. El objetivo es que el estudiante fortalezca su autonomía y la toma de decisiones responsable.
A60: {=_xlfn.XLOOKUP(B60,'Paso 3 Redacción RA '!$I$3:$I$15,'Paso 3 Redacción RA '!$C$3:$C$15,,0,1)} -> Saberhacer | B60: Emplea los procesos y procedimientos que permiten gestionar una correcta administración de justicia, para generar los soportes documentales o verbales que apoyan la resolución de conflictos objeto de negociación, en las diferentes áreas del derecho.
A61: {=_xlfn.XLOOKUP(B61,'Paso 3 Redacción RA '!$I$3:$I$15,'Paso 3 Redacción RA '!$C$3:$C$15,,0,1)} -> Saberser | B61: Aplica adecuadamente técnicas, procesos, procedimientos y métodos propios del actuar jurídico y de la gestión documental judicial, para plantear soluciones acordes con la normatividad y con las necesidades identificadas en el contexto o en el objeto de negociación en la etapa judicial o extra judicial, según corresponda.
A62: {=_xlfn.XLOOKUP(B62,'Paso 3 Redacción RA '!$I$3:$I$15,'Paso 3 Redacción RA '!$C$3:$C$15,,0,1)} -> Saber | B62: Reconoce los textos jurídicos y contractuales que se deben generar en las diferentes áreas del derecho, para determinar el proceso archivístico o de digitalización que permite organizar y gestionar la documentación de información en las entidades.
A63: {=_xlfn.XLOOKUP(B63,'Paso 3 Redacción RA '!$I$3:$I$15,'Paso 3 Redacción RA '!$C$3:$C$15,,0,1)} -> Saber | B63: Identifica fenómenos contemporáneos y su relación con la profesión, para determinar sus impactos e influencia en la sociedad, de forma responsable y crítica.
A64: {=_xlfn.XLOOKUP(B64,'Paso 3 Redacción RA '!$I$3:$I$15,'Paso 3 Redacción RA '!$C$3:$C$15,,0,1)} -> Saberhacer | B64: Aplica técnicas para categorizar o documentar información acatando los requisitos establecidos en la normatividad sustancial y procesal, así como de la voluntad de los intervinientes.
A65: {=_xlfn.XLOOKUP(B65,'Paso 3 Redacción RA '!$I$3:$I$15,'Paso 3 Redacción RA '!$C$3:$C$15,,0,1)} -> Saber | B65: Identifica los procesos y procedimientos asociados a las diferentes áreas del derecho para estructurar las etapas necesarias y lo que de ellas se deriva, en la resolución de conflictos judiciales y extra judiciales. | C65: 3 | D65: Procedimientos Judiciales | E65: Identifica las etapas procesales según la jurisdicción y competencia para proyectar documentos en la realización de actuaciones judiciales, de acuerdo con la fase de la litis. Conoce las causales de nulidad (sustanciales y procesales) para proyectar la actuación necesaria de saneamiento de documentos o trámites, en los procesos judiciales. Aplica técnicas de intervención oral para construir argumentos válidos, según las necesidades eventuales del proceso jurídico. | F65: TP | H65: X | J65: 3 | K65: =12*J65 -> 36 | L65: =36*J65 -> 108 | M65: =SUM(K65:L70) -> 144 | N65: 1. Aspectos fundamentales del proceso judicial. 2. Procedimientos y recursos en el proceso judicial. 3. La oralidad como esquema procesal y sus aplicaciones en Colombia. 4. Habilidades para una intervención oral efectiva. | O65: Trabajo directo: Encuentros sincrónicos Mensajería interna Anuncios Trabajo independiente: Lecturas fundamentales y complementarias Recursos de apoyo Trabajo Colaborativo Foros de discusión grupal | P65: Evaluación diagnóstica (semana 1- Cuestionario inicial de, mínimo, cinco preguntas, que recopila información sobre el conocimiento previo o las habilidades del estudiante). Actividad formativa (semana 2 - Foro individual o grupal, creado para que el estudiante participe activamente en la construcción de su conocimiento y desarrollo de habilidades. Varía entre una actividad entregable y la participación en un foro). Actividad de entrega 1 (semana 4 - Actividad individual o grupal, diseñada para evaluar de manera integral el nivel de conocimiento, comprensión y el desempeño de los indicadores de logro. Varía entre entregas independientes o secuenciales). Actividad formativa (semana 5 - Foro individual o grupal, creado para que el estudiante participe activamente en la construcción de su conocimiento y desarrollo de habilidades. Varía entre una actividad entregable y la participación en un foro). Actividad evaluativa (semana 6 - Cuestionario de mínimo cinco preguntas, que da cuenta del desarrollo total o parcial de los indicadores de logro y el desarrollo de los temas vistos hasta la unidad 3). Actividad de entrega 2 (semana 7 - Actividad individual o grupal, diseñada para evaluar de manera integral el nivel de conocimiento, comprensión y el desempeño de los indicadores de logro. Varía entre entregas independientes o secuenciales). Autoevaluación (semana 8 - Cuestionario final de, mínimo, cinco preguntas, en el cual el estudiante reflexiona sobre su propio desempeño, habilidades y resultados en un contexto específico). | Q65: Las acciones de retroalimentación giran en torno a las siguientes. Formar: donde se crean las condiciones para que los estudiantes adquieran conocimientos, habilidades, actitudes, aptitudes y destrezas. Además, debe promover su desarrollo integral y debe acompañarlos en las situaciones académicas que enfrenten durante el desarrollo de un módulo o una asignatura. Informar: para que los estudiantes identifiquen los cambios que pueden afectarlos directa o indirectamente tanto en el aula de clase como en otros espacios. Prevenir: con el fin de anticiparse a las situaciones académicas que pueden representar dificultad para los estudiantes. Esto se logra a través de la interacción individual con los estudiantes y del completo conocimiento del contexto educativo en que el tutor se desenvuelve. Ayudar a decidir: donde se orienta a los estudiantes para que tomen la mejor decisión ante una situación concreta. El objetivo es que el estudiante fortalezca su autonomía y la toma de decisiones responsable.
A66: {=_xlfn.XLOOKUP(B66,'Paso 3 Redacción RA '!$I$3:$I$15,'Paso 3 Redacción RA '!$C$3:$C$15,,0,1)} -> Saberhacer | B66: Emplea los procesos y procedimientos que permiten gestionar una correcta administración de justicia, para generar los soportes documentales o verbales que apoyan la resolución de conflictos objeto de negociación, en las diferentes áreas del derecho.
A67: {=_xlfn.XLOOKUP(B67,'Paso 3 Redacción RA '!$I$3:$I$15,'Paso 3 Redacción RA '!$C$3:$C$15,,0,1)} -> Saberser | B67: Aplica adecuadamente técnicas, procesos, procedimientos y métodos propios del actuar jurídico y de la gestión documental judicial, para plantear soluciones acordes con la normatividad y con las necesidades identificadas en el contexto o en el objeto de negociación en la etapa judicial o extra judicial, según corresponda.
A68: {=_xlfn.XLOOKUP(B68,'Paso 3 Redacción RA '!$I$3:$I$15,'Paso 3 Redacción RA '!$C$3:$C$15,,0,1)} -> Saber | B68: Reconoce los textos jurídicos y contractuales que se deben generar en las diferentes áreas del derecho, para determinar el proceso archivístico o de digitalización que permite organizar y gestionar la documentación de información en las entidades.
A69: {=_xlfn.XLOOKUP(B69,'Paso 3 Redacción RA '!$I$3:$I$15,'Paso 3 Redacción RA '!$C$3:$C$15,,0,1)} -> Saber | B69: Identifica fenómenos contemporáneos y su relación con la profesión, para determinar sus impactos e influencia en la sociedad, de forma responsable y crítica.
A70: {=_xlfn.XLOOKUP(B70,'Paso 3 Redacción RA '!$I$3:$I$15,'Paso 3 Redacción RA '!$C$3:$C$15,,0,1)} -> Saberhacer | B70: Aplica técnicas para categorizar o documentar información acatando los requisitos establecidos en la normatividad sustancial y procesal, así como de la voluntad de los intervinientes.
A71: {=_xlfn.XLOOKUP(B71,'Paso 3 Redacción RA '!$I$3:$I$15,'Paso 3 Redacción RA '!$C$3:$C$15,,0,1)} -> Saber | B71: Identifica fenómenos contemporáneos y su relación con la profesión, para determinar sus impactos e influencia en la sociedad, de forma responsable y crítica. | C71: 3 | D71: Oportunidades para Emprender | E71: Propone soluciones a los problemas, frustraciones y expectativas de un grupo de personas en su comunidad para idear productos o servicios con valor agregado dentro de su campo de acción profesional. Diseña una idea de negocio que represente una oportunidad de mercado teniendo en cuenta sus habilidades para emprender y el análisis del entorno. | F71: TP | G71: X | J71: 3 | K71: =12*J71 -> 36 | L71: =36*J71 -> 108 | M71: =SUM(K71:L71) -> 144 | N71: 1. Empatía y Comprensión del Usuario. 2. Co-creación con los Usuarios. 3. Enfoque en la Experiencia del Usuario. 4. Diseño del modelo de negocio. | O71: Trabajo directo: Encuentros sincrónicos Mensajería interna Anuncios Trabajo independiente: Lecturas fundamentales y complementarias Material de trabajo Participación en foros | P71: Evaluación diagnóstica: Cuestionario inicial de mínimo cinco preguntas que recopila información sobre el conocimiento previo y las habilidades del estudiante. Actividad formativa: Foro individual o grupal, creado para que el estudiante participe activamente en la construcción de su conocimiento y desarrollo de habilidades. Varía entre una actividad entregable y la participación en un foro. Actividad de entrega 1 y 2: Actividad individual o grupal, diseñada para evaluar de manera integral el nivel de conocimiento, comprensión y el desempeño de los indicadores de logro. Varía entre entregas independientes o secuenciales. Actividad evaluativa: Cuestionario de, mínimo, cinco preguntas, que da cuenta del desarrollo total o parcial de los indicadores de logro y el desarrollo de los temas vistos hasta la unidad 3. Autoevaluación: Cuestionario final de mínimo cinco preguntas en el cual el estudiante reflexiona sobre su propio desempeño, habilidades y resultados en un contexto específico. | Q71: Las acciones de retroalimentación giran en torno a las siguientes. Formar: donde se crean las condiciones para que los estudiantes adquieran conocimientos, habilidades, actitudes, aptitudes y destrezas. Además, debe promover su desarrollo integral y debe acompañarlos en las situaciones académicas que enfrenten durante el desarrollo de un módulo o una asignatura. Informar: para que los estudiantes identifiquen los cambios que pueden afectarlos directa o indirectamente tanto en el aula de clase como en otros espacios. Prevenir: con el fin de anticiparse a las situaciones académicas que pueden representar dificultad para los estudiantes. Esto se logra a través de la interacción individual con los estudiantes y del completo conocimiento del contexto educativo en que el tutor se desenvuelve. Ayudar a decidir: donde se orienta a los estudiantes para que tomen la mejor decisión ante una situación concreta. El objetivo es que el estudiante fortalezca su autonomía y la toma de decisiones responsable.
A72: {=_xlfn.XLOOKUP(B72,'Paso 3 Redacción RA '!$I$3:$I$15,'Paso 3 Redacción RA '!$C$3:$C$15,,0,1)} -> Saber | B72: Identifica los procesos y procedimientos asociados a las diferentes áreas del derecho para estructurar las etapas necesarias y lo que de ellas se deriva, en la resolución de conflictos judiciales y extra judiciales. | C72: 3 | D72: Derecho Comercial | E72: Reconoce los pilares y fuentes del derecho comercial, sus características y su incidencia con otras ramas del derecho, para aplicar las normas comerciales con fundamento en las nociones de comerciante y acto de comercio, identificando el régimen legal de los bienes mercantiles y las obligaciones de los comerciantes en casos concretos. | F72: TP | H72: X | J72: 3 | K72: =12*J72 -> 36 | L72: =36*J72 -> 108 | M72: =SUM(K72:L77) -> 144 | N72: 1. Acercamiento al Derecho Comercial. 2. El comerciante. 3. El establecimiento de comercio. 4. Conflictos mercantiles y los MASC. | O72: Trabajo directo: Encuentros sincrónicos Mensajería interna Anuncios Trabajo independiente: Lecturas fundamentales y complementarias Recursos de apoyo Trabajo Colaborativo Foros de discusión grupal | P72: Actividad de puntos evaluables (semana 2 – Cuestionario de 5 preguntas). Entrega previa 1 (semana 3 - Laboratorio, taller, ejercicios, resolución de casos o de problemas, desarrollo de procesos o ejecución de propuestas. Entrega de forma individual o grupal, según indicaciones del profesor). Parcial (semana 4 - Cuestionarios de entre 15 y 20 preguntas). Entrega previa 2 (semana 5 - Laboratorio, taller, ejercicios, resolución de casos o de problemas, desarrollo de procesos o ejecución de propuestas. Entrega de forma individual o grupal, según indicaciones dadas por el profesor). Entrega final (semana 7 - Laboratorio, taller, ejercicios, resolución de casos o de problemas, desarrollo de procesos o ejecución de propuestas. Entrega de forma individual o grupal, según indicaciones dadas por el profesor). Evaluación final (semana 8 - Cuestionario de entre 15 y 20 preguntas). | Q72: Las acciones de retroalimentación giran en torno a las siguientes. Formar: donde se crean las condiciones para que los estudiantes adquieran conocimientos, habilidades, actitudes, aptitudes y destrezas. Además, debe promover su desarrollo integral y debe acompañarlos en las situaciones académicas que enfrenten durante el desarrollo de un módulo o una asignatura. Informar: para que los estudiantes identifiquen los cambios que pueden afectarlos directa o indirectamente tanto en el aula de clase como en otros espacios. Prevenir: con el fin de anticiparse a las situaciones académicas que pueden representar dificultad para los estudiantes. Esto se logra a través de la interacción individual con los estudiantes y del completo conocimiento del contexto educativo en que el tutor se desenvuelve. Ayudar a decidir: donde se orienta a los estudiantes para que tomen la mejor decisión ante una situación concreta. El objetivo es que el estudiante fortalezca su autonomía y la toma de decisiones responsable.
A73: {=_xlfn.XLOOKUP(B73,'Paso 3 Redacción RA '!$I$3:$I$15,'Paso 3 Redacción RA '!$C$3:$C$15,,0,1)} -> Saberhacer | B73: Emplea los procesos y procedimientos que permiten gestionar una correcta administración de justicia, para generar los soportes documentales o verbales que apoyan la resolución de conflictos objeto de negociación, en las diferentes áreas del derecho.
A74: {=_xlfn.XLOOKUP(B74,'Paso 3 Redacción RA '!$I$3:$I$15,'Paso 3 Redacción RA '!$C$3:$C$15,,0,1)} -> Saberser | B74: Aplica adecuadamente técnicas, procesos, procedimientos y métodos propios del actuar jurídico y de la gestión documental judicial, para plantear soluciones acordes con la normatividad y con las necesidades identificadas en el contexto o en el objeto de negociación en la etapa judicial o extra judicial, según corresponda.
A75: {=_xlfn.XLOOKUP(B75,'Paso 3 Redacción RA '!$I$3:$I$15,'Paso 3 Redacción RA '!$C$3:$C$15,,0,1)} -> Saber | B75: Reconoce los textos jurídicos y contractuales que se deben generar en las diferentes áreas del derecho, para determinar el proceso archivístico o de digitalización que permite organizar y gestionar la documentación de información en las entidades.
A76: {=_xlfn.XLOOKUP(B76,'Paso 3 Redacción RA '!$I$3:$I$15,'Paso 3 Redacción RA '!$C$3:$C$15,,0,1)} -> Saber | B76: Identifica fenómenos contemporáneos y su relación con la profesión, para determinar sus impactos e influencia en la sociedad, de forma responsable y crítica.
A77: {=_xlfn.XLOOKUP(B77,'Paso 3 Redacción RA '!$I$3:$I$15,'Paso 3 Redacción RA '!$C$3:$C$15,,0,1)} -> Saberhacer | B77: Aplica técnicas para categorizar o documentar información acatando los requisitos establecidos en la normatividad sustancial y procesal, así como de la voluntad de los intervinientes.
A78: {=_xlfn.XLOOKUP(B78,'Paso 3 Redacción RA '!$I$3:$I$15,'Paso 3 Redacción RA '!$C$3:$C$15,,0,1)} -> Saber | B78: Identifica los procesos y procedimientos asociados a las diferentes áreas del derecho para estructurar las etapas necesarias y lo que de ellas se deriva, en la resolución de conflictos judiciales y extra judiciales. | C78: 3 | D78: Derecho Laboral Individual y Seguridad Social | E78: Reconoce los elementos y conceptos básicos del derecho laboral individual y seguridad social desde los fundamentos normativos y constitucionales (Código Sustantivo del Trabajo y la Constitución Política de Colombia), para aplicarlos en la resolución de contextos con problemáticas laborales. Explica los requisitos que debe reunir un contrato de trabajo para determinar los derechos ciertos e indiscutibles que surgen de esa relación jurídica. | F78: TP | H78: X | J78: 3 | K78: =12*J78 -> 36 | L78: =36*J78 -> 108 | M78: =SUM(K78:L82) -> 144 | N78: 1. Historia, principios generales y fuentes del Derecho Laboral. 2. Contrato de trabajo, jornada laboral, salario y prestaciones sociales. 3. Reglamento interno de trabajo y fueros laborales. 4. Seguridad Social. | O78: Trabajo directo: Encuentros sincrónicos Mensajería interna Anuncios Trabajo independiente: Lecturas fundamentales y complementarias Recursos de apoyo Trabajo Colaborativo Foros de discusión grupal | P78: Actividad de puntos evaluables (semana 2 – Cuestionario de 5 preguntas). Entrega previa 1 (semana 3 - Laboratorio, taller, ejercicios, resolución de casos o de problemas, desarrollo de procesos o ejecución de propuestas. Entrega de forma individual o grupal, según indicaciones del profesor). Parcial (semana 4 - Cuestionarios de entre 15 y 20 preguntas). Entrega previa 2 (semana 5 - Laboratorio, taller, ejercicios, resolución de casos o de problemas, desarrollo de procesos o ejecución de propuestas. Entrega de forma individual o grupal, según indicaciones dadas por el profesor). Entrega final (semana 7 - Laboratorio, taller, ejercicios, resolución de casos o de problemas, desarrollo de procesos o ejecución de propuestas. Entrega de forma individual o grupal, según indicaciones dadas por el profesor). Evaluación final (semana 8 - Cuestionario de entre 15 y 20 preguntas). | Q78: Las acciones de retroalimentación giran en torno a las siguientes. Formar: donde se crean las condiciones para que los estudiantes adquieran conocimientos, habilidades, actitudes, aptitudes y destrezas. Además, debe promover su desarrollo integral y debe acompañarlos en las situaciones académicas que enfrenten durante el desarrollo de un módulo o una asignatura. Informar: para que los estudiantes identifiquen los cambios que pueden afectarlos directa o indirectamente tanto en el aula de clase como en otros espacios. Prevenir: con el fin de anticiparse a las situaciones académicas que pueden representar dificultad para los estudiantes. Esto se logra a través de la interacción individual con los estudiantes y del completo conocimiento del contexto educativo en que el tutor se desenvuelve. Ayudar a decidir: donde se orienta a los estudiantes para que tomen la mejor decisión ante una situación concreta. El objetivo es que el estudiante fortalezca su autonomía y la toma de decisiones responsable.
A79: {=_xlfn.XLOOKUP(B79,'Paso 3 Redacción RA '!$I$3:$I$15,'Paso 3 Redacción RA '!$C$3:$C$15,,0,1)} -> Saberhacer | B79: Emplea los procesos y procedimientos que permiten gestionar una correcta administración de justicia, para generar los soportes documentales o verbales que apoyan la resolución de conflictos objeto de negociación, en las diferentes áreas del derecho.
A80: {=_xlfn.XLOOKUP(B80,'Paso 3 Redacción RA '!$I$3:$I$15,'Paso 3 Redacción RA '!$C$3:$C$15,,0,1)} -> Saberser | B80: Aplica adecuadamente técnicas, procesos, procedimientos y métodos propios del actuar jurídico y de la gestión documental judicial, para plantear soluciones acordes con la normatividad y con las necesidades identificadas en el contexto o en el objeto de negociación en la etapa judicial o extra judicial, según corresponda.
A81: {=_xlfn.XLOOKUP(B81,'Paso 3 Redacción RA '!$I$3:$I$15,'Paso 3 Redacción RA '!$C$3:$C$15,,0,1)} -> Saber | B81: Reconoce los textos jurídicos y contractuales que se deben generar en las diferentes áreas del derecho, para determinar el proceso archivístico o de digitalización que permite organizar y gestionar la documentación de información en las entidades.
A82: {=_xlfn.XLOOKUP(B82,'Paso 3 Redacción RA '!$I$3:$I$15,'Paso 3 Redacción RA '!$C$3:$C$15,,0,1)} -> Saberhacer | B82: Aplica técnicas para categorizar o documentar información acatando los requisitos establecidos en la normatividad sustancial y procesal, así como de la voluntad de los intervinientes.
A83: {=_xlfn.XLOOKUP(B83,'Paso 3 Redacción RA '!$I$3:$I$15,'Paso 3 Redacción RA '!$C$3:$C$15,,0,1)} -> Saber | B83: Identifica los procesos y procedimientos asociados a las diferentes áreas del derecho para estructurar las etapas necesarias y lo que de ellas se deriva, en la resolución de conflictos judiciales y extra judiciales. | C83: 4 | D83: Administrativo Especial | E83: Identifica el derecho de petición y su clasificación, así como los medios de control y mecanismos alternativos de solución de conflictos para proponer soluciones legales en las cuales se restablezcan o reconozcan derechos ante la jurisdicción de lo contencioso administrativo. | F83: TP | H83: X | J83: 3 | K83: =12*J83 -> 36 | L83: =36*J83 -> 108 | M83: =SUM(K83:L88) -> 144 | N83: 1. Procedimiento administrativo general y Derecho de petición. 2. Organización de la Jurisdicción contenciosa administrativa y competencia. 3. Demanda y proceso contencioso administrativo y medios de control. 4. MASC en los procesos contenciosos administrativos. | O83: Trabajo directo: Encuentros sincrónicos Mensajería interna Anuncios Trabajo independiente: Lecturas fundamentales y complementarias Recursos de apoyo Trabajo Colaborativo Foros de discusión grupal | P83: Actividad de puntos evaluables (semana 2 – Cuestionario de 5 preguntas). Entrega previa 1 (semana 3 - Laboratorio, taller, ejercicios, resolución de casos o de problemas, desarrollo de procesos o ejecución de propuestas. Entrega de forma individual o grupal, según indicaciones del profesor). Parcial (semana 4 - Cuestionarios de entre 15 y 20 preguntas). Entrega previa 2 (semana 5 - Laboratorio, taller, ejercicios, resolución de casos o de problemas, desarrollo de procesos o ejecución de propuestas. Entrega de forma individual o grupal, según indicaciones dadas por el profesor). Entrega final (semana 7 - Laboratorio, taller, ejercicios, resolución de casos o de problemas, desarrollo de procesos o ejecución de propuestas. Entrega de forma individual o grupal, según indicaciones dadas por el profesor). Evaluación final (semana 8 - Cuestionario de entre 15 y 20 preguntas). | Q83: Las acciones de retroalimentación giran en torno a las siguientes. Formar: donde se crean las condiciones para que los estudiantes adquieran conocimientos, habilidades, actitudes, aptitudes y destrezas. Además, debe promover su desarrollo integral y debe acompañarlos en las situaciones académicas que enfrenten durante el desarrollo de un módulo o una asignatura. Informar: para que los estudiantes identifiquen los cambios que pueden afectarlos directa o indirectamente tanto en el aula de clase como en otros espacios. Prevenir: con el fin de anticiparse a las situaciones académicas que pueden representar dificultad para los estudiantes. Esto se logra a través de la interacción individual con los estudiantes y del completo conocimiento del contexto educativo en que el tutor se desenvuelve. Ayudar a decidir: donde se orienta a los estudiantes para que tomen la mejor decisión ante una situación concreta. El objetivo es que el estudiante fortalezca su autonomía y la toma de decisiones responsable.
A84: {=_xlfn.XLOOKUP(B84,'Paso 3 Redacción RA '!$I$3:$I$15,'Paso 3 Redacción RA '!$C$3:$C$15,,0,1)} -> Saberhacer | B84: Emplea los procesos y procedimientos que permiten gestionar una correcta administración de justicia, para generar los soportes documentales o verbales que apoyan la resolución de conflictos objeto de negociación, en las diferentes áreas del derecho.
A85: {=_xlfn.XLOOKUP(B85,'Paso 3 Redacción RA '!$I$3:$I$15,'Paso 3 Redacción RA '!$C$3:$C$15,,0,1)} -> Saberser | B85: Aplica adecuadamente técnicas, procesos, procedimientos y métodos propios del actuar jurídico y de la gestión documental judicial, para plantear soluciones acordes con la normatividad y con las necesidades identificadas en el contexto o en el objeto de negociación en la etapa judicial o extra judicial, según corresponda.
A86: {=_xlfn.XLOOKUP(B86,'Paso 3 Redacción RA '!$I$3:$I$15,'Paso 3 Redacción RA '!$C$3:$C$15,,0,1)} -> Saber | B86: Reconoce los textos jurídicos y contractuales que se deben generar en las diferentes áreas del derecho, para determinar el proceso archivístico o de digitalización que permite organizar y gestionar la documentación de información en las entidades.
A87: {=_xlfn.XLOOKUP(B87,'Paso 3 Redacción RA '!$I$3:$I$15,'Paso 3 Redacción RA '!$C$3:$C$15,,0,1)} -> Saber | B87: Identifica fenómenos contemporáneos y su relación con la profesión, para determinar sus impactos e influencia en la sociedad, de forma responsable y crítica.
A88: {=_xlfn.XLOOKUP(B88,'Paso 3 Redacción RA '!$I$3:$I$15,'Paso 3 Redacción RA '!$C$3:$C$15,,0,1)} -> Saberhacer | B88: Aplica técnicas para categorizar o documentar información acatando los requisitos establecidos en la normatividad sustancial y procesal, así como de la voluntad de los intervinientes.
A89: {=_xlfn.XLOOKUP(B89,'Paso 3 Redacción RA '!$I$3:$I$15,'Paso 3 Redacción RA '!$C$3:$C$15,,0,1)} -> Saber | B89: Identifica los procesos y procedimientos asociados a las diferentes áreas del derecho para estructurar las etapas necesarias y lo que de ellas se deriva, en la resolución de conflictos judiciales y extra judiciales. | C89: 4 | D89: Derecho del Consumo y la Competencia | E89: Identifica los derechos de los consumidores, garantías, regímenes de responsabilidad y protección contractual, para aplicar los instrumentos jurídicos de protección ante las entidades encargadas competentes en aras de proteger los derechos del consumidor. | F89: TP | H89: X | J89: 3 | K89: =12*J89 -> 36 | L89: =36*J89 -> 108 | M89: =SUM(K89:L94) -> 144 | N89: 1. Fundamento Constitucional de la Protección al Consumidor. 2. Regulación de Derechos y Obligaciones entre Productores, Proveedores y Consumidores. 3. Derecho de Información y publicidad engañosa. 4. Aspectos Procesales de la Protección al Consumidor. | O89: Trabajo directo: Encuentros sincrónicos Mensajería interna Anuncios Trabajo independiente: Lecturas fundamentales y complementarias Recursos de apoyo Trabajo Colaborativo Foros de discusión grupal | P89: Actividad de puntos evaluables (semana 2 – Cuestionario de 5 preguntas). Entrega previa 1 (semana 3 - Laboratorio, taller, ejercicios, resolución de casos o de problemas, desarrollo de procesos o ejecución de propuestas. Entrega de forma individual o grupal, según indicaciones del profesor). Parcial (semana 4 - Cuestionarios de entre 15 y 20 preguntas). Entrega previa 2 (semana 5 - Laboratorio, taller, ejercicios, resolución de casos o de problemas, desarrollo de procesos o ejecución de propuestas. Entrega de forma individual o grupal, según indicaciones dadas por el profesor). Entrega final (semana 7 - Laboratorio, taller, ejercicios, resolución de casos o de problemas, desarrollo de procesos o ejecución de propuestas. Entrega de forma individual o grupal, según indicaciones dadas por el profesor). Evaluación final (semana 8 - Cuestionario de entre 15 y 20 preguntas). | Q89: Las acciones de retroalimentación giran en torno a las siguientes. Formar: donde se crean las condiciones para que los estudiantes adquieran conocimientos, habilidades, actitudes, aptitudes y destrezas. Además, debe promover su desarrollo integral y debe acompañarlos en las situaciones académicas que enfrenten durante el desarrollo de un módulo o una asignatura. Informar: para que los estudiantes identifiquen los cambios que pueden afectarlos directa o indirectamente tanto en el aula de clase como en otros espacios. Prevenir: con el fin de anticiparse a las situaciones académicas que pueden representar dificultad para los estudiantes. Esto se logra a través de la interacción individual con los estudiantes y del completo conocimiento del contexto educativo en que el tutor se desenvuelve. Ayudar a decidir: donde se orienta a los estudiantes para que tomen la mejor decisión ante una situación concreta. El objetivo es que el estudiante fortalezca su autonomía y la toma de decisiones responsable.
A90: {=_xlfn.XLOOKUP(B90,'Paso 3 Redacción RA '!$I$3:$I$15,'Paso 3 Redacción RA '!$C$3:$C$15,,0,1)} -> Saberhacer | B90: Emplea los procesos y procedimientos que permiten gestionar una correcta administración de justicia, para generar los soportes documentales o verbales que apoyan la resolución de conflictos objeto de negociación, en las diferentes áreas del derecho.
A91: {=_xlfn.XLOOKUP(B91,'Paso 3 Redacción RA '!$I$3:$I$15,'Paso 3 Redacción RA '!$C$3:$C$15,,0,1)} -> Saberser | B91: Aplica adecuadamente técnicas, procesos, procedimientos y métodos propios del actuar jurídico y de la gestión documental judicial, para plantear soluciones acordes con la normatividad y con las necesidades identificadas en el contexto o en el objeto de negociación en la etapa judicial o extra judicial, según corresponda.
A92: {=_xlfn.XLOOKUP(B92,'Paso 3 Redacción RA '!$I$3:$I$15,'Paso 3 Redacción RA '!$C$3:$C$15,,0,1)} -> Saber | B92: Reconoce los textos jurídicos y contractuales que se deben generar en las diferentes áreas del derecho, para determinar el proceso archivístico o de digitalización que permite organizar y gestionar la documentación de información en las entidades.
A93: {=_xlfn.XLOOKUP(B93,'Paso 3 Redacción RA '!$I$3:$I$15,'Paso 3 Redacción RA '!$C$3:$C$15,,0,1)} -> Saber | B93: Identifica fenómenos contemporáneos y su relación con la profesión, para determinar sus impactos e influencia en la sociedad, de forma responsable y crítica.
A94: {=_xlfn.XLOOKUP(B94,'Paso 3 Redacción RA '!$I$3:$I$15,'Paso 3 Redacción RA '!$C$3:$C$15,,0,1)} -> Saberhacer | B94: Aplica técnicas para categorizar o documentar información acatando los requisitos establecidos en la normatividad sustancial y procesal, así como de la voluntad de los intervinientes.
A95: {=_xlfn.XLOOKUP(B95,'Paso 3 Redacción RA '!$I$3:$I$15,'Paso 3 Redacción RA '!$C$3:$C$15,,0,1)} -> Saber | B95: Identifica los procesos y procedimientos asociados a las diferentes áreas del derecho para estructurar las etapas necesarias y lo que de ellas se deriva, en la resolución de conflictos judiciales y extra judiciales. | C95: 4 | D95: Sociedades | E95: Identifica las necesidades legales sustanciales y formales de la constitución de cualquier sociedad o empresa unipersonal que quiera ser competitiva en el siglo XXI para reconocer el manejo de las distintas formas asociativas que se proponen en el derecho nacional e internacional. Reconoce el concepto de empresa como sociedad mercantil en cada tipología junto con sus atributos, para aplicarlo en la creación, modificación, fusión o liquidación de estas. | F95: TP | H95: X | J95: 3 | K95: =12*J95 -> 36 | L95: =36*J95 -> 108 | M95: =SUM(K95:L100) -> 144 | N95: 1. Fundamentos constitucionales del esquema societario. 2. Personalidad jurídica y tipicidad societaria. 3. Estructura del contrato de sociedad y asamblea general de socios. 4. La propiedad industrial y la SIC. | O95: Trabajo directo: Encuentros sincrónicos Mensajería interna Anuncios Trabajo independiente: Lecturas fundamentales y complementarias Recursos de apoyo Trabajo Colaborativo Foros de discusión grupal | P95: Actividad de puntos evaluables (semana 2 – Cuestionario de 5 preguntas). Entrega previa 1 (semana 3 - Laboratorio, taller, ejercicios, resolución de casos o de problemas, desarrollo de procesos o ejecución de propuestas. Entrega de forma individual o grupal, según indicaciones del profesor). Parcial (semana 4 - Cuestionarios de entre 15 y 20 preguntas). Entrega previa 2 (semana 5 - Laboratorio, taller, ejercicios, resolución de casos o de problemas, desarrollo de procesos o ejecución de propuestas. Entrega de forma individual o grupal, según indicaciones dadas por el profesor). Entrega final (semana 7 - Laboratorio, taller, ejercicios, resolución de casos o de problemas, desarrollo de procesos o ejecución de propuestas. Entrega de forma individual o grupal, según indicaciones dadas por el profesor). Evaluación final (semana 8 - Cuestionario de entre 15 y 20 preguntas). | Q95: Las acciones de retroalimentación giran en torno a las siguientes. Formar: donde se crean las condiciones para que los estudiantes adquieran conocimientos, habilidades, actitudes, aptitudes y destrezas. Además, debe promover su desarrollo integral y debe acompañarlos en las situaciones académicas que enfrenten durante el desarrollo de un módulo o una asignatura. Informar: para que los estudiantes identifiquen los cambios que pueden afectarlos directa o indirectamente tanto en el aula de clase como en otros espacios. Prevenir: con el fin de anticiparse a las situaciones académicas que pueden representar dificultad para los estudiantes. Esto se logra a través de la interacción individual con los estudiantes y del completo conocimiento del contexto educativo en que el tutor se desenvuelve. Ayudar a decidir: donde se orienta a los estudiantes para que tomen la mejor decisión ante una situación concreta. El objetivo es que el estudiante fortalezca su autonomía y la toma de decisiones responsable.
A96: {=_xlfn.XLOOKUP(B96,'Paso 3 Redacción RA '!$I$3:$I$15,'Paso 3 Redacción RA '!$C$3:$C$15,,0,1)} -> Saberhacer | B96: Emplea los procesos y procedimientos que permiten gestionar una correcta administración de justicia, para generar los soportes documentales o verbales que apoyan la resolución de conflictos objeto de negociación, en las diferentes áreas del derecho.
A97: {=_xlfn.XLOOKUP(B97,'Paso 3 Redacción RA '!$I$3:$I$15,'Paso 3 Redacción RA '!$C$3:$C$15,,0,1)} -> Saberser | B97: Aplica adecuadamente técnicas, procesos, procedimientos y métodos propios del actuar jurídico y de la gestión documental judicial, para plantear soluciones acordes con la normatividad y con las necesidades identificadas en el contexto o en el objeto de negociación en la etapa judicial o extra judicial, según corresponda.
A98: {=_xlfn.XLOOKUP(B98,'Paso 3 Redacción RA '!$I$3:$I$15,'Paso 3 Redacción RA '!$C$3:$C$15,,0,1)} -> Saber | B98: Reconoce los textos jurídicos y contractuales que se deben generar en las diferentes áreas del derecho, para determinar el proceso archivístico o de digitalización que permite organizar y gestionar la documentación de información en las entidades.
A99: {=_xlfn.XLOOKUP(B99,'Paso 3 Redacción RA '!$I$3:$I$15,'Paso 3 Redacción RA '!$C$3:$C$15,,0,1)} -> Saber | B99: Identifica fenómenos contemporáneos y su relación con la profesión, para determinar sus impactos e influencia en la sociedad, de forma responsable y crítica.
A100: {=_xlfn.XLOOKUP(B100,'Paso 3 Redacción RA '!$I$3:$I$15,'Paso 3 Redacción RA '!$C$3:$C$15,,0,1)} -> Saberhacer | B100: Aplica técnicas para categorizar o documentar información acatando los requisitos establecidos en la normatividad sustancial y procesal, así como de la voluntad de los intervinientes.
...

Sheet Taxonomía para competencias
B1: VerbosCompetencias
B2: Actualizar
B3: Administrar
B4: Asegurar
B5: Asesorar
B6: Auditar
B7: Comunicar
B8: Conducir
B9: Conocer
B10: Coordinar
B11: Definir
B12: Desarrollar
... B37: Analizar

Sheet Taxonomias para RA
S1: Taxonomía de Bloom Adaptada bajo las ideas de Anderson y Krathwohl | AL1: Taxonomía de Bloom adaptada bajo las ideas de Lorin y Krathwohl (LK) | AT1: Taxonomía de Bloom adaptada bajo las ideas de Anderson y Kendal (AK)
L2: Taxonomía de Bloom | S2: Cognitivo(BAK) | Y2: Procedimental(BAK) | AC2: Actitudinal(BAK)
A3: Taxonomías | C3: BAK | D3: LK | E3: AK | G3: CognitivoB | H3: ProcedimentalB | I3: ActitudinalB | L3: ConocimientoB | M3: ComprensiónB | N3: AplicaciónB | O3: AnálisisB | P3: SíntesisB | Q3: EvaluaciónB | S3: ConocimientoBAK | T3: ComprensiónBAK | U3: AplicaciónBAK | V3: AnálisisBAK | W3: SíntesisBAK | X3: EvaluaciónBAK | Y3: ImitaciónBAK | Z3: ManipulaciónBAK | AA3: PrecisiónBAK | AB3: ControlBAK | AC3: PercepciónBAK | AD3: ResponderBAK | AE3: ValorarBAK | AF3: OrganizarBAK | AG3: CaracterizarBAK | AL3: Procesos cognitivos de orden inferior | AO3: Procesos cognitivos de orden superior
A4: Bloom | C4: CognitivoBAK | D4: HechosLK | E4: InformaciónAK | G4: ConocimientoB | H4: ConocimientoB | I4: ConocimientoB | L4: Adquirir | M4: Auditar | N4: Aplicar | O4: Aislar | P4: Adaptar | Q4: Aconsejar | S4: Adquirir | T4: Auditar | U4: Aplicar | V4: Aislar | W4: Adaptar | X4: Aconsejar | Y4: Ajustar | Z4: Direccionar | AA4: Disponer | AB4: Remover | AC4: Hacer | AD4: Aprobar | AE4: Adoptar | AF4: Extraer | AG4: Negociar | AL4: RecordarLK | AM4: ComprenderLK | AN4: AplicarLK | AO4: AnalizarLK | AP4: EvaluarLK | AQ4: CrearLK | AT4: RecuperaciónAK | AU4: ComprensiónAK | AV4: AnálisisAK | AW4: UsoConocimientoAK | AX4: MetacogniciónAK | AY4: SistemadelYoAK
A5: BAK | C5: ProcedimentalBAK | D5: ConceptosLK | E5: ProcesosMentalesAK | G5: ComprensiónB | H5: ComprensiónB | I5: ComprensiónB | L5: Buscar | M5: Bosquejar | N5: Calisificar | O5: Analizar | P5: Administrar | Q5: Adjuntar | S5: Buscar | T5: Bosquejar | U5: Calisificar | V5: Analizar | W5: Administrar | X5: Adjuntar | Y5: Adaptar | Z5: Desmontar | AA5: Planear | AB5: Quitar | AC5: Conducir | AD5: Autorizar | AE5: Aprobar | AF5: Resumir | AG5: Ofrecer | AL5: Afirmar | AM5: Clasificar | AN5: Actuar | AO5: Agrupar | AP5: Adaptar | AQ5: Desarrollar | AT5: Afirmar | AU5: Auditar | AV5: Agrupar | AW5: Actuar | AX5: Aceptar | AY5: Aceptar
A6: LK | C6: ActitudinalBAK | D6: ProcedimientoslLK | E6: PsicomotorAK | G6: AplicaciónB | H6: AplicaciónB | I6: AplicaciónB | L6: Citar | M6: Comentar | N6: Combinar | O6: Calcular | P6: Arreglar | Q6: Agregar | S6: Citar | T6: Comentar | U6: Combinar | V6: Calcular | W6: Arreglar | X6: Agregar | Y6: Modificar | Z6: Dramatizar | AA6: Apalancar | AB6: Suprimir | AC6: Dirigir | AD6: Demostrar | AE6: Aceptar | AF6: Promover | AG6: Conducir | AL6: Citar | AM6: Comparar | AN6: Agrupar | AO6: Aislar | AP6: Añadir | AQ6: Elaborar | AT6: Citar | AU6: Bosquejar | AV6: Aislar | AW6: Agrupar | AX6: Adelantar | AY6: Adoptar
A7: AK | D7: MetacogniciónLK | G7: AnálisisB | H7: AnálisisB | I7: AnálisisB | L7: Consignar | M7: Comunicar | N7: Componer | O7: Categorizar | P7: Arreglar | Q7: Alinear | S7: Consignar | T7: Comunicar | U7: Componer | V7: Categorizar | W7: Arreglar | X7: Alinear | Y7: Concretar | Z7: Docificar | AA7: Levantar | AB7: Eliminar | AC7: Direccionar | AD7: Afirmar | AE7: Afirmar | AF7: Adelantar | AG7: Comportarse bajo condiciones | AL7: Copiar | AM7: Contrastar | AN7: Calcular | AO7: Asumir | AP7: Apoyar | AQ7: Maximizar | AT7: Copiar | AU7: Clasificar | AV7: Analizar | AW7: Aplicar | AX7: Adoptar | AY7: Afinar
G8: SíntesisB | H8: SíntesisB | I8: SíntesisB | L8: Decir | M8: Convertir | N8: Conducir | O8: Comparar | P8: Articular | Q8: Arbitrar | S8: Decir | T8: Convertir | U8: Conducir | V8: Comparar | W8: Articular | X8: Arbitrar | Y8: Asegurar | Z8: Dibujar | AA8: Estimular | AB8: Retirar | AC8: Aplicar | AD8: Asegurar | AE8: Ratificar | AF8: Fomentar | AG8: Completar | AL8: Decir | AM8: Demostrar | AN8: Categorizar | AO8: Buscar similitudes | AP8: Argumentar | AQ8: Mejorar | AT8: Decir | AU8: Comentar | AV8: Aplicar | AW8: Calcular | AX8: Afinar | AY8: Agradecer
G9: EvaluaciónB | H9: EvaluaciónB | I9: EvaluaciónB | L9: Definir | M9: Criticar | N9: Construir | O9: Considerar | P9: Aumentar | Q9: Asegurar | S9: Definir | T9: Criticar | U9: Construir | V9: Considerar | W9: Aumentar | X9: Asegurar | Y9: Alinear | Z9: Trazar | AA9: Localizar | AB9: Extirpar | AC9: Manejar | AD9: Hacer | AE9: Apreciar | AF9: Anticipar | AG9: Afinar | AL9: Definir | AM9: Discutir | AN9: Conectar | AO9: Categorizar | AP9: Cambiar | AQ9: Minimizar | AT9: Definir | AU9: Comparar | AV9: Asumir | AW9: Calisificar | AX9: Afirmar | AY9: Ambicionar
L10: Deletrear | M10: Dar ejemplos | N10: Demostrar | O10: Contrastar | P10: Calcular | Q10: Asesorar | S10: Deletrear | T10: Dar ejemplos | U10: Demostrar | V10: Contrastar | W10: Calcular | X10: Asesorar | Y10: Analizar | Z10: Hacer | AA10: Ubicar | AB10: Disipar | AC10: Guiar | AD10: Comunicar | AE10: Comprender | AF10: Proponer | AG10: Acabar | AL10: Deletrear | AM10: Ejemplificar | AN10: Construir | AO10: Centrarse | AP10: Combinar | AQ10: Modelar | AT10: Deletrear | AU10: Comunicar | AV10: Buscar similitudes | AW10: Categorizar | AX10: Agradecer | AY10: Anhelar
G11: HechosLK | H11: ConceptosLK | I11: ProcedimientosLK | J11: MetacogniciónLK | L11: Demostrar | M11: Debatir | N11: Determinar | O11: Criticar | P11: Componer | Q11: Atar | S11: Demostrar | T11: Debatir | U11: Determinar | V11: Criticar | W11: Componer | X11: Atar | Y11: Aplicar | Z11: Extraer | AA11: Encontrar | AB11: Hacer | AC11: Realizar | AD11: Hablar | AE11: Agradecer | AF11: Defender | AG11: Terminar | AL11: Duplicar | AM11: Esquematizar | AN11: Demostrar | AO11: Comparar | AP11: Comparar | AQ11: Pensar | AT11: Duplicar | AU11: Contrastar | AV11: Calcular | AW11: Combinar | AX11: Ambicionar | AY11: Anticipar
G12: RecordarLK | H12: RecordarLK | I12: RecordarLK | J12: RecordarLK | L12: Describir | M12: Describir | N12: Dibujar | O12: Cuestionar | P12: Computar | Q12: Calcular | S12: Describir | T12: Describir | U12: Dibujar | V12: Cuestionar | W12: Computar | X12: Calcular | Y12: Arreglar | Z12: Perforar | AA12: Colocar | AB12: Reproducir | AC12: Emplear | AD12: Discutir | AE12: Estimar | AF12: Proteger | AG12: Contextualizar | AL12: Elegir | AM12: Explicar | AN12: Desarrollar | AO12: Correlacionar | AP12: Compilar | AQ12: Planear | AT12: Elegir | AU12: Convertir | AV12: Calisificar | AW12: Componer | AX12: Anhelar | AY12: Apreciar
G13: ComprenderLK | H13: ComprenderLK | I13: ComprenderLK | J13: ComprenderLK | L13: Elegir | M13: Desplegar | N13: Discriminar | O13: Debatir | P13: Concluir | Q13: Calificar | S13: Elegir | T13: Desplegar | U13: Discriminar | V13: Debatir | W13: Concluir | X13: Calificar | Y13: Organizar | Z13: Ejercitar | AA13: Establecer | AB13: Traducir | AC13: Aceptar | AD13: Cooperar | AE13: Tasar | AF13: Definir | AG13: Cooperar | AL13: Escribir | AM13: Expresar | AN13: Dramatizar | AO13: Descomponer | AP13: Componer | AQ13: Proponer | AT13: Escribir | AU13: Criticar | AV13: Categorizar | AW13: Conducir | AX13: Anticipar | AY13: Aprobar
G14: AplicarLK | H14: AplicarLK | I14: AplicarLK | J14: AplicarLK | L14: Enseñar | M14: Dibujar | N14: Diseñar | O14: Deducir | P14: Conectar | Q14: Censurar | S14: Enseñar | T14: Dibujar | U14: Diseñar | V14: Deducir | W14: Conectar | X14: Censurar | Y14: Ordenar | Z14: Enseñar | AA14: Hallar | AB14: Entregar | AC14: Admitir | AD14: Colaborar | AE14: Aspirar | AF14: Determinar | AG14: Colaborar | AL14: Leer | AM14: Generalizar | AN14: Elegir | AO14: Diferenciar | AP14: Construir | AQ14: Reescribir | AT14: Leer | AU14: Dar ejemplos | AV14: Centrarse | AW14: Conectar | AX14: Apoyar | AY14: Asistir
G15: AnalizarLK | H15: AnalizarLK | I15: AnalizarLK | J15: AnalizarLK | L15: Escribir | M15: Discutir | N15: Dramatizar | O15: Desarrollar | P15: Construir | Q15: Clasificar | S15: Escribir | T15: Discutir | U15: Dramatizar | V15: Desarrollar | W15: Construir | X15: Clasificar | Y15: Disponer | Z15: Conducir | AA15: Situar | AB15: Conducir | AC15: Evaluar | AD15: Actuar recíprocamente | AE15: Ambicionar | AF15: Considerar | AG15: Discriminar | AL15: Listar | AM15: Ilustrar | AN15: Emplear | AO15: Distinguir | AP15: Convencer | AQ15: Simplificar | AT15: Listar | AU15: Debatir | AV15: Combinar | AW15: Construir | AX15: Apreciar | AY15: Aspirar
G16: EvaluarLK | H16: EvaluarLK | I16: EvaluarLK | J16: EvaluarLK | L16: Establecer | M16: Diseñar | N16: Duplicar | O16: Detectar | P16: Crear | Q16: Computar | S16: Establecer | T16: Diseñar | U16: Duplicar | V16: Detectar | W16: Crear | X16: Computar | Y16: Acordar | Z16: Dirigir | AA16: Bajar | AB16: Direccionar | AC16: Valorar | AD16: Obrar recíprocamente | AE16: Anhelar | AF16: Discernir | AG16: Distinguir | AL16: Localizar | AM16: Inferir | AN16: Enseñar | AO16: Dividir | AP16: Crear | AQ16: Suponer | AT16: Localizar | AU16: Demostrar | AV16: Comparar | AW16: Demostrar | AX16: Aprobar | AY16: Atender
G17: CrearLK | H17: CrearLK | I17: CrearLK | J17: CrearLK | L17: Etiquetar | M17: Establecer | N17: Elegir | O17: Diagramar | P17: Decidir | Q17: Concluir | S17: Etiquetar | T17: Establecer | U17: Elegir | V17: Diagramar | W17: Decidir | X17: Concluir | Y17: Gestionar | Z17: Manejar | AA17: Manipular | AB17: Reparar | AC17: Apreciar | AD17: Recitar | AE17: Creer | AF17: Percibir | AG17: Categorizar | AL17: Memorizar | AM17: Informar | AN17: Entrevistar | AO17: Elegir | AP17: Criticar | AQ17: Sustituir | AT17: Memorizar | AU17: Describir | AV17: Componer | AW17: Desarrollar | AX17: Arreglar | AY17: Categorizar
L18: Examinar | M18: Examinar | N18: Emparejar | O18: Diferenciar | P18: Deducir | Q18: Conformar | S18: Examinar | T18: Examinar | U18: Emparejar | V18: Diferenciar | W18: Deducir | X18: Conformar | Y18: Armar | Z18: Guiar | AA18: Manejar | AB18: Componer | AC18: Tasar | AD18: Decir | AE18: Ser partidario de | AF18: Identificar | AG18: Juzgar | AL18: Mostrar | AM18: Interpretar | AN18: Hacer uso | AO18: Encontrar | AP18: Debatir | AQ18: Teorizar | AT18: Mostrar | AU18: Desplegar | AV18: Conducir | AW18: Determinar | AX18: Asistir | AY18: Clasificar
G19: InformaciónAK | H19: ProcesosAK | I19: PsicomotorAK | L19: Examinar | M19: Explicar | N19: Emplear | O19: Discernir | P19: Derivar | Q19: Constrastar | S19: Examinar | T19: Explicar | U19: Emplear | V19: Discernir | W19: Derivar | X19: Constrastar | Y19: Ensamblar | Z19: Examinar | AA19: Medir | AB19: Reemplazar | AC19: Estimar | AD19: Enumerar | AE19: Cuidar | AF19: Reconocer | AG19: Participar | AL19: Nombrar | AM19: Mostrar | AN19: Identificar | AO19: Encuestar | AP19: Decidir | AQ19: Testar | AT19: Nombrar | AU19: Dibujar | AV19: Considerar | AW19: Dibujar | AX19: Aspirar | AY19: Completar
G20: RecuperaciónAK | H20: RecuperaciónAK | I20: RecuperaciónAK | L20: Grabar | M20: Exponer | N20: Esquematizar | O20: Discriminar | P20: Desarrollar | Q20: Contabilizar | S20: Grabar | T20: Exponer | U20: Esquematizar | V20: Discriminar | W20: Desarrollar | X20: Contabilizar | Y20: Reunir | Z20: Ejecutar | AA20: Racionar | AB20: Sustituir | AC20: Preguntar | AD20: Narrar | AE20: Atender | AF20: Formular | AG20: Atender | AL20: Observar | AM20: Observar | AN20: Interpretar | AO20: Establecer | AP20: Deducir | AQ20: Transformar | AT20: Observar | AU20: Discutir | AV20: Construir | AW20: Discriminar | AX20: Atender | AY20: Comprender
G21: ComprensiónAK | H21: ComprensiónAK | I21: ComprensiónAK | L21: Hacer | M21: Expresar | N21: Estimar | O21: Distinguir | P21: Describir | Q21: Controlar | S21: Hacer | T21: Expresar | U21: Estimar | V21: Distinguir | W21: Describir | X21: Controlar | Y21: Construir | Z21: Explorar | AA21: Separer | AB21: Reponer | AC21: Interrogar | AD21: Referir | AE21: Asistir | AF21: Arreglar | AG21: Servir | AL21: Omitir | AM21: Parafrasear | AN21: Manipular | AO21: Examinar | AP21: Defender | AQ21: Visualizar | AT21: Omitir | AU21: Diseñar | AV21: Contrastar | AW21: Diseñar | AX21: Aunar | AY21: Conducir
G22: AnálisisAK | H22: AnálisisAK | I22: AnálisisAK | L22: Identificar | M22: Extraer | N22: Estructurar | O22: Estructurar | P22: Desempeñar | Q22: Corregir | S22: Identificar | T22: Extraer | U22: Estructurar | V22: Estructurar | W22: Desempeñar | X22: Corregir | Y22: Edificar | Z22: Expresar | AA22: Dividir | AB22: Colocar | AC22: Publicar | AD22: Resolver | AE22: Preocuparse de o por | AF22: Preguntar | AG22: Cumplir | AL22: Rastrear | AM22: Predecir | AN22: Organizar | AO22: Inferir | AP22: Demostrar | AT22: Parafrasear | AU22: Ejemplificar | AV22: Correlacionar | AW22: Dramatizar | AX22: Categorizar | AY22: Conectar
G23: UsoConocimientoAK | H23: UsoConocimientoAK | I23: UsoConocimientoAK | L23: Ilustrar | M23: Generalizar | N23: Estructurar | O23: Examinar | P23: Dirigir | Q23: Criticar | S23: Ilustrar | T23: Generalizar | U23: Estructurar | V23: Examinar | W23: Dirigir | X23: Criticar | Y23: Hacer | Z23: Encajar | AA23: Repartir | AB23: Ubicar | AC23: Asisitir | AD23: Acordar | AE23: Elegir | AF23: Cuestionar | AG23: Ejercer | AL23: Recitar | AM23: Preguntar | AN23: Planear | AO23: Inspeccionar | AP23: Descubrir | AT23: Rastrear | AU23: Esquematizar | AV23: Criticar | AW23: Duplicar | AX23: Clasificar | AY23: Considerar
G24: MetacogniciónAK | H24: MetacogniciónAK | I24: MetacogniciónAK | L24: Listar | M24: Hacer | N24: Evaluar | O24: Experimentar | P24: Diseñar | Q24: Cuestionar | S24: Listar | T24: Hacer | U24: Evaluar | V24: Experimentar | W24: Diseñar | X24: Cuestionar | Y24: Trazar | Z24: Ajustar | AA24: Mezclar | AB24: Ejecutar | AC24: Atender | AD24: Seleccionar | AE24: Seleccionar | AF24: Relacionar | AG24: Entregar | AL24: Reconocer | AM24: Relacionar | AN24: Practicar | AO24: Investigar | AP24: Diseñar | AT24: Recitar | AU24: Establecer | AV24: Cuestionar | AW24: Elegir | AX24: Colaborar | AY24: Constatar
G25: AutoSistemaAK | H25: AutoSistemaAK | I25: AutoSistemaAK | L25: Mostar | M25: Identificar | N25: Experimentar | O25: Inspeccionar | P25: Ejercer | Q25: Culminar | S25: Mostar | T25: Identificar | U25: Experimentar | V25: Inspeccionar | W25: Ejercer | X25: Culminar | Y25: Preparar | Z25: Acceder | AA25: Porcionar | AB25: Correr | AC25: Servir | AD25: Elegir | AE25: Escoger | AF25: Conectar | AG25: Apoyar | AL25: Relacionar | AM25: Resumir | AN25: Resolver | AO25: Motivar | AP25: Estimar | AT25: Reconocer | AU25: Examinar | AV25: Debatir | AW25: Emparejar | AX25: Compartir | AY25: Contextualizar
L26: Nombrar | M26: Indicar | N26: Ilustrar | O26: Inventariar | P26: Ensamblar | Q26: Debatir | S26: Nombrar | T26: Indicar | U26: Ilustrar | V26: Inventariar | W26: Ensamblar | X26: Debatir | Y26: Cambiar | Z26: Arreglar | AA26: Modificar | AB26: Llevar | AC26: Ocupar | AD26: Escoger | AE26: Clasificar | AF26: Relatar | AG26: Soportar | AL26: Relacionar | AM26: Revisar | AN26: Resumir | AO26: Observar | AP26: Evaluar | AT26: Relacionar | AU26: Explicar | AV26: Deducir | AW26: Emplear | AX26: Completar | AY26: Cuestionar
L27: Numerar | M27: Inferir | N27: Indicar | O27: Investigar | P27: Escribir | Q27: Decidir | S27: Numerar | T27: Inferir | U27: Indicar | V27: Investigar | W27: Escribir | X27: Decidir | Y27: Modificar | Z27: Mejorar | AA27: Ajustar | AB27: Manejar | AC27: Elegir | AD27: Clasificar | AE27: Convocar | AF27: Revelar | AG27: Verificar | AL27: Repetir | AM27: Traducir | AN27: Seleccionar | AO27: Ordenar | AP27: Experimentar | AT27: Repetir | AU27: Exponer | AV27: Demostrar | AW27: Enseñar | AX27: Comportarse bajo condiciones | AY27: Cuidar
L28: Observar | M28: Interpretar | N28: Interpretar | O28: Listar | P28: Establecer | Q28: Deducir | S28: Observar | T28: Interpretar | U28: Interpretar | V28: Listar | W28: Establecer | X28: Deducir | Y28: Transformar | Z28: Manipular | AA28: Mover | AB28: Seguir | AC28: Escoger | AD28: Contar | AE28: Unir | AF28: Exteriorizar | AG28: Constatar | AN28: Simular | AO28: Preguntar | AP28: Explicar | AU28: Expresar | AV28: Desarrollar | AW28: Entrevistar | AX28: Comprender | AY28: Cumplir
L29: Obtener | M29: Inventariar | N29: Investigar | O29: Medir | P29: Estudiar | Q29: Defender | S29: Obtener | T29: Inventariar | U29: Investigar | V29: Medir | W29: Estudiar | X29: Defender | Y29: Comprobar | Z29: Maniobrar | AA29: Maniobrar | AB29: Trasladar | AC29: Seleccionar | AD29: Informar | AE29: Ensamblar | AF29: Desplegar | AG29: Controlar | AN29: Transferir | AO29: Priorizar | AP29: Extender | AU29: Extraer | AV29: Descomponer | AW29: Esquematizar | AX29: Conducir | AY29: Defender
L30: Ordenar | M30: Localizar | N30: Listar | O30: Planear | P30: Figurar | Q30: Defender | S30: Ordenar | T30: Localizar | U30: Listar | V30: Planear | W30: Figurar | X30: Defender | Y30: Verificar | Z30: Identificar | AA30: Gestionar | AB30: Implementar | AC30: Escuchar | AD30: Indicar | AE30: Participar | AN30: Unir | AO30: Probar | AP30: Formular | AU30: Generalizar | AV30: Detectar | AW30: Estimar | AX30: Conectar | AY30: Determinar
L31: Organizar | M31: Narrar | N31: Manipular | O31: Preguntar | P31: Formular | Q31: Determinar | S31: Organizar | T31: Narrar | U31: Manipular | V31: Preguntar | W31: Formular | X31: Determinar | Y31: Controlar | Z31: Inspeccionar | AA31: Negociar | AB31: Esculpir | AC31: Anotar | AD31: Distinguir | AE31: Aunar | AN31: Usar | AO31: Razonar | AP31: Hipotetizar | AU31: Hacer | AV31: Determinar | AW31: Estructurar | AX31: Considerar | AY31: Discernir
L32: Preguntar | M32: Parafrasear | N32: Modelar | O32: Probar | P32: Generar | Q32: Discutir | S32: Preguntar | T32: Parafrasear | U32: Modelar | V32: Probar | W32: Generar | X32: Discutir | Y32: Contrastar | Z32: Revisar | AA32: Emitir | AB32: Entallar | AC32: Observar | AD32: Relatar | AE32: Proporcionar | AO32: Reorganizar | AP32: Influir | AU32: Identificar | AV32: Diagramar | AW32: Evaluar | AX32: Constatar | AY32: Discriminar
L33: Presentar | M33: Presentar | N33: Operar | O33: Reconocer | P33: Gestionar | Q33: Elegir | S33: Presentar | T33: Presentar | U33: Operar | V33: Reconocer | W33: Gestionar | X33: Elegir | Y33: Contar | Z33: Registrar | AA33: Abrir | AB33: Servir | AC33: Cumplir | AD33: Conocer | AE33: Estimular | AO33: Resaltar | AP33: Innovar | AU33: Ilustrar | AV33: Dibujar | AW33: Experimentar | AX33: Contextualizar | AY33: Distinguir
L34: Probar | M34: Relatar | N34: Organizar | O34: Relacionar | P34: Hacer | Q34: Ensamblar | S34: Probar | T34: Relatar | U34: Organizar | V34: Relacionar | W34: Hacer | X34: Ensamblar | Y34: Limpiar | Z34: Reconocer | AA34: Destapar | AB34: Coser | AC34: Examinar | AE34: Contribuir | AO34: Separar | AP34: Justificar | AU34: Indicar | AV34: Diferenciar | AW34: Hacer uso | AX34: Contribuir | AY34: Ejercer
L35: Realizar | M35: Reportar | N35: Patronar | O35: Separar | P35: Inferir | Q35: Escoger | S35: Realizar | T35: Reportar | U35: Patronar | V35: Separar | W35: Inferir | X35: Escoger | Y35: Filtrar | Z35: Instalar | AA35: Comenzar | AB35: Soldar | AC35: Usar | AE35: Provocar | AO35: Simplificar | AP35: Juzgar | AU35: Inferir | AV35: Discernir | AW35: Identificar | AX35: Controlar | AY35: Elegir
L36: Reconocer | M36: Resumir | N36: Practicar | O36: Subdividir | P36: Instalar | Q36: Establecer | S36: Reconocer | T36: Resumir | U36: Practicar | V36: Subdividir | W36: Instalar | X36: Establecer | Y36: Escoger | Z36: Poner | AA36: Operar | AB36: Clasificar | AC36: Decir | AE36: Compartir | AP36: Medir | AU36: Informar | AV36: Discriminar | AW36: Ilustrar | AX36: Convocar | AY36: Escoger
L37: Recordar | M37: Revisar | N37: Recoger | P37: Interpretar | Q37: Estimar | S37: Recordar | T37: Revisar | U37: Recoger | W37: Interpretar | X37: Estimar | Y37: Recoger | Z37: Colocar | AA37: Dirigir | AB37: Ordenar | AC37: Apreciar | AE37: Apoyar | AP37: Opinar | AU37: Interpretar | AV37: Diseñar | AW37: Indicar | AX37: Cooperar | AY37: Estimar
L38: Registrar | M38: Seleccionar | N38: Relacionar | P38: Introducir | Q38: Evaluar | S38: Registrar | T38: Seleccionar | U38: Relacionar | W38: Introducir | X38: Evaluar | Y38: Recaudar | Z38: Inventariar | AA38: Impulsar | AB38: Arreglar | AC38: Distinguir | AE38: Soportar | AP38: Originar | AU38: Inventariar | AV38: Distinguir | AW38: Interpretar | AX38: Creer | AY38: Estimular
L39: Relacionar | M39: Separar | N39: Reportar | P39: Inventar | Q39: Evaluar | S39: Relacionar | T39: Separar | U39: Reportar | W39: Inventar | X39: Evaluar | Y39: Juntar | Z39: Aislar | AA39: Organizar | AB39: Extender | AC39: Detectar | AP39: Percibir | AU39: Localizar | AV39: Dividir | AW39: Investigar | AX39: Cuestionar | AY39: Exteriorizar
L40: Relatar | M40: Traducir | N40: Resolver | P40: Juntar | Q40: Finalizar | S40: Relatar | T40: Traducir | U40: Resolver | W40: Juntar | X40: Finalizar | Y40: Comparar | Z40: Ampliar | AA40: Ordenar | AB40: Ensanchar | AC40: Clasificar | AP40: Persuadir | AU40: Mostrar | AV40: Dramatizar | AW40: Listar | AX40: Cuidar | AY40: Extraer
L41: Reproducir | M41: Transformar | N41: Transferir | P41: Manipular | Q41: Formar | S41: Reproducir | T41: Transformar | U41: Transferir | W41: Manipular | X41: Formar | Y41: Cotejar | AA41: Revisar | AB41: Preguntar | AP41: Premiar | AU41: Narrar | AV41: Duplicar | AW41: Manipular | AX41: Cumplir | AY41: Formular
L42: Revisar | M42: Ubicar | N42: Usar | P42: Mejorar | Q42: Justificar | S42: Revisar | T42: Ubicar | U42: Usar | W42: Mejorar | X42: Justificar | Y42: Conducir | AA42: Repasar | AB42: Mover | AP42: Probar | AU42: Observar | AV42: Elegir | AW42: Modelar | AX42: Defender | AY42: Identificar
L43: Rotular | N43: Valorar | P43: Modificar | Q43: Juzgar | S43: Rotular | U43: Valorar | W43: Modificar | X43: Juzgar | Y43: Direccionar | AA43: Empaquetar | AB43: Balancear | AP43: Recomendar | AU43: Predecir | AV43: Emparejar | AW43: Operar | AX43: Definir | AY43: Juzgar
L44: Seleccionar | P44: Numerar | Q44: Marcar | S44: Seleccionar | W44: Numerar | X44: Marcar | Y44: Inspeccionar | AA44: Envasar | AB44: Reconocer | AP44: Seleccionar | AU44: Preguntar | AV44: Emplear | AW44: Organizar | AX44: Desplegar | AY44: Negociar
L45: Subrayar | P45: Obtener | Q45: Marcar | S45: Subrayar | W45: Obtener | X45: Marcar | Y45: Coordinar | AA45: Pintar | AB45: Inspeccionar | AP45: Testar | AU45: Presentar | AV45: Encontrar | AW45: Patronar | AX45: Determinar | AY45: Ofrecer
P46: Ordenar | Q46: Medir | W46: Ordenar | X46: Medir | Y46: Cortar | AA46: Realizar | AB46: Diseñar | AP46: Valorar | AU46: Relacionar | AV46: Encuestar | AW46: Planear | AX46: Discernir | AY46: Participar
P47: Organizar | Q47: Modificar | W47: Organizar | X47: Modificar | Y47: Recortar | AA47: Hacer | AB47: Sincronizar | AU47: Relatar | AV47: Esquematizar | AW47: Practicar | AX47: Discriminar | AY47: Percibir
P48: Organizar | Q48: Numerar | W48: Organizar | X48: Numerar | Y48: Bailar | AA48: Ejecutar | AB48: Verificar | AU48: Reportar | AV48: Establecer | AW48: Recoger | AX48: Distinguir | AY48: Preguntar
P49: Perfeccionar | Q49: Peritar | W49: Perfeccionar | X49: Peritar | Y49: Demostrar | AA49: Cumplir | AB49: Validar | AU49: Resumir | AV49: Estimar | AW49: Relacionar | AX49: Ejercer | AY49: Promover
P50: Planear | Q50: Predecir | W50: Planear | X50: Predecir | Y50: Detectar | AA50: Actuar | AB50: Revisar | AU50: Revisar | AV50: Estructurar | AW50: Reportar | AX50: Elegir | AY50: Proponer
P51: Planificar | Q51: Pronosticar | W51: Planificar | X51: Pronosticar | Y51: Señalar | AA51: Ejercer | AB51: Probar | AU51: Seleccionar | AV51: Evaluar | AW51: Resolver | AX51: Ensamblar | AY51: Proporcionar
P52: Poner | Q52: Recomendar | W52: Poner | X52: Recomendar | Y52: Probar | AA52: Interpretar | AB52: Difundir | AU52: Separar | AV52: Examinar | AW52: Resumir | AX52: Entregar | AY52: Provocar
P53: Predecir | Q53: Repartir | W53: Predecir | X53: Repartir | AA53: Tocar | AB53: Transmitir | AU53: Traducir | AV53: Experimentar | AW53: Seleccionar | AX53: Escoger | AY53: Reconocer
P54: Preparar | Q54: Resolver | W54: Preparar | X54: Resolver | AA54: Representar | AB54: Resolver | AU54: Transformar | AV54: Ilustrar | AW54: Simular | AX54: Estimar | AY54: Relacionar
P55: Producir | Q55: Reunir | W55: Producir | X55: Reunir | AA55: Practicar | AB55: Tapizar | AU55: Ubicar | AV55: Indicar | AW55: Transferir | AX55: Estimular | AY55: Resumir
P56: Proponer | Q56: Revisar | W56: Proponer | X56: Revisar | AA56: Entrenar | AB56: Usar | AV56: Inferir | AW56: Unir | AX56: Exteriorizar | AY56: Seleccionar
P57: Proyectar | Q57: Seleccionar | W57: Proyectar | X57: Seleccionar | AA57: Grabar | AB57: Emplear | AV57: Inspeccionar | AW57: Usar | AX57: Extraer | AY57: Ser partidario de
P58: Resolver | Q58: Sistematizar | W58: Resolver | X58: Sistematizar | AA58: Sacar | AB58: Utilizar | AV58: Interpretar | AX58: Fomentar | AY58: Unir
P59: Reunir | Q59: Sugerir | W59: Reunir | X59: Sugerir | AA59: Imprimir | AB59: Ponderar | AV59: Inventariar | AX59: Formular | AY59: Valorar
P60: Señalar | Q60: Tasar | W60: Señalar | X60: Tasar | AA60: Estampar | AB60: Mecanizar | AV60: Investigar | AX60: Identificar
P61: Simplificar | Q61: Terminar | W61: Simplificar | X61: Terminar | AA61: Extraer | AB61: Industrializar | AV61: Listar | AX61: Juzgar
P62: Subdividir | Q62: Unir | W62: Subdividir | X62: Unir | AA62: Producir | AB62: Codificar | AV62: Manipular | AX62: Negociar
P63: Suponer | Q63: Validar | W63: Suponer | X63: Validar | AA63: Fabricar | AV63: Medir | AX63: Ofrecer
Q64: Valorar | X64: Valorar | AA64: Presentar | AV64: Modelar | AX64: Participar
Q65: Verificar | X65: Verificar | AA65: Cortar | AV65: Motivar | AX65: Percibir
Q66: Vincular | X66: Vincular | AA66: Reducir | AV66: Observar | AX66: Preguntar
AA67: Mitigar | AV67: Operar | AX67: Preocuparse de o por
AA68: Emitir | AV68: Ordenar | AX68: Promover
AV69: Organizar | AX69: Proponer
AV70: Patronar | AX70: Proporcionar
AV71: Planear | AX71: Proteger
AV72: Practicar | AX72: Provocar
AV73: Preguntar | AX73: Ratificar
AV74: Priorizar | AX74: Reconocer
AV75: Probar | AX75: Relacionar
AV76: Razonar | AX76: Relatar
AV77: Recoger | AX77: Resumir
AV78: Reconocer | AX78: Revelar
AV79: Relacionar | AX79: Seleccionar
AV80: Reorganizar | AX80: Ser partidario de
... AV87: Transferir | AX87: Verificar
AV88: Usar
