Workbook
Name ActitudinalBAK: 'Taxonomias para RA'!$AC$3:$AG$3
Name Bloom: 'Taxonomias para RA'!$G$3:$I$3
Name Circutos: 'Paso 2 Redacción competen'!$F$4
Name CognitivoBAK: 'Taxonomias para RA'!$S$3:$X$3
Name CompetenciaEspecifica1: 'Paso 2 Redacción competen'!$F$4
Name competencias: #REF!
Name ComponentesCompetencias: 'Paso1 Analisis perfil egreso'!$E$2:$G$2
Name Conocimientos: #REF!
Name FACULTADES: #REF!
Name ProcedimentalBAK: 'Taxonomias para RA'!$Y$3:$AB$3
Name RA: 'Paso 5 Estrategias micro'!$B$8
Name resultadoaprendizaje: '[2]Paso 3 Redacción RA '!$I$2:$I$21
Name Saber: 'Paso1 Analisis perfil egreso'!$E$3:$E$6
Name SaberHacer: 'Paso1 Analisis perfil egreso'!$F$3:$F$6
Name SaberSer: 'Paso1 Analisis perfil egreso'!$G$3:$G$6
Name taxonomiasra: [3]!Tabla1715[Taxonomías]
Name TIC: 'Paso 2 Redacción competen'!$F$7

Sheet Paso1 Analisis perfil egreso
A1: [Escribir el nombre del programa] | B1: [Escribir la modalidad: presencial o virtual] | C1: [Escribir el perfil profesional del egresado.] | D1: [Escribir el perfil ocupacional del egresado.] | E1: Componentes fundamentales aplicables a la solución de problemas en la vida profesional [Listar, según lo escrito en el perfil profesional, qué debe saber el egresado en las categorías de Saber -conocimientos, hechos, teorías-, Saber hacer -técnicas, procedimientos, metodologías-, y Saber ser -valores, condiciones, etc.] | H1: Componentes fundamentales de la ocupación laboral del profesional [Listar, según lo escrito en el perfil ocupacional, en qué áreas, qué tareas potenciales y en qué poblaciones o contextos podrá laborar el profesional.] | K1: Diferencial (valor agregado) del profesional [Listar, según lo escrito en los perfiles, los elementos que son diferenciales y generan un valor agregado al egresado.]
A2: Programa | B2: Modalidad | C2: Perfil profesional | D2: Perfil ocupacional | E2: Saber | F2: SaberHacer | G2: SaberSer | H2: Áreas profesionales | I2: Tareas profesionales | J2: Poblaciones actuación | K2: Valor agregado
A3: Administración de Empresas | B3: Presencial | C3: El profesional en Administración de Empresas del Politécnico Grancolombiano formula y ejecuta estrategias organizacionales innovadoras, integrando conocimientos en gestión organizacional con metodologías de análisis de información. Su formación integral le permite tomar decisiones informadas en contextos cambiantes, liderar proyectos empresariales, y promover modelos de negocio sostenibles, aportando a la generación de valor organizacional. Se caracteriza por su pensamiento crítico y compromiso con el desarrollo organizacional, según las dinámicas del entorno y el marco legal vigente. | D3: El administrador de empresas del Politécnico Grancolombiano está capacitado para desarrollar estrategias corporativas alineadas con la dinámica del entorno y la competitividad empresarial. Su formación le permite gestionar áreas funcionales clave con visión sostenible y criterio estratégico, dirigir equipos de trabajo según las tendencias organizacionales, implementar planes estratégicos, tácticos y operativos, y administrar sistemas de gestión empresarial. Además, cuenta con las competencias necesarias para identificar oportunidades de negocio y convertirlas en iniciativas productivas que generen valor en distintos sectores económicos. | E3: Principios económicos y sociales, y normatividad empresarial | F3: tomar decisiones informadas | G3: considerando tanto criterios de sostenibilidad como la legislación vigente en contextos organizacionales y empresariales. | H3: Gerencia administrativa. Gestión empresarial. Gestión de proyectos. Análisis estratégico. Consultoría empresarial. | I3: Coordinar o liderar áreas de empresas, así como proyectos empresariales. Estructurar e implementar planes estratégicos, tácticos y operativos. Desarrollar proyectos empresariales. Realizar consultoría en el campo de la gestión empresarial. Emprender iniciativas empresariales emergentes. Gerenciar y administrar cualquier tipo de empresa, especialmente medianas o pequeñas. Gerenciar proyectos de cualquier tipo de organización. | J3: Empresas privadas o de economía mixta, existentes o emergentes, de cualquier sector de la economía. StarUps. Organizaciones no gubernamentales. Sector público. Ecosistemas de innovación y emprendimiento. | K3: El programa de Administración de Empresas del Politécnico Grancolombiano ofrece un enfoque distintivo en estrategia empresarial, articulando análisis, planeación y ejecución con el uso de herramientas para la toma de decisiones y la creación de valor sostenible. Forma profesionales capaces de liderar procesos de transformación en organizaciones que enfrentan entornos cambiantes, con visión económica, social y ambiental
E4: Planeación estratégica y gestión de procesos | F4: desarrollar estrategias empresariales | G4: contribuyendo a la generación de valor dentro entornos organizacionales cambiantes.
E5: Habilidades poderosas o socioemocionales | F5: liderar equipos y procesos con enfoque humano | G5: orientados a la adapatación y al desarrollo organizacional, según las dinámicas del entorno.
E6: Modelos de negocio | F6: impulsar iniciativas o proyectos de emprendimiento | G6: teniendo en cuenta las necesidades económicas, ambientales y sociales del entorno.
E7: Fenómenos contemporáneos | F7: reconocer sus afectaciones o contribuciones en el marco de las ciudadanías globales y de una sociedad responsable y sostenible. | G7: desde una perspectiva global, soportada en datos, con una mirada ética y crítica.

Sheet Paso 2 Redacción competen
A1: Elementos para redactar las competencias que desarrollará el programa
A2: [Enumerar las competencias que se van a declarar.] | B2: [A partir de la celda B2 dar clic sobre el ícono de lista desplegable y elegir el verbo que considere adecuado.] | C2: [A partir de la celda C2 dar clic sobre la lista desplegable y elegir el saber extraído del perfil de egreso.] | D2: [Escribir para qué se abordará el saber elegido. Se sugiere apoyarse en el saber hacer.] | E2: [Escribir la condición describiendo los referentes, parámetros, principios, requerimientos o retos que se necesitan para alcanzar las características del perfil en el contexto donde el egresado se desenvolverá.] | F2: [Articular los componentes. Iniciar con el verbo, continuar con el objeto conceptual, luego la finalidad y condición de contexto o referencia; estos últimos no requieren un orden particular.] | G2: [Escribir el tipo de competencia del perfil: Específica (si es del bloque Disciplinar para pregrado o de los componentes para el caso de posgrado) o Genérica (si aplica bloque institucional pregrado)]
A3: No. | B3: Verbo competencia | C3: Objeto conceptual | D3: Finalidad | E3: Condición de contexto o referencia | F3: Redacción competencia | G3: Tipo de competencia
A4: 1 | B4: Analizar | C4: Principios económicos y sociales, y normatividad empresarial | D4: tomar decisiones informadas | E4: considerando tanto criterios de sostenibilidad como la legislación vigente en contextos organizacionales y empresariales. | F4: Analizar los principios económicos y sociales, así como la normatividad empresarial, para tomar decisiones informadas, considerando tanto criterios de sostenibilidad como la legislación vigente en contextos organizacionales y empresariales. | G4: Específica
A5: 2 | B5: Gestionar | C5: Planeación estratégica y procesos funcionales | D5: desarrollar estrategias empresariales | E5: contribuyendo a la generación de valor dentro entornos organizacionales cambiantes. | F5: Gestiona procesos funcionales y de planeación estratégica para desarrollar estrategias empresariales, contribuyendo a la generación de valor dentro entornos organizacionales cambiantes. | G5: Específica
A6: 3 | B6: Aplicar | C6: Habilidades poderosas o socioemocionales | D6: liderar equipos y procesos con enfoque humano | E6: orientados a la adapatación y al desarrollo organizacional, según las dinámicas del entorno. | F6: Aplicar habilidades poderosas o socioemocionales para liderar equipos y procesos con enfoque humano, orientados a la adapatación y al desarrollo organizacional, según las dinámicas del entorno. | G6: Específica
A7: 4 | B7: Desarrollar | C7: Modelos de negocio | D7: impulsar iniciativas o proyectos de emprendimiento | E7: teniendo en cuenta las necesidades económicas, ambientales y sociales del entorno. | F7: Desarrolla modelos de negocio para impulsar iniciativas o proyectos de emprendimiento teniendo en cuenta las necesidades económicas, ambientales y sociales del entorno. | G7: Específica
A8: 5 | B8: Analizar | C8: Fenómenos contemporáneos | D8: reconocer sus afectaciones o contribuciones en el marco de las ciudadanías globales y de una sociedad responsable y sostenible. | E8: desde una perspectiva global, soportada en datos, con una mirada ética y crítica | F8: Analizar los fenómenos contemporáneos desde una perspectiva glocal, soportada en datos, con una mirada ética y crítica, para reconocer sus afectaciones o contribuciones en el marco de las ciudadanías globales y de una sociedad responsable y sostenible. | G8: Genérica

Sheet Paso 3 Redacción RA
A1: [A partir de la celda A2 dar clic en la lista desplegable y seleccionar la competencia redactada en el paso 2.] | B1: [Enumerar los resultados de aprendizaje que se van a declarar.] | C1: [A partir de la celda C2, dar clic en la lista desplegable y elegir el tipo de dominio a tratar en el resultado de aprendizaje.] | D1: [A partir de la cela D2, dar clic en la lista desplegable y elegir el saber correspondiente al dominio.] | E1: [A partir de la celda E2, dar clic en la lista desplegable y elegir la taxonomía que se considere adecuada, solo se elige una para todos los saberes.] | F1: [A partir de la celda F2, dar clic en la lista desplegable y elegir el dominio que se considera adecuado.] | G1: [A partir de la celda G2, dar clic en la lista desplegable y elegir el nivel del dominio que se considera adecuado.] | H1: [A partir de la celda H2, dar clic en la lista desplegable y elegir el verbo que se considera adecuado.] | I1: [Iniciar con el verbo elegido (columna H), en infinitivo, luego el objeto sobre el cual recae la acción (columna D) y finalmente la condición de contexto (académico, disciplinar, social u otro).]
A2: Competencia por desarrollar | B2: Número de resultado | C2: TipoSaber | D2: SaberAsociado | E2: Taxonomía | F2: Dominio Asociado | G2: Nivel Dominio | H2: Verbo RA | I2: Resultados Aprendizaje
A3: Analizar los principios económicos y sociales, así como la normatividad empresarial, para tomar decisiones informadas, considerando tanto criterios de sostenibilidad como la legislación vigente en contextos organizacionales y empresariales. | B3: 1 | C3: Saber | D3: Principios económicos y sociales, y normatividad empresarial | E3: BAK | F3: CognitivoBAK | G3: AnálisisBAK | H3: Analizar | I3: Analiza los principios económicos y sociales, así como la normatividad empresarial para determinar rutas estratégicas de acción y procesos asociados a la gestión, según el funcionamiento de los entornos internos y externos que operan en los contextos organizacionales.
A4: Analizar los principios económicos y sociales, así como la normatividad empresarial, para tomar decisiones informadas, considerando tanto criterios de sostenibilidad como la legislación vigente en contextos organizacionales y empresariales. | B4: 3 | C4: SaberHacer | D4: tomar decisiones informadas | E4: BAK | F4: ProcedimentalBAK | G4: ControlBAK | H4: Ejecutar | I4: Ejecuta acciones de gestión de equipos y procesos, para tomar decisiones informadas que promuevan el liderazgo colaborativo en escenarios organizacionales.
A5: Analizar los principios económicos y sociales, así como la normatividad empresarial, para tomar decisiones informadas, considerando tanto criterios de sostenibilidad como la legislación vigente en contextos organizacionales y empresariales. | B5: 4 | C5: SaberSer | D5: considerando tanto criterios de sostenibilidad como la legislación vigente en contextos organizacionales y empresariales. | E5: BAK | F5: ActitudinalBAK | G5: ValorarBAK | H5: Integrar | I5: Integra criterios económicos, sociales y jurídicos que apoyen la toma de decisiones, para contribuir a la generación de valor y al desarrollo organizacional, considerando principios de sostenibilidad, así como las dinámicas y necesidades del entorno.
A6: Gestiona procesos funcionales y de planeación estratégica para desarrollar estrategias empresariales, contribuyendo a la generación de valor dentro entornos organizacionales cambiantes. | B6: 1 | C6: Saber | D6: Planeación estratégica y gestión de procesos | E6: BAK | F6: CognitivoBAK | G6: AnálisisBAK | H6: Analizar | I6: Analiza los principios económicos y sociales, así como la normatividad empresarial para determinar rutas estratégicas de acción y procesos asociados a la gestión, según el funcionamiento de los entornos internos y externos que operan en los contextos organizacionales.
A7: Gestiona procesos funcionales y de planeación estratégica para desarrollar estrategias empresariales, contribuyendo a la generación de valor dentro entornos organizacionales cambiantes. | B7: 5 | C7: SaberHacer | D7: desarrollar estrategias empresariales | E7: BAK | F7: ProcedimentalBAK | G7: ControlBAK | H7: Diseñar | I7: Diseña estrategias empresariales para estructurar propuestas de mejora orientadas al fortalecimiento de la competitividad empresarial y al desarrollo de iniciativas de emprendimiento e intraemprendimiento.
A8: Gestiona procesos funcionales y de planeación estratégica para desarrollar estrategias empresariales, contribuyendo a la generación de valor dentro entornos organizacionales cambiantes. | B8: 4 | C8: SaberSer | D8: contribuyendo a la generación de valor dentro entornos organizacionales cambiantes. | E8: BAK | F8: ActitudinalBAK | G8: ValorarBAK | H8: Integrar | I8: Integra criterios económicos, sociales y jurídicos que apoyen la toma de decisiones, para contribuir a la generación de valor y al desarrollo organizacional, considerando principios de sostenibilidad, así como las dinámicas y necesidades del entorno.
A9: Aplicar habilidades poderosas o socioemocionales para liderar equipos y procesos con enfoque humano, orientados a la adapatación y al desarrollo organizacional, según las dinámicas del entorno. | B9: 6 | C9: Saber | D9: Habilidades poderosas o socioemocionales | E9: BAK | F9: CognitivoBAK | G9: AnálisisBAK | H9: Reconocer | I9: Reconoce las habilidades poderosas o socioemocionales que intervienen en escenarios organizacionales y en las relaciones humanas, para determinar aquellas que son pertinentes en el abordaje de situaciones propias de los distintos ámbitos de la gestión empresarial.
A10: Aplicar habilidades poderosas o socioemocionales para liderar equipos y procesos con enfoque humano, orientados a la adapatación y al desarrollo organizacional, según las dinámicas del entorno. | B10: 3 | C10: SaberHacer | D10: liderar equipos y procesos con enfoque humano | E10: BAK | F10: ProcedimentalBAK | G10: ControlBAK | H10: Ejecutar | I10: Ejecuta acciones de gestión de equipos y procesos, para tomar decisiones informadas que promuevan el liderazgo colaborativo en escenarios organizacionales.
A11: Aplicar habilidades poderosas o socioemocionales para liderar equipos y procesos con enfoque humano, orientados a la adapatación y al desarrollo organizacional, según las dinámicas del entorno. | B11: 4 | C11: SaberSer | D11: orientados a la adapatación y al desarrollo organizacional, según las dinámicas del entorno. | E11: BAK | F11: ActitudinalBAK | G11: ValorarBAK | H11: Integrar | I11: Integra criterios económicos, sociales y jurídicos que apoyen la toma de decisiones, para contribuir a la generación de valor y al desarrollo organizacional, considerando principios de sostenibilidad, así como las dinámicas y necesidades del entorno.
A12: Desarrolla modelos de negocio para impulsar iniciativas o proyectos de emprendimiento teniendo en cuenta las necesidades económicas, ambientales y sociales del entorno. | B12: 7 | C12: Saber | D12: Modelos de negocio | E12: BAK | F12: CognitivoBAK | G12: AnálisisBAK | H12: Reconocer | I12: Reconoce distintos modelos de negocio y de innovación aplicables tanto a intraemprendimientos como a nuevos negocios, para seleccionar el más adecuado en el diseño de propuestas empresariales sostenibles y coherentes con el entorno.
A13: Desarrolla modelos de negocio para impulsar iniciativas o proyectos de emprendimiento teniendo en cuenta las necesidades económicas, ambientales y sociales del entorno. | B13: 5 | C13: SaberHacer | D13: impulsar iniciativas o proyectos de emprendimiento | E13: BAK | F13: ProcedimentalBAK | G13: ControlBAK | H13: Diseñar | I13: Diseña estrategias empresariales para estructurar propuestas de mejora orientadas al fortalecimiento de la competitividad empresarial y al desarrollo de iniciativas de emprendimiento e intraemprendimiento.
A14: Desarrolla modelos de negocio para impulsar iniciativas o proyectos de emprendimiento teniendo en cuenta las necesidades económicas, ambientales y sociales del entorno. | B14: 4 | C14: SaberSer | D14: teniendo en cuenta las necesidades económicas, ambientales y sociales del entorno. | E14: BAK | F14: ActitudinalBAK | G14: ValorarBAK | H14: Integrar | I14: Integra criterios económicos, sociales y jurídicos que apoyen la toma de decisiones, para contribuir a la generación de valor y al desarrollo organizacional, considerando principios de sostenibilidad, así como las dinámicas y necesidades del entorno.
A15: Analizar los fenómenos contemporáneos desde una perspectiva glocal, soportada en datos, con una mirada ética y crítica, para reconocer sus afectaciones o contribuciones en el marco de las ciudadanías globales y de una sociedad responsable y sostenible. | B15: 2 | C15: Saber | D15: Fenómenos contemporáneos | E15: Bloom | F15: CognitivoB | G15: ComprensiónB | H15: Identificar | I15: Identifica fenómenos contemporáneos y su relación con la profesión, para determinar sus impactos e influencia en la sociedad, de forma responsable y crítica.

Sheet Paso 3 Redacción RA - Backup 
A1: [A partir de la celda A2 dar clic en la lista desplegable y seleccionar la competencia redactada en el paso 2.] | B1: [Enumerar los resultados de aprendizaje que se van a declarar.] | C1: [A partir de la celda C2, dar clic en la lista desplegable y elegir el tipo de dominio a tratar en el resultado de aprendizaje.] | D1: [A partir de la cela D2, dar clic en la lista desplegable y elegir el saber correspondiente al dominio.] | E1: [A partir de la celda E2, dar clic en la lista desplegable y elegir la taxonomía que se considere adecuada, solo se elige una para todos los saberes.] | F1: [A partir de la celda F2, dar clic en la lista desplegable y elegir el dominio que se considera adecuado.] | G1: [A partir de la celda G2, dar clic en la lista desplegable y elegir el nivel del dominio que se considera adecuado.] | H1: [A partir de la celda H2, dar clic en la lista desplegable y elegir el verbo que se considera adecuado.] | I1: [Iniciar con el verbo elegido (columna H), en infinitivo, luego el objeto sobre el cual recae la acción (columna D) y finalmente la condición de contexto (académico, disciplinar, social u otro).]
A2: Competencia por desarrollar | B2: Número de resultado | C2: TipoSaber | D2: SaberAsociado | E2: Taxonomía | F2: Dominio Asociado | G2: Nivel Dominio | H2: Verbo RA | I2: Resultados Aprendizaje
A3: Dominar los elementos de teoría de circuitos y transmisión de información para diseñar, implementar o administrar la infraestructura eléctrica y los dispositivos electrónicos que dan soporte a los sistemas de telecomunicaciones alineado con prácticas basadas en estándares del sector y la normatividad vigente, teniendo en cuenta las condiciones, restricciones y requerimientos técnicos del entorno. | B3: 1 | C3: Saber | D3: los elementos de teoría de circuitos y transmisión de información | E3: BAK | F3: CognitivoBAK | G3: ComprensiónBAK | H3: Identificar | I3: Identifica los elementos de teoría de circuitos, de transmisión de información, de seguridad de la información, de redes de comunicaciones, de sistemas de cómputo, de estandares y marcos de referencia que hacen parte de la gestión de proyectos como del desarrollo de actividades relacionadas a las infraestructuras de TIC, para explicar soluciones de diseño, administración o implementación a problemáticas del sector, desde un abordaje teórico-práctico, a través de herramientas de simulación, análisis de casos prácticos y uso de equipos de laboratorio.
A4: Dominar los elementos de teoría de circuitos y transmisión de información para diseñar, implementar o administrar la infraestructura eléctrica y los dispositivos electrónicos que dan soporte a los sistemas de telecomunicaciones alineado con prácticas basadas en estándares del sector y la normatividad vigente, teniendo en cuenta las condiciones, restricciones y requerimientos técnicos del entorno. | B4: 4 | C4: SaberHacer | D4: para diseñar, implementar o administrar la infraestructura eléctrica y los dispositivos electrónicos que dan soporte a los sistemas de telecomunicaciones | E4: BAK | F4: ProcedimentalBAK | G4: ManipulaciónBAK | H4: Aplicar | I4: Aplica los elementos de teoría de circuitos, de transmisión de información, de seguridad de la información, de redes de comunicaciones, de sistemas de cómputo, de estandares tecnológicos y marcos de referencia que hacen parte de la gestión de proyectos como del desarrollo de actividades relacionadas a las infraestructuras de TIC, para construir propuestas de diseño, implementación o administración de infraestructura eléctrica, dispositivos electrónicos, servicios de comunicaciones en nube o en sitio, sistemas de telecomunicaciones, a través de herramientas de simulación, análisis de casos prácticos y uso de equipos de laboratorio.
A5: Dominar los elementos de teoría de circuitos y transmisión de información para diseñar, implementar o administrar la infraestructura eléctrica y los dispositivos electrónicos que dan soporte a los sistemas de telecomunicaciones alineado con prácticas basadas en estándares del sector y la normatividad vigente, teniendo en cuenta las condiciones, restricciones y requerimientos técnicos del entorno. | B5: 7 | C5: SaberSer | D5: alineado con prácticas basadas en estándares del sector y la normatividad vigente, teniendo en cuenta las condiciones, restricciones y requerimientos técnicos del entorno. | E5: BAK | F5: ActitudinalBAK | G5: ValorarBAK | H5: Emplear | I5: Emplea las buenas prácticas de teoría de circuitos y transmisión, y de seguridad de la información, redes y sistemas de cómputo basadas en estándares del sector y la normatividad vigente, teniendo en cuenta las condiciones, restricciones y requerimientos técnicos de un proyecto, para formular soluciones en infraestructuras TIC o del área de las telecomunicaciones.
A6: Dominar los elementos de seguridad de la información, redes de comunicaciones y sistemas de cómputo que hacen parte de infraestructuras TIC para diseñar, implementar o administrar infraestructuras y servicios de comunicaciones en sitio o en nube alineado con prácticas basadas en estándares del sector y la normatividad vigente, teniendo en cuenta las condiciones, restricciones y requerimientos técnicos del entorno. | B6: 1 | C6: Saber | D6: los elementos de seguridad de la información, redes de comunicaciones y sistemas de cómputo que hacen parte de infraestructuras TIC | E6: BAK | F6: CognitivoBAK | G6: ComprensiónBAK | H6: Identificar | I6: Identifica los elementos de teoría de circuitos, de transmisión de información, de seguridad de la información, de redes de comunicaciones, de sistemas de cómputo, de estandares y marcos de referencia que hacen parte de la gestión de proyectos como del desarrollo de actividades relacionadas a las infraestructuras de TIC, para evaluar soluciones a problemáticas del sector, desde un abordaje teórico-práctico, a través de herramientas de simulación, análisis de casos prácticos y uso de equipos de laboratorio.
A7: Dominar los elementos de seguridad de la información, redes de comunicaciones y sistemas de cómputo que hacen parte de infraestructuras TIC para diseñar, implementar o administrar infraestructuras y servicios de comunicaciones en sitio o en nube alineado con prácticas basadas en estándares del sector y la normatividad vigente, teniendo en cuenta las condiciones, restricciones y requerimientos técnicos del entorno. | B7: 5 | C7: SaberHacer | D7: para diseñar, implementar o administrar infraestructuras y servicios de comunicaciones en sitio o en nube | E7: BAK | F7: ProcedimentalBAK | G7: ManipulaciónBAK | H7: Aplicar | I7: Aplica los elementos de teoría de circuitos, de transmisión de información, de seguridad de la información, de redes de comunicaciones, de sistemas de cómputo, de estandares tecnológicos y marcos de referencia que hacen parte de la gestión de proyectos como del desarrollo de actividades relacionadas a las infraestructuras de TIC, para construir propuestas de diseño, implementación o administración de infraestructura eléctrica, dispositivos electrónicos, servicios de comunicaciones en nube o en sitio, sistemas de telecomunicaciones, a través de herramientas de simulación, análisis de casos prácticos y uso de equipos de laboratorio.
A8: Dominar los elementos de seguridad de la información, redes de comunicaciones y sistemas de cómputo que hacen parte de infraestructuras TIC para diseñar, implementar o administrar infraestructuras y servicios de comunicaciones en sitio o en nube alineado con prácticas basadas en estándares del sector y la normatividad vigente, teniendo en cuenta las condiciones, restricciones y requerimientos técnicos del entorno. | B8: 7 | C8: SaberSer | D8: alineado con prácticas basadas en estándares del sector y la normatividad vigente, teniendo en cuenta las condiciones, restricciones y requerimientos técnicos del entorno. | E8: BAK | F8: ActitudinalBAK | G8: ValorarBAK | H8: Emplear | I8: Emplea las buenas prácticas de teoría de circuitos y transmisión, y de seguridad de la información, redes y sistemas de cómputo basadas en estándares del sector y la normatividad vigente, teniendo en cuenta las condiciones, restricciones y requerimientos técnicos de un proyecto, para formular soluciones en infraestructuras TIC o del área de las telecomunicaciones.
A9: Conocer los estándares y marcos de referencia asociados tanto a la gestión de proyectos como al desarrollo de actividades relacionadas a las tecnologías de la información para diseñar, implementar o administrar soluciones del área de las telecomunicaciones, la seguridad de la información y la infraestructura TIC manteniendo una postura socialmente responsable, autónoma, teniendo en cuenta las condiciones, restricciones y requerimientos técnicos del entorno. | B9: 2 | C9: Saber | D9: los estándares y marcos de referencia asociados tanto a la gestión de proyectos como al desarrollo de actividades relacionadas a las tecnologías de la información | E9: BAK | F9: CognitivoBAK | G9: ComprensiónBAK | H9: Identificar | I9: Identifica los elementos de teoría de circuitos, de transmisión de información, de seguridad de la información, de redes de comunicaciones, de sistemas de cómputo, de estandares y marcos de referencia que hacen parte de la gestión de proyectos como del desarrollo de actividades relacionadas a las infraestructuras de TIC, para evaluar soluciones a problemáticas del sector, desde un abordaje teórico-práctico, a través de herramientas de simulación, análisis de casos prácticos y uso de equipos de laboratorio.
A10: Conocer los estándares y marcos de referencia asociados tanto a la gestión de proyectos como al desarrollo de actividades relacionadas a las tecnologías de la información para diseñar, implementar o administrar soluciones del área de las telecomunicaciones, la seguridad de la información y la infraestructura TIC manteniendo una postura socialmente responsable, autónoma, teniendo en cuenta las condiciones, restricciones y requerimientos técnicos del entorno. | B10: 6 | C10: SaberHacer | D10: para diseñar, implementar o administrar soluciones del área de las telecomunicaciones, la seguridad de la información y la infraestructura TIC | E10: BAK | F10: ProcedimentalBAK | G10: ManipulaciónBAK | H10: Aplicar | I10: Aplica los elementos de teoría de circuitos, de transmisión de información, de seguridad de la información, de redes de comunicaciones, de sistemas de cómputo, de estandares tecnológicos y marcos de referencia que hacen parte de la gestión de proyectos como del desarrollo de actividades relacionadas a las infraestructuras de TIC, para construir propuestas de diseño, implementación o administración de infraestructura eléctrica, dispositivos electrónicos, servicios de comunicaciones en nube o en sitio, sistemas de telecomunicaciones, a través de herramientas de simulación, análisis de casos prácticos y uso de equipos de laboratorio.
A11: Conocer los estándares y marcos de referencia asociados tanto a la gestión de proyectos como al desarrollo de actividades relacionadas a las tecnologías de la información para diseñar, implementar o administrar soluciones del área de las telecomunicaciones, la seguridad de la información y la infraestructura TIC manteniendo una postura socialmente responsable, autónoma, teniendo en cuenta las condiciones, restricciones y requerimientos técnicos del entorno. | B11: 7 | C11: SaberSer | D11: manteniendo una postura socialmente responsable, autónoma, teniendo en cuenta las condiciones, restricciones y requerimientos técnicos del entorno. | E11: BAK | F11: ActitudinalBAK | G11: ValorarBAK | H11: Emplear | I11: Emplea las buenas prácticas de teoría de circuitos y transmisión, y de seguridad de la información, redes y sistemas de cómputo basadas en estándares del sector y la normatividad vigente, teniendo en cuenta las condiciones, restricciones y requerimientos técnicos de un proyecto, para formular soluciones en infraestructuras TIC o del área de las telecomunicaciones.
A12: Analizar los fenómenos contemporáneos desde una perspectiva glocal, soportada en datos, con una mirada ética y crítica, para reconocer sus afectaciones o contribuciones en el marco de las ciudadanías globales y de una sociedad responsable y sostenible. | B12: 3 | C12: Saber | D12: Fenómenos contemporáneos | E12: Bloom | F12: CognitivoB | G12: ComprensiónB | H12: Identificar | I12: Identifica fenómenos contemporáneos y su relación con la profesión, para determinar sus impactos e influencia en la sociedad, de forma responsable y crítica.

Sheet Paso 4 Estrategias mesocurricu
A1: [A partir de la celda A3 despliegue el(los) resultado(s) de aprendizaje y elegir aquel (aquellos) al(a los) que se contribuye desde la estrategia.] | B1: [Escribir el nombre de la estrategia a desarrollar. Participación de los estudiantes en cursos, talleres, seminarios, conferencias, pruebas estandarizadas, investigaciones, actividades o experiencias, cuerpos académicos, redes, comunidades, la elaboración de textos y materiales, así como las publicaciones, entre otros.] | C1: [Describir la(s) estrategia(s) definidas por el programa.] | D1: [Escribir los indicadores de impacto de la estrategia. Se sugieren indicadores como: Valora el nivel de contribución de la estrategia a los resultados de aprendizaje; Número de estudiantes que participan en la estrategia; Número de veces que se realiza la estrategia, entre otros.] | E1: [Escribir las acciones de retroalimentación que usará el programa para comunicar a los estudiantes sobre el alcance de sus resultados de aprendizaje.] | F1: [Escribir, para cada indicador con qué instrumento se recogerá información para evidenciar el (los) impacto (s) declarados. Encuesta, lista de asistencia, informe, entre otros.]
A2: Resultado de aprendizaje | B2: Estrategia del programa | C2: Descripción | D2: Indicador de Impacto de la Estrategia | E2: Acciones de retroalimentación para los estudiantes | F2: Instrumentos de medición
A3: Analiza los principios económicos y sociales, así como la normatividad empresarial para determinar rutas estratégicas de acción y procesos asociados a la gestión, según el funcionamiento de los entornos internos y externos que operan en los contextos organizacionales. | B3: Prueba estandandarizada (simulacro Pruebas Saber Pro) | C3: El proyecto ser pro es un proyecto en el cual la escuela de administracion y competitividad realiza actividades en cuatro frentes. El primero es la capacitacion de docentes en la elaboracion de preguntas por competencias, el segundo es la elaboracion de simulacros de presentacion de pruebas saber pro, en especial en el componente especifico de nucleo básico del conocimiento, el tercero son los talleres de refuerzo para que los estudiantes mejoren sus competencias en la presentacion de las pruebas de estado y por ultimo, en el cuarto frente se encuentra el desarrollo de concursos institucionales e interinstitucionales sustentados en la metodologia de preguntas saber pro. | D3: Número de veces que se realiza la estrategia por periodo académico. | E3: Informar sobre el desempeño alcanzado en los simulacros, destacando avances y brechas frente al promedio del programa. Formar en el uso de estrategias para resolver preguntas por competencias, enfocadas en los componentes de menor desempeño. | F3: Informe o Reporte.
A4: Integra criterios económicos, sociales y jurídicos que apoyen la toma de decisiones, para contribuir a la generación de valor y al desarrollo organizacional, considerando principios de sostenibilidad, así como las dinámicas y necesidades del entorno. | D4: Número de estudiantes que participan en la estrategia por periodo académico. | F4: Listados de participación.
A5: Reconoce las habilidades poderosas o socioemocionales que intervienen en escenarios organizacionales y en las relaciones humanas, para determinar aquellas que son pertinentes en el abordaje de situaciones propias de los distintos ámbitos de la gestión empresarial. | D5: Valoración del nivel de aporte de la estrategia a los resultados de aprendizaje del programa. | F5: Encuesta de valoración.
A6: Reconoce distintos modelos de negocio y de innovación aplicables tanto a intraemprendimientos como a nuevos negocios, para seleccionar el más adecuado en el diseño de propuestas empresariales sostenibles y coherentes con el entorno.
A7: Analiza los principios económicos y sociales, así como la normatividad empresarial para determinar rutas estratégicas de acción y procesos asociados a la gestión, según el funcionamiento de los entornos internos y externos que operan en los contextos organizacionales. | B7: Consultoría a empresas | C7: El proceso de consultoría estratégica inicia con la búsqueda de empresa por parte del estudiante, para esta empresa se genera un contrato de consultoría a costo cero y al final del proceso a la empresa se le entrega una propuesta estratégica, que se sugiere sea implementada en los años posteriores en la compañía. El proceso termina cuando la empresa entrega a la institución una carta de recibido a conformidad del plan estratégico propuesto. | D7: Número de estudiantes que participan en la estrategia por periodo académico. | E7: Formar en la aplicación rigurosa de herramientas diagnósticas y en la formulación de propuestas alineadas con las necesidades reales de la empresa. Ayudar a tomar decisiones sobre las estrategias que pueden ser priorizadas según el contexto empresarial identificado. | F7: Listados de participación.
A8: Ejecuta acciones de gestión de equipos y procesos, para tomar decisiones informadas que promuevan el liderazgo colaborativo en escenarios organizacionales. | D8: Número de veces que se realiza la estrategia por periodo académico. | F8: Informe o Reporte.
A9: Integra criterios económicos, sociales y jurídicos que apoyen la toma de decisiones, para contribuir a la generación de valor y al desarrollo organizacional, considerando principios de sostenibilidad, así como las dinámicas y necesidades del entorno. | D9: Valoración del nivel de aporte de la estrategia a los resultados de aprendizaje del programa. | F9: Encuesta de valoración.
A10: Diseña estrategias empresariales para estructurar propuestas de mejora orientadas al fortalecimiento de la competitividad empresarial y al desarrollo de iniciativas de emprendimiento e intraemprendimiento.
A11: Ejecuta acciones de gestión de equipos y procesos, para tomar decisiones informadas que promuevan el liderazgo colaborativo en escenarios organizacionales.
A12: Analiza los principios económicos y sociales, así como la normatividad empresarial para determinar rutas estratégicas de acción y procesos asociados a la gestión, según el funcionamiento de los entornos internos y externos que operan en los contextos organizacionales. | B12: Diagnóstico de habilidades gerenciales | C12: El desarrollo de habilidades gerenciales en los estudiantes del programa es fundamental, para ello desde el centro de liderazgo 360, este se aborda desde las ópticas del liderazgo personal, liderazgo organizacional y liderazgo social. En este sentido, los estudiantes desarrollan actividades y talleres que complementan las labores académicas del programa. | D12: Número de estudiantes que participan en la estrategia. | E12: Informar sobre el nivel de desarrollo de habilidades blandas evidenciado en las actividades realizadas. Formar en la identificación de estilos de liderazgo y su aplicación práctica según situaciones organizacionales. | F12: Listados de participación.
A13: Ejecuta acciones de gestión de equipos y procesos, para tomar decisiones informadas que promuevan el liderazgo colaborativo en escenarios organizacionales. | D13: Número de oportunidades de consultoría, auditoría e interventoría desarrolladas con medición semestral. | F13: Informe o Reporte.
A14: Integra criterios económicos, sociales y jurídicos que apoyen la toma de decisiones, para contribuir a la generación de valor y al desarrollo organizacional, considerando principios de sostenibilidad, así como las dinámicas y necesidades del entorno. | D14: Valoración del nivel de aporte de la estrategia a los resultados de aprendizaje del programa. | F14: Encuesta de valoración.
A15: Analiza los principios económicos y sociales, así como la normatividad empresarial para determinar rutas estratégicas de acción y procesos asociados a la gestión, según el funcionamiento de los entornos internos y externos que operan en los contextos organizacionales. | B15: Publicación de libros académicos (resultados de las investigaciones de los estudiantes) | C15: La convocatoria a publicación de libros académicos se realiza principalmente para los trabajos que surgen de la colaboracion estudiante-docente, de este modo, las publicaciones son conjuntas. El propósito de esta actividad es generar espacios que incentiven el desarrollo de competencias investigativas en los estudiantes del programa. | D15: Número de estudiantes que participan en la estrategia por periodo académico. | E15: Formar en prácticas de escritura académica, citación y construcción de argumentación sólida, así como en procesos de investigación. | F15: Listados de participación.
A16: Integra criterios económicos, sociales y jurídicos que apoyen la toma de decisiones, para contribuir a la generación de valor y al desarrollo organizacional, considerando principios de sostenibilidad, así como las dinámicas y necesidades del entorno. | D16: Relación de actividades desarrolladas en el grupo de interés con actividades del perfil ocupacional del programa. | F16: Informe o Reporte.
A17: Reconoce las habilidades poderosas o socioemocionales que intervienen en escenarios organizacionales y en las relaciones humanas, para determinar aquellas que son pertinentes en el abordaje de situaciones propias de los distintos ámbitos de la gestión empresarial. | D17: Valoración del nivel de aporte de la estrategia a los resultados de aprendizaje del programa. | F17: Encuesta de valoración.
A18: Reconoce distintos modelos de negocio y de innovación aplicables tanto a intraemprendimientos como a nuevos negocios, para seleccionar el más adecuado en el diseño de propuestas empresariales sostenibles y coherentes con el entorno.
A19: Analiza los principios económicos y sociales, así como la normatividad empresarial para determinar rutas estratégicas de acción y procesos asociados a la gestión, según el funcionamiento de los entornos internos y externos que operan en los contextos organizacionales. | B19: Coloquios y encuentros de investigación (investigación formativa) | C19: Existen dos eventos específicos desarrollados, uno es un evento de facultad denominado POLIPIF, en el cual participan los mejores proyectos de investigación formativa de la facultad y tambien participan estudiantes de otras universidades. En segundo lugar, se encuentra el Coloquio de Investigación en Diagnóstico Empresarial, el cual se enfoca en los resultados de investigación del campo de la consultoría empresarial. | D19: Número de estudiantes que participan en la estrategia por periodo académico. | E19: Formar en habilidades de comunicación científica y sustentación de proyectos ante audiencias académicas. Ayudar a tomar decisiones sobre cómo continuar el proceso investigativo o transformar el proyecto en otra producción académica. | F19: Listados de participación.
A20: Ejecuta acciones de gestión de equipos y procesos, para tomar decisiones informadas que promuevan el liderazgo colaborativo en escenarios organizacionales. | D20: Número de veces que se realiza la estrategia por periodo académico. | F20: Informe o Reporte.
A21: Integra criterios económicos, sociales y jurídicos que apoyen la toma de decisiones, para contribuir a la generación de valor y al desarrollo organizacional, considerando principios de sostenibilidad, así como las dinámicas y necesidades del entorno. | D21: Valoración del nivel de aporte de la estrategia a los resultados de aprendizaje del programa. | F21: Encuesta de valoración.
A22: Reconoce distintos modelos de negocio y de innovación aplicables tanto a intraemprendimientos como a nuevos negocios, para seleccionar el más adecuado en el diseño de propuestas empresariales sostenibles y coherentes con el entorno.
A23: Analiza los principios económicos y sociales, así como la normatividad empresarial para determinar rutas estratégicas de acción y procesos asociados a la gestión, según el funcionamiento de los entornos internos y externos que operan en los contextos organizacionales. | B23: Fomento al empredimiento | C23: El fomento al emprendimiento se desarrolla bajo el liderazgo del centro de emprendimiento adscrito a la Escuela de Administración y Competitividad. El centro de emprendimiento se descata principalmente por desarrollar actividades de formación, encuentros con emprendedores, concursos de emprendimiento y acompañamiento a emprendedores para hacer hacer realidad su idea de negocio. | D23: Número de estudiantes que participan en la estrategia en el periodo de su realización. | E23: Informar sobre los elementos clave que debe contener un modelo de negocio para ser competitivo. Ayudar a tomar decisiones sobre las acciones requeridas para avanzar o ajustar el desarrollo del proyecto emprendedor. | F23: Listas de participación.
A24: Ejecuta acciones de gestión de equipos y procesos, para tomar decisiones informadas que promuevan el liderazgo colaborativo en escenarios organizacionales. | D24: Número de veces que se realiza la estrategia por periodo académico. | F24: Informe o Reporte.
A25: Diseña estrategias empresariales para estructurar propuestas de mejora orientadas al fortalecimiento de la competitividad empresarial y al desarrollo de iniciativas de emprendimiento e intraemprendimiento. | D25: Valoración del nivel de aporte de la estrategia a los resultados de aprendizaje del programa. | F25: Encuesta de valoración.
A26: Reconoce las habilidades poderosas o socioemocionales que intervienen en escenarios organizacionales y en las relaciones humanas, para determinar aquellas que son pertinentes en el abordaje de situaciones propias de los distintos ámbitos de la gestión empresarial.
A27: Reconoce distintos modelos de negocio y de innovación aplicables tanto a intraemprendimientos como a nuevos negocios, para seleccionar el más adecuado en el diseño de propuestas empresariales sostenibles y coherentes con el entorno.

Sheet Paso 5 Estrategias micro
A1: [Estas celdas se diligencian automáticamente. No ajustar.] | B1: [A partir de la celda A3 despliegue el(los) resultado(s) de aprendizaje y elija aquel (aquellos) al(a los) que se contribuye desde la asignatura o módulo).] | C1: [Escribir el semestre en el que se cursa la asignatura o módulo.] | D1: [Escribir el nombre de la asignatura o módulo que contribuye al logro del resultado de aprendizaje.] | E1: [Redactar los indicadores iniciando con el verbo en presente indicativo, luego el objeto conceptual y finalmente el complemento de oración (que indique una condición o finalidad, con, para, de, entre otros conectores).] | F1: [Escribir la tipología: T (teórico), P (Práctico), TP (Teórico Práctico)] | G1: [Marcar con X el bloque o componente al que pertenece la asignatura o módulo. Por favor ajustar para posgrado, eliminar una columna y ubicar los títulos C.Fundamentación y C.Profundización.] | J1: [Escribir el número de créditos de la asignatura o módulo] | K1: [Escribir el número de horas de trabajo directo: 16*# o 12*#, para presencial o virtual, según sea el caso.] | L1: [Escribir el número de horas de trabajo independiente: 32*# columna J o 36*# columna J, para presencial o virtual, respectivamente.] | M1: [Escribir la suma de los números de horas de las dos celdas anteriores.] | N1: [Escribir el nombre de los cuatro núcleos temáticos que abordará la asignatura o el módulo.] | O1: [Escribir las lecturas, talleres, análisis, referentes, etc., que realiza el estudiante, clasificadas en trabajo directo e independiente.] | P1: [Escribir las actividades de evaluación que se emplean para identificar el alcance del (de los) indicador(es) de logro(s).] | Q1: [Escribir las acciones de retroalimentación que se emplearán en la asignatura o módulo, para retroalimentar a los estudiantes respecto al alcance de los indicadores de logro. Recordar que son cuatro acciones: informar, formar, prevenir y ayudar a tomar decisiones e indique cómo.]
A2: Tipo de Saber | B2: Resultado de aprendizaje | C2: Semestre | D2: Nombre asignatura o módulo | E2: Indicadores de logro asignatura o módulo | F2: Tipología | G2: B.Institucional | H2: B.Disciplinar | I2: B.Electivo | J2: Créditos | K2: Número de horas trabajo directo | L2: Número de horas trabajo independiente | M2: Total de horas | N2: Núcleos temáticos | O2: Actividades de aprendizaje | P2: Actividades de evaluación | Q2: Acciones de retroalimentación
A3: =_xlfn.XLOOKUP(B3,'Paso 3 Redacción RA'!I$3:I$15,'Paso 3 Redacción RA'!C$3:C$15,,0,1) -> Saber | B3: Identifica fenómenos contemporáneos y su relación con la profesión, para determinar sus impactos e influencia en la sociedad, de forma responsable y crítica. | C3: 1 | D3: Razonamiento Cuantitativo | E3: Analiza datos numéricos presentados en tablas, gráficos o textos para proponer soluciones informadas a situaciones problema del contexto. | F3: TP | G3: X | J3: 3 | K3: =16*J3 -> 48 | L3: =32*J3 -> 96 | M3: =SUM(K3:L3) -> 144 | N3: 1. Pensamiento numérico. Interpretación y representación de información numérica 2. Pensamiento algebraico. Desde la representación de regularidades y patrones 3. Pensamiento algebraico. Desde las relaciones de comparación entre cantidades o expresiones numéricas 4. Pensamiento geométrico. Propiedades, formas y relaciones espaciales | O3: Trabajo directo: Clase magistral activa Trabajo independiente: Lecturas Laboratorios, talleres, resolución de problemas | P3: Se sugiere emplear estrategias como las siguientes. Evaluación formativa: Preguntas intercaladas, presentaciones de situaciones problema. Evaluación sumativa: Valoración de laboratorios, talleres, estudios de casos y una evaluación final. | Q3: Informar oportunamente a través de la plataforma institucional y sesiones sincrónicas sobre el propósito, el proceso de realización, entrega de la actividad y criterios de evaluación. En las sesiones sincrónicas, atender las inquietudes y dar orientaciones al respecto, así como invitar a tomar asesorías ofrecidas por la Escuela de Ciencia Básicas, como estrategia de prevención y ayuda. Ayudar a tomar decisiones a través de preguntas orientadoras y actividades de refuerzo dentro del trabajo directo y autónomo. Retroalimentación por medio de rúbrica que indica el nivel de alcance del logro obtenido. Retroalimentación general del docente acorde a los resultados alcanzados por el grupo
A4: =_xlfn.XLOOKUP(B4,'Paso 3 Redacción RA'!I$3:I$15,'Paso 3 Redacción RA'!C$3:C$15,,0,1) -> Saber | B4: Identifica fenómenos contemporáneos y su relación con la profesión, para determinar sus impactos e influencia en la sociedad, de forma responsable y crítica. | C4: 1 | D4: Cultura, Política y Sociedad | E4: Reconoce las problemáticas, escenarios y mecanismos de participación ciudadana en el marco de sociedades de información y digitales para abordarlas desde iniciativas investigativas. Identifica los objetivos de desarrollo sostenible para la comprensión de problemáticas sociales, ambientales y culturales. Reflexiona los impactos de avances tecnológicos en su contexto profesional y ciudadano para el análisis de contextos situados. | F4: TP | G4: X | J4: 3 | K4: =16*J4 -> 48 | L4: =32*J4 -> 96 | M4: =SUM(K4:L4) -> 144 | N4: 1. ODS, problemas locales: una mirada a Colombia, territorio en búsqueda de la consolidación de la Paz. 2. Ciudadanía y su lugar: relaciones, dinámicas, construcción, expresión y mecanismos de participación. 3. Ecosistemas digitales: relaciones, dinámicas, construcción, expresión e impactos en el contexto profesional. 4. Narrativas y contenidos digitales: análisis de contextos situados. | O4: Trabajo directo: Clase magistral activa combinada con estrategias de aprendizaje basado en investigación Trabajo independiente: Lecturas Laboratorios Talleres Estudios de caso | P4: Evaluación formativa: Construcción de textos argumentativos sobre problemáticas en las sociedades de la información. ,elaboración de ejercicios para la citación en APA última edición., cartografías sociales de problemáticas sociales, culturales y ambientales., elaboración de árbol de problemas, construcción de objetivos generales y específicos, desarrollo de anteproyectos, talleres experienciales con juegos de roles, realización de exposición a través de la caja italiana para el manejo del espacio, la lectura y la oralidad, exposiciones creativas del PIF en el marco del evento “Feria de proyectos” Evaluación sumativa comprende los logros obtenidos en cada actividad y en todo el proceso, representados en porcentajes acumulativos según la parametrización de 0 a 5; Árbol de problemas, Exposiciones Creativas , Seguimiento , Entre Proyecto: Parte 1, Quiz , Seguimiento , Entre Proyecto: Parte 1I , Entrevista a expertos , Feria de proyectos , Seguimiento | Q4: Las acciones de retroalimentación giran en torno a las siguientes. Formar: donde se crean las condiciones para que los estudiantes adquieran conocimientos, habilidades, actitudes, aptitudes y destrezas. Además, debe promover su desarrollo integral y debe acompañarlos en las situaciones académicas que enfrenten durante el desarrollo de un módulo o una asignatura. Informar: para que los estudiantes identifiquen los cambios que pueden afectarlos directa o indirectamente tanto en el aula de clase como en otros espacios. Prevenir: con el fin de anticiparse a las situaciones académicas que pueden representar dificultad para los estudiantes. Esto se logra a través de la interacción individual con los estudiantes y del completo conocimiento del contexto educativo en que el tutor se desenvuelve. Ayudar a decidir: donde se orienta a los estudiantes para que tomen la mejor decisión ante una situación concreta. El objetivo es que el estudiante fortalezca su autonomía y la toma de decisiones responsable.
A5: =_xlfn.XLOOKUP(B5,'Paso 3 Redacción RA'!I$3:I$15,'Paso 3 Redacción RA'!C$3:C$15,,0,1) -> Saber | B5: Analiza los principios económicos y sociales, así como la normatividad empresarial para determinar rutas estratégicas de acción y procesos asociados a la gestión, según el funcionamiento de los entornos internos y externos que operan en los contextos organizacionales. | C5: 1 | D5: Derecho Comercial y Laboral | E5: Caracteriza los negocios jurídicos tanto en los actos de comercio como en las relaciones laborales en atención a la legislación vigente para crear modelos de empresas o contratos civiles, comerciales y laborales. | F5: TP | H5: X | J5: 3 | K5: =J5*16 -> 48 | L5: =32*J5 -> 96 | M5: =SUM(K5:L5) -> 144 | N5: 1. Acercamiento al derecho comercial 2. Costumbre mercantil 3. Historia, principios generales y fuentes del derecho laboral 4. Contrato de trabajo, jornada laboral, salario y prestaciones sociales | O5: Las estrategias pueden variar entre estas u otras: Trabajo directo: Clases magistrales Talleres / Laboratorios Soluciones numéricas Uso de herramientas computacionales Resolución de problemas Trabajo independiente: Lecturas Resolución de problemas Soluciones numéricas Uso de herramientas computacionales | P5: Se sugiere emplear estrategias como las siguientes. Formativa: Talleres Exposiciones Proyectos Sumativa: Trabajos escritos Pruebas conceptuales Examenes Exposiciones | Q5: Las acciones de retroalimentación giran en torno a las siguientes. Formar: donde se crean las condiciones para que los estudiantes adquieran conocimientos, habilidades, actitudes, aptitudes y destrezas. Además, debe promover su desarrollo integral y debe acompañarlos en las situaciones académicas que enfrenten durante el desarrollo de un módulo o una asignatura. Informar: para que los estudiantes identifiquen los cambios que pueden afectarlos directa o indirectamente tanto en el aula de clase como en otros espacios. Prevenir: con el fin de anticiparse a las situaciones académicas que pueden representar dificultad para los estudiantes. Esto se logra a través de la interacción individual con los estudiantes y del completo conocimiento del contexto educativo en que el tutor se desenvuelve. Ayudar a decidir: donde se orienta a los estudiantes para que tomen la mejor decisión ante una situación concreta. El objetivo es que el estudiante fortalezca su autonomía y la toma de decisiones responsable.
A6: =_xlfn.XLOOKUP(B6,'Paso 3 Redacción RA'!I$3:I$15,'Paso 3 Redacción RA'!C$3:C$15,,0,1) -> Saber | B6: Reconoce las habilidades poderosas o socioemocionales que intervienen en escenarios organizacionales y en las relaciones humanas, para determinar aquellas que son pertinentes en el abordaje de situaciones propias de los distintos ámbitos de la gestión empresarial.
A7: =_xlfn.XLOOKUP(B7,'Paso 3 Redacción RA'!I$3:I$15,'Paso 3 Redacción RA'!C$3:C$15,,0,1) -> SaberSer | B7: Integra criterios económicos, sociales y jurídicos que apoyen la toma de decisiones, para contribuir a la generación de valor y al desarrollo organizacional, considerando principios de sostenibilidad, así como las dinámicas y necesidades del entorno.
A8: =_xlfn.XLOOKUP(B8,'Paso 3 Redacción RA'!I$3:I$15,'Paso 3 Redacción RA'!C$3:C$15,,0,1) -> Saber | B8: Analiza los principios económicos y sociales, así como la normatividad empresarial para determinar rutas estratégicas de acción y procesos asociados a la gestión, según el funcionamiento de los entornos internos y externos que operan en los contextos organizacionales. | C8: 1 | D8: Contabilidad General | E8: Elabora el registro de las operaciones, conforme a la normatividad vigente y la técnica contable a partir del objeto social de una organización, teniendo en cuenta el marco conceptual de las normas internacionales de información financiera para elaborar los estados financieros. | F8: TP | H8: X | J8: 3 | K8: =J8*16 -> 48 | L8: =32*J8 -> 96 | M8: =SUM(K8:L8) -> 144 | N8: 1. Fundamentación teórica y técnica contable 2. Elementos de los Estados Financieros y sus características 3. Transacciones comerciales y operaciones con cuentas de resultado 4. Estructura de los Estados Financieros | O8: Las estrategias pueden variar entre estas u otras: Trabajo directo Clase magistral activa/Análisis o Estudio de casos/Resolución de problemas/Talleres prácticos Trabajo independiente Lecturas relacionadas o de materiales complementarios/Resolución de problemas/Ejercicios aplicados/Desarrollo de proyectos/Talleres grupales o individuales/Análisis o Estudio de casos/Elaboración de informes o documentos técnicos | P8: Las actividades varían entre las siguientes y otras que pueda considerar el profesor y funcionan como formativas o sumativas, según sea el caso. Estudio de casos Resolución de problemas Desarrollo de proyectos Talleres Exposiciones Pruebas escritas | Q8: Las acciones de retroalimentación giran en torno a las siguientes. Formar: donde se crean las condiciones para que los estudiantes adquieran conocimientos, habilidades, actitudes, aptitudes y destrezas. Además, debe promover su desarrollo integral y debe acompañarlos en las situaciones académicas que enfrenten durante el desarrollo de un módulo o una asignatura. Informar: para que los estudiantes identifiquen los cambios que pueden afectarlos directa o indirectamente tanto en el aula de clase como en otros espacios. Prevenir: con el fin de anticiparse a las situaciones académicas que pueden representar dificultad para los estudiantes. Esto se logra a través de la interacción individual con los estudiantes y del completo conocimiento del contexto educativo en que el tutor se desenvuelve. Ayudar a decidir: donde se orienta a los estudiantes para que tomen la mejor decisión ante una situación concreta. El objetivo es que el estudiante fortalezca su autonomía y la toma de decisiones responsable.
A9: =_xlfn.XLOOKUP(B9,'Paso 3 Redacción RA'!I$3:I$15,'Paso 3 Redacción RA'!C$3:C$15,,0,1) -> SaberHacer | B9: Diseña estrategias empresariales para estructurar propuestas de mejora orientadas al fortalecimiento de la competitividad empresarial y al desarrollo de iniciativas de emprendimiento e intraemprendimiento.
A10: =_xlfn.XLOOKUP(B10,'Paso 3 Redacción RA'!I$3:I$15,'Paso 3 Redacción RA'!C$3:C$15,,0,1) -> Saber | B10: Reconoce distintos modelos de negocio y de innovación aplicables tanto a intraemprendimientos como a nuevos negocios, para seleccionar el más adecuado en el diseño de propuestas empresariales sostenibles y coherentes con el entorno.
A11: =_xlfn.XLOOKUP(B11,'Paso 3 Redacción RA'!I$3:I$15,'Paso 3 Redacción RA'!C$3:C$15,,0,1) -> Saber | B11: Analiza los principios económicos y sociales, así como la normatividad empresarial para determinar rutas estratégicas de acción y procesos asociados a la gestión, según el funcionamiento de los entornos internos y externos que operan en los contextos organizacionales. | C11: 1 | D11: Proceso Administrativo | E11: Reconoce las etapas del proceso administrativo (planeación, organización, dirección y control) para aplicarlas en situaciones organizacionales. | F11: T | H11: X | J11: 3 | K11: =J11*16 -> 48 | L11: =32*J11 -> 96 | M11: =SUM(K11:L11) -> 144 | N11: 1. Planeación 2. Organización 3. Dirección: Integración de Personal - Motivación – liderazgo y comunicación 4. Control | O11: Las estrategias pueden variar entre estas u otras: Trabajo directo Clase magistral activa/Análisis o Estudio de casos/Resolución de problemas/Talleres prácticos Trabajo independiente Lecturas relacionadas o de materiales complementarios/Resolución de problemas/Ejercicios aplicados/Desarrollo de proyectos/Talleres grupales o individuales/Análisis o Estudio de casos/Elaboración de informes o documentos técnicos | P11: Las actividades varían entre las siguientes y otras que pueda considerar el profesor y funcionan como formativas o sumativas, según sea el caso. Estudio de casos Resolución de problemas Desarrollo de proyectos Talleres Exposiciones Pruebas escritas | Q11: Las acciones de retroalimentación giran en torno a las siguientes. Formar: donde se crean las condiciones para que los estudiantes adquieran conocimientos, habilidades, actitudes, aptitudes y destrezas. Además, debe promover su desarrollo integral y debe acompañarlos en las situaciones académicas que enfrenten durante el desarrollo de un módulo o una asignatura. Informar: para que los estudiantes identifiquen los cambios que pueden afectarlos directa o indirectamente tanto en el aula de clase como en otros espacios. Prevenir: con el fin de anticiparse a las situaciones académicas que pueden representar dificultad para los estudiantes. Esto se logra a través de la interacción individual con los estudiantes y del completo conocimiento del contexto educativo en que el tutor se desenvuelve. Ayudar a decidir: donde se orienta a los estudiantes para que tomen la mejor decisión ante una situación concreta. El objetivo es que el estudiante fortalezca su autonomía y la toma de decisiones responsable.
A12: =_xlfn.XLOOKUP(B12,'Paso 3 Redacción RA'!I$3:I$15,'Paso 3 Redacción RA'!C$3:C$15,,0,1) -> SaberHacer | B12: Ejecuta acciones de gestión de equipos y procesos, para tomar decisiones informadas que promuevan el liderazgo colaborativo en escenarios organizacionales.
A13: =_xlfn.XLOOKUP(B13,'Paso 3 Redacción RA'!I$3:I$15,'Paso 3 Redacción RA'!C$3:C$15,,0,1) -> Saber | B13: Reconoce las habilidades poderosas o socioemocionales que intervienen en escenarios organizacionales y en las relaciones humanas, para determinar aquellas que son pertinentes en el abordaje de situaciones propias de los distintos ámbitos de la gestión empresarial.
A14: =_xlfn.XLOOKUP(B14,'Paso 3 Redacción RA'!I$3:I$15,'Paso 3 Redacción RA'!C$3:C$15,,0,1) -> SaberSer | B14: Integra criterios económicos, sociales y jurídicos que apoyen la toma de decisiones, para contribuir a la generación de valor y al desarrollo organizacional, considerando principios de sostenibilidad, así como las dinámicas y necesidades del entorno.
A15: =_xlfn.XLOOKUP(B15,'Paso 3 Redacción RA'!I$3:I$15,'Paso 3 Redacción RA'!C$3:C$15,,0,1) -> Saber | B15: Analiza los principios económicos y sociales, así como la normatividad empresarial para determinar rutas estratégicas de acción y procesos asociados a la gestión, según el funcionamiento de los entornos internos y externos que operan en los contextos organizacionales. | C15: 1 | D15: Gestión del Talento Humano | E15: Identifica las características y evolución en el tiempo de la gestión del talento humano, para, a partir de casos concretos, proponer soluciones en un contexto organizacional. | F15: TP | H15: X | J15: 3 | K15: =J15*16 -> 48 | L15: =32*J15 -> 96 | M15: =SUM(K15:L15) -> 144 | N15: 1. Importancia del Talento humano en las organizaciones 2. Análisis, descripción y diseño de cargos dentro de la incorporación de las personas en las organizaciones 3. Desarrollo, formación y retribución de las personas en las organizaciones 4. Impacto en las organizaciones, mediante la generación de valor, a través de la evaluación desempeño y el proceso de Seguridad y Salud en el Trabajo | O15: Las estrategias pueden variar entre estas u otras: Trabajo directo Clase magistral activa/Análisis o Estudio de casos/Resolución de problemas/Talleres prácticos Trabajo independiente Lecturas relacionadas o de materiales complementarios/Resolución de problemas/Ejercicios aplicados/Desarrollo de proyectos/Talleres grupales o individuales/Análisis o Estudio de casos/Elaboración de informes o documentos técnicos | P15: Las actividades varían entre las siguientes y otras que pueda considerar el profesor y funcionan como formativas o sumativas, según sea el caso. Estudio de casos Resolución de problemas Desarrollo de proyectos Talleres Exposiciones Pruebas escritas | Q15: Las acciones de retroalimentación giran en torno a las siguientes. Formar: donde se crean las condiciones para que los estudiantes adquieran conocimientos, habilidades, actitudes, aptitudes y destrezas. Además, debe promover su desarrollo integral y debe acompañarlos en las situaciones académicas que enfrenten durante el desarrollo de un módulo o una asignatura. Informar: para que los estudiantes identifiquen los cambios que pueden afectarlos directa o indirectamente tanto en el aula de clase como en otros espacios. Prevenir: con el fin de anticiparse a las situaciones académicas que pueden representar dificultad para los estudiantes. Esto se logra a través de la interacción individual con los estudiantes y del completo conocimiento del contexto educativo en que el tutor se desenvuelve. Ayudar a decidir: donde se orienta a los estudiantes para que tomen la mejor decisión ante una situación concreta. El objetivo es que el estudiante fortalezca su autonomía y la toma de decisiones responsable.
A16: =_xlfn.XLOOKUP(B16,'Paso 3 Redacción RA'!I$3:I$15,'Paso 3 Redacción RA'!C$3:C$15,,0,1) -> SaberHacer | B16: Ejecuta acciones de gestión de equipos y procesos, para tomar decisiones informadas que promuevan el liderazgo colaborativo en escenarios organizacionales.
A17: =_xlfn.XLOOKUP(B17,'Paso 3 Redacción RA'!I$3:I$15,'Paso 3 Redacción RA'!C$3:C$15,,0,1) -> SaberSer | B17: Integra criterios económicos, sociales y jurídicos que apoyen la toma de decisiones, para contribuir a la generación de valor y al desarrollo organizacional, considerando principios de sostenibilidad, así como las dinámicas y necesidades del entorno. | R17: =SUM(J3:J17) -> 18 | S17: =COUNTA(D3:D17) -> 6
A18: =_xlfn.XLOOKUP(B18,'Paso 3 Redacción RA'!I$3:I$15,'Paso 3 Redacción RA'!C$3:C$15,,0,1) -> Saber | B18: Identifica fenómenos contemporáneos y su relación con la profesión, para determinar sus impactos e influencia en la sociedad, de forma responsable y crítica. | C18: 2 | D18: Análisis y Visualización de Datos | E18: Identifica conceptos básicos relacionados con el análisis y visualización de datos con el propósito de comunicar información relevante de manera efectiva en diversos contextos. Utiliza herramientas para realizar análisis y transformación de datos que garanticen una visualización sencilla y eficiente. Utiliza asistentes virtuales para realizar tareas prácticas y resolver problemas en su campo de estudio. Evalúa la presencia de sesgos y cuestiones éticas en el análisis y tratamiento de dato para garantizar que su uso esté desprovisto de efectos negativos en el entorno. | F18: TP | G18: X | J18: 3 | K18: =16*J18 -> 48 | L18: =32*J18 -> 96 | M18: =SUM(K18:L18) -> 144 | N18: 1. Contextualización 2. Análisis de Datos y Visualización 3. Usos de la Inteligencia Artificial 4. Casos de Estudio | O18: Trabajo directo: Clase magistral activa combinada con estrategias de metodologías activas Trabajo independiente: Lecturas Laboratorios Talleres Estudios de caso. | P18: Se sugiere emplear estrategias como las siguientes. Evaluación formativa: Preguntas intercaladas, presentaciones de situaciones problema, talleres, exposiciones, análisis de casos, trabajos de campo o proyectos. Evaluación sumativa: Valoración de trabajo, talleres, estudios de casos y una evaluación final. | Q18: Las acciones de retroalimentación giran en torno a las siguientes. Formar: donde se crean las condiciones para que los estudiantes adquieran conocimientos, habilidades, actitudes, aptitudes y destrezas. Además, debe promover su desarrollo integral y debe acompañarlos en las situaciones académicas que enfrenten durante el desarrollo de un módulo o una asignatura. Informar: para que los estudiantes identifiquen los cambios que pueden afectarlos directa o indirectamente tanto en el aula de clase como en otros espacios. Prevenir: con el fin de anticiparse a las situaciones académicas que pueden representar dificultad para los estudiantes. Esto se logra a través de la interacción individual con los estudiantes y del completo conocimiento del contexto educativo en que el tutor se desenvuelve. Ayudar a decidir: donde se orienta a los estudiantes para que tomen la mejor decisión ante una situación concreta. El objetivo es que el estudiante fortalezca su autonomía y la toma de decisiones responsable.
A19: =_xlfn.XLOOKUP(B19,'Paso 3 Redacción RA'!I$3:I$15,'Paso 3 Redacción RA'!C$3:C$15,,0,1) -> Saber | B19: Analiza los principios económicos y sociales, así como la normatividad empresarial para determinar rutas estratégicas de acción y procesos asociados a la gestión, según el funcionamiento de los entornos internos y externos que operan en los contextos organizacionales. | C19: 2 | D19: Razonamiento Variacional | E19: Aplica el pensamiento variacional y acumulativo para interpretar, modelar y resolver problemas de cambio y acumulación, relacionados con su contexto profesional y personal, mediante el uso reflexivo de las propiedades y aplicaciones de las derivadas e integrales. | F19: TP | H19: X | J19: 3 | K19: =J19*16 -> 48 | L19: =32*J19 -> 96 | M19: =SUM(K19:L19) -> 144 | N19: 1. Fundamentos del pensamiento variacional 2. Análisis del cambio y dinámica 3. Acumulación y modelado integral 4. Aplicaciones avanzadas y modelización | O19: Las estrategias pueden variar entre estas u otras: Trabajo directo Clase magistral activa/Resolución de problemas/Talleres prácticos Trabajo independiente Lecturas relacionadas o de materiales complementarios/Resolución de problemas/Ejercicios aplicado/Talleres grupales o individuales/ | P19: Las actividades varían entre las siguientes y otras que pueda considerar el profesor y funcionan como formativas o sumativas, según sea el caso. Resolución de problemas Talleres Exposiciones Pruebas escritas | Q19: Las acciones de retroalimentación giran en torno a las siguientes. Formar: donde se crean las condiciones para que los estudiantes adquieran conocimientos, habilidades, actitudes, aptitudes y destrezas. Además, debe promover su desarrollo integral y debe acompañarlos en las situaciones académicas que enfrenten durante el desarrollo de un módulo o una asignatura. Informar: para que los estudiantes identifiquen los cambios que pueden afectarlos directa o indirectamente tanto en el aula de clase como en otros espacios. Prevenir: con el fin de anticiparse a las situaciones académicas que pueden representar dificultad para los estudiantes. Esto se logra a través de la interacción individual con los estudiantes y del completo conocimiento del contexto educativo en que el tutor se desenvuelve. Ayudar a decidir: donde se orienta a los estudiantes para que tomen la mejor decisión ante una situación concreta. El objetivo es que el estudiante fortalezca su autonomía y la toma de decisiones responsable.
A20: =_xlfn.XLOOKUP(B20,'Paso 3 Redacción RA'!I$3:I$15,'Paso 3 Redacción RA'!C$3:C$15,,0,1) -> SaberHacer | B20: Ejecuta acciones de gestión de equipos y procesos, para tomar decisiones informadas que promuevan el liderazgo colaborativo en escenarios organizacionales.
A21: =_xlfn.XLOOKUP(B21,'Paso 3 Redacción RA'!I$3:I$15,'Paso 3 Redacción RA'!C$3:C$15,,0,1) -> Saber | B21: Reconoce las habilidades poderosas o socioemocionales que intervienen en escenarios organizacionales y en las relaciones humanas, para determinar aquellas que son pertinentes en el abordaje de situaciones propias de los distintos ámbitos de la gestión empresarial.
A22: =_xlfn.XLOOKUP(B22,'Paso 3 Redacción RA'!I$3:I$15,'Paso 3 Redacción RA'!C$3:C$15,,0,1) -> SaberSer | B22: Integra criterios económicos, sociales y jurídicos que apoyen la toma de decisiones, para contribuir a la generación de valor y al desarrollo organizacional, considerando principios de sostenibilidad, así como las dinámicas y necesidades del entorno. | C22: 2 | D22: Fundamentos de Mercadeo | E22: Relaciona los conceptos teóricos del mercadeo como un proceso estratégico y táctico para estructurar propuestas de valor a los clientes (consumidores y empresas), que cumplan con los objetivos que la organización se ha trazado en el mercado. | F22: TP | H22: X | J22: 3 | K22: =J22*16 -> 48 | L22: =32*J22 -> 96 | M22: =SUM(K22:L22) -> 144 | N22: 1. Principios y conceptos básicos de Mercadeo 2. Conocimiento del mercado y de los consumidores 3. Mercadeo estratégico 4. Mercadeo táctico | O22: Las estrategias pueden variar entre estas u otras: Trabajo directo Clase magistral activa/Análisis o Estudio de casos/Resolución de problemas/Talleres prácticos Trabajo independiente Lecturas relacionadas o de materiales complementarios/Resolución de problemas/Ejercicios aplicados/Desarrollo de proyectos/Talleres grupales o individuales/Análisis o Estudio de casos/Elaboración de informes o documentos técnicos | P22: Las actividades varían entre las siguientes y otras que pueda considerar el profesor y funcionan como formativas o sumativas, según sea el caso. Estudio de casos Resolución de problemas Desarrollo de proyectos Talleres Exposiciones Pruebas escritas | Q22: Las acciones de retroalimentación giran en torno a las siguientes. Formar: donde se crean las condiciones para que los estudiantes adquieran conocimientos, habilidades, actitudes, aptitudes y destrezas. Además, debe promover su desarrollo integral y debe acompañarlos en las situaciones académicas que enfrenten durante el desarrollo de un módulo o una asignatura. Informar: para que los estudiantes identifiquen los cambios que pueden afectarlos directa o indirectamente tanto en el aula de clase como en otros espacios. Prevenir: con el fin de anticiparse a las situaciones académicas que pueden representar dificultad para los estudiantes. Esto se logra a través de la interacción individual con los estudiantes y del completo conocimiento del contexto educativo en que el tutor se desenvuelve. Ayudar a decidir: donde se orienta a los estudiantes para que tomen la mejor decisión ante una situación concreta. El objetivo es que el estudiante fortalezca su autonomía y la toma de decisiones responsable.
A23: =_xlfn.XLOOKUP(B23,'Paso 3 Redacción RA'!I$3:I$15,'Paso 3 Redacción RA'!C$3:C$15,,0,1) -> SaberHacer | B23: Diseña estrategias empresariales para estructurar propuestas de mejora orientadas al fortalecimiento de la competitividad empresarial y al desarrollo de iniciativas de emprendimiento e intraemprendimiento.
A24: =_xlfn.XLOOKUP(B24,'Paso 3 Redacción RA'!I$3:I$15,'Paso 3 Redacción RA'!C$3:C$15,,0,1) -> Saber | B24: Analiza los principios económicos y sociales, así como la normatividad empresarial para determinar rutas estratégicas de acción y procesos asociados a la gestión, según el funcionamiento de los entornos internos y externos que operan en los contextos organizacionales.
A25: =_xlfn.XLOOKUP(B25,'Paso 3 Redacción RA'!I$3:I$15,'Paso 3 Redacción RA'!C$3:C$15,,0,1) -> Saber | B25: Analiza los principios económicos y sociales, así como la normatividad empresarial para determinar rutas estratégicas de acción y procesos asociados a la gestión, según el funcionamiento de los entornos internos y externos que operan en los contextos organizacionales. | C25: 2 | D25: Costos y Presupuestos | E25: Clasifica los elementos de los costos de producción y la proyección presupuestal para la construcción de información financiera, como el cálculo de los sistemas de acumulación de costos, el Estado de Costos, Estado de Resultados, Estado de Situación Financiera, insumos requeridos en la toma de decisiones estratégicas. | F25: TP | H25: X | J25: 3 | K25: =J25*16 -> 48 | L25: =32*J25 -> 96 | M25: =SUM(K25:L25) -> 144 | N25: 1. Conceptualización general de los costos 2. Sistemas de costeo y aplicación de los costos en la toma de decisiones 3. Presupuesto maestro 4. Estados financieros proyectados | O25: Las estrategias pueden variar entre estas u otras: Trabajo directo Clase magistral activa/Análisis o Estudio de casos/Resolución de problemas/Talleres prácticos Trabajo independiente Lecturas relacionadas o de materiales complementarios/Resolución de problemas/Ejercicios aplicados/Desarrollo de proyectos/Talleres grupales o individuales/Análisis o Estudio de casos/Elaboración de informes o documentos técnicos | P25: Las actividades varían entre las siguientes y otras que pueda considerar el profesor y funcionan como formativas o sumativas, según sea el caso. Estudio de casos Resolución de problemas Desarrollo de proyectos Talleres Exposiciones Pruebas escritas | Q25: Las acciones de retroalimentación giran en torno a las siguientes. Formar: donde se crean las condiciones para que los estudiantes adquieran conocimientos, habilidades, actitudes, aptitudes y destrezas. Además, debe promover su desarrollo integral y debe acompañarlos en las situaciones académicas que enfrenten durante el desarrollo de un módulo o una asignatura. Informar: para que los estudiantes identifiquen los cambios que pueden afectarlos directa o indirectamente tanto en el aula de clase como en otros espacios. Prevenir: con el fin de anticiparse a las situaciones académicas que pueden representar dificultad para los estudiantes. Esto se logra a través de la interacción individual con los estudiantes y del completo conocimiento del contexto educativo en que el tutor se desenvuelve. Ayudar a decidir: donde se orienta a los estudiantes para que tomen la mejor decisión ante una situación concreta. El objetivo es que el estudiante fortalezca su autonomía y la toma de decisiones responsable.
A26: =_xlfn.XLOOKUP(B26,'Paso 3 Redacción RA'!I$3:I$15,'Paso 3 Redacción RA'!C$3:C$15,,0,1) -> SaberHacer | B26: Ejecuta acciones de gestión de equipos y procesos, para tomar decisiones informadas que promuevan el liderazgo colaborativo en escenarios organizacionales.
A27: =_xlfn.XLOOKUP(B27,'Paso 3 Redacción RA'!I$3:I$15,'Paso 3 Redacción RA'!C$3:C$15,,0,1) -> Saber | B27: Reconoce distintos modelos de negocio y de innovación aplicables tanto a intraemprendimientos como a nuevos negocios, para seleccionar el más adecuado en el diseño de propuestas empresariales sostenibles y coherentes con el entorno.
A28: =_xlfn.XLOOKUP(B28,'Paso 3 Redacción RA'!I$3:I$15,'Paso 3 Redacción RA'!C$3:C$15,,0,1) -> SaberSer | B28: Integra criterios económicos, sociales y jurídicos que apoyen la toma de decisiones, para contribuir a la generación de valor y al desarrollo organizacional, considerando principios de sostenibilidad, así como las dinámicas y necesidades del entorno.
A29: =_xlfn.XLOOKUP(B29,'Paso 3 Redacción RA'!I$3:I$15,'Paso 3 Redacción RA'!C$3:C$15,,0,1) -> Saber | B29: Analiza los principios económicos y sociales, así como la normatividad empresarial para determinar rutas estratégicas de acción y procesos asociados a la gestión, según el funcionamiento de los entornos internos y externos que operan en los contextos organizacionales. | C29: 2 | D29: Riesgo Operativo y LA/FT | E29: Identifica las características del Sistema de administración de riesgo operativo (SARO)y riesgo de LA y FT en contextos organizacionales para determinar el impacto en el logro de los objetivos estratégicos, tácticos, de proyectos, productos y servicios. | F29: T | H29: X | J29: 4 | K29: =J29*16 -> 64 | L29: =32*J29 -> 128 | M29: =SUM(K29:L29) -> 192 | N29: 1. Generalidades del Riesgo y Sistema de administración de riesgo operativo 2. Medición y tratamiento del riesgo operativo 3. Continuidad de negocio y SARLAFT 4. Salafí y otros sistemas de administración de riesgo de lavado de activos | O29: Las estrategias pueden variar entre estas u otras: Trabajo directo Clase magistral activa/Análisis o Estudio de casos/Resolución de problemas/Talleres prácticos Trabajo independiente Lecturas relacionadas o de materiales complementarios/Resolución de problemas/Ejercicios aplicados/Desarrollo de proyectos/Talleres grupales o individuales/Análisis o Estudio de casos/Elaboración de informes o documentos técnicos | P29: Las actividades varían entre las siguientes y otras que pueda considerar el profesor y funcionan como formativas o sumativas, según sea el caso. Estudio de casos Resolución de problemas Desarrollo de proyectos Talleres Exposiciones Pruebas escritas | Q29: Las acciones de retroalimentación giran en torno a las siguientes. Formar: donde se crean las condiciones para que los estudiantes adquieran conocimientos, habilidades, actitudes, aptitudes y destrezas. Además, debe promover su desarrollo integral y debe acompañarlos en las situaciones académicas que enfrenten durante el desarrollo de un módulo o una asignatura. Informar: para que los estudiantes identifiquen los cambios que pueden afectarlos directa o indirectamente tanto en el aula de clase como en otros espacios. Prevenir: con el fin de anticiparse a las situaciones académicas que pueden representar dificultad para los estudiantes. Esto se logra a través de la interacción individual con los estudiantes y del completo conocimiento del contexto educativo en que el tutor se desenvuelve. Ayudar a decidir: donde se orienta a los estudiantes para que tomen la mejor decisión ante una situación concreta. El objetivo es que el estudiante fortalezca su autonomía y la toma de decisiones responsable.
A30: =_xlfn.XLOOKUP(B30,'Paso 3 Redacción RA'!I$3:I$15,'Paso 3 Redacción RA'!C$3:C$15,,0,1) -> SaberSer | B30: Integra criterios económicos, sociales y jurídicos que apoyen la toma de decisiones, para contribuir a la generación de valor y al desarrollo organizacional, considerando principios de sostenibilidad, así como las dinámicas y necesidades del entorno.
A31: =_xlfn.XLOOKUP(B31,'Paso 3 Redacción RA'!I$3:I$15,'Paso 3 Redacción RA'!C$3:C$15,,0,1) -> SaberHacer | B31: Diseña estrategias empresariales para estructurar propuestas de mejora orientadas al fortalecimiento de la competitividad empresarial y al desarrollo de iniciativas de emprendimiento e intraemprendimiento. | R31: =SUM(J18:J31) -> 16 | S31: =COUNTA(D18:D31) -> 5
A32: =_xlfn.XLOOKUP(B32,'Paso 3 Redacción RA'!I$3:I$15,'Paso 3 Redacción RA'!C$3:C$15,,0,1) -> Saber | B32: Identifica fenómenos contemporáneos y su relación con la profesión, para determinar sus impactos e influencia en la sociedad, de forma responsable y crítica. | C32: 3 | D32: Oportunidades para Emprender | E32: Propone soluciones a los problemas, frustraciones y expectativas de un grupo de personas en su comunidad para idear productos o servicios con valor agregado dentro de su campo de acción profesional. Diseña una idea de negocio que represente una oportunidad de mercado teniendo en cuenta sus habilidades para emprender y el análisis del entorno. | F32: TP | G32: X | J32: 3 | K32: =16*J32 -> 48 | L32: =32*J32 -> 96 | M32: =SUM(K32:L32) -> 144 | N32: 1. Empatía y Comprensión del Usuario 2. Co-creación con los Usuarios 3. Enfoque en la Experiencia del Usuario 4. Diseño del modelo de negocio | O32: Trabajo directo: Clase magistral activa combinada con estrategias de metodologías activas Trabajo independiente: Lecturas. Laboratorios, talleres, estudios de caso. | P32: Se sugiere emplear estrategias como las siguientes. Evaluación formativa: Preguntas intercaladas, presentaciones de situaciones problema, talleres, exposiciones, análisis de casos, trabajos de campo o proyectos. Evaluación sumativa: Valoración de trabajo, talleres, estudios de casos y una evaluación final. | Q32: Las acciones de retroalimentación giran en torno a las siguientes. Formar: donde se crean las condiciones para que los estudiantes adquieran conocimientos, habilidades, actitudes, aptitudes y destrezas. Además, debe promover su desarrollo integral y debe acompañarlos en las situaciones académicas que enfrenten durante el desarrollo de un módulo o una asignatura. Informar: para que los estudiantes identifiquen los cambios que pueden afectarlos directa o indirectamente tanto en el aula de clase como en otros espacios. Prevenir: con el fin de anticiparse a las situaciones académicas que pueden representar dificultad para los estudiantes. Esto se logra a través de la interacción individual con los estudiantes y del completo conocimiento del contexto educativo en que el tutor se desenvuelve. Ayudar a decidir: donde se orienta a los estudiantes para que tomen la mejor decisión ante una situación concreta. El objetivo es que el estudiante fortalezca su autonomía y la toma de decisiones responsable.
A33: =_xlfn.XLOOKUP(B33,'Paso 3 Redacción RA'!I$3:I$15,'Paso 3 Redacción RA'!C$3:C$15,,0,1) -> Saber | B33: Identifica fenómenos contemporáneos y su relación con la profesión, para determinar sus impactos e influencia en la sociedad, de forma responsable y crítica. | C33: 3 | D33: Pensamiento Crítico y Ciudadanías Activas | E33: Identifica los Derechos y Deberes consignados en la Constitución 1991 en relación con la ciudadanía de manera local y global para la comprensión de inmersiones sociales éticas. Reflexiona los impactos de la investigación- acción sin daño en los espacios académicos y los territorios para el abordaje desde proyectos de investigación formativa. Elabora el diseño de planes detallados desde abordajes investigativos e inmersiones creativas para divulgar hallazgos en el ámbito académico. | F33: TP | G33: X | J33: 3 | K33: =16*J33 -> 48 | L33: =32*J33 -> 96 | M33: =SUM(K33:L33) -> 144 | N33: 1. Pacto social colombiano y marco de referencias de DDHH internacionales 2. Planes detallados e inmersiones sociales desde procesos participativos, acciones sociales e iniciativas ciudadanas como respuesta a problemas glocales 3. Perspectivas para la participación ciudadana en los territorios 4. Los avances tecnológicos y su impacto en lo social, cultural y ambiental en el marco de las sociedades de información | O33: Trabajo directo: Encuentros presenciales con las horas asignadas a la semana para el desarrollo de la asignatura Aprendizaje basado en problemas Trabajo independiente: Resumen (incluyendo la lectura de textos narrativos, expositivos y argumentativos) Análisis crítico de noticias sociales, culturales y ambientales Elaboración de Árbol de problemas como técnica para planteamiento de problemas del PIF Talleres individuales y por grupos sobre la tipología de textos | P33: Construcción de planes detallados según las problemáticas desarrolladas en la asignatura. Evaluación y autoevaluación de Anteproyectos entre pares académicos a través de la guía “Lecturas cruzadas” Reflexión y análisis sobre la ética y la mora en sus contextos locales, globales y profesionales. Comprensión de conceptos temáticas a través de cine documental y cine foros. Exploración de estrategias y actividades para los planes detallados. Desarrollo de anteproyectos. Talleres experienciales con juegos de roles. Realización de exposición a través de la caja italiana para el manejo del espacio, la lectura y la oralidad. Exposiciones creativas del PIF en el marco del evento “Feria de proyectos” | Q33: Las acciones de retroalimentación giran en torno a las siguientes. Formar: donde se crean las condiciones para que los estudiantes adquieran conocimientos, habilidades, actitudes, aptitudes y destrezas. Además, debe promover su desarrollo integral y debe acompañarlos en las situaciones académicas que enfrenten durante el desarrollo de un módulo o una asignatura. Informar: para que los estudiantes identifiquen los cambios que pueden afectarlos directa o indirectamente tanto en el aula de clase como en otros espacios. Prevenir: con el fin de anticiparse a las situaciones académicas que pueden representar dificultad para los estudiantes. Esto se logra a través de la interacción individual con los estudiantes y del completo conocimiento del contexto educativo en que el tutor se desenvuelve. Ayudar a decidir: donde se orienta a los estudiantes para que tomen la mejor decisión ante una situación concreta. El objetivo es que el estudiante fortalezca su autonomía y la toma de decisiones responsable.
A34: =_xlfn.XLOOKUP(B34,'Paso 3 Redacción RA'!I$3:I$15,'Paso 3 Redacción RA'!C$3:C$15,,0,1) -> Saber | B34: Analiza los principios económicos y sociales, así como la normatividad empresarial para determinar rutas estratégicas de acción y procesos asociados a la gestión, según el funcionamiento de los entornos internos y externos que operan en los contextos organizacionales. | C34: 3 | D34: Análisis Descriptivo de Datos | E34: Aplica herramientas tecnológicas y modelos probabilísticos para representar procesos aleatorios y determinar valores de probabilidad en diferentes escenarios. Aplica conceptos de probabilidad elemental y distribuciones como la normal y la binomial, para apoyar decisiones en diversos contextos. | F34: TP | H34: X | J34: 3 | K34: =J34*16 -> 48 | L34: =32*J34 -> 96 | M34: =SUM(K34:L34) -> 144 | N34: 1. Estadística descriptiva 2. Teoría de la probabilidad 3. Variables aleatorias y distribuciones de probabilidad 4. Distribuciones de probabilidad discretas y continuas | O34: Las estrategias pueden variar entre estas u otras: Trabajo directo Clase magistral activa/Análisis o Estudio de casos/Resolución de problemas/Talleres prácticos Trabajo independiente Lecturas relacionadas o de materiales complementarios/Resolución de problemas/Ejercicios aplicados/Desarrollo de proyectos/Talleres grupales o individuales/Análisis o Estudio de casos/Elaboración de informes o documentos técnicos | P34: Las actividades varían entre las siguientes y otras que pueda considerar el profesor y funcionan como formativas o sumativas, según sea el caso. Estudio de casos Resolución de problemas Desarrollo de proyectos Talleres Exposiciones Pruebas escritas | Q34: Las acciones de retroalimentación giran en torno a las siguientes. Formar: donde se crean las condiciones para que los estudiantes adquieran conocimientos, habilidades, actitudes, aptitudes y destrezas. Además, debe promover su desarrollo integral y debe acompañarlos en las situaciones académicas que enfrenten durante el desarrollo de un módulo o una asignatura. Informar: para que los estudiantes identifiquen los cambios que pueden afectarlos directa o indirectamente tanto en el aula de clase como en otros espacios. Prevenir: con el fin de anticiparse a las situaciones académicas que pueden representar dificultad para los estudiantes. Esto se logra a través de la interacción individual con los estudiantes y del completo conocimiento del contexto educativo en que el tutor se desenvuelve. Ayudar a decidir: donde se orienta a los estudiantes para que tomen la mejor decisión ante una situación concreta. El objetivo es que el estudiante fortalezca su autonomía y la toma de decisiones responsable.
A35: =_xlfn.XLOOKUP(B35,'Paso 3 Redacción RA'!I$3:I$15,'Paso 3 Redacción RA'!C$3:C$15,,0,1) -> SaberHacer | B35: Diseña estrategias empresariales para estructurar propuestas de mejora orientadas al fortalecimiento de la competitividad empresarial y al desarrollo de iniciativas de emprendimiento e intraemprendimiento.
A36: =_xlfn.XLOOKUP(B36,'Paso 3 Redacción RA'!I$3:I$15,'Paso 3 Redacción RA'!C$3:C$15,,0,1) -> SaberHacer | B36: Ejecuta acciones de gestión de equipos y procesos, para tomar decisiones informadas que promuevan el liderazgo colaborativo en escenarios organizacionales.
A37: =_xlfn.XLOOKUP(B37,'Paso 3 Redacción RA'!I$3:I$15,'Paso 3 Redacción RA'!C$3:C$15,,0,1) -> Saber | B37: Analiza los principios económicos y sociales, así como la normatividad empresarial para determinar rutas estratégicas de acción y procesos asociados a la gestión, según el funcionamiento de los entornos internos y externos que operan en los contextos organizacionales. | C37: 3 | D37: Teoría de las Organizaciones | E37: Reconoce la evolución de las organizaciones y las escuelas del pensamiento administrativo, para identificar las transformaciones que han dado lugar a las tendencias contemporáneas en la administración de negocios. | F37: TP | H37: X | J37: 3 | K37: =J37*16 -> 48 | L37: =32*J37 -> 96 | M37: =SUM(K37:L37) -> 144 | N37: 1. Relación conceptos de administración, organización y teorías administrativas 2. Marco temporal de la teoría administrativa: un enfoque neoclásico 3. Teorías contemporáneas y su impacto en la organización 4. Nuevas tendencias y teorías administrativas un enfoque internacional | O37: Las estrategias pueden variar entre estas u otras: Trabajo directo Clase magistral activa/Análisis o Estudio de casos/Resolución de problemas/Talleres prácticos Trabajo independiente Lecturas relacionadas o de materiales complementarios/Resolución de problemas/Ejercicios aplicados/Desarrollo de proyectos/Talleres grupales o individuales/Análisis o Estudio de casos/Elaboración de informes o documentos técnicos | P37: Las actividades varían entre las siguientes y otras que pueda considerar el profesor y funcionan como formativas o sumativas, según sea el caso. Estudio de casos Resolución de problemas Desarrollo de proyectos Talleres Exposiciones Pruebas escritas | Q37: Las acciones de retroalimentación giran en torno a las siguientes. Formar: donde se crean las condiciones para que los estudiantes adquieran conocimientos, habilidades, actitudes, aptitudes y destrezas. Además, debe promover su desarrollo integral y debe acompañarlos en las situaciones académicas que enfrenten durante el desarrollo de un módulo o una asignatura. Informar: para que los estudiantes identifiquen los cambios que pueden afectarlos directa o indirectamente tanto en el aula de clase como en otros espacios. Prevenir: con el fin de anticiparse a las situaciones académicas que pueden representar dificultad para los estudiantes. Esto se logra a través de la interacción individual con los estudiantes y del completo conocimiento del contexto educativo en que el tutor se desenvuelve. Ayudar a decidir: donde se orienta a los estudiantes para que tomen la mejor decisión ante una situación concreta. El objetivo es que el estudiante fortalezca su autonomía y la toma de decisiones responsable.
A38: =_xlfn.XLOOKUP(B38,'Paso 3 Redacción RA'!I$3:I$15,'Paso 3 Redacción RA'!C$3:C$15,,0,1) -> Saber | B38: Reconoce las habilidades poderosas o socioemocionales que intervienen en escenarios organizacionales y en las relaciones humanas, para determinar aquellas que son pertinentes en el abordaje de situaciones propias de los distintos ámbitos de la gestión empresarial.
A39: =_xlfn.XLOOKUP(B39,'Paso 3 Redacción RA'!I$3:I$15,'Paso 3 Redacción RA'!C$3:C$15,,0,1) -> SaberSer | B39: Integra criterios económicos, sociales y jurídicos que apoyen la toma de decisiones, para contribuir a la generación de valor y al desarrollo organizacional, considerando principios de sostenibilidad, así como las dinámicas y necesidades del entorno.
A40: =_xlfn.XLOOKUP(B40,'Paso 3 Redacción RA'!I$3:I$15,'Paso 3 Redacción RA'!C$3:C$15,,0,1) -> Saber | B40: Analiza los principios económicos y sociales, así como la normatividad empresarial para determinar rutas estratégicas de acción y procesos asociados a la gestión, según el funcionamiento de los entornos internos y externos que operan en los contextos organizacionales. | C40: 3 | D40: Microeconomía | E40: Calcula el equilibrio de mercado a partir de los cambios generados en la oferta y la demanda y su implicación en los agentes económicos individuales familias y empresas para soportar la toma de decisiones. | F40: TP | H40: X | J40: 3 | K40: =J40*16 -> 48 | L40: =32*J40 -> 96 | M40: =SUM(K40:L40) -> 144 | N40: 1. Conceptos básicos de la ciencia económica. Frontera de posibilidades de producción y circuito económico 2. Análisis microeconómico, funciones, demanda y oferta 3. Estudio de la conducta del consumidor y del productor 4. Análisis de los costos de producción y de los mercados de competencia perfecta e imperfecta | O40: Las estrategias pueden variar entre estas u otras: Trabajo directo Clase magistral activa/Análisis o Estudio de casos/Resolución de problemas/Talleres prácticos Trabajo independiente Lecturas relacionadas o de materiales complementarios/Resolución de problemas/Ejercicios aplicados/Desarrollo de proyectos/Talleres grupales o individuales/Análisis o Estudio de casos/Elaboración de informes o documentos técnicos | P40: Las actividades varían entre las siguientes y otras que pueda considerar el profesor y funcionan como formativas o sumativas, según sea el caso. Estudio de casos Resolución de problemas Desarrollo de proyectos Talleres Exposiciones Pruebas escritas | Q40: Las acciones de retroalimentación giran en torno a las siguientes. Formar: donde se crean las condiciones para que los estudiantes adquieran conocimientos, habilidades, actitudes, aptitudes y destrezas. Además, debe promover su desarrollo integral y debe acompañarlos en las situaciones académicas que enfrenten durante el desarrollo de un módulo o una asignatura. Informar: para que los estudiantes identifiquen los cambios que pueden afectarlos directa o indirectamente tanto en el aula de clase como en otros espacios. Prevenir: con el fin de anticiparse a las situaciones académicas que pueden representar dificultad para los estudiantes. Esto se logra a través de la interacción individual con los estudiantes y del completo conocimiento del contexto educativo en que el tutor se desenvuelve. Ayudar a decidir: donde se orienta a los estudiantes para que tomen la mejor decisión ante una situación concreta. El objetivo es que el estudiante fortalezca su autonomía y la toma de decisiones responsable.
A41: =_xlfn.XLOOKUP(B41,'Paso 3 Redacción RA'!I$3:I$15,'Paso 3 Redacción RA'!C$3:C$15,,0,1) -> SaberHacer | B41: Diseña estrategias empresariales para estructurar propuestas de mejora orientadas al fortalecimiento de la competitividad empresarial y al desarrollo de iniciativas de emprendimiento e intraemprendimiento.
A42: =_xlfn.XLOOKUP(B42,'Paso 3 Redacción RA'!I$3:I$15,'Paso 3 Redacción RA'!C$3:C$15,,0,1) -> Saber | B42: Reconoce distintos modelos de negocio y de innovación aplicables tanto a intraemprendimientos como a nuevos negocios, para seleccionar el más adecuado en el diseño de propuestas empresariales sostenibles y coherentes con el entorno.
A43: =_xlfn.XLOOKUP(B43,'Paso 3 Redacción RA'!I$3:I$15,'Paso 3 Redacción RA'!C$3:C$15,,0,1) -> Saber | B43: Analiza los principios económicos y sociales, así como la normatividad empresarial para determinar rutas estratégicas de acción y procesos asociados a la gestión, según el funcionamiento de los entornos internos y externos que operan en los contextos organizacionales. | C43: 3 | D43: Matemáticas Financieras | E43: Aplica conceptos de costo de dinero en el tiempo para estimar valores presentes y futuros de inversiones y créditos, y elaboración de tablas de amortización. | F43: TP | H43: X | J43: 3 | K43: =J43*16 -> 48 | L43: =32*J43 -> 96 | M43: =SUM(K43:L43) -> 144 | N43: 1. Interés simple, descuento simple e interés compuesto 2. Series uniformes 3. Series variables 4. Sistemas de amortización y de capitalización | O43: Las estrategias pueden variar entre estas u otras: Trabajo directo Clase magistral activa/Análisis o Estudio de casos/Resolución de problemas/Talleres prácticos Trabajo independiente Lecturas relacionadas o de materiales complementarios/Resolución de problemas/Ejercicios aplicados/Desarrollo de proyectos/Talleres grupales o individuales/Análisis o Estudio de casos/Elaboración de informes o documentos técnicos | P43: Las actividades varían entre las siguientes y otras que pueda considerar el profesor y funcionan como formativas o sumativas, según sea el caso. Estudio de casos Resolución de problemas Desarrollo de proyectos Talleres Exposiciones Pruebas escritas | Q43: Las acciones de retroalimentación giran en torno a las siguientes. Formar: donde se crean las condiciones para que los estudiantes adquieran conocimientos, habilidades, actitudes, aptitudes y destrezas. Además, debe promover su desarrollo integral y debe acompañarlos en las situaciones académicas que enfrenten durante el desarrollo de un módulo o una asignatura. Informar: para que los estudiantes identifiquen los cambios que pueden afectarlos directa o indirectamente tanto en el aula de clase como en otros espacios. Prevenir: con el fin de anticiparse a las situaciones académicas que pueden representar dificultad para los estudiantes. Esto se logra a través de la interacción individual con los estudiantes y del completo conocimiento del contexto educativo en que el tutor se desenvuelve. Ayudar a decidir: donde se orienta a los estudiantes para que tomen la mejor decisión ante una situación concreta. El objetivo es que el estudiante fortalezca su autonomía y la toma de decisiones responsable.
A44: =_xlfn.XLOOKUP(B44,'Paso 3 Redacción RA'!I$3:I$15,'Paso 3 Redacción RA'!C$3:C$15,,0,1) -> SaberHacer | B44: Ejecuta acciones de gestión de equipos y procesos, para tomar decisiones informadas que promuevan el liderazgo colaborativo en escenarios organizacionales.
A45: =_xlfn.XLOOKUP(B45,'Paso 3 Redacción RA'!I$3:I$15,'Paso 3 Redacción RA'!C$3:C$15,,0,1) -> SaberSer | B45: Integra criterios económicos, sociales y jurídicos que apoyen la toma de decisiones, para contribuir a la generación de valor y al desarrollo organizacional, considerando principios de sostenibilidad, así como las dinámicas y necesidades del entorno. | R45: =SUM(J32:J45) -> 18 | S45: =COUNTA(D32:D45) -> 6
A46: =_xlfn.XLOOKUP(B46,'Paso 3 Redacción RA'!I$3:I$15,'Paso 3 Redacción RA'!C$3:C$15,,0,1) -> Saber | B46: Identifica fenómenos contemporáneos y su relación con la profesión, para determinar sus impactos e influencia en la sociedad, de forma responsable y crítica. | C46: 4 | D46: Desarrollo Sostenible | E46: Identifica ejemplos de problemas ambientales, sociales y económicos en la sociedad contemporánea para analizar sus causas y efectos desde el enfoque del desarrollo sostenible a escala local y global. Compara enfoques y aproximaciones tanto privados como público/colectivos desde la sostenibilidad y otras visiones alternativas para proponer ideas de solución que respondan a los desafíos contemporáneos. | F46: TP | G46: X | J46: 3 | K46: =16*J46 -> 48 | L46: =32*J46 -> 96 | M46: =SUM(K46:L46) -> 144 | N46: 1. Análisis de la Era del Antropoceno 2. Otras Alternativas al Desarrollo Sostenible 3. Ciudadanía y Políticas Públicas para el Desarrollo Sostenible 4. El aporte de Negocios para la Búsqueda del Desarrollo Sostenible | O46: Trabajo directo: Encuentros sincrónicos Mensajería interna Anuncios Trabajo independiente: Lecturas fundamentales y complementarias Material de trabajo Participación en foros | P46: Las actividades pueden variar entre estas u otras: Formativas Resolución de problemas/Talleres/Representaciones gráficas o visuales (mapas conceptuales, infografías, presentaciones, entre otros) Sumativas Pruebas escritas/Proyectos aplicados/Estudios de caso/Simulaciones y modelado de procesos/Informes técnicos/Presentaciones orales o defensa de propuestas | Q46: Las acciones de retroalimentación giran en torno a las siguientes. Formar: donde se crean las condiciones para que los estudiantes adquieran conocimientos, habilidades, actitudes, aptitudes y destrezas. Además, debe promover su desarrollo integral y debe acompañarlos en las situaciones académicas que enfrenten durante el desarrollo de un módulo o una asignatura. Informar: para que los estudiantes identifiquen los cambios que pueden afectarlos directa o indirectamente tanto en el aula de clase como en otros espacios. Prevenir: con el fin de anticiparse a las situaciones académicas que pueden representar dificultad para los estudiantes. Esto se logra a través de la interacción individual con los estudiantes y del completo conocimiento del contexto educativo en que el tutor se desenvuelve. Ayudar a decidir: donde se orienta a los estudiantes para que tomen la mejor decisión ante una situación concreta. El objetivo es que el estudiante fortalezca su autonomía y la toma de decisiones responsable.
A47: =_xlfn.XLOOKUP(B47,'Paso 3 Redacción RA'!I$3:I$15,'Paso 3 Redacción RA'!C$3:C$15,,0,1) -> Saber | B47: Analiza los principios económicos y sociales, así como la normatividad empresarial para determinar rutas estratégicas de acción y procesos asociados a la gestión, según el funcionamiento de los entornos internos y externos que operan en los contextos organizacionales. | C47: 4 | D47: Análisis Estratégico | E47: Realiza un diagnóstico del macro y micro entorno de una organización, utilizando herramientas estratégicas, para formular estrategias que respondan a las oportunidades y amenazas del mercado y fortalezcan su ventaja competitiva, dependiendo de la realidad específica de la organización. | F47: TP | H47: X | J47: 3 | K47: =J47*16 -> 48 | L47: =32*J47 -> 96 | M47: =SUM(K47:L47) -> 144 | N47: 1. Administración estratégica 2. Matrices de insumos 3. Matrices de Adecuación y decisión 4. Formulación de estrategias | O47: Las estrategias pueden variar entre estas u otras: Trabajo directo Clase magistral activa/Análisis o Estudio de casos/Resolución de problemas/Talleres prácticos Trabajo independiente Lecturas relacionadas o de materiales complementarios/Resolución de problemas/Ejercicios aplicados/Desarrollo de proyectos/Talleres grupales o individuales/Análisis o Estudio de casos/Elaboración de informes o documentos técnicos | P47: Las actividades varían entre las siguientes y otras que pueda considerar el profesor y funcionan como formativas o sumativas, según sea el caso. Estudio de casos Resolución de problemas Desarrollo de proyectos Talleres Exposiciones Pruebas escritas | Q47: Las acciones de retroalimentación giran en torno a las siguientes. Formar: donde se crean las condiciones para que los estudiantes adquieran conocimientos, habilidades, actitudes, aptitudes y destrezas. Además, debe promover su desarrollo integral y debe acompañarlos en las situaciones académicas que enfrenten durante el desarrollo de un módulo o una asignatura. Informar: para que los estudiantes identifiquen los cambios que pueden afectarlos directa o indirectamente tanto en el aula de clase como en otros espacios. Prevenir: con el fin de anticiparse a las situaciones académicas que pueden representar dificultad para los estudiantes. Esto se logra a través de la interacción individual con los estudiantes y del completo conocimiento del contexto educativo en que el tutor se desenvuelve. Ayudar a decidir: donde se orienta a los estudiantes para que tomen la mejor decisión ante una situación concreta. El objetivo es que el estudiante fortalezca su autonomía y la toma de decisiones responsable.
A48: =_xlfn.XLOOKUP(B48,'Paso 3 Redacción RA'!I$3:I$15,'Paso 3 Redacción RA'!C$3:C$15,,0,1) -> Saber | B48: Reconoce las habilidades poderosas o socioemocionales que intervienen en escenarios organizacionales y en las relaciones humanas, para determinar aquellas que son pertinentes en el abordaje de situaciones propias de los distintos ámbitos de la gestión empresarial.
A49: =_xlfn.XLOOKUP(B49,'Paso 3 Redacción RA'!I$3:I$15,'Paso 3 Redacción RA'!C$3:C$15,,0,1) -> SaberHacer | B49: Ejecuta acciones de gestión de equipos y procesos, para tomar decisiones informadas que promuevan el liderazgo colaborativo en escenarios organizacionales.
A50: =_xlfn.XLOOKUP(B50,'Paso 3 Redacción RA'!I$3:I$15,'Paso 3 Redacción RA'!C$3:C$15,,0,1) -> SaberHacer | B50: Diseña estrategias empresariales para estructurar propuestas de mejora orientadas al fortalecimiento de la competitividad empresarial y al desarrollo de iniciativas de emprendimiento e intraemprendimiento.
A51: =_xlfn.XLOOKUP(B51,'Paso 3 Redacción RA'!I$3:I$15,'Paso 3 Redacción RA'!C$3:C$15,,0,1) -> Saber | B51: Analiza los principios económicos y sociales, así como la normatividad empresarial para determinar rutas estratégicas de acción y procesos asociados a la gestión, según el funcionamiento de los entornos internos y externos que operan en los contextos organizacionales. | C51: 4 | D51: Taller Financiero Aplicado a BI | E51: Utiliza la minería de datos, visualización de datos y tableros de control para realizar reportes financieros que permiten orientar la tomar decisiones y eliminar las ineficiencias basadas en una visión integral en los datos. | F51: TP | H51: X | J51: 4 | K51: =J51*16 -> 64 | L51: =32*J51 -> 128 | M51: =SUM(K51:L51) -> 192 | N51: 1. Principales Herramientas de Matemáticas Financieras 2. Diagnóstico Financiero y análisis de la información 3. Introducción a herramientas BI 4. Análisis de información financiera con herramientas BI | O51: Las estrategias pueden variar entre estas u otras: Trabajo directo Clase magistral activa/Análisis o Estudio de casos/Resolución de problemas/Talleres prácticos Trabajo independiente Lecturas relacionadas o de materiales complementarios/Resolución de problemas/Ejercicios aplicados/Desarrollo de proyectos/Talleres grupales o individuales/Análisis o Estudio de casos/Elaboración de informes o documentos técnicos | P51: Las actividades varían entre las siguientes y otras que pueda considerar el profesor y funcionan como formativas o sumativas, según sea el caso. Estudio de casos Resolución de problemas Desarrollo de proyectos Talleres Exposiciones Pruebas escritas | Q51: Las acciones de retroalimentación giran en torno a las siguientes. Formar: donde se crean las condiciones para que los estudiantes adquieran conocimientos, habilidades, actitudes, aptitudes y destrezas. Además, debe promover su desarrollo integral y debe acompañarlos en las situaciones académicas que enfrenten durante el desarrollo de un módulo o una asignatura. Informar: para que los estudiantes identifiquen los cambios que pueden afectarlos directa o indirectamente tanto en el aula de clase como en otros espacios. Prevenir: con el fin de anticiparse a las situaciones académicas que pueden representar dificultad para los estudiantes. Esto se logra a través de la interacción individual con los estudiantes y del completo conocimiento del contexto educativo en que el tutor se desenvuelve. Ayudar a decidir: donde se orienta a los estudiantes para que tomen la mejor decisión ante una situación concreta. El objetivo es que el estudiante fortalezca su autonomía y la toma de decisiones responsable.
A52: =_xlfn.XLOOKUP(B52,'Paso 3 Redacción RA'!I$3:I$15,'Paso 3 Redacción RA'!C$3:C$15,,0,1) -> SaberHacer | B52: Ejecuta acciones de gestión de equipos y procesos, para tomar decisiones informadas que promuevan el liderazgo colaborativo en escenarios organizacionales.
A53: =_xlfn.XLOOKUP(B53,'Paso 3 Redacción RA'!I$3:I$15,'Paso 3 Redacción RA'!C$3:C$15,,0,1) -> SaberHacer | B53: Diseña estrategias empresariales para estructurar propuestas de mejora orientadas al fortalecimiento de la competitividad empresarial y al desarrollo de iniciativas de emprendimiento e intraemprendimiento.
A54: =_xlfn.XLOOKUP(B54,'Paso 3 Redacción RA'!I$3:I$15,'Paso 3 Redacción RA'!C$3:C$15,,0,1) -> Saber | B54: Reconoce distintos modelos de negocio y de innovación aplicables tanto a intraemprendimientos como a nuevos negocios, para seleccionar el más adecuado en el diseño de propuestas empresariales sostenibles y coherentes con el entorno.
A55: =_xlfn.XLOOKUP(B55,'Paso 3 Redacción RA'!I$3:I$15,'Paso 3 Redacción RA'!C$3:C$15,,0,1) -> Saber | B55: Analiza los principios económicos y sociales, así como la normatividad empresarial para determinar rutas estratégicas de acción y procesos asociados a la gestión, según el funcionamiento de los entornos internos y externos que operan en los contextos organizacionales. | C55: 4 | D55: Estadística Predictiva | E55: Aplica conceptos de distribuciones muestrales, intervalos de confianza, pruebas de hipótesis y modelos de regresión lineal para estimar parámetros poblacionales orientados a la predicción del comportamiento de una variable en diferentes escenarios. | F55: TP | H55: X | J55: 3 | K55: =J55*16 -> 48 | L55: =32*J55 -> 96 | M55: =SUM(K55:L55) -> 144 | N55: 1. Muestreo y distribuciones muestrales 2. Teoría de la estimación. Estimación de parámetros 3. Pruebas de hipótesis 4. Regresión lineal simple | O55: Las estrategias pueden variar entre estas u otras: Trabajo directo Clase magistral activa/Análisis o Estudio de casos/Resolución de problemas/Talleres prácticos Trabajo independiente Lecturas relacionadas o de materiales complementarios/Resolución de problemas/Ejercicios aplicados/Desarrollo de proyectos/Talleres grupales o individuales/Análisis o Estudio de casos/Elaboración de informes o documentos técnicos | P55: Las actividades varían entre las siguientes y otras que pueda considerar el profesor y funcionan como formativas o sumativas, según sea el caso. Estudio de casos Resolución de problemas Desarrollo de proyectos Talleres Exposiciones Pruebas escritas | Q55: Las acciones de retroalimentación giran en torno a las siguientes. Formar: donde se crean las condiciones para que los estudiantes adquieran conocimientos, habilidades, actitudes, aptitudes y destrezas. Además, debe promover su desarrollo integral y debe acompañarlos en las situaciones académicas que enfrenten durante el desarrollo de un módulo o una asignatura. Informar: para que los estudiantes identifiquen los cambios que pueden afectarlos directa o indirectamente tanto en el aula de clase como en otros espacios. Prevenir: con el fin de anticiparse a las situaciones académicas que pueden representar dificultad para los estudiantes. Esto se logra a través de la interacción individual con los estudiantes y del completo conocimiento del contexto educativo en que el tutor se desenvuelve. Ayudar a decidir: donde se orienta a los estudiantes para que tomen la mejor decisión ante una situación concreta. El objetivo es que el estudiante fortalezca su autonomía y la toma de decisiones responsable.
A56: =_xlfn.XLOOKUP(B56,'Paso 3 Redacción RA'!I$3:I$15,'Paso 3 Redacción RA'!C$3:C$15,,0,1) -> Saber | B56: Reconoce distintos modelos de negocio y de innovación aplicables tanto a intraemprendimientos como a nuevos negocios, para seleccionar el más adecuado en el diseño de propuestas empresariales sostenibles y coherentes con el entorno.
A57: =_xlfn.XLOOKUP(B57,'Paso 3 Redacción RA'!I$3:I$15,'Paso 3 Redacción RA'!C$3:C$15,,0,1) -> SaberSer | B57: Integra criterios económicos, sociales y jurídicos que apoyen la toma de decisiones, para contribuir a la generación de valor y al desarrollo organizacional, considerando principios de sostenibilidad, así como las dinámicas y necesidades del entorno.
A58: =_xlfn.XLOOKUP(B58,'Paso 3 Redacción RA'!I$3:I$15,'Paso 3 Redacción RA'!C$3:C$15,,0,1) -> Saber | B58: Analiza los principios económicos y sociales, así como la normatividad empresarial para determinar rutas estratégicas de acción y procesos asociados a la gestión, según el funcionamiento de los entornos internos y externos que operan en los contextos organizacionales. | C58: 4 | D58: Macroeconomía | E58: Interpreta las variables macroeconómicas y su impacto en el equilibrio, para desarrollar análisis del comportamiento del mercado de bienes y servicios y de las políticas fiscal, monetaria y cambiaria. | F58: TP | H58: X | J58: 3 | K58: =J58*16 -> 48 | L58: =32*J58 -> 96 | M58: =SUM(K58:L58) -> 144 | N58: 1. Generalidades de la macroeconomía, funcionamiento del sistema económico y de las cuentas nacionales 2. Mercado de bienes y servicios y estabilidad macroeconómica 3. Modelo IS-LM 4. La balanza de pagos y el equilibrio general | O58: Las estrategias pueden variar entre estas u otras: Trabajo directo Clase magistral activa/Análisis o Estudio de casos/Resolución de problemas/Talleres prácticos Trabajo independiente Lecturas relacionadas o de materiales complementarios/Resolución de problemas/Ejercicios aplicados/Desarrollo de proyectos/Talleres grupales o individuales/Análisis o Estudio de casos/Elaboración de informes o documentos técnicos | P58: Las actividades varían entre las siguientes y otras que pueda considerar el profesor y funcionan como formativas o sumativas, según sea el caso. Estudio de casos Resolución de problemas Desarrollo de proyectos Talleres Exposiciones Pruebas escritas | Q58: Las acciones de retroalimentación giran en torno a las siguientes. Formar: donde se crean las condiciones para que los estudiantes adquieran conocimientos, habilidades, actitudes, aptitudes y destrezas. Además, debe promover su desarrollo integral y debe acompañarlos en las situaciones académicas que enfrenten durante el desarrollo de un módulo o una asignatura. Informar: para que los estudiantes identifiquen los cambios que pueden afectarlos directa o indirectamente tanto en el aula de clase como en otros espacios. Prevenir: con el fin de anticiparse a las situaciones académicas que pueden representar dificultad para los estudiantes. Esto se logra a través de la interacción individual con los estudiantes y del completo conocimiento del contexto educativo en que el tutor se desenvuelve. Ayudar a decidir: donde se orienta a los estudiantes para que tomen la mejor decisión ante una situación concreta. El objetivo es que el estudiante fortalezca su autonomía y la toma de decisiones responsable.
A59: =_xlfn.XLOOKUP(B59,'Paso 3 Redacción RA'!I$3:I$15,'Paso 3 Redacción RA'!C$3:C$15,,0,1) -> SaberHacer | B59: Diseña estrategias empresariales para estructurar propuestas de mejora orientadas al fortalecimiento de la competitividad empresarial y al desarrollo de iniciativas de emprendimiento e intraemprendimiento.
A60: =_xlfn.XLOOKUP(B60,'Paso 3 Redacción RA'!I$3:I$15,'Paso 3 Redacción RA'!C$3:C$15,,0,1) -> SaberSer | B60: Integra criterios económicos, sociales y jurídicos que apoyen la toma de decisiones, para contribuir a la generación de valor y al desarrollo organizacional, considerando principios de sostenibilidad, así como las dinámicas y necesidades del entorno. | R60: =SUM(J46:J60) -> 16 | S60: =COUNTA(D46:D60) -> 5
A61: =_xlfn.XLOOKUP(B61,'Paso 3 Redacción RA'!I$3:I$15,'Paso 3 Redacción RA'!C$3:C$15,,0,1) -> Saber | B61: Analiza los principios económicos y sociales, así como la normatividad empresarial para determinar rutas estratégicas de acción y procesos asociados a la gestión, según el funcionamiento de los entornos internos y externos que operan en los contextos organizacionales. | C61: 5 | D61: Gerencia Estratégica de Proyectos en Cascada | E61: Aplica conceptos, buenas prácticas y herramientas de la gestión de proyectos en cascada, para estructurar proyectos alineados con los objetivos del alcance definido, teniendo en cuenta las partes interesadas. Determina las restricciones de cronograma, costo y alcance en escenarios reales o simulados, para desarrollar propuestas ejecutables que atiendan el manejo adecuado de recursos y los requerimientos de las partes interesadas. | F61: TP | H61: X | J61: 3 | K61: =J61*16 -> 48 | L61: =32*J61 -> 96 | M61: =SUM(K61:L61) -> 144 | N61: 1. Contexto Organizacional 2. Fundamentos de la gestión de proyectos 3. Gestión de la Integración y Alcance del proyecto 4. Gestión del cronograma y presupuesto del proyecto | O61: Las estrategias pueden variar entre estas u otras: Trabajo directo Clase magistral activa/Análisis o Estudio de casos/Resolución de problemas/Talleres prácticos Trabajo independiente Lecturas relacionadas o de materiales complementarios/Resolución de problemas/Ejercicios aplicados/Desarrollo de proyectos/Talleres grupales o individuales/Análisis o Estudio de casos/Elaboración de informes o documentos técnicos | P61: Las actividades varían entre las siguientes y otras que pueda considerar el profesor y funcionan como formativas o sumativas, según sea el caso. Estudio de casos Resolución de problemas Desarrollo de proyectos Talleres Exposiciones Pruebas escritas | Q61: Las acciones de retroalimentación giran en torno a las siguientes. Formar: donde se crean las condiciones para que los estudiantes adquieran conocimientos, habilidades, actitudes, aptitudes y destrezas. Además, debe promover su desarrollo integral y debe acompañarlos en las situaciones académicas que enfrenten durante el desarrollo de un módulo o una asignatura. Informar: para que los estudiantes identifiquen los cambios que pueden afectarlos directa o indirectamente tanto en el aula de clase como en otros espacios. Prevenir: con el fin de anticiparse a las situaciones académicas que pueden representar dificultad para los estudiantes. Esto se logra a través de la interacción individual con los estudiantes y del completo conocimiento del contexto educativo en que el tutor se desenvuelve. Ayudar a decidir: donde se orienta a los estudiantes para que tomen la mejor decisión ante una situación concreta. El objetivo es que el estudiante fortalezca su autonomía y la toma de decisiones responsable.
A62: =_xlfn.XLOOKUP(B62,'Paso 3 Redacción RA'!I$3:I$15,'Paso 3 Redacción RA'!C$3:C$15,,0,1) -> SaberHacer | B62: Diseña estrategias empresariales para estructurar propuestas de mejora orientadas al fortalecimiento de la competitividad empresarial y al desarrollo de iniciativas de emprendimiento e intraemprendimiento.
A63: =_xlfn.XLOOKUP(B63,'Paso 3 Redacción RA'!I$3:I$15,'Paso 3 Redacción RA'!C$3:C$15,,0,1) -> SaberSer | B63: Integra criterios económicos, sociales y jurídicos que apoyen la toma de decisiones, para contribuir a la generación de valor y al desarrollo organizacional, considerando principios de sostenibilidad, así como las dinámicas y necesidades del entorno.
A64: =_xlfn.XLOOKUP(B64,'Paso 3 Redacción RA'!I$3:I$15,'Paso 3 Redacción RA'!C$3:C$15,,0,1) -> Saber | B64: Analiza los principios económicos y sociales, así como la normatividad empresarial para determinar rutas estratégicas de acción y procesos asociados a la gestión, según el funcionamiento de los entornos internos y externos que operan en los contextos organizacionales. | C64: 5 | D64: Gestión Estratégica | E64: Reconoce los conceptos asociados a la formulación de objetivos, indicadores, metas y planes de acción para formular estrategias en contextos relacionados con estructuras organizacionales y procesos internos de las empresas. | F64: TP | H64: X | J64: 3 | K64: =J64*16 -> 48 | L64: =32*J64 -> 96 | M64: =SUM(K64:L64) -> 144 | N64: 1. Cuadro De Mando Integral 2. Medición De La Gestión 3. Control Y Seguimiento 4. Gestión De Riesgos | O64: Las estrategias pueden variar entre estas u otras: Trabajo directo Clase magistral activa/Análisis o Estudio de casos/Resolución de problemas/Talleres prácticos Trabajo independiente Lecturas relacionadas o de materiales complementarios/Resolución de problemas/Ejercicios aplicados/Desarrollo de proyectos/Talleres grupales o individuales/Análisis o Estudio de casos/Elaboración de informes o documentos técnicos | P64: Las actividades varían entre las siguientes y otras que pueda considerar el profesor y funcionan como formativas o sumativas, según sea el caso. Estudio de casos Resolución de problemas Desarrollo de proyectos Talleres Exposiciones Pruebas escritas | Q64: Las acciones de retroalimentación giran en torno a las siguientes. Formar: donde se crean las condiciones para que los estudiantes adquieran conocimientos, habilidades, actitudes, aptitudes y destrezas. Además, debe promover su desarrollo integral y debe acompañarlos en las situaciones académicas que enfrenten durante el desarrollo de un módulo o una asignatura. Informar: para que los estudiantes identifiquen los cambios que pueden afectarlos directa o indirectamente tanto en el aula de clase como en otros espacios. Prevenir: con el fin de anticiparse a las situaciones académicas que pueden representar dificultad para los estudiantes. Esto se logra a través de la interacción individual con los estudiantes y del completo conocimiento del contexto educativo en que el tutor se desenvuelve. Ayudar a decidir: donde se orienta a los estudiantes para que tomen la mejor decisión ante una situación concreta. El objetivo es que el estudiante fortalezca su autonomía y la toma de decisiones responsable.
A65: =_xlfn.XLOOKUP(B65,'Paso 3 Redacción RA'!I$3:I$15,'Paso 3 Redacción RA'!C$3:C$15,,0,1) -> SaberHacer | B65: Ejecuta acciones de gestión de equipos y procesos, para tomar decisiones informadas que promuevan el liderazgo colaborativo en escenarios organizacionales.
A66: =_xlfn.XLOOKUP(B66,'Paso 3 Redacción RA'!I$3:I$15,'Paso 3 Redacción RA'!C$3:C$15,,0,1) -> Saber | B66: Reconoce las habilidades poderosas o socioemocionales que intervienen en escenarios organizacionales y en las relaciones humanas, para determinar aquellas que son pertinentes en el abordaje de situaciones propias de los distintos ámbitos de la gestión empresarial.
A67: =_xlfn.XLOOKUP(B67,'Paso 3 Redacción RA'!I$3:I$15,'Paso 3 Redacción RA'!C$3:C$15,,0,1) -> SaberHacer | B67: Diseña estrategias empresariales para estructurar propuestas de mejora orientadas al fortalecimiento de la competitividad empresarial y al desarrollo de iniciativas de emprendimiento e intraemprendimiento.
A68: =_xlfn.XLOOKUP(B68,'Paso 3 Redacción RA'!I$3:I$15,'Paso 3 Redacción RA'!C$3:C$15,,0,1) -> SaberSer | B68: Integra criterios económicos, sociales y jurídicos que apoyen la toma de decisiones, para contribuir a la generación de valor y al desarrollo organizacional, considerando principios de sostenibilidad, así como las dinámicas y necesidades del entorno.
A69: =_xlfn.XLOOKUP(B69,'Paso 3 Redacción RA'!I$3:I$15,'Paso 3 Redacción RA'!C$3:C$15,,0,1) -> Saber | B69: Analiza los principios económicos y sociales, así como la normatividad empresarial para determinar rutas estratégicas de acción y procesos asociados a la gestión, según el funcionamiento de los entornos internos y externos que operan en los contextos organizacionales. | C69: 5 | D69: Gerencia Financiera | E69: Analiza los inductores de valor, incluyendo el Valor Económico Agregado (EVA), para diseñar estrategias financieras que contribuyan a la creación de valor en la gestión financiera de la organización. | F69: TP | H69: X | J69: 3 | K69: =J69*16 -> 48 | L69: =32*J69 -> 96 | M69: =SUM(K69:L69) -> 144 | N69: 1. Conceptos básicos de la Gerencia Financiera 2. Gerencia del valor 3. Estructura financiera y costo de capital 4. Prospección financiera | O69: Las estrategias pueden variar entre estas u otras: Trabajo directo Clase magistral activa/Análisis o Estudio de casos/Resolución de problemas/Talleres prácticos Trabajo independiente Lecturas relacionadas o de materiales complementarios/Resolución de problemas/Ejercicios aplicados/Desarrollo de proyectos/Talleres grupales o individuales/Análisis o Estudio de casos/Elaboración de informes o documentos técnicos | P69: Las actividades varían entre las siguientes y otras que pueda considerar el profesor y funcionan como formativas o sumativas, según sea el caso. Estudio de casos Resolución de problemas Desarrollo de proyectos Talleres Exposiciones Pruebas escritas | Q69: Las acciones de retroalimentación giran en torno a las siguientes. Formar: donde se crean las condiciones para que los estudiantes adquieran conocimientos, habilidades, actitudes, aptitudes y destrezas. Además, debe promover su desarrollo integral y debe acompañarlos en las situaciones académicas que enfrenten durante el desarrollo de un módulo o una asignatura. Informar: para que los estudiantes identifiquen los cambios que pueden afectarlos directa o indirectamente tanto en el aula de clase como en otros espacios. Prevenir: con el fin de anticiparse a las situaciones académicas que pueden representar dificultad para los estudiantes. Esto se logra a través de la interacción individual con los estudiantes y del completo conocimiento del contexto educativo en que el tutor se desenvuelve. Ayudar a decidir: donde se orienta a los estudiantes para que tomen la mejor decisión ante una situación concreta. El objetivo es que el estudiante fortalezca su autonomía y la toma de decisiones responsable.
A70: =_xlfn.XLOOKUP(B70,'Paso 3 Redacción RA'!I$3:I$15,'Paso 3 Redacción RA'!C$3:C$15,,0,1) -> SaberSer | B70: Integra criterios económicos, sociales y jurídicos que apoyen la toma de decisiones, para contribuir a la generación de valor y al desarrollo organizacional, considerando principios de sostenibilidad, así como las dinámicas y necesidades del entorno.
A71: =_xlfn.XLOOKUP(B71,'Paso 3 Redacción RA'!I$3:I$15,'Paso 3 Redacción RA'!C$3:C$15,,0,1) -> Saber | B71: Reconoce distintos modelos de negocio y de innovación aplicables tanto a intraemprendimientos como a nuevos negocios, para seleccionar el más adecuado en el diseño de propuestas empresariales sostenibles y coherentes con el entorno.
A72: =_xlfn.XLOOKUP(B72,'Paso 3 Redacción RA'!I$3:I$15,'Paso 3 Redacción RA'!C$3:C$15,,0,1) -> Saber | B72: Analiza los principios económicos y sociales, así como la normatividad empresarial para determinar rutas estratégicas de acción y procesos asociados a la gestión, según el funcionamiento de los entornos internos y externos que operan en los contextos organizacionales. | C72: 5 | D72: Gerencia de Desarrollo Sostenible | E72: Integra herramientas de gestión y estrategia desde el enfoque de triple cuenta de resultados, para aplicar principios de sostenibilidad en el diseño de propuestas empresariales. | F72: TP | H72: X | J72: 4 | K72: =J72*16 -> 64 | L72: =32*J72 -> 128 | M72: =SUM(K72:L72) -> 192 | N72: 1. Introducción a la sostenibilidad empresarial 2. Gerencia Ambiental 3. Creación de valor sostenible 4. Innovación empresarial en sostenibilidad | O72: Las estrategias pueden variar entre estas u otras: Trabajo directo Clase magistral activa/Análisis o Estudio de casos/Resolución de problemas/Talleres prácticos Trabajo independiente Lecturas relacionadas o de materiales complementarios/Resolución de problemas/Ejercicios aplicados/Desarrollo de proyectos/Talleres grupales o individuales/Análisis o Estudio de casos/Elaboración de informes o documentos técnicos | P72: Las actividades varían entre las siguientes y otras que pueda considerar el profesor y funcionan como formativas o sumativas, según sea el caso. Estudio de casos Resolución de problemas Desarrollo de proyectos Talleres Exposiciones Pruebas escritas | Q72: Las acciones de retroalimentación giran en torno a las siguientes. Formar: donde se crean las condiciones para que los estudiantes adquieran conocimientos, habilidades, actitudes, aptitudes y destrezas. Además, debe promover su desarrollo integral y debe acompañarlos en las situaciones académicas que enfrenten durante el desarrollo de un módulo o una asignatura. Informar: para que los estudiantes identifiquen los cambios que pueden afectarlos directa o indirectamente tanto en el aula de clase como en otros espacios. Prevenir: con el fin de anticiparse a las situaciones académicas que pueden representar dificultad para los estudiantes. Esto se logra a través de la interacción individual con los estudiantes y del completo conocimiento del contexto educativo en que el tutor se desenvuelve. Ayudar a decidir: donde se orienta a los estudiantes para que tomen la mejor decisión ante una situación concreta. El objetivo es que el estudiante fortalezca su autonomía y la toma de decisiones responsable.
A73: =_xlfn.XLOOKUP(B73,'Paso 3 Redacción RA'!I$3:I$15,'Paso 3 Redacción RA'!C$3:C$15,,0,1) -> SaberSer | B73: Integra criterios económicos, sociales y jurídicos que apoyen la toma de decisiones, para contribuir a la generación de valor y al desarrollo organizacional, considerando principios de sostenibilidad, así como las dinámicas y necesidades del entorno.
A74: =_xlfn.XLOOKUP(B74,'Paso 3 Redacción RA'!I$3:I$15,'Paso 3 Redacción RA'!C$3:C$15,,0,1) -> SaberHacer | B74: Ejecuta acciones de gestión de equipos y procesos, para tomar decisiones informadas que promuevan el liderazgo colaborativo en escenarios organizacionales.
A75: =_xlfn.XLOOKUP(B75,'Paso 3 Redacción RA'!I$3:I$15,'Paso 3 Redacción RA'!C$3:C$15,,0,1) -> Saber | B75: Reconoce distintos modelos de negocio y de innovación aplicables tanto a intraemprendimientos como a nuevos negocios, para seleccionar el más adecuado en el diseño de propuestas empresariales sostenibles y coherentes con el entorno.
A76: =_xlfn.XLOOKUP(B76,'Paso 3 Redacción RA'!I$3:I$15,'Paso 3 Redacción RA'!C$3:C$15,,0,1) -> Saber | B76: Analiza los principios económicos y sociales, así como la normatividad empresarial para determinar rutas estratégicas de acción y procesos asociados a la gestión, según el funcionamiento de los entornos internos y externos que operan en los contextos organizacionales. | C76: 5 | D76: Gerencia de Producción | E76: Aplica herramientas de pronóstico, planeación global y gestión de capacidad, para estructurar propuestas de mejora en procesos productivos. | F76: TP | H76: X | J76: 4 | K76: =J76*16 -> 64 | L76: =32*J76 -> 128 | M76: =SUM(K76:L76) -> 192 | N76: 1. Estrategias de producción 2. Gestión de la demanda - pronósticos 3. Planeación global de la producción 4. Planeación de la capacida | O76: Las estrategias pueden variar entre estas u otras: Trabajo directo Clase magistral activa/Análisis o Estudio de casos/Resolución de problemas/Talleres prácticos Trabajo independiente Lecturas relacionadas o de materiales complementarios/Resolución de problemas/Ejercicios aplicados/Desarrollo de proyectos/Talleres grupales o individuales/Análisis o Estudio de casos/Elaboración de informes o documentos técnicos | P76: Las actividades varían entre las siguientes y otras que pueda considerar el profesor y funcionan como formativas o sumativas, según sea el caso. Estudio de casos Resolución de problemas Desarrollo de proyectos Talleres Exposiciones Pruebas escritas | Q76: Las acciones de retroalimentación giran en torno a las siguientes. Formar: donde se crean las condiciones para que los estudiantes adquieran conocimientos, habilidades, actitudes, aptitudes y destrezas. Además, debe promover su desarrollo integral y debe acompañarlos en las situaciones académicas que enfrenten durante el desarrollo de un módulo o una asignatura. Informar: para que los estudiantes identifiquen los cambios que pueden afectarlos directa o indirectamente tanto en el aula de clase como en otros espacios. Prevenir: con el fin de anticiparse a las situaciones académicas que pueden representar dificultad para los estudiantes. Esto se logra a través de la interacción individual con los estudiantes y del completo conocimiento del contexto educativo en que el tutor se desenvuelve. Ayudar a decidir: donde se orienta a los estudiantes para que tomen la mejor decisión ante una situación concreta. El objetivo es que el estudiante fortalezca su autonomía y la toma de decisiones responsable.
A77: =_xlfn.XLOOKUP(B77,'Paso 3 Redacción RA'!I$3:I$15,'Paso 3 Redacción RA'!C$3:C$15,,0,1) -> SaberHacer | B77: Ejecuta acciones de gestión de equipos y procesos, para tomar decisiones informadas que promuevan el liderazgo colaborativo en escenarios organizacionales.
A78: =_xlfn.XLOOKUP(B78,'Paso 3 Redacción RA'!I$3:I$15,'Paso 3 Redacción RA'!C$3:C$15,,0,1) -> Saber | B78: Reconoce las habilidades poderosas o socioemocionales que intervienen en escenarios organizacionales y en las relaciones humanas, para determinar aquellas que son pertinentes en el abordaje de situaciones propias de los distintos ámbitos de la gestión empresarial.
A79: =_xlfn.XLOOKUP(B79,'Paso 3 Redacción RA'!I$3:I$15,'Paso 3 Redacción RA'!C$3:C$15,,0,1) -> SaberSer | B79: Integra criterios económicos, sociales y jurídicos que apoyen la toma de decisiones, para contribuir a la generación de valor y al desarrollo organizacional, considerando principios de sostenibilidad, así como las dinámicas y necesidades del entorno. | R79: =SUM(J61:J79) -> 17 | S79: =COUNTA(D61:D79) -> 5
A80: =_xlfn.XLOOKUP(B80,'Paso 3 Redacción RA'!I$3:I$15,'Paso 3 Redacción RA'!C$3:C$15,,0,1) -> Saber | B80: Analiza los principios económicos y sociales, así como la normatividad empresarial para determinar rutas estratégicas de acción y procesos asociados a la gestión, según el funcionamiento de los entornos internos y externos que operan en los contextos organizacionales. | C80: 6 | D80: Gerencia Estratégica de Proyectos Ágiles | E80: Aplica conceptos, buenas prácticas y herramientas de la gestión de proyectos ágiles, para estructurar proyectos alineados con los objetivos del alcance definido, teniendo en cuenta las partes interesadas. Determina las restricciones y roles de un proyecto, a partir de marcos de trabajos ágiles, para desarrollar propuestas ejecutables que atiendan el manejo adecuado de recursos y los requerimientos de las partes interesadas en escenarios reales o simulados. | F80: TP | H80: X | J80: 3 | K80: =J80*16 -> 48 | L80: =32*J80 -> 96 | M80: =SUM(K80:L80) -> 144 | N80: 1. Fundamentos de la Gerencia de Proyectos Ágiles 2. Planificación Ágil de Proyectos 3. Ejecución y Control Ágil de Proyectos 4. Mejora Continua y Gestión Estratégica | O80: Las estrategias pueden variar entre estas u otras: Trabajo directo Clase magistral activa/Análisis o Estudio de casos/Resolución de problemas/Talleres prácticos Trabajo independiente Lecturas relacionadas o de materiales complementarios/Resolución de problemas/Ejercicios aplicados/Desarrollo de proyectos/Talleres grupales o individuales/Análisis o Estudio de casos/Elaboración de informes o documentos técnicos | P80: Las actividades varían entre las siguientes y otras que pueda considerar el profesor y funcionan como formativas o sumativas, según sea el caso. Estudio de casos Resolución de problemas Desarrollo de proyectos Talleres Exposiciones Pruebas escritas | Q80: Las acciones de retroalimentación giran en torno a las siguientes. Formar: donde se crean las condiciones para que los estudiantes adquieran conocimientos, habilidades, actitudes, aptitudes y destrezas. Además, debe promover su desarrollo integral y debe acompañarlos en las situaciones académicas que enfrenten durante el desarrollo de un módulo o una asignatura. Informar: para que los estudiantes identifiquen los cambios que pueden afectarlos directa o indirectamente tanto en el aula de clase como en otros espacios. Prevenir: con el fin de anticiparse a las situaciones académicas que pueden representar dificultad para los estudiantes. Esto se logra a través de la interacción individual con los estudiantes y del completo conocimiento del contexto educativo en que el tutor se desenvuelve. Ayudar a decidir: donde se orienta a los estudiantes para que tomen la mejor decisión ante una situación concreta. El objetivo es que el estudiante fortalezca su autonomía y la toma de decisiones responsable.
A81: =_xlfn.XLOOKUP(B81,'Paso 3 Redacción RA'!I$3:I$15,'Paso 3 Redacción RA'!C$3:C$15,,0,1) -> SaberSer | B81: Integra criterios económicos, sociales y jurídicos que apoyen la toma de decisiones, para contribuir a la generación de valor y al desarrollo organizacional, considerando principios de sostenibilidad, así como las dinámicas y necesidades del entorno.
A82: =_xlfn.XLOOKUP(B82,'Paso 3 Redacción RA'!I$3:I$15,'Paso 3 Redacción RA'!C$3:C$15,,0,1) -> SaberHacer | B82: Ejecuta acciones de gestión de equipos y procesos, para tomar decisiones informadas que promuevan el liderazgo colaborativo en escenarios organizacionales.
A83: =_xlfn.XLOOKUP(B83,'Paso 3 Redacción RA'!I$3:I$15,'Paso 3 Redacción RA'!C$3:C$15,,0,1) -> Saber | B83: Reconoce distintos modelos de negocio y de innovación aplicables tanto a intraemprendimientos como a nuevos negocios, para seleccionar el más adecuado en el diseño de propuestas empresariales sostenibles y coherentes con el entorno.
A84: =_xlfn.XLOOKUP(B84,'Paso 3 Redacción RA'!I$3:I$15,'Paso 3 Redacción RA'!C$3:C$15,,0,1) -> Saber | B84: Analiza los principios económicos y sociales, así como la normatividad empresarial para determinar rutas estratégicas de acción y procesos asociados a la gestión, según el funcionamiento de los entornos internos y externos que operan en los contextos organizacionales. | C84: 6 | D84: Sistemas Integrados de Gestión (HSEQ) | E84: Describe la estructura y operación de los Sistemas Integrados de Gestión de una organización, para diseñar los procesos y procedimientos de acuerdo con la normatividad vigente. | F84: TP | H84: X | J84: 3 | K84: =J84*16 -> 48 | L84: =32*J84 -> 96 | M84: =SUM(K84:L84) -> 144 | N84: 1. Sistema de gestión de la calidad (ISO 9001: 2015) o su versión actualizada. 2. Sistemas de gestión ambiental (ISO 14001:2015) o su versión actualizada 3. Sistemas de gestión de la seguridad y salud en el trabajo (ISO 45001:2018) o su versión actualizada 4. Sistemas de gestión guía para la integración de los sistemas de gestión (une 66177:2005) o su versión actualizada | O84: Las estrategias pueden variar entre estas u otras: Trabajo directo Clase magistral activa/Análisis o Estudio de casos/Resolución de problemas/Talleres prácticos Trabajo independiente Lecturas relacionadas o de materiales complementarios/Resolución de problemas/Ejercicios aplicados/Desarrollo de proyectos/Talleres grupales o individuales/Análisis o Estudio de casos/Elaboración de informes o documentos técnicos | P84: Las actividades varían entre las siguientes y otras que pueda considerar el profesor y funcionan como formativas o sumativas, según sea el caso. Estudio de casos Resolución de problemas Desarrollo de proyectos Talleres Exposiciones Pruebas escritas | Q84: Las acciones de retroalimentación giran en torno a las siguientes. Formar: donde se crean las condiciones para que los estudiantes adquieran conocimientos, habilidades, actitudes, aptitudes y destrezas. Además, debe promover su desarrollo integral y debe acompañarlos en las situaciones académicas que enfrenten durante el desarrollo de un módulo o una asignatura. Informar: para que los estudiantes identifiquen los cambios que pueden afectarlos directa o indirectamente tanto en el aula de clase como en otros espacios. Prevenir: con el fin de anticiparse a las situaciones académicas que pueden representar dificultad para los estudiantes. Esto se logra a través de la interacción individual con los estudiantes y del completo conocimiento del contexto educativo en que el tutor se desenvuelve. Ayudar a decidir: donde se orienta a los estudiantes para que tomen la mejor decisión ante una situación concreta. El objetivo es que el estudiante fortalezca su autonomía y la toma de decisiones responsable.
A85: =_xlfn.XLOOKUP(B85,'Paso 3 Redacción RA'!I$3:I$15,'Paso 3 Redacción RA'!C$3:C$15,,0,1) -> SaberHacer | B85: Diseña estrategias empresariales para estructurar propuestas de mejora orientadas al fortalecimiento de la competitividad empresarial y al desarrollo de iniciativas de emprendimiento e intraemprendimiento.
A86: =_xlfn.XLOOKUP(B86,'Paso 3 Redacción RA'!I$3:I$15,'Paso 3 Redacción RA'!C$3:C$15,,0,1) -> SaberSer | B86: Integra criterios económicos, sociales y jurídicos que apoyen la toma de decisiones, para contribuir a la generación de valor y al desarrollo organizacional, considerando principios de sostenibilidad, así como las dinámicas y necesidades del entorno.
A87: =_xlfn.XLOOKUP(B87,'Paso 3 Redacción RA'!I$3:I$15,'Paso 3 Redacción RA'!C$3:C$15,,0,1) -> Saber | B87: Analiza los principios económicos y sociales, así como la normatividad empresarial para determinar rutas estratégicas de acción y procesos asociados a la gestión, según el funcionamiento de los entornos internos y externos que operan en los contextos organizacionales. | C87: 6 | D87: Evaluación de Proyectos | E87: Evalúa la factibilidad financiera de un proyecto de inversión mediante la formulación de supuestos, la proyección de estados financieros y la aplicación de métodos de decisión, para determinar su viabilidad y apoyar la toma de decisiones en contextos empresariales. | F87: TP | H87: X | J87: 3 | K87: =J87*16 -> 48 | L87: =32*J87 -> 96 | M87: =SUM(K87:L87) -> 144 | N87: 1. Conceptos básicos contables y financieros para la evaluación de proyectos 2. Flujos de caja en proyectos de inversión 3. Métodos de decisión financiera 4. Análisis de sensibilidad en los proyectos | O87: Las estrategias pueden variar entre estas u otras: Trabajo directo Clase magistral activa/Análisis o Estudio de casos/Resolución de problemas/Talleres prácticos Trabajo independiente Lecturas relacionadas o de materiales complementarios/Resolución de problemas/Ejercicios aplicados/Desarrollo de proyectos/Talleres grupales o individuales/Análisis o Estudio de casos/Elaboración de informes o documentos técnicos | P87: Las actividades varían entre las siguientes y otras que pueda considerar el profesor y funcionan como formativas o sumativas, según sea el caso. Estudio de casos Resolución de problemas Desarrollo de proyectos Talleres Exposiciones Pruebas escritas | Q87: Las acciones de retroalimentación giran en torno a las siguientes. Formar: donde se crean las condiciones para que los estudiantes adquieran conocimientos, habilidades, actitudes, aptitudes y destrezas. Además, debe promover su desarrollo integral y debe acompañarlos en las situaciones académicas que enfrenten durante el desarrollo de un módulo o una asignatura. Informar: para que los estudiantes identifiquen los cambios que pueden afectarlos directa o indirectamente tanto en el aula de clase como en otros espacios. Prevenir: con el fin de anticiparse a las situaciones académicas que pueden representar dificultad para los estudiantes. Esto se logra a través de la interacción individual con los estudiantes y del completo conocimiento del contexto educativo en que el tutor se desenvuelve. Ayudar a decidir: donde se orienta a los estudiantes para que tomen la mejor decisión ante una situación concreta. El objetivo es que el estudiante fortalezca su autonomía y la toma de decisiones responsable.
A88: =_xlfn.XLOOKUP(B88,'Paso 3 Redacción RA'!I$3:I$15,'Paso 3 Redacción RA'!C$3:C$15,,0,1) -> SaberHacer | B88: Ejecuta acciones de gestión de equipos y procesos, para tomar decisiones informadas que promuevan el liderazgo colaborativo en escenarios organizacionales.
A89: =_xlfn.XLOOKUP(B89,'Paso 3 Redacción RA'!I$3:I$15,'Paso 3 Redacción RA'!C$3:C$15,,0,1) -> Saber | B89: Reconoce las habilidades poderosas o socioemocionales que intervienen en escenarios organizacionales y en las relaciones humanas, para determinar aquellas que son pertinentes en el abordaje de situaciones propias de los distintos ámbitos de la gestión empresarial.
A90: =_xlfn.XLOOKUP(B90,'Paso 3 Redacción RA'!I$3:I$15,'Paso 3 Redacción RA'!C$3:C$15,,0,1) -> SaberHacer | B90: Diseña estrategias empresariales para estructurar propuestas de mejora orientadas al fortalecimiento de la competitividad empresarial y al desarrollo de iniciativas de emprendimiento e intraemprendimiento.
A91: =_xlfn.XLOOKUP(B91,'Paso 3 Redacción RA'!I$3:I$15,'Paso 3 Redacción RA'!C$3:C$15,,0,1) -> Saber | B91: Reconoce distintos modelos de negocio y de innovación aplicables tanto a intraemprendimientos como a nuevos negocios, para seleccionar el más adecuado en el diseño de propuestas empresariales sostenibles y coherentes con el entorno.
A92: =_xlfn.XLOOKUP(B92,'Paso 3 Redacción RA'!I$3:I$15,'Paso 3 Redacción RA'!C$3:C$15,,0,1) -> Saber | B92: Analiza los principios económicos y sociales, así como la normatividad empresarial para determinar rutas estratégicas de acción y procesos asociados a la gestión, según el funcionamiento de los entornos internos y externos que operan en los contextos organizacionales. | C92: 6 | D92: Consultorio Empresarial | E92: Aplica herramientas de diagnóstico empresarial, para formular estrategias competitivas y sostenibles que respondan a las necesidades y problemáticas de la empresa. | F92: P | H92: X | J92: 6 | K92: =J92*16 -> 96 | L92: =32*J92 -> 192 | M92: =SUM(K92:L92) -> 288 | N92: 1. Consultoría - Particularidades de una organización empresarial desde el ámbito Interno y Financiero. 2. Formulación de estrategia y matrices de administración. 3. Balanced Scorecard y Propuesta de Mejora para la organización. 4. Lineamientos estratégicos para la intervención organizacional | O92: Las estrategias pueden variar entre estas u otras: Trabajo directo Clase magistral activa/Análisis o Estudio de casos/Resolución de problemas/Talleres prácticos Trabajo independiente Lecturas relacionadas o de materiales complementarios/Resolución de problemas/Ejercicios aplicados/Desarrollo de proyectos/Talleres grupales o individuales/Análisis o Estudio de casos/Elaboración de informes o documentos técnicos | P92: Las actividades varían entre las siguientes y otras que pueda considerar el profesor y funcionan como formativas o sumativas, según sea el caso. Estudio de casos Resolución de problemas Desarrollo de proyectos Talleres Exposiciones Pruebas escritas | Q92: Las acciones de retroalimentación giran en torno a las siguientes. Formar: donde se crean las condiciones para que los estudiantes adquieran conocimientos, habilidades, actitudes, aptitudes y destrezas. Además, debe promover su desarrollo integral y debe acompañarlos en las situaciones académicas que enfrenten durante el desarrollo de un módulo o una asignatura. Informar: para que los estudiantes identifiquen los cambios que pueden afectarlos directa o indirectamente tanto en el aula de clase como en otros espacios. Prevenir: con el fin de anticiparse a las situaciones académicas que pueden representar dificultad para los estudiantes. Esto se logra a través de la interacción individual con los estudiantes y del completo conocimiento del contexto educativo en que el tutor se desenvuelve. Ayudar a decidir: donde se orienta a los estudiantes para que tomen la mejor decisión ante una situación concreta. El objetivo es que el estudiante fortalezca su autonomía y la toma de decisiones responsable.
A93: =_xlfn.XLOOKUP(B93,'Paso 3 Redacción RA'!I$3:I$15,'Paso 3 Redacción RA'!C$3:C$15,,0,1) -> SaberHacer | B93: Ejecuta acciones de gestión de equipos y procesos, para tomar decisiones informadas que promuevan el liderazgo colaborativo en escenarios organizacionales.
A94: =_xlfn.XLOOKUP(B94,'Paso 3 Redacción RA'!I$3:I$15,'Paso 3 Redacción RA'!C$3:C$15,,0,1) -> SaberSer | B94: Integra criterios económicos, sociales y jurídicos que apoyen la toma de decisiones, para contribuir a la generación de valor y al desarrollo organizacional, considerando principios de sostenibilidad, así como las dinámicas y necesidades del entorno.
A95: =_xlfn.XLOOKUP(B95,'Paso 3 Redacción RA'!I$3:I$15,'Paso 3 Redacción RA'!C$3:C$15,,0,1) -> SaberHacer | B95: Diseña estrategias empresariales para estructurar propuestas de mejora orientadas al fortalecimiento de la competitividad empresarial y al desarrollo de iniciativas de emprendimiento e intraemprendimiento.
A96: =_xlfn.XLOOKUP(B96,'Paso 3 Redacción RA'!I$3:I$15,'Paso 3 Redacción RA'!C$3:C$15,,0,1) -> Saber | B96: Reconoce las habilidades poderosas o socioemocionales que intervienen en escenarios organizacionales y en las relaciones humanas, para determinar aquellas que son pertinentes en el abordaje de situaciones propias de los distintos ámbitos de la gestión empresarial.
A97: =_xlfn.XLOOKUP(B97,'Paso 3 Redacción RA'!I$3:I$15,'Paso 3 Redacción RA'!C$3:C$15,,0,1) -> Saber | B97: Reconoce distintos modelos de negocio y de innovación aplicables tanto a intraemprendimientos como a nuevos negocios, para seleccionar el más adecuado en el diseño de propuestas empresariales sostenibles y coherentes con el entorno.
A98: =_xlfn.XLOOKUP(B98,'Paso 3 Redacción RA'!I$3:I$15,'Paso 3 Redacción RA'!C$3:C$15,,0,1) -> Saber | B98: Analiza los principios económicos y sociales, así como la normatividad empresarial para determinar rutas estratégicas de acción y procesos asociados a la gestión, según el funcionamiento de los entornos internos y externos que operan en los contextos organizacionales. | C98: 6 | D98: Gobierno Corporativo y Compilance | E98: Identifica la normativa nacional e internacional aplicable a la empresa para plantear prácticas de buen gobierno dentro de la organización con miras a generar transparencia en la gestión de cara a sus grupos de interés. | F98: TP | H98: X | J98: 3 | K98: =J98*16 -> 48 | L98: =32*J98 -> 96 | M98: =SUM(K98:L98) -> 144 | N98: 1. Órganos sociales 2. Gobierno corporativo y sus clases según el tipo de sociedad empresarial 3. Controversias en el gobierno corporativo 4. Compliance | O98: Las estrategias pueden variar entre estas u otras: Trabajo directo Clase magistral activa/Análisis o Estudio de casos/Resolución de problemas/Talleres prácticos Trabajo independiente Lecturas relacionadas o de materiales complementarios/Resolución de problemas/Ejercicios aplicados/Desarrollo de proyectos/Talleres grupales o individuales/Análisis o Estudio de casos/Elaboración de informes o documentos técnicos | P98: Las actividades varían entre las siguientes y otras que pueda considerar el profesor y funcionan como formativas o sumativas, según sea el caso. Estudio de casos Resolución de problemas Desarrollo de proyectos Talleres Exposiciones Pruebas escritas | Q98: Las acciones de retroalimentación giran en torno a las siguientes. Formar: donde se crean las condiciones para que los estudiantes adquieran conocimientos, habilidades, actitudes, aptitudes y destrezas. Además, debe promover su desarrollo integral y debe acompañarlos en las situaciones académicas que enfrenten durante el desarrollo de un módulo o una asignatura. Informar: para que los estudiantes identifiquen los cambios que pueden afectarlos directa o indirectamente tanto en el aula de clase como en otros espacios. Prevenir: con el fin de anticiparse a las situaciones académicas que pueden representar dificultad para los estudiantes. Esto se logra a través de la interacción individual con los estudiantes y del completo conocimiento del contexto educativo en que el tutor se desenvuelve. Ayudar a decidir: donde se orienta a los estudiantes para que tomen la mejor decisión ante una situación concreta. El objetivo es que el estudiante fortalezca su autonomía y la toma de decisiones responsable.
A99: =_xlfn.XLOOKUP(B99,'Paso 3 Redacción RA'!I$3:I$15,'Paso 3 Redacción RA'!C$3:C$15,,0,1) -> SaberHacer | B99: Ejecuta acciones de gestión de equipos y procesos, para tomar decisiones informadas que promuevan el liderazgo colaborativo en escenarios organizacionales.
A100: =_xlfn.XLOOKUP(B100,'Paso 3 Redacción RA'!I$3:I$15,'Paso 3 Redacción RA'!C$3:C$15,,0,1) -> Saber | B100: Reconoce las habilidades poderosas o socioemocionales que intervienen en escenarios organizacionales y en las relaciones humanas, para determinar aquellas que son pertinentes en el abordaje de situaciones propias de los distintos ámbitos de la gestión empresarial.
...

Sheet Taxonomía para competencias
B1: Verbos Competencias
B2: Actualizar
B3: Administrar
B4: Asegurar
B5: Asesorar
B6: Auditar
B7: Comunicar
B8: Conducir
B9: Conocer
B10: Coordinar
B11: Definir
B12: Desarrollar
... B40: Aplicar

Sheet Taxonomias para RA
S1: Taxonomía de Bloom Adaptada bajo las ideas de Anderson y Krathwohl | AL1: Taxonomía de Bloom adaptada bajo las ideas de Lorin y Krathwohl (LK) | AT1: Taxonomía de Bloom adaptada bajo las ideas de Anderson y Kendal (AK)
L2: Taxonomía de Bloom | S2: Cognitivo(BAK) | Y2: Procedimental(BAK) | AC2: Actitudinal(BAK)
A3: Taxonomías | C3: BAK | D3: LK | E3: AK | G3: CognitivoB | H3: ProcedimentalB | I3: ActitudinalB | L3: ConocimientoB | M3: ComprensiónB | N3: AplicaciónB | O3: AnálisisB | P3: SíntesisB | Q3: EvaluaciónB | S3: ConocimientoBAK | T3: ComprensiónBAK | U3: AplicaciónBAK | V3: AnálisisBAK | W3: SíntesisBAK | X3: EvaluaciónBAK | Y3: ImitaciónBAK | Z3: ManipulaciónBAK | AA3: PrecisiónBAK | AB3: ControlBAK | AC3: PercepciónBAK | AD3: ResponderBAK | AE3: ValorarBAK | AF3: OrganizarBAK | AG3: CaracterizarBAK | AL3: Procesos cognitivos de orden inferior | AO3: Procesos cognitivos de orden superior
A4: Bloom | C4: CognitivoBAK | D4: HechosLK | E4: InformaciónAK | G4: ConocimientoB | H4: ConocimientoB | I4: ConocimientoB | L4: Adquirir | M4: Auditar | N4: Aplicar | O4: Aislar | P4: Adaptar | Q4: Aconsejar | S4: Adquirir | T4: Auditar | U4: Aplicar | V4: Aislar | W4: Adaptar | X4: Aconsejar | Y4: Acordar | Z4: Acceder | AA4: Abrir | AB4: Arreglar | AC4: Aceptar | AD4: Acordar | AE4: Aceptar | AF4: Adelantar | AG4: Acabar | AL4: RecordarLK | AM4: ComprenderLK | AN4: AplicarLK | AO4: AnalizarLK | AP4: EvaluarLK | AQ4: CrearLK | AT4: RecuperaciónAK | AU4: ComprensiónAK | AV4: AnálisisAK | AW4: UsoConocimientoAK | AX4: MetacogniciónAK | AY4: SistemadelYoAK
A5: BAK | C5: ProcedimentalBAK | D5: ConceptosLK | E5: ProcesosMentalesAK | G5: ComprensiónB | H5: ComprensiónB | I5: ComprensiónB | L5: Buscar | M5: Bosquejar | N5: Calisificar | O5: Analizar | P5: Administrar | Q5: Adjuntar | S5: Buscar | T5: Bosquejar | U5: Calisificar | V5: Analizar | W5: Administrar | X5: Adjuntar | Y5: Adaptar | Z5: Aislar | AA5: Actuar | AB5: Balancear | AC5: Admitir | AD5: Actuar recíprocamente | AE5: Adoptar | AF5: Anticipar | AG5: Afinar | AL5: Afirmar | AM5: Clasificar | AN5: Actuar | AO5: Agrupar | AP5: Adaptar | AQ5: Desarrollar | AT5: Afirmar | AU5: Auditar | AV5: Agrupar | AW5: Actuar | AX5: Aceptar | AY5: Aceptar
A6: LK | C6: ActitudinalBAK | D6: ProcedimientoslLK | E6: PsicomotorAK | G6: AplicaciónB | H6: AplicaciónB | I6: AplicaciónB | L6: Citar | M6: Comentar | N6: Combinar | O6: Calcular | P6: Arreglar | Q6: Agregar | S6: Citar | T6: Comentar | U6: Combinar | V6: Calcular | W6: Arreglar | X6: Agregar | Y6: Ajustar | Z6: Ajustar | AA6: Adaptar | AB6: Clasificar | AC6: Anotar | AD6: Afirmar | AE6: Afirmar | AF6: Arreglar | AG6: Apoyar | AL6: Citar | AM6: Comparar | AN6: Agrupar | AO6: Aislar | AP6: Añadir | AQ6: Elaborar | AT6: Citar | AU6: Bosquejar | AV6: Aislar | AW6: Agrupar | AX6: Adelantar | AY6: Adoptar
A7: AK | D7: MetacogniciónLK | G7: AnálisisB | H7: AnálisisB | I7: AnálisisB | L7: Consignar | M7: Comunicar | N7: Componer | O7: Categorizar | P7: Arreglar | Q7: Alinear | S7: Consignar | T7: Comunicar | U7: Componer | V7: Categorizar | W7: Arreglar | X7: Alinear | Y7: Alinear | Z7: Ampliar | AA7: Ajustar | AB7: Codificar | AC7: Aplicar | AD7: Aprobar | AE7: Agradecer | AF7: Conectar | AG7: Atender | AL7: Copiar | AM7: Contrastar | AN7: Calcular | AO7: Asumir | AP7: Apoyar | AQ7: Maximizar | AT7: Copiar | AU7: Clasificar | AV7: Analizar | AW7: Aplicar | AX7: Adoptar | AY7: Afinar
G8: SíntesisB | H8: SíntesisB | I8: SíntesisB | L8: Decir | M8: Convertir | N8: Conducir | O8: Comparar | P8: Articular | Q8: Arbitrar | S8: Decir | T8: Convertir | U8: Conducir | V8: Comparar | W8: Articular | X8: Arbitrar | Y8: Analizar | Z8: Aplicar | AA8: Apalancar | AB8: Colocar | AC8: Apreciar | AD8: Asegurar | AE8: Ambicionar | AF8: Considerar | AG8: Categorizar | AL8: Decir | AM8: Demostrar | AN8: Categorizar | AO8: Buscar similitudes | AP8: Argumentar | AQ8: Mejorar | AT8: Decir | AU8: Comentar | AV8: Aplicar | AW8: Calcular | AX8: Afinar | AY8: Agradecer
G9: EvaluaciónB | H9: EvaluaciónB | I9: EvaluaciónB | L9: Definir | M9: Criticar | N9: Construir | O9: Considerar | P9: Aumentar | Q9: Asegurar | S9: Definir | T9: Criticar | U9: Construir | V9: Considerar | W9: Aumentar | X9: Asegurar | Y9: Aplicar | Z9: Arreglar | AA9: Bajar | AB9: Componer | AC9: Apreciar | AD9: Autorizar | AE9: Anhelar | AF9: Cuestionar | AG9: Colaborar | AL9: Definir | AM9: Discutir | AN9: Conectar | AO9: Categorizar | AP9: Cambiar | AQ9: Minimizar | AT9: Definir | AU9: Comparar | AV9: Asumir | AW9: Calisificar | AX9: Afirmar | AY9: Ambicionar
L10: Deletrear | M10: Dar ejemplos | N10: Demostrar | O10: Contrastar | P10: Calcular | Q10: Asesorar | S10: Deletrear | T10: Dar ejemplos | U10: Demostrar | V10: Contrastar | W10: Calcular | X10: Asesorar | Y10: Armar | Z10: Colocar | AA10: Colocar | AB10: Conducir | AC10: Asisitir | AD10: Clasificar | AE10: Apoyar | AF10: Defender | AG10: Completar | AL10: Deletrear | AM10: Ejemplificar | AN10: Construir | AO10: Centrarse | AP10: Combinar | AQ10: Modelar | AT10: Deletrear | AU10: Comunicar | AV10: Buscar similitudes | AW10: Categorizar | AX10: Agradecer | AY10: Anhelar
G11: HechosLK | H11: ConceptosLK | I11: ProcedimientosLK | J11: MetacogniciónLK | L11: Demostrar | M11: Debatir | N11: Determinar | O11: Criticar | P11: Componer | Q11: Atar | S11: Demostrar | T11: Debatir | U11: Determinar | V11: Criticar | W11: Componer | X11: Atar | Y11: Arreglar | Z11: Conducir | AA11: Comenzar | AB11: Correr | AC11: Atender | AD11: Colaborar | AE11: Apreciar | AF11: Definir | AG11: Comportarse bajo condiciones | AL11: Duplicar | AM11: Esquematizar | AN11: Demostrar | AO11: Comparar | AP11: Comparar | AQ11: Pensar | AT11: Duplicar | AU11: Contrastar | AV11: Calcular | AW11: Combinar | AX11: Ambicionar | AY11: Anticipar
G12: RecordarLK | H12: RecordarLK | I12: RecordarLK | J12: RecordarLK | L12: Describir | M12: Describir | N12: Dibujar | O12: Cuestionar | P12: Computar | Q12: Calcular | S12: Describir | T12: Describir | U12: Dibujar | V12: Cuestionar | W12: Computar | X12: Calcular | Y12: Asegurar | Z12: Desmontar | AA12: Cortar | AB12: Coser | AC12: Clasificar | AD12: Comunicar | AE12: Aprobar | AF12: Desplegar | AG12: Conducir | AL12: Elegir | AM12: Explicar | AN12: Desarrollar | AO12: Correlacionar | AP12: Compilar | AQ12: Planear | AT12: Elegir | AU12: Convertir | AV12: Calisificar | AW12: Componer | AX12: Anhelar | AY12: Apreciar
G13: ComprenderLK | H13: ComprenderLK | I13: ComprenderLK | J13: ComprenderLK | L13: Elegir | M13: Desplegar | N13: Discriminar | O13: Debatir | P13: Concluir | Q13: Calificar | S13: Elegir | T13: Desplegar | U13: Discriminar | V13: Debatir | W13: Concluir | X13: Calificar | Y13: Bailar | Z13: Dibujar | AA13: Cumplir | AB13: Difundir | AC13: Conducir | AD13: Conocer | AE13: Asistir | AF13: Determinar | AG13: Constatar | AL13: Escribir | AM13: Expresar | AN13: Dramatizar | AO13: Descomponer | AP13: Componer | AQ13: Proponer | AT13: Escribir | AU13: Criticar | AV13: Categorizar | AW13: Conducir | AX13: Anticipar | AY13: Aprobar
G14: AplicarLK | H14: AplicarLK | I14: AplicarLK | J14: AplicarLK | L14: Enseñar | M14: Dibujar | N14: Diseñar | O14: Deducir | P14: Conectar | Q14: Censurar | S14: Enseñar | T14: Dibujar | U14: Diseñar | V14: Deducir | W14: Conectar | X14: Censurar | Y14: Cambiar | Z14: Direccionar | AA14: Destapar | AB14: Direccionar | AC14: Cumplir | AD14: Contar | AE14: Aspirar | AF14: Discernir | AG14: Contextualizar | AL14: Leer | AM14: Generalizar | AN14: Elegir | AO14: Diferenciar | AP14: Construir | AQ14: Reescribir | AT14: Leer | AU14: Dar ejemplos | AV14: Centrarse | AW14: Conectar | AX14: Apoyar | AY14: Asistir
G15: AnalizarLK | H15: AnalizarLK | I15: AnalizarLK | J15: AnalizarLK | L15: Escribir | M15: Discutir | N15: Dramatizar | O15: Desarrollar | P15: Construir | Q15: Clasificar | S15: Escribir | T15: Discutir | U15: Dramatizar | V15: Desarrollar | W15: Construir | X15: Clasificar | Y15: Comparar | Z15: Dirigir | AA15: Dirigir | AB15: Diseñar | AC15: Decir | AD15: Cooperar | AE15: Atender | AF15: Exteriorizar | AG15: Controlar | AL15: Listar | AM15: Ilustrar | AN15: Emplear | AO15: Distinguir | AP15: Convencer | AQ15: Simplificar | AT15: Listar | AU15: Debatir | AV15: Combinar | AW15: Construir | AX15: Apreciar | AY15: Aspirar
G16: EvaluarLK | H16: EvaluarLK | I16: EvaluarLK | J16: EvaluarLK | L16: Establecer | M16: Diseñar | N16: Duplicar | O16: Detectar | P16: Crear | Q16: Computar | S16: Establecer | T16: Diseñar | U16: Duplicar | V16: Detectar | W16: Crear | X16: Computar | Y16: Comprobar | Z16: Docificar | AA16: Disponer | AB16: Disipar | AC16: Detectar | AD16: Decir | AE16: Aunar | AF16: Extraer | AG16: Cooperar | AL16: Localizar | AM16: Inferir | AN16: Enseñar | AO16: Dividir | AP16: Crear | AQ16: Suponer | AT16: Localizar | AU16: Demostrar | AV16: Comparar | AW16: Demostrar | AX16: Aprobar | AY16: Atender
G17: CrearLK | H17: CrearLK | I17: CrearLK | J17: CrearLK | L17: Etiquetar | M17: Establecer | N17: Elegir | O17: Diagramar | P17: Decidir | Q17: Concluir | S17: Etiquetar | T17: Establecer | U17: Elegir | V17: Diagramar | W17: Decidir | X17: Concluir | Y17: Concretar | Z17: Dramatizar | AA17: Dividir | AB17: Ejecutar | AC17: Direccionar | AD17: Demostrar | AE17: Clasificar | AF17: Fomentar | AG17: Cumplir | AL17: Memorizar | AM17: Informar | AN17: Entrevistar | AO17: Elegir | AP17: Criticar | AQ17: Sustituir | AT17: Memorizar | AU17: Describir | AV17: Componer | AW17: Desarrollar | AX17: Arreglar | AY17: Categorizar
L18: Examinar | M18: Examinar | N18: Emparejar | O18: Diferenciar | P18: Deducir | Q18: Conformar | S18: Examinar | T18: Examinar | U18: Emparejar | V18: Diferenciar | W18: Deducir | X18: Conformar | Y18: Conducir | Z18: Ejecutar | AA18: Ejecutar | AB18: Eliminar | AC18: Dirigir | AD18: Discutir | AE18: Compartir | AF18: Formular | AG18: Discriminar | AL18: Mostrar | AM18: Interpretar | AN18: Hacer uso | AO18: Encontrar | AP18: Debatir | AQ18: Teorizar | AT18: Mostrar | AU18: Desplegar | AV18: Conducir | AW18: Determinar | AX18: Asistir | AY18: Clasificar
G19: InformaciónAK | H19: ProcesosAK | I19: PsicomotorAK | L19: Examinar | M19: Explicar | N19: Emplear | O19: Discernir | P19: Derivar | Q19: Constrastar | S19: Examinar | T19: Explicar | U19: Emplear | V19: Discernir | W19: Derivar | X19: Constrastar | Y19: Construir | Z19: Ejercitar | AA19: Ejercer | AB19: Emplear | AC19: Distinguir | AD19: Distinguir | AE19: Comprender | AF19: Identificar | AG19: Distinguir | AL19: Nombrar | AM19: Mostrar | AN19: Identificar | AO19: Encuestar | AP19: Decidir | AQ19: Testar | AT19: Nombrar | AU19: Dibujar | AV19: Considerar | AW19: Dibujar | AX19: Aspirar | AY19: Completar
G20: RecuperaciónAK | H20: RecuperaciónAK | I20: RecuperaciónAK | L20: Grabar | M20: Exponer | N20: Esquematizar | O20: Discriminar | P20: Desarrollar | Q20: Contabilizar | S20: Grabar | T20: Exponer | U20: Esquematizar | V20: Discriminar | W20: Desarrollar | X20: Contabilizar | Y20: Contar | Z20: Encajar | AA20: Emitir | AB20: Ensanchar | AC20: Elegir | AD20: Elegir | AE20: Contribuir | AF20: Percibir | AG20: Ejercer | AL20: Observar | AM20: Observar | AN20: Interpretar | AO20: Establecer | AP20: Deducir | AQ20: Transformar | AT20: Observar | AU20: Discutir | AV20: Construir | AW20: Discriminar | AX20: Atender | AY20: Comprender
G21: ComprensiónAK | H21: ComprensiónAK | I21: ComprensiónAK | L21: Hacer | M21: Expresar | N21: Estimar | O21: Distinguir | P21: Describir | Q21: Controlar | S21: Hacer | T21: Expresar | U21: Estimar | V21: Distinguir | W21: Describir | X21: Controlar | Y21: Contrastar | Z21: Enseñar | AA21: Emitir | AB21: Entallar | AC21: Emplear | AD21: Enumerar | AE21: Convocar | AF21: Preguntar | AG21: Entregar | AL21: Omitir | AM21: Parafrasear | AN21: Manipular | AO21: Examinar | AP21: Defender | AQ21: Visualizar | AT21: Omitir | AU21: Diseñar | AV21: Contrastar | AW21: Diseñar | AX21: Aunar | AY21: Conducir
G22: AnálisisAK | H22: AnálisisAK | I22: AnálisisAK | L22: Identificar | M22: Extraer | N22: Estructurar | O22: Estructurar | P22: Desempeñar | Q22: Corregir | S22: Identificar | T22: Extraer | U22: Estructurar | V22: Estructurar | W22: Desempeñar | X22: Corregir | Y22: Controlar | Z22: Examinar | AA22: Empaquetar | AB22: Entregar | AC22: Escoger | AD22: Escoger | AE22: Creer | AF22: Promover | AG22: Juzgar | AL22: Rastrear | AM22: Predecir | AN22: Organizar | AO22: Inferir | AP22: Demostrar | AT22: Parafrasear | AU22: Ejemplificar | AV22: Correlacionar | AW22: Dramatizar | AX22: Categorizar | AY22: Conectar
G23: UsoConocimientoAK | H23: UsoConocimientoAK | I23: UsoConocimientoAK | L23: Ilustrar | M23: Generalizar | N23: Estructurar | O23: Examinar | P23: Dirigir | Q23: Criticar | S23: Ilustrar | T23: Generalizar | U23: Estructurar | V23: Examinar | W23: Dirigir | X23: Criticar | Y23: Coordinar | Z23: Explorar | AA23: Encontrar | AB23: Esculpir | AC23: Escuchar | AD23: Hablar | AE23: Cuidar | AF23: Proponer | AG23: Negociar | AL23: Recitar | AM23: Preguntar | AN23: Planear | AO23: Inspeccionar | AP23: Descubrir | AT23: Rastrear | AU23: Esquematizar | AV23: Criticar | AW23: Duplicar | AX23: Clasificar | AY23: Considerar
G24: MetacogniciónAK | H24: MetacogniciónAK | I24: MetacogniciónAK | L24: Listar | M24: Hacer | N24: Evaluar | O24: Experimentar | P24: Diseñar | Q24: Cuestionar | S24: Listar | T24: Hacer | U24: Evaluar | V24: Experimentar | W24: Diseñar | X24: Cuestionar | Y24: Cortar | Z24: Expresar | AA24: Entrenar | AB24: Extender | AC24: Estimar | AD24: Hacer | AE24: Elegir | AF24: Proteger | AG24: Ofrecer | AL24: Reconocer | AM24: Relacionar | AN24: Practicar | AO24: Investigar | AP24: Diseñar | AT24: Recitar | AU24: Establecer | AV24: Cuestionar | AW24: Elegir | AX24: Colaborar | AY24: Constatar
G25: AutoSistemaAK | H25: AutoSistemaAK | I25: AutoSistemaAK | L25: Mostar | M25: Identificar | N25: Experimentar | O25: Inspeccionar | P25: Ejercer | Q25: Culminar | S25: Mostar | T25: Identificar | U25: Experimentar | V25: Inspeccionar | W25: Ejercer | X25: Culminar | Y25: Cotejar | Z25: Extraer | AA25: Envasar | AB25: Extirpar | AC25: Evaluar | AD25: Indicar | AE25: Emplear | AF25: Reconocer | AG25: Participar | AL25: Relacionar | AM25: Resumir | AN25: Resolver | AO25: Motivar | AP25: Estimar | AT25: Reconocer | AU25: Examinar | AV25: Debatir | AW25: Emparejar | AX25: Compartir | AY25: Contextualizar
L26: Nombrar | M26: Indicar | N26: Ilustrar | O26: Inventariar | P26: Ensamblar | Q26: Debatir | S26: Nombrar | T26: Indicar | U26: Ilustrar | V26: Inventariar | W26: Ensamblar | X26: Debatir | Y26: Demostrar | Z26: Guiar | AA26: Establecer | AB26: Hacer | AC26: Examinar | AD26: Informar | AE26: Ensamblar | AF26: Relacionar | AG26: Servir | AL26: Relacionar | AM26: Revisar | AN26: Resumir | AO26: Observar | AP26: Evaluar | AT26: Relacionar | AU26: Explicar | AV26: Deducir | AW26: Emplear | AX26: Completar | AY26: Cuestionar
L27: Numerar | M27: Inferir | N27: Indicar | O27: Investigar | P27: Escribir | Q27: Decidir | S27: Numerar | T27: Inferir | U27: Indicar | V27: Investigar | W27: Escribir | X27: Decidir | Y27: Detectar | Z27: Hacer | AA27: Estampar | AB27: Implementar | AC27: Guiar | AD27: Narrar | AE27: Escoger | AF27: Relatar | AG27: Soportar | AL27: Repetir | AM27: Traducir | AN27: Seleccionar | AO27: Ordenar | AP27: Experimentar | AT27: Repetir | AU27: Exponer | AV27: Demostrar | AW27: Enseñar | AX27: Comportarse bajo condiciones | AY27: Cuidar
L28: Observar | M28: Interpretar | N28: Interpretar | O28: Listar | P28: Establecer | Q28: Deducir | S28: Observar | T28: Interpretar | U28: Interpretar | V28: Listar | W28: Establecer | X28: Deducir | Y28: Direccionar | Z28: Identificar | AA28: Estimular | AB28: Industrializar | AC28: Hacer | AD28: Obrar recíprocamente | AE28: Estimar | AF28: Resumir | AG28: Terminar | AN28: Simular | AO28: Preguntar | AP28: Explicar | AU28: Expresar | AV28: Desarrollar | AW28: Entrevistar | AX28: Comprender | AY28: Cumplir
L29: Obtener | M29: Inventariar | N29: Investigar | O29: Medir | P29: Estudiar | Q29: Defender | S29: Obtener | T29: Inventariar | U29: Investigar | V29: Medir | W29: Estudiar | X29: Defender | Y29: Disponer | Z29: Inspeccionar | AA29: Extraer | AB29: Inspeccionar | AC29: Interrogar | AD29: Recitar | AE29: Estimular | AF29: Revelar | AG29: Verificar | AN29: Transferir | AO29: Priorizar | AP29: Extender | AU29: Extraer | AV29: Descomponer | AW29: Esquematizar | AX29: Conducir | AY29: Defender
L30: Ordenar | M30: Localizar | N30: Listar | O30: Planear | P30: Figurar | Q30: Defender | S30: Ordenar | T30: Localizar | U30: Listar | V30: Planear | W30: Figurar | X30: Defender | Y30: Edificar | Z30: Instalar | AA30: Fabricar | AB30: Llevar | AC30: Manejar | AD30: Referir | AE30: Participar | AG30: Examinar | AN30: Unir | AO30: Probar | AP30: Formular | AU30: Generalizar | AV30: Detectar | AW30: Estimar | AX30: Conectar | AY30: Determinar
L31: Organizar | M31: Narrar | N31: Manipular | O31: Preguntar | P31: Formular | Q31: Determinar | S31: Organizar | T31: Narrar | U31: Manipular | V31: Preguntar | W31: Formular | X31: Determinar | Y31: Ensamblar | Z31: Inventariar | AA31: Gestionar | AB31: Manejar | AC31: Observar | AD31: Relatar | AE31: Preocuparse de o por | AN31: Usar | AO31: Razonar | AP31: Hipotetizar | AU31: Hacer | AV31: Determinar | AW31: Estructurar | AX31: Considerar | AY31: Discernir
L32: Preguntar | M32: Parafrasear | N32: Modelar | O32: Probar | P32: Generar | Q32: Discutir | S32: Preguntar | T32: Parafrasear | U32: Modelar | V32: Probar | W32: Generar | X32: Discutir | Y32: Escoger | Z32: Manejar | AA32: Grabar | AB32: Mecanizar | AC32: Ocupar | AD32: Resolver | AE32: Proporcionar | AO32: Reorganizar | AP32: Influir | AU32: Identificar | AV32: Diagramar | AW32: Evaluar | AX32: Constatar | AY32: Discriminar
L33: Presentar | M33: Presentar | N33: Operar | O33: Reconocer | P33: Gestionar | Q33: Elegir | S33: Presentar | T33: Presentar | U33: Operar | V33: Reconocer | W33: Gestionar | X33: Elegir | Y33: Filtrar | Z33: Maniobrar | AA33: Hacer | AB33: Mover | AC33: Preguntar | AD33: Seleccionar | AE33: Provocar | AO33: Resaltar | AP33: Innovar | AU33: Ilustrar | AV33: Dibujar | AW33: Experimentar | AX33: Contextualizar | AY33: Distinguir
L34: Probar | M34: Relatar | N34: Organizar | O34: Relacionar | P34: Hacer | Q34: Ensamblar | S34: Probar | T34: Relatar | U34: Organizar | V34: Relacionar | W34: Hacer | X34: Ensamblar | Y34: Gestionar | Z34: Manipular | AA34: Hallar | AB34: Ordenar | AC34: Publicar | AE34: Ratificar | AO34: Separar | AP34: Justificar | AU34: Indicar | AV34: Diferenciar | AW34: Hacer uso | AX34: Contribuir | AY34: Ejercer
L35: Realizar | M35: Reportar | N35: Patronar | O35: Separar | P35: Inferir | Q35: Escoger | S35: Realizar | T35: Reportar | U35: Patronar | V35: Separar | W35: Inferir | X35: Escoger | Y35: Hacer | Z35: Mejorar | AA35: Imprimir | AB35: Ponderar | AC35: Realizar | AE35: Seleccionar | AO35: Simplificar | AP35: Juzgar | AU35: Inferir | AV35: Discernir | AW35: Identificar | AX35: Controlar | AY35: Elegir
L36: Reconocer | M36: Resumir | N36: Practicar | O36: Subdividir | P36: Instalar | Q36: Establecer | S36: Reconocer | T36: Resumir | U36: Practicar | V36: Subdividir | W36: Instalar | X36: Establecer | Y36: Inspeccionar | Z36: Perforar | AA36: Impulsar | AB36: Preguntar | AC36: Seleccionar | AE36: Ser partidario de | AP36: Medir | AU36: Informar | AV36: Discriminar | AW36: Ilustrar | AX36: Convocar | AY36: Escoger
L37: Recordar | M37: Revisar | N37: Recoger | P37: Interpretar | Q37: Estimar | S37: Recordar | T37: Revisar | U37: Recoger | W37: Interpretar | X37: Estimar | Y37: Juntar | Z37: Poner | AA37: Interpretar | AB37: Probar | AC37: Servir | AE37: Soportar | AP37: Opinar | AU37: Interpretar | AV37: Diseñar | AW37: Indicar | AX37: Cooperar | AY37: Estimar
L38: Registrar | M38: Seleccionar | N38: Relacionar | P38: Introducir | Q38: Evaluar | S38: Registrar | T38: Seleccionar | U38: Relacionar | W38: Introducir | X38: Evaluar | Y38: Limpiar | Z38: Reconocer | AA38: Levantar | AB38: Quitar | AC38: Tasar | AE38: Tasar | AP38: Originar | AU38: Inventariar | AV38: Distinguir | AW38: Interpretar | AX38: Creer | AY38: Estimular
L39: Relacionar | M39: Separar | N39: Reportar | P39: Inventar | Q39: Evaluar | S39: Relacionar | T39: Separar | U39: Reportar | W39: Inventar | X39: Evaluar | Y39: Modificar | Z39: Registrar | AA39: Localizar | AB39: Reconocer | AC39: Usar | AE39: Unir | AP39: Percibir | AU39: Localizar | AV39: Dividir | AW39: Investigar | AX39: Cuestionar | AY39: Exteriorizar
L40: Relatar | M40: Traducir | N40: Resolver | P40: Juntar | Q40: Finalizar | S40: Relatar | T40: Traducir | U40: Resolver | W40: Juntar | X40: Finalizar | Y40: Modificar | Z40: Revisar | AA40: Manejar | AB40: Reemplazar | AC40: Valorar | AE40: Integrar | AP40: Persuadir | AU40: Mostrar | AV40: Dramatizar | AW40: Listar | AX40: Cuidar | AY40: Extraer
L41: Reproducir | M41: Transformar | N41: Transferir | P41: Manipular | Q41: Formar | S41: Reproducir | T41: Transformar | U41: Transferir | W41: Manipular | X41: Formar | Y41: Ordenar | Z41: Trazar | AA41: Maniobrar | AB41: Remover | AP41: Premiar | AU41: Narrar | AV41: Duplicar | AW41: Manipular | AX41: Cumplir | AY41: Formular
L42: Revisar | M42: Ubicar | N42: Usar | P42: Mejorar | Q42: Justificar | S42: Revisar | T42: Ubicar | U42: Usar | W42: Mejorar | X42: Justificar | Y42: Organizar | AA42: Manipular | AB42: Reparar | AP42: Probar | AU42: Observar | AV42: Elegir | AW42: Modelar | AX42: Defender | AY42: Identificar
L43: Rotular | N43: Valorar | P43: Modificar | Q43: Juzgar | S43: Rotular | U43: Valorar | W43: Modificar | X43: Juzgar | Y43: Preparar | AA43: Medir | AB43: Reponer | AP43: Recomendar | AU43: Predecir | AV43: Emparejar | AW43: Operar | AX43: Definir | AY43: Juzgar
L44: Seleccionar | P44: Numerar | Q44: Marcar | S44: Seleccionar | W44: Numerar | X44: Marcar | Y44: Probar | AA44: Mezclar | AB44: Reproducir | AP44: Seleccionar | AU44: Preguntar | AV44: Emplear | AW44: Organizar | AX44: Desplegar | AY44: Negociar
L45: Subrayar | P45: Obtener | Q45: Marcar | S45: Subrayar | W45: Obtener | X45: Marcar | Y45: Recaudar | AA45: Mitigar | AB45: Resolver | AP45: Testar | AU45: Presentar | AV45: Encontrar | AW45: Patronar | AX45: Determinar | AY45: Ofrecer
P46: Ordenar | Q46: Medir | W46: Ordenar | X46: Medir | Y46: Recoger | AA46: Modificar | AB46: Retirar | AP46: Valorar | AU46: Relacionar | AV46: Encuestar | AW46: Planear | AX46: Discernir | AY46: Participar
P47: Organizar | Q47: Modificar | W47: Organizar | X47: Modificar | Y47: Recortar | AA47: Mover | AB47: Revisar | AU47: Relatar | AV47: Esquematizar | AW47: Practicar | AX47: Discriminar | AY47: Percibir
P48: Organizar | Q48: Numerar | W48: Organizar | X48: Numerar | Y48: Reunir | AA48: Negociar | AB48: Seguir | AU48: Reportar | AV48: Establecer | AW48: Recoger | AX48: Distinguir | AY48: Preguntar
P49: Perfeccionar | Q49: Peritar | W49: Perfeccionar | X49: Peritar | Y49: Señalar | AA49: Operar | AB49: Servir | AU49: Resumir | AV49: Estimar | AW49: Relacionar | AX49: Ejercer | AY49: Promover
P50: Planear | Q50: Predecir | W50: Planear | X50: Predecir | Y50: Transformar | AA50: Ordenar | AB50: Sincronizar | AU50: Revisar | AV50: Estructurar | AW50: Reportar | AX50: Elegir | AY50: Proponer
P51: Planificar | Q51: Pronosticar | W51: Planificar | X51: Pronosticar | Y51: Trazar | AA51: Organizar | AB51: Soldar | AU51: Seleccionar | AV51: Evaluar | AW51: Resolver | AX51: Ensamblar | AY51: Proporcionar
P52: Poner | Q52: Recomendar | W52: Poner | X52: Recomendar | Y52: Verificar | AA52: Pintar | AB52: Suprimir | AU52: Separar | AV52: Examinar | AW52: Resumir | AX52: Entregar | AY52: Provocar
P53: Predecir | Q53: Repartir | W53: Predecir | X53: Repartir | AA53: Planear | AB53: Sustituir | AU53: Traducir | AV53: Experimentar | AW53: Seleccionar | AX53: Escoger | AY53: Reconocer
P54: Preparar | Q54: Resolver | W54: Preparar | X54: Resolver | AA54: Porcionar | AB54: Tapizar | AU54: Transformar | AV54: Ilustrar | AW54: Simular | AX54: Estimar | AY54: Relacionar
P55: Producir | Q55: Reunir | W55: Producir | X55: Reunir | AA55: Practicar | AB55: Traducir | AU55: Ubicar | AV55: Indicar | AW55: Transferir | AX55: Estimular | AY55: Resumir
P56: Proponer | Q56: Revisar | W56: Proponer | X56: Revisar | AA56: Presentar | AB56: Transmitir | AV56: Inferir | AW56: Unir | AX56: Exteriorizar | AY56: Seleccionar
P57: Proyectar | Q57: Seleccionar | W57: Proyectar | X57: Seleccionar | AA57: Producir | AB57: Trasladar | AV57: Inspeccionar | AW57: Usar | AX57: Extraer | AY57: Ser partidario de
P58: Resolver | Q58: Sistematizar | W58: Resolver | X58: Sistematizar | AA58: Racionar | AB58: Ubicar | AV58: Interpretar | AX58: Fomentar | AY58: Unir
P59: Reunir | Q59: Sugerir | W59: Reunir | X59: Sugerir | AA59: Realizar | AB59: Usar | AV59: Inventariar | AX59: Formular | AY59: Valorar
P60: Señalar | Q60: Tasar | W60: Señalar | X60: Tasar | AA60: Reducir | AB60: Utilizar | AV60: Investigar | AX60: Identificar
P61: Simplificar | Q61: Terminar | W61: Simplificar | X61: Terminar | AA61: Repartir | AB61: Validar | AV61: Listar | AX61: Juzgar
P62: Subdividir | Q62: Unir | W62: Subdividir | X62: Unir | AA62: Repasar | AB62: Verificar | AV62: Manipular | AX62: Negociar
P63: Suponer | Q63: Validar | W63: Suponer | X63: Validar | AA63: Representar | AV63: Medir | AX63: Ofrecer
Q64: Valorar | X64: Valorar | AA64: Revisar | AV64: Modelar | AX64: Participar
Q65: Verificar | X65: Verificar | AA65: Sacar | AV65: Motivar | AX65: Percibir
Q66: Vincular | X66: Vincular | AA66: Separer | AV66: Observar | AX66: Preguntar
AA67: Situar | AV67: Operar | AX67: Preocuparse de o por
AA68: Tocar | AV68: Ordenar | AX68: Promover
AA69: Ubicar | AV69: Organizar | AX69: Proponer
AV70: Patronar | AX70: Proporcionar
AV71: Planear | AX71: Proteger
AV72: Practicar | AX72: Provocar
AV73: Preguntar | AX73: Ratificar
AV74: Priorizar | AX74: Reconocer
AV75: Probar | AX75: Relacionar
AV76: Razonar | AX76: Relatar
AV77: Recoger | AX77: Resumir
AV78: Reconocer | AX78: Revelar
AV79: Relacionar | AX79: Seleccionar
AV80: Reorganizar | AX80: Ser partidario de
AV81: Reportar | AX81: Servir
... AV87: Transferir | AX87: Verificar
AV88: Usar
