Workbook
Name ActitudinalBAK: 'Taxonomias para RA'!$AC$3:$AG$3
Name Bloom: 'Taxonomias para RA'!$G$3:$I$3
Name Circutos: 'Paso 2 Redacción competen'!$F$4
Name CognitivoBAK: 'Taxonomias para RA'!$S$3:$X$3
Name CompetenciaEspecifica1: 'Paso 2 Redacción competen'!$F$4
Name ComponentesCompetencias: 'Paso1 Analisis perfil egreso'!$E$2:$G$2
Name FACULTADES: #REF!
Name ProcedimentalBAK: 'Taxonomias para RA'!$Y$3:$AB$3
Name RA: 'Paso 5 Estrategias micro'!$B$8
Name resultadoaprendizaje: #REF!
Name Saber: 'Paso1 Analisis perfil egreso'!$E$3:$E$5
Name SaberHacer: 'Paso1 Analisis perfil egreso'!$F$3:$F$5
Name SaberSer: 'Paso1 Analisis perfil egreso'!$G$3:$G$5
Name TIC: 'Paso 2 Redacción competen'!$F$6

Sheet Paso1 Analisis perfil egreso
A1: [Escribir el nombre del programa] | B1: [Escribir la modalidad: presencial o virtual] | C1: [Escribir el perfil profesional del egresado.] | D1: [Escribir el perfil ocupacional del egresado.] | E1: Componentes fundamentales aplicables a la solución de problemas en la vida profesional [Listar, según lo escrito en el perfil profesional, qué debe saber el egresado en las categorías de Saber -conocimientos, hechos, teorías-, Saber hacer -técnicas, procedimientos, metodologías-, y Saber ser -valores, condiciones, etc.] | H1: Componentes fundamentales de la ocupación laboral del profesional [Listar, según lo escrito en el perfil ocupacional, en qué áreas, qué tareas potenciales y en qué poblaciones o contextos podrá laborar el profesional.] | K1: Diferencial (valor agregado) del profesional [Listar, según lo escrito en los perfiles, los elementos que son diferenciales y generan un valor agregado al egresado.]
A2: Programa | B2: Modalidad | C2: Perfil profesional | D2: Perfil ocupacional | E2: Saber | F2: SaberHacer | G2: SaberSer | H2: Áreas profesionales | I2: Tareas profesionales | J2: Poblaciones actuación | K2: Valor agregado
A3: Ingeniería de Sistemas | B3: Presencial | C3: El ingeniero de sistemas de la Institución Universitaria Politécnico Grancolombiano posee una formación integral que le permite intervenir en distintas fases de proyectos de tecnologías de la información, generando valor a los procesos organizacionales. Asimismo, diseña e implementa soluciones de software orientadas al desarrollo tecnológico y a la construcción de sistemas computacionales alineados con los objetivos del país. Su desempeño se caracteriza por el uso responsable del conocimiento, la autonomía, el pensamiento crítico y una actitud ética y honesta en el ámbito de los sistemas informáticos y la computación. | D3: El egresado de Ingeniería de Sistemas posee competencias técnicas que le permiten aportar en diversas etapas del ciclo de vida del software y de los sistemas de información. Está preparado para desempeñarse en funciones de desarrollo de aplicaciones, análisis de requerimientos, consultoría, dirección de proyectos, infraestructura tecnológica, arquitectura de la información y gestión de bases de datos, contribuyendo con soluciones innovadoras y eficientes a las demandas del sector productivo nacional. | E3: Ingeniería de software e infraestructura TIC | F3: diseñar soluciones de software | G3: alineadas con prácticas basadas en estándares y marcos de referencia aplicados en los sistemas empresariales u organizacionales. | H3: Análisis de sistemas Desarrollo de software Administración de sistemas Diseño y administración de bases de datos Consultoría de sistemas | I3: Analizar software y sistemas de información Diseñar sistemas TI Diseñar sistemas informáticos Analizar y diseñar sistemas Implemetar procesos de negocio de tecnología de la información proponer arquitecturas de información para análisis de negocio Diseño de software. Aplicar metodologías de desarrollo de software. | J3: Sistemas informáticos Sistemas de producción de software Sistemas informáticos Datos e información de la organización | K3: El graduado en Ingeniería de Sistemas del Politécnico Grancolombiano se distingue por su capacidad de abordar problemas complejos con un enfoque estructurado y analítico, optimizando recursos y diseñando soluciones eficientes. Su formación le permite desarrollar un pensamiento lógico riguroso, descomponer problemas en componentes fundamentales y construir modelos precisos que mejoran el desempeño de los sistemas computacionales. Esta habilidad para razonar con claridad, abstraer conceptos y aplicar principios formales en el desarrollo de tecnología lo convierte en un profesional altamente competitivo, preparado para enfrentar desafíos en diversos campos de la industria, desde la implementación de algoritmos hasta la innovación en software y la toma de decisiones basada en datos.
E4: Esquemas de representación de información | F4: manipular la información adecuadamente | G4: considerando principios de integridad, de acuerdo con los retos propios del sector.
E5: Algoritmia y programación | F5: construir soluciones computacionales | G5: integrando criterios de eficiencia, según las necesidades tecnológicas de las empresas u organizaciones.
E6: Fenómenos contemporáneos | F6: reconocer sus afectaciones o contribuciones en el marco de las ciudadanías globales y de una sociedad responsable y sostenible. | G6: desde una perspectiva global, soportada en datos, con una mirada ética y crítica.

Sheet Paso 2 Redacción competen
A1: Elementos para redactar las competencias que desarrollará el programa
A2: [Enumerar las competencias que se van a declarar.] | B2: [A partir de la celda B2 dar clic sobre el ícono de lista desplegable y elegir el verbo que considere adecuado.] | C2: [A partir de la celda C2 dar clic sobre la lista desplegable y elegir el saber extraído del perfil de egreso.] | D2: [Escribir para qué se abordará el saber elegido. Se sugiere apoyarse en el saber hacer.] | E2: [Escribir la condición describiendo los referentes, parámetros, principios, requerimientos o retos que se necesitan para alcanzar las características del perfil en el contexto donde el egresado se desenvolverá.] | F2: [Articular los componentes. Iniciar con el verbo, continuar con el objeto conceptual, luego la finalidad y condición de contexto o referencia; estos últimos no requieren un orden particular.] | G2: [Escribir el tipo de competencia del perfil: Específica (si es del bloque Disciplinar para pregrado o de los componentes para el caso de posgrado) o Genérica (si aplica bloque institucional pregrado)]
A3: No. | B3: Verbo competencia | C3: Objeto conceptual | D3: Finalidad | E3: Condición de contexto o referencia | F3: Redacción competencia | G3: Tipo de competencia
A4: 1 | B4: Dominar | C4: Ingeniería de software e infraestructura TIC | D4: diseñar soluciones de software | E4: alineadas con prácticas basadas en estándares y marcos de referencia aplicados en los sistemas empresariales u organizacionales. | F4: Dominar los conceptos propios de la ingeniería de software y la infraestructura TIC para diseñar soluciones de software, alineadas con prácticas basadas en estándares y marcos de referencia aplicados en sistemas empresariales u organizacionales. | G4: Específica
A5: 2 | B5: Diseñar | C5: Esquemas de representación de información | D5: manipular la información adecuadamente | E5: considerando principios de integridad, de acuerdo con los retos propios del sector. | F5: Diseñar esquemas de representación para manipular apropiadamente la información, considerando principios de integridad, de acuerdo con los retos propios del sector. | G5: Específica
A6: 3 | B6: Dominar | C6: Algoritmia y programación | D6: construir soluciones computacionales | E6: integrando criterios de eficiencia, según las necesidades tecnológicas de las empresas u organizaciones. | F6: Dominar conceptos de algoritmia y programación para construir soluciones computacionales, integrando criterios de eficiencia, según las necesidades tecnológicas de las empresas u organizaciones. | G6: Específica
A7: 4 | B7: Analizar | C7: Fenómenos contemporáneos | D7: reconocer sus afectaciones o contribuciones en el marco de las ciudadanías globales y de una sociedad responsable y sostenible. | E7: desde una perspectiva global, soportada en datos, con una mirada ética y crítica | F7: Analizar los fenómenos contemporáneos desde una perspectiva glocal, soportada en datos, con una mirada ética y crítica, para reconocer sus afectaciones o contribuciones en el marco de las ciudadanías globales y de una sociedad responsable y sostenible. | G7: Genérica

Sheet Paso 3 Redacción RA
A1: [A partir de la celda A2 dar clic en la lista desplegable y seleccionar la competencia redactada en el paso 2.] | B1: [Enumerar los resultados de aprendizaje que se van a declarar.] | C1: [A partir de la celda C2, dar clic en la lista desplegable y elegir el tipo de dominio a tratar en el resultado de aprendizaje.] | D1: [A partir de la cela D2, dar clic en la lista desplegable y elegir el saber correspondiente al dominio.] | E1: [A partir de la celda E2, dar clic en la lista desplegable y elegir la taxonomía que se considere adecuada, solo se elige una para todos los saberes.] | F1: [A partir de la celda F2, dar clic en la lista desplegable y elegir el dominio que se considera adecuado.] | G1: [A partir de la celda G2, dar clic en la lista desplegable y elegir el nivel del dominio que se considera adecuado.] | H1: [A partir de la celda H2, dar clic en la lista desplegable y elegir el verbo que se considera adecuado.] | I1: [Iniciar con el verbo elegido (columna H), en infinitivo, luego el objeto sobre el cual recae la acción (columna D) y finalmente la condición de contexto (académico, disciplinar, social u otro).]
A2: Competencia por desarrollar | B2: Número de resultado | C2: TipoSaber | D2: SaberAsociado | E2: Taxonomía | F2: Dominio Asociado | G2: Nivel Dominio | H2: Verbo RA | I2: Resultados Aprendizaje
A3: Dominar los conceptos propios de la ingeniería de software y la infraestructura TIC para diseñar soluciones de software, alineadas con prácticas basadas en estándares y marcos de referencia aplicados en sistemas empresariales u organizacionales. | B3: 1 | C3: Saber | D3: Ingeniería de software e infraestructura TIC | E3: BAK | F3: CognitivoBAK | G3: SíntesisBAK | H3: Interpretar | I3: Interpreta patrones de arquitectura y diseño de software, así como de infraestructura TIC, para determinar las necesidades técnicas y tecnológicas de los sistemas de información, según las condiciones que emergen en los proyectos de software.
A4: Dominar los conceptos propios de la ingeniería de software y la infraestructura TIC para diseñar soluciones de software, alineadas con prácticas basadas en estándares y marcos de referencia aplicados en sistemas empresariales u organizacionales. | B4: 3 | C4: SaberHacer | D4: diseñar soluciones de software | E4: BAK | F4: ProcedimentalBAK | G4: PrecisiónBAK | H4: Producir | I4: Produce artefactos de software para estructurar soluciones correspondientes, según las condiciones y restricciones del contexto.
A5: Dominar los conceptos propios de la ingeniería de software y la infraestructura TIC para diseñar soluciones de software, alineadas con prácticas basadas en estándares y marcos de referencia aplicados en sistemas empresariales u organizacionales. | B5: 4 | C5: SaberSer | D5: alineadas con prácticas basadas en estándares y marcos de referencia aplicados en los sistemas empresariales u organizacionales. | E5: BAK | F5: ActitudinalBAK | G5: OrganizarBAK | H5: Identificar | I5: Identifica los requisitos de sistemas que emergen en contextos de desarrollo tecnológico, teniendo en cuenta los referentes técnicos y normativos, para formular propuestas y proyectos, incorporando criterios de eficiencia e integridad en entornos empresariales u organizacionales.
A6: Diseñar esquemas de representación para manipular apropiadamente la información, considerando principios de integridad, de acuerdo con los retos propios del sector. | B6: 5 | C6: Saber | D6: Esquemas de representación de información | E6: BAK | F6: CognitivoBAK | G6: AnálisisBAK | H6: Analizar | I6: Analiza estructuras de representación de datos para determinar su idoneidad en la resolución de problemas computacionales, teniendo en cuenta los requerimientos tecnológicos del contexto.
A7: Diseñar esquemas de representación para manipular apropiadamente la información, considerando principios de integridad, de acuerdo con los retos propios del sector. | B7: 6 | C7: SaberHacer | D7: manipular la información adecuadamente | E7: BAK | F7: ProcedimentalBAK | G7: ControlBAK | H7: Utilizar | I7: Utiliza herramientas y tecnologías de almacenamiento, gestión y transformación de los datos para obtener información, según las condiciones y restricciones que se observen en el contexto.
A8: Diseñar esquemas de representación para manipular apropiadamente la información, considerando principios de integridad, de acuerdo con los retos propios del sector. | B8: 4 | C8: SaberSer | D8: considerando principios de integridad, de acuerdo con los retos propios del sector. | E8: BAK | F8: ActitudinalBAK | G8: OrganizarBAK | H8: Identificar | I8: Identifica los requisitos de sistemas que emergen en contextos de desarrollo tecnológico, teniendo en cuenta los referentes técnicos y normativos, para formular propuestas y proyectos, incorporando criterios de eficiencia e integridad en entornos empresariales u organizacionales.
A9: Dominar conceptos de algoritmia y programación para construir soluciones computacionales, integrando criterios de eficiencia, según las necesidades tecnológicas de las empresas u organizaciones. | B9: 7 | C9: Saber | D9: Algoritmia y programación | E9: BAK | F9: CognitivoBAK | G9: SíntesisBAK | H9: Articular | I9: Articula principios de algoritmia y programación para establecer la viabilidad técnica de soluciones computacionales, según el tipo de usuario y las condiciones del entorno tecnológico.
A10: Dominar conceptos de algoritmia y programación para construir soluciones computacionales, integrando criterios de eficiencia, según las necesidades tecnológicas de las empresas u organizaciones. | B10: 8 | C10: SaberHacer | D10: construir soluciones computacionales | E10: BAK | F10: ProcedimentalBAK | G10: ControlBAK | H10: Implementar | I10: Implementa algoritmos para generar soluciones computacionales, siguiendo métodos, técnicas y estructuras propios de los paradigmas de programación.
A11: Dominar conceptos de algoritmia y programación para construir soluciones computacionales, integrando criterios de eficiencia, según las necesidades tecnológicas de las empresas u organizaciones. | B11: 4 | C11: SaberSer | D11: integrando criterios de eficiencia, según las necesidades tecnológicas de las empresas u organizaciones. | E11: BAK | F11: ActitudinalBAK | G11: OrganizarBAK | H11: Identificar | I11: Identifica los requisitos de sistemas que emergen en contextos de desarrollo tecnológico, teniendo en cuenta los referentes técnicos y normativos, para formular propuestas y proyectos, incorporando criterios de eficiencia e integridad en entornos empresariales u organizacionales.
A12: Analizar los fenómenos contemporáneos desde una perspectiva glocal, soportada en datos, con una mirada ética y crítica, para reconocer sus afectaciones o contribuciones en el marco de las ciudadanías globales y de una sociedad responsable y sostenible. | B12: 2 | C12: Saber | D12: Fenómenos contemporáneos | E12: Bloom | F12: CognitivoB | G12: ComprensiónB | H12: Identificar | I12: Identifica fenómenos contemporáneos y su relación con la profesión, para determinar sus impactos e influencia en la sociedad, de forma responsable y crítica.

Sheet Paso 4 Estrategias mesocurricu
A1: [A partir de la celda A3 despliegue el(los) resultado(s) de aprendizaje y elegir aquel (aquellos) al(a los) que se contribuye desde la estrategia.] | B1: [Escribir el nombre de la estrategia a desarrollar. Participación de los estudiantes en cursos, talleres, seminarios, conferencias, pruebas estandarizadas, investigaciones, actividades o experiencias, cuerpos académicos, redes, comunidades, la elaboración de textos y materiales, así como las publicaciones, entre otros.] | C1: [Describir la(s) estrategia(s) definidas por el programa.] | D1: [Escribir los indicadores de impacto de la estrategia. Se sugieren indicadores como: Valora el nivel de contribución de la estrategia a los resultados de aprendizaje; Número de estudiantes que participan en la estrategia; Número de veces que se realiza la estrategia, entre otros.] | E1: [Escribir las acciones de retroalimentación que usará el programa para comunicar a los estudiantes sobre el alcance de sus resultados de aprendizaje.] | F1: [Escribir, para cada indicador con qué instrumento se recogerá información para evidenciar el (los) impacto (s) declarados. Encuesta, lista de asistencia, informe, entre otros.]
A2: Resultado de aprendizaje | B2: Estrategia del programa | C2: Descripción | D2: Indicador de Impacto de la Estrategia | E2: Acciones de retroalimentación para los estudiantes | F2: Instrumentos de medición
A3: Identifica los requisitos de sistemas que emergen en contextos de desarrollo tecnológico, teniendo en cuenta los referentes técnicos y normativos, para formular propuestas y proyectos, incorporando criterios de eficiencia e integridad en entornos empresariales u organizacionales. | B3: Visitas técnicas | C3: Realización de visitas técnicas presenciales y virtuales a empresas públicas y privadas afines a las asignaturas del programa con el fin de reconocer los elementos conceptuales vistos en el aula en espacios de aplicación real en empresas del sector e identificar los entornos empresariales de aplicación de los conocimientos adquiridos, así como las tendencias de la industria. | D3: Número de estudiantes que participan en la estrategia por año. | E3: Informar a estudiantes y docentes, mediante un informe anual, el grado de alineación entre lo observado en las visitas técnicas y los resultados de aprendizaje del programa. Formar a los estudiantes, a través de talleres posteriores a las visitas, en la aplicación práctica de los conceptos observados en empresas reales. | F3: Listados de participación.
A4: Analiza estructuras de representación de datos para determinar su idoneidad en la resolución de problemas computacionales, teniendo en cuenta los requerimientos tecnológicos del contexto. | D4: Número de veces que se realiza la estrategia por año. | F4: Informe o Reporte.
A5: Articula principios de algoritmia y programación para establecer la viabilidad técnica de soluciones computacionales, según el tipo de usuario y las condiciones del entorno tecnológico. | D5: Valoración del nivel de aporte de la estrategia a los resultados de aprendizaje del programa. | F5: Encuesta de valoración.
A6: Interpreta patrones de arquitectura y diseño de software, así como de infraestructura TIC, para determinar las necesidades técnicas y tecnológicas de los sistemas de información, según las condiciones que emergen en los proyectos de software. | B6: Monitorias académicas | C6: Se proveen los recursos y habilitan los espacios en modalidad presencial, remota o combinada para que estudiantes con excelente desempeño académico, conocimientos y habilidades en asignaturas específicas y cualidades humanas orienten y apoyen a sus compañeros que tienen dificultades en determinados campos del saber con el objetivo de fortalecer las prácticas pedagógicas y el mejoramiento del desempeño académico, en un marco de solidaridad entre estudiantes. | D6: Número de estudiantes que participan en la estrategia por periodo académico. | E6: Prevenir dificultades recurrentes en el aprendizaje al identificar, durante las monitorías, los temas en los que los estudiantes muestran mayores vacíos conceptuales. Ayudar a tomar decisiones sobre ajustes pedagógicos en las asignaturas al sistematizar la información recogida en las monitorías. | F6: Listados de participación.
A7: Analiza estructuras de representación de datos para determinar su idoneidad en la resolución de problemas computacionales, teniendo en cuenta los requerimientos tecnológicos del contexto. | D7: Número de veces que se realiza la estrategia por periodo académico. | F7: Informe o Reporte.
A8: Articula principios de algoritmia y programación para establecer la viabilidad técnica de soluciones computacionales, según el tipo de usuario y las condiciones del entorno tecnológico. | D8: Valoración del nivel de aporte de la estrategia a los resultados de aprendizaje del programa. | F8: Encuesta de valoración.
A9: Interpreta patrones de arquitectura y diseño de software, así como de infraestructura TIC, para determinar las necesidades técnicas y tecnológicas de los sistemas de información, según las condiciones que emergen en los proyectos de software. | B9: Líderes académicos en el aula | C9: Incentivar a los estudiantes que participan de los espacios académicos, desarrollar habilidades blandas como liderazgo, trabajo en equipo, comunicación asertiva, ejerciendo un papel como líder académico al interior del aula. De tal forma que pueda ser un enlace entre el docente y el grupo de estudiantes. | D9: Número de estudiantes que participan en la estrategia. | E9: Formar a los estudiantes líderes en habilidades de comunicación y gestión académica que potencien su papel como enlace entre el docente y el grupo. | F9: Listados de participación.
A10: Analiza estructuras de representación de datos para determinar su idoneidad en la resolución de problemas computacionales, teniendo en cuenta los requerimientos tecnológicos del contexto. | D10: Número de veces que se realiza la estrategia por año. | F10: Informe o Reporte.
A11: Articula principios de algoritmia y programación para establecer la viabilidad técnica de soluciones computacionales, según el tipo de usuario y las condiciones del entorno tecnológico. | D11: Valoración del nivel de aporte de la estrategia a los resultados de aprendizaje del programa. | F11: Encuesta de valoración.
A12: Identifica los requisitos de sistemas que emergen en contextos de desarrollo tecnológico, teniendo en cuenta los referentes técnicos y normativos, para formular propuestas y proyectos, incorporando criterios de eficiencia e integridad en entornos empresariales u organizacionales. | B12: Consultorías, auditorías e interventorias | C12: Designación de expertos en temáticas específicas de las TIC, encargados de definir de forma dinámica los campos de desarrollo de procesos de consultorías, auditorías e interventorías. Creación de espacios conformados por estudiantes, egresados, docentes y expertos capacitados para desarrollar procesos de consultoría y/o auditoría en temáticas asociadas a la ingeniería de telecomunicaciones. | D12: Número de estudiantes que participan en la estrategia por año. | E12: Informar a la comunidad académica sobre los resultados, hallazgos y aprendizajes derivados de los procesos de consultoría, auditoría e interventoría desarrollados con participación estudiantil. Ayudar a tomar decisiones sobre la actualización curricular y las líneas de proyección del programa a partir de la sistematización de los aportes y necesidades identificadas en dichos procesos. | F12: Listados de participación.
A13: Produce artefactos de software para estructurar soluciones correspondientes, según las condiciones y restricciones del contexto. | D13: Número de oportunidades de consultoría, auditoría e interventoría desarrolladas con medición anual. | F13: Informe o Reporte.
A14: Utiliza herramientas y tecnologías de almacenamiento, gestión y transformación de los datos para obtener información, según las condiciones y restricciones que se observen en el contexto. | D14: Valoración del nivel de aporte de la estrategia a los resultados de aprendizaje del programa. | F14: Encuesta de valoración.
A15: Implementa algoritmos para generar soluciones computacionales, siguiendo métodos, técnicas y estructuras propios de los paradigmas de programación. | B15: Grupos de interés (Asociaciones, grupos de estudio) | C15: Grupos estudiantiles adscritos a una agremiación nacional o internacional (ejemplo IEEE) o para el desarrollo de una temática propia del programa (ejemplo grupo de estudio en matemáticas), con el fin de profundizar en los contenidos desarrollados en los espacios académicos, participar en eventos, desarrollar proyectos de formación en investigación, entre otros. | D15: Número de estudiantes que participan en la estrategia por año. | E15: Prevenir la desconexión entre las actividades de los grupos y los objetivos curriculares mediante un seguimiento de sus proyectos y logros. | F15: Listados de participación.
A16: Interpreta patrones de arquitectura y diseño de software, así como de infraestructura TIC, para determinar las necesidades técnicas y tecnológicas de los sistemas de información, según las condiciones que emergen en los proyectos de software. | D16: Relación de actividades desarrolladas en el grupo de interés con actividades del perfil ocupacional del programa. | F16: Informe o Reporte.
A17: Analiza estructuras de representación de datos para determinar su idoneidad en la resolución de problemas computacionales, teniendo en cuenta los requerimientos tecnológicos del contexto. | D17: Valoración del nivel de aporte de la estrategia a los resultados de aprendizaje del programa. | F17: Encuesta de valoración.
A18: Produce artefactos de software para estructurar soluciones correspondientes, según las condiciones y restricciones del contexto. | B18: Semilleros | C18: Grupos de trabajo orientados a la discusión y apropiación en diferentes áreas temáticas propuestas por la facultad, adquiriendo en esta dinámica habilidades investigativas. Se generan a partir del desarrollo de las líneas de investigación del grupo CITIC y estan liderados por docentes con asignación de investigación de la escuela TIC | D18: Número de estudiantes que participan en la estrategia por periodo académico. | E18: Informar periódicamente a estudiantes y docentes sobre los avances, productos y logros obtenidos en los semilleros, destacando su aporte a los resultados de aprendizaje del programa. Formar a los participantes en metodologías de investigación aplicada que fortalezcan su capacidad para producir software, gestionar datos e implementar algoritmos en proyectos académicos. | F18: Listas de participación.
A19: Utiliza herramientas y tecnologías de almacenamiento, gestión y transformación de los datos para obtener información, según las condiciones y restricciones que se observen en el contexto. | D19: Número de veces que se realiza la estrategia por periodo académico. | F19: Informe o Reporte.
A20: Implementa algoritmos para generar soluciones computacionales, siguiendo métodos, técnicas y estructuras propios de los paradigmas de programación. | D20: Valoración del nivel de aporte de la estrategia a los resultados de aprendizaje del programa. | F20: Encuesta de valoración.
A21: Interpreta patrones de arquitectura y diseño de software, así como de infraestructura TIC, para determinar las necesidades técnicas y tecnológicas de los sistemas de información, según las condiciones que emergen en los proyectos de software. | B21: Tutorías | C21: Espacios en los que se recibe ayuda y realimentación por parte de profesores, de manera presencial o en línea, respecto a temas o actividades del diario vivir del estudiante, haciendo uso de las herramientas tecnológicas apropiadas para los fines. | D21: Número de estudiantes que participan en la estrategia por periodo académico. | E21: Prevenir la repetición de dificultades de aprendizaje al registrar y analizar los temas más consultados en las tutorías para orientar mejoras pedagógicas. Ayudar a tomar decisiones sobre la pertinencia de reforzar ciertos contenidos o metodologías en las asignaturas a partir de la evidencia recogida en las tutorías. | F21: Listas de participación.
A23: Analiza estructuras de representación de datos para determinar su idoneidad en la resolución de problemas computacionales, teniendo en cuenta los requerimientos tecnológicos del contexto. | D23: Número de veces que se realiza la estrategia por periodo académico. | F23: Informe o Reporte.
A24: Articula principios de algoritmia y programación para establecer la viabilidad técnica de soluciones computacionales, según el tipo de usuario y las condiciones del entorno tecnológico. | D24: Valoración del nivel de aporte de la estrategia a los resultados de aprendizaje del programa. | F24: Encuesta de valoración.

Sheet Paso 3 Redacción RA - Backup 
A1: [A partir de la celda A2 dar clic en la lista desplegable y seleccionar la competencia redactada en el paso 2.] | B1: [Enumerar los resultados de aprendizaje que se van a declarar.] | C1: [A partir de la celda C2, dar clic en la lista desplegable y elegir el tipo de dominio a tratar en el resultado de aprendizaje.] | D1: [A partir de la cela D2, dar clic en la lista desplegable y elegir el saber correspondiente al dominio.] | E1: [A partir de la celda E2, dar clic en la lista desplegable y elegir la taxonomía que se considere adecuada, solo se elige una para todos los saberes.] | F1: [A partir de la celda F2, dar clic en la lista desplegable y elegir el dominio que se considera adecuado.] | G1: [A partir de la celda G2, dar clic en la lista desplegable y elegir el nivel del dominio que se considera adecuado.] | H1: [A partir de la celda H2, dar clic en la lista desplegable y elegir el verbo que se considera adecuado.] | I1: [Iniciar con el verbo elegido (columna H), en infinitivo, luego el objeto sobre el cual recae la acción (columna D) y finalmente la condición de contexto (académico, disciplinar, social u otro).]
A2: Competencia por desarrollar | B2: Número de resultado | C2: TipoSaber | D2: SaberAsociado | E2: Taxonomía | F2: Dominio Asociado | G2: Nivel Dominio | H2: Verbo RA | I2: Resultados Aprendizaje
A3: Dominar los elementos de teoría de circuitos y transmisión de información para diseñar, implementar o administrar la infraestructura eléctrica y los dispositivos electrónicos que dan soporte a los sistemas de telecomunicaciones alineado con prácticas basadas en estándares del sector y la normatividad vigente, teniendo en cuenta las condiciones, restricciones y requerimientos técnicos del entorno. | B3: 1 | C3: Saber | D3: los elementos de teoría de circuitos y transmisión de información | E3: BAK | F3: CognitivoBAK | G3: ComprensiónBAK | H3: Identificar | I3: Identifica los elementos de teoría de circuitos, de transmisión de información, de seguridad de la información, de redes de comunicaciones, de sistemas de cómputo, de estandares y marcos de referencia que hacen parte de la gestión de proyectos como del desarrollo de actividades relacionadas a las infraestructuras de TIC, para explicar soluciones de diseño, administración o implementación a problemáticas del sector, desde un abordaje teórico-práctico, a través de herramientas de simulación, análisis de casos prácticos y uso de equipos de laboratorio.
A4: Dominar los elementos de teoría de circuitos y transmisión de información para diseñar, implementar o administrar la infraestructura eléctrica y los dispositivos electrónicos que dan soporte a los sistemas de telecomunicaciones alineado con prácticas basadas en estándares del sector y la normatividad vigente, teniendo en cuenta las condiciones, restricciones y requerimientos técnicos del entorno. | B4: 4 | C4: SaberHacer | D4: para diseñar, implementar o administrar la infraestructura eléctrica y los dispositivos electrónicos que dan soporte a los sistemas de telecomunicaciones | E4: BAK | F4: ProcedimentalBAK | G4: ManipulaciónBAK | H4: Aplicar | I4: Aplica los elementos de teoría de circuitos, de transmisión de información, de seguridad de la información, de redes de comunicaciones, de sistemas de cómputo, de estandares tecnológicos y marcos de referencia que hacen parte de la gestión de proyectos como del desarrollo de actividades relacionadas a las infraestructuras de TIC, para construir propuestas de diseño, implementación o administración de infraestructura eléctrica, dispositivos electrónicos, servicios de comunicaciones en nube o en sitio, sistemas de telecomunicaciones, a través de herramientas de simulación, análisis de casos prácticos y uso de equipos de laboratorio.
A5: Dominar los elementos de teoría de circuitos y transmisión de información para diseñar, implementar o administrar la infraestructura eléctrica y los dispositivos electrónicos que dan soporte a los sistemas de telecomunicaciones alineado con prácticas basadas en estándares del sector y la normatividad vigente, teniendo en cuenta las condiciones, restricciones y requerimientos técnicos del entorno. | B5: 7 | C5: SaberSer | D5: alineado con prácticas basadas en estándares del sector y la normatividad vigente, teniendo en cuenta las condiciones, restricciones y requerimientos técnicos del entorno. | E5: BAK | F5: ActitudinalBAK | G5: ValorarBAK | H5: Emplear | I5: Emplea las buenas prácticas de teoría de circuitos y transmisión, y de seguridad de la información, redes y sistemas de cómputo basadas en estándares del sector y la normatividad vigente, teniendo en cuenta las condiciones, restricciones y requerimientos técnicos de un proyecto, para formular soluciones en infraestructuras TIC o del área de las telecomunicaciones.
A6: Dominar los elementos de seguridad de la información, redes de comunicaciones y sistemas de cómputo que hacen parte de infraestructuras TIC para diseñar, implementar o administrar infraestructuras y servicios de comunicaciones en sitio o en nube alineado con prácticas basadas en estándares del sector y la normatividad vigente, teniendo en cuenta las condiciones, restricciones y requerimientos técnicos del entorno. | B6: 1 | C6: Saber | D6: los elementos de seguridad de la información, redes de comunicaciones y sistemas de cómputo que hacen parte de infraestructuras TIC | E6: BAK | F6: CognitivoBAK | G6: ComprensiónBAK | H6: Identificar | I6: Identifica los elementos de teoría de circuitos, de transmisión de información, de seguridad de la información, de redes de comunicaciones, de sistemas de cómputo, de estandares y marcos de referencia que hacen parte de la gestión de proyectos como del desarrollo de actividades relacionadas a las infraestructuras de TIC, para evaluar soluciones a problemáticas del sector, desde un abordaje teórico-práctico, a través de herramientas de simulación, análisis de casos prácticos y uso de equipos de laboratorio.
A7: Dominar los elementos de seguridad de la información, redes de comunicaciones y sistemas de cómputo que hacen parte de infraestructuras TIC para diseñar, implementar o administrar infraestructuras y servicios de comunicaciones en sitio o en nube alineado con prácticas basadas en estándares del sector y la normatividad vigente, teniendo en cuenta las condiciones, restricciones y requerimientos técnicos del entorno. | B7: 5 | C7: SaberHacer | D7: para diseñar, implementar o administrar infraestructuras y servicios de comunicaciones en sitio o en nube | E7: BAK | F7: ProcedimentalBAK | G7: ManipulaciónBAK | H7: Aplicar | I7: Aplica los elementos de teoría de circuitos, de transmisión de información, de seguridad de la información, de redes de comunicaciones, de sistemas de cómputo, de estandares tecnológicos y marcos de referencia que hacen parte de la gestión de proyectos como del desarrollo de actividades relacionadas a las infraestructuras de TIC, para construir propuestas de diseño, implementación o administración de infraestructura eléctrica, dispositivos electrónicos, servicios de comunicaciones en nube o en sitio, sistemas de telecomunicaciones, a través de herramientas de simulación, análisis de casos prácticos y uso de equipos de laboratorio.
A8: Dominar los elementos de seguridad de la información, redes de comunicaciones y sistemas de cómputo que hacen parte de infraestructuras TIC para diseñar, implementar o administrar infraestructuras y servicios de comunicaciones en sitio o en nube alineado con prácticas basadas en estándares del sector y la normatividad vigente, teniendo en cuenta las condiciones, restricciones y requerimientos técnicos del entorno. | B8: 7 | C8: SaberSer | D8: alineado con prácticas basadas en estándares del sector y la normatividad vigente, teniendo en cuenta las condiciones, restricciones y requerimientos técnicos del entorno. | E8: BAK | F8: ActitudinalBAK | G8: ValorarBAK | H8: Emplear | I8: Emplea las buenas prácticas de teoría de circuitos y transmisión, y de seguridad de la información, redes y sistemas de cómputo basadas en estándares del sector y la normatividad vigente, teniendo en cuenta las condiciones, restricciones y requerimientos técnicos de un proyecto, para formular soluciones en infraestructuras TIC o del área de las telecomunicaciones.
A9: Conocer los estándares y marcos de referencia asociados tanto a la gestión de proyectos como al desarrollo de actividades relacionadas a las tecnologías de la información para diseñar, implementar o administrar soluciones del área de las telecomunicaciones, la seguridad de la información y la infraestructura TIC manteniendo una postura socialmente responsable, autónoma, teniendo en cuenta las condiciones, restricciones y requerimientos técnicos del entorno. | B9: 2 | C9: Saber | D9: los estándares y marcos de referencia asociados tanto a la gestión de proyectos como al desarrollo de actividades relacionadas a las tecnologías de la información | E9: BAK | F9: CognitivoBAK | G9: ComprensiónBAK | H9: Identificar | I9: Identifica los elementos de teoría de circuitos, de transmisión de información, de seguridad de la información, de redes de comunicaciones, de sistemas de cómputo, de estandares y marcos de referencia que hacen parte de la gestión de proyectos como del desarrollo de actividades relacionadas a las infraestructuras de TIC, para evaluar soluciones a problemáticas del sector, desde un abordaje teórico-práctico, a través de herramientas de simulación, análisis de casos prácticos y uso de equipos de laboratorio.
A10: Conocer los estándares y marcos de referencia asociados tanto a la gestión de proyectos como al desarrollo de actividades relacionadas a las tecnologías de la información para diseñar, implementar o administrar soluciones del área de las telecomunicaciones, la seguridad de la información y la infraestructura TIC manteniendo una postura socialmente responsable, autónoma, teniendo en cuenta las condiciones, restricciones y requerimientos técnicos del entorno. | B10: 6 | C10: SaberHacer | D10: para diseñar, implementar o administrar soluciones del área de las telecomunicaciones, la seguridad de la información y la infraestructura TIC | E10: BAK | F10: ProcedimentalBAK | G10: ManipulaciónBAK | H10: Aplicar | I10: Aplica los elementos de teoría de circuitos, de transmisión de información, de seguridad de la información, de redes de comunicaciones, de sistemas de cómputo, de estandares tecnológicos y marcos de referencia que hacen parte de la gestión de proyectos como del desarrollo de actividades relacionadas a las infraestructuras de TIC, para construir propuestas de diseño, implementación o administración de infraestructura eléctrica, dispositivos electrónicos, servicios de comunicaciones en nube o en sitio, sistemas de telecomunicaciones, a través de herramientas de simulación, análisis de casos prácticos y uso de equipos de laboratorio.
A11: Conocer los estándares y marcos de referencia asociados tanto a la gestión de proyectos como al desarrollo de actividades relacionadas a las tecnologías de la información para diseñar, implementar o administrar soluciones del área de las telecomunicaciones, la seguridad de la información y la infraestructura TIC manteniendo una postura socialmente responsable, autónoma, teniendo en cuenta las condiciones, restricciones y requerimientos técnicos del entorno. | B11: 7 | C11: SaberSer | D11: manteniendo una postura socialmente responsable, autónoma, teniendo en cuenta las condiciones, restricciones y requerimientos técnicos del entorno. | E11: BAK | F11: ActitudinalBAK | G11: ValorarBAK | H11: Emplear | I11: Emplea las buenas prácticas de teoría de circuitos y transmisión, y de seguridad de la información, redes y sistemas de cómputo basadas en estándares del sector y la normatividad vigente, teniendo en cuenta las condiciones, restricciones y requerimientos técnicos de un proyecto, para formular soluciones en infraestructuras TIC o del área de las telecomunicaciones.
A12: Analizar los fenómenos contemporáneos desde una perspectiva glocal, soportada en datos, con una mirada ética y crítica, para reconocer sus afectaciones o contribuciones en el marco de las ciudadanías globales y de una sociedad responsable y sostenible. | B12: 3 | C12: Saber | D12: Fenómenos contemporáneos | E12: Bloom | F12: CognitivoB | G12: ComprensiónB | H12: Identificar | I12: Identifica fenómenos contemporáneos y su relación con la profesión, para determinar sus impactos e influencia en la sociedad, de forma responsable y crítica.

Sheet Paso 5 Estrategias micro
A1: [Estas celdas se diligencian automáticamente. No ajustar.] | B1: [A partir de la celda A3 despliegue el(los) resultado(s) de aprendizaje y elija aquel (aquellos) al(a los) que se contribuye desde la asignatura o módulo).] | C1: [Escribir el semestre en el que se cursa la asignatura o módulo.] | D1: [Escribir el nombre de la asignatura o módulo que contribuye al logro del resultado de aprendizaje.] | E1: [Redactar los indicadores iniciando con el verbo en presente indicativo, luego el objeto conceptual y finalmente el complemento de oración (que indique una condición o finalidad, con, para, de, entre otros conectores).] | F1: [Escribir la tipología: T (teórico), P (Práctico), TP (Teórico Práctico)] | G1: [Marcar con X el bloque o componente al que pertenece la asignatura o módulo. Por favor ajustar para posgrado, eliminar una columna y ubicar los títulos C.Fundamentación y C.Profundización.] | J1: [Escribir el número de créditos de la asignatura o módulo] | K1: [Escribir el número de horas de trabajo directo: 16*# o 12*#, para presencial o virtual, según sea el caso.] | L1: [Escribir el número de horas de trabajo independiente: 32*# columna J o 36*# columna J, para presencial o virtual, respectivamente.] | M1: [Escribir la suma de los números de horas de las dos celdas anteriores.] | N1: [Escribir el nombre de los cuatro núcleos temáticos que abordará la asignatura o el módulo.] | O1: [Escribir las lecturas, talleres, análisis, referentes, etc., que realiza el estudiante, clasificadas en trabajo directo e independiente.] | P1: [Escribir las actividades de evaluación que se emplean para identificar el alcance del (de los) indicador(es) de logro(s).] | Q1: [Escribir las acciones de retroalimentación que se emplearán en la asignatura o módulo, para retroalimentar a los estudiantes respecto al alcance de los indicadores de logro. Recordar que son cuatro acciones: informar, formar, prevenir y ayudar a tomar decisiones e indique cómo.]
A2: Tipo de Saber | B2: Resultado de aprendizaje | C2: Semestre | D2: Nombre asignatura o módulo | E2: Indicadores de logro asignatura o módulo | F2: Tipología | G2: B.Institucional | H2: B.Disciplinar | I2: B.Electivo | J2: Créditos | K2: Número de horas trabajo directo | L2: Número de horas trabajo independiente | M2: Total de horas | N2: Núcleos temáticos | O2: Actividades de aprendizaje | P2: Actividades de evaluación | Q2: Acciones de retroalimentación
A3: =_xlfn.XLOOKUP(B3,'Paso 3 Redacción RA'!I$3:I$12,'Paso 3 Redacción RA'!C$3:C$12,,0,1) -> Saber | B3: Identifica fenómenos contemporáneos y su relación con la profesión, para determinar sus impactos e influencia en la sociedad, de forma responsable y crítica. | C3: 1 | D3: Razonamiento Cuantitativo | E3: Analiza datos numéricos presentados en tablas, gráficos o textos para proponer soluciones informadas a situaciones problema del contexto. | F3: TP | G3: X | J3: 3 | K3: =16*J3 -> 48 | L3: =32*J3 -> 96 | M3: =SUM(K3:L3) -> 144 | N3: 1. Pensamiento numérico. Interpretación y representación de información numérica 2. Pensamiento algebraico. Desde la representación de regularidades y patrones 3. Pensamiento algebraico. Desde las relaciones de comparación entre cantidades o expresiones numéricas 4. Pensamiento geométrico. Propiedades, formas y relaciones espaciales | O3: Trabajo directo: Clase magistral activa Trabajo independiente: Lecturas Laboratorios, talleres, resolución de problemas | P3: Se sugiere emplear estrategias como las siguientes. Evaluación formativa: Preguntas intercaladas, presentaciones de situaciones problema. Evaluación sumativa: Valoración de laboratorios, talleres, estudios de casos y una evaluación final. | Q3: Las acciones de retroalimentación giran en torno a las siguientes. Formar: donde se crean las condiciones para que los estudiantes adquieran conocimientos, habilidades, actitudes, aptitudes y destrezas. Además, debe promover su desarrollo integral y debe acompañarlos en las situaciones académicas que enfrenten durante el desarrollo de un módulo o una asignatura. Informar: para que los estudiantes identifiquen los cambios que pueden afectarlos directa o indirectamente tanto en el aula de clase como en otros espacios. Prevenir: con el fin de anticiparse a las situaciones académicas que pueden representar dificultad para los estudiantes. Esto se logra a través de la interacción individual con los estudiantes y del completo conocimiento del contexto educativo en que el tutor se desenvuelve. Ayudar a decidir: donde se orienta a los estudiantes para que tomen la mejor decisión ante una situación concreta. El objetivo es que el estudiante fortalezca su autonomía y la toma de decisiones responsable.
A4: =_xlfn.XLOOKUP(B4,'Paso 3 Redacción RA'!I$3:I$12,'Paso 3 Redacción RA'!C$3:C$12,,0,1) -> Saber | B4: Identifica fenómenos contemporáneos y su relación con la profesión, para determinar sus impactos e influencia en la sociedad, de forma responsable y crítica. | C4: 1 | D4: Cultura, Política Y Sociedad | E4: Reconoce las problemáticas, escenarios y mecanismos de participación ciudadana en el marco de sociedades de información y digitales para abordarlas desde iniciativas investigativas. Identifica los objetivos de desarrollo sostenible para la comprensión de problemáticas sociales, ambientales y culturales. Reflexiona los impactos de avances tecnológicos en su contexto profesional y ciudadano para el análisis de contextos situados. | F4: TP | G4: X | J4: 3 | K4: =16*J4 -> 48 | L4: =32*J4 -> 96 | M4: =SUM(K4:L4) -> 144 | N4: 1. ODS, problemas locales: una mirada a Colombia, territorio en búsqueda de la consolidación de la Paz. 2. Ciudadanía y su lugar: relaciones, dinámicas, construcción, expresión y mecanismos de participación. 3. Ecosistemas digitales: relaciones, dinámicas, construcción, expresión e impactos en el contexto profesional. 4. Narrativas y contenidos digitales: análisis de contextos situados. | O4: Trabajo directo: Clase magistral activa combinada con estrategias de aprendizaje basado en investigación Trabajo independiente: Lecturas Laboratorios Talleres Estudios de caso | P4: Evaluación formativa: Construcción de textos argumentativos sobre problemáticas en las sociedades de la información. ,elaboración de ejercicios para la citación en APA última edición., cartografías sociales de problemáticas sociales, culturales y ambientales., elaboración de árbol de problemas, construcción de objetivos generales y específicos, desarrollo de anteproyectos, talleres experienciales con juegos de roles, realización de exposición a través de la caja italiana para el manejo del espacio, la lectura y la oralidad, exposiciones creativas del PIF en el marco del evento “Feria de proyectos” Evaluación sumativa comprende los logros obtenidos en cada actividad y en todo el proceso, representados en porcentajes acumulativos según la parametrización de 0 a 5; Árbol de problemas, Exposiciones Creativas , Seguimiento , Entre Proyecto: Parte 1, Quiz , Seguimiento , Entre Proyecto: Parte 1I , Entrevista a expertos , Feria de proyectos , Seguimiento | Q4: Las acciones de retroalimentación giran en torno a las siguientes. Formar: donde se crean las condiciones para que los estudiantes adquieran conocimientos, habilidades, actitudes, aptitudes y destrezas. Además, debe promover su desarrollo integral y debe acompañarlos en las situaciones académicas que enfrenten durante el desarrollo de un módulo o una asignatura. Informar: para que los estudiantes identifiquen los cambios que pueden afectarlos directa o indirectamente tanto en el aula de clase como en otros espacios. Prevenir: con el fin de anticiparse a las situaciones académicas que pueden representar dificultad para los estudiantes. Esto se logra a través de la interacción individual con los estudiantes y del completo conocimiento del contexto educativo en que el tutor se desenvuelve. Ayudar a decidir: donde se orienta a los estudiantes para que tomen la mejor decisión ante una situación concreta. El objetivo es que el estudiante fortalezca su autonomía y la toma de decisiones responsable.
A5: =_xlfn.XLOOKUP(B5,'Paso 3 Redacción RA'!I$3:I$12,'Paso 3 Redacción RA'!C$3:C$12,,0,1) -> Saber | B5: Interpreta patrones de arquitectura y diseño de software, así como de infraestructura TIC, para determinar las necesidades técnicas y tecnológicas de los sistemas de información, según las condiciones que emergen en los proyectos de software. | C5: 1 | D5: Introducción a las Redes de Datos | E5: Identifica los elementos que hacen parte de una red de telecomunicaciones, para diseñar infraestructuras y servicios de tecnologías de la información y las comunicaciones, teniendo en cuenta condiciones, restricciones y requerimientos técnicos de un proyecto desde un abordaje teórico-práctico, a través de herramientas de simulación, análisis de casos y uso de equipos de laboratorio. Configura los elementos que hacen parte de una red de telecomunicaciones, para implementar infraestructuras y servicios de tecnologías de la información y las comunicaciones, teniendo en cuenta condiciones, restricciones y requerimientos técnicos de un proyecto desde un abordaje teórico-práctico, a través de herramientas de simulación, análisis de casos y uso de equipos de laboratorio. Emplea los elementos que hacen parte de una red de telecomunicaciones, para resolver problemas asociados a la administración de los sistemas de telecomunicaciones, infraestructuras TIC, teniendo en cuenta condiciones, restricciones y requerimientos técnicos, desde un abordaje teórico-práctico, a través de herramientas de simulación, análisis de casos y uso de equipos de laboratorio. | F5: TP | H5: X | J5: 3 | K5: =16*J5 -> 48 | L5: =32*J5 -> 96 | M5: =SUM(K5:L5) -> 144 | N5: 1. Fundamentos de redes de datos 2. Modelos de referencia OSI y TCP/IP 3. Protocolos de comunicación 4. Configuración básica de redes | O5: Las estrategias pueden variar entre estas y otras que emerjan en el proceso formativo. Trabajo directo: Prácticas guiadas de laboratorio y simulación. Clase magistral activa Trabajo independiente: Prácticas de laboratorio y simulación Lecturas Desarrollo de cuestionarios teórico-prácticos Desarrollo de proyectos de aula | P5: Formativa: Trabajo en clase. Sumativa: Pruebas conceptuales. Trabajo en clase. Exámenes. Avances del proyecto de aul | Q5: Las acciones de retroalimentación giran en torno a las siguientes. Formar: donde se crean las condiciones para que los estudiantes adquieran conocimientos, habilidades, actitudes, aptitudes y destrezas. Además, debe promover su desarrollo integral y debe acompañarlos en las situaciones académicas que enfrenten durante el desarrollo de un módulo o una asignatura. Informar: para que los estudiantes identifiquen los cambios que pueden afectarlos directa o indirectamente tanto en el aula de clase como en otros espacios. Prevenir: con el fin de anticiparse a las situaciones académicas que pueden representar dificultad para los estudiantes. Esto se logra a través de la interacción individual con los estudiantes y del completo conocimiento del contexto educativo en que el tutor se desenvuelve. Ayudar a decidir: donde se orienta a los estudiantes para que tomen la mejor decisión ante una situación concreta. El objetivo es que el estudiante fortalezca su autonomía y la toma de decisiones responsable.
A6: =_xlfn.XLOOKUP(B6,'Paso 3 Redacción RA'!I$3:I$12,'Paso 3 Redacción RA'!C$3:C$12,,0,1) -> Saber | B6: Analiza estructuras de representación de datos para determinar su idoneidad en la resolución de problemas computacionales, teniendo en cuenta los requerimientos tecnológicos del contexto.
A7: =_xlfn.XLOOKUP(B7,'Paso 3 Redacción RA'!I$3:I$12,'Paso 3 Redacción RA'!C$3:C$12,,0,1) -> SaberHacer | B7: Utiliza herramientas y tecnologías de almacenamiento, gestión y transformación de los datos para obtener información, según las condiciones y restricciones que se observen en el contexto.
A8: =_xlfn.XLOOKUP(B8,'Paso 3 Redacción RA'!I$3:I$12,'Paso 3 Redacción RA'!C$3:C$12,,0,1) -> Saber | B8: Interpreta patrones de arquitectura y diseño de software, así como de infraestructura TIC, para determinar las necesidades técnicas y tecnológicas de los sistemas de información, según las condiciones que emergen en los proyectos de software. | C8: 1 | D8: Introducción a la Ingeniería y Ciencias Básicas | E8: Reconoce conceptos básicos de ingeniería, herramientas técnicas y principios éticos para identificar problemas sencillos de ingeniería según su naturaleza técnica, social y ambiental. | F8: TP | H8: X | J8: 2 | K8: =16*J8 -> 32 | L8: =32*J8 -> 64 | M8: =SUM(K8:L8) -> 96 | N8: 1. Fundamentos de la Ingeniería 2. Herramientas y Técnicas de Ingeniería 3. Aplicaciones Prácticas y Proyectos 4. Ingeniería y Sostenibilidad | O8: Las estrategias pueden variar entre estas y otras que emerjan en el proceso formativo. Trabajo directo: Clase magistral activa Estudio de casos Resolución de problemas Trabajo independiente: Estudio de casos Resolución de problemas Desarrollo de proyectos Talleres Exposiciones Pruebas escritas | P8: Formativa: Exposiciones PIF Sumativa: Trabajos escritos Exposiciones PIF | Q8: Las acciones de retroalimentación giran en torno a las siguientes. Formar: donde se crean las condiciones para que los estudiantes adquieran conocimientos, habilidades, actitudes, aptitudes y destrezas. Además, debe promover su desarrollo integral y debe acompañarlos en las situaciones académicas que enfrenten durante el desarrollo de un módulo o una asignatura. Informar: para que los estudiantes identifiquen los cambios que pueden afectarlos directa o indirectamente tanto en el aula de clase como en otros espacios. Prevenir: con el fin de anticiparse a las situaciones académicas que pueden representar dificultad para los estudiantes. Esto se logra a través de la interacción individual con los estudiantes y del completo conocimiento del contexto educativo en que el tutor se desenvuelve. Ayudar a decidir: donde se orienta a los estudiantes para que tomen la mejor decisión ante una situación concreta. El objetivo es que el estudiante fortalezca su autonomía y la toma de decisiones responsable.
A9: =_xlfn.XLOOKUP(B9,'Paso 3 Redacción RA'!I$3:I$12,'Paso 3 Redacción RA'!C$3:C$12,,0,1) -> SaberSer | B9: Identifica los requisitos de sistemas que emergen en contextos de desarrollo tecnológico, teniendo en cuenta los referentes técnicos y normativos, para formular propuestas y proyectos, incorporando criterios de eficiencia e integridad en entornos empresariales u organizacionales.
A10: =_xlfn.XLOOKUP(B10,'Paso 3 Redacción RA'!I$3:I$12,'Paso 3 Redacción RA'!C$3:C$12,,0,1) -> Saber | B10: Articula principios de algoritmia y programación para establecer la viabilidad técnica de soluciones computacionales, según el tipo de usuario y las condiciones del entorno tecnológico.
A11: =_xlfn.XLOOKUP(B11,'Paso 3 Redacción RA'!I$3:I$12,'Paso 3 Redacción RA'!C$3:C$12,,0,1) -> Saber | B11: Analiza estructuras de representación de datos para determinar su idoneidad en la resolución de problemas computacionales, teniendo en cuenta los requerimientos tecnológicos del contexto. | C11: 1 | D11: Pensamiento Algorítmico | E11: Identifica variables relevantes, su naturaleza y la forma en que se relacionan para modelar un problema computacional básico. Implementa expresiones matemáticas y estructuras básicas de programación para desarrollar soluciones a problemas computacionales básicos. | F11: T | H11: X | J11: 2 | K11: =16*J11 -> 32 | L11: =32*J11 -> 64 | M11: =SUM(K11:L11) -> 96 | N11: 1. Fundamentos de pensamiento algorítmico 2. Modelado y especificación de problemas 3. Estructuras básicas de un algoritmo 4. Relaciones de recurrencias | O11: Las estrategias pueden variar entre estas y otras que emerjan en el proceso formativo. Trabajo directo: Clase magistral Ejemplos y talleres en clase Trabajo independiente: Lecturas complementarias Talleres de trabajo autónomo Actividades de refuerzo Tutorías o monitorias | P11: Formativa: Trabajo en clase. Sumativa: Pruebas conceptuales. Trabajo en clase. Exámenes. Avances del proyecto de aula. | Q11: Las acciones de retroalimentación giran en torno a las siguientes. Formar: donde se crean las condiciones para que los estudiantes adquieran conocimientos, habilidades, actitudes, aptitudes y destrezas. Además, debe promover su desarrollo integral y debe acompañarlos en las situaciones académicas que enfrenten durante el desarrollo de un módulo o una asignatura. Informar: para que los estudiantes identifiquen los cambios que pueden afectarlos directa o indirectamente tanto en el aula de clase como en otros espacios. Prevenir: con el fin de anticiparse a las situaciones académicas que pueden representar dificultad para los estudiantes. Esto se logra a través de la interacción individual con los estudiantes y del completo conocimiento del contexto educativo en que el tutor se desenvuelve. Ayudar a decidir: donde se orienta a los estudiantes para que tomen la mejor decisión ante una situación concreta. El objetivo es que el estudiante fortalezca su autonomía y la toma de decisiones responsable.
A12: =_xlfn.XLOOKUP(B12,'Paso 3 Redacción RA'!I$3:I$12,'Paso 3 Redacción RA'!C$3:C$12,,0,1) -> Saber | B12: Articula principios de algoritmia y programación para establecer la viabilidad técnica de soluciones computacionales, según el tipo de usuario y las condiciones del entorno tecnológico.
A13: =_xlfn.XLOOKUP(B13,'Paso 3 Redacción RA'!I$3:I$12,'Paso 3 Redacción RA'!C$3:C$12,,0,1) -> SaberHacer | B13: Implementa algoritmos para generar soluciones computacionales, siguiendo métodos, técnicas y estructuras propios de los paradigmas de programación.
A14: =_xlfn.XLOOKUP(B14,'Paso 3 Redacción RA'!I$3:I$12,'Paso 3 Redacción RA'!C$3:C$12,,0,1) -> Saber | B14: Interpreta patrones de arquitectura y diseño de software, así como de infraestructura TIC, para determinar las necesidades técnicas y tecnológicas de los sistemas de información, según las condiciones que emergen en los proyectos de software. | C14: 1 | D14: Pensamiento Sistémico | E14: Identifica las partes que conforman un sistema y las relaciones entre ellas para crear un modelo que lo represente. Crea diagramas sencillos de representación de sistemas para determinar el tipo de retroalimentación entre sus componentes. Discrimina los efectos que tiene cada una de las partes de un sistema sobre las demás para identificar la dinámica emergente del sistema como un todo. | F14: T | H14: X | J14: 4 | K14: =16*J14 -> 64 | L14: =32*J14 -> 128 | M14: =SUM(K14:L14) -> 192 | N14: 1. Fundamentos de pensamiento sistémico 2. Diagramas de bucle causal 3. Dinámica de sistemas 4. Control de sistemas | O14: Las estrategias pueden variar entre estas y otras que emerjan en el proceso formativo. Trabajo directo: Clase magistral Ejemplos y talleres en clase. Trabajo independiente: Lecturas complementarias. Talleres de trabajo autónomo. Actividades de refuerzo. Tutorías o monitorias | P14: Formativa: Trabajo en clase Sumativa: Estudio de casos Resolución de problemas Desarrollo de proyectos Talleres Exposiciones Pruebas escritas | Q14: Las acciones de retroalimentación giran en torno a las siguientes. Formar: donde se crean las condiciones para que los estudiantes adquieran conocimientos, habilidades, actitudes, aptitudes y destrezas. Además, debe promover su desarrollo integral y debe acompañarlos en las situaciones académicas que enfrenten durante el desarrollo de un módulo o una asignatura. Informar: para que los estudiantes identifiquen los cambios que pueden afectarlos directa o indirectamente tanto en el aula de clase como en otros espacios. Prevenir: con el fin de anticiparse a las situaciones académicas que pueden representar dificultad para los estudiantes. Esto se logra a través de la interacción individual con los estudiantes y del completo conocimiento del contexto educativo en que el tutor se desenvuelve. Ayudar a decidir: donde se orienta a los estudiantes para que tomen la mejor decisión ante una situación concreta. El objetivo es que el estudiante fortalezca su autonomía y la toma de decisiones responsable.
A15: =_xlfn.XLOOKUP(B15,'Paso 3 Redacción RA'!I$3:I$12,'Paso 3 Redacción RA'!C$3:C$12,,0,1) -> SaberHacer | B15: Produce artefactos de software para estructurar soluciones correspondientes, según las condiciones y restricciones del contexto.
A16: =_xlfn.XLOOKUP(B16,'Paso 3 Redacción RA'!I$3:I$12,'Paso 3 Redacción RA'!C$3:C$12,,0,1) -> SaberSer | B16: Identifica los requisitos de sistemas que emergen en contextos de desarrollo tecnológico, teniendo en cuenta los referentes técnicos y normativos, para formular propuestas y proyectos, incorporando criterios de eficiencia e integridad en entornos empresariales u organizacionales. | R16: =SUM(J3:J16) -> 17 | S16: =COUNTA(D3:D16) -> 6
A17: =_xlfn.XLOOKUP(B17,'Paso 3 Redacción RA'!I$3:I$12,'Paso 3 Redacción RA'!C$3:C$12,,0,1) -> Saber | B17: Identifica fenómenos contemporáneos y su relación con la profesión, para determinar sus impactos e influencia en la sociedad, de forma responsable y crítica. | C17: 2 | D17: Analisís Y Visualización De Datos | E17: Identifica conceptos básicos relacionados con el análisis y visualización de datos con el propósito de comunicar información relevante de manera efectiva en diversos contextos. Utiliza herramientas para realizar análisis y transformación de datos que garanticen una visualización sencilla y eficiente. Utiliza asistentes virtuales para realizar tareas prácticas y resolver problemas en su campo de estudio. Evalúa la presencia de sesgos y cuestiones éticas en el análisis y tratamiento de dato para garantizar que su uso esté desprovisto de efectos negativos en el entorno. | F17: TP | G17: X | J17: 3 | K17: =16*J17 -> 48 | L17: =32*J17 -> 96 | M17: =SUM(K17:L17) -> 144 | N17: 1. Contextualización 2. Análisis de Datos y Visualización 3. Usos de la Inteligencia Artificial 4. Casos de Estudio | O17: Trabajo directo: Clase magistral activa combinada con estrategias de metodologías activas Trabajo independiente: Lecturas Laboratorios Talleres Estudios de caso. | P17: Se sugiere emplear estrategias como las siguientes. Evaluación formativa: Preguntas intercaladas, presentaciones de situaciones problema, talleres, exposiciones, análisis de casos, trabajos de campo o proyectos. Evaluación sumativa: Valoración de trabajo, talleres, estudios de casos y una evaluación final. | Q17: Las acciones de retroalimentación giran en torno a las siguientes. Formar: donde se crean las condiciones para que los estudiantes adquieran conocimientos, habilidades, actitudes, aptitudes y destrezas. Además, debe promover su desarrollo integral y debe acompañarlos en las situaciones académicas que enfrenten durante el desarrollo de un módulo o una asignatura. Informar: para que los estudiantes identifiquen los cambios que pueden afectarlos directa o indirectamente tanto en el aula de clase como en otros espacios. Prevenir: con el fin de anticiparse a las situaciones académicas que pueden representar dificultad para los estudiantes. Esto se logra a través de la interacción individual con los estudiantes y del completo conocimiento del contexto educativo en que el tutor se desenvuelve. Ayudar a decidir: donde se orienta a los estudiantes para que tomen la mejor decisión ante una situación concreta. El objetivo es que el estudiante fortalezca su autonomía y la toma de decisiones responsable.
A18: =_xlfn.XLOOKUP(B18,'Paso 3 Redacción RA'!I$3:I$12,'Paso 3 Redacción RA'!C$3:C$12,,0,1) -> Saber | B18: Articula principios de algoritmia y programación para establecer la viabilidad técnica de soluciones computacionales, según el tipo de usuario y las condiciones del entorno tecnológico. | C18: 2 | D18: Cálculo Diferencial | E18: Aplica representaciones y razonamientos matemáticos, para analizar situaciones de variación y cambio a partir de la interpretación de resultados en contextos teóricos y aplicados. | F18: TP | H18: X | J18: 4 | K18: =16*J18 -> 64 | L18: =32*J18 -> 128 | M18: =SUM(K18:L18) -> 192 | N18: 1. Funciones de valor real 2. Límites 3. La derivada 4. Aplicaciones de la derivada | O18: Las estrategias pueden variar entre estas y otras que emerjan en el proceso formativo. Trabajo directo: Clases magistrales Talleres /laboratorios Soluciones numéricas Uso de herramientas computacionales Resolución de problemas Trabajo independiente: Lecturas Resolución de problemas Soluciones numéricas Uso de herramientas computacionales | P18: Las estrategias pueden variar entre las siguientes u otras que puedan ser pertinentes para el proceso de aprendizaje. Evaluación formativa: Resolución de problemas. Soluciones numéricas. Uso de herramientas computacionales. Tareas. Evaluación sumativa: Evaluación parcial. Quiz. Taller / Laboratorios. Proyecto de investigación formativa. | Q18: Las acciones de retroalimentación giran en torno a las siguientes. Formar: donde se crean las condiciones para que los estudiantes adquieran conocimientos, habilidades, actitudes, aptitudes y destrezas. Además, debe promover su desarrollo integral y debe acompañarlos en las situaciones académicas que enfrenten durante el desarrollo de un módulo o una asignatura. Informar: para que los estudiantes identifiquen los cambios que pueden afectarlos directa o indirectamente tanto en el aula de clase como en otros espacios. Prevenir: con el fin de anticiparse a las situaciones académicas que pueden representar dificultad para los estudiantes. Esto se logra a través de la interacción individual con los estudiantes y del completo conocimiento del contexto educativo en que el tutor se desenvuelve. Ayudar a decidir: donde se orienta a los estudiantes para que tomen la mejor decisión ante una situación concreta. El objetivo es que el estudiante fortalezca su autonomía y la toma de decisiones responsable.
A19: =_xlfn.XLOOKUP(B19,'Paso 3 Redacción RA'!I$3:I$12,'Paso 3 Redacción RA'!C$3:C$12,,0,1) -> SaberSer | B19: Identifica los requisitos de sistemas que emergen en contextos de desarrollo tecnológico, teniendo en cuenta los referentes técnicos y normativos, para formular propuestas y proyectos, incorporando criterios de eficiencia e integridad en entornos empresariales u organizacionales.
A20: =_xlfn.XLOOKUP(B20,'Paso 3 Redacción RA'!I$3:I$12,'Paso 3 Redacción RA'!C$3:C$12,,0,1) -> Saber | B20: Analiza estructuras de representación de datos para determinar su idoneidad en la resolución de problemas computacionales, teniendo en cuenta los requerimientos tecnológicos del contexto.
A21: =_xlfn.XLOOKUP(B21,'Paso 3 Redacción RA'!I$3:I$12,'Paso 3 Redacción RA'!C$3:C$12,,0,1) -> Saber | B21: Interpreta patrones de arquitectura y diseño de software, así como de infraestructura TIC, para determinar las necesidades técnicas y tecnológicas de los sistemas de información, según las condiciones que emergen en los proyectos de software. | C21: 2 | D21: Programación de Computadores | E21: Describe objetos del mundo real y cómo se relacionan entre ellos para proponer soluciones a problemas computacionales por medio de datos y expresiones matemáticas. Aplica estructuras de control en la construcción de programas para resolver problemas computacionales. | F21: TP | H21: X | J21: 3 | K21: =16*J21 -> 48 | L21: =32*J21 -> 96 | M21: =SUM(K21:L21) -> 144 | N21: 1. Fundamentos de programación de computadores 2. Estructuras de control 3. Estructuras de datos básicas 4. Recursividad | O21: Las estrategias pueden variar entre estas y otras que emerjan en el proceso formativo. Trabajo directo: Clase magistral Ejemplos y talleres en clase. Trabajo independiente: Lecturas complementarias. Talleres de trabajo autónomo. Actividades de refuerzo. Tutorías o monitorias | P21: Las estrategias pueden variar entre las siguientes u otras que puedan ser pertinentes para el proceso de aprendizaje. Evaluación formativa: Resolución de problemas. Soluciones numéricas. Uso de herramientas computacionales. Tareas. Evaluación sumativa: Evaluación parcial. Quiz. Taller / Laboratorios. Proyecto de investigación formativa. | Q21: Las acciones de retroalimentación giran en torno a las siguientes. Formar: donde se crean las condiciones para que los estudiantes adquieran conocimientos, habilidades, actitudes, aptitudes y destrezas. Además, debe promover su desarrollo integral y debe acompañarlos en las situaciones académicas que enfrenten durante el desarrollo de un módulo o una asignatura. Informar: para que los estudiantes identifiquen los cambios que pueden afectarlos directa o indirectamente tanto en el aula de clase como en otros espacios. Prevenir: con el fin de anticiparse a las situaciones académicas que pueden representar dificultad para los estudiantes. Esto se logra a través de la interacción individual con los estudiantes y del completo conocimiento del contexto educativo en que el tutor se desenvuelve. Ayudar a decidir: donde se orienta a los estudiantes para que tomen la mejor decisión ante una situación concreta. El objetivo es que el estudiante fortalezca su autonomía y la toma de decisiones responsable.
A22: =_xlfn.XLOOKUP(B22,'Paso 3 Redacción RA'!I$3:I$12,'Paso 3 Redacción RA'!C$3:C$12,,0,1) -> SaberHacer | B22: Produce artefactos de software para estructurar soluciones correspondientes, según las condiciones y restricciones del contexto.
A23: =_xlfn.XLOOKUP(B23,'Paso 3 Redacción RA'!I$3:I$12,'Paso 3 Redacción RA'!C$3:C$12,,0,1) -> Saber | B23: Articula principios de algoritmia y programación para establecer la viabilidad técnica de soluciones computacionales, según el tipo de usuario y las condiciones del entorno tecnológico.
A24: =_xlfn.XLOOKUP(B24,'Paso 3 Redacción RA'!I$3:I$12,'Paso 3 Redacción RA'!C$3:C$12,,0,1) -> SaberHacer | B24: Implementa algoritmos para generar soluciones computacionales, siguiendo métodos, técnicas y estructuras propios de los paradigmas de programación.
A25: =_xlfn.XLOOKUP(B25,'Paso 3 Redacción RA'!I$3:I$12,'Paso 3 Redacción RA'!C$3:C$12,,0,1) -> SaberSer | B25: Identifica los requisitos de sistemas que emergen en contextos de desarrollo tecnológico, teniendo en cuenta los referentes técnicos y normativos, para formular propuestas y proyectos, incorporando criterios de eficiencia e integridad en entornos empresariales u organizacionales. | C25: 2 | D25: Herramientas de Lógica Computacional | E25: Transforma proposiciones existentes en el mundo real a proposiciones de lógica de predicados para modelar la lógica computacional. Aplica las operaciones de álgebra booleana para determinar valores de verdad de proposiciones. Usa diferentes métodos de demostración para establecer propiedades elementales de los números. | F25: TP | H25: X | J25: 3 | K25: =16*J25 -> 48 | L25: =32*J25 -> 96 | M25: =SUM(K25:L25) -> 144 | N25: 1. Lógica proposicional 2. Métodos de Demostración 3. Cálculo de predicados 4. Introducción a la teoría de conjuntos | O25: Las estrategias pueden variar entre estas y otras que emerjan en el proceso formativo. Trabajo directo: Clase magistral activa Desarrollo de ejercicios en clase Asesorías Extra clase Trabajo independiente: Talleres de aplicación del tema Revisión bibliografía recomendada | P25: Las estrategias pueden variar entre las siguientes u otras que puedan ser pertinentes para el proceso de aprendizaje. Evaluación formativa: Resolución de problemas. Soluciones numéricas. Uso de herramientas computacionales. Tareas. Evaluación sumativa: Evaluación parcial. Quiz. Taller / Laboratorios. Proyecto de investigación formativa. | Q25: Las acciones de retroalimentación giran en torno a las siguientes. Formar: donde se crean las condiciones para que los estudiantes adquieran conocimientos, habilidades, actitudes, aptitudes y destrezas. Además, debe promover su desarrollo integral y debe acompañarlos en las situaciones académicas que enfrenten durante el desarrollo de un módulo o una asignatura. Informar: para que los estudiantes identifiquen los cambios que pueden afectarlos directa o indirectamente tanto en el aula de clase como en otros espacios. Prevenir: con el fin de anticiparse a las situaciones académicas que pueden representar dificultad para los estudiantes. Esto se logra a través de la interacción individual con los estudiantes y del completo conocimiento del contexto educativo en que el tutor se desenvuelve. Ayudar a decidir: donde se orienta a los estudiantes para que tomen la mejor decisión ante una situación concreta. El objetivo es que el estudiante fortalezca su autonomía y la toma de decisiones responsable.
A26: =_xlfn.XLOOKUP(B26,'Paso 3 Redacción RA'!I$3:I$12,'Paso 3 Redacción RA'!C$3:C$12,,0,1) -> Saber | B26: Analiza estructuras de representación de datos para determinar su idoneidad en la resolución de problemas computacionales, teniendo en cuenta los requerimientos tecnológicos del contexto.
A27: =_xlfn.XLOOKUP(B27,'Paso 3 Redacción RA'!I$3:I$12,'Paso 3 Redacción RA'!C$3:C$12,,0,1) -> Saber | B27: Articula principios de algoritmia y programación para establecer la viabilidad técnica de soluciones computacionales, según el tipo de usuario y las condiciones del entorno tecnológico.
A28: =_xlfn.XLOOKUP(B28,'Paso 3 Redacción RA'!I$3:I$12,'Paso 3 Redacción RA'!C$3:C$12,,0,1) -> Saber | B28: Interpreta patrones de arquitectura y diseño de software, así como de infraestructura TIC, para determinar las necesidades técnicas y tecnológicas de los sistemas de información, según las condiciones que emergen en los proyectos de software. | C28: 2 | D28: Análisis y Diseño de Sistemas | E28: Genera modelos de una organización usando herramientas gráficas para identificar los flujos de información en el contexto de un caso de estudio. Identifica necesidades de información para generar un análisis de los requerimientos de información en el contexto de un caso de estudio. | F28: TP | H28: X | J28: 4 | K28: =16*J28 -> 64 | L28: =32*J28 -> 128 | M28: =SUM(K28:L28) -> 192 | N28: 1. Introducción a los sistemas, roles y metodologías de desarrollo 2. Comprensión y modelado de los sistemas organizacionales 3. Análisis de los requerimientos de información 4. Fundamentos del diseño de sistemas | O28: Las estrategias pueden variar entre estas y otras que emerjan en el proceso formativo. Trabajo directo Clase magistral activa Estudio de casos Talleres individuales Trabajo con herramientas digitales Trabajo independiente Lecturas Resolución de problemas Uso de herramientas computacionales Proyectos individuales | P28: Las estrategias pueden variar entre las siguientes u otras que puedan ser pertinentes para el proceso de aprendizaje. Evaluación formativa: Resolución de problemas. Soluciones numéricas. Uso de herramientas computacionales. Tareas. Evaluación sumativa: Evaluación parcial. Quiz. Taller / Laboratorios. Proyecto de investigación formativa. | Q28: Las acciones de retroalimentación giran en torno a las siguientes. Formar: donde se crean las condiciones para que los estudiantes adquieran conocimientos, habilidades, actitudes, aptitudes y destrezas. Además, debe promover su desarrollo integral y debe acompañarlos en las situaciones académicas que enfrenten durante el desarrollo de un módulo o una asignatura. Informar: para que los estudiantes identifiquen los cambios que pueden afectarlos directa o indirectamente tanto en el aula de clase como en otros espacios. Prevenir: con el fin de anticiparse a las situaciones académicas que pueden representar dificultad para los estudiantes. Esto se logra a través de la interacción individual con los estudiantes y del completo conocimiento del contexto educativo en que el tutor se desenvuelve. Ayudar a decidir: donde se orienta a los estudiantes para que tomen la mejor decisión ante una situación concreta. El objetivo es que el estudiante fortalezca su autonomía y la toma de decisiones responsable.
A29: =_xlfn.XLOOKUP(B29,'Paso 3 Redacción RA'!I$3:I$12,'Paso 3 Redacción RA'!C$3:C$12,,0,1) -> SaberHacer | B29: Produce artefactos de software para estructurar soluciones correspondientes, según las condiciones y restricciones del contexto.
A30: =_xlfn.XLOOKUP(B30,'Paso 3 Redacción RA'!I$3:I$12,'Paso 3 Redacción RA'!C$3:C$12,,0,1) -> SaberSer | B30: Identifica los requisitos de sistemas que emergen en contextos de desarrollo tecnológico, teniendo en cuenta los referentes técnicos y normativos, para formular propuestas y proyectos, incorporando criterios de eficiencia e integridad en entornos empresariales u organizacionales.
A31: =_xlfn.XLOOKUP(B31,'Paso 3 Redacción RA'!I$3:I$12,'Paso 3 Redacción RA'!C$3:C$12,,0,1) -> Saber | B31: Articula principios de algoritmia y programación para establecer la viabilidad técnica de soluciones computacionales, según el tipo de usuario y las condiciones del entorno tecnológico. | R31: =SUM(J17:J31) -> 17 | S31: =COUNTA(D17:D31) -> 5
A32: =_xlfn.XLOOKUP(B32,'Paso 3 Redacción RA'!I$3:I$12,'Paso 3 Redacción RA'!C$3:C$12,,0,1) -> Saber | B32: Identifica fenómenos contemporáneos y su relación con la profesión, para determinar sus impactos e influencia en la sociedad, de forma responsable y crítica. | C32: 3 | D32: Oportunidades para Emprender | E32: Propone soluciones a los problemas, frustraciones y expectativas de un grupo de personas en su comunidad para idear productos o servicios con valor agregado dentro de su campo de acción profesional. Diseña una idea de negocio que represente una oportunidad de mercado teniendo en cuenta sus habilidades para emprender y el análisis del entorno. | F32: TP | G32: X | J32: 3 | K32: =16*J32 -> 48 | L32: =32*J32 -> 96 | M32: =SUM(K32:L32) -> 144 | N32: 1. Empatía y Comprensión del Usuario 2. Co-creación con los Usuarios 3. Enfoque en la Experiencia del Usuario 4. Diseño del modelo de negocio | O32: Trabajo directo: Clase magistral activa combinada con estrategias de metodologías activas Trabajo independiente: Lecturas. Laboratorios, talleres, estudios de caso. | P32: Se sugiere emplear estrategias como las siguientes. Evaluación formativa: Preguntas intercaladas, presentaciones de situaciones problema, talleres, exposiciones, análisis de casos, trabajos de campo o proyectos. Evaluación sumativa: Valoración de trabajo, talleres, estudios de casos y una evaluación final. | Q32: Las acciones de retroalimentación giran en torno a las siguientes. Formar: donde se crean las condiciones para que los estudiantes adquieran conocimientos, habilidades, actitudes, aptitudes y destrezas. Además, debe promover su desarrollo integral y debe acompañarlos en las situaciones académicas que enfrenten durante el desarrollo de un módulo o una asignatura. Informar: para que los estudiantes identifiquen los cambios que pueden afectarlos directa o indirectamente tanto en el aula de clase como en otros espacios. Prevenir: con el fin de anticiparse a las situaciones académicas que pueden representar dificultad para los estudiantes. Esto se logra a través de la interacción individual con los estudiantes y del completo conocimiento del contexto educativo en que el tutor se desenvuelve. Ayudar a decidir: donde se orienta a los estudiantes para que tomen la mejor decisión ante una situación concreta. El objetivo es que el estudiante fortalezca su autonomía y la toma de decisiones responsable.
A33: =_xlfn.XLOOKUP(B33,'Paso 3 Redacción RA'!I$3:I$12,'Paso 3 Redacción RA'!C$3:C$12,,0,1) -> Saber | B33: Identifica fenómenos contemporáneos y su relación con la profesión, para determinar sus impactos e influencia en la sociedad, de forma responsable y crítica. | C33: 3 | D33: Pensamiento Crítico y Ciudadanías Activas | E33: Identifica los Derechos y Deberes consignados en la Constitución 1991 en relación con la ciudadanía de manera local y global para la comprensión de inmersiones sociales éticas. Reflexiona los impactos de la investigación- acción sin daño en los espacios académicos y los territorios para el abordaje desde proyectos de investigación formativa. Elabora el diseño de planes detallados desde abordajes investigativos e inmersiones creativas para divulgar hallazgos en el ámbito académico. | F33: TP | G33: X | J33: 3 | K33: =16*J33 -> 48 | L33: =32*J33 -> 96 | M33: =SUM(K33:L33) -> 144 | N33: 1. Pacto social colombiano y marco de referencias de DDHH internacionales 2. Planes detallados e inmersiones sociales desde procesos participativos, acciones sociales e iniciativas ciudadanas como respuesta a problemas glocales 3. Perspectivas para la participación ciudadana en los territorios 4. Los avances tecnológicos y su impacto en lo social, cultural y ambiental en el marco de las sociedades de información | O33: Trabajo directo: Encuentros presenciales con las horas asignadas a la semana para el desarrollo de la asignatura Aprendizaje basado en problemas Trabajo independiente: Resumen (incluyendo la lectura de textos narrativos, expositivos y argumentativos) Análisis crítico de noticias sociales, culturales y ambientales Elaboración de Árbol de problemas como técnica para planteamiento de problemas del PIF Talleres individuales y por grupos sobre la tipología de textos | P33: Construcción de planes detallados según las problemáticas desarrolladas en la asignatura. Evaluación y autoevaluación de Anteproyectos entre pares académicos a través de la guía “Lecturas cruzadas” Reflexión y análisis sobre la ética y la mora en sus contextos locales, globales y profesionales. Comprensión de conceptos temáticas a través de cine documental y cine foros. Exploración de estrategias y actividades para los planes detallados. Desarrollo de anteproyectos. Talleres experienciales con juegos de roles. Realización de exposición a través de la caja italiana para el manejo del espacio, la lectura y la oralidad. Exposiciones creativas del PIF en el marco del evento “Feria de proyectos” | Q33: Las acciones de retroalimentación giran en torno a las siguientes. Formar: donde se crean las condiciones para que los estudiantes adquieran conocimientos, habilidades, actitudes, aptitudes y destrezas. Además, debe promover su desarrollo integral y debe acompañarlos en las situaciones académicas que enfrenten durante el desarrollo de un módulo o una asignatura. Informar: para que los estudiantes identifiquen los cambios que pueden afectarlos directa o indirectamente tanto en el aula de clase como en otros espacios. Prevenir: con el fin de anticiparse a las situaciones académicas que pueden representar dificultad para los estudiantes. Esto se logra a través de la interacción individual con los estudiantes y del completo conocimiento del contexto educativo en que el tutor se desenvuelve. Ayudar a decidir: donde se orienta a los estudiantes para que tomen la mejor decisión ante una situación concreta. El objetivo es que el estudiante fortalezca su autonomía y la toma de decisiones responsable.
A34: =_xlfn.XLOOKUP(B34,'Paso 3 Redacción RA'!I$3:I$12,'Paso 3 Redacción RA'!C$3:C$12,,0,1) -> Saber | B34: Interpreta patrones de arquitectura y diseño de software, así como de infraestructura TIC, para determinar las necesidades técnicas y tecnológicas de los sistemas de información, según las condiciones que emergen en los proyectos de software. | C34: 3 | D34: Elementos de Teorías de la Computación | E34: Aplica los conceptos lógicos y conjuntistas para demostrar propiedades de las operaciones conjuntistas. Analiza ecuaciones recurrentes para modelar fenómenos sucesivos. Usa de manera correcta conceptos de conteo para resolver problemas prácticos o teóricos. | F34: TP | H34: X | J34: 3 | K34: =16*J34 -> 48 | L34: =32*J34 -> 96 | M34: =SUM(K34:L34) -> 144 | N34: 1. Técnicas de demostración en teoría elemental de conjuntos 2. Ecuaciones recurrentes e inducción matemática 3. Aritmética modular 4. Permutaciones y combinaciones | O34: Las estrategias pueden variar entre estas y otras que emerjan en el proceso formativo. Trabajo directo: Clase magistral activa Desarrollo de ejercicios en clase Asesorías Extra clase Trabajo independiente: Talleres de aplicación del tema Revisión bibliografía recomendada Actividades de refuerzo | P34: Las estrategias pueden variar entre las siguientes u otras que puedan ser pertinentes para el proceso de aprendizaje. Evaluación formativa: Resolución de problemas. Soluciones numéricas. Uso de herramientas computacionales. Tareas. Evaluación sumativa: Evaluación parcial. Quiz. Taller / Laboratorios. Proyecto de investigación formativa. | Q34: Las acciones de retroalimentación giran en torno a las siguientes. Formar: donde se crean las condiciones para que los estudiantes adquieran conocimientos, habilidades, actitudes, aptitudes y destrezas. Además, debe promover su desarrollo integral y debe acompañarlos en las situaciones académicas que enfrenten durante el desarrollo de un módulo o una asignatura. Informar: para que los estudiantes identifiquen los cambios que pueden afectarlos directa o indirectamente tanto en el aula de clase como en otros espacios. Prevenir: con el fin de anticiparse a las situaciones académicas que pueden representar dificultad para los estudiantes. Esto se logra a través de la interacción individual con los estudiantes y del completo conocimiento del contexto educativo en que el tutor se desenvuelve. Ayudar a decidir: donde se orienta a los estudiantes para que tomen la mejor decisión ante una situación concreta. El objetivo es que el estudiante fortalezca su autonomía y la toma de decisiones responsable.
A35: =_xlfn.XLOOKUP(B35,'Paso 3 Redacción RA'!I$3:I$12,'Paso 3 Redacción RA'!C$3:C$12,,0,1) -> SaberSer | B35: Identifica los requisitos de sistemas que emergen en contextos de desarrollo tecnológico, teniendo en cuenta los referentes técnicos y normativos, para formular propuestas y proyectos, incorporando criterios de eficiencia e integridad en entornos empresariales u organizacionales.
A36: =_xlfn.XLOOKUP(B36,'Paso 3 Redacción RA'!I$3:I$12,'Paso 3 Redacción RA'!C$3:C$12,,0,1) -> Saber | B36: Analiza estructuras de representación de datos para determinar su idoneidad en la resolución de problemas computacionales, teniendo en cuenta los requerimientos tecnológicos del contexto.
A37: =_xlfn.XLOOKUP(B37,'Paso 3 Redacción RA'!I$3:I$12,'Paso 3 Redacción RA'!C$3:C$12,,0,1) -> Saber | B37: Analiza estructuras de representación de datos para determinar su idoneidad en la resolución de problemas computacionales, teniendo en cuenta los requerimientos tecnológicos del contexto. | C37: 3 | D37: Estructuras de Datos | E37: Aplica conceptos de análisis de algoritmos y notación asintótica para determinar la complejidad temporal y espacial de un programa. Describe objetos del mundo real y cómo se relacionan entre ellos para proponer soluciones a problemas computacionales por medio de estructuras de datos. | F37: TP | H37: X | J37: 3 | K37: =16*J37 -> 48 | L37: =32*J37 -> 96 | M37: =SUM(K37:L37) -> 144 | N37: 1. Introducción al análisis de algoritmos 2. Estructuras de datos lineales 3. Estructuras de datos jerárquicas 4. Tablas hash y grafos | O37: Las estrategias pueden variar entre estas y otras que emerjan en el proceso formativo. Trabajo directo: Clase magistral Ejemplos y talleres en clase. Trabajo independiente: Lecturas complementarias. Talleres de trabajo autónomo. Actividades de refuerzo. | P37: Las estrategias pueden variar entre las siguientes u otras que puedan ser pertinentes para el proceso de aprendizaje. Evaluación formativa: Resolución de problemas. Soluciones numéricas. Uso de herramientas computacionales. Tareas. Evaluación sumativa: Evaluación parcial. Quiz. Taller / Laboratorios. Proyecto de investigación formativa. | Q37: Las acciones de retroalimentación giran en torno a las siguientes. Formar: donde se crean las condiciones para que los estudiantes adquieran conocimientos, habilidades, actitudes, aptitudes y destrezas. Además, debe promover su desarrollo integral y debe acompañarlos en las situaciones académicas que enfrenten durante el desarrollo de un módulo o una asignatura. Informar: para que los estudiantes identifiquen los cambios que pueden afectarlos directa o indirectamente tanto en el aula de clase como en otros espacios. Prevenir: con el fin de anticiparse a las situaciones académicas que pueden representar dificultad para los estudiantes. Esto se logra a través de la interacción individual con los estudiantes y del completo conocimiento del contexto educativo en que el tutor se desenvuelve. Ayudar a decidir: donde se orienta a los estudiantes para que tomen la mejor decisión ante una situación concreta. El objetivo es que el estudiante fortalezca su autonomía y la toma de decisiones responsable.
A38: =_xlfn.XLOOKUP(B38,'Paso 3 Redacción RA'!I$3:I$12,'Paso 3 Redacción RA'!C$3:C$12,,0,1) -> Saber | B38: Articula principios de algoritmia y programación para establecer la viabilidad técnica de soluciones computacionales, según el tipo de usuario y las condiciones del entorno tecnológico.
A39: =_xlfn.XLOOKUP(B39,'Paso 3 Redacción RA'!I$3:I$12,'Paso 3 Redacción RA'!C$3:C$12,,0,1) -> SaberHacer | B39: Implementa algoritmos para generar soluciones computacionales, siguiendo métodos, técnicas y estructuras propios de los paradigmas de programación.
A40: =_xlfn.XLOOKUP(B40,'Paso 3 Redacción RA'!I$3:I$12,'Paso 3 Redacción RA'!C$3:C$12,,0,1) -> SaberSer | B40: Identifica los requisitos de sistemas que emergen en contextos de desarrollo tecnológico, teniendo en cuenta los referentes técnicos y normativos, para formular propuestas y proyectos, incorporando criterios de eficiencia e integridad en entornos empresariales u organizacionales. | C40: 3 | D40: Paradigmas de Programación | E40: Elige un lenguaje de programación según las características del paradigma para construir soluciones apropiadas. Usa un lenguaje orientado a objetos para desarrollar programas aplicando los conceptos que lo definen. Emplea los paradigmas de programación funcional y lógico para la creación de programas simples. | F40: TP | H40: X | J40: 3 | K40: =16*J40 -> 48 | L40: =32*J40 -> 96 | M40: 192 | N40: 1. Exploración de los principales paradigmas de programación 2. Paradigma de programación orientada a objetos 3. Paradigma de programación funcional 4. Paradigma de programación lógica | O40: Las estrategias pueden variar entre estas y otras que emerjan en el proceso formativo. Trabajo directo: Clase magistral, Talleres en clase Trabajo independiente: Lecturas complementarias (capítulos de libros y artículos), listas de ejercicios para trabajo en casa, uso de recursos multimedia disponibles en la web. | P40: Las estrategias pueden variar entre las siguientes u otras que puedan ser pertinentes para el proceso de aprendizaje. Evaluación formativa: Resolución de problemas. Soluciones numéricas. Uso de herramientas computacionales. Tareas. Evaluación sumativa: Evaluación parcial. Quiz. Taller / Laboratorios. Proyecto de investigación formativa. | Q40: Las acciones de retroalimentación giran en torno a las siguientes. Formar: donde se crean las condiciones para que los estudiantes adquieran conocimientos, habilidades, actitudes, aptitudes y destrezas. Además, debe promover su desarrollo integral y debe acompañarlos en las situaciones académicas que enfrenten durante el desarrollo de un módulo o una asignatura. Informar: para que los estudiantes identifiquen los cambios que pueden afectarlos directa o indirectamente tanto en el aula de clase como en otros espacios. Prevenir: con el fin de anticiparse a las situaciones académicas que pueden representar dificultad para los estudiantes. Esto se logra a través de la interacción individual con los estudiantes y del completo conocimiento del contexto educativo en que el tutor se desenvuelve. Ayudar a decidir: donde se orienta a los estudiantes para que tomen la mejor decisión ante una situación concreta. El objetivo es que el estudiante fortalezca su autonomía y la toma de decisiones responsable.
A41: =_xlfn.XLOOKUP(B41,'Paso 3 Redacción RA'!I$3:I$12,'Paso 3 Redacción RA'!C$3:C$12,,0,1) -> Saber | B41: Articula principios de algoritmia y programación para establecer la viabilidad técnica de soluciones computacionales, según el tipo de usuario y las condiciones del entorno tecnológico.
A42: =_xlfn.XLOOKUP(B42,'Paso 3 Redacción RA'!I$3:I$12,'Paso 3 Redacción RA'!C$3:C$12,,0,1) -> SaberHacer | B42: Implementa algoritmos para generar soluciones computacionales, siguiendo métodos, técnicas y estructuras propios de los paradigmas de programación.
A43: =_xlfn.XLOOKUP(B43,'Paso 3 Redacción RA'!I$3:I$12,'Paso 3 Redacción RA'!C$3:C$12,,0,1) -> SaberSer | B43: Identifica los requisitos de sistemas que emergen en contextos de desarrollo tecnológico, teniendo en cuenta los referentes técnicos y normativos, para formular propuestas y proyectos, incorporando criterios de eficiencia e integridad en entornos empresariales u organizacionales. | C43: 3 | D43: Álgebra Lineal | E43: Establece conexiones entre los objetos, conceptos y procesos del álgebra lineal para resolver diferentes situaciones en contextos reales o teóricos. | F43: TP | H43: X | J43: 3 | K43: =16*J43 -> 48 | L43: =32*J43 -> 96 | M43: 192 | N43: 1. Álgebra matricial, determinantes y sistemas de ecuaciones lineales. 2. Vectores, geometría en ℝⁿ y operaciones vectoriales. 3. Espacios vectoriales y estructura algebraica. 4. Transformaciones lineales y operadores. | O43: Las estrategias pueden variar entre estas y otras que emerjan en el proceso formativo. Trabajo directo: Clases magistrales Talleres / Laboratorios Soluciones numéricas Uso de herramientas computacionales Resolución de problemas Trabajo independiente: Lecturas Resolución de problemas Soluciones numéricas Uso de herramientas computacionales | P43: Las estrategias pueden variar entre las siguientes u otras que puedan ser pertinentes para el proceso de aprendizaje. Evaluación formativa: Resolución de problemas. Soluciones numéricas. Uso de herramientas computacionales. Tareas. Evaluación sumativa: Evaluación parcial. Quiz. Taller / Laboratorios. Proyecto de investigación formativa. | Q43: Las acciones de retroalimentación giran en torno a las siguientes. Formar: donde se crean las condiciones para que los estudiantes adquieran conocimientos, habilidades, actitudes, aptitudes y destrezas. Además, debe promover su desarrollo integral y debe acompañarlos en las situaciones académicas que enfrenten durante el desarrollo de un módulo o una asignatura. Informar: para que los estudiantes identifiquen los cambios que pueden afectarlos directa o indirectamente tanto en el aula de clase como en otros espacios. Prevenir: con el fin de anticiparse a las situaciones académicas que pueden representar dificultad para los estudiantes. Esto se logra a través de la interacción individual con los estudiantes y del completo conocimiento del contexto educativo en que el tutor se desenvuelve. Ayudar a decidir: donde se orienta a los estudiantes para que tomen la mejor decisión ante una situación concreta. El objetivo es que el estudiante fortalezca su autonomía y la toma de decisiones responsable.
A44: =_xlfn.XLOOKUP(B44,'Paso 3 Redacción RA'!I$3:I$12,'Paso 3 Redacción RA'!C$3:C$12,,0,1) -> Saber | B44: Analiza estructuras de representación de datos para determinar su idoneidad en la resolución de problemas computacionales, teniendo en cuenta los requerimientos tecnológicos del contexto.
A45: =_xlfn.XLOOKUP(B45,'Paso 3 Redacción RA'!I$3:I$12,'Paso 3 Redacción RA'!C$3:C$12,,0,1) -> Saber | B45: Articula principios de algoritmia y programación para establecer la viabilidad técnica de soluciones computacionales, según el tipo de usuario y las condiciones del entorno tecnológico. | R45: =SUM(J32:J45) -> 18 | S45: =COUNTA(D32:D45) -> 6
A46: =_xlfn.XLOOKUP(B46,'Paso 3 Redacción RA'!I$3:I$12,'Paso 3 Redacción RA'!C$3:C$12,,0,1) -> Saber | B46: Identifica fenómenos contemporáneos y su relación con la profesión, para determinar sus impactos e influencia en la sociedad, de forma responsable y crítica. | C46: 4 | D46: Desarrollo Sostenible | E46: Identifica ejemplos de problemas ambientales, sociales y económicos en la sociedad contemporánea para analizar sus causas y efectos desde el enfoque del desarrollo sostenible a escala local y global. Compara enfoques y aproximaciones tanto privados como público/colectivos desde la sostenibilidad y otras visiones alternativas para proponer ideas de solución que respondan a los desafíos contemporáneos. | F46: TP | G46: X | J46: 3 | K46: =16*J46 -> 48 | L46: =32*J46 -> 96 | M46: =SUM(K46:L46) -> 144 | N46: 1. Análisis de la Era del Antropoceno 2. Otras Alternativas al Desarrollo Sostenible 3. Ciudadanía y Políticas Públicas para el Desarrollo Sostenible 4. El aporte de Negocios para la Búsqueda del Desarrollo Sostenible | O46: Trabajo directo: Clase magistral activa combinada con estrategias de metodologías activas Trabajo independiente: Lecturas. Laboratorios, talleres, estudios de caso. | P46: Se sugiere emplear estrategias como las siguientes. Evaluación formativa: Preguntas intercaladas, presentaciones de situaciones problema, talleres, exposiciones, análisis de casos, trabajos de campo o proyectos. Evaluación sumativa: Valoración de trabajo, talleres, estudios de casos y una evaluación final. | Q46: Las acciones de retroalimentación giran en torno a las siguientes. Formar: donde se crean las condiciones para que los estudiantes adquieran conocimientos, habilidades, actitudes, aptitudes y destrezas. Además, debe promover su desarrollo integral y debe acompañarlos en las situaciones académicas que enfrenten durante el desarrollo de un módulo o una asignatura. Informar: para que los estudiantes identifiquen los cambios que pueden afectarlos directa o indirectamente tanto en el aula de clase como en otros espacios. Prevenir: con el fin de anticiparse a las situaciones académicas que pueden representar dificultad para los estudiantes. Esto se logra a través de la interacción individual con los estudiantes y del completo conocimiento del contexto educativo en que el tutor se desenvuelve. Ayudar a decidir: donde se orienta a los estudiantes para que tomen la mejor decisión ante una situación concreta. El objetivo es que el estudiante fortalezca su autonomía y la toma de decisiones responsable.
A47: =_xlfn.XLOOKUP(B47,'Paso 3 Redacción RA'!I$3:I$12,'Paso 3 Redacción RA'!C$3:C$12,,0,1) -> Saber | B47: Analiza estructuras de representación de datos para determinar su idoneidad en la resolución de problemas computacionales, teniendo en cuenta los requerimientos tecnológicos del contexto. | C47: 4 | D47: Bases de Datos | E47: Identifica las estructuras de las bases de datos como los atributos, tablas, llaves y tipos de relaciones que conforman una entidad de una base de datos relacional para aplicarlos en un sistema de información en el tiempo real. Utiliza el lenguaje de diseño, construcción y administración de bases de datos, para desarrollar sistemas de información. | F47: TP | H47: X | J47: 3 | K47: =16*J47 -> 48 | L47: =32*J47 -> 96 | M47: =SUM(K47:L47) -> 144 | N47: 1. Generalidades de las bases de datos relacionales vs NoSQL 2. Modelo conceptual y normalización 3. Modelo lógico y álgebra relacional 4. Modelo físico, SQL, PLSQL y caso de estudio | O47: Las estrategias pueden variar entre estas y otras que emerjan en el proceso formativo. Trabajo directo: Clase magistral activa Practicas guiadas de laboratorio Talleres programados con casos reales Trabajo independiente Prácticas de aplicación y laboratorio Lecturas Desarrollo de proyecto de aula | P47: Las estrategias pueden variar entre las siguientes u otras que puedan ser pertinentes para el proceso de aprendizaje. Evaluación formativa: Resolución de problemas. Soluciones numéricas. Uso de herramientas computacionales. Tareas. Evaluación sumativa: Evaluación parcial. Quiz. Taller / Laboratorios. Proyecto de investigación formativa. | Q47: Las acciones de retroalimentación giran en torno a las siguientes. Formar: donde se crean las condiciones para que los estudiantes adquieran conocimientos, habilidades, actitudes, aptitudes y destrezas. Además, debe promover su desarrollo integral y debe acompañarlos en las situaciones académicas que enfrenten durante el desarrollo de un módulo o una asignatura. Informar: para que los estudiantes identifiquen los cambios que pueden afectarlos directa o indirectamente tanto en el aula de clase como en otros espacios. Prevenir: con el fin de anticiparse a las situaciones académicas que pueden representar dificultad para los estudiantes. Esto se logra a través de la interacción individual con los estudiantes y del completo conocimiento del contexto educativo en que el tutor se desenvuelve. Ayudar a decidir: donde se orienta a los estudiantes para que tomen la mejor decisión ante una situación concreta. El objetivo es que el estudiante fortalezca su autonomía y la toma de decisiones responsable.
A48: =_xlfn.XLOOKUP(B48,'Paso 3 Redacción RA'!I$3:I$12,'Paso 3 Redacción RA'!C$3:C$12,,0,1) -> SaberHacer | B48: Utiliza herramientas y tecnologías de almacenamiento, gestión y transformación de los datos para obtener información, según las condiciones y restricciones que se observen en el contexto.
A49: =_xlfn.XLOOKUP(B49,'Paso 3 Redacción RA'!I$3:I$12,'Paso 3 Redacción RA'!C$3:C$12,,0,1) -> SaberHacer | B49: Implementa algoritmos para generar soluciones computacionales, siguiendo métodos, técnicas y estructuras propios de los paradigmas de programación.
A50: =_xlfn.XLOOKUP(B50,'Paso 3 Redacción RA'!I$3:I$12,'Paso 3 Redacción RA'!C$3:C$12,,0,1) -> SaberSer | B50: Identifica los requisitos de sistemas que emergen en contextos de desarrollo tecnológico, teniendo en cuenta los referentes técnicos y normativos, para formular propuestas y proyectos, incorporando criterios de eficiencia e integridad en entornos empresariales u organizacionales. | C50: 4 | D50: Autómatas, Gramáticas y Lenguajes | E50: Emplea máquinas de estados finitos para procesar y generar lenguajes de acuerdo con la teoría de Chomsky. Construye máquinas de estados finitos para ejecutar tareas algorítmicas sencillas. Reconoce los conceptos de computabilidad y complejidad para analizar un problema. | F50: TP | H50: X | J50: 3 | K50: =16*J50 -> 48 | L50: =32*J50 -> 96 | M50: =SUM(K50:L50) -> 144 | N50: 1. Introducción a modelos computacionales 2. Autómatas finitos 3. Lenguajes libres de contexto 4. Intratabilidad | O50: Las estrategias pueden variar entre estas y otras que emerjan en el proceso formativo. Trabajo directo: Clases Magistrales Talleres en clase Trabajo independiente: Desarrollo de talleres en casa Lecturas complementarias Actividades de refuerzo Tutorías o monitorias | P50: Las estrategias pueden variar entre las siguientes u otras que puedan ser pertinentes para el proceso de aprendizaje. Evaluación formativa: Resolución de problemas. Soluciones numéricas. Uso de herramientas computacionales. Tareas. Evaluación sumativa: Evaluación parcial. Quiz. Taller / Laboratorios. Proyecto de investigación formativa. | Q50: Las acciones de retroalimentación giran en torno a las siguientes. Formar: donde se crean las condiciones para que los estudiantes adquieran conocimientos, habilidades, actitudes, aptitudes y destrezas. Además, debe promover su desarrollo integral y debe acompañarlos en las situaciones académicas que enfrenten durante el desarrollo de un módulo o una asignatura. Informar: para que los estudiantes identifiquen los cambios que pueden afectarlos directa o indirectamente tanto en el aula de clase como en otros espacios. Prevenir: con el fin de anticiparse a las situaciones académicas que pueden representar dificultad para los estudiantes. Esto se logra a través de la interacción individual con los estudiantes y del completo conocimiento del contexto educativo en que el tutor se desenvuelve. Ayudar a decidir: donde se orienta a los estudiantes para que tomen la mejor decisión ante una situación concreta. El objetivo es que el estudiante fortalezca su autonomía y la toma de decisiones responsable.
A51: =_xlfn.XLOOKUP(B51,'Paso 3 Redacción RA'!I$3:I$12,'Paso 3 Redacción RA'!C$3:C$12,,0,1) -> Saber | B51: Articula principios de algoritmia y programación para establecer la viabilidad técnica de soluciones computacionales, según el tipo de usuario y las condiciones del entorno tecnológico.
A52: =_xlfn.XLOOKUP(B52,'Paso 3 Redacción RA'!I$3:I$12,'Paso 3 Redacción RA'!C$3:C$12,,0,1) -> SaberHacer | B52: Implementa algoritmos para generar soluciones computacionales, siguiendo métodos, técnicas y estructuras propios de los paradigmas de programación.
A53: =_xlfn.XLOOKUP(B53,'Paso 3 Redacción RA'!I$3:I$12,'Paso 3 Redacción RA'!C$3:C$12,,0,1) -> SaberSer | B53: Identifica los requisitos de sistemas que emergen en contextos de desarrollo tecnológico, teniendo en cuenta los referentes técnicos y normativos, para formular propuestas y proyectos, incorporando criterios de eficiencia e integridad en entornos empresariales u organizacionales. | C53: 4 | D53: Cálculo Integral | E53: Aplica los principios del cálculo integral para resolver problemas que involucren procesos de integración y acumulación desde la anti-derivación, el análisis de áreas y comportamientos infinitos con la interpretación de resultados en contextos matemáticos y aplicados. | F53: TP | H53: X | J53: 4 | K53: =16*J53 -> 64 | L53: =32*J53 -> 128 | M53: =SUM(K53:L53) -> 192 | N53: 1. Funciones trascendentes 2. Integral definida e indefinida 3. Técnicas de integración e integral impropia 4. Aplicaciones de la integral – Sucesiones y series | O53: Las estrategias pueden variar entre estas y otras que emerjan en el proceso formativo. Trabajo directo: Talleres (individuales o grupales) Resolución de problemas Preguntas intercaladas Analogías Simuladores Señalizaciones Trabajo independiente: Lecturas Simuladores Organizadores previos Talleres (individuales o grupales) | P53: Las estrategias pueden variar entre las siguientes u otras que puedan ser pertinentes para el proceso de aprendizaje. Evaluación formativa: Resolución de problemas. Soluciones numéricas. Uso de herramientas computacionales. Tareas. Evaluación sumativa: Evaluación parcial. Quiz. Taller / Laboratorios. Proyecto de investigación formativa. | Q53: Las acciones de retroalimentación giran en torno a las siguientes. Formar: donde se crean las condiciones para que los estudiantes adquieran conocimientos, habilidades, actitudes, aptitudes y destrezas. Además, debe promover su desarrollo integral y debe acompañarlos en las situaciones académicas que enfrenten durante el desarrollo de un módulo o una asignatura. Informar: para que los estudiantes identifiquen los cambios que pueden afectarlos directa o indirectamente tanto en el aula de clase como en otros espacios. Prevenir: con el fin de anticiparse a las situaciones académicas que pueden representar dificultad para los estudiantes. Esto se logra a través de la interacción individual con los estudiantes y del completo conocimiento del contexto educativo en que el tutor se desenvuelve. Ayudar a decidir: donde se orienta a los estudiantes para que tomen la mejor decisión ante una situación concreta. El objetivo es que el estudiante fortalezca su autonomía y la toma de decisiones responsable.
A54: =_xlfn.XLOOKUP(B54,'Paso 3 Redacción RA'!I$3:I$12,'Paso 3 Redacción RA'!C$3:C$12,,0,1) -> Saber | B54: Articula principios de algoritmia y programación para establecer la viabilidad técnica de soluciones computacionales, según el tipo de usuario y las condiciones del entorno tecnológico.
A55: =_xlfn.XLOOKUP(B55,'Paso 3 Redacción RA'!I$3:I$12,'Paso 3 Redacción RA'!C$3:C$12,,0,1) -> SaberHacer | B55: Implementa algoritmos para generar soluciones computacionales, siguiendo métodos, técnicas y estructuras propios de los paradigmas de programación.
A56: =_xlfn.XLOOKUP(B56,'Paso 3 Redacción RA'!I$3:I$12,'Paso 3 Redacción RA'!C$3:C$12,,0,1) -> Saber | B56: Identifica fenómenos contemporáneos y su relación con la profesión, para determinar sus impactos e influencia en la sociedad, de forma responsable y crítica. | C56: 4 | D56: Física Mecánica | E56: Identifica las cantidades, leyes y principios fundamentales del movimiento de los cuerpos en la mecánica clásica para analizar contextos reales y situaciones de aprendizaje. Aplica las leyes y principios fundamentales de la física mecánica para desarrollarlas en los procesos de solución de situaciones prácticas. | F56: TP | H56: X | J56: 4 | K56: =16*J56 -> 64 | L56: =32*J56 -> 128 | M56: =SUM(K56:L56) -> 192 | N56: 1. El Movimiento. Cinemática unidimensional y bidimensional de una partícula 2. Fuerza. Dinámica, leyes de Newton y aplicaciones 3. Análisis de energía. Trabajo, energía mecánica, sistema de partículas y cantidad de movimiento 4. Cinemática y dinámica de cuerpo rígido. Torques, momento de inercia, rodadura y momento angular | O56: Las estrategias pueden variar entre estas y otras que emerjan en el proceso formativo. Trabajo directo: Clase magistral activa Asesorías extra clase Trabajo independiente: Ejercicios de lectura Actividades de refuerzo Presentación de un proyecto de profundización a partir de un ejercicio investigativo | P56: Las estrategias pueden variar entre las siguientes u otras que puedan ser pertinentes para el proceso de aprendizaje. Evaluación formativa: Resolución de problemas. Soluciones numéricas. Uso de herramientas computacionales. Tareas. Evaluación sumativa: Evaluación parcial. Quiz. Taller / Laboratorios. Proyecto de investigación formativa. | Q56: Las acciones de retroalimentación giran en torno a las siguientes. Formar: donde se crean las condiciones para que los estudiantes adquieran conocimientos, habilidades, actitudes, aptitudes y destrezas. Además, debe promover su desarrollo integral y debe acompañarlos en las situaciones académicas que enfrenten durante el desarrollo de un módulo o una asignatura. Informar: para que los estudiantes identifiquen los cambios que pueden afectarlos directa o indirectamente tanto en el aula de clase como en otros espacios. Prevenir: con el fin de anticiparse a las situaciones académicas que pueden representar dificultad para los estudiantes. Esto se logra a través de la interacción individual con los estudiantes y del completo conocimiento del contexto educativo en que el tutor se desenvuelve. Ayudar a decidir: donde se orienta a los estudiantes para que tomen la mejor decisión ante una situación concreta. El objetivo es que el estudiante fortalezca su autonomía y la toma de decisiones responsable.
A57: =_xlfn.XLOOKUP(B57,'Paso 3 Redacción RA'!I$3:I$12,'Paso 3 Redacción RA'!C$3:C$12,,0,1) -> Saber | B57: Articula principios de algoritmia y programación para establecer la viabilidad técnica de soluciones computacionales, según el tipo de usuario y las condiciones del entorno tecnológico.
A58: =_xlfn.XLOOKUP(B58,'Paso 3 Redacción RA'!I$3:I$12,'Paso 3 Redacción RA'!C$3:C$12,,0,1) -> SaberHacer | B58: Implementa algoritmos para generar soluciones computacionales, siguiendo métodos, técnicas y estructuras propios de los paradigmas de programación. | R58: =SUM(J46:J58) -> 17 | S58: =COUNTA(D46:D58) -> 5
A59: =_xlfn.XLOOKUP(B59,'Paso 3 Redacción RA'!I$3:I$12,'Paso 3 Redacción RA'!C$3:C$12,,0,1) -> Saber | B59: Interpreta patrones de arquitectura y diseño de software, así como de infraestructura TIC, para determinar las necesidades técnicas y tecnológicas de los sistemas de información, según las condiciones que emergen en los proyectos de software. | C59: 5 | D59: Ingeniería de Software I | E59: Reconoce las fases del ciclo de vida del software para desarrollar soluciones de software en un contexto de un caso de estudio. Modela soluciones usando el lenguaje unificado de modelado (UML) y patrones de diseño para construir un producto de software de acuerdo a las reglas de negocio definidas. Implementa prototipos funcionales de software para aplicar buenas prácticas de desarrollo de software en un contexto de un caso de estudio | F59: TP | H59: X | J59: 3 | K59: =16*J59 -> 48 | L59: =32*J59 -> 96 | M59: =SUM(K59:L59) -> 144 | N59: 1. Conceptos básicos de la ingeniería de software 2. Metodologías y modelos de proceso 3. Generalidades de calidad de software 4. Patrones de software | O59: Las estrategias pueden variar entre estas y otras que emerjan en el proceso formativo. Trabajo directo: Clase magistral activa Asesorías extra clase Trabajo independiente: Ejercicios de lectura Actividades de refuerzo Presentación de un proyecto de profundización a partir de un ejercicio investigativo | P59: Las estrategias pueden variar entre las siguientes u otras que puedan ser pertinentes para el proceso de aprendizaje. Evaluación formativa: Resolución de problemas. Soluciones numéricas. Uso de herramientas computacionales. Tareas. Evaluación sumativa: Evaluación parcial. Quiz. Taller / Laboratorios. Proyecto de investigación formativa. | Q59: Las acciones de retroalimentación giran en torno a las siguientes. Formar: donde se crean las condiciones para que los estudiantes adquieran conocimientos, habilidades, actitudes, aptitudes y destrezas. Además, debe promover su desarrollo integral y debe acompañarlos en las situaciones académicas que enfrenten durante el desarrollo de un módulo o una asignatura. Informar: para que los estudiantes identifiquen los cambios que pueden afectarlos directa o indirectamente tanto en el aula de clase como en otros espacios. Prevenir: con el fin de anticiparse a las situaciones académicas que pueden representar dificultad para los estudiantes. Esto se logra a través de la interacción individual con los estudiantes y del completo conocimiento del contexto educativo en que el tutor se desenvuelve. Ayudar a decidir: donde se orienta a los estudiantes para que tomen la mejor decisión ante una situación concreta. El objetivo es que el estudiante fortalezca su autonomía y la toma de decisiones responsable.
A60: =_xlfn.XLOOKUP(B60,'Paso 3 Redacción RA'!I$3:I$12,'Paso 3 Redacción RA'!C$3:C$12,,0,1) -> SaberHacer | B60: Produce artefactos de software para estructurar soluciones correspondientes, según las condiciones y restricciones del contexto.
A61: =_xlfn.XLOOKUP(B61,'Paso 3 Redacción RA'!I$3:I$12,'Paso 3 Redacción RA'!C$3:C$12,,0,1) -> SaberSer | B61: Identifica los requisitos de sistemas que emergen en contextos de desarrollo tecnológico, teniendo en cuenta los referentes técnicos y normativos, para formular propuestas y proyectos, incorporando criterios de eficiencia e integridad en entornos empresariales u organizacionales.
A62: =_xlfn.XLOOKUP(B62,'Paso 3 Redacción RA'!I$3:I$12,'Paso 3 Redacción RA'!C$3:C$12,,0,1) -> SaberHacer | B62: Implementa algoritmos para generar soluciones computacionales, siguiendo métodos, técnicas y estructuras propios de los paradigmas de programación.
A63: =_xlfn.XLOOKUP(B63,'Paso 3 Redacción RA'!I$3:I$12,'Paso 3 Redacción RA'!C$3:C$12,,0,1) -> SaberSer | B63: Identifica los requisitos de sistemas que emergen en contextos de desarrollo tecnológico, teniendo en cuenta los referentes técnicos y normativos, para formular propuestas y proyectos, incorporando criterios de eficiencia e integridad en entornos empresariales u organizacionales. | C63: 5 | D63: Bases de Datos en la Nube | E63: Diseña bases de datos para desarrollar sistemas de información en infraestructura propia o de nube. Reconoce los elementos de un sistema de bases de datos para diseñar soluciones de implementación de software en contextos de casos de estudio. | F63: TP | H63: X | J63: 4 | K63: =16*J63 -> 64 | L63: =32*J63 -> 128 | M63: =SUM(K63:L63) -> 192 | N63: 1. Fundamentos de las bases de datos NoSQL. 2. Arquitecturas y Modelos de bd NoSQL 3. Ecosistemas de bases de datos en la nube. 4. Aplicaciones de bases de datos en la nube. | O63: Las estrategias pueden variar entre estas y otras que emerjan en el proceso formativo. Trabajo directo: Clase magistral activa Practicas guiadas de laboratorio Talleres programados con casos reales Trabajo independiente Practicas de aplicación y laboratorio Lecturas Desarrollo de proyecto de aula | P63: Las estrategias pueden variar entre las siguientes u otras que puedan ser pertinentes para el proceso de aprendizaje. Evaluación formativa: Resolución de problemas. Soluciones numéricas. Uso de herramientas computacionales. Tareas. Evaluación sumativa: Evaluación parcial. Quiz. Taller / Laboratorios. Proyecto de investigación formativa. | Q63: Las acciones de retroalimentación giran en torno a las siguientes. Formar: donde se crean las condiciones para que los estudiantes adquieran conocimientos, habilidades, actitudes, aptitudes y destrezas. Además, debe promover su desarrollo integral y debe acompañarlos en las situaciones académicas que enfrenten durante el desarrollo de un módulo o una asignatura. Informar: para que los estudiantes identifiquen los cambios que pueden afectarlos directa o indirectamente tanto en el aula de clase como en otros espacios. Prevenir: con el fin de anticiparse a las situaciones académicas que pueden representar dificultad para los estudiantes. Esto se logra a través de la interacción individual con los estudiantes y del completo conocimiento del contexto educativo en que el tutor se desenvuelve. Ayudar a decidir: donde se orienta a los estudiantes para que tomen la mejor decisión ante una situación concreta. El objetivo es que el estudiante fortalezca su autonomía y la toma de decisiones responsable.
A64: =_xlfn.XLOOKUP(B64,'Paso 3 Redacción RA'!I$3:I$12,'Paso 3 Redacción RA'!C$3:C$12,,0,1) -> Saber | B64: Analiza estructuras de representación de datos para determinar su idoneidad en la resolución de problemas computacionales, teniendo en cuenta los requerimientos tecnológicos del contexto.
A65: =_xlfn.XLOOKUP(B65,'Paso 3 Redacción RA'!I$3:I$12,'Paso 3 Redacción RA'!C$3:C$12,,0,1) -> SaberHacer | B65: Utiliza herramientas y tecnologías de almacenamiento, gestión y transformación de los datos para obtener información, según las condiciones y restricciones que se observen en el contexto.
A66: =_xlfn.XLOOKUP(B66,'Paso 3 Redacción RA'!I$3:I$12,'Paso 3 Redacción RA'!C$3:C$12,,0,1) -> Saber | B66: Articula principios de algoritmia y programación para establecer la viabilidad técnica de soluciones computacionales, según el tipo de usuario y las condiciones del entorno tecnológico.
A67: =_xlfn.XLOOKUP(B67,'Paso 3 Redacción RA'!I$3:I$12,'Paso 3 Redacción RA'!C$3:C$12,,0,1) -> Saber | B67: Analiza estructuras de representación de datos para determinar su idoneidad en la resolución de problemas computacionales, teniendo en cuenta los requerimientos tecnológicos del contexto. | C67: 5 | D67: Análisis Descriptivo de Datos | E67: Aplica herramientas tecnológicas y modelos probabilísticos, para representar procesos, aleatorios y determinar valores de probabilidad en diferentes escenarios. Aplica conceptos de probabilidad elemental y distribuciones como la normal y la binomial, para apoyar la toma de decisiones en diversos contextos. | F67: TP | H67: X | J67: 3 | K67: =16*J67 -> 48 | L67: =32*J67 -> 96 | M67: =SUM(K67:L67) -> 144 | N67: 1. Estadística descriptiva 2. Teoría de la probabilidad y variables aleatorias 3. Distribuciones de probabilidad de variable discreta 4. Distribuciones de probabilidad de variable continua | O67: Trabajo directo: Las estrategias pueden variar entre estas y otras que emerjan en el proceso formativo. Clase magistral activa Practicas guiadas de laboratorio Talleres programados con casos reales Trabajo independiente Practicas de aplicación y laboratorio Lecturas Desarrollo de proyecto de aula | P67: Las estrategias pueden variar entre las siguientes u otras que puedan ser pertinentes para el proceso de aprendizaje. Evaluación formativa: Resolución de problemas. Soluciones numéricas. Uso de herramientas computacionales. Tareas. Evaluación sumativa: Evaluación parcial. Quiz. Taller / Laboratorios. Proyecto de investigación formativa. | Q67: Las acciones de retroalimentación giran en torno a las siguientes. Formar: donde se crean las condiciones para que los estudiantes adquieran conocimientos, habilidades, actitudes, aptitudes y destrezas. Además, debe promover su desarrollo integral y debe acompañarlos en las situaciones académicas que enfrenten durante el desarrollo de un módulo o una asignatura. Informar: para que los estudiantes identifiquen los cambios que pueden afectarlos directa o indirectamente tanto en el aula de clase como en otros espacios. Prevenir: con el fin de anticiparse a las situaciones académicas que pueden representar dificultad para los estudiantes. Esto se logra a través de la interacción individual con los estudiantes y del completo conocimiento del contexto educativo en que el tutor se desenvuelve. Ayudar a decidir: donde se orienta a los estudiantes para que tomen la mejor decisión ante una situación concreta. El objetivo es que el estudiante fortalezca su autonomía y la toma de decisiones responsable.
A68: =_xlfn.XLOOKUP(B68,'Paso 3 Redacción RA'!I$3:I$12,'Paso 3 Redacción RA'!C$3:C$12,,0,1) -> SaberHacer | B68: Utiliza herramientas y tecnologías de almacenamiento, gestión y transformación de los datos para obtener información, según las condiciones y restricciones que se observen en el contexto.
A69: =_xlfn.XLOOKUP(B69,'Paso 3 Redacción RA'!I$3:I$12,'Paso 3 Redacción RA'!C$3:C$12,,0,1) -> Saber | B69: Articula principios de algoritmia y programación para establecer la viabilidad técnica de soluciones computacionales, según el tipo de usuario y las condiciones del entorno tecnológico.
A70: =_xlfn.XLOOKUP(B70,'Paso 3 Redacción RA'!I$3:I$12,'Paso 3 Redacción RA'!C$3:C$12,,0,1) -> Saber | B70: Interpreta patrones de arquitectura y diseño de software, así como de infraestructura TIC, para determinar las necesidades técnicas y tecnológicas de los sistemas de información, según las condiciones que emergen en los proyectos de software. | C70: 5 | D70: Investigación de Operaciones | E70: Modela sistemas a partir de los elementos que lo conforman y sus restricciones, con el uso de abstracciones de carácter matemático, para determinar soluciones factibles y la solución óptima que responde a sus características. Aplica las técnicas básicas y avanzadas de la programación lineal para resolver problemas de optimización relacionados con la asignación de recursos y la eficiencia en el flujo de procesos. | F70: TP | H70: X | J70: 3 | K70: =16*J70 -> 48 | L70: =32*J70 -> 96 | M70: =SUM(K70:L70) -> 144 | N70: 1.Programación lineal y formulación 2.Métodos de solución - Lenguaje de modelaje matemático 3.Teoría de la dualidad y análisis de sensibilidad 4.Flujo en redes | O70: Las estrategias pueden variar entre estas y otras que emerjan en el proceso formativo. Trabajo directo: Clase magistral activa Uso de elementos asociados con los métodos de: Aprendizaje basado en proyectos; Aprendizaje basado en problemas; Estudio de caso; Clase expositiva; TIC; Demostración Trabajo independiente: Simulación; Aprendizaje basado en investigación; Aprendizaje basado en equipos | P70: Las estrategias pueden variar entre las siguientes u otras que puedan ser pertinentes para el proceso de aprendizaje. Evaluación formativa: Resolución de problemas. Soluciones numéricas. Uso de herramientas computacionales. Tareas. Evaluación sumativa: Evaluación parcial. Quiz. Taller / Laboratorios. Proyecto de investigación formativa. | Q70: Las acciones de retroalimentación giran en torno a las siguientes. Formar: donde se crean las condiciones para que los estudiantes adquieran conocimientos, habilidades, actitudes, aptitudes y destrezas. Además, debe promover su desarrollo integral y debe acompañarlos en las situaciones académicas que enfrenten durante el desarrollo de un módulo o una asignatura. Informar: para que los estudiantes identifiquen los cambios que pueden afectarlos directa o indirectamente tanto en el aula de clase como en otros espacios. Prevenir: con el fin de anticiparse a las situaciones académicas que pueden representar dificultad para los estudiantes. Esto se logra a través de la interacción individual con los estudiantes y del completo conocimiento del contexto educativo en que el tutor se desenvuelve. Ayudar a decidir: donde se orienta a los estudiantes para que tomen la mejor decisión ante una situación concreta. El objetivo es que el estudiante fortalezca su autonomía y la toma de decisiones responsable.
A71: =_xlfn.XLOOKUP(B71,'Paso 3 Redacción RA'!I$3:I$12,'Paso 3 Redacción RA'!C$3:C$12,,0,1) -> SaberHacer | B71: Produce artefactos de software para estructurar soluciones correspondientes, según las condiciones y restricciones del contexto.
A72: =_xlfn.XLOOKUP(B72,'Paso 3 Redacción RA'!I$3:I$12,'Paso 3 Redacción RA'!C$3:C$12,,0,1) -> SaberSer | B72: Identifica los requisitos de sistemas que emergen en contextos de desarrollo tecnológico, teniendo en cuenta los referentes técnicos y normativos, para formular propuestas y proyectos, incorporando criterios de eficiencia e integridad en entornos empresariales u organizacionales.
A73: =_xlfn.XLOOKUP(B73,'Paso 3 Redacción RA'!I$3:I$12,'Paso 3 Redacción RA'!C$3:C$12,,0,1) -> Saber | B73: Analiza estructuras de representación de datos para determinar su idoneidad en la resolución de problemas computacionales, teniendo en cuenta los requerimientos tecnológicos del contexto. | C73: 5 | D73: Métodos Numéricos | E73: Implementa métodos y herramientas de aproximación numérica para resolver problemas teóricos y aplicados que involucren ecuaciones, ajuste de curvas, cálculo diferencial e integral, y ecuaciones diferenciales ordinarias. | F73: TP | H73: X | J73: 3 | K73: =16*J73 -> 48 | L73: =32*J73 -> 96 | M73: =SUM(K73:L73) -> 144 | N73: 1. Solución numérica de ecuaciones y sistemas de ecuaciones. 2. Ajuste de curvas 3. Derivación e Integración numérica 4. Solución numérica de ecuaciones diferenciales ordinarias | O73: Las estrategias pueden variar entre estas y otras que emerjan en el proceso formativo. Trabajo directo: Clases magistrales Talleres / Laboratorios Soluciones numéricas Uso de herramientas computacionales Resolución de problemas Trabajo independiente: Lecturas Resolución de problemas Soluciones numéricas Uso de herramientas computacionales | P73: Las estrategias pueden variar entre las siguientes u otras que puedan ser pertinentes para el proceso de aprendizaje. Evaluación formativa: Resolución de problemas. Soluciones numéricas. Uso de herramientas computacionales. Tareas. Evaluación sumativa: Evaluación parcial. Quiz. Taller / Laboratorios. Proyecto de investigación formativa. | Q73: Las acciones de retroalimentación giran en torno a las siguientes. Formar: donde se crean las condiciones para que los estudiantes adquieran conocimientos, habilidades, actitudes, aptitudes y destrezas. Además, debe promover su desarrollo integral y debe acompañarlos en las situaciones académicas que enfrenten durante el desarrollo de un módulo o una asignatura. Informar: para que los estudiantes identifiquen los cambios que pueden afectarlos directa o indirectamente tanto en el aula de clase como en otros espacios. Prevenir: con el fin de anticiparse a las situaciones académicas que pueden representar dificultad para los estudiantes. Esto se logra a través de la interacción individual con los estudiantes y del completo conocimiento del contexto educativo en que el tutor se desenvuelve. Ayudar a decidir: donde se orienta a los estudiantes para que tomen la mejor decisión ante una situación concreta. El objetivo es que el estudiante fortalezca su autonomía y la toma de decisiones responsable.
A74: =_xlfn.XLOOKUP(B74,'Paso 3 Redacción RA'!I$3:I$12,'Paso 3 Redacción RA'!C$3:C$12,,0,1) -> Saber | B74: Articula principios de algoritmia y programación para establecer la viabilidad técnica de soluciones computacionales, según el tipo de usuario y las condiciones del entorno tecnológico.
A75: =_xlfn.XLOOKUP(B75,'Paso 3 Redacción RA'!I$3:I$12,'Paso 3 Redacción RA'!C$3:C$12,,0,1) -> SaberHacer | B75: Implementa algoritmos para generar soluciones computacionales, siguiendo métodos, técnicas y estructuras propios de los paradigmas de programación. | R75: =SUM(J59:J75) -> 16 | S75: =COUNTA(D59:D75) -> 5
A76: =_xlfn.XLOOKUP(B76,'Paso 3 Redacción RA'!I$3:I$12,'Paso 3 Redacción RA'!C$3:C$12,,0,1) -> Saber | B76: Interpreta patrones de arquitectura y diseño de software, así como de infraestructura TIC, para determinar las necesidades técnicas y tecnológicas de los sistemas de información, según las condiciones que emergen en los proyectos de software. | C76: 6 | D76: Ingeniería de Software II | E76: Realiza estimaciones de requisitos y funcionalidades para medir tiempo, alcance y recursos dentro del desarrollo de proyectos de construcción de software. Define planes de ejecución y pruebas tanto unitarios, de integración y de usuario final acordes al plan de construcción definido para implementar estrategias de aseguramiento de calidad del software. Construye soluciones de software acordes a un diseño para satisfacer requisitos funcionales y no funcionales. | F76: TP | H76: X | J76: 3 | K76: =16*J76 -> 48 | L76: =32*J76 -> 96 | M76: =SUM(K76:L76) -> 144 | N76: 1. Panorama de la ingeniería de software 2. Planeación y estimación de proyectos de ingeniería de software 3. Patrones de diseño y arquitectura de software 4. Gestión de calidad, testing y documentación | O76: Las estrategias pueden variar entre estas y otras que emerjan en el proceso formativo. Trabajo directo: Clase magistral activa Desarrollo de ejercicios en clase Asesorías Extra clase Trabajo independiente: Talleres de aplicación del tema Revisión bibliografía recomendada Actividades de refuerzo | P76: Las estrategias pueden variar entre las siguientes u otras que puedan ser pertinentes para el proceso de aprendizaje. Evaluación formativa: Resolución de problemas. Soluciones numéricas. Uso de herramientas computacionales. Tareas. Evaluación sumativa: Evaluación parcial. Quiz. Taller / Laboratorios. Proyecto de investigación formativa. | Q76: Las acciones de retroalimentación giran en torno a las siguientes. Formar: donde se crean las condiciones para que los estudiantes adquieran conocimientos, habilidades, actitudes, aptitudes y destrezas. Además, debe promover su desarrollo integral y debe acompañarlos en las situaciones académicas que enfrenten durante el desarrollo de un módulo o una asignatura. Informar: para que los estudiantes identifiquen los cambios que pueden afectarlos directa o indirectamente tanto en el aula de clase como en otros espacios. Prevenir: con el fin de anticiparse a las situaciones académicas que pueden representar dificultad para los estudiantes. Esto se logra a través de la interacción individual con los estudiantes y del completo conocimiento del contexto educativo en que el tutor se desenvuelve. Ayudar a decidir: donde se orienta a los estudiantes para que tomen la mejor decisión ante una situación concreta. El objetivo es que el estudiante fortalezca su autonomía y la toma de decisiones responsable.
A77: =_xlfn.XLOOKUP(B77,'Paso 3 Redacción RA'!I$3:I$12,'Paso 3 Redacción RA'!C$3:C$12,,0,1) -> SaberHacer | B77: Produce artefactos de software para estructurar soluciones correspondientes, según las condiciones y restricciones del contexto.
A78: =_xlfn.XLOOKUP(B78,'Paso 3 Redacción RA'!I$3:I$12,'Paso 3 Redacción RA'!C$3:C$12,,0,1) -> SaberSer | B78: Identifica los requisitos de sistemas que emergen en contextos de desarrollo tecnológico, teniendo en cuenta los referentes técnicos y normativos, para formular propuestas y proyectos, incorporando criterios de eficiencia e integridad en entornos empresariales u organizacionales.
A79: =_xlfn.XLOOKUP(B79,'Paso 3 Redacción RA'!I$3:I$12,'Paso 3 Redacción RA'!C$3:C$12,,0,1) -> SaberHacer | B79: Implementa algoritmos para generar soluciones computacionales, siguiendo métodos, técnicas y estructuras propios de los paradigmas de programación.
A80: =_xlfn.XLOOKUP(B80,'Paso 3 Redacción RA'!I$3:I$12,'Paso 3 Redacción RA'!C$3:C$12,,0,1) -> Saber | B80: Interpreta patrones de arquitectura y diseño de software, así como de infraestructura TIC, para determinar las necesidades técnicas y tecnológicas de los sistemas de información, según las condiciones que emergen en los proyectos de software. | C80: 6 | D80: Infraestructura en la Nube | E80: Identifica los elementos que hacen parte de sistemas de cómputo, redes de telecomunicaciones, para diseñar infraestructuras y servicios de tecnologías de la información y las comunicaciones, teniendo en cuenta condiciones, restricciones y requerimientos técnicos de un proyecto desde un abordaje teórico-práctico, a través de herramientas de simulación, análisis de casos y uso de equipos de laboratorio. Configura los elementos que hacen parte de sistemas de cómputo, redes de telecomunicaciones, para implementar infraestructuras y servicios de tecnologías de la información y las comunicaciones, teniendo en cuenta condiciones, restricciones y requerimientos técnicos de un proyecto desde un abordaje teórico-práctico, a través de herramientas de simulación, análisis de casos y uso de equipos de laboratorio. Emplea los elementos que hacen parte de sistemas de cómputo, redes de telecomunicaciones, para resolver problemas asociados a la administración de los sistemas de telecomunicaciones, infraestructuras TIC, teniendo en cuenta condiciones, restricciones y requerimientos técnicos, desde un abordaje teórico-práctico, a través de herramientas de simulación, análisis de casos y uso de equipos de laboratorio. | F80: TP | H80: X | J80: 3 | K80: =16*J80 -> 48 | L80: =32*J80 -> 96 | M80: =SUM(K80:L80) -> 144 | N80: 1. Introducción a la Infraestructura como Código 2. Gestión y Automatización de Infraestructura 3. Fundamentos de Computación en la Nube 4. Automatización y Escalabilidad | O80: Las estrategias pueden variar entre estas y otras que emerjan en el proceso formativo. Trabajo directo: Clase magistral activa Desarrollo de ejercicios en clase Asesorías Extra clase Trabajo independiente: Talleres de aplicación del tema Revisión bibliografía recomendada Actividades de refuerzo | P80: Las estrategias pueden variar entre las siguientes u otras que puedan ser pertinentes para el proceso de aprendizaje. Evaluación formativa: Resolución de problemas. Soluciones numéricas. Uso de herramientas computacionales. Tareas. Evaluación sumativa: Evaluación parcial. Quiz. Taller / Laboratorios. Proyecto de investigación formativa. | Q80: Las acciones de retroalimentación giran en torno a las siguientes. Formar: donde se crean las condiciones para que los estudiantes adquieran conocimientos, habilidades, actitudes, aptitudes y destrezas. Además, debe promover su desarrollo integral y debe acompañarlos en las situaciones académicas que enfrenten durante el desarrollo de un módulo o una asignatura. Informar: para que los estudiantes identifiquen los cambios que pueden afectarlos directa o indirectamente tanto en el aula de clase como en otros espacios. Prevenir: con el fin de anticiparse a las situaciones académicas que pueden representar dificultad para los estudiantes. Esto se logra a través de la interacción individual con los estudiantes y del completo conocimiento del contexto educativo en que el tutor se desenvuelve. Ayudar a decidir: donde se orienta a los estudiantes para que tomen la mejor decisión ante una situación concreta. El objetivo es que el estudiante fortalezca su autonomía y la toma de decisiones responsable.
A81: =_xlfn.XLOOKUP(B81,'Paso 3 Redacción RA'!I$3:I$12,'Paso 3 Redacción RA'!C$3:C$12,,0,1) -> SaberHacer | B81: Produce artefactos de software para estructurar soluciones correspondientes, según las condiciones y restricciones del contexto.
A82: =_xlfn.XLOOKUP(B82,'Paso 3 Redacción RA'!I$3:I$12,'Paso 3 Redacción RA'!C$3:C$12,,0,1) -> Saber | B82: Analiza estructuras de representación de datos para determinar su idoneidad en la resolución de problemas computacionales, teniendo en cuenta los requerimientos tecnológicos del contexto.
A83: =_xlfn.XLOOKUP(B83,'Paso 3 Redacción RA'!I$3:I$12,'Paso 3 Redacción RA'!C$3:C$12,,0,1) -> SaberHacer | B83: Utiliza herramientas y tecnologías de almacenamiento, gestión y transformación de los datos para obtener información, según las condiciones y restricciones que se observen en el contexto.
A84: =_xlfn.XLOOKUP(B84,'Paso 3 Redacción RA'!I$3:I$12,'Paso 3 Redacción RA'!C$3:C$12,,0,1) -> Saber | B84: Interpreta patrones de arquitectura y diseño de software, así como de infraestructura TIC, para determinar las necesidades técnicas y tecnológicas de los sistemas de información, según las condiciones que emergen en los proyectos de software. | C84: 6 | D84: Desarrollo Web | E84: Construye la implementación de la parte del servidor usando un framework para generar una aplicación web. Construye la implementación de la parte del cliente usando un framework para generar una aplicación web. Adapta las implementaciones de la parte del servidor y de la parte del cliente para entregar una aplicación web. | F84: TP | H84: X | J84: 3 | K84: =16*J84 -> 48 | L84: =32*J84 -> 96 | M84: =SUM(K84:L84) -> 144 | N84: 1. Conceptos de la arquitectura de las aplicaciones web 2. Framework de desarrollo para parte del servidor, capa de lógica de negocio o backend 3. Librerías disponibles en los frameworks 4. Framework de desarrollo para parte del cliente, capa de presentación o frontend | O84: Las estrategias pueden variar entre estas y otras que emerjan en el proceso formativo. Trabajo directo: Clase magistral activa Practicas guiadas de laboratorio Talleres programados con casos reales Trabajo independiente Prácticas de aplicación y laboratorio Lecturas Desarrollo de proyecto de aula | P84: Las estrategias pueden variar entre las siguientes u otras que puedan ser pertinentes para el proceso de aprendizaje. Evaluación formativa: Resolución de problemas. Soluciones numéricas. Uso de herramientas computacionales. Tareas. Evaluación sumativa: Evaluación parcial. Quiz. Taller / Laboratorios. Proyecto de investigación formativa. | Q84: Las acciones de retroalimentación giran en torno a las siguientes. Formar: donde se crean las condiciones para que los estudiantes adquieran conocimientos, habilidades, actitudes, aptitudes y destrezas. Además, debe promover su desarrollo integral y debe acompañarlos en las situaciones académicas que enfrenten durante el desarrollo de un módulo o una asignatura. Informar: para que los estudiantes identifiquen los cambios que pueden afectarlos directa o indirectamente tanto en el aula de clase como en otros espacios. Prevenir: con el fin de anticiparse a las situaciones académicas que pueden representar dificultad para los estudiantes. Esto se logra a través de la interacción individual con los estudiantes y del completo conocimiento del contexto educativo en que el tutor se desenvuelve. Ayudar a decidir: donde se orienta a los estudiantes para que tomen la mejor decisión ante una situación concreta. El objetivo es que el estudiante fortalezca su autonomía y la toma de decisiones responsable.
A85: =_xlfn.XLOOKUP(B85,'Paso 3 Redacción RA'!I$3:I$12,'Paso 3 Redacción RA'!C$3:C$12,,0,1) -> SaberHacer | B85: Produce artefactos de software para estructurar soluciones correspondientes, según las condiciones y restricciones del contexto.
A86: =_xlfn.XLOOKUP(B86,'Paso 3 Redacción RA'!I$3:I$12,'Paso 3 Redacción RA'!C$3:C$12,,0,1) -> SaberSer | B86: Identifica los requisitos de sistemas que emergen en contextos de desarrollo tecnológico, teniendo en cuenta los referentes técnicos y normativos, para formular propuestas y proyectos, incorporando criterios de eficiencia e integridad en entornos empresariales u organizacionales.
A87: =_xlfn.XLOOKUP(B87,'Paso 3 Redacción RA'!I$3:I$12,'Paso 3 Redacción RA'!C$3:C$12,,0,1) -> Saber | B87: Analiza estructuras de representación de datos para determinar su idoneidad en la resolución de problemas computacionales, teniendo en cuenta los requerimientos tecnológicos del contexto. | C87: 6 | D87: Fundamentos de Ciencia de Datos | E87: Reconoce las etapas del proceso de ciencia de datos para desarrollar soluciones a problemas en un contexto de caso de estudio. Implementa reportes de análisis de datos para visualizar gráficos de datos en un caso de estudio. | F87: TP | H87: X | J87: 3 | K87: =16*J87 -> 48 | L87: =32*J87 -> 96 | M87: =SUM(K87:L87) -> 144 | N87: 1. Conceptos básicos de Ciencia de Datos 2. Proceso de ciencia de datos 3. Estadística y probabilidad para Ciencia de Datos. 4. Comunicación efectiva de soluciones de ciencia de datos | O87: Las estrategias pueden variar entre estas y otras que emerjan en el proceso formativo. Trabajo directo: Clase magistral activa Asesorías extra clase Trabajo independiente: Ejercicios de lectura Actividades de refuerzo Presentación de un proyecto de profundización a partir de un ejercicio investigativo | P87: Las estrategias pueden variar entre las siguientes u otras que puedan ser pertinentes para el proceso de aprendizaje. Evaluación formativa: Resolución de problemas. Soluciones numéricas. Uso de herramientas computacionales. Tareas. Evaluación sumativa: Evaluación parcial. Quiz. Taller / Laboratorios. Proyecto de investigación formativa. | Q87: Las acciones de retroalimentación giran en torno a las siguientes. Formar: donde se crean las condiciones para que los estudiantes adquieran conocimientos, habilidades, actitudes, aptitudes y destrezas. Además, debe promover su desarrollo integral y debe acompañarlos en las situaciones académicas que enfrenten durante el desarrollo de un módulo o una asignatura. Informar: para que los estudiantes identifiquen los cambios que pueden afectarlos directa o indirectamente tanto en el aula de clase como en otros espacios. Prevenir: con el fin de anticiparse a las situaciones académicas que pueden representar dificultad para los estudiantes. Esto se logra a través de la interacción individual con los estudiantes y del completo conocimiento del contexto educativo en que el tutor se desenvuelve. Ayudar a decidir: donde se orienta a los estudiantes para que tomen la mejor decisión ante una situación concreta. El objetivo es que el estudiante fortalezca su autonomía y la toma de decisiones responsable.
A88: =_xlfn.XLOOKUP(B88,'Paso 3 Redacción RA'!I$3:I$12,'Paso 3 Redacción RA'!C$3:C$12,,0,1) -> SaberHacer | B88: Utiliza herramientas y tecnologías de almacenamiento, gestión y transformación de los datos para obtener información, según las condiciones y restricciones que se observen en el contexto.
A89: =_xlfn.XLOOKUP(B89,'Paso 3 Redacción RA'!I$3:I$12,'Paso 3 Redacción RA'!C$3:C$12,,0,1) -> SaberSer | B89: Identifica los requisitos de sistemas que emergen en contextos de desarrollo tecnológico, teniendo en cuenta los referentes técnicos y normativos, para formular propuestas y proyectos, incorporando criterios de eficiencia e integridad en entornos empresariales u organizacionales.
A90: =_xlfn.XLOOKUP(B90,'Paso 3 Redacción RA'!I$3:I$12,'Paso 3 Redacción RA'!C$3:C$12,,0,1) -> Saber | B90: Analiza estructuras de representación de datos para determinar su idoneidad en la resolución de problemas computacionales, teniendo en cuenta los requerimientos tecnológicos del contexto. | C90: 6 | D90: Análisis y Verificación de Algoritmos | E90: Establece la especificación formal de un problema de programación para demostrar la corrección de un algoritmo que lo solucione. Crea algoritmos eficientes haciendo uso de técnicas de diseño en la resolución de problemas del mundo real. Establece la complejidad de los programas en función de su tamaño para identificar los requerimientos de memoria y costo computacional. | F90: TP | H90: X | J90: 3 | K90: =16*J90 -> 48 | L90: =32*J90 -> 96 | M90: =SUM(K90:L90) -> 144 | N90: 1. Verificación de programas 2. Análisis de algoritmos 3. Técnicas de diseño de algoritmos 4. Intratabilidad | O90: Las estrategias pueden variar entre estas y otras que emerjan en el proceso formativo. Trabajo directo Clase magistral activa Estudio de casos Talleres individuales Trabajo con herramientas digitales y computacionales. Trabajo independiente Lecturas Resolución de problemas Uso de herramientas computacionales Proyectos individuales | P90: Las estrategias pueden variar entre las siguientes u otras que puedan ser pertinentes para el proceso de aprendizaje. Evaluación formativa: Resolución de problemas. Soluciones numéricas. Uso de herramientas computacionales. Tareas. Evaluación sumativa: Evaluación parcial. Quiz. Taller / Laboratorios. Proyecto de investigación formativa. | Q90: Las acciones de retroalimentación giran en torno a las siguientes. Formar: donde se crean las condiciones para que los estudiantes adquieran conocimientos, habilidades, actitudes, aptitudes y destrezas. Además, debe promover su desarrollo integral y debe acompañarlos en las situaciones académicas que enfrenten durante el desarrollo de un módulo o una asignatura. Informar: para que los estudiantes identifiquen los cambios que pueden afectarlos directa o indirectamente tanto en el aula de clase como en otros espacios. Prevenir: con el fin de anticiparse a las situaciones académicas que pueden representar dificultad para los estudiantes. Esto se logra a través de la interacción individual con los estudiantes y del completo conocimiento del contexto educativo en que el tutor se desenvuelve. Ayudar a decidir: donde se orienta a los estudiantes para que tomen la mejor decisión ante una situación concreta. El objetivo es que el estudiante fortalezca su autonomía y la toma de decisiones responsable.
A91: =_xlfn.XLOOKUP(B91,'Paso 3 Redacción RA'!I$3:I$12,'Paso 3 Redacción RA'!C$3:C$12,,0,1) -> SaberHacer | B91: Utiliza herramientas y tecnologías de almacenamiento, gestión y transformación de los datos para obtener información, según las condiciones y restricciones que se observen en el contexto.
A92: =_xlfn.XLOOKUP(B92,'Paso 3 Redacción RA'!I$3:I$12,'Paso 3 Redacción RA'!C$3:C$12,,0,1) -> Saber | B92: Articula principios de algoritmia y programación para establecer la viabilidad técnica de soluciones computacionales, según el tipo de usuario y las condiciones del entorno tecnológico.
A93: =_xlfn.XLOOKUP(B93,'Paso 3 Redacción RA'!I$3:I$12,'Paso 3 Redacción RA'!C$3:C$12,,0,1) -> SaberHacer | B93: Implementa algoritmos para generar soluciones computacionales, siguiendo métodos, técnicas y estructuras propios de los paradigmas de programación. | R93: =SUM(J76:J93) -> 15 | S93: =COUNTA(D76:D93) -> 5
A94: =_xlfn.XLOOKUP(B94,'Paso 3 Redacción RA'!I$3:I$12,'Paso 3 Redacción RA'!C$3:C$12,,0,1) -> Saber | B94: Interpreta patrones de arquitectura y diseño de software, así como de infraestructura TIC, para determinar las necesidades técnicas y tecnológicas de los sistemas de información, según las condiciones que emergen en los proyectos de software. | C94: 7 | D94: Gerencia de Proyectos Informáticos | E94: Reconoce los elementos de una metodología de gerencia de proyectos de desarrollo de software para planificar, diseñar y desarrollar soluciones de Tecnologías de la Información en un contexto de un caso de estudio. | F94: TP | H94: X | J94: 4 | K94: =16*J94 -> 64 | L94: =32*J94 -> 128 | M94: =SUM(K94:L94) -> 192 | N94: 1. Marco conceptual y aspectos generales 2. Preparación: iniciación y definición- alcance- requisitos 3. Ejecución y control: planeación y asignación de recursos, control y revisión 4. Cierre: Terminación y evaluación | O94: Las estrategias pueden variar entre estas y otras que emerjan en el proceso formativo. Trabajo directo Clase magistral activa Estudio de casos Talleres individuales Trabajo con herramientas digitales o computacionales. Trabajo independiente Lecturas Resolución de problemas Uso de herramientas computacionales Proyectos individuales | P94: Las estrategias pueden variar entre las siguientes u otras que puedan ser pertinentes para el proceso de aprendizaje. Evaluación formativa: Resolución de problemas. Soluciones numéricas. Uso de herramientas computacionales. Tareas. Evaluación sumativa: Evaluación parcial. Quiz. Taller / Laboratorios. Proyecto de investigación formativa. | Q94: Las acciones de retroalimentación giran en torno a las siguientes. Formar: donde se crean las condiciones para que los estudiantes adquieran conocimientos, habilidades, actitudes, aptitudes y destrezas. Además, debe promover su desarrollo integral y debe acompañarlos en las situaciones académicas que enfrenten durante el desarrollo de un módulo o una asignatura. Informar: para que los estudiantes identifiquen los cambios que pueden afectarlos directa o indirectamente tanto en el aula de clase como en otros espacios. Prevenir: con el fin de anticiparse a las situaciones académicas que pueden representar dificultad para los estudiantes. Esto se logra a través de la interacción individual con los estudiantes y del completo conocimiento del contexto educativo en que el tutor se desenvuelve. Ayudar a decidir: donde se orienta a los estudiantes para que tomen la mejor decisión ante una situación concreta. El objetivo es que el estudiante fortalezca su autonomía y la toma de decisiones responsable.
A95: =_xlfn.XLOOKUP(B95,'Paso 3 Redacción RA'!I$3:I$12,'Paso 3 Redacción RA'!C$3:C$12,,0,1) -> SaberHacer | B95: Produce artefactos de software para estructurar soluciones correspondientes, según las condiciones y restricciones del contexto.
A96: =_xlfn.XLOOKUP(B96,'Paso 3 Redacción RA'!I$3:I$12,'Paso 3 Redacción RA'!C$3:C$12,,0,1) -> SaberSer | B96: Identifica los requisitos de sistemas que emergen en contextos de desarrollo tecnológico, teniendo en cuenta los referentes técnicos y normativos, para formular propuestas y proyectos, incorporando criterios de eficiencia e integridad en entornos empresariales u organizacionales.
A97: =_xlfn.XLOOKUP(B97,'Paso 3 Redacción RA'!I$3:I$12,'Paso 3 Redacción RA'!C$3:C$12,,0,1) -> Saber | B97: Articula principios de algoritmia y programación para establecer la viabilidad técnica de soluciones computacionales, según el tipo de usuario y las condiciones del entorno tecnológico.
A98: =_xlfn.XLOOKUP(B98,'Paso 3 Redacción RA'!I$3:I$12,'Paso 3 Redacción RA'!C$3:C$12,,0,1) -> Saber | B98: Interpreta patrones de arquitectura y diseño de software, así como de infraestructura TIC, para determinar las necesidades técnicas y tecnológicas de los sistemas de información, según las condiciones que emergen en los proyectos de software. | C98: 7 | D98: Sistemas Operacionales | E98: Identifica las características de un sistema operacional para hacer la instalación del sistema operativo en una plataforma en contraste con los recursos de hardware disponibles. Observa los procesos que ejecuta un sistema operacional para construir aplicaciones seguras que saquen el mayor rendimiento del hardware y el software que corra sobre dicha plataforma. Diseña procedimientos para operar, administrar y proteger un sistema operacional, según la plataforma sobre la que se ejecuta. | F98: TP | H98: X | J98: 3 | K98: =16*J98 -> 48 | L98: =32*J98 -> 96 | M98: =SUM(K98:L98) -> 144 | N98: 1. Conceptos fundamentales sistemas operacionales en general y el sistema Linux 2. Gestores de un Sistema Operativo 3. Componentes de un Sistema Operativo 4. Seguridad y Sistemas operacionales para móviles | O98: Las estrategias pueden variar entre estas y otras que emerjan en el proceso formativo. Trabajo directo Clase magistral activa Estudio de casos Talleres individuales Trabajo con herramientasdigitales o computacionales Trabajo independiente Lecturas Resolución de problemas Uso de herramientas computacionales Proyectos individuales | P98: Las estrategias pueden variar entre las siguientes u otras que puedan ser pertinentes para el proceso de aprendizaje. Evaluación formativa: Resolución de problemas. Soluciones numéricas. Uso de herramientas computacionales. Tareas. Evaluación sumativa: Evaluación parcial. Quiz. Taller / Laboratorios. Proyecto de investigación formativa. | Q98: Las acciones de retroalimentación giran en torno a las siguientes. Formar: donde se crean las condiciones para que los estudiantes adquieran conocimientos, habilidades, actitudes, aptitudes y destrezas. Además, debe promover su desarrollo integral y debe acompañarlos en las situaciones académicas que enfrenten durante el desarrollo de un módulo o una asignatura. Informar: para que los estudiantes identifiquen los cambios que pueden afectarlos directa o indirectamente tanto en el aula de clase como en otros espacios. Prevenir: con el fin de anticiparse a las situaciones académicas que pueden representar dificultad para los estudiantes. Esto se logra a través de la interacción individual con los estudiantes y del completo conocimiento del contexto educativo en que el tutor se desenvuelve. Ayudar a decidir: donde se orienta a los estudiantes para que tomen la mejor decisión ante una situación concreta. El objetivo es que el estudiante fortalezca su autonomía y la toma de decisiones responsable.
A99: =_xlfn.XLOOKUP(B99,'Paso 3 Redacción RA'!I$3:I$12,'Paso 3 Redacción RA'!C$3:C$12,,0,1) -> SaberHacer | B99: Produce artefactos de software para estructurar soluciones correspondientes, según las condiciones y restricciones del contexto.
A100: =_xlfn.XLOOKUP(B100,'Paso 3 Redacción RA'!I$3:I$12,'Paso 3 Redacción RA'!C$3:C$12,,0,1) -> SaberSer | B100: Identifica los requisitos de sistemas que emergen en contextos de desarrollo tecnológico, teniendo en cuenta los referentes técnicos y normativos, para formular propuestas y proyectos, incorporando criterios de eficiencia e integridad en entornos empresariales u organizacionales.
...

Sheet Taxonomía para competencias
B1: Verbos Competencias
B2: Actualizar
B3: Administrar
B4: Asegurar
B5: Asesorar
B6: Auditar
B7: Comunicar
B8: Conducir
B9: Conocer
B10: Coordinar
B11: Definir
B12: Desarrollar
... B38: Reconocer

Sheet Taxonomias para RA
S1: Taxonomía de Bloom Adaptada bajo las ideas de Anderson y Krathwohl | AL1: Taxonomía de Bloom adaptada bajo las ideas de Lorin y Krathwohl (LK) | AT1: Taxonomía de Bloom adaptada bajo las ideas de Anderson y Kendal (AK)
L2: Taxonomía de Bloom | S2: Cognitivo(BAK) | Y2: Procedimental(BAK) | AC2: Actitudinal(BAK)
A3: Taxonomías | C3: BAK | D3: LK | E3: AK | G3: CognitivoB | H3: ProcedimentalB | I3: ActitudinalB | L3: ConocimientoB | M3: ComprensiónB | N3: AplicaciónB | O3: AnálisisB | P3: SíntesisB | Q3: EvaluaciónB | S3: ConocimientoBAK | T3: ComprensiónBAK | U3: AplicaciónBAK | V3: AnálisisBAK | W3: SíntesisBAK | X3: EvaluaciónBAK | Y3: ImitaciónBAK | Z3: ManipulaciónBAK | AA3: PrecisiónBAK | AB3: ControlBAK | AC3: PercepciónBAK | AD3: ResponderBAK | AE3: ValorarBAK | AF3: OrganizarBAK | AG3: CaracterizarBAK | AL3: Procesos cognitivos de orden inferior | AO3: Procesos cognitivos de orden superior
A4: Bloom | C4: CognitivoBAK | D4: HechosLK | E4: InformaciónAK | G4: ConocimientoB | H4: ConocimientoB | I4: ConocimientoB | L4: Adquirir | M4: Auditar | N4: Aplicar | O4: Aislar | P4: Adaptar | Q4: Aconsejar | S4: Adquirir | T4: Auditar | U4: Aplicar | V4: Aislar | W4: Adaptar | X4: Aconsejar | Y4: Acordar | Z4: Acceder | AA4: Abrir | AB4: Arreglar | AC4: Aceptar | AD4: Acordar | AE4: Aceptar | AF4: Adelantar | AG4: Acabar | AL4: RecordarLK | AM4: ComprenderLK | AN4: AplicarLK | AO4: AnalizarLK | AP4: EvaluarLK | AQ4: CrearLK | AT4: RecuperaciónAK | AU4: ComprensiónAK | AV4: AnálisisAK | AW4: UsoConocimientoAK | AX4: MetacogniciónAK | AY4: SistemadelYoAK
A5: BAK | C5: ProcedimentalBAK | D5: ConceptosLK | E5: ProcesosMentalesAK | G5: ComprensiónB | H5: ComprensiónB | I5: ComprensiónB | L5: Buscar | M5: Bosquejar | N5: Calisificar | O5: Analizar | P5: Administrar | Q5: Adjuntar | S5: Buscar | T5: Bosquejar | U5: Calisificar | V5: Analizar | W5: Administrar | X5: Adjuntar | Y5: Adaptar | Z5: Aislar | AA5: Actuar | AB5: Balancear | AC5: Admitir | AD5: Actuar recíprocamente | AE5: Adoptar | AF5: Anticipar | AG5: Afinar | AL5: Afirmar | AM5: Clasificar | AN5: Actuar | AO5: Agrupar | AP5: Adaptar | AQ5: Desarrollar | AT5: Afirmar | AU5: Auditar | AV5: Agrupar | AW5: Actuar | AX5: Aceptar | AY5: Aceptar
A6: LK | C6: ActitudinalBAK | D6: ProcedimientoslLK | E6: PsicomotorAK | G6: AplicaciónB | H6: AplicaciónB | I6: AplicaciónB | L6: Citar | M6: Comentar | N6: Combinar | O6: Calcular | P6: Arreglar | Q6: Agregar | S6: Citar | T6: Comentar | U6: Combinar | V6: Calcular | W6: Arreglar | X6: Agregar | Y6: Ajustar | Z6: Ajustar | AA6: Adaptar | AB6: Clasificar | AC6: Anotar | AD6: Afirmar | AE6: Afirmar | AF6: Arreglar | AG6: Apoyar | AL6: Citar | AM6: Comparar | AN6: Agrupar | AO6: Aislar | AP6: Añadir | AQ6: Elaborar | AT6: Citar | AU6: Bosquejar | AV6: Aislar | AW6: Agrupar | AX6: Adelantar | AY6: Adoptar
A7: AK | D7: MetacogniciónLK | G7: AnálisisB | H7: AnálisisB | I7: AnálisisB | L7: Consignar | M7: Comunicar | N7: Componer | O7: Categorizar | P7: Arreglar | Q7: Alinear | S7: Consignar | T7: Comunicar | U7: Componer | V7: Categorizar | W7: Arreglar | X7: Alinear | Y7: Alinear | Z7: Ampliar | AA7: Ajustar | AB7: Codificar | AC7: Aplicar | AD7: Aprobar | AE7: Agradecer | AF7: Conectar | AG7: Atender | AL7: Copiar | AM7: Contrastar | AN7: Calcular | AO7: Asumir | AP7: Apoyar | AQ7: Maximizar | AT7: Copiar | AU7: Clasificar | AV7: Analizar | AW7: Aplicar | AX7: Adoptar | AY7: Afinar
G8: SíntesisB | H8: SíntesisB | I8: SíntesisB | L8: Decir | M8: Convertir | N8: Conducir | O8: Comparar | P8: Articular | Q8: Arbitrar | S8: Decir | T8: Convertir | U8: Conducir | V8: Comparar | W8: Articular | X8: Arbitrar | Y8: Analizar | Z8: Aplicar | AA8: Apalancar | AB8: Colocar | AC8: Apreciar | AD8: Asegurar | AE8: Ambicionar | AF8: Considerar | AG8: Categorizar | AL8: Decir | AM8: Demostrar | AN8: Categorizar | AO8: Buscar similitudes | AP8: Argumentar | AQ8: Mejorar | AT8: Decir | AU8: Comentar | AV8: Aplicar | AW8: Calcular | AX8: Afinar | AY8: Agradecer
G9: EvaluaciónB | H9: EvaluaciónB | I9: EvaluaciónB | L9: Definir | M9: Criticar | N9: Construir | O9: Considerar | P9: Aumentar | Q9: Asegurar | S9: Definir | T9: Criticar | U9: Construir | V9: Considerar | W9: Aumentar | X9: Asegurar | Y9: Aplicar | Z9: Arreglar | AA9: Bajar | AB9: Componer | AC9: Apreciar | AD9: Autorizar | AE9: Anhelar | AF9: Cuestionar | AG9: Colaborar | AL9: Definir | AM9: Discutir | AN9: Conectar | AO9: Categorizar | AP9: Cambiar | AQ9: Minimizar | AT9: Definir | AU9: Comparar | AV9: Asumir | AW9: Calisificar | AX9: Afirmar | AY9: Ambicionar
L10: Deletrear | M10: Dar ejemplos | N10: Demostrar | O10: Contrastar | P10: Calcular | Q10: Asesorar | S10: Deletrear | T10: Dar ejemplos | U10: Demostrar | V10: Contrastar | W10: Calcular | X10: Asesorar | Y10: Armar | Z10: Colocar | AA10: Colocar | AB10: Conducir | AC10: Asisitir | AD10: Clasificar | AE10: Apoyar | AF10: Defender | AG10: Completar | AL10: Deletrear | AM10: Ejemplificar | AN10: Construir | AO10: Centrarse | AP10: Combinar | AQ10: Modelar | AT10: Deletrear | AU10: Comunicar | AV10: Buscar similitudes | AW10: Categorizar | AX10: Agradecer | AY10: Anhelar
G11: HechosLK | H11: ConceptosLK | I11: ProcedimientosLK | J11: MetacogniciónLK | L11: Demostrar | M11: Debatir | N11: Determinar | O11: Criticar | P11: Componer | Q11: Atar | S11: Demostrar | T11: Debatir | U11: Determinar | V11: Criticar | W11: Componer | X11: Atar | Y11: Arreglar | Z11: Conducir | AA11: Comenzar | AB11: Correr | AC11: Atender | AD11: Colaborar | AE11: Apreciar | AF11: Definir | AG11: Comportarse bajo condiciones | AL11: Duplicar | AM11: Esquematizar | AN11: Demostrar | AO11: Comparar | AP11: Comparar | AQ11: Pensar | AT11: Duplicar | AU11: Contrastar | AV11: Calcular | AW11: Combinar | AX11: Ambicionar | AY11: Anticipar
G12: RecordarLK | H12: RecordarLK | I12: RecordarLK | J12: RecordarLK | L12: Describir | M12: Describir | N12: Dibujar | O12: Cuestionar | P12: Computar | Q12: Calcular | S12: Describir | T12: Describir | U12: Dibujar | V12: Cuestionar | W12: Computar | X12: Calcular | Y12: Asegurar | Z12: Desmontar | AA12: Cortar | AB12: Coser | AC12: Clasificar | AD12: Comunicar | AE12: Aprobar | AF12: Desplegar | AG12: Conducir | AL12: Elegir | AM12: Explicar | AN12: Desarrollar | AO12: Correlacionar | AP12: Compilar | AQ12: Planear | AT12: Elegir | AU12: Convertir | AV12: Calisificar | AW12: Componer | AX12: Anhelar | AY12: Apreciar
G13: ComprenderLK | H13: ComprenderLK | I13: ComprenderLK | J13: ComprenderLK | L13: Elegir | M13: Desplegar | N13: Discriminar | O13: Debatir | P13: Concluir | Q13: Calificar | S13: Elegir | T13: Desplegar | U13: Discriminar | V13: Debatir | W13: Concluir | X13: Calificar | Y13: Bailar | Z13: Dibujar | AA13: Cumplir | AB13: Difundir | AC13: Conducir | AD13: Conocer | AE13: Asistir | AF13: Determinar | AG13: Constatar | AL13: Escribir | AM13: Expresar | AN13: Dramatizar | AO13: Descomponer | AP13: Componer | AQ13: Proponer | AT13: Escribir | AU13: Criticar | AV13: Categorizar | AW13: Conducir | AX13: Anticipar | AY13: Aprobar
G14: AplicarLK | H14: AplicarLK | I14: AplicarLK | J14: AplicarLK | L14: Enseñar | M14: Dibujar | N14: Diseñar | O14: Deducir | P14: Conectar | Q14: Censurar | S14: Enseñar | T14: Dibujar | U14: Diseñar | V14: Deducir | W14: Conectar | X14: Censurar | Y14: Cambiar | Z14: Direccionar | AA14: Destapar | AB14: Direccionar | AC14: Cumplir | AD14: Contar | AE14: Aspirar | AF14: Discernir | AG14: Contextualizar | AL14: Leer | AM14: Generalizar | AN14: Elegir | AO14: Diferenciar | AP14: Construir | AQ14: Reescribir | AT14: Leer | AU14: Dar ejemplos | AV14: Centrarse | AW14: Conectar | AX14: Apoyar | AY14: Asistir
G15: AnalizarLK | H15: AnalizarLK | I15: AnalizarLK | J15: AnalizarLK | L15: Escribir | M15: Discutir | N15: Dramatizar | O15: Desarrollar | P15: Construir | Q15: Clasificar | S15: Escribir | T15: Discutir | U15: Dramatizar | V15: Desarrollar | W15: Construir | X15: Clasificar | Y15: Comparar | Z15: Dirigir | AA15: Dirigir | AB15: Diseñar | AC15: Decir | AD15: Cooperar | AE15: Atender | AF15: Exteriorizar | AG15: Controlar | AL15: Listar | AM15: Ilustrar | AN15: Emplear | AO15: Distinguir | AP15: Convencer | AQ15: Simplificar | AT15: Listar | AU15: Debatir | AV15: Combinar | AW15: Construir | AX15: Apreciar | AY15: Aspirar
G16: EvaluarLK | H16: EvaluarLK | I16: EvaluarLK | J16: EvaluarLK | L16: Establecer | M16: Diseñar | N16: Duplicar | O16: Detectar | P16: Crear | Q16: Computar | S16: Establecer | T16: Diseñar | U16: Duplicar | V16: Detectar | W16: Crear | X16: Computar | Y16: Comprobar | Z16: Docificar | AA16: Disponer | AB16: Disipar | AC16: Detectar | AD16: Decir | AE16: Aunar | AF16: Extraer | AG16: Cooperar | AL16: Localizar | AM16: Inferir | AN16: Enseñar | AO16: Dividir | AP16: Crear | AQ16: Suponer | AT16: Localizar | AU16: Demostrar | AV16: Comparar | AW16: Demostrar | AX16: Aprobar | AY16: Atender
G17: CrearLK | H17: CrearLK | I17: CrearLK | J17: CrearLK | L17: Etiquetar | M17: Establecer | N17: Elegir | O17: Diagramar | P17: Decidir | Q17: Concluir | S17: Etiquetar | T17: Establecer | U17: Elegir | V17: Diagramar | W17: Decidir | X17: Concluir | Y17: Concretar | Z17: Dramatizar | AA17: Dividir | AB17: Ejecutar | AC17: Direccionar | AD17: Demostrar | AE17: Clasificar | AF17: Fomentar | AG17: Cumplir | AL17: Memorizar | AM17: Informar | AN17: Entrevistar | AO17: Elegir | AP17: Criticar | AQ17: Sustituir | AT17: Memorizar | AU17: Describir | AV17: Componer | AW17: Desarrollar | AX17: Arreglar | AY17: Categorizar
L18: Examinar | M18: Examinar | N18: Emparejar | O18: Diferenciar | P18: Deducir | Q18: Conformar | S18: Examinar | T18: Examinar | U18: Emparejar | V18: Diferenciar | W18: Deducir | X18: Conformar | Y18: Conducir | Z18: Ejecutar | AA18: Ejecutar | AB18: Eliminar | AC18: Dirigir | AD18: Discutir | AE18: Compartir | AF18: Formular | AG18: Discriminar | AL18: Mostrar | AM18: Interpretar | AN18: Hacer uso | AO18: Encontrar | AP18: Debatir | AQ18: Teorizar | AT18: Mostrar | AU18: Desplegar | AV18: Conducir | AW18: Determinar | AX18: Asistir | AY18: Clasificar
G19: InformaciónAK | H19: ProcesosAK | I19: PsicomotorAK | L19: Examinar | M19: Explicar | N19: Emplear | O19: Discernir | P19: Derivar | Q19: Constrastar | S19: Examinar | T19: Explicar | U19: Emplear | V19: Discernir | W19: Derivar | X19: Constrastar | Y19: Construir | Z19: Ejercitar | AA19: Ejercer | AB19: Emplear | AC19: Distinguir | AD19: Distinguir | AE19: Comprender | AF19: Identificar | AG19: Distinguir | AL19: Nombrar | AM19: Mostrar | AN19: Identificar | AO19: Encuestar | AP19: Decidir | AQ19: Testar | AT19: Nombrar | AU19: Dibujar | AV19: Considerar | AW19: Dibujar | AX19: Aspirar | AY19: Completar
G20: RecuperaciónAK | H20: RecuperaciónAK | I20: RecuperaciónAK | L20: Grabar | M20: Exponer | N20: Esquematizar | O20: Discriminar | P20: Desarrollar | Q20: Contabilizar | S20: Grabar | T20: Exponer | U20: Esquematizar | V20: Discriminar | W20: Desarrollar | X20: Contabilizar | Y20: Contar | Z20: Encajar | AA20: Emitir | AB20: Ensanchar | AC20: Elegir | AD20: Elegir | AE20: Contribuir | AF20: Percibir | AG20: Ejercer | AL20: Observar | AM20: Observar | AN20: Interpretar | AO20: Establecer | AP20: Deducir | AQ20: Transformar | AT20: Observar | AU20: Discutir | AV20: Construir | AW20: Discriminar | AX20: Atender | AY20: Comprender
G21: ComprensiónAK | H21: ComprensiónAK | I21: ComprensiónAK | L21: Hacer | M21: Expresar | N21: Estimar | O21: Distinguir | P21: Describir | Q21: Controlar | S21: Hacer | T21: Expresar | U21: Estimar | V21: Distinguir | W21: Describir | X21: Controlar | Y21: Contrastar | Z21: Enseñar | AA21: Emitir | AB21: Entallar | AC21: Emplear | AD21: Enumerar | AE21: Convocar | AF21: Preguntar | AG21: Entregar | AL21: Omitir | AM21: Parafrasear | AN21: Manipular | AO21: Examinar | AP21: Defender | AQ21: Visualizar | AT21: Omitir | AU21: Diseñar | AV21: Contrastar | AW21: Diseñar | AX21: Aunar | AY21: Conducir
G22: AnálisisAK | H22: AnálisisAK | I22: AnálisisAK | L22: Identificar | M22: Extraer | N22: Estructurar | O22: Estructurar | P22: Desempeñar | Q22: Corregir | S22: Identificar | T22: Extraer | U22: Estructurar | V22: Estructurar | W22: Desempeñar | X22: Corregir | Y22: Controlar | Z22: Examinar | AA22: Empaquetar | AB22: Entregar | AC22: Escoger | AD22: Escoger | AE22: Creer | AF22: Promover | AG22: Juzgar | AL22: Rastrear | AM22: Predecir | AN22: Organizar | AO22: Inferir | AP22: Demostrar | AT22: Parafrasear | AU22: Ejemplificar | AV22: Correlacionar | AW22: Dramatizar | AX22: Categorizar | AY22: Conectar
G23: UsoConocimientoAK | H23: UsoConocimientoAK | I23: UsoConocimientoAK | L23: Ilustrar | M23: Generalizar | N23: Estructurar | O23: Examinar | P23: Dirigir | Q23: Criticar | S23: Ilustrar | T23: Generalizar | U23: Estructurar | V23: Examinar | W23: Dirigir | X23: Criticar | Y23: Coordinar | Z23: Explorar | AA23: Encontrar | AB23: Esculpir | AC23: Escuchar | AD23: Hablar | AE23: Cuidar | AF23: Proponer | AG23: Negociar | AL23: Recitar | AM23: Preguntar | AN23: Planear | AO23: Inspeccionar | AP23: Descubrir | AT23: Rastrear | AU23: Esquematizar | AV23: Criticar | AW23: Duplicar | AX23: Clasificar | AY23: Considerar
G24: MetacogniciónAK | H24: MetacogniciónAK | I24: MetacogniciónAK | L24: Listar | M24: Hacer | N24: Evaluar | O24: Experimentar | P24: Diseñar | Q24: Cuestionar | S24: Listar | T24: Hacer | U24: Evaluar | V24: Experimentar | W24: Diseñar | X24: Cuestionar | Y24: Cortar | Z24: Expresar | AA24: Entrenar | AB24: Extender | AC24: Estimar | AD24: Hacer | AE24: Elegir | AF24: Proteger | AG24: Ofrecer | AL24: Reconocer | AM24: Relacionar | AN24: Practicar | AO24: Investigar | AP24: Diseñar | AT24: Recitar | AU24: Establecer | AV24: Cuestionar | AW24: Elegir | AX24: Colaborar | AY24: Constatar
G25: AutoSistemaAK | H25: AutoSistemaAK | I25: AutoSistemaAK | L25: Mostar | M25: Identificar | N25: Experimentar | O25: Inspeccionar | P25: Ejercer | Q25: Culminar | S25: Mostar | T25: Identificar | U25: Experimentar | V25: Inspeccionar | W25: Ejercer | X25: Culminar | Y25: Cotejar | Z25: Extraer | AA25: Envasar | AB25: Extirpar | AC25: Evaluar | AD25: Indicar | AE25: Emplear | AF25: Reconocer | AG25: Participar | AL25: Relacionar | AM25: Resumir | AN25: Resolver | AO25: Motivar | AP25: Estimar | AT25: Reconocer | AU25: Examinar | AV25: Debatir | AW25: Emparejar | AX25: Compartir | AY25: Contextualizar
L26: Nombrar | M26: Indicar | N26: Ilustrar | O26: Inventariar | P26: Ensamblar | Q26: Debatir | S26: Nombrar | T26: Indicar | U26: Ilustrar | V26: Inventariar | W26: Ensamblar | X26: Debatir | Y26: Demostrar | Z26: Guiar | AA26: Establecer | AB26: Hacer | AC26: Examinar | AD26: Informar | AE26: Ensamblar | AF26: Relacionar | AG26: Servir | AL26: Relacionar | AM26: Revisar | AN26: Resumir | AO26: Observar | AP26: Evaluar | AT26: Relacionar | AU26: Explicar | AV26: Deducir | AW26: Emplear | AX26: Completar | AY26: Cuestionar
L27: Numerar | M27: Inferir | N27: Indicar | O27: Investigar | P27: Escribir | Q27: Decidir | S27: Numerar | T27: Inferir | U27: Indicar | V27: Investigar | W27: Escribir | X27: Decidir | Y27: Detectar | Z27: Hacer | AA27: Estampar | AB27: Implementar | AC27: Guiar | AD27: Narrar | AE27: Escoger | AF27: Relatar | AG27: Soportar | AL27: Repetir | AM27: Traducir | AN27: Seleccionar | AO27: Ordenar | AP27: Experimentar | AT27: Repetir | AU27: Exponer | AV27: Demostrar | AW27: Enseñar | AX27: Comportarse bajo condiciones | AY27: Cuidar
L28: Observar | M28: Interpretar | N28: Interpretar | O28: Listar | P28: Establecer | Q28: Deducir | S28: Observar | T28: Interpretar | U28: Interpretar | V28: Listar | W28: Establecer | X28: Deducir | Y28: Direccionar | Z28: Identificar | AA28: Estimular | AB28: Industrializar | AC28: Hacer | AD28: Obrar recíprocamente | AE28: Estimar | AF28: Resumir | AG28: Terminar | AN28: Simular | AO28: Preguntar | AP28: Explicar | AU28: Expresar | AV28: Desarrollar | AW28: Entrevistar | AX28: Comprender | AY28: Cumplir
L29: Obtener | M29: Inventariar | N29: Investigar | O29: Medir | P29: Estudiar | Q29: Defender | S29: Obtener | T29: Inventariar | U29: Investigar | V29: Medir | W29: Estudiar | X29: Defender | Y29: Disponer | Z29: Inspeccionar | AA29: Extraer | AB29: Inspeccionar | AC29: Interrogar | AD29: Recitar | AE29: Estimular | AF29: Revelar | AG29: Verificar | AN29: Transferir | AO29: Priorizar | AP29: Extender | AU29: Extraer | AV29: Descomponer | AW29: Esquematizar | AX29: Conducir | AY29: Defender
L30: Ordenar | M30: Localizar | N30: Listar | O30: Planear | P30: Figurar | Q30: Defender | S30: Ordenar | T30: Localizar | U30: Listar | V30: Planear | W30: Figurar | X30: Defender | Y30: Edificar | Z30: Instalar | AA30: Fabricar | AB30: Llevar | AC30: Manejar | AD30: Referir | AE30: Participar | AG30: Examinar | AN30: Unir | AO30: Probar | AP30: Formular | AU30: Generalizar | AV30: Detectar | AW30: Estimar | AX30: Conectar | AY30: Determinar
L31: Organizar | M31: Narrar | N31: Manipular | O31: Preguntar | P31: Formular | Q31: Determinar | S31: Organizar | T31: Narrar | U31: Manipular | V31: Preguntar | W31: Formular | X31: Determinar | Y31: Ensamblar | Z31: Inventariar | AA31: Gestionar | AB31: Manejar | AC31: Observar | AD31: Relatar | AE31: Preocuparse de o por | AN31: Usar | AO31: Razonar | AP31: Hipotetizar | AU31: Hacer | AV31: Determinar | AW31: Estructurar | AX31: Considerar | AY31: Discernir
L32: Preguntar | M32: Parafrasear | N32: Modelar | O32: Probar | P32: Generar | Q32: Discutir | S32: Preguntar | T32: Parafrasear | U32: Modelar | V32: Probar | W32: Generar | X32: Discutir | Y32: Escoger | Z32: Manejar | AA32: Grabar | AB32: Mecanizar | AC32: Ocupar | AD32: Resolver | AE32: Proporcionar | AO32: Reorganizar | AP32: Influir | AU32: Identificar | AV32: Diagramar | AW32: Evaluar | AX32: Constatar | AY32: Discriminar
L33: Presentar | M33: Presentar | N33: Operar | O33: Reconocer | P33: Gestionar | Q33: Elegir | S33: Presentar | T33: Presentar | U33: Operar | V33: Reconocer | W33: Gestionar | X33: Elegir | Y33: Filtrar | Z33: Maniobrar | AA33: Hacer | AB33: Mover | AC33: Preguntar | AD33: Seleccionar | AE33: Provocar | AO33: Resaltar | AP33: Innovar | AU33: Ilustrar | AV33: Dibujar | AW33: Experimentar | AX33: Contextualizar | AY33: Distinguir
L34: Probar | M34: Relatar | N34: Organizar | O34: Relacionar | P34: Hacer | Q34: Ensamblar | S34: Probar | T34: Relatar | U34: Organizar | V34: Relacionar | W34: Hacer | X34: Ensamblar | Y34: Gestionar | Z34: Manipular | AA34: Hallar | AB34: Ordenar | AC34: Publicar | AE34: Ratificar | AO34: Separar | AP34: Justificar | AU34: Indicar | AV34: Diferenciar | AW34: Hacer uso | AX34: Contribuir | AY34: Ejercer
L35: Realizar | M35: Reportar | N35: Patronar | O35: Separar | P35: Inferir | Q35: Escoger | S35: Realizar | T35: Reportar | U35: Patronar | V35: Separar | W35: Inferir | X35: Escoger | Y35: Hacer | Z35: Mejorar | AA35: Imprimir | AB35: Ponderar | AC35: Realizar | AE35: Seleccionar | AO35: Simplificar | AP35: Juzgar | AU35: Inferir | AV35: Discernir | AW35: Identificar | AX35: Controlar | AY35: Elegir
L36: Reconocer | M36: Resumir | N36: Practicar | O36: Subdividir | P36: Instalar | Q36: Establecer | S36: Reconocer | T36: Resumir | U36: Practicar | V36: Subdividir | W36: Instalar | X36: Establecer | Y36: Inspeccionar | Z36: Perforar | AA36: Impulsar | AB36: Preguntar | AC36: Seleccionar | AE36: Ser partidario de | AP36: Medir | AU36: Informar | AV36: Discriminar | AW36: Ilustrar | AX36: Convocar | AY36: Escoger
L37: Recordar | M37: Revisar | N37: Recoger | P37: Interpretar | Q37: Estimar | S37: Recordar | T37: Revisar | U37: Recoger | W37: Interpretar | X37: Estimar | Y37: Juntar | Z37: Poner | AA37: Interpretar | AB37: Probar | AC37: Servir | AE37: Soportar | AP37: Opinar | AU37: Interpretar | AV37: Diseñar | AW37: Indicar | AX37: Cooperar | AY37: Estimar
L38: Registrar | M38: Seleccionar | N38: Relacionar | P38: Introducir | Q38: Evaluar | S38: Registrar | T38: Seleccionar | U38: Relacionar | W38: Introducir | X38: Evaluar | Y38: Limpiar | Z38: Reconocer | AA38: Levantar | AB38: Quitar | AC38: Tasar | AE38: Tasar | AP38: Originar | AU38: Inventariar | AV38: Distinguir | AW38: Interpretar | AX38: Creer | AY38: Estimular
L39: Relacionar | M39: Separar | N39: Reportar | P39: Inventar | Q39: Evaluar | S39: Relacionar | T39: Separar | U39: Reportar | W39: Inventar | X39: Evaluar | Y39: Modificar | Z39: Registrar | AA39: Localizar | AB39: Reconocer | AC39: Usar | AE39: Unir | AP39: Percibir | AU39: Localizar | AV39: Dividir | AW39: Investigar | AX39: Cuestionar | AY39: Exteriorizar
L40: Relatar | M40: Traducir | N40: Resolver | P40: Juntar | Q40: Finalizar | S40: Relatar | T40: Traducir | U40: Resolver | W40: Juntar | X40: Finalizar | Y40: Modificar | Z40: Revisar | AA40: Manejar | AB40: Reemplazar | AC40: Valorar | AP40: Persuadir | AU40: Mostrar | AV40: Dramatizar | AW40: Listar | AX40: Cuidar | AY40: Extraer
L41: Reproducir | M41: Transformar | N41: Transferir | P41: Manipular | Q41: Formar | S41: Reproducir | T41: Transformar | U41: Transferir | W41: Manipular | X41: Formar | Y41: Ordenar | Z41: Trazar | AA41: Maniobrar | AB41: Remover | AP41: Premiar | AU41: Narrar | AV41: Duplicar | AW41: Manipular | AX41: Cumplir | AY41: Formular
L42: Revisar | M42: Ubicar | N42: Usar | P42: Mejorar | Q42: Justificar | S42: Revisar | T42: Ubicar | U42: Usar | W42: Mejorar | X42: Justificar | Y42: Organizar | AA42: Manipular | AB42: Reparar | AP42: Probar | AU42: Observar | AV42: Elegir | AW42: Modelar | AX42: Defender | AY42: Identificar
L43: Rotular | N43: Valorar | P43: Modificar | Q43: Juzgar | S43: Rotular | U43: Valorar | W43: Modificar | X43: Juzgar | Y43: Preparar | AA43: Medir | AB43: Reponer | AP43: Recomendar | AU43: Predecir | AV43: Emparejar | AW43: Operar | AX43: Definir | AY43: Juzgar
L44: Seleccionar | P44: Numerar | Q44: Marcar | S44: Seleccionar | W44: Numerar | X44: Marcar | Y44: Probar | AA44: Mezclar | AB44: Reproducir | AP44: Seleccionar | AU44: Preguntar | AV44: Emplear | AW44: Organizar | AX44: Desplegar | AY44: Negociar
L45: Subrayar | P45: Obtener | Q45: Marcar | S45: Subrayar | W45: Obtener | X45: Marcar | Y45: Recaudar | AA45: Mitigar | AB45: Resolver | AP45: Testar | AU45: Presentar | AV45: Encontrar | AW45: Patronar | AX45: Determinar | AY45: Ofrecer
P46: Ordenar | Q46: Medir | W46: Ordenar | X46: Medir | Y46: Recoger | AA46: Modificar | AB46: Retirar | AP46: Valorar | AU46: Relacionar | AV46: Encuestar | AW46: Planear | AX46: Discernir | AY46: Participar
P47: Organizar | Q47: Modificar | W47: Organizar | X47: Modificar | Y47: Recortar | AA47: Mover | AB47: Revisar | AU47: Relatar | AV47: Esquematizar | AW47: Practicar | AX47: Discriminar | AY47: Percibir
P48: Organizar | Q48: Numerar | W48: Organizar | X48: Numerar | Y48: Reunir | AA48: Negociar | AB48: Seguir | AU48: Reportar | AV48: Establecer | AW48: Recoger | AX48: Distinguir | AY48: Preguntar
P49: Perfeccionar | Q49: Peritar | W49: Perfeccionar | X49: Peritar | Y49: Señalar | AA49: Operar | AB49: Servir | AU49: Resumir | AV49: Estimar | AW49: Relacionar | AX49: Ejercer | AY49: Promover
P50: Planear | Q50: Predecir | W50: Planear | X50: Predecir | Y50: Transformar | AA50: Ordenar | AB50: Sincronizar | AU50: Revisar | AV50: Estructurar | AW50: Reportar | AX50: Elegir | AY50: Proponer
P51: Planificar | Q51: Pronosticar | W51: Planificar | X51: Pronosticar | Y51: Trazar | AA51: Organizar | AB51: Soldar | AU51: Seleccionar | AV51: Evaluar | AW51: Resolver | AX51: Ensamblar | AY51: Proporcionar
P52: Poner | Q52: Recomendar | W52: Poner | X52: Recomendar | Y52: Verificar | AA52: Pintar | AB52: Suprimir | AU52: Separar | AV52: Examinar | AW52: Resumir | AX52: Entregar | AY52: Provocar
P53: Predecir | Q53: Repartir | W53: Predecir | X53: Repartir | AA53: Planear | AB53: Sustituir | AU53: Traducir | AV53: Experimentar | AW53: Seleccionar | AX53: Escoger | AY53: Reconocer
P54: Preparar | Q54: Resolver | W54: Preparar | X54: Resolver | AA54: Porcionar | AB54: Tapizar | AU54: Transformar | AV54: Ilustrar | AW54: Simular | AX54: Estimar | AY54: Relacionar
P55: Producir | Q55: Reunir | W55: Producir | X55: Reunir | AA55: Practicar | AB55: Traducir | AU55: Ubicar | AV55: Indicar | AW55: Transferir | AX55: Estimular | AY55: Resumir
P56: Proponer | Q56: Revisar | W56: Proponer | X56: Revisar | AA56: Presentar | AB56: Transmitir | AV56: Inferir | AW56: Unir | AX56: Exteriorizar | AY56: Seleccionar
P57: Proyectar | Q57: Seleccionar | W57: Proyectar | X57: Seleccionar | AA57: Producir | AB57: Trasladar | AV57: Inspeccionar | AW57: Usar | AX57: Extraer | AY57: Ser partidario de
P58: Resolver | Q58: Sistematizar | W58: Resolver | X58: Sistematizar | AA58: Racionar | AB58: Ubicar | AV58: Interpretar | AX58: Fomentar | AY58: Unir
P59: Reunir | Q59: Sugerir | W59: Reunir | X59: Sugerir | AA59: Realizar | AB59: Usar | AV59: Inventariar | AX59: Formular | AY59: Valorar
P60: Señalar | Q60: Tasar | W60: Señalar | X60: Tasar | AA60: Reducir | AB60: Utilizar | AV60: Investigar | AX60: Identificar
P61: Simplificar | Q61: Terminar | W61: Simplificar | X61: Terminar | AA61: Repartir | AB61: Validar | AV61: Listar | AX61: Juzgar
P62: Subdividir | Q62: Unir | W62: Subdividir | X62: Unir | AA62: Repasar | AB62: Verificar | AV62: Manipular | AX62: Negociar
P63: Suponer | Q63: Validar | W63: Suponer | X63: Validar | AA63: Representar | AB63: Desarrollar | AV63: Medir | AX63: Ofrecer
Q64: Valorar | X64: Valorar | AA64: Revisar | AV64: Modelar | AX64: Participar
Q65: Verificar | X65: Verificar | AA65: Sacar | AV65: Motivar | AX65: Percibir
Q66: Vincular | X66: Vincular | AA66: Separer | AV66: Observar | AX66: Preguntar
AA67: Situar | AV67: Operar | AX67: Preocuparse de o por
AA68: Tocar | AV68: Ordenar | AX68: Promover
AA69: Ubicar | AV69: Organizar | AX69: Proponer
AA70: Elaborar | AV70: Patronar | AX70: Proporcionar
AV71: Planear | AX71: Proteger
AV72: Practicar | AX72: Provocar
AV73: Preguntar | AX73: Ratificar
AV74: Priorizar | AX74: Reconocer
AV75: Probar | AX75: Relacionar
AV76: Razonar | AX76: Relatar
AV77: Recoger | AX77: Resumir
AV78: Reconocer | AX78: Revelar
AV79: Relacionar | AX79: Seleccionar
AV80: Reorganizar | AX80: Ser partidario de
AV81: Reportar | AX81: Servir
AV82: Resaltar | AX82: Soportar
... AV87: Transferir | AX87: Verificar
AV88: Usar
