Workbook
Name actitudinalB: Tabla5785[ActitudinalB]
Name ActitudinalBAK: 'Taxonomias para RA'!$AC$3:$AG$3
Name AK: Tabla5987[AK]
Name AnálisisB: Tabla385280[AnálisisB]
Name AnálisisBAK: Tabla3865[AnálisisBAK]
Name AnálisisMK: Tabla99[AnálisisMK]
Name AnalizarLK: Tabla2129[AnalizarLK]
Name AplicaciónB: Tabla375179[AplicaciónB]
Name AplicaciónBAK: Tabla3764[AplicaciónBAK]
Name AplicarLK: Tabla2028[AplicarLK]
Name áreasprofesionales: #REF!
Name BAK: Tabla5886[BAK]
Name Bloom: 'Taxonomias para RA'!$G$3:$I$3
Name CaracterizarBAK: Tabla4776[CaracterizarBAK]
Name Cognitivo: 'Paso1 Analisis perfil egreso'!$E$3:$E$16
Name CognitivoAK: 'Taxonomias para RA'!$AL$4:$AQ$4
Name cognitivoB: Tabla5583[CognitivoB]
Name CognitivoBAK: 'Taxonomias para RA'!$S$3:$X$3
Name competencias: 'Paso 2 Redacción competen'!$F$3:$F$7
Name ComprenderLK: 'Taxonomias para RA'!$AM$5:$AM$27
Name ComprensionB: Tabla365078[ComprensiónB]
Name ComprensiónBAK: Tabla3663[ComprensiónBAK]
Name ComprensiónMK: Tabla98[ComprensiónMK]
Name ConceptosLK: Tabla91[ConceptosAK]
Name ConocimientoB: Tabla354977[ConocimientoB]
Name ConocimientoBAK: Tabla3555[ConocimientoBAK]
Name Conocimientos: 'Paso1 Analisis perfil egreso'!$E$3:$E$16
Name ControlBAK: Tabla4271[ControlBAK]
Name CrearLK: Tabla2333[CrearLK]
Name dominios: 'Paso1 Analisis perfil egreso'!$E$2:$G$2
Name EvaluaciónB: Tabla405482[EvaluaciónB]
Name EvaluaciónBAK: Tabla4067[EvaluaciónBAK]
Name EvaluarLK: 'Taxonomias para RA'!$AP$5:$AP$46
Name HechosLK: Tabla90[CognitivoAK]
Name ImitaciónBAK: Tabla1168[ImitaciónBAK]
Name ManipulaciónBAK: Tabla3069[ManipulaciónBAK]
Name MetacogniciónLK: Tabla93[MetacogniciónAK]
Name MetacogniciónMK: Tabla101[MetacogniciónMK]
Name MetocogniciónAK: Tabla101[MetacogniciónMK]
Name MK: Tabla6088[MK]
Name ocupacional: 'Paso1 Analisis perfil egreso'!#REF!
Name OrganizarBAK: Tabla4675[OrganizarBAK]
Name PercepciónBAK: 'Taxonomias para RA'!$AC$4:$AC$40
Name poblacionactuacion: #REF!
Name poblaciones: #REF!
Name poblacionesactuación: #REF!
Name PrecisiónBAK: Tabla4170[PrecisiónBAK]
Name procedimentalB: Tabla5684[ProcedimentalB]
Name ProcedimentalBAK: 'Taxonomias para RA'!$Y$3:$AB$3
Name ProcedimientosMK: Tabla92[ProcedimientosAK]
Name ProcesosAK: ProcesosMentalesMK[ProcesosMentalesMK]
Name PsicomotorMK: Tabla96[PsicomotorMK]
Name RecordarLK: 'Taxonomias para RA'!$AL$5:$AL$27
Name RecuperaciónMK: 'Taxonomias para RA'!$BB$5:$BB$27
Name ResponderBAK: Tabla4473[ResponderBAK]
Name resultadoaprendizaje: 'Paso 3 Redacción RA '!$I$3:$I$11
Name Saber: 'Paso1 Analisis perfil egreso'!$E$2:$E$5
Name Saberhacer: 'Paso1 Analisis perfil egreso'!$F$3:$F$15
Name saberser: 'Paso1 Analisis perfil egreso'!$G$3:$G$15
Name SíntesisB: Tabla395381[SíntesisB]

Sheet Paso1 Analisis perfil egreso
A1: [Escribir el nombre del programa] | B1: [Escribir la modalidad: presencial o virtual] | C1: [Escribir el perfil profesional del egresado.] | D1: [Escribir el perfil ocupacional del egresado.] | E1: Componentes fundamentales para definir competencias [Listar las palabras clave, no armar oraciones, respecto qué debe saber el egresado en las categorías de Saber -conocimientos, hechos, teorías-, Saber hacer -técnicas, procedimientos, metodologías-, y Saber ser -valores, condiciones. Esta información se estructura a partir del perfil profesional y cada saber hacer depende del saber ubicado a su izquierda, lo mismo ocurre con el saber ser.] | H1: Componentes fundamentales de la ocupación laboral del profesional [Listar, según lo escrito en el perfil ocupacional, en qué áreas, qué tareas potenciales y en qué poblaciones o contextos podrá laborar el profesional. Esta información es un listado general no requiere dependencia horizontal] | K1: Diferencial (valor agregado) del profesional [Listar, según lo escrito en los perfiles, los elementos que son diferenciales y generan un valor agregado al egresado. Debe ser disciplinar, asociado al perfil, ¿qué es lo que lo hace diferente a otros perfiles similares.]
A2: Programa | B2: Modalidad | C2: Perfil profesional | D2: Perfil ocupacional | E2: Saber | F2: Saberhacer | G2: Saberser | H2: ÁreasProfesionales | I2: TareasProfesionales | J2: PoblacionesActuacion | K2: ValorAgregado
A3: Maestría en Educación STEM | B3: Virtual | C3: El egresado es un ser humano que impulsa el cambio educativo en los diferentes niveles de formación del país, profundizando en la integración de las ciencias, la tecnología, la ingeniería y las matemáticas (STEM), para proyectar propuestas educativas o curriculares innovadoras enmarcadas en el estudio y la promoción del desarrollo de vocaciones STEM, el cierre de brechas e inclusión en las áreas STEM, y la apropiación social de la ciencia, la tecnología y la innovación, en la población estudiantil, de acuerdo con las condiciones y necesidades de las regiones. | D3: El egresado del programa tendrá habilidades para gestionar, asesorar, coordinar, diseñar, implementar y evaluar proyectos o propuestas educativas o curriculares en educación STEM, orientados al mejoramiento de la educación y la integración conocimientos de estas áreas disciplinares. | E3: Educación STEM | F3: para desarrollar competencias analíticas, sistémicas, críticas y de alfabetización digital, desde un enfoque integrador | G3: que transforme los procesos de enseñanza y de aprendizaje, en los distintos niveles de formación, de acuerdo con las condiciones locales o regionales de la comunidad educativa. | H3: Docencia Dirección de proyectos educativos Coordinación de proyectos educativos Gestión de proyectos educativos Consultoría | I3: Diseñar y orientar procesos de formación bajo el marco de la educación STEM en diferentes niveles educativos. Gestionar propuestas educativas innovadoras bajo un marco integrador de las ciencias, la tecnología, la ingeniería y las matemáticas. Direccionar el horizonte institucional atendiendo a los requerimientos del contexto local y regional. Coordinar equipo de trabajo en acciones asociadas a la educación STEM y dirigidos a la comunidad educativa. Asesorar y orientar procesos de gestión de proyectos educativos o currículos en educación formal y no formal. Promover y articular acciones, procesos y estrategias de gestión intrainstitucional e intersectorial en el marco de la educación STEM. | J3: Educación formal en diferentes niveles educativos. Instituciones cuyo propósito es la apropiación y divulgación de la ciencia y la tecnología para la apropiación social del conocimiento. | K3: Estar en la capacidad de generar propuestas o proyectos innovadores que contribuyen a la apropiación social del conocimiento. Desarrollar procesos y estrategias de educación STEM intrainstitucionales o intersectoriales.
E4: Vocaciones STEM, cierre de brechas e inclusión en STEM, apropiación social de CTeI | F4: para plantear estudios que permitan reconocer y comprender las necesidades formativas del país | G4: que emergen a partir de las diferencias y potencialidades regionales ante los cambios culturales y educativos que demanda la sociedad del conocimiento.
E5: Proyectos educativos y curriculares | F5: para materializar propuestas y experiencias en educación STEM | G5: que aborden los retos y problemas de la educación en el país, con una perspectiva analítica, reflexiva, crítica y constructiva.

Sheet Paso 2 Redacción competen
A1: [Enumerar las competencias que se van a declarar.] | B1: [A partir de la celda B2 dar clic sobre el ícono de lista desplegable y elegir el verbo que considere adecuado.] | C1: [A partir de la celda C2 dar clic sobre la lista desplegable y elegir el saber extraído del perfil de egreso.] | D1: [Escribir para qué se abordará el saber elegido. Se sugiere apoyarse en el saber hacer.] | E1: [Escribir la condición describiendo los referentes, parámetros, principios, requerimientos o retos que se necesitan para alcanzar las características del perfil en el contexto donde el egresado se desenvolverá.] | F1: [Articular los componentes. Iniciar con el verbo, continuar con el objeto conceptual, luego la finalidad y condición de contexto o referencia; estos últimos no requieren un orden particular.] | G1: [Escribir el tipo de competencia del perfil: Específica (si es del bloque Disciplinar para pregrado o de los componentes para el caso de posgrado) o Genérica (si aplica bloque institucional pregrado)]
A2: No. | B2: Verbo competencia | C2: Objeto conceptual | D2: Finalidad | E2: Condición de contexto o referencia | F2: Redacción competencia | G2: Tipo competencia
A3: 1 | B3: Dominar | C3: Educación STEM | D3: para desarrollar competencias analíticas, sistémicas, críticas y de alfabetización digital, desde un enfoque integrador | E3: que transforme los procesos de enseñanza y de aprendizaje, en los distintos niveles de formación, de acuerdo con las condiciones locales o regionales de la comunidad educativa. | F3: Dominar los elementos teóricos y prácticos de la educación STEM para el desarrollo de competencias analíticas, sistémicas, computacionales, críticas y de alfabetización digital, desde un enfoque integrador, que transforme los procesos de enseñanza y de aprendizaje, en los distintos niveles de formación, de acuerdo con las condiciones locales o regionales de la comunidad educativa. | G3: Específica
A4: 2 | B4: Analizar | C4: Vocaciones STEM, cierre de brechas e inclusión en STEM, apropiación social de CTeI | D4: para plantear estudios que permitan reconocer y comprender las necesidades formativas del país | E4: que emergen a partir de las diferencias y potencialidades regionales ante los cambios culturales y educativos que demanda la sociedad del conocimiento. | F4: Analiza problemáticas asociadas al desarrollo de vocaciones STEM, el cierre de brechas e inclusión en STEM y la apropiación social de CTI, para darles solución a través de estudios o propuestas de investigación en los que se reconozcan y comprendan las necesidades formativas del país, según las diferencias y potencialidades regionales que demandan los cambios culturales y educativos en la sociedad del conocimiento. | G4: Específica
A5: 3 | B5: Formular | C5: Proyectos educativos y curriculares | D5: para materializar propuestas y experiencias en educación STEM | E5: que aborden los retos y problemas de la educación en el país, con una perspectiva analítica, reflexiva, crítica y constructiva. | F5: Formula proyectos educativos y curriculares para materializar propuestas y experiencias educativas innovadoras en STEM, desde la práctica profesional, que aborden los retos y problemas de la educación en el país, con una perspectiva analítica, reflexiva, crítica y constructiva. | G5: Específica

Sheet Paso 3 Redacción RA 
A1: [A partir de la celda A2 dar clic en la lista desplegable y seleccionar la competencia redactada en el paso 2.] | B1: [Enumerar los resultados de aprendizaje que se van a declarar.] | C1: [A partir de la celda C2, dar clic en la lista desplegable y elegir el tipo de dominio a tratar en el resultado de aprendizaje.] | D1: [A partir de la cela D2, dar clic en la lista desplegable y elegir el saber correspondiente al dominio.] | E1: [A partir de la celda E2, dar clic en la lista desplegable y elegir la taxonomía que se considere adecuada, solo se elige una para todos los saberes.] | F1: [A partir de la celda F2, dar clic en la lista desplegable y elegir el dominio que se considera adecuado.] | G1: [A partir de la celda G2, dar clic en la lista desplegable y elegir el nivel del dominio que se considera adecuado.] | H1: [A partir de la celda H2, dar clic en la lista desplegable y elegir el verbo que se considera adecuado.] | I1: [Iniciar con el verbo elegido (columna H), en infinitivo, luego el objeto sobre el cual recae la acción (columna D) y finalmente la condición de contexto (académico, disciplinar, social u otro).]
A2: Competencia por desarrollar | B2: Número de resultado | C2: TipoSaber | D2: SaberAsociado | E2: Taxonomía | F2: Dominio Asociado | G2: Nivel Dominio | H2: Verbo RA | I2: Resultados Aprendizaje
A3: Domina los elementos teóricos y prácticos de la educación STEM para el desarrollo de competencias analíticas, sistémicas, computacionales, críticas y de alfabetización digital, desde un enfoque integrador, que transforme los procesos de enseñanza y de aprendizaje, en los distintos niveles de formación, de acuerdo con las condiciones locales o regionales de la comunidad educativa. | B3: 1 | C3: Saber | D3: Educación STEM | E3: BAK | F3: CognitivoBAK | G3: EvaluaciónBAK | H3: Determinar | I3: Determina las condiciones y estructuras de pensamiento que se requieren para impulsar el aprendizaje en la educación STEM, contrastando los factores que inciden en el desarrollo de competencias analíticas, sistémicas, computacionales, críticas y de alfabetización digital con los principios teóricos y prácticos de este marco educativo.
A4: Domina los elementos teóricos y prácticos de la educación STEM para el desarrollo de competencias analíticas, sistémicas, computacionales, críticas y de alfabetización digital, desde un enfoque integrador, que transforme los procesos de enseñanza y de aprendizaje, en los distintos niveles de formación, de acuerdo con las condiciones locales o regionales de la comunidad educativa. | B4: 2 | C4: Saberhacer | D4: para desarrollar competencias analíticas, sistémicas, críticas y de alfabetización digital, desde un enfoque integrador | E4: BAK | F4: ProcedimentalBAK | G4: PrecisiónBAK | H4: Elaborar | I4: Elabora una ruta pedagógica y didáctica que articule los factores que inciden en el desarrollo de competencias analíticas, sistémicas, computacionales, críticas y de alfabetización digital con los principios teóricos y prácticos de la educación STEM para definir una propuesta formativa.
A5: Domina los elementos teóricos y prácticos de la educación STEM para el desarrollo de competencias analíticas, sistémicas, computacionales, críticas y de alfabetización digital, desde un enfoque integrador, que transforme los procesos de enseñanza y de aprendizaje, en los distintos niveles de formación, de acuerdo con las condiciones locales o regionales de la comunidad educativa. | B5: 3 | C5: Saberser | D5: que transforme los procesos de enseñanza y de aprendizaje, en los distintos niveles de formación, de acuerdo con las condiciones locales o regionales de la comunidad educativa. | E5: BAK | F5: ActitudinalBAK | G5: CaracterizarBAK | H5: Evaluar | I5: Evalúa las condiciones y necesidades educativas del contexto local o regional para validar la pertinencia de estudios o propuestas formativas en educación STEM con una visión transformadora de los procesos de enseñanza y de aprendizaje.
A6: Analiza problemáticas asociadas al desarrollo de vocaciones STEM, el cierre de brechas e inclusión en STEM y la apropiación social de CTI, para darles solución a través de estudios o propuestas de investigación en los que se reconozcan y comprendan las necesidades formativas del país, según las diferencias y potencialidades regionales que demandan los cambios culturales y educativos en la sociedad del conocimiento. | B6: 4 | C6: Saber | D6: Vocaciones STEM, cierre de brechas e inclusión en STEM, apropiación social de CTeI | E6: BAK | F6: CognitivoBAK | G6: EvaluaciónBAK | H6: Diagnosticar | I6: Diagnostica los factores y necesidades formativas del país, según las diferencias y potencialidades regionales que demandan los cambios culturales y educativos, para identificar problemáticas asociadas al desarrollo de vocaciones STEM, el cierre de brechas e inclusión en STEM y la apropiación social de CTI.
A7: Analiza problemáticas asociadas al desarrollo de vocaciones STEM, el cierre de brechas e inclusión en STEM y la apropiación social de CTI, para darles solución a través de estudios o propuestas de investigación en los que se reconozcan y comprendan las necesidades formativas del país, según las diferencias y potencialidades regionales que demandan los cambios culturales y educativos en la sociedad del conocimiento. | B7: 5 | C7: Saberhacer | D7: para plantear estudios que permitan reconocer y comprender las necesidades formativas del país | E7: BAK | F7: ProcedimentalBAK | G7: ControlBAK | H7: Diseñar | I7: Diseña un estudio o una propuesta de investigación que aborde problemáticas asociadas al desarrollo de vocaciones STEM, el cierre de brechas e inclusión en STEM y la apropiación social de CTI, desde un enfoque integrador, incorporando una ruta pedagógica y didáctica para el desarrollo de competencias analíticas, sistémicas, computacionales, críticas y de alfabetización digital en la población estudiantil.
A8: Analiza problemáticas asociadas al desarrollo de vocaciones STEM, el cierre de brechas e inclusión en STEM y la apropiación social de CTI, para darles solución a través de estudios o propuestas de investigación en los que se reconozcan y comprendan las necesidades formativas del país, según las diferencias y potencialidades regionales que demandan los cambios culturales y educativos en la sociedad del conocimiento. | B8: 3 | C8: Saberser | D8: que emergen a partir de las diferencias y potencialidades regionales ante los cambios culturales y educativos que demanda la sociedad del conocimiento. | E8: BAK | F8: ActitudinalBAK | G8: CaracterizarBAK | H8: Evaluar | I8: Evalúa las condiciones y necesidades educativas del contexto local o regional para validar la pertinencia de estudios o propuestas formativas en educación STEM con una visión transformadora de los procesos de enseñanza y de aprendizaje.
A9: Formula proyectos educativos y curriculares para materializar propuestas y experiencias educativas innovadoras en STEM, desde la práctica profesional, que aborden los retos y problemas de la educación en el país, con una perspectiva analítica, reflexiva, crítica y constructiva. | B9: 4 | C9: Saber | D9: Proyectos educativos y curriculares | E9: BAK | F9: CognitivoBAK | G9: EvaluaciónBAK | H9: Diagnosticar | I9: Diagnostica los factores y necesidades formativas del país, según las diferencias y potencialidades regionales que demandan los cambios culturales y educativos, para identificar problemáticas asociadas al desarrollo de vocaciones STEM, el cierre de brechas e inclusión en STEM y la apropiación social de CTI.
A10: Formula proyectos educativos y curriculares para materializar propuestas y experiencias educativas innovadoras en STEM, desde la práctica profesional, que aborden los retos y problemas de la educación en el país, con una perspectiva analítica, reflexiva, crítica y constructiva. | B10: 6 | C10: Saberhacer | D10: para materializar propuestas y experiencias en educación STEM | E10: BAK | F10: ProcedimentalBAK | G10: ControlBAK | H10: Desarrollar | I10: Desarrolla un estudio o una propuesta educativa innovadora basada en la educación STEM desde un enfoque integrador, para abordar los retos y problemas de la educación en el país, con una perspectiva analítica, reflexiva, crítica y constructiva.
A11: Formula proyectos educativos y curriculares para materializar propuestas y experiencias educativas innovadoras en STEM, desde la práctica profesional, que aborden los retos y problemas de la educación en el país, con una perspectiva analítica, reflexiva, crítica y constructiva. | B11: 3 | C11: Saberser | D11: que aborden los retos y problemas de la educación en el país, con una perspectiva analítica, reflexiva, crítica y constructiva. | E11: BAK | F11: ActitudinalBAK | G11: CaracterizarBAK | H11: Evaluar | I11: Evalúa las condiciones y necesidades educativas del contexto local o regional para validar la pertinencia de estudios o propuestas formativas en educación STEM con una visión transformadora de los procesos de enseñanza y de aprendizaje.

Sheet Paso 4 Estrategias mesocurricu
A1: [A partir de la celda A3 despliegue el(los) resultado(s) de aprendizaje y elegir aquel (aquellos) al(a los) que se contribuye desde la estrategia.] | B1: [Escribir el nombre de la estrategia a desarrollar. Participación de los estudiantes en cursos, talleres, seminarios, conferencias, pruebas estandarizadas, investigaciones, actividades o experiencias, cuerpos académicos, redes, comunidades, la elaboración de textos y materiales, así como las publicaciones, entre otros.] | C1: [Describir la(s) estrategia(s) definidas por el programa.] | D1: [Escribir los indicadores de impacto de la estrategia. Se sugieren indicadores como: Valora el nivel de contribución de la estrategia a los resultados de aprendizaje; Número de estudiantes que participan en la estrategia; Número de veces que se realiza la estrategia, entre otros.] | E1: [Escribir las acciones de retroalimentación que usará el programa para comunicar a los estudiantes sobre el alcance de sus resultados de aprendizaje.] | F1: [Escribir, para cada indicador con qué instrumento se recogerá información para evidenciar el (los) impacto (s) declarados. Encuesta, lista de asistencia, informe, entre otros.]
A2: Resultado de aprendizaje | B2: Estrategia del programa | C2: Descripción | D2: Indicador de Impacto de la Estrategia | E2: Acciones de retroalimentación para los estudiantes | F2: Instrumentos de medición
A3: Evalúa las condiciones y necesidades educativas del contexto local o regional para validar la pertinencia de estudios o propuestas formativas en educación STEM con una visión transformadora de los procesos de enseñanza y de aprendizaje. | B3: Clases espejo | C3: Contacto con universidades a nivel nacional o internacional que tengan grupos de estudio, de investigación o planes de estudio cuyo objeto sea la Educación STEM. | D3: Valoración del nivel de contribución de la estrategia a los resultados de aprendizaje del programa, en una escala de 1 a 5. | E3: Informar y formar a los estudiantes sobre temas asociados a la Educación STEM a través de las clases y para quienes no puedan participar sincrónicamente se publicarán las grabaciones en la sección de anuncios de los módulos. | F3: Encuesta
A4: Diagnostica los factores y necesidades formativas del país, según las diferencias y potencialidades regionales que demandan los cambios culturales y educativos, para identificar problemáticas asociadas al desarrollo de vocaciones STEM, el cierre de brech | D4: Número de estudiantes y graduados que participan en la estrategia. | F4: Listado
A5: Diseña un estudio o una propuesta de investigación que aborde problemáticas asociadas al desarrollo de vocaciones STEM, el cierre de brechas e inclusión en STEM y la apropiación social de CTI, desde un enfoque integrador, incorporando una ruta pedagógica | D5: Número de veces que se realiza la estrategia en el tiempo que determine el programa. | F5: Informe o Reporte
A6: Determina las condiciones y estructuras de pensamiento que se requieren para impulsar el aprendizaje en la educación STEM, contrastando los factores que inciden en el desarrollo de competencias analíticas, sistémicas, computacionales, críticas y de alfabe | B6: Eventos con expertos | C6: Sesiones de encuentro sincrónico con expertos o líderes de proyectos de Educación STEM para el reconocimiento de experiencias llevadas a cabo a nivel nacional o internacional tanto en instituciones educativas como en instituciones cuyo propósito sea la apropiación y la divulgación de la ciencia y la tecnología..(internacionalización movilidad entrante); se relaciona con el sector externo. | D6: Valoración del nivel de contribución de la estrategia a los resultados de aprendizaje del programa, en una escala de 1 a 5. | E6: Informar y formar a los estudiantes sobre temas asociados a la Educación STEM a través de diálogos, foros, talleres o conferencias y para quienes no puedan participar sincrónicamente se publicarán las grabaciones en la sección de anuncios de los módulos. Ayudar a tomar decisiones respecto a los temas que se pueden abordar en los trabajos de investigación. | F6: Encuesta
A7: Elabora una ruta pedagógica y didáctica que articule los factores que inciden en el desarrollo de competencias analíticas, sistémicas, computacionales, críticas y de alfabetización digital con los principios teóricos y prácticos de la educación STEM para | D7: Número de estudiantes que participan en la estrategia. | F7: Listado
A8: Diagnostica los factores y necesidades formativas del país, según las diferencias y potencialidades regionales que demandan los cambios culturales y educativos, para identificar problemáticas asociadas al desarrollo de vocaciones STEM, el cierre de brech | D8: Número de veces que se realiza la estrategia en el tiempo que determine el programa. | F8: Informe o Reporte
A9: Diseña un estudio o una propuesta de investigación que aborde problemáticas asociadas al desarrollo de vocaciones STEM, el cierre de brechas e inclusión en STEM y la apropiación social de CTI, desde un enfoque integrador, incorporando una ruta pedagógica
A10: Determina las condiciones y estructuras de pensamiento que se requieren para impulsar el aprendizaje en la educación STEM, contrastando los factores que inciden en el desarrollo de competencias analíticas, sistémicas, computacionales, críticas y de alfabe | B10: Participación en el proyecto de proyección social Articulación TIC con Colegios | C10: Participar en el proyecto liderado por la Facultad de Ingeniería Diseño e Innovación a través del diseño de propuestas educativas para el fortalecimiento de las competencias TIC en estudiantes de educación inicial, básica y media de Colombia y como una estrategia de relación con el sector externo. | D10: Valoración del nivel de contribución de la estrategia a los resultados de aprendizaje del programa, en una escala de 1 a 5. | E10: Formar a los estudiantes sobre temas de proyectos educativo en STEM a través de un trabajo articulado con colegios y para quienes no puedan participar se socializarán los resultados parciales y finales de los proyectos. Prevenir y ayudar a tomar decisiones respecto a los temas que se pueden abordar en los trabajos de investigación y temas asociados a cómo investigar, cómo escribir, cómo divulgar y cómo validar propuestas educativas o de investigación. | F10: Encuesta
A11: Elabora una ruta pedagógica y didáctica que articule los factores que inciden en el desarrollo de competencias analíticas, sistémicas, computacionales, críticas y de alfabetización digital con los principios teóricos y prácticos de la educación STEM para | D11: Número de estudiantes que participan en la estrategia. | F11: Listado
A12: Evalúa las condiciones y necesidades educativas del contexto local o regional para validar la pertinencia de estudios o propuestas formativas en educación STEM con una visión transformadora de los procesos de enseñanza y de aprendizaje. | D12: Número de veces que se realiza la estrategia en el tiempo que determine el programa. | F12: Informe o Reporte
A13: Desarrolla un estudio o una propuesta educativa innovadora basada en la educación STEM desde un enfoque integrador, para abordar los retos y problemas de la educación en el país, con una perspectiva analítica, reflexiva, crítica y constructiva.

Sheet Paso 5 Estrategias micro
A1: [Estas celdas se diligencian automáticamente. No ajustar.] | B1: [A partir de la celda A3 despliegue el(los) resultado(s) de aprendizaje y elija aquel (aquellos) al(a los) que se contribuye desde la asignatura o módulo).] | C1: [Escribir el semestre en el que se cursa la asignatura o módulo.] | D1: [Escribir el nombre de la asignatura o módulo que contribuye al logro del resultado de aprendizaje.] | E1: [Redactar los indicadores iniciando con el verbo en presente indicativo, luego el objeto conceptual y finalmente el complemento de oración (que indique una condición o finalidad, con, para, de, entre otros conectores).] | F1: [Escribir la tipología: T (teórico), P (Práctico), TP (Teórico Práctico)] | G1: [Marcar con X el bloque o componente al que pertenece la asignatura o módulo. Por favor ajustar para posgrado, eliminar una columna y ubicar los títulos C.Fundamentación y C.Profundización.] | I1: [Escribir el número de créditos de la asignatura o módulo] | J1: [Escribir el número de horas de trabajo directo: 16*# o 12*#, para presencial o virtual, según sea el caso.] | K1: [Escribir el número de horas de trabajo independiente: 32*# columna J o 36*# columna J, para presencial o virtual, respectivamente.] | L1: [Escribir la suma de los números de horas de las dos celdas anteriores.] | M1: [Escribir el nombre de los cuatro núcleos temáticos que abordará la asignatura o el módulo.] | N1: [Escribir las lecturas, talleres, análisis, referentes, etc., que realiza el estudiante, clasificadas en trabajo directo e independiente.] | O1: [Escribir las actividades de evaluación que se emplean para identificar el alcance del (de los) indicador(es) de logro(s).] | P1: [Escribir las acciones de retroalimentación que se emplearán en la asignatura o módulo, para retroalimentar a los estudiantes respecto al alcance de los indicadores de logro. Recordar que son cuatro acciones: informar, formar, prevenir y ayudar a tomar decisiones e indique cómo.]
A2: Tipo de Saber | B2: Resultado de aprendizaje | C2: Semestre | D2: Nombre asignatura o módulo | E2: Indicadores de logro asignatura o módulo | F2: Tipología | G2: C.Fudamentación | H2: C.Profundización | I2: Créditos | J2: Número de horas trabajo directo | K2: Número de horas trabajo independiente | L2: Total de horas | M2: Núcleos temáticos | N2: Actividades de aprendizaje | O2: Actividades de evaluación | P2: Acciones de retroalimentación
A3: =_xlfn.XLOOKUP(B3,'Paso 3 Redacción RA '!I$3:I$11,'Paso 3 Redacción RA '!C$3:C$11,,0,1) -> Saber | B3: Diagnostica los factores y necesidades formativas del país, según las diferencias y potencialidades regionales que demandan los cambios culturales y educativos, para identificar problemáticas asociadas al desarrollo de vocaciones STEM, el cierre de brechas e inclusión en STEM y la apropiación social de CTI. | C3: 1 | D3: Equidad e Inclusión en la Educación STEM | E3: Reconoce la situación actual de participación y rendimiento en educación STEM de la población de un territorio local o regional, para identificar oportunidades de atención a través de propuestas educativas o estudios que articulen los factores que inciden en su mejoramiento. Examina programas y estrategias de intervención para la inclusión y cierre de brechas en STEM, para validar la pertinencia de su implementación teniendo en cuenta las condiciones y necesidades educativas del contexto local o regional. | F3: TP | H3: X | I3: 3 | J3: =12*I3 -> 36 | K3: =36*I3 -> 108 | L3: =SUM(J3:K5) -> 144 | M3: 1. Políticas para la inclusión y cierre de brechas en STEM 2. Estado actual de participación en STEM de grupos étnicos minoritarios 3. Caracterización de factores que influyen en la participación y rendimiento en STEM 4. Intervenciones estratégicas desde la educación STEM | N3: Trabajo directo: Encuentros sincrónicos, mensajeria interna, foros generales, anuncios. Trabajo independiente: Lecturas Fundamentales y complementarias Anuncios Foros Actividades de refuerzo y recursos del módulo | O3: Actividad de puntos evaluables (semana 2 – Cuestionario de 5 preguntas). Entrega previa 1 (semana 3 - Laboratorio, taller, ejercicios, resolución de casos o de problemas, desarrollo de procesos o ejecución de propuestas. Entrega de forma individual o grupal, según indicaciones del profesor). Parcial (semana 4 - Cuestionarios de entre 15 y 20 preguntas). Entrega previa 2 (semana 5 - Laboratorio, taller, ejercicios, resolución de casos o de problemas, desarrollo de procesos o ejecución de propuestas. Entrega de forma individual o grupal, según indicaciones dadas por el profesor). Entrega final (semana 7 - Laboratorio, taller, ejercicios, resolución de casos o de problemas, desarrollo de procesos o ejecución de propuestas. Entrega de forma individual o grupal, según indicaciones dadas por el profesor). Evaluación final (semana 8 - Cuestionario de entre 15 y 20 preguntas). | P3: Las acciones retroalimentación varían entre las siguientes, según las condiciones que identifique el tutor. Formar: donde se crean las condiciones para que los estudiantes adquieran conocimientos, habilidades, actitudes, aptitudes y destrezas. Además, debe promover su desarrollo integral y debe acompañarlos en las situaciones académicas que enfrenten durante el desarrollo de un módulo o una asignatura. Informar: para que los estudiantes identifiquen los cambios que pueden afectarlos directa o indirectamente tanto en el aula de clase como en otros espacios. Prevenir: con el fin de anticiparse a las situaciones académicas que pueden representar dificultad para los estudiantes. Esto se logra a través de la interacción individual con los estudiantes y del completo conocimiento del contexto educativo en que el tutor se desenvuelve. Ayudar a decidir: donde se orienta a los estudiantes para que tomen la mejor decisión ante una situación concreta. El objetivo es que el estudiante fortalezca su autonomía y la toma de decisiones responsable.
A4: =_xlfn.XLOOKUP(B4,'Paso 3 Redacción RA '!I$3:I$11,'Paso 3 Redacción RA '!C$3:C$11,,0,1) -> Saberhacer | B4: Diseña un estudio o una propuesta de investigación que aborde problemáticas asociadas al desarrollo de vocaciones STEM, el cierre de brechas e inclusión en STEM y la apropiación social de CTI, desde un enfoque integrador, incorporando una ruta pedagógica y didáctica para el desarrollo de competencias analíticas, sistémicas, computacionales, críticas y de alfabetización digital en la población estudiantil.
A5: =_xlfn.XLOOKUP(B5,'Paso 3 Redacción RA '!I$3:I$11,'Paso 3 Redacción RA '!C$3:C$11,,0,1) -> Saberser | B5: Evalúa las condiciones y necesidades educativas del contexto local o regional para validar la pertinencia de estudios o propuestas formativas en educación STEM con una visión transformadora de los procesos de enseñanza y de aprendizaje.
A6: =_xlfn.XLOOKUP(B6,'Paso 3 Redacción RA '!I$3:I$11,'Paso 3 Redacción RA '!C$3:C$11,,0,1) -> Saberhacer | B6: Elabora una ruta pedagógica y didáctica que articule los factores que inciden en el desarrollo de competencias analíticas, sistémicas, computacionales, críticas y de alfabetización digital con los principios teóricos y prácticos de la educación STEM para definir una propuesta formativa. | C6: 1 | D6: Territorios y Educación STEM | E6: Aplica estrategias y herramientas adecuadas que permiten evaluar las condiciones y necesidades educativas del territorio respecto al estado, equidad e inclusión en el desarrollo de competencias y vocaciones científicas y tecnológicas. Plantea una problemática asociada a las necesidades educativas de un contexto local o regional para ser abordada por medio del diseño de un estudio o propuesta formativa bajo el marco de la educación STEM. | F6: TP | H6: X | I6: 4 | J6: =12*I6 -> 48 | K6: =36*I6 -> 144 | L6: =SUM(J6:K10) -> 192 | M6: 1. Reconocimiento del contexto educativo en los territorios respecto a CTI 2. Análisis territorial de los elementos estratégicos que movilizan la educación STEM 3. Diagnóstico e interpretación de datos para al análisis de Educación STEM en el territorio 4. Delimitación del problema orientado a soluciones de contexto asociado a educación STEM y territorio | N6: Trabajo directo: Encuentros sincrónicos, mensajeria interna, foros generales, anuncios. Trabajo independiente: Lecturas Fundamentales y complementarias Anuncios Foros Actividades de refuerzo y recursos del módulo | O6: Actividad de puntos evaluables (semana 2 – Cuestionario de 5 preguntas). Entrega previa 1 (semana 3 - Laboratorio, taller, ejercicios, resolución de casos o de problemas, desarrollo de procesos o ejecución de propuestas. Entrega de forma individual o grupal, según indicaciones del profesor). Parcial (semana 4 - Cuestionarios de entre 15 y 20 preguntas). Entrega previa 2 (semana 5 - Laboratorio, taller, ejercicios, resolución de casos o de problemas, desarrollo de procesos o ejecución de propuestas. Entrega de forma individual o grupal, según indicaciones dadas por el profesor). Entrega final (semana 7 - Laboratorio, taller, ejercicios, resolución de casos o de problemas, desarrollo de procesos o ejecución de propuestas. Entrega de forma individual o grupal, según indicaciones dadas por el profesor). Evaluación final (semana 8 - Cuestionario de entre 15 y 20 preguntas). | P6: Formar: donde se crean las condiciones para que los estudiantes adquieran conocimientos, habilidades, actitudes, aptitudes y destrezas. Además, debe promover su desarrollo integral y debe acompañarlos en las situaciones académicas que enfrenten durante el desarrollo de un módulo o una asignatura. Informar: para que los estudiantes identifiquen los cambios que pueden afectarlos directa o indirectamente tanto en el aula de clase como en otros espacios. Prevenir: con el fin de anticiparse a las situaciones académicas que pueden representar dificultad para los estudiantes. Esto se logra a través de la interacción individual con los estudiantes y del completo conocimiento del contexto educativo en que el tutor se desenvuelve. Ayudar a decidir: donde se orienta a los estudiantes para que tomen la mejor decisión ante una situación concreta. El objetivo es que el estudiante fortalezca su autonomía y la toma de decisiones responsable.
A7: =_xlfn.XLOOKUP(B7,'Paso 3 Redacción RA '!I$3:I$11,'Paso 3 Redacción RA '!C$3:C$11,,0,1) -> Saber | B7: Diagnostica los factores y necesidades formativas del país, según las diferencias y potencialidades regionales que demandan los cambios culturales y educativos, para identificar problemáticas asociadas al desarrollo de vocaciones STEM, el cierre de brechas e inclusión en STEM y la apropiación social de CTI.
A8: =_xlfn.XLOOKUP(B8,'Paso 3 Redacción RA '!I$3:I$11,'Paso 3 Redacción RA '!C$3:C$11,,0,1) -> Saberhacer | B8: Diseña un estudio o una propuesta de investigación que aborde problemáticas asociadas al desarrollo de vocaciones STEM, el cierre de brechas e inclusión en STEM y la apropiación social de CTI, desde un enfoque integrador, incorporando una ruta pedagógica y didáctica para el desarrollo de competencias analíticas, sistémicas, computacionales, críticas y de alfabetización digital en la población estudiantil.
A9: =_xlfn.XLOOKUP(B9,'Paso 3 Redacción RA '!I$3:I$11,'Paso 3 Redacción RA '!C$3:C$11,,0,1) -> Saberhacer | B9: Desarrolla un estudio o una propuesta educativa innovadora basada en la educación STEM desde un enfoque integrador, para abordar los retos y problemas de la educación en el país, con una perspectiva analítica, reflexiva, crítica y constructiva.
A10: =_xlfn.XLOOKUP(B10,'Paso 3 Redacción RA '!I$3:I$11,'Paso 3 Redacción RA '!C$3:C$11,,0,1) -> Saberser | B10: Evalúa las condiciones y necesidades educativas del contexto local o regional para validar la pertinencia de estudios o propuestas formativas en educación STEM con una visión transformadora de los procesos de enseñanza y de aprendizaje.
A11: =_xlfn.XLOOKUP(B11,'Paso 3 Redacción RA '!I$3:I$11,'Paso 3 Redacción RA '!C$3:C$11,,0,1) -> Saber | B11: Determina las condiciones y estructuras de pensamiento que se requieren para impulsar el aprendizaje en la educación STEM, contrastando los factores que inciden en el desarrollo de competencias analíticas, sistémicas, computacionales, críticas y de alfabetización digital con los principios teóricos y prácticos de este marco educativo. | C11: 1 | D11: Competencias en STEM | E11: Reconoce las competencias que se promueven desde la educación STEM, para identificar su desarrollo en estrategias y experiencias educativas, de acuerdo con el nivel escolar y el contexto local o regional en el que se lleva a cabo su proceso formativo. | F11: TP | G11: X | I11: 2 | J11: =12*I11 -> 24 | K11: =36*I11 -> 72 | L11: =SUM(J11:K11) -> 96 | M11: 1. Condiciones y estructuras del pensamiento 2. Competencia analítica y crítica 3. Competencias sistémicas y de pensamiento computacional 4. Competencia de alfabetización digital | N11: Trabajo directo: Encuentros sincrónicos, mensajeria interna, foros generales, anuncios. Trabajo independiente: Lecturas Fundamentales y complementarias Anuncios Foros Actividades de refuerzo y recursos del módulo | O11: Actividad de puntos evaluables (semana 2 – Cuestionario de 5 preguntas). Entrega previa 1 (semana 3 - Laboratorio, taller, ejercicios, resolución de casos o de problemas, desarrollo de procesos o ejecución de propuestas. Entrega de forma individual o grupal, según indicaciones del profesor). Parcial (semana 4 - Cuestionarios de entre 15 y 20 preguntas). Entrega previa 2 (semana 5 - Laboratorio, taller, ejercicios, resolución de casos o de problemas, desarrollo de procesos o ejecución de propuestas. Entrega de forma individual o grupal, según indicaciones dadas por el profesor). Entrega final (semana 7 - Laboratorio, taller, ejercicios, resolución de casos o de problemas, desarrollo de procesos o ejecución de propuestas. Entrega de forma individual o grupal, según indicaciones dadas por el profesor). Evaluación final (semana 8 - Cuestionario de entre 15 y 20 preguntas). | P11: Las acciones retroalimentación varían entre las siguientes, según las condiciones que identifique el tutor. Formar: donde se crean las condiciones para que los estudiantes adquieran conocimientos, habilidades, actitudes, aptitudes y destrezas. Además, debe promover su desarrollo integral y debe acompañarlos en las situaciones académicas que enfrenten durante el desarrollo de un módulo o una asignatura. Informar: para que los estudiantes identifiquen los cambios que pueden afectarlos directa o indirectamente tanto en el aula de clase como en otros espacios. Prevenir: con el fin de anticiparse a las situaciones académicas que pueden representar dificultad para los estudiantes. Esto se logra a través de la interacción individual con los estudiantes y del completo conocimiento del contexto educativo en que el tutor se desenvuelve. Ayudar a decidir: donde se orienta a los estudiantes para que tomen la mejor decisión ante una situación concreta. El objetivo es que el estudiante fortalezca su autonomía y la toma de decisiones responsable.
A12: =_xlfn.XLOOKUP(B12,'Paso 3 Redacción RA '!I$3:I$11,'Paso 3 Redacción RA '!C$3:C$11,,0,1) -> Saberhacer | B12: Elabora una ruta pedagógica y didáctica que articule los factores que inciden en el desarrollo de competencias analíticas, sistémicas, computacionales, críticas y de alfabetización digital con los principios teóricos y prácticos de la educación STEM para definir una propuesta formativa.
A13: =_xlfn.XLOOKUP(B13,'Paso 3 Redacción RA '!I$3:I$11,'Paso 3 Redacción RA '!C$3:C$11,,0,1) -> Saberser | B13: Evalúa las condiciones y necesidades educativas del contexto local o regional para validar la pertinencia de estudios o propuestas formativas en educación STEM con una visión transformadora de los procesos de enseñanza y de aprendizaje.
A14: =_xlfn.XLOOKUP(B14,'Paso 3 Redacción RA '!I$3:I$11,'Paso 3 Redacción RA '!C$3:C$11,,0,1) -> Saber | B14: Diagnostica los factores y necesidades formativas del país, según las diferencias y potencialidades regionales que demandan los cambios culturales y educativos, para identificar problemáticas asociadas al desarrollo de vocaciones STEM, el cierre de brechas e inclusión en STEM y la apropiación social de CTI.
A15: =_xlfn.XLOOKUP(B15,'Paso 3 Redacción RA '!I$3:I$11,'Paso 3 Redacción RA '!C$3:C$11,,0,1) -> Saberhacer | B15: Diseña un estudio o una propuesta de investigación que aborde problemáticas asociadas al desarrollo de vocaciones STEM, el cierre de brechas e inclusión en STEM y la apropiación social de CTI, desde un enfoque integrador, incorporando una ruta pedagógica y didáctica para el desarrollo de competencias analíticas, sistémicas, computacionales, críticas y de alfabetización digital en la población estudiantil.
A16: =_xlfn.XLOOKUP(B16,'Paso 3 Redacción RA '!I$3:I$11,'Paso 3 Redacción RA '!C$3:C$11,,0,1) -> Saberhacer | B16: Desarrolla un estudio o una propuesta educativa innovadora basada en la educación STEM desde un enfoque integrador, para abordar los retos y problemas de la educación en el país, con una perspectiva analítica, reflexiva, crítica y constructiva.
A17: =_xlfn.XLOOKUP(B17,'Paso 3 Redacción RA '!I$3:I$11,'Paso 3 Redacción RA '!C$3:C$11,,0,1) -> Saber | B17: Determina las condiciones y estructuras de pensamiento que se requieren para impulsar el aprendizaje en la educación STEM, contrastando los factores que inciden en el desarrollo de competencias analíticas, sistémicas, computacionales, críticas y de alfabetización digital con los principios teóricos y prácticos de este marco educativo. | C17: 1 | D17: Fundamentos de la Educación STEM | E17: Contrasta los fundamentos de la educación STEM con las prácticas educativas del contexto local o regional para identificar oportunidades de transformación en los procesos formativos, a través de la integración de las áreas STEM y en correspondencia con los desafíos y condiciones del país. | F17: TP | G17: X | I17: 2 | J17: =I17*12 -> 24 | K17: =I17*32 -> 64 | L17: =SUM(J17:K17) -> 88 | M17: 1. Inicios y evolución del STEM y la educación STEM 2. Principios y alcance de la educación STEM 3. Relaciones entre las áreas STEM 4. Visión integradora de la educación STEM | N17: Trabajo directo: Encuentros sincrónicos, mensajeria interna, foros generales, anuncios. Trabajo independiente: Lecturas Fundamentales y complementarias Anuncios Foros Actividades de refuerzo y recursos del módulo | O17: Actividad de puntos evaluables (semana 2 – Cuestionario de 5 preguntas). Entrega previa 1 (semana 3 - Laboratorio, taller, ejercicios, resolución de casos o de problemas, desarrollo de procesos o ejecución de propuestas. Entrega de forma individual o grupal, según indicaciones del profesor). Parcial (semana 4 - Cuestionarios de entre 15 y 20 preguntas). Entrega previa 2 (semana 5 - Laboratorio, taller, ejercicios, resolución de casos o de problemas, desarrollo de procesos o ejecución de propuestas. Entrega de forma individual o grupal, según indicaciones dadas por el profesor). Entrega final (semana 7 - Laboratorio, taller, ejercicios, resolución de casos o de problemas, desarrollo de procesos o ejecución de propuestas. Entrega de forma individual o grupal, según indicaciones dadas por el profesor). Evaluación final (semana 8 - Cuestionario de entre 15 y 20 preguntas). | P17: Las acciones retroalimentación varían entre las siguientes, según las condiciones que identifique el tutor. Formar: donde se crean las condiciones para que los estudiantes adquieran conocimientos, habilidades, actitudes, aptitudes y destrezas. Además, debe promover su desarrollo integral y debe acompañarlos en las situaciones académicas que enfrenten durante el desarrollo de un módulo o una asignatura. Informar: para que los estudiantes identifiquen los cambios que pueden afectarlos directa o indirectamente tanto en el aula de clase como en otros espacios. Prevenir: con el fin de anticiparse a las situaciones académicas que pueden representar dificultad para los estudiantes. Esto se logra a través de la interacción individual con los estudiantes y del completo conocimiento del contexto educativo en que el tutor se desenvuelve. Ayudar a decidir: donde se orienta a los estudiantes para que tomen la mejor decisión ante una situación concreta. El objetivo es que el estudiante fortalezca su autonomía y la toma de decisiones responsable.
A18: =_xlfn.XLOOKUP(B18,'Paso 3 Redacción RA '!I$3:I$11,'Paso 3 Redacción RA '!C$3:C$11,,0,1) -> Saberhacer | B18: Elabora una ruta pedagógica y didáctica que articule los factores que inciden en el desarrollo de competencias analíticas, sistémicas, computacionales, críticas y de alfabetización digital con los principios teóricos y prácticos de la educación STEM para definir una propuesta formativa.
A19: =_xlfn.XLOOKUP(B19,'Paso 3 Redacción RA '!I$3:I$11,'Paso 3 Redacción RA '!C$3:C$11,,0,1) -> Saberhacer | B19: Desarrolla un estudio o una propuesta educativa innovadora basada en la educación STEM desde un enfoque integrador, para abordar los retos y problemas de la educación en el país, con una perspectiva analítica, reflexiva, crítica y constructiva.
A20: =_xlfn.XLOOKUP(B20,'Paso 3 Redacción RA '!I$3:I$11,'Paso 3 Redacción RA '!C$3:C$11,,0,1) -> Saberser | B20: Evalúa las condiciones y necesidades educativas del contexto local o regional para validar la pertinencia de estudios o propuestas formativas en educación STEM con una visión transformadora de los procesos de enseñanza y de aprendizaje.
A21: =_xlfn.XLOOKUP(B21,'Paso 3 Redacción RA '!I$3:I$11,'Paso 3 Redacción RA '!C$3:C$11,,0,1) -> Saberhacer | B21: Elabora una ruta pedagógica y didáctica que articule los factores que inciden en el desarrollo de competencias analíticas, sistémicas, computacionales, críticas y de alfabetización digital con los principios teóricos y prácticos de la educación STEM para definir una propuesta formativa. | C21: 1 | D21: Diseño Curricular y de Propuestas Educativas | E21: Analiza las representaciones de los enfoques implícitos del currículo teniendo en cuenta las dimensiones transversales de la educación bajo un enfoque STEM. Estructura una propuesta curricular o educativa para la transformación de los procesos formativos, que integre los fundamentos de la educación STEM para el desarrollo de competencias en estas áreas y que esté en correspondencia con los desafíos y condiciones del país. | F21: TP | G21: X | I21: 3 | J21: =12*I21 -> 36 | K21: =36*I21 -> 108 | L21: =SUM(J21:K23) -> 144 | M21: 1. El currículo 2. El diseño curricular 3. Las propuestas educativas 4. El diseño de propuestas educativas | N21: Trabajo directo: Encuentros sincrónicos, mensajeria interna, foros generales, anuncios. Trabajo independiente: Lecturas Fundamentales y complementarias Anuncios Foros Actividades de refuerzo y recursos del módulo | O21: Actividad de puntos evaluables (semana 2 – Cuestionario de 5 preguntas). Entrega previa 1 (semana 3 - Laboratorio, taller, ejercicios, resolución de casos o de problemas, desarrollo de procesos o ejecución de propuestas. Entrega de forma individual o grupal, según indicaciones del profesor). Parcial (semana 4 - Cuestionarios de entre 15 y 20 preguntas). Entrega previa 2 (semana 5 - Laboratorio, taller, ejercicios, resolución de casos o de problemas, desarrollo de procesos o ejecución de propuestas. Entrega de forma individual o grupal, según indicaciones dadas por el profesor). Entrega final (semana 7 - Laboratorio, taller, ejercicios, resolución de casos o de problemas, desarrollo de procesos o ejecución de propuestas. Entrega de forma individual o grupal, según indicaciones dadas por el profesor). Evaluación final (semana 8 - Cuestionario de entre 15 y 20 preguntas). | P21: Las acciones retroalimentación varían entre las siguientes, según las condiciones que identifique el tutor. Formar: donde se crean las condiciones para que los estudiantes adquieran conocimientos, habilidades, actitudes, aptitudes y destrezas. Además, debe promover su desarrollo integral y debe acompañarlos en las situaciones académicas que enfrenten durante el desarrollo de un módulo o una asignatura. Informar: para que los estudiantes identifiquen los cambios que pueden afectarlos directa o indirectamente tanto en el aula de clase como en otros espacios. Prevenir: con el fin de anticiparse a las situaciones académicas que pueden representar dificultad para los estudiantes. Esto se logra a través de la interacción individual con los estudiantes y del completo conocimiento del contexto educativo en que el tutor se desenvuelve. Ayudar a decidir: donde se orienta a los estudiantes para que tomen la mejor decisión ante una situación concreta. El objetivo es que el estudiante fortalezca su autonomía y la toma de decisiones responsable.
A22: =_xlfn.XLOOKUP(B22,'Paso 3 Redacción RA '!I$3:I$11,'Paso 3 Redacción RA '!C$3:C$11,,0,1) -> Saberhacer | B22: Diseña un estudio o una propuesta de investigación que aborde problemáticas asociadas al desarrollo de vocaciones STEM, el cierre de brechas e inclusión en STEM y la apropiación social de CTI, desde un enfoque integrador, incorporando una ruta pedagógica y didáctica para el desarrollo de competencias analíticas, sistémicas, computacionales, críticas y de alfabetización digital en la población estudiantil.
A23: =_xlfn.XLOOKUP(B23,'Paso 3 Redacción RA '!I$3:I$11,'Paso 3 Redacción RA '!C$3:C$11,,0,1) -> Saberhacer | B23: Desarrolla un estudio o una propuesta educativa innovadora basada en la educación STEM desde un enfoque integrador, para abordar los retos y problemas de la educación en el país, con una perspectiva analítica, reflexiva, crítica y constructiva. | Q23: =SUM(I3:I23) -> 14
A24: =_xlfn.XLOOKUP(B24,'Paso 3 Redacción RA '!I$3:I$11,'Paso 3 Redacción RA '!C$3:C$11,,0,1) -> Saberhacer | B24: Elabora una ruta pedagógica y didáctica que articule los factores que inciden en el desarrollo de competencias analíticas, sistémicas, computacionales, críticas y de alfabetización digital con los principios teóricos y prácticos de la educación STEM para definir una propuesta formativa. | C24: 2 | D24: Modelos y Metodologías Activas en Educación STEM | E24: Estructura una propuesta de transformación de una práctica educativa profesional, que atienda al fomento de competencias, a la inclusión o cierre de brechas, reconociendo modelos y metodologías para el aprendizaje activo y el desarrollo de procesos educativos en STEM, desde un enfoque integrador. | F24: TP | H24: X | I24: 3 | J24: =12*I24 -> 36 | K24: =36*I24 -> 108 | L24: =SUM(J24:K26) -> 144 | M24: 1. Modelos teóricos sobre educación STEM 2. Metodologías para el aprendizaje activo y social 3. Metodologías en educación STEM 4. Experiencias de educación STEM | N24: Trabajo directo: Encuentros sincrónicos, mensajeria interna, foros generales, anuncios. Trabajo independiente: Lecturas Fundamentales y complementarias Anuncios Foros Actividades de refuerzo y recursos del módulo | O24: Actividad de puntos evaluables (semana 2 – Cuestionario de 5 preguntas). Entrega previa 1 (semana 3 - Laboratorio, taller, ejercicios, resolución de casos o de problemas, desarrollo de procesos o ejecución de propuestas. Entrega de forma individual o grupal, según indicaciones del profesor). Parcial (semana 4 - Cuestionarios de entre 15 y 20 preguntas). Entrega previa 2 (semana 5 - Laboratorio, taller, ejercicios, resolución de casos o de problemas, desarrollo de procesos o ejecución de propuestas. Entrega de forma individual o grupal, según indicaciones dadas por el profesor). Entrega final (semana 7 - Laboratorio, taller, ejercicios, resolución de casos o de problemas, desarrollo de procesos o ejecución de propuestas. Entrega de forma individual o grupal, según indicaciones dadas por el profesor). Evaluación final (semana 8 - Cuestionario de entre 15 y 20 preguntas). | P24: Las acciones retroalimentación varían entre las siguientes, según las condiciones que identifique el tutor. Formar: donde se crean las condiciones para que los estudiantes adquieran conocimientos, habilidades, actitudes, aptitudes y destrezas. Además, debe promover su desarrollo integral y debe acompañarlos en las situaciones académicas que enfrenten durante el desarrollo de un módulo o una asignatura. Informar: para que los estudiantes identifiquen los cambios que pueden afectarlos directa o indirectamente tanto en el aula de clase como en otros espacios. Prevenir: con el fin de anticiparse a las situaciones académicas que pueden representar dificultad para los estudiantes. Esto se logra a través de la interacción individual con los estudiantes y del completo conocimiento del contexto educativo en que el tutor se desenvuelve. Ayudar a decidir: donde se orienta a los estudiantes para que tomen la mejor decisión ante una situación concreta. El objetivo es que el estudiante fortalezca su autonomía y la toma de decisiones responsable.
A25: =_xlfn.XLOOKUP(B25,'Paso 3 Redacción RA '!I$3:I$11,'Paso 3 Redacción RA '!C$3:C$11,,0,1) -> Saberhacer | B25: Diseña un estudio o una propuesta de investigación que aborde problemáticas asociadas al desarrollo de vocaciones STEM, el cierre de brechas e inclusión en STEM y la apropiación social de CTI, desde un enfoque integrador, incorporando una ruta pedagógica y didáctica para el desarrollo de competencias analíticas, sistémicas, computacionales, críticas y de alfabetización digital en la población estudiantil.
A26: =_xlfn.XLOOKUP(B26,'Paso 3 Redacción RA '!I$3:I$11,'Paso 3 Redacción RA '!C$3:C$11,,0,1) -> Saberhacer | B26: Desarrolla un estudio o una propuesta educativa innovadora basada en la educación STEM desde un enfoque integrador, para abordar los retos y problemas de la educación en el país, con una perspectiva analítica, reflexiva, crítica y constructiva.
A27: =_xlfn.XLOOKUP(B27,'Paso 3 Redacción RA '!I$3:I$11,'Paso 3 Redacción RA '!C$3:C$11,,0,1) -> Saberhacer | B27: Elabora una ruta pedagógica y didáctica que articule los factores que inciden en el desarrollo de competencias analíticas, sistémicas, computacionales, críticas y de alfabetización digital con los principios teóricos y prácticos de la educación STEM para definir una propuesta formativa. | C27: 2 | D27: La Pedagogía y el Enfoque Integrador | E27: Analiza el tipo de conexión, el énfasis disciplinario y los niveles de integración de las áreas STEM para establecer el alcance y la naturaleza de una propuesta educativa enmarcada en el desarrollo de competencias, de inclusión o de cierre de brechas en educación STEM. | F27: TP | G27: X | I27: 3 | J27: =I27*12 -> 36 | K27: =I27*36 -> 108 | L27: =SUM(J27:K30) -> 144 | M27: 1. Pedagogía 2. Pedagogía integradora 3. Niveles de integración disciplinar 4. Integración de las áreas STEM en la educación | N27: Trabajo directo: Encuentros sincrónicos, mensajeria interna, foros generales, anuncios. Trabajo independiente: Lecturas Fundamentales y complementarias Anuncios Foros Actividades de refuerzo y recursos del módulo | O27: Actividad de puntos evaluables (semana 2 – Cuestionario de 5 preguntas). Entrega previa 1 (semana 3 - Laboratorio, taller, ejercicios, resolución de casos o de problemas, desarrollo de procesos o ejecución de propuestas. Entrega de forma individual o grupal, según indicaciones del profesor). Parcial (semana 4 - Cuestionarios de entre 15 y 20 preguntas). Entrega previa 2 (semana 5 - Laboratorio, taller, ejercicios, resolución de casos o de problemas, desarrollo de procesos o ejecución de propuestas. Entrega de forma individual o grupal, según indicaciones dadas por el profesor). Entrega final (semana 7 - Laboratorio, taller, ejercicios, resolución de casos o de problemas, desarrollo de procesos o ejecución de propuestas. Entrega de forma individual o grupal, según indicaciones dadas por el profesor). Evaluación final (semana 8 - Cuestionario de entre 15 y 20 preguntas). | P27: Las acciones retroalimentación varían entre las siguientes, según las condiciones que identifique el tutor. Formar: donde se crean las condiciones para que los estudiantes adquieran conocimientos, habilidades, actitudes, aptitudes y destrezas. Además, debe promover su desarrollo integral y debe acompañarlos en las situaciones académicas que enfrenten durante el desarrollo de un módulo o una asignatura. Informar: para que los estudiantes identifiquen los cambios que pueden afectarlos directa o indirectamente tanto en el aula de clase como en otros espacios. Prevenir: con el fin de anticiparse a las situaciones académicas que pueden representar dificultad para los estudiantes. Esto se logra a través de la interacción individual con los estudiantes y del completo conocimiento del contexto educativo en que el tutor se desenvuelve. Ayudar a decidir: donde se orienta a los estudiantes para que tomen la mejor decisión ante una situación concreta. El objetivo es que el estudiante fortalezca su autonomía y la toma de decisiones responsable.
A28: =_xlfn.XLOOKUP(B28,'Paso 3 Redacción RA '!I$3:I$11,'Paso 3 Redacción RA '!C$3:C$11,,0,1) -> Saberhacer | B28: Diseña un estudio o una propuesta de investigación que aborde problemáticas asociadas al desarrollo de vocaciones STEM, el cierre de brechas e inclusión en STEM y la apropiación social de CTI, desde un enfoque integrador, incorporando una ruta pedagógica y didáctica para el desarrollo de competencias analíticas, sistémicas, computacionales, críticas y de alfabetización digital en la población estudiantil.
A29: =_xlfn.XLOOKUP(B29,'Paso 3 Redacción RA '!I$3:I$11,'Paso 3 Redacción RA '!C$3:C$11,,0,1) -> Saberhacer | B29: Desarrolla un estudio o una propuesta educativa innovadora basada en la educación STEM desde un enfoque integrador, para abordar los retos y problemas de la educación en el país, con una perspectiva analítica, reflexiva, crítica y constructiva.
A30: =_xlfn.XLOOKUP(B30,'Paso 3 Redacción RA '!I$3:I$11,'Paso 3 Redacción RA '!C$3:C$11,,0,1) -> Saberser | B30: Evalúa las condiciones y necesidades educativas del contexto local o regional para validar la pertinencia de estudios o propuestas formativas en educación STEM con una visión transformadora de los procesos de enseñanza y de aprendizaje.
A31: =_xlfn.XLOOKUP(B31,'Paso 3 Redacción RA '!I$3:I$11,'Paso 3 Redacción RA '!C$3:C$11,,0,1) -> Saberhacer | B31: Diseña un estudio o una propuesta de investigación que aborde problemáticas asociadas al desarrollo de vocaciones STEM, el cierre de brechas e inclusión en STEM y la apropiación social de CTI, desde un enfoque integrador, incorporando una ruta pedagógica y didáctica para el desarrollo de competencias analíticas, sistémicas, computacionales, críticas y de alfabetización digital en la población estudiantil. | C31: 2 | D31: Investigación | E31: Reconoce las características metodológicas del diseño y desarrollo de proyectos de investigación-innovación o de estudios de caso en el área de la educación, para generar una propuesta que exponga cómo abordar una problemática o un tema en educación STEM. | F31: TP | G31: X | I31: 2 | J31: =I31*12 -> 24 | K31: =I31*36 -> 72 | L31: =SUM(J31:K31) -> 96 | M31: 1. Investigación en educación. 2. Análisis sistemático de literatura 3. Proyectos de estudio de caso. 4. Proyectos de investigación-innovación. | N31: Trabajo directo: Encuentros sincrónicos, mensajeria interna, foros generales, anuncios. Trabajo independiente: Lecturas Fundamentales y complementarias Anuncios Foros Actividades de refuerzo y recursos del módulo | O31: Actividad de puntos evaluables (semana 2 – Cuestionario de 5 preguntas). Entrega previa 1 (semana 3 - Laboratorio, taller, ejercicios, resolución de casos o de problemas, desarrollo de procesos o ejecución de propuestas. Entrega de forma individual o grupal, según indicaciones del profesor). Parcial (semana 4 - Cuestionarios de entre 15 y 20 preguntas). Entrega previa 2 (semana 5 - Laboratorio, taller, ejercicios, resolución de casos o de problemas, desarrollo de procesos o ejecución de propuestas. Entrega de forma individual o grupal, según indicaciones dadas por el profesor). Entrega final (semana 7 - Laboratorio, taller, ejercicios, resolución de casos o de problemas, desarrollo de procesos o ejecución de propuestas. Entrega de forma individual o grupal, según indicaciones dadas por el profesor). Evaluación final (semana 8 - Cuestionario de entre 15 y 20 preguntas). | P31: Las acciones retroalimentación varían entre las siguientes, según las condiciones que identifique el tutor. Formar: donde se crean las condiciones para que los estudiantes adquieran conocimientos, habilidades, actitudes, aptitudes y destrezas. Además, debe promover su desarrollo integral y debe acompañarlos en las situaciones académicas que enfrenten durante el desarrollo de un módulo o una asignatura. Informar: para que los estudiantes identifiquen los cambios que pueden afectarlos directa o indirectamente tanto en el aula de clase como en otros espacios. Prevenir: con el fin de anticiparse a las situaciones académicas que pueden representar dificultad para los estudiantes. Esto se logra a través de la interacción individual con los estudiantes y del completo conocimiento del contexto educativo en que el tutor se desenvuelve. Ayudar a decidir: donde se orienta a los estudiantes para que tomen la mejor decisión ante una situación concreta. El objetivo es que el estudiante fortalezca su autonomía y la toma de decisiones responsable.
A32: =_xlfn.XLOOKUP(B32,'Paso 3 Redacción RA '!I$3:I$11,'Paso 3 Redacción RA '!C$3:C$11,,0,1) -> Saber | B32: Determina las condiciones y estructuras de pensamiento que se requieren para impulsar el aprendizaje en la educación STEM, contrastando los factores que inciden en el desarrollo de competencias analíticas, sistémicas, computacionales, críticas y de alfabetización digital con los principios teóricos y prácticos de este marco educativo. | C32: 2 | D32: Vocaciones STEM | E32: Reconoce la situación de desarrollo de vocaciones STEM para elaborar un diagnóstico que describa las condiciones y necesidades de un contexto educativo en una población, susceptible de intervenir, en un territorio local o regional. | F32: TP | H32: X | I32: 3 | J32: =I32*12 -> 36 | K32: =I32*36 -> 108 | L32: =SUM(J32:K32) -> 144 | M32: 1. Diagnóstico del estado actual vocaciones STEM 2. Caracterización de factores que influyen en el desarrollo de vocaciones STEM 3. Políticas para el desarrollo de vocaciones STEM 4. Intervenciones estratégicas desde la educación STEM | N32: Trabajo directo: Encuentros sincrónicos, mensajeria interna, foros generales, anuncios. Trabajo independiente: Lecturas Fundamentales y complementarias Anuncios Foros Actividades de refuerzo y recursos del módulo | O32: Actividad de puntos evaluables (semana 2 – Cuestionario de 5 preguntas). Entrega previa 1 (semana 3 - Laboratorio, taller, ejercicios, resolución de casos o de problemas, desarrollo de procesos o ejecución de propuestas. Entrega de forma individual o grupal, según indicaciones del profesor). Parcial (semana 4 - Cuestionarios de entre 15 y 20 preguntas). Entrega previa 2 (semana 5 - Laboratorio, taller, ejercicios, resolución de casos o de problemas, desarrollo de procesos o ejecución de propuestas. Entrega de forma individual o grupal, según indicaciones dadas por el profesor). Entrega final (semana 7 - Laboratorio, taller, ejercicios, resolución de casos o de problemas, desarrollo de procesos o ejecución de propuestas. Entrega de forma individual o grupal, según indicaciones dadas por el profesor). Evaluación final (semana 8 - Cuestionario de entre 15 y 20 preguntas). | P32: Las acciones retroalimentación varían entre las siguientes, según las condiciones que identifique el tutor. Formar: donde se crean las condiciones para que los estudiantes adquieran conocimientos, habilidades, actitudes, aptitudes y destrezas. Además, debe promover su desarrollo integral y debe acompañarlos en las situaciones académicas que enfrenten durante el desarrollo de un módulo o una asignatura. Informar: para que los estudiantes identifiquen los cambios que pueden afectarlos directa o indirectamente tanto en el aula de clase como en otros espacios. Prevenir: con el fin de anticiparse a las situaciones académicas que pueden representar dificultad para los estudiantes. Esto se logra a través de la interacción individual con los estudiantes y del completo conocimiento del contexto educativo en que el tutor se desenvuelve. Ayudar a decidir: donde se orienta a los estudiantes para que tomen la mejor decisión ante una situación concreta. El objetivo es que el estudiante fortalezca su autonomía y la toma de decisiones responsable.
A33: =_xlfn.XLOOKUP(B33,'Paso 3 Redacción RA '!I$3:I$11,'Paso 3 Redacción RA '!C$3:C$11,,0,1) -> Saberhacer | B33: Elabora una ruta pedagógica y didáctica que articule los factores que inciden en el desarrollo de competencias analíticas, sistémicas, computacionales, críticas y de alfabetización digital con los principios teóricos y prácticos de la educación STEM para definir una propuesta formativa.
A34: =_xlfn.XLOOKUP(B34,'Paso 3 Redacción RA '!I$3:I$11,'Paso 3 Redacción RA '!C$3:C$11,,0,1) -> Saber | B34: Diagnostica los factores y necesidades formativas del país, según las diferencias y potencialidades regionales que demandan los cambios culturales y educativos, para identificar problemáticas asociadas al desarrollo de vocaciones STEM, el cierre de brechas e inclusión en STEM y la apropiación social de CTI.
A35: =_xlfn.XLOOKUP(B35,'Paso 3 Redacción RA '!I$3:I$11,'Paso 3 Redacción RA '!C$3:C$11,,0,1) -> Saberhacer | B35: Diseña un estudio o una propuesta de investigación que aborde problemáticas asociadas al desarrollo de vocaciones STEM, el cierre de brechas e inclusión en STEM y la apropiación social de CTI, desde un enfoque integrador, incorporando una ruta pedagógica y didáctica para el desarrollo de competencias analíticas, sistémicas, computacionales, críticas y de alfabetización digital en la población estudiantil.
A36: =_xlfn.XLOOKUP(B36,'Paso 3 Redacción RA '!I$3:I$11,'Paso 3 Redacción RA '!C$3:C$11,,0,1) -> Saberser | B36: Evalúa las condiciones y necesidades educativas del contexto local o regional para validar la pertinencia de estudios o propuestas formativas en educación STEM con una visión transformadora de los procesos de enseñanza y de aprendizaje.
A37: =_xlfn.XLOOKUP(B37,'Paso 3 Redacción RA '!I$3:I$11,'Paso 3 Redacción RA '!C$3:C$11,,0,1) -> Saber | B37: Determina las condiciones y estructuras de pensamiento que se requieren para impulsar el aprendizaje en la educación STEM, contrastando los factores que inciden en el desarrollo de competencias analíticas, sistémicas, computacionales, críticas y de alfabetización digital con los principios teóricos y prácticos de este marco educativo. | C37: 2 | D37: Tecnologías Emergentes | E37: Reconoce las competencias digitales y tecnologías que favorecen los procesos de formación en educación STEM, identificando el estado y las oportunidades de desarrollo social o de cierre de brechas de una población en un territorio local o regional, mediante el análisis de tecnologías en tendencia o de vanguardia. | F37: TP | G37: X | I37: 3 | J37: =I37*12 -> 36 | K37: =I37*36 -> 108 | L37: =SUM(J37:K37) -> 144 | M37: 1. Desarrollo de habilidades tecnológicas para la ciudadanía 2. Formación tecnológica para la vida 3. Pensamiento computacional para pensar y actuar en el mundo 4. Tecnologías disruptivas y su impacto en la educación y la sociedad | N37: Trabajo directo: Encuentros sincrónicos, mensajeria interna, foros generales, anuncios. Trabajo independiente: Lecturas Fundamentales y complementarias Anuncios Foros Actividades de refuerzo y recursos del módulo | O37: Actividad de puntos evaluables (semana 2 – Cuestionario de 5 preguntas). Entrega previa 1 (semana 3 - Laboratorio, taller, ejercicios, resolución de casos o de problemas, desarrollo de procesos o ejecución de propuestas. Entrega de forma individual o grupal, según indicaciones del profesor). Parcial (semana 4 - Cuestionarios de entre 15 y 20 preguntas). Entrega previa 2 (semana 5 - Laboratorio, taller, ejercicios, resolución de casos o de problemas, desarrollo de procesos o ejecución de propuestas. Entrega de forma individual o grupal, según indicaciones dadas por el profesor). Entrega final (semana 7 - Laboratorio, taller, ejercicios, resolución de casos o de problemas, desarrollo de procesos o ejecución de propuestas. Entrega de forma individual o grupal, según indicaciones dadas por el profesor). Evaluación final (semana 8 - Cuestionario de entre 15 y 20 preguntas). | P37: Las acciones retroalimentación varían entre las siguientes, según las condiciones que identifique el tutor. Formar: donde se crean las condiciones para que los estudiantes adquieran conocimientos, habilidades, actitudes, aptitudes y destrezas. Además, debe promover su desarrollo integral y debe acompañarlos en las situaciones académicas que enfrenten durante el desarrollo de un módulo o una asignatura. Informar: para que los estudiantes identifiquen los cambios que pueden afectarlos directa o indirectamente tanto en el aula de clase como en otros espacios. Prevenir: con el fin de anticiparse a las situaciones académicas que pueden representar dificultad para los estudiantes. Esto se logra a través de la interacción individual con los estudiantes y del completo conocimiento del contexto educativo en que el tutor se desenvuelve. Ayudar a decidir: donde se orienta a los estudiantes para que tomen la mejor decisión ante una situación concreta. El objetivo es que el estudiante fortalezca su autonomía y la toma de decisiones responsable.
A38: =_xlfn.XLOOKUP(B38,'Paso 3 Redacción RA '!I$3:I$11,'Paso 3 Redacción RA '!C$3:C$11,,0,1) -> Saberhacer | B38: Elabora una ruta pedagógica y didáctica que articule los factores que inciden en el desarrollo de competencias analíticas, sistémicas, computacionales, críticas y de alfabetización digital con los principios teóricos y prácticos de la educación STEM para definir una propuesta formativa.
A39: =_xlfn.XLOOKUP(B39,'Paso 3 Redacción RA '!I$3:I$11,'Paso 3 Redacción RA '!C$3:C$11,,0,1) -> Saberhacer | B39: Diseña un estudio o una propuesta de investigación que aborde problemáticas asociadas al desarrollo de vocaciones STEM, el cierre de brechas e inclusión en STEM y la apropiación social de CTI, desde un enfoque integrador, incorporando una ruta pedagógica y didáctica para el desarrollo de competencias analíticas, sistémicas, computacionales, críticas y de alfabetización digital en la población estudiantil.
A40: =_xlfn.XLOOKUP(B40,'Paso 3 Redacción RA '!I$3:I$11,'Paso 3 Redacción RA '!C$3:C$11,,0,1) -> Saberhacer | B40: Desarrolla un estudio o una propuesta educativa innovadora basada en la educación STEM desde un enfoque integrador, para abordar los retos y problemas de la educación en el país, con una perspectiva analítica, reflexiva, crítica y constructiva.
A41: =_xlfn.XLOOKUP(B41,'Paso 3 Redacción RA '!I$3:I$11,'Paso 3 Redacción RA '!C$3:C$11,,0,1) -> Saber | B41: Diagnostica los factores y necesidades formativas del país, según las diferencias y potencialidades regionales que demandan los cambios culturales y educativos, para identificar problemáticas asociadas al desarrollo de vocaciones STEM, el cierre de brechas e inclusión en STEM y la apropiación social de CTI.
A42: =_xlfn.XLOOKUP(B42,'Paso 3 Redacción RA '!I$3:I$11,'Paso 3 Redacción RA '!C$3:C$11,,0,1) -> Saberser | B42: Evalúa las condiciones y necesidades educativas del contexto local o regional para validar la pertinencia de estudios o propuestas formativas en educación STEM con una visión transformadora de los procesos de enseñanza y de aprendizaje. | C42: II | Q42: =SUM(I24:I42) -> 14
A43: =_xlfn.XLOOKUP(B43,'Paso 3 Redacción RA '!I$3:I$11,'Paso 3 Redacción RA '!C$3:C$11,,0,1) -> Saberhacer | B43: Diseña un estudio o una propuesta de investigación que aborde problemáticas asociadas al desarrollo de vocaciones STEM, el cierre de brechas e inclusión en STEM y la apropiación social de CTI, desde un enfoque integrador, incorporando una ruta pedagógica y didáctica para el desarrollo de competencias analíticas, sistémicas, computacionales, críticas y de alfabetización digital en la población estudiantil. | C43: 3 | D43: Formulación y Gestión de Propuestas y Proyectos STEM | E43: Planea una propuesta de proyecto educativo STEM considerando sus etapas y tipos de recursos, que permitan atender necesidades de carácter educativo y social de un contexto local o regional respecto al desarrollo de vocaciones STEM, inclusión y cierre de brechas o de apropiación social del conocimiento científico tecnológico. | F43: TP | H43: X | I43: 3 | J43: =12*I43 -> 36 | K43: =36*I43 -> 108 | L43: =SUM(J43:K45) -> 144 | M43: 1. Fundamentos de propuestas y proyectos educativos STEM 2. Formulación de propuestas y proyectos en educación STEM 3. Gestión de propuestas y proyectos en educación STEM 4. Evaluación y seguimiento de propuestas y proyectos en educación STEM | N43: Trabajo directo: Encuentros sincrónicos, mensajeria interna, foros generales, anuncios. Trabajo independiente: Lecturas Fundamentales y complementarias Anuncios Foros Actividades de refuerzo y recursos del módulo | O43: Actividad de puntos evaluables (semana 2 – Cuestionario de 5 preguntas). Entrega previa 1 (semana 3 - Laboratorio, taller, ejercicios, resolución de casos o de problemas, desarrollo de procesos o ejecución de propuestas. Entrega de forma individual o grupal, según indicaciones del profesor). Parcial (semana 4 - Cuestionarios de entre 15 y 20 preguntas). Entrega previa 2 (semana 5 - Laboratorio, taller, ejercicios, resolución de casos o de problemas, desarrollo de procesos o ejecución de propuestas. Entrega de forma individual o grupal, según indicaciones dadas por el profesor). Entrega final (semana 7 - Laboratorio, taller, ejercicios, resolución de casos o de problemas, desarrollo de procesos o ejecución de propuestas. Entrega de forma individual o grupal, según indicaciones dadas por el profesor). Evaluación final (semana 8 - Cuestionario de entre 15 y 20 preguntas). | P43: Las acciones retroalimentación varían entre las siguientes, según las condiciones que identifique el tutor. Formar: donde se crean las condiciones para que los estudiantes adquieran conocimientos, habilidades, actitudes, aptitudes y destrezas. Además, debe promover su desarrollo integral y debe acompañarlos en las situaciones académicas que enfrenten durante el desarrollo de un módulo o una asignatura. Informar: para que los estudiantes identifiquen los cambios que pueden afectarlos directa o indirectamente tanto en el aula de clase como en otros espacios. Prevenir: con el fin de anticiparse a las situaciones académicas que pueden representar dificultad para los estudiantes. Esto se logra a través de la interacción individual con los estudiantes y del completo conocimiento del contexto educativo en que el tutor se desenvuelve. Ayudar a decidir: donde se orienta a los estudiantes para que tomen la mejor decisión ante una situación concreta. El objetivo es que el estudiante fortalezca su autonomía y la toma de decisiones responsable.
A44: =_xlfn.XLOOKUP(B44,'Paso 3 Redacción RA '!I$3:I$11,'Paso 3 Redacción RA '!C$3:C$11,,0,1) -> Saberhacer | B44: Desarrolla un estudio o una propuesta educativa innovadora basada en la educación STEM desde un enfoque integrador, para abordar los retos y problemas de la educación en el país, con una perspectiva analítica, reflexiva, crítica y constructiva.
A45: =_xlfn.XLOOKUP(B45,'Paso 3 Redacción RA '!I$3:I$11,'Paso 3 Redacción RA '!C$3:C$11,,0,1) -> Saberser | B45: Evalúa las condiciones y necesidades educativas del contexto local o regional para validar la pertinencia de estudios o propuestas formativas en educación STEM con una visión transformadora de los procesos de enseñanza y de aprendizaje.
A46: =_xlfn.XLOOKUP(B46,'Paso 3 Redacción RA '!I$3:I$11,'Paso 3 Redacción RA '!C$3:C$11,,0,1) -> Saberhacer | B46: Elabora una ruta pedagógica y didáctica que articule los factores que inciden en el desarrollo de competencias analíticas, sistémicas, computacionales, críticas y de alfabetización digital con los principios teóricos y prácticos de la educación STEM para definir una propuesta formativa. | C46: 3 | D46: Diseño de Ambientes de Aprendizaje en Educación STEM | E46: Identifica oportunidades de transformación de las propias prácticas profesionales desde el diseño de ambientes de aprendizaje en educación STEM, para atender una problemática diagnosticada en un contexto local o regional. Formula un ambiente de aprendizaje en educación STEM desde un enfoque integrador, que atienda una problemática diagnosticada en un contexto local o regional. | F46: TP | H46: X | I46: 3 | J46: =I46*12 -> 36 | K46: =I46*36 -> 108 | L46: =SUM(J46:K48) -> 144 | M46: 1. Principios orientadores en el enfoque STEM 2. Caracterización de un ambiente de aprendizaje con enfoque educativo STEM 3. Estrategias para el diseño e implementación 4. Evaluación desde la educación STEM | N46: Trabajo directo: Encuentros sincrónicos, mensajeria interna, foros generales, anuncios. Trabajo independiente: Lecturas Fundamentales y complementarias Anuncios Foros Actividades de refuerzo y recursos del módulo | O46: Actividad de puntos evaluables (semana 2 – Cuestionario de 5 preguntas). Entrega previa 1 (semana 3 - Laboratorio, taller, ejercicios, resolución de casos o de problemas, desarrollo de procesos o ejecución de propuestas. Entrega de forma individual o grupal, según indicaciones del profesor). Parcial (semana 4 - Cuestionarios de entre 15 y 20 preguntas). Entrega previa 2 (semana 5 - Laboratorio, taller, ejercicios, resolución de casos o de problemas, desarrollo de procesos o ejecución de propuestas. Entrega de forma individual o grupal, según indicaciones dadas por el profesor). Entrega final (semana 7 - Laboratorio, taller, ejercicios, resolución de casos o de problemas, desarrollo de procesos o ejecución de propuestas. Entrega de forma individual o grupal, según indicaciones dadas por el profesor). Evaluación final (semana 8 - Cuestionario de entre 15 y 20 preguntas). | P46: Las acciones retroalimentación varían entre las siguientes, según las condiciones que identifique el tutor. Formar: donde se crean las condiciones para que los estudiantes adquieran conocimientos, habilidades, actitudes, aptitudes y destrezas. Además, debe promover su desarrollo integral y debe acompañarlos en las situaciones académicas que enfrenten durante el desarrollo de un módulo o una asignatura. Informar: para que los estudiantes identifiquen los cambios que pueden afectarlos directa o indirectamente tanto en el aula de clase como en otros espacios. Prevenir: con el fin de anticiparse a las situaciones académicas que pueden representar dificultad para los estudiantes. Esto se logra a través de la interacción individual con los estudiantes y del completo conocimiento del contexto educativo en que el tutor se desenvuelve. Ayudar a decidir: donde se orienta a los estudiantes para que tomen la mejor decisión ante una situación concreta. El objetivo es que el estudiante fortalezca su autonomía y la toma de decisiones responsable.
A47: =_xlfn.XLOOKUP(B47,'Paso 3 Redacción RA '!I$3:I$11,'Paso 3 Redacción RA '!C$3:C$11,,0,1) -> Saberhacer | B47: Diseña un estudio o una propuesta de investigación que aborde problemáticas asociadas al desarrollo de vocaciones STEM, el cierre de brechas e inclusión en STEM y la apropiación social de CTI, desde un enfoque integrador, incorporando una ruta pedagógica y didáctica para el desarrollo de competencias analíticas, sistémicas, computacionales, críticas y de alfabetización digital en la población estudiantil.
A48: =_xlfn.XLOOKUP(B48,'Paso 3 Redacción RA '!I$3:I$11,'Paso 3 Redacción RA '!C$3:C$11,,0,1) -> Saberhacer | B48: Desarrolla un estudio o una propuesta educativa innovadora basada en la educación STEM desde un enfoque integrador, para abordar los retos y problemas de la educación en el país, con una perspectiva analítica, reflexiva, crítica y constructiva.
C49: 3 | D49: Electiva | H49: X | I49: 2 | J49: =I49*12 -> 24 | K49: =I49*36 -> 72 | L49: =SUM(J49:K49) -> 96
A50: =_xlfn.XLOOKUP(B50,'Paso 3 Redacción RA '!I$3:I$11,'Paso 3 Redacción RA '!C$3:C$11,,0,1) -> Saber | B50: Diagnostica los factores y necesidades formativas del país, según las diferencias y potencialidades regionales que demandan los cambios culturales y educativos, para identificar problemáticas asociadas al desarrollo de vocaciones STEM, el cierre de brechas e inclusión en STEM y la apropiación social de CTI. | C50: 3 | D50: Apropiación Social del Conocimiento Científico Tecnológico | E50: Diseña una estrategia de apropiación social del conocimiento en el marco de la educación STEM, teniendo en cuenta las características y necesidades específicas del territorio, para estimular la cultura científica y tecnológica, y promover el desarrollo regional. | F50: TP | H50: X | I50: 3 | J50: =I50*12 -> 36 | K50: =I50*36 -> 108 | L50: =SUM(J50:K50) -> 144 | M50: 1. Conceptos y políticas públicas de apropiación social del conocimiento en el marco de la CTI 2. Metodologías para la apropiación social del conocimiento en el marco de la CTI 3. Formulación, evaluación y seguimiento de procesos de apropiación social del conocimiento 4. Intervenciones estratégicas desde la educación STEM | N50: Trabajo directo: Encuentros sincrónicos, mensajeria interna, foros generales, anuncios. Trabajo independiente: Lecturas Fundamentales y complementarias Anuncios Foros Actividades de refuerzo y recursos del módulo | O50: Actividad de puntos evaluables (semana 2 – Cuestionario de 5 preguntas). Entrega previa 1 (semana 3 - Laboratorio, taller, ejercicios, resolución de casos o de problemas, desarrollo de procesos o ejecución de propuestas. Entrega de forma individual o grupal, según indicaciones del profesor). Parcial (semana 4 - Cuestionarios de entre 15 y 20 preguntas). Entrega previa 2 (semana 5 - Laboratorio, taller, ejercicios, resolución de casos o de problemas, desarrollo de procesos o ejecución de propuestas. Entrega de forma individual o grupal, según indicaciones dadas por el profesor). Entrega final (semana 7 - Laboratorio, taller, ejercicios, resolución de casos o de problemas, desarrollo de procesos o ejecución de propuestas. Entrega de forma individual o grupal, según indicaciones dadas por el profesor). Evaluación final (semana 8 - Cuestionario de entre 15 y 20 preguntas). | P50: Las acciones retroalimentación varían entre las siguientes, según las condiciones que identifique el tutor. Formar: donde se crean las condiciones para que los estudiantes adquieran conocimientos, habilidades, actitudes, aptitudes y destrezas. Además, debe promover su desarrollo integral y debe acompañarlos en las situaciones académicas que enfrenten durante el desarrollo de un módulo o una asignatura. Informar: para que los estudiantes identifiquen los cambios que pueden afectarlos directa o indirectamente tanto en el aula de clase como en otros espacios. Prevenir: con el fin de anticiparse a las situaciones académicas que pueden representar dificultad para los estudiantes. Esto se logra a través de la interacción individual con los estudiantes y del completo conocimiento del contexto educativo en que el tutor se desenvuelve. Ayudar a decidir: donde se orienta a los estudiantes para que tomen la mejor decisión ante una situación concreta. El objetivo es que el estudiante fortalezca su autonomía y la toma de decisiones responsable.
A51: =_xlfn.XLOOKUP(B51,'Paso 3 Redacción RA '!I$3:I$11,'Paso 3 Redacción RA '!C$3:C$11,,0,1) -> Saberhacer | B51: Diseña un estudio o una propuesta de investigación que aborde problemáticas asociadas al desarrollo de vocaciones STEM, el cierre de brechas e inclusión en STEM y la apropiación social de CTI, desde un enfoque integrador, incorporando una ruta pedagógica y didáctica para el desarrollo de competencias analíticas, sistémicas, computacionales, críticas y de alfabetización digital en la población estudiantil.
A52: =_xlfn.XLOOKUP(B52,'Paso 3 Redacción RA '!I$3:I$11,'Paso 3 Redacción RA '!C$3:C$11,,0,1) -> Saberhacer | B52: Desarrolla un estudio o una propuesta educativa innovadora basada en la educación STEM desde un enfoque integrador, para abordar los retos y problemas de la educación en el país, con una perspectiva analítica, reflexiva, crítica y constructiva.
A53: =_xlfn.XLOOKUP(B53,'Paso 3 Redacción RA '!I$3:I$11,'Paso 3 Redacción RA '!C$3:C$11,,0,1) -> Saberhacer | B53: Diseña un estudio o una propuesta de investigación que aborde problemáticas asociadas al desarrollo de vocaciones STEM, el cierre de brechas e inclusión en STEM y la apropiación social de CTI, desde un enfoque integrador, incorporando una ruta pedagógica y didáctica para el desarrollo de competencias analíticas, sistémicas, computacionales, críticas y de alfabetización digital en la población estudiantil. | C53: 3 | D53: Trabajo de Investigación [STEM] | E53: Elabora el informe final del trabajo de investigación seleccionando y aplicando el método de análisis, de acuerdo con el diseño de investigación seleccionado. | F53: P | H53: X | I53: 3 | J53: =I53*12 -> 36 | K53: =I53*36 -> 108 | L53: =SUM(J53:K53) -> 144 | M53: 1. Diseño metodológico 2. Análisis, validación y revisión de resultados 3. Elaboración de la discusión y conclusiones 4. Estrategias de comunicación y difusión | N53: Trabajo directo: Encuentros sincrónicos, mensajeria interna, foros generales, anuncios. Trabajo independiente: Lecturas Fundamentales y complementarias Anuncios Foros Actividades de refuerzo y recursos del módulo | O53: Evaluación diagnóstica (semana 1 – Cuestionario de 5 preguntas) Actividad formativa (semanas 2 a 7 - Foro de carácter individual o grupal según las características del módulo) Informe inicial (semana 5 - Escrito expositivo parcial en el que se explican y describen los aspectos referidos al ejercicio investigativo o de estudio en su primera fase de implementación) Informe final (semana 7 - Escrito expositivo de consolidación en el que se explica y describe el desarrollo del ejercicio investigativo o de estudio a partir de las realimentaciones obtenidas en las entregas parciales) Autoevaluación (semana 8 - Cuestionario de 5 preguntas) | P53: Las acciones retroalimentación varían entre las siguientes, según las condiciones que identifique el tutor. Formar: donde se crean las condiciones para que los estudiantes adquieran conocimientos, habilidades, actitudes, aptitudes y destrezas. Además, debe promover su desarrollo integral y debe acompañarlos en las situaciones académicas que enfrenten durante el desarrollo de un módulo o una asignatura. Informar: para que los estudiantes identifiquen los cambios que pueden afectarlos directa o indirectamente tanto en el aula de clase como en otros espacios. Prevenir: con el fin de anticiparse a las situaciones académicas que pueden representar dificultad para los estudiantes. Esto se logra a través de la interacción individual con los estudiantes y del completo conocimiento del contexto educativo en que el tutor se desenvuelve. Ayudar a decidir: donde se orienta a los estudiantes para que tomen la mejor decisión ante una situación concreta. El objetivo es que el estudiante fortalezca su autonomía y la toma de decisiones responsable.
A54: =_xlfn.XLOOKUP(B54,'Paso 3 Redacción RA '!I$3:I$11,'Paso 3 Redacción RA '!C$3:C$11,,0,1) -> Saberhacer | B54: Desarrolla un estudio o una propuesta educativa innovadora basada en la educación STEM desde un enfoque integrador, para abordar los retos y problemas de la educación en el país, con una perspectiva analítica, reflexiva, crítica y constructiva.
A55: =_xlfn.XLOOKUP(B55,'Paso 3 Redacción RA '!I$3:I$11,'Paso 3 Redacción RA '!C$3:C$11,,0,1) -> Saberser | B55: Evalúa las condiciones y necesidades educativas del contexto local o regional para validar la pertinencia de estudios o propuestas formativas en educación STEM con una visión transformadora de los procesos de enseñanza y de aprendizaje. | C55: II | Q55: =SUM(I43:I55) -> 14
C56: Total módulos del programa | D56: =COUNTA(D3:D55) -> 15 | H56: Total créditos programa | I56: =SUM(I3:I55) -> 42 | Q56: =SUM(Q3:Q55) -> 42
H57: Total créditos fundamentación | I57: =SUM(I37,I31,I27,I21,I17,I11) -> 15
H58: Total créditos profundización | I58: =SUM(I53,I50,I49,I46,I43,I32,I24,I6,I3) -> 27

Sheet Taxonomía para competencias
B1: Verbos Competencias | D1: Observación: estos verbos son solo algunos y se pueden agregar tantos como se requieran; solo hay que tener en cuenta que debe estar al nivel de un perfil profesional.
B2: Actualizar
B3: Administrar
B4: Aplicar
B5: Asegurar
B6: Asesorar
B7: Auditar
B8: Comunicar
B9: Conducir
B10: Conocer
B11: Coordinar
B12: Definir
B13: Desarrollar
... B38: Analizar

Sheet Taxonomias para RA
S1: Taxonomía de Bloom Adaptada con las propuestas de Anderson y Krathwohl | AL1: Taxonomía de Anderson y Krathwohl (AK) | BB1: Taxonomía de Marzano y Kendal (MK)
L2: Taxonomía de Bloom | S2: Cognitivo(BAK) | Y2: Procedimental(BAK) | AC2: Actitudinal(BAK)
A3: Taxonomías | C3: BAK | D3: AK | E3: MK | G3: CognitivoB | H3: ProcedimentalB | I3: ActitudinalB | L3: ConocimientoB | M3: ComprensiónB | N3: AplicaciónB | O3: AnálisisB | P3: SíntesisB | Q3: EvaluaciónB | S3: ConocimientoBAK | T3: ComprensiónBAK | U3: AplicaciónBAK | V3: AnálisisBAK | W3: SíntesisBAK | X3: EvaluaciónBAK | Y3: ImitaciónBAK | Z3: ManipulaciónBAK | AA3: PrecisiónBAK | AB3: ControlBAK | AC3: PercepciónBAK | AD3: ResponderBAK | AE3: ValorarBAK | AF3: OrganizarBAK | AG3: CaracterizarBAK | AL3: CognitivoInf(AK) | AO3: CognitivoSup(AK) | AR3: Procedimental(AK) | AV3: Actitudinal(AK)
A4: Bloom | C4: CognitivoBAK | D4: HechosAK | E4: InformaciónMK | G4: ConocimientoB | H4: ConocimientoB | I4: ConocimientoB | L4: Adquirir | M4: Auditar | N4: Aplicar | O4: Aislar | P4: Adaptar | Q4: Aconsejar | S4: Adquirir | T4: Auditar | U4: Aplicar | V4: Aislar | W4: Adaptar | X4: Aconsejar | Y4: Ajustar | Z4: Direccionar | AA4: Disponer | AB4: Remover | AC4: Hacer | AD4: Aprobar | AE4: Adoptar | AF4: Extraer | AG4: Negociar | AL4: RecordarLK | AM4: ComprenderLK | AN4: AplicarLK | AO4: AnalizarLK | AP4: EvaluarLK | AQ4: CrearLK | AR4: ImitaciónBAK | AS4: ManipulaciónBAK | AT4: PrecisiónBAK | AU4: ControlBAK | AV4: PercepciónBAK | AW4: ResponderBAK | AX4: ValorarBAK | AY4: OrganizarBAK | AZ4: CaracterizarBAK | BB4: RecuperaciónMK | BC4: ComprensiónMK | BD4: AnálisisMK | BE4: UsoConocimientoMK | BF4: MetacogniciónMK | BG4: SistemadelYoMK
A5: BAK | C5: ProcedimentalBAK | D5: ConceptosAK | E5: ProcesosMentalesMK | G5: ComprensiónB | H5: ComprensiónB | I5: ComprensiónB | L5: Buscar | M5: Bosquejar | N5: Calisificar | O5: Analizar | P5: Administrar | Q5: Adjuntar | S5: Buscar | T5: Bosquejar | U5: Calisificar | V5: Analizar | W5: Administrar | X5: Adjuntar | Y5: Adaptar | Z5: Desmontar | AA5: Planear | AB5: Quitar | AC5: Conducir | AD5: Autorizar | AE5: Aprobar | AF5: Resumir | AG5: Ofrecer | AL5: Afirmar | AM5: Clasificar | AN5: Actuar | AO5: Agrupar | AP5: Adaptar | AQ5: Desarrollar | AR5: Ajustar | AS5: Direccionar | AT5: Disponer | AU5: Remover | AV5: Hacer | AW5: Aprobar | AX5: Adoptar | AY5: Extraer | AZ5: Negociar | BB5: Afirmar | BC5: Auditar | BD5: Agrupar | BE5: Actuar | BF5: Aceptar | BG5: Aceptar
A6: AK | C6: ActitudinalBAK | D6: ProcedimientoslAK | E6: PsicomotorMK | G6: AplicaciónB | H6: AplicaciónB | I6: AplicaciónB | L6: Citar | M6: Comentar | N6: Combinar | O6: Calcular | P6: Arreglar | Q6: Agregar | S6: Citar | T6: Comentar | U6: Combinar | V6: Calcular | W6: Arreglar | X6: Agregar | Y6: Modificar | Z6: Dramatizar | AA6: Apalancar | AB6: Suprimir | AC6: Dirigir | AD6: Demostrar | AE6: Aceptar | AF6: Promover | AG6: Conducir | AL6: Citar | AM6: Comparar | AN6: Agrupar | AO6: Aislar | AP6: Añadir | AQ6: Elaborar | AR6: Adaptar | AS6: Desmontar | AT6: Planear | AU6: Quitar | AV6: Conducir | AW6: Autorizar | AX6: Aprobar | AY6: Resumir | AZ6: Ofrecer | BB6: Citar | BC6: Bosquejar | BD6: Aislar | BE6: Agrupar | BF6: Adelantar | BG6: Adoptar
A7: MK | D7: MetacogniciónAK | G7: AnálisisB | H7: AnálisisB | I7: AnálisisB | L7: Consignar | M7: Comunicar | N7: Componer | O7: Categorizar | P7: Arreglar | Q7: Alinear | S7: Consignar | T7: Comunicar | U7: Componer | V7: Categorizar | W7: Arreglar | X7: Alinear | Y7: Concretar | Z7: Docificar | AA7: Levantar | AB7: Eliminar | AC7: Direccionar | AD7: Afirmar | AE7: Afirmar | AF7: Adelantar | AG7: Comportarse bajo condiciones | AL7: Copiar | AM7: Contrastar | AN7: Calcular | AO7: Asumir | AP7: Apoyar | AQ7: Maximizar | AR7: Modificar | AS7: Dramatizar | AT7: Apalancar | AU7: Suprimir | AV7: Dirigir | AW7: Demostrar | AX7: Aceptar | AY7: Promover | AZ7: Conducir | BB7: Copiar | BC7: Clasificar | BD7: Analizar | BE7: Aplicar | BF7: Adoptar | BG7: Afinar
G8: SíntesisB | H8: SíntesisB | I8: SíntesisB | L8: Decir | M8: Convertir | N8: Conducir | O8: Comparar | P8: Articular | Q8: Arbitrar | S8: Decir | T8: Convertir | U8: Conducir | V8: Comparar | W8: Articular | X8: Arbitrar | Y8: Asegurar | Z8: Dibujar | AA8: Estimular | AB8: Retirar | AC8: Aplicar | AD8: Asegurar | AE8: Ratificar | AF8: Fomentar | AG8: Completar | AL8: Decir | AM8: Demostrar | AN8: Categorizar | AO8: Buscar similitudes | AP8: Argumentar | AQ8: Mejorar | AR8: Concretar | AS8: Docificar | AT8: Levantar | AU8: Eliminar | AV8: Direccionar | AW8: Afirmar | AX8: Afirmar | AY8: Adelantar | AZ8: Comportarse bajo condiciones | BB8: Decir | BC8: Comentar | BD8: Aplicar | BE8: Calcular | BF8: Afinar | BG8: Agradecer
G9: EvaluaciónB | H9: EvaluaciónB | I9: EvaluaciónB | L9: Definir | M9: Criticar | N9: Construir | O9: Considerar | P9: Aumentar | Q9: Asegurar | S9: Definir | T9: Criticar | U9: Construir | V9: Considerar | W9: Aumentar | X9: Asegurar | Y9: Alinear | Z9: Trazar | AA9: Localizar | AB9: Extirpar | AC9: Manejar | AD9: Hacer | AE9: Apreciar | AF9: Anticipar | AG9: Afinar | AL9: Definir | AM9: Discutir | AN9: Conectar | AO9: Categorizar | AP9: Cambiar | AQ9: Minimizar | AR9: Asegurar | AS9: Dibujar | AT9: Estimular | AU9: Retirar | AV9: Aplicar | AW9: Asegurar | AX9: Ratificar | AY9: Fomentar | AZ9: Completar | BB9: Definir | BC9: Comparar | BD9: Asumir | BE9: Calisificar | BF9: Afirmar | BG9: Ambicionar
L10: Deletrear | M10: Dar ejemplos | N10: Demostrar | O10: Contrastar | P10: Calcular | Q10: Asesorar | S10: Deletrear | T10: Dar ejemplos | U10: Demostrar | V10: Contrastar | W10: Calcular | X10: Asesorar | Y10: Analizar | Z10: Hacer | AA10: Ubicar | AB10: Disipar | AC10: Guiar | AD10: Comunicar | AE10: Comprender | AF10: Proponer | AG10: Acabar | AL10: Deletrear | AM10: Ejemplificar | AN10: Construir | AO10: Centrarse | AP10: Combinar | AQ10: Modelar | AR10: Alinear | AS10: Trazar | AT10: Localizar | AU10: Extirpar | AV10: Manejar | AW10: Hacer | AX10: Apreciar | AY10: Anticipar | AZ10: Afinar | BB10: Deletrear | BC10: Comunicar | BD10: Buscar similitudes | BE10: Categorizar | BF10: Agradecer | BG10: Anhelar
G11: CognitivoAK | H11: ConceptosAK | I11: ProcedimientosAK | J11: MetacogniciónAK | L11: Demostrar | M11: Debatir | N11: Determinar | O11: Criticar | P11: Componer | Q11: Atar | S11: Demostrar | T11: Debatir | U11: Determinar | V11: Criticar | W11: Componer | X11: Atar | Y11: Aplicar | Z11: Extraer | AA11: Encontrar | AB11: Hacer | AC11: Realizar | AD11: Hablar | AE11: Agradecer | AF11: Defender | AG11: Terminar | AL11: Duplicar | AM11: Esquematizar | AN11: Demostrar | AO11: Comparar | AP11: Comparar | AQ11: Pensar | AR11: Analizar | AS11: Hacer | AT11: Ubicar | AU11: Disipar | AV11: Guiar | AW11: Comunicar | AX11: Comprender | AY11: Proponer | AZ11: Acabar | BB11: Duplicar | BC11: Contrastar | BD11: Calcular | BE11: Combinar | BF11: Ambicionar | BG11: Anticipar
G12: RecordarAK | H12: RecordarAK | I12: RecordarAK | J12: RecordarAK | L12: Describir | M12: Describir | N12: Dibujar | O12: Cuestionar | P12: Computar | Q12: Calcular | S12: Describir | T12: Describir | U12: Dibujar | V12: Cuestionar | W12: Computar | X12: Calcular | Y12: Arreglar | Z12: Perforar | AA12: Colocar | AB12: Reproducir | AC12: Emplear | AD12: Discutir | AE12: Estimar | AF12: Proteger | AG12: Contextualizar | AL12: Elegir | AM12: Explicar | AN12: Desarrollar | AO12: Correlacionar | AP12: Compilar | AQ12: Planear | AR12: Aplicar | AS12: Extraer | AT12: Encontrar | AU12: Hacer | AV12: Realizar | AW12: Hablar | AX12: Agradecer | AY12: Defender | AZ12: Terminar | BB12: Elegir | BC12: Convertir | BD12: Clasificar | BE12: Componer | BF12: Anhelar | BG12: Apreciar
G13: ComprenderAK | H13: ComprenderAK | I13: ComprenderAK | J13: ComprendeAK | L13: Elegir | M13: Desplegar | N13: Discriminar | O13: Debatir | P13: Concluir | Q13: Calificar | S13: Elegir | T13: Desplegar | U13: Discriminar | V13: Debatir | W13: Concluir | X13: Calificar | Y13: Organizar | Z13: Ejercitar | AA13: Establecer | AB13: Traducir | AC13: Aceptar | AD13: Cooperar | AE13: Tasar | AF13: Definir | AG13: Cooperar | AL13: Escribir | AM13: Expresar | AN13: Dramatizar | AO13: Descomponer | AP13: Componer | AQ13: Proponer | AR13: Arreglar | AS13: Perforar | AT13: Colocar | AU13: Reproducir | AV13: Emplear | AW13: Discutir | AX13: Estimar | AY13: Proteger | AZ13: Contextualizar | BB13: Escribir | BC13: Criticar | BD13: Categorizar | BE13: Conducir | BF13: Anticipar | BG13: Aprobar
G14: AplicarAK | H14: AplicarAK | I14: AplicarAK | J14: AplicarAK | L14: Enseñar | M14: Dibujar | N14: Diseñar | O14: Deducir | P14: Conectar | Q14: Censurar | S14: Enseñar | T14: Dibujar | U14: Diseñar | V14: Deducir | W14: Conectar | X14: Censurar | Y14: Ordenar | Z14: Enseñar | AA14: Hallar | AB14: Entregar | AC14: Admitir | AD14: Colaborar | AE14: Aspirar | AF14: Determinar | AG14: Colaborar | AL14: Leer | AM14: Generalizar | AN14: Elegir | AO14: Diferenciar | AP14: Construir | AQ14: Reescribir | AR14: Organizar | AS14: Ejercitar | AT14: Establecer | AU14: Traducir | AV14: Aceptar | AW14: Cooperar | AX14: Tasar | AY14: Definir | AZ14: Cooperar | BB14: Leer | BC14: Dar ejemplos | BD14: Centrarse | BE14: Conectar | BF14: Apoyar | BG14: Asistir
G15: AnalizarAK | H15: AnalizarAK | I15: AnalizarAK | J15: AnalizarAK | L15: Escribir | M15: Discutir | N15: Dramatizar | O15: Desarrollar | P15: Construir | Q15: Clasificar | S15: Escribir | T15: Discutir | U15: Dramatizar | V15: Desarrollar | W15: Construir | X15: Clasificar | Y15: Disponer | Z15: Conducir | AA15: Situar | AB15: Conducir | AC15: Evaluar | AD15: Actuar recíprocamente | AE15: Ambicionar | AF15: Considerar | AG15: Discriminar | AL15: Listar | AM15: Ilustrar | AN15: Emplear | AO15: Distinguir | AP15: Convencer | AQ15: Simplificar | AR15: Ordenar | AS15: Enseñar | AT15: Hallar | AU15: Entregar | AV15: Admitir | AW15: Colaborar | AX15: Aspirar | AY15: Determinar | AZ15: Colaborar | BB15: Listar | BC15: Debatir | BD15: Combinar | BE15: Construir | BF15: Apreciar | BG15: Aspirar
G16: EvaluarAK | H16: EvaluarAK | I16: EvaluarAK | J16: EvaluarAK | L16: Establecer | M16: Diseñar | N16: Duplicar | O16: Detectar | P16: Crear | Q16: Computar | S16: Establecer | T16: Diseñar | U16: Duplicar | V16: Detectar | W16: Crear | X16: Computar | Y16: Acordar | Z16: Dirigir | AA16: Bajar | AB16: Direccionar | AC16: Valorar | AD16: Obrar recíprocamente | AE16: Anhelar | AF16: Discernir | AG16: Distinguir | AL16: Localizar | AM16: Inferir | AN16: Enseñar | AO16: Dividir | AP16: Crear | AQ16: Suponer | AR16: Disponer | AS16: Conducir | AT16: Situar | AU16: Conducir | AV16: Evaluar | AW16: Actuar recíprocamente | AX16: Ambicionar | AY16: Considerar | AZ16: Discriminar | BB16: Localizar | BC16: Demostrar | BD16: Comparar | BE16: Demostrar | BF16: Aprobar | BG16: Atender
G17: CrearAK | H17: CrearAK | I17: CrearAK | J17: CrearAK | L17: Etiquetar | M17: Establecer | N17: Elegir | O17: Diagramar | P17: Decidir | Q17: Concluir | S17: Etiquetar | T17: Establecer | U17: Elegir | V17: Diagramar | W17: Decidir | X17: Concluir | Y17: Gestionar | Z17: Manejar | AA17: Manipular | AB17: Reparar | AC17: Apreciar | AD17: Recitar | AE17: Creer | AF17: Percibir | AG17: Categorizar | AL17: Memorizar | AM17: Informar | AN17: Entrevistar | AO17: Elegir | AP17: Criticar | AQ17: Sustituir | AR17: Acordar | AS17: Dirigir | AT17: Bajar | AU17: Direccionar | AV17: Valorar | AW17: Obrar recíprocamente | AX17: Anhelar | AY17: Discernir | AZ17: Distinguir | BB17: Memorizar | BC17: Describir | BD17: Componer | BE17: Desarrollar | BF17: Arreglar | BG17: Categorizar
L18: Examinar | M18: Examinar | N18: Emparejar | O18: Diferenciar | P18: Deducir | Q18: Conformar | S18: Examinar | T18: Examinar | U18: Emparejar | V18: Diferenciar | W18: Deducir | X18: Conformar | Y18: Armar | Z18: Guiar | AA18: Manejar | AB18: Componer | AC18: Tasar | AD18: Decir | AE18: Ser partidario de | AF18: Identificar | AG18: Juzgar | AL18: Mostrar | AM18: Interpretar | AN18: Hacer uso | AO18: Encontrar | AP18: Debatir | AQ18: Teorizar | AR18: Gestionar | AS18: Manejar | AT18: Manipular | AU18: Reparar | AV18: Apreciar | AW18: Recitar | AX18: Creer | AY18: Percibir | AZ18: Categorizar | BB18: Mostrar | BC18: Desplegar | BD18: Conducir | BE18: Determinar | BF18: Asistir | BG18: Clasificar
G19: InformaciónMK | H19: ProcesosMentalesMK | I19: PsicomotorMK | L19: Examinar | M19: Explicar | N19: Emplear | O19: Discernir | P19: Derivar | Q19: Constrastar | S19: Examinar | T19: Explicar | U19: Emplear | V19: Discernir | W19: Derivar | X19: Constrastar | Y19: Ensamblar | Z19: Examinar | AA19: Medir | AB19: Reemplazar | AC19: Estimar | AD19: Enumerar | AE19: Cuidar | AF19: Reconocer | AG19: Participar | AL19: Nombrar | AM19: Mostrar | AN19: Identificar | AO19: Encuestar | AP19: Decidir | AQ19: Testar | AR19: Armar | AS19: Guiar | AT19: Manejar | AU19: Componer | AV19: Tasar | AW19: Decir | AX19: Ser partidario de | AY19: Identificar | AZ19: Juzgar | BB19: Nombrar | BC19: Dibujar | BD19: Considerar | BE19: Dibujar | BF19: Aspirar | BG19: Completar
G20: RecuperaciónMK | H20: RecuperaciónMK | I20: RecuperaciónMK | L20: Grabar | M20: Exponer | N20: Esquematizar | O20: Discriminar | P20: Desarrollar | Q20: Contabilizar | S20: Grabar | T20: Exponer | U20: Esquematizar | V20: Discriminar | W20: Desarrollar | X20: Contabilizar | Y20: Reunir | Z20: Ejecutar | AA20: Racionar | AB20: Sustituir | AC20: Preguntar | AD20: Narrar | AE20: Atender | AF20: Formular | AG20: Atender | AL20: Observar | AM20: Observar | AN20: Interpretar | AO20: Establecer | AP20: Deducir | AQ20: Transformar | AR20: Ensamblar | AS20: Examinar | AT20: Medir | AU20: Reemplazar | AV20: Estimar | AW20: Enumerar | AX20: Cuidar | AY20: Reconocer | AZ20: Participar | BB20: Observar | BC20: Discutir | BD20: Construir | BE20: Discriminar | BF20: Atender | BG20: Comprender
G21: ComprensiónMK | H21: ComprensiónMK | I21: ComprensiónMK | L21: Hacer | M21: Expresar | N21: Estimar | O21: Distinguir | P21: Describir | Q21: Controlar | S21: Hacer | T21: Expresar | U21: Estimar | V21: Distinguir | W21: Describir | X21: Controlar | Y21: Construir | Z21: Explorar | AA21: Separer | AB21: Reponer | AC21: Interrogar | AD21: Referir | AE21: Asistir | AF21: Arreglar | AG21: Servir | AL21: Omitir | AM21: Parafrasear | AN21: Manipular | AO21: Examinar | AP21: Defender | AQ21: Visualizar | AR21: Reunir | AS21: Ejecutar | AT21: Racionar | AU21: Sustituir | AV21: Preguntar | AW21: Narrar | AX21: Atender | AY21: Formular | AZ21: Atender | BB21: Omitir | BC21: Diseñar | BD21: Contrastar | BE21: Diseñar | BF21: Aunar | BG21: Conducir
G22: AnálisisMK | H22: AnálisisMK | I22: AnálisisMK | L22: Identificar | M22: Extraer | N22: Estructurar | O22: Estructurar | P22: Desempeñar | Q22: Corregir | S22: Identificar | T22: Extraer | U22: Estructurar | V22: Estructurar | W22: Desempeñar | X22: Corregir | Y22: Edificar | Z22: Expresar | AA22: Dividir | AB22: Colocar | AC22: Publicar | AD22: Resolver | AE22: Preocuparse de o por | AF22: Preguntar | AG22: Cumplir | AL22: Rastrear | AM22: Predecir | AN22: Organizar | AO22: Inferir | AP22: Demostrar | AR22: Construir | AS22: Explorar | AT22: Separer | AU22: Reponer | AV22: Interrogar | AW22: Referir | AX22: Asistir | AY22: Arreglar | AZ22: Servir | BB22: Parafrasear | BC22: Ejemplificar | BD22: Correlacionar | BE22: Dramatizar | BF22: Categorizar | BG22: Conectar
G23: UsoConocimientoMK | H23: UsoConocimientoMK | I23: UsoConocimientoMK | L23: Ilustrar | M23: Generalizar | N23: Estructurar | O23: Examinar | P23: Dirigir | Q23: Criticar | S23: Ilustrar | T23: Generalizar | U23: Estructurar | V23: Examinar | W23: Dirigir | X23: Criticar | Y23: Hacer | Z23: Encajar | AA23: Repartir | AB23: Ubicar | AC23: Asisitir | AD23: Acordar | AE23: Elegir | AF23: Cuestionar | AG23: Ejercer | AL23: Recitar | AM23: Preguntar | AN23: Planear | AO23: Inspeccionar | AP23: Descubrir | AR23: Edificar | AS23: Expresar | AT23: Dividir | AU23: Colocar | AV23: Publicar | AW23: Resolver | AX23: Preocuparse de o por | AY23: Preguntar | AZ23: Cumplir | BB23: Rastrear | BC23: Esquematizar | BD23: Criticar | BE23: Duplicar | BF23: Clasificar | BG23: Considerar
G24: MetacogniciónMK | H24: MetacogniciónMK | I24: MetacogniciónMK | L24: Listar | M24: Hacer | N24: Evaluar | O24: Experimentar | P24: Diseñar | Q24: Cuestionar | S24: Listar | T24: Hacer | U24: Evaluar | V24: Experimentar | W24: Diseñar | X24: Cuestionar | Y24: Trazar | Z24: Ajustar | AA24: Mezclar | AB24: Ejecutar | AC24: Atender | AD24: Seleccionar | AE24: Seleccionar | AF24: Relacionar | AG24: Entregar | AL24: Reconocer | AM24: Relacionar | AN24: Practicar | AO24: Investigar | AP24: Diseñar | AR24: Hacer | AS24: Encajar | AT24: Repartir | AU24: Ubicar | AV24: Asisitir | AW24: Acordar | AX24: Elegir | AY24: Cuestionar | AZ24: Ejercer | BB24: Recitar | BC24: Establecer | BD24: Cuestionar | BE24: Elegir | BF24: Colaborar | BG24: Constatar
G25: SistemadelYoMK | H25: SistemadelYoMK | I25: SistemadelYoMK | L25: Mostar | M25: Identificar | N25: Experimentar | O25: Inspeccionar | P25: Ejercer | Q25: Culminar | S25: Mostar | T25: Identificar | U25: Experimentar | V25: Inspeccionar | W25: Ejercer | X25: Culminar | Y25: Preparar | Z25: Acceder | AA25: Porcionar | AB25: Correr | AC25: Servir | AD25: Elegir | AE25: Escoger | AF25: Conectar | AG25: Apoyar | AL25: Relacionar | AM25: Resumir | AN25: Resolver | AO25: Motivar | AP25: Estimar | AR25: Trazar | AS25: Ajustar | AT25: Mezclar | AU25: Ejecutar | AV25: Atender | AW25: Seleccionar | AX25: Seleccionar | AY25: Relacionar | AZ25: Entregar | BB25: Reconocer | BC25: Examinar | BD25: Debatir | BE25: Emparejar | BF25: Compartir | BG25: Contextualizar
L26: Nombrar | M26: Indicar | N26: Ilustrar | O26: Inventariar | P26: Ensamblar | Q26: Debatir | S26: Nombrar | T26: Indicar | U26: Ilustrar | V26: Inventariar | W26: Ensamblar | X26: Debatir | Y26: Cambiar | Z26: Arreglar | AA26: Modificar | AB26: Llevar | AC26: Ocupar | AD26: Escoger | AE26: Clasificar | AF26: Relatar | AG26: Soportar | AL26: Relacionar | AM26: Revisar | AN26: Resumir | AO26: Observar | AP26: Evaluar | AR26: Preparar | AS26: Acceder | AT26: Porcionar | AU26: Correr | AV26: Servir | AW26: Elegir | AX26: Escoger | AY26: Conectar | AZ26: Apoyar | BB26: Relacionar | BC26: Explicar | BD26: Deducir | BE26: Emplear | BF26: Completar | BG26: Cuestionar
L27: Numerar | M27: Inferir | N27: Indicar | O27: Investigar | P27: Escribir | Q27: Decidir | S27: Numerar | T27: Inferir | U27: Indicar | V27: Investigar | W27: Escribir | X27: Decidir | Y27: Modificar | Z27: Mejorar | AA27: Ajustar | AB27: Manejar | AC27: Elegir | AD27: Clasificar | AE27: Convocar | AF27: Revelar | AG27: Verificar | AL27: Repetir | AM27: Traducir | AN27: Seleccionar | AO27: Ordenar | AP27: Experimentar | AR27: Cambiar | AS27: Arreglar | AT27: Modificar | AU27: Llevar | AV27: Ocupar | AW27: Escoger | AX27: Clasificar | AY27: Relatar | AZ27: Soportar | BB27: Repetir | BC27: Exponer | BD27: Demostrar | BE27: Enseñar | BF27: Comportarse bajo condiciones | BG27: Cuidar
L28: Observar | M28: Interpretar | N28: Interpretar | O28: Listar | P28: Establecer | Q28: Deducir | S28: Observar | T28: Interpretar | U28: Interpretar | V28: Listar | W28: Establecer | X28: Deducir | Y28: Transformar | Z28: Manipular | AA28: Mover | AB28: Seguir | AC28: Escoger | AD28: Contar | AE28: Unir | AF28: Exteriorizar | AG28: Constatar | AN28: Simular | AO28: Preguntar | AP28: Explicar | AR28: Modificar | AS28: Mejorar | AT28: Ajustar | AU28: Manejar | AV28: Elegir | AW28: Clasificar | AX28: Convocar | AY28: Revelar | AZ28: Verificar | BC28: Expresar | BD28: Desarrollar | BE28: Entrevistar | BF28: Comprender | BG28: Cumplir
L29: Obtener | M29: Inventariar | N29: Investigar | O29: Medir | P29: Estudiar | Q29: Defender | S29: Obtener | T29: Inventariar | U29: Investigar | V29: Medir | W29: Estudiar | X29: Defender | Y29: Comprobar | Z29: Maniobrar | AA29: Maniobrar | AB29: Trasladar | AC29: Seleccionar | AD29: Informar | AE29: Ensamblar | AF29: Desplegar | AG29: Controlar | AN29: Transferir | AO29: Priorizar | AP29: Extender | AR29: Transformar | AS29: Manipular | AT29: Mover | AU29: Seguir | AV29: Escoger | AW29: Contar | AX29: Unir | AY29: Exteriorizar | AZ29: Constatar | BC29: Extraer | BD29: Descomponer | BE29: Esquematizar | BF29: Conducir | BG29: Defender
L30: Ordenar | M30: Localizar | N30: Listar | O30: Planear | P30: Figurar | Q30: Defender | S30: Ordenar | T30: Localizar | U30: Listar | V30: Planear | W30: Figurar | X30: Defender | Y30: Verificar | Z30: Identificar | AA30: Gestionar | AB30: Implementar | AC30: Escuchar | AD30: Indicar | AE30: Participar | AG30: Evaluar | AN30: Unir | AO30: Probar | AP30: Formular | AR30: Comprobar | AS30: Maniobrar | AT30: Maniobrar | AU30: Trasladar | AV30: Seleccionar | AW30: Informar | AX30: Ensamblar | AY30: Desplegar | AZ30: Controlar | BC30: Generalizar | BD30: Detectar | BE30: Estimar | BF30: Conectar | BG30: Determinar
L31: Organizar | M31: Narrar | N31: Manipular | O31: Preguntar | P31: Formular | Q31: Determinar | S31: Organizar | T31: Narrar | U31: Manipular | V31: Preguntar | W31: Formular | X31: Determinar | Y31: Controlar | Z31: Inspeccionar | AA31: Negociar | AB31: Esculpir | AC31: Anotar | AD31: Distinguir | AE31: Aunar | AN31: Usar | AO31: Razonar | AP31: Hipotetizar | AR31: Verificar | AS31: Identificar | AT31: Gestionar | AU31: Implementar | AV31: Escuchar | AW31: Indicar | AX31: Participar | BC31: Hacer | BD31: Determinar | BE31: Estructurar | BF31: Considerar | BG31: Discernir
L32: Preguntar | M32: Parafrasear | N32: Modelar | O32: Probar | P32: Generar | Q32: Discutir | S32: Preguntar | T32: Parafrasear | U32: Modelar | V32: Probar | W32: Generar | X32: Discutir | Y32: Contrastar | Z32: Revisar | AA32: Emitir | AB32: Entallar | AC32: Observar | AD32: Relatar | AE32: Proporcionar | AO32: Reorganizar | AP32: Influir | AR32: Controlar | AS32: Inspeccionar | AT32: Negociar | AU32: Esculpir | AV32: Anotar | AW32: Distinguir | AX32: Aunar | BC32: Identificar | BD32: Diagramar | BE32: Evaluar | BF32: Constatar | BG32: Discriminar
L33: Presentar | M33: Presentar | N33: Operar | O33: Reconocer | P33: Gestionar | Q33: Elegir | S33: Presentar | T33: Presentar | U33: Operar | V33: Reconocer | W33: Gestionar | X33: Elegir | Y33: Contar | Z33: Registrar | AA33: Abrir | AB33: Servir | AC33: Cumplir | AD33: Conocer | AE33: Estimular | AO33: Resaltar | AP33: Innovar | AR33: Contrastar | AS33: Revisar | AT33: Emitir | AU33: Entallar | AV33: Observar | AW33: Relatar | AX33: Proporcionar | BC33: Ilustrar | BD33: Dibujar | BE33: Experimentar | BF33: Contextualizar | BG33: Distinguir
L34: Probar | M34: Relatar | N34: Organizar | O34: Relacionar | P34: Hacer | Q34: Ensamblar | S34: Probar | T34: Relatar | U34: Organizar | V34: Relacionar | W34: Hacer | X34: Ensamblar | Y34: Limpiar | Z34: Reconocer | AA34: Destapar | AB34: Coser | AC34: Examinar | AE34: Contribuir | AO34: Separar | AP34: Justificar | AR34: Contar | AS34: Registrar | AT34: Abrir | AU34: Servir | AV34: Cumplir | AW34: Conocer | AX34: Estimular | BC34: Indicar | BD34: Diferenciar | BE34: Hacer uso | BF34: Contribuir | BG34: Ejercer
L35: Realizar | M35: Reportar | N35: Patronar | O35: Separar | P35: Inferir | Q35: Escoger | S35: Realizar | T35: Reportar | U35: Patronar | V35: Separar | W35: Inferir | X35: Escoger | Y35: Filtrar | Z35: Instalar | AA35: Comenzar | AB35: Soldar | AC35: Usar | AE35: Provocar | AO35: Simplificar | AP35: Juzgar | AR35: Limpiar | AS35: Reconocer | AT35: Destapar | AU35: Coser | AV35: Examinar | AX35: Contribuir | BC35: Inferir | BD35: Discernir | BE35: Identificar | BF35: Controlar | BG35: Elegir
L36: Reconocer | M36: Resumir | N36: Practicar | O36: Subdividir | P36: Instalar | Q36: Establecer | S36: Reconocer | T36: Resumir | U36: Practicar | V36: Subdividir | W36: Instalar | X36: Establecer | Y36: Escoger | Z36: Poner | AA36: Operar | AB36: Clasificar | AC36: Decir | AE36: Compartir | AP36: Medir | AR36: Filtrar | AS36: Instalar | AT36: Comenzar | AU36: Soldar | AV36: Usar | AX36: Provocar | BC36: Informar | BD36: Discriminar | BE36: Ilustrar | BF36: Convocar | BG36: Escoger
L37: Recordar | M37: Revisar | N37: Recoger | P37: Interpretar | Q37: Estimar | S37: Recordar | T37: Revisar | U37: Recoger | W37: Interpretar | X37: Estimar | Y37: Recoger | Z37: Colocar | AA37: Dirigir | AB37: Ordenar | AC37: Apreciar | AE37: Apoyar | AP37: Opinar | AR37: Escoger | AS37: Poner | AT37: Operar | AU37: Clasificar | AV37: Decir | AX37: Compartir | BC37: Interpretar | BD37: Diseñar | BE37: Indicar | BF37: Cooperar | BG37: Estimar
L38: Registrar | M38: Seleccionar | N38: Relacionar | P38: Introducir | Q38: Evaluar | S38: Registrar | T38: Seleccionar | U38: Relacionar | W38: Introducir | X38: Evaluar | Y38: Recaudar | Z38: Inventariar | AA38: Impulsar | AB38: Arreglar | AC38: Distinguir | AE38: Soportar | AP38: Originar | AR38: Recoger | AS38: Colocar | AT38: Dirigir | AU38: Ordenar | AV38: Apreciar | AX38: Apoyar | BC38: Inventariar | BD38: Distinguir | BE38: Interpretar | BF38: Creer | BG38: Estimular
L39: Relacionar | M39: Separar | N39: Reportar | P39: Inventar | Q39: Evaluar | S39: Relacionar | T39: Separar | U39: Reportar | W39: Inventar | X39: Evaluar | Y39: Juntar | Z39: Aislar | AA39: Organizar | AB39: Extender | AC39: Detectar | AP39: Percibir | AR39: Recaudar | AS39: Inventariar | AT39: Impulsar | AU39: Arreglar | AV39: Distinguir | AX39: Soportar | BC39: Localizar | BD39: Dividir | BE39: Investigar | BF39: Cuestionar | BG39: Exteriorizar
L40: Relatar | M40: Traducir | N40: Resolver | P40: Juntar | Q40: Finalizar | S40: Relatar | T40: Traducir | U40: Resolver | W40: Juntar | X40: Finalizar | Y40: Comparar | Z40: Ampliar | AA40: Ordenar | AB40: Ensanchar | AC40: Clasificar | AP40: Persuadir | AR40: Juntar | AS40: Aislar | AT40: Organizar | AU40: Extender | AV40: Detectar | BC40: Mostrar | BD40: Dramatizar | BE40: Listar | BF40: Cuidar | BG40: Extraer
L41: Reproducir | M41: Transformar | N41: Transferir | P41: Manipular | Q41: Formar | S41: Reproducir | T41: Transformar | U41: Transferir | W41: Manipular | X41: Formar | Y41: Cotejar | AA41: Revisar | AB41: Preguntar | AP41: Premiar | AR41: Comparar | AS41: Ampliar | AT41: Ordenar | AU41: Ensanchar | AV41: Clasificar | BC41: Narrar | BD41: Duplicar | BE41: Manipular | BF41: Cumplir | BG41: Formular
L42: Revisar | M42: Ubicar | N42: Usar | P42: Mejorar | Q42: Justificar | S42: Revisar | T42: Ubicar | U42: Usar | W42: Mejorar | X42: Justificar | Y42: Conducir | AA42: Repasar | AB42: Mover | AP42: Probar | AR42: Cotejar | AT42: Revisar | AU42: Preguntar | BC42: Observar | BD42: Elegir | BE42: Modelar | BF42: Defender | BG42: Identificar
L43: Rotular | N43: Valorar | P43: Modificar | Q43: Juzgar | S43: Rotular | U43: Valorar | W43: Modificar | X43: Juzgar | Y43: Direccionar | AA43: Empaquetar | AB43: Balancear | AP43: Recomendar | AR43: Conducir | AT43: Repasar | AU43: Mover | BC43: Predecir | BD43: Emparejar | BE43: Operar | BF43: Definir | BG43: Juzgar
L44: Seleccionar | P44: Numerar | Q44: Marcar | S44: Seleccionar | W44: Numerar | X44: Marcar | Y44: Inspeccionar | AA44: Envasar | AB44: Reconocer | AP44: Seleccionar | AR44: Direccionar | AT44: Empaquetar | AU44: Balancear | BC44: Preguntar | BD44: Emplear | BE44: Organizar | BF44: Desplegar | BG44: Negociar
L45: Subrayar | P45: Obtener | Q45: Marcar | S45: Subrayar | W45: Obtener | X45: Marcar | Y45: Coordinar | AA45: Pintar | AB45: Inspeccionar | AP45: Testar | AR45: Inspeccionar | AT45: Envasar | AU45: Reconocer | BC45: Presentar | BD45: Encontrar | BE45: Patronar | BF45: Determinar | BG45: Ofrecer
P46: Ordenar | Q46: Medir | W46: Ordenar | X46: Medir | Y46: Cortar | AA46: Realizar | AB46: Diseñar | AP46: Valorar | AR46: Coordinar | AT46: Pintar | AU46: Inspeccionar | BC46: Relacionar | BD46: Encuestar | BE46: Planear | BF46: Discernir | BG46: Participar
P47: Organizar | Q47: Modificar | W47: Organizar | X47: Modificar | Y47: Recortar | AA47: Hacer | AB47: Sincronizar | AR47: Cortar | AT47: Realizar | AU47: Diseñar | BC47: Relatar | BD47: Esquematizar | BE47: Practicar | BF47: Discriminar | BG47: Percibir
P48: Organizar | Q48: Numerar | W48: Organizar | X48: Numerar | Y48: Bailar | AA48: Ejecutar | AB48: Verificar | AR48: Recortar | AT48: Hacer | AU48: Sincronizar | BC48: Reportar | BD48: Establecer | BE48: Recoger | BF48: Distinguir | BG48: Preguntar
P49: Perfeccionar | Q49: Peritar | W49: Perfeccionar | X49: Peritar | Y49: Demostrar | AA49: Cumplir | AB49: Validar | AR49: Bailar | AT49: Ejecutar | AU49: Verificar | BC49: Resumir | BD49: Estimar | BE49: Relacionar | BF49: Ejercer | BG49: Promover
P50: Planear | Q50: Predecir | W50: Planear | X50: Predecir | Y50: Detectar | AA50: Actuar | AB50: Revisar | AR50: Demostrar | AT50: Cumplir | AU50: Validar | BC50: Revisar | BD50: Estructurar | BE50: Reportar | BF50: Elegir | BG50: Proponer
P51: Planificar | Q51: Pronosticar | W51: Planificar | X51: Pronosticar | Y51: Señalar | AA51: Ejercer | AB51: Probar | AR51: Detectar | AT51: Actuar | AU51: Revisar | BC51: Seleccionar | BD51: Evaluar | BE51: Resolver | BF51: Ensamblar | BG51: Proporcionar
P52: Poner | Q52: Recomendar | W52: Poner | X52: Recomendar | Y52: Probar | AA52: Interpretar | AB52: Difundir | AR52: Señalar | AT52: Elaborar | AU52: Probar | BC52: Separar | BD52: Examinar | BE52: Resumir | BF52: Entregar | BG52: Provocar
P53: Predecir | Q53: Repartir | W53: Predecir | X53: Repartir | AA53: Tocar | AB53: Transmitir | AR53: Probar | AT53: Interpretar | AU53: Difundir | BC53: Traducir | BD53: Experimentar | BE53: Seleccionar | BF53: Escoger | BG53: Reconocer
P54: Preparar | Q54: Resolver | W54: Preparar | X54: Resolver | AA54: Representar | AB54: Resolver | AT54: Tocar | AU54: Transmitir | BC54: Transformar | BD54: Ilustrar | BE54: Simular | BF54: Estimar | BG54: Relacionar
P55: Producir | Q55: Reunir | W55: Producir | X55: Reunir | AA55: Practicar | AB55: Tapizar | AT55: Representar | AU55: Resolver | BC55: Ubicar | BD55: Indicar | BE55: Transferir | BF55: Estimular | BG55: Resumir
P56: Proponer | Q56: Revisar | W56: Proponer | X56: Revisar | AA56: Entrenar | AB56: Usar | AT56: Practicar | AU56: Tapizar | BD56: Inferir | BE56: Unir | BF56: Exteriorizar | BG56: Seleccionar
P57: Proyectar | Q57: Seleccionar | W57: Proyectar | X57: Seleccionar | AA57: Grabar | AB57: Emplear | AT57: Entrenar | AU57: Usar | BD57: Inspeccionar | BE57: Usar | BF57: Extraer | BG57: Ser partidario de
P58: Resolver | Q58: Sistematizar | W58: Resolver | X58: Sistematizar | AA58: Sacar | AB58: Utilizar | AT58: Grabar | AU58: Emplear | BD58: Interpretar | BF58: Fomentar | BG58: Unir
P59: Reunir | Q59: Sugerir | W59: Reunir | X59: Sugerir | AA59: Imprimir | AB59: Ponderar | AT59: Sacar | AU59: Utilizar | BD59: Inventariar | BF59: Formular | BG59: Valorar
P60: Señalar | Q60: Tasar | W60: Señalar | X60: Tasar | AA60: Estampar | AB60: Mecanizar | AT60: Imprimir | AU60: Ponderar | BD60: Investigar | BF60: Identificar
P61: Simplificar | Q61: Terminar | W61: Simplificar | X61: Terminar | AA61: Extraer | AB61: Industrializar | AT61: Estampar | AU61: Mecanizar | BD61: Listar | BF61: Juzgar
P62: Subdividir | Q62: Unir | W62: Subdividir | X62: Unir | AA62: Producir | AB62: Codificar | AT62: Extraer | AU62: Industrializar | BD62: Manipular | BF62: Negociar
P63: Suponer | Q63: Validar | W63: Suponer | X63: Validar | AA63: Fabricar | AB63: Desarrollar | AT63: Producir | AU63: Codificar | BD63: Medir | BF63: Ofrecer
Q64: Valorar | X64: Valorar | AA64: Presentar | AT64: Fabricar | BD64: Modelar | BF64: Participar
Q65: Verificar | X65: Verificar | AA65: Cortar | AT65: Presentar | BD65: Motivar | BF65: Percibir
Q66: Vincular | X66: Vincular | AA66: Reducir | AT66: Cortar | BD66: Observar | BF66: Preguntar
X67: Diagnosticar | AA67: Mitigar | AT67: Reducir | BD67: Operar | BF67: Preocuparse de o por
AA68: Emitir | AT68: Mitigar | BD68: Ordenar | BF68: Promover
AA69: Elaborar | AT69: Emitir | BD69: Organizar | BF69: Proponer
AT70: Elaborar | BD70: Patronar | BF70: Proporcionar
BD71: Planear | BF71: Proteger
BD72: Practicar | BF72: Provocar
BD73: Preguntar | BF73: Ratificar
BD74: Priorizar | BF74: Reconocer
BD75: Probar | BF75: Relacionar
BD76: Razonar | BF76: Relatar
BD77: Recoger | BF77: Resumir
BD78: Reconocer | BF78: Revelar
BD79: Relacionar | BF79: Seleccionar
BD80: Reorganizar | BF80: Ser partidario de
BD81: Reportar | BF81: Servir
BD82: Resaltar | BF82: Soportar
... BD88: Usar | BF88: Establecer
BF89: Interpretar
