Workbook
Name ActitudinalBAK: 'Taxonomias para RA'!$AC$3:$AG$3
Name Bloom: 'Taxonomias para RA'!$G$3:$I$3
Name Circutos: 'Paso 2 Redacción competen'!$F$4
Name CognitivoBAK: 'Taxonomias para RA'!$S$3:$X$3
Name CompetenciaEspecifica1: 'Paso 2 Redacción competen'!$F$4
Name ComponentesCompetencias: #REF!
Name ComponentesCompetencias: 'Paso1 Analisis perfil egreso'!$E$2:$G$2
Name Creditos: #REF!,#REF!,#REF!,#REF!,#REF!,#REF!,#REF!,#REF!,#REF!
Name FACULTADES: #REF!
Name ProcedimentalBAK: 'Taxonomias para RA'!$Y$3:$AB$3
Name RA: 'Paso 5 Estrategias micro'!$B$10
Name RA: #REF!
Name resultadoaprendizaje: #REF!
Name resultadoaprendizaje: #REF!
Name Saber: 'Paso1 Analisis perfil egreso'!$E$3:$E$9
Name SaberHacer: 'Paso1 Analisis perfil egreso'!$F$3:$F$9
Name SaberSer: 'Paso1 Analisis perfil egreso'!$G$3:$G$9
Name TIC: 'Paso 2 Redacción competen'!$F$9

Sheet Paso1 Analisis perfil egreso
A1: [Escribir el nombre del programa] | B1: [Escribir la modalidad: presencial o virtual] | C1: [Escribir el perfil profesional del egresado.] | D1: [Escribir el perfil ocupacional del egresado.] | E1: Componentes fundamentales aplicables a la solución de problemas en la vida profesional [Listar, según lo escrito en el perfil profesional, qué debe saber el egresado en las categorías de Saber -conocimientos, hechos, teorías-, Saber hacer -técnicas, procedimientos, metodologías-, y Saber ser -valores, condiciones, etc.] | H1: Componentes fundamentales de la ocupación laboral del profesional [Listar, según lo escrito en el perfil ocupacional, en qué áreas, qué tareas potenciales y en qué poblaciones o contextos podrá laborar el profesional.] | K1: Diferencial (valor agregado) del profesional [Listar, según lo escrito en los perfiles, los elementos que son diferenciales y generan un valor agregado al egresado.]
A2: Programa | B2: Modalidad | C2: Perfil profesional | D2: Perfil ocupacional | E2: Saber | F2: SaberHacer | G2: SaberSer | H2: Áreas profesionales | I2: Tareas profesionales | J2: Poblaciones actuación | K2: Valor agregado
A3: Derecho | B3: Virtual | C3: El egresado del programa de Derecho del Politécnico Grancolombiano actúa con perspectiva crítica, analítica, argumentativa e interdisciplinar en cada una de las áreas del ejercicio profesional del abogado; es competitivo, eficiente, tiene habilidades para la negociación, la conciliación y la resolución de conflictos; apropia la responsabilidad social y desarrolla sus conocimientos con ética profesional. Cuenta con capacidad para comprender, abordar y dar soluciones jurídicas a los desafíos de la sociedad y de las organizaciones tanto públicas como privadas, desempeñándose en cargos de dirección y gestión, brindando asesoría y consultoría o ejerciendo funciones de investigación en materia jurídica a nivel nacional e internacional. | D3: El abogado Grancolombiano está capacitado para actuar con criterio ético, competitividad y eficiencia dentro de múltiples ámbitos del ejercicio profesional, desempeñándose en campos de asesoría y consultoría jurídica y organizacional a nivel público y privado; cargos de dirección y gestión de organizaciones empresariales; funciones de investigación en materia socio jurídica y empresarial. Igualmente, podrá actuar como profesional al servicio de la administración de justicia; de instituciones o empresas del sector público y privado; como abogado independiente en cualquier área del Derecho; con orientación hacia la solución alternativa de conflictos; y como docente en áreas del Derecho con particular énfasis por el desarrollo empresarial. | E3: Derecho privado | F3: aplicar los derechos y obligaciones que surgen de relaciones jurídicas entre los particulares, así como buscar su cumplimiento o declaración en escenarios judiciales | G3: de acuerdo con los diferentes instrumentos internacionales, constitucionales, legales y reglamentarios que comprende el derecho civil en escenarios de consulta y litigio | H3: Asesor jurídico en entidades públicas o privadas / Consultor legal corporativo / Oficial de cumplimiento legal y normativo / Consultor en contratación estatal, derecho laboral o tributario / Abogado litigante en áreas civil, penal, laboral, administrativa y comercial / Defensor público / Fiscal o Procurador (previo cumplimiento de requisitos del sistema judicial) / Representante legal en procesos judiciales y extrajudiciales / Coordinador o jefe de asuntos jurídicos / Gerente jurídico en organizaciones empresariales / Director de departamentos legales o unidades normativas / Líder de cumplimiento legal y regulatorio / Funcionario judicial / Servidor público en personerías, defensorías del pueblo, procuradurías y juzgados / Abogado en organismos de control, tribunales o entidades gubernamentales / Asesor legislativo en cuerpos normativos o comisiones / Conciliador extrajudicial en derecho / Mediador o negociador jurídico / Árbitro en procesos civiles y comerciales / Coordinador de proyectos de investigación en derecho, política o ciencias sociales / Analista de política pública y normativa / Docente universitario en áreas del derecho / Abogado en organizaciones internacionales (derechos humanos, comercio, cooperación) / Consultor en proyectos jurídicos internacionales o transnacionales / Defensor de derechos ante cortes internacionales o redes de cooperación. | I3: Elaborar conceptos jurídicos sobre normativas aplicables a casos específicos. / Revisar, redactar y negociar contratos civiles, comerciales y laborales. / Brindar asesoría jurídica a empresas en temas societarios, tributarios o laborales. / Interpretar normas y jurisprudencia para proponer soluciones legales. / Diseñar estrategias legales preventivas para organizaciones públicas y privadas. / Representar clientes en procesos judiciales ante tribunales civiles, penales, laborales y administrativos. / Elaborar demandas, contestaciones, recursos y demás piezas procesales. / Comparecer en audiencias públicas y privadas en calidad de apoderado judicial. / Asesorar jurídicamente a víctimas o imputados en procesos penales. / Ejecutar estrategias de defensa técnica en litigios civiles o comerciales. / Coordinar equipos legales internos en organizaciones empresariales. / Supervisar el cumplimiento normativo de las operaciones jurídicas de la entidad. / Diseñar y aplicar políticas jurídicas internas, manuales y procedimientos legales. / Evaluar riesgos jurídicos en la toma de decisiones estratégicas de la organización. / Representar jurídicamente a empresas ante autoridades administrativas o judiciales. / Apoyar en la elaboración de providencias, autos o sentencias como auxiliar jurídico. / Actuar como secretario de despacho en juzgados o tribunales. / Tramitar expedientes judiciales y dar soporte técnico a jueces o magistrados. / Asesorar jurídicamente a entidades estatales o de control. / Participar en procesos de vigilancia de derechos humanos desde defensorías y personerías. / Participar como conciliador extrajudicial en centros de conciliación. / Redactar acuerdos de conciliación legalmente válidos. / Actuar como facilitador en procesos de negociación privada o institucional. / Diseñar estrategias jurídicas para prevenir y resolver conflictos sin litigio. / Asesorar a partes interesadas en procedimientos de mediación o arbitraje. / Formular problemas jurídicos y estructurar proyectos de investigación. / Analizar fuentes doctrinales, jurisprudenciales y normativas. / Participar en actividades académicas como foros, talleres y simulaciones jurídicas. / Analizar y aplicar normas del derecho internacional público y privado. / Asesorar en materia de derechos humanos, comercio internacional y cooperación jurídica. / Participar en redacción de informes para organismos internacionales. / Apoyar misiones jurídicas internacionales o transnacionales. / Actuar como enlace legal en proyectos binacionales o multilaterales. | J3: Ciudadanos en general que requieren defensa, asesoría o representación legal. / Víctimas o imputados en procesos penales. / Individuos en situaciones de conflicto civil, familiar, laboral o administrativo. / Personas en procesos de conciliación o mediación. / Micro, pequeñas, medianas y grandes empresas. / Organizaciones con actividades comerciales, industriales, tecnológicas o del sector servicios. / Fundaciones y asociaciones sin ánimo de lucro. / Entidades financieras y corporaciones multinacionales. / Alcaldías, gobernaciones y entidades descentralizadas. / Entidades del orden nacional (ministerios, superintendencias, agencias estatales). / Órganos de control (Procuraduría, Contraloría, Defensoría del Pueblo). / Juzgados, tribunales y fiscalías. / Población en situación de pobreza o exclusión social. / Víctimas del conflicto armado interno. / Comunidades étnicas (pueblos indígenas, comunidades afrodescendientes, raizales y ROM). / Personas privadas de la libertad o en procesos de resocialización. / Mujeres víctimas de violencia y personas con discapacidad. / Menores en situación de riesgo o vulneración de derechos. / Sujetos de procesos de adopción, custodia, alimentos o responsabilidad parental. / Víctimas o victimarios en procesos penales de responsabilidad penal juvenil. / Sindicatos, cooperativas, movimientos sociales y colectivos ciudadanos. / Agrupaciones de defensa de derechos humanos o del medio ambiente. / Representaciones legales de barrios, veredas o comunidades rurales. / Asociaciones de víctimas o líderes comunitarios. / Migrantes, refugiados o solicitantes de asilo. / Personas y empresas vinculadas a relaciones jurídicas internacionales. / Instituciones extranjeras que requieren asesoría legal en Colombia. / Población atendida en misiones humanitarias o jurídicas transnacionales. | K3: El programa de Derecho del Politécnico Grancolombiano se distingue por integrar, de forma consistente a lo largo del currículo, contenidos orientados al derecho empresarial, lo que permite a los estudiantes interpretar el entorno organizacional y abordar sus retos jurídicos con criterio normativo y sentido práctico. Esta orientación específica diferencia al programa al incluir temáticas como sociedades, consumo, competencia y derecho corporativo. La estructura curricular incorpora la práctica jurídica desde los consultorios y fomenta una mirada crítica sobre el papel del derecho en la actividad empresarial y su impacto social. Este enfoque brinda al egresado una ventaja formativa en sectores que demandan asesoría jurídica con perspectiva organizacional, donde convergen normatividad, economía y responsabilidad social.
E4: Derecho comercial | F4: asesorar en la generación, modificación o extinción de obligaciones, así como para elaborar contratos de cualquier tipología | G4: de acuerdo con la normatividad colombiana y los estándares internacionales vigentes en planeación, control y administración empresarial
E5: Derecho público | F5: identificar los diferentes instrumentos constitucionales, legales y reglamentarios que comprenden las relaciones con intervención del Estado | G5: de acuerdo con el marco universal de principios y valores propios del Estado Social de Derecho y de la Democracia Participativa, desde una perspectiva social, económica, política y humanista, dentro del contexto nacional e internacional
E6: Derecho penal | F6: asumir y resolver asuntos en pro de la defensa, la acusación o el juzgamiento de conductas punibles, así como la aplicación en cada caso en concreto de los fundamentos del derecho procesal penal | G6: de conformidad con los principios rectores de la actividad penal, como la buena fe, la duda, la presunción de inocencia, y en general la Constitución Política, los fundamentos del Derecho y sus fuentes
E7: Negociación y resolución de conflictos | F7: hacer uso de los diferentes métodos alternativos de solución de conflictos auto y hetero compositivos | G7: de acuerdo con las posibilidades que la ley ofrece, que permiten racionalizar e interpretar los desencuentros que se presentan en las relaciones familiares, sociales, políticas y laborales, así como la toma de conciencia de la existencia y del manejo adecuado de los conflictos
E8: Relaciones de producción desde el ámbito interdisciplinar, según el entorno en el que se desenvuelven los individuos en las organizaciones, empresas o instituciones | F8: comprender los modelos económicos, políticos, laborales y sociales, así como las problemáticas que existen o emergen de estas relaciones | G8: teniendo en cuenta el ordenamiento jurídico colombiano y las políticas económicas
E9: Fenómenos contemporáneos | F9: reconocer sus afectaciones o contribuciones en el marco de las ciudadanías globales y de una sociedad responsable y sostenible | G9: desde una perspectiva global, soportada en datos, con una mirada ética y crítica

Sheet Paso 2 Redacción competen
A1: Elementos para redactar las competencias que desarrollará el programa
A2: [Enumerar las competencias que se van a declarar.] | B2: [A partir de la celda B2 dar clic sobre el ícono de lista desplegable y elegir el verbo que considere adecuado.] | C2: [A partir de la celda C2 dar clic sobre la lista desplegable y elegir el saber extraído del perfil de egreso.] | D2: [Escribir para qué se abordará el saber elegido. Se sugiere apoyarse en el saber hacer.] | E2: [Escribir la condición describiendo los referentes, parámetros, principios, requerimientos o retos que se necesitan para alcanzar las características del perfil en el contexto donde el egresado se desenvolverá.] | F2: [Articular los componentes. Iniciar con el verbo, continuar con el objeto conceptual, luego la finalidad y condición de contexto o referencia; estos últimos no requieren un orden particular.] | G2: [Escribir el tipo de competencia del perfil: Específica (si es del bloque Disciplinar para pregrado o de los componentes para el caso de posgrado) o Genérica (si aplica bloque institucional pregrado)]
A3: No. | B3: Verbo competencia | C3: Objeto conceptual | D3: Finalidad | E3: Condición de contexto o referencia | F3: Redacción competencia | G3: Tipo de competencia
A4: 1 | B4: Dominar | C4: Derecho privado | D4: aplicar los derechos y obligaciones que surgen de relaciones jurídicas entre los particulares, así como buscar su cumplimiento o declaración en escenarios judiciales | E4: de acuerdo con los diferentes instrumentos internacionales, constitucionales, legales y reglamentarios que comprende el derecho civil en escenarios de consulta y litigio | F4: Dominar el derecho privado, para aplicar los derechos y obligaciones que surgen de relaciones jurídicas entre los particulares, así como buscar su cumplimiento o declaración en escenarios judiciales, de acuerdo con los diferentes instrumentos internacionales, constitucionales, legales y reglamentarios que comprende el derecho civil en escenarios de consulta y litigio. | G4: Específica
A5: 2 | B5: Dominar | C5: Derecho comercial | D5: asesorar en la generación, modificación o extinción de obligaciones, así como para elaborar contratos de cualquier tipología | E5: de acuerdo con la normatividad colombiana y los estándares internacionales vigentes en planeación, control y administración empresarial | F5: Dominar el derecho comercial, para asesorar en la generación, modificación o extinción de obligaciones, así como para elaborar contratos de cualquier tipología, de acuerdo con al normatividad colombiana y los estándares internacionales vigentes en planeación, control y administración empresarial. | G5: Específica
A6: 3 | B6: Conocer | C6: Derecho público | D6: identificar los diferentes instrumentos constitucionales, legales y reglamentarios que comprenden las relaciones con intervención del Estado | E6: de acuerdo con el marco universal de principios y valores propios del Estado Social de Derecho y de la Democracia Participativa, desde una perspectiva social, económica, política y humanista, dentro del contexto nacional e internacional | F6: Conocer el derecho público, para identificar los diferentes instrumentos constitucionales, legales y reglamentarios que comprenden las relaciones con intervención del Estado, de acuerdo con el marco universal de principios y valores propios del Estado Social de Derecho y de la Democracia Participativa, desde una perspectiva social, económica, política y humanista, dentro del contexto nacional e internacional. | G6: Específica
A7: 4 | B7: Aplicar | C7: Derecho penal | D7: asumir y resolver asuntos en pro de la defensa, la acusación o el juzgamiento de conductas punibles, así como la aplicación en cada caso en concreto de los fundamentos del derecho procesal penal | E7: de conformidad con los principios rectores de la actividad penal, como la buena fe, la duda, la presunción de inocencia, y en general la Constitución Política, los fundamentos del Derecho y sus fuentes | F7: Aplicar el derecho penal, para asumir y resolver asuntos en pro de la defensa, la acusación o el juzgamiento de conductas punibles, así como la aplicación en cada caso en concreto de los fundamentos del derecho procesal penal, de conformidad con los principios rectores de la actividad penal, como la buena fe, la duda, la presunción de inocencia, y en general la Constitución Política, los fundamentos del Derecho y sus fuentes. | G7: Específica
A8: 5 | B8: Aplicar | C8: Negociación y resolución de conflictos | D8: hacer uso de los diferentes métodos alternativos de solución de conflictos auto y hetero compositivos | E8: de acuerdo con las posibilidades que la ley ofrece, que permiten racionalizar e interpretar los desencuentros que se presentan en las relaciones familiares, sociales, políticas y laborales, así como la toma de conciencia de la existencia y del manejo adecuado de los conflictos | F8: Aplicar las habilidades de negociación y resolución de conflictos para hacer uso de los diferentes métodos alternativos de solución de conflictos auto y hetero compositivos, de acuerdo con las posibilidades que la ley ofrece, que permiten racionalizar e interpretar los desencuentros que se presentan en las relaciones familiares, sociales, políticas y laborales, así como la toma de conciencia de la existencia y del manejo adecuado de los conflictos. | G8: Específica
A9: 6 | B9: Conocer | C9: Relaciones de producción desde el ámbito interdisciplinar, según el entorno en el que se desenvuelven los individuos en las organizaciones, empresas o instituciones | D9: comprender los modelos económicos, políticos, laborales y sociales, así como las problemáticas que existen o emergen de estas relaciones | E9: teniendo en cuenta el ordenamiento jurídico colombiano y las políticas económicas | F9: Conocer los aspectos asociados a las relaciones de producción desde el ámbito interdisciplinar, según el entorno en el que se desenvuelven los individuos en las organizaciones, empresas o instituciones, para comprender los modelos económicos, políticos, laborales y sociales, así como las problemáticas que existen o emergen de estas relaciones, teniendo en cuenta el ordenamiento jurídico colombiano y las políticas económicas. | G9: Específica
A10: 7 | B10: Analizar | C10: Fenómenos contemporáneos | D10: reconocer sus afectaciones o contribuciones en el marco de las ciudadanías globales y de una sociedad responsable y sostenible. | E10: desde una perspectiva global, soportada en datos, con una mirada ética y crítica | F10: Analizar los fenómenos contemporáneos desde una perspectiva glocal, soportada en datos, con una mirada ética y crítica, para reconocer sus afectaciones o contribuciones en el marco de las ciudadanías globales y de una sociedad responsable y sostenible. | G10: Genérica

Sheet Paso 3 Redacción RA
A1: [A partir de la celda A2 dar clic en la lista desplegable y seleccionar la competencia redactada en el paso 2.] | B1: [Enumerar los resultados de aprendizaje que se van a declarar.] | C1: [A partir de la celda C2, dar clic en la lista desplegable y elegir el tipo de dominio a tratar en el resultado de aprendizaje.] | D1: [A partir de la cela D2, dar clic en la lista desplegable y elegir el saber correspondiente al dominio.] | E1: [A partir de la celda E2, dar clic en la lista desplegable y elegir la taxonomía que se considere adecuada, solo se elige una para todos los saberes.] | F1: [A partir de la celda F2, dar clic en la lista desplegable y elegir el dominio que se considera adecuado.] | G1: [A partir de la celda G2, dar clic en la lista desplegable y elegir el nivel del dominio que se considera adecuado.] | H1: [A partir de la celda H2, dar clic en la lista desplegable y elegir el verbo que se considera adecuado.] | I1: [Iniciar con el verbo elegido (columna H), en infinitivo, luego el objeto sobre el cual recae la acción (columna D) y finalmente la condición de contexto (académico, disciplinar, social u otro).]
A2: Competencia por desarrollar | B2: Número de resultado | C2: TipoSaber | D2: SaberAsociado | E2: Taxonomía | F2: Dominio Asociado | G2: Nivel Dominio | H2: Verbo RA | I2: Resultados Aprendizaje
A3: Dominar el derecho privado, para aplicar los derechos y obligaciones que surgen de relaciones jurídicas entre los particulares, así como buscar su cumplimiento o declaración en escenarios judiciales, de acuerdo con los diferentes instrumentos internacionales, constitucionales, legales y reglamentarios que comprende el derecho civil en escenarios de consulta y litigio. | B3: 1 | C3: Saber | D3: Derecho privado | E3: Bloom | F3: CognitivoB | G3: AnálisisB | H3: Reconocer | I3: Reconoce los fundamentos del derecho penal, comercial, público, laboral y privado para determinar el procedimiento a seguir en la resolución de conflictos o de actos jurídicos, observando los principios rectores de cada actividad y atendiendo a la legislación y normatividad vigente, que permitan generar acciones positivas y acordes a las necesidades de los individuos o las organizaciones, según sea el caso.
A4: Dominar el derecho privado, para aplicar los derechos y obligaciones que surgen de relaciones jurídicas entre los particulares, así como buscar su cumplimiento o declaración en escenarios judiciales, de acuerdo con los diferentes instrumentos internacionales, constitucionales, legales y reglamentarios que comprende el derecho civil en escenarios de consulta y litigio. | B4: 3 | C4: SaberHacer | D4: aplicar los derechos y obligaciones que surgen de relaciones jurídicas entre los particulares, así como buscar su cumplimiento o declaración en escenarios judiciales | E4: Bloom | F4: ProcedimentalB | G4: AplicaciónB | H4: Aplicar | I4: Aplica el derecho privado, atendiendo la legislación y normatividad vigente, para dar solución a casos concretos.
A5: Dominar el derecho privado, para aplicar los derechos y obligaciones que surgen de relaciones jurídicas entre los particulares, así como buscar su cumplimiento o declaración en escenarios judiciales, de acuerdo con los diferentes instrumentos internacionales, constitucionales, legales y reglamentarios que comprende el derecho civil en escenarios de consulta y litigio. | B5: 9 | C5: SaberSer | D5: de acuerdo con los diferentes instrumentos internacionales, constitucionales, legales y reglamentarios que comprende el derecho civil en escenarios de consulta y litigio | E5: Bloom | F5: ActitudinalB | G5: AnálisisB | H5: Reconocer | I5: Reconoce los principios éticos del derecho para implementarlos en su conducta y ejercicio profesional, atendiendo a los casos que llegan a su conocimiento en escenarios nacionales e internacionales.
A6: Dominar el derecho comercial, para asesorar en la generación, modificación o extinción de obligaciones, así como para elaborar contratos de cualquier tipología, de acuerdo con al normatividad colombiana y los estándares internacionales vigentes en planeación, control y administración empresarial. | B6: 1 | C6: Saber | D6: Derecho comercial | E6: Bloom | F6: CognitivoB | G6: AnálisisB | H6: Reconocer | I6: Reconoce los fundamentos del derecho penal, comercial, público, laboral y privado para determinar el procedimiento a seguir en la resolución de conflictos o de actos jurídicos, observando los principios rectores de cada actividad y atendiendo a la legislación y normatividad vigente, que permitan generar acciones positivas y acordes a las necesidades de los individuos o las organizaciones, según sea el caso.
A7: Dominar el derecho comercial, para asesorar en la generación, modificación o extinción de obligaciones, así como para elaborar contratos de cualquier tipología, de acuerdo con al normatividad colombiana y los estándares internacionales vigentes en planeación, control y administración empresarial. | B7: 4 | C7: SaberHacer | D7: asesorar en la generación, modificación o extinción de obligaciones, así como para elaborar contratos de cualquier tipología | E7: Bloom | F7: ProcedimentalB | G7: AplicaciónB | H7: Aplicar | I7: Aplica el régimen de las obligaciones y los contratos comerciales de cualquier tipología, nacional e internacional, atendiendo a las necesidades que se derivan de las relaciones comerciales entorno a su nacimiento, modificación y extinción, para adelantar los procesos jurídicos que correspondan al caso.
A8: Dominar el derecho comercial, para asesorar en la generación, modificación o extinción de obligaciones, así como para elaborar contratos de cualquier tipología, de acuerdo con al normatividad colombiana y los estándares internacionales vigentes en planeación, control y administración empresarial. | B8: 9 | C8: SaberSer | D8: de acuerdo con la normatividad colombiana y los estándares internacionales vigentes en planeación, control y administración empresarial | E8: Bloom | F8: ActitudinalB | G8: AnálisisB | H8: Reconocer | I8: Reconoce los principios éticos del derecho para implementarlos en su conducta y ejercicio profesional, atendiendo a los casos que llegan a su conocimiento en escenarios nacionales e internacionales.
A9: Conocer el derecho público, para identificar los diferentes instrumentos constitucionales, legales y reglamentarios que comprenden las relaciones con intervención del Estado, de acuerdo con el marco universal de principios y valores propios del Estado Social de Derecho y de la Democracia Participativa, desde una perspectiva social, económica, política y humanista, dentro del contexto nacional e internacional. | B9: 2 | C9: Saber | D9: Derecho público | E9: Bloom | F9: CognitivoB | G9: ComprensiónB | H9: Identificar | I9: Identifica los elementos característicos de la negociación y resolución de conflictos para caracterizar la información y argumentación requerida en los procesos de acuerdos, transacciones o laudos arbitrales que den por terminados los conflictos puestos a su conocimiento.
A10: Conocer el derecho público, para identificar los diferentes instrumentos constitucionales, legales y reglamentarios que comprenden las relaciones con intervención del Estado, de acuerdo con el marco universal de principios y valores propios del Estado Social de Derecho y de la Democracia Participativa, desde una perspectiva social, económica, política y humanista, dentro del contexto nacional e internacional. | B10: 5 | C10: SaberHacer | D10: identificar los diferentes instrumentos constitucionales, legales y reglamentarios que comprenden las relaciones con intervención del Estado | E10: Bloom | F10: ProcedimentalB | G10: AplicaciónB | H10: Aplicar | I10: Aplica las acciones administrativas y judiciales procedentes del derecho público para proyectar procesos jurídicos que garanticen el reconocimiento y la protección de los derechos de las personas.
A11: Conocer el derecho público, para identificar los diferentes instrumentos constitucionales, legales y reglamentarios que comprenden las relaciones con intervención del Estado, de acuerdo con el marco universal de principios y valores propios del Estado Social de Derecho y de la Democracia Participativa, desde una perspectiva social, económica, política y humanista, dentro del contexto nacional e internacional. | B11: 9 | C11: SaberSer | D11: de acuerdo con el marco universal de principios y valores propios del Estado Social de Derecho y de la Democracia Participativa, desde una perspectiva social, económica, política y humanista, dentro del contexto nacional e internacional | E11: Bloom | F11: ActitudinalB | G11: AnálisisB | H11: Reconocer | I11: Reconoce los principios éticos del derecho para implementarlos en su conducta y ejercicio profesional, atendiendo a los casos que llegan a su conocimiento en escenarios nacionales e internacionales.
A12: Aplicar el derecho penal, para asumir y resolver asuntos en pro de la defensa, la acusación o el juzgamiento de conductas punibles, así como la aplicación en cada caso en concreto de los fundamentos del derecho procesal penal, de conformidad con los principios rectores de la actividad penal, como la buena fe, la duda, la presunción de inocencia, y en general la Constitución Política, los fundamentos del Derecho y sus fuentes. | B12: 1 | C12: Saber | D12: Derecho penal | E12: Bloom | F12: CognitivoB | G12: AnálisisB | H12: Reconocer | I12: Reconoce los fundamentos del derecho penal, comercial, público, laboral y privado para determinar el procedimiento a seguir en la resolución de conflictos o de actos jurídicos, observando los principios rectores de cada actividad y atendiendo a la legislación y normatividad vigente, que permitan generar acciones positivas y acordes a las necesidades de los individuos o las organizaciones, según sea el caso.
A13: Aplicar el derecho penal, para asumir y resolver asuntos en pro de la defensa, la acusación o el juzgamiento de conductas punibles, así como la aplicación en cada caso en concreto de los fundamentos del derecho procesal penal, de conformidad con los principios rectores de la actividad penal, como la buena fe, la duda, la presunción de inocencia, y en general la Constitución Política, los fundamentos del Derecho y sus fuentes. | B13: 6 | C13: SaberHacer | D13: asumir y resolver asuntos en pro de la defensa, la acusación o el juzgamiento de conductas punibles, así como la aplicación en cada caso en concreto de los fundamentos del derecho procesal penal | E13: Bloom | F13: ProcedimentalB | G13: AplicaciónB | H13: Aplicar | I13: Aplica el derecho penal en el procedimiento y la acción procedente en atención al tipo penal identificado para adelantar los procesos jurídicos que correspondan al caso.
A14: Aplicar el derecho penal, para asumir y resolver asuntos en pro de la defensa, la acusación o el juzgamiento de conductas punibles, así como la aplicación en cada caso en concreto de los fundamentos del derecho procesal penal, de conformidad con los principios rectores de la actividad penal, como la buena fe, la duda, la presunción de inocencia, y en general la Constitución Política, los fundamentos del Derecho y sus fuentes. | B14: 9 | C14: SaberSer | D14: de conformidad con los principios rectores de la actividad penal, como la buena fe, la duda, la presunción de inocencia, y en general la Constitución Política, los fundamentos del Derecho y sus fuentes | E14: Bloom | F14: ActitudinalB | G14: AnálisisB | H14: Reconocer | I14: Reconoce los principios éticos del derecho para implementarlos en su conducta y ejercicio profesional, atendiendo a los casos que llegan a su conocimiento en escenarios nacionales e internacionales.
... A21: Analizar los fenómenos contemporáneos desde una perspectiva glocal, soportada en datos, con una mirada ética y crítica, para reconocer sus afectaciones o contribuciones en el marco de las ciudadanías globales y de una sociedad responsable y sostenible. | B21: 2 | C21: Saber | D21: Fenómenos contemporáneos | E21: Bloom | F21: CognitivoB | G21: ComprensiónB | H21: Identificar | I21: Identifica fenómenos contemporáneos y su relación con la profesión, para determinar sus impactos e influencia en la sociedad, de forma responsable y crítica.

Sheet Paso 3 Redacción RA - Backup 
A1: [A partir de la celda A2 dar clic en la lista desplegable y seleccionar la competencia redactada en el paso 2.] | B1: [Enumerar los resultados de aprendizaje que se van a declarar.] | C1: [A partir de la celda C2, dar clic en la lista desplegable y elegir el tipo de dominio a tratar en el resultado de aprendizaje.] | D1: [A partir de la cela D2, dar clic en la lista desplegable y elegir el saber correspondiente al dominio.] | E1: [A partir de la celda E2, dar clic en la lista desplegable y elegir la taxonomía que se considere adecuada, solo se elige una para todos los saberes.] | F1: [A partir de la celda F2, dar clic en la lista desplegable y elegir el dominio que se considera adecuado.] | G1: [A partir de la celda G2, dar clic en la lista desplegable y elegir el nivel del dominio que se considera adecuado.] | H1: [A partir de la celda H2, dar clic en la lista desplegable y elegir el verbo que se considera adecuado.] | I1: [Iniciar con el verbo elegido (columna H), en infinitivo, luego el objeto sobre el cual recae la acción (columna D) y finalmente la condición de contexto (académico, disciplinar, social u otro).]
A2: Competencia por desarrollar | B2: Número de resultado | C2: TipoSaber | D2: SaberAsociado | E2: Taxonomía | F2: Dominio Asociado | G2: Nivel Dominio | H2: Verbo RA | I2: Resultados Aprendizaje
A3: Dominar los elementos de teoría de circuitos y transmisión de información para diseñar, implementar o administrar la infraestructura eléctrica y los dispositivos electrónicos que dan soporte a los sistemas de telecomunicaciones alineado con prácticas basadas en estándares del sector y la normatividad vigente, teniendo en cuenta las condiciones, restricciones y requerimientos técnicos del entorno. | B3: 1 | C3: Saber | D3: los elementos de teoría de circuitos y transmisión de información | E3: BAK | F3: CognitivoBAK | G3: ComprensiónBAK | H3: Identificar | I3: Identifica los elementos de teoría de circuitos, de transmisión de información, de seguridad de la información, de redes de comunicaciones, de sistemas de cómputo, de estandares y marcos de referencia que hacen parte de la gestión de proyectos como del desarrollo de actividades relacionadas a las infraestructuras de TIC, para explicar soluciones de diseño, administración o implementación a problemáticas del sector, desde un abordaje teórico-práctico, a través de herramientas de simulación, análisis de casos prácticos y uso de equipos de laboratorio.
A4: Dominar los elementos de teoría de circuitos y transmisión de información para diseñar, implementar o administrar la infraestructura eléctrica y los dispositivos electrónicos que dan soporte a los sistemas de telecomunicaciones alineado con prácticas basadas en estándares del sector y la normatividad vigente, teniendo en cuenta las condiciones, restricciones y requerimientos técnicos del entorno. | B4: 4 | C4: SaberHacer | D4: para diseñar, implementar o administrar la infraestructura eléctrica y los dispositivos electrónicos que dan soporte a los sistemas de telecomunicaciones | E4: BAK | F4: ProcedimentalBAK | G4: ManipulaciónBAK | H4: Aplicar | I4: Aplica los elementos de teoría de circuitos, de transmisión de información, de seguridad de la información, de redes de comunicaciones, de sistemas de cómputo, de estandares tecnológicos y marcos de referencia que hacen parte de la gestión de proyectos como del desarrollo de actividades relacionadas a las infraestructuras de TIC, para construir propuestas de diseño, implementación o administración de infraestructura eléctrica, dispositivos electrónicos, servicios de comunicaciones en nube o en sitio, sistemas de telecomunicaciones, a través de herramientas de simulación, análisis de casos prácticos y uso de equipos de laboratorio.
A5: Dominar los elementos de teoría de circuitos y transmisión de información para diseñar, implementar o administrar la infraestructura eléctrica y los dispositivos electrónicos que dan soporte a los sistemas de telecomunicaciones alineado con prácticas basadas en estándares del sector y la normatividad vigente, teniendo en cuenta las condiciones, restricciones y requerimientos técnicos del entorno. | B5: 7 | C5: SaberSer | D5: alineado con prácticas basadas en estándares del sector y la normatividad vigente, teniendo en cuenta las condiciones, restricciones y requerimientos técnicos del entorno. | E5: BAK | F5: ActitudinalBAK | G5: ValorarBAK | H5: Emplear | I5: Emplea las buenas prácticas de teoría de circuitos y transmisión, y de seguridad de la información, redes y sistemas de cómputo basadas en estándares del sector y la normatividad vigente, teniendo en cuenta las condiciones, restricciones y requerimientos técnicos de un proyecto, para formular soluciones en infraestructuras TIC o del área de las telecomunicaciones.
A6: Dominar los elementos de seguridad de la información, redes de comunicaciones y sistemas de cómputo que hacen parte de infraestructuras TIC para diseñar, implementar o administrar infraestructuras y servicios de comunicaciones en sitio o en nube alineado con prácticas basadas en estándares del sector y la normatividad vigente, teniendo en cuenta las condiciones, restricciones y requerimientos técnicos del entorno. | B6: 1 | C6: Saber | D6: los elementos de seguridad de la información, redes de comunicaciones y sistemas de cómputo que hacen parte de infraestructuras TIC | E6: BAK | F6: CognitivoBAK | G6: ComprensiónBAK | H6: Identificar | I6: Identifica los elementos de teoría de circuitos, de transmisión de información, de seguridad de la información, de redes de comunicaciones, de sistemas de cómputo, de estandares y marcos de referencia que hacen parte de la gestión de proyectos como del desarrollo de actividades relacionadas a las infraestructuras de TIC, para evaluar soluciones a problemáticas del sector, desde un abordaje teórico-práctico, a través de herramientas de simulación, análisis de casos prácticos y uso de equipos de laboratorio.
A7: Dominar los elementos de seguridad de la información, redes de comunicaciones y sistemas de cómputo que hacen parte de infraestructuras TIC para diseñar, implementar o administrar infraestructuras y servicios de comunicaciones en sitio o en nube alineado con prácticas basadas en estándares del sector y la normatividad vigente, teniendo en cuenta las condiciones, restricciones y requerimientos técnicos del entorno. | B7: 5 | C7: SaberHacer | D7: para diseñar, implementar o administrar infraestructuras y servicios de comunicaciones en sitio o en nube | E7: BAK | F7: ProcedimentalBAK | G7: ManipulaciónBAK | H7: Aplicar | I7: Aplica los elementos de teoría de circuitos, de transmisión de información, de seguridad de la información, de redes de comunicaciones, de sistemas de cómputo, de estandares tecnológicos y marcos de referencia que hacen parte de la gestión de proyectos como del desarrollo de actividades relacionadas a las infraestructuras de TIC, para construir propuestas de diseño, implementación o administración de infraestructura eléctrica, dispositivos electrónicos, servicios de comunicaciones en nube o en sitio, sistemas de telecomunicaciones, a través de herramientas de simulación, análisis de casos prácticos y uso de equipos de laboratorio.
A8: Dominar los elementos de seguridad de la información, redes de comunicaciones y sistemas de cómputo que hacen parte de infraestructuras TIC para diseñar, implementar o administrar infraestructuras y servicios de comunicaciones en sitio o en nube alineado con prácticas basadas en estándares del sector y la normatividad vigente, teniendo en cuenta las condiciones, restricciones y requerimientos técnicos del entorno. | B8: 7 | C8: SaberSer | D8: alineado con prácticas basadas en estándares del sector y la normatividad vigente, teniendo en cuenta las condiciones, restricciones y requerimientos técnicos del entorno. | E8: BAK | F8: ActitudinalBAK | G8: ValorarBAK | H8: Emplear | I8: Emplea las buenas prácticas de teoría de circuitos y transmisión, y de seguridad de la información, redes y sistemas de cómputo basadas en estándares del sector y la normatividad vigente, teniendo en cuenta las condiciones, restricciones y requerimientos técnicos de un proyecto, para formular soluciones en infraestructuras TIC o del área de las telecomunicaciones.
A9: Conocer los estándares y marcos de referencia asociados tanto a la gestión de proyectos como al desarrollo de actividades relacionadas a las tecnologías de la información para diseñar, implementar o administrar soluciones del área de las telecomunicaciones, la seguridad de la información y la infraestructura TIC manteniendo una postura socialmente responsable, autónoma, teniendo en cuenta las condiciones, restricciones y requerimientos técnicos del entorno. | B9: 2 | C9: Saber | D9: los estándares y marcos de referencia asociados tanto a la gestión de proyectos como al desarrollo de actividades relacionadas a las tecnologías de la información | E9: BAK | F9: CognitivoBAK | G9: ComprensiónBAK | H9: Identificar | I9: Identifica los elementos de teoría de circuitos, de transmisión de información, de seguridad de la información, de redes de comunicaciones, de sistemas de cómputo, de estandares y marcos de referencia que hacen parte de la gestión de proyectos como del desarrollo de actividades relacionadas a las infraestructuras de TIC, para evaluar soluciones a problemáticas del sector, desde un abordaje teórico-práctico, a través de herramientas de simulación, análisis de casos prácticos y uso de equipos de laboratorio.
A10: Conocer los estándares y marcos de referencia asociados tanto a la gestión de proyectos como al desarrollo de actividades relacionadas a las tecnologías de la información para diseñar, implementar o administrar soluciones del área de las telecomunicaciones, la seguridad de la información y la infraestructura TIC manteniendo una postura socialmente responsable, autónoma, teniendo en cuenta las condiciones, restricciones y requerimientos técnicos del entorno. | B10: 6 | C10: SaberHacer | D10: para diseñar, implementar o administrar soluciones del área de las telecomunicaciones, la seguridad de la información y la infraestructura TIC | E10: BAK | F10: ProcedimentalBAK | G10: ManipulaciónBAK | H10: Aplicar | I10: Aplica los elementos de teoría de circuitos, de transmisión de información, de seguridad de la información, de redes de comunicaciones, de sistemas de cómputo, de estandares tecnológicos y marcos de referencia que hacen parte de la gestión de proyectos como del desarrollo de actividades relacionadas a las infraestructuras de TIC, para construir propuestas de diseño, implementación o administración de infraestructura eléctrica, dispositivos electrónicos, servicios de comunicaciones en nube o en sitio, sistemas de telecomunicaciones, a través de herramientas de simulación, análisis de casos prácticos y uso de equipos de laboratorio.
A11: Conocer los estándares y marcos de referencia asociados tanto a la gestión de proyectos como al desarrollo de actividades relacionadas a las tecnologías de la información para diseñar, implementar o administrar soluciones del área de las telecomunicaciones, la seguridad de la información y la infraestructura TIC manteniendo una postura socialmente responsable, autónoma, teniendo en cuenta las condiciones, restricciones y requerimientos técnicos del entorno. | B11: 7 | C11: SaberSer | D11: manteniendo una postura socialmente responsable, autónoma, teniendo en cuenta las condiciones, restricciones y requerimientos técnicos del entorno. | E11: BAK | F11: ActitudinalBAK | G11: ValorarBAK | H11: Emplear | I11: Emplea las buenas prácticas de teoría de circuitos y transmisión, y de seguridad de la información, redes y sistemas de cómputo basadas en estándares del sector y la normatividad vigente, teniendo en cuenta las condiciones, restricciones y requerimientos técnicos de un proyecto, para formular soluciones en infraestructuras TIC o del área de las telecomunicaciones.
A12: Analizar los fenómenos contemporáneos desde una perspectiva glocal, soportada en datos, con una mirada ética y crítica, para reconocer sus afectaciones o contribuciones en el marco de las ciudadanías globales y de una sociedad responsable y sostenible. | B12: 3 | C12: Saber | D12: Fenómenos contemporáneos | E12: Bloom | F12: CognitivoB | G12: ComprensiónB | H12: Identificar | I12: Identifica fenómenos contemporáneos y su relación con la profesión, para determinar sus impactos e influencia en la sociedad, de forma responsable y crítica.

Sheet Paso 4 Estrategias mesocurricu
A1: [A partir de la celda A3 despliegue el(los) resultado(s) de aprendizaje y elegir aquel (aquellos) al(a los) que se contribuye desde la estrategia.] | B1: [Escribir el nombre de la estrategia a desarrollar. Participación de los estudiantes en cursos, talleres, seminarios, conferencias, pruebas estandarizadas, investigaciones, actividades o experiencias, cuerpos académicos, redes, comunidades, la elaboración de textos y materiales, así como las publicaciones, entre otros.] | C1: [Describir la(s) estrategia(s) definidas por el programa.] | D1: [Escribir los indicadores de impacto de la estrategia. Se sugieren indicadores como: Valora el nivel de contribución de la estrategia a los resultados de aprendizaje; Número de estudiantes que participan en la estrategia; Número de veces que se realiza la estrategia, entre otros.] | E1: [Escribir las acciones de retroalimentación que usará el programa para comunicar a los estudiantes sobre el alcance de sus resultados de aprendizaje.] | F1: [Escribir, para cada indicador con qué instrumento se recogerá información para evidenciar el (los) impacto (s) declarados. Encuesta, lista de asistencia, informe, entre otros.]
A2: Resultado de aprendizaje | B2: Estrategia del programa | C2: Descripción | D2: Indicador de Impacto de la Estrategia | E2: Acciones de retroalimentación para los estudiantes | F2: Instrumentos de medición
A3: Reconoce los fundamentos del derecho penal, comercial, público, laboral y privado para determinar el procedimiento a seguir en la resolución de conflictos o de actos jurídicos, observando los principios rectores de cada actividad y atendiendo a la legislación y normatividad vigente, que permitan generar acciones positivas y acordes a las necesidades de los individuos o las organizaciones, según sea el caso. | B3: Seminario Internacional | C3: Los estudiantes con un avance en su plan de estudios superior al 70% podrán optar por un seminario internacional en el que al finalizar entregaran un artículo científico que se sustentará ante jurado, demostrando la identificación de un problema jurídico y la solución del mismo en uso de las diferentes fuentes del derecho. | D3: Valoración de la contribución de la estrategia a los resultados de aprendizaje del programa en una escala de Likert. | E3: Informar y formar sobre los temas de tendencia de manera que se contribuya al desarrollo formativo de los estudiantes. | F3: Encuesta.
A4: Aplica el derecho privado, atendiendo la legislación y normatividad vigente, para dar solución a casos concretos. | D4: Número de estudiantes que participan de la estrategia. | F4: Listados de participación.
A5: Reconoce los principios éticos del derecho para implementarlos en su conducta y ejercicio profesional, atendiendo a los casos que llegan a su conocimiento en escenarios nacionales e internacionales. | D5: Número de veces que se desarrolla el seminario. | F5: Reporte.
A6: Aplica el régimen de las obligaciones y los contratos comerciales de cualquier tipología, nacional e internacional, atendiendo a las necesidades que se derivan de las relaciones comerciales entorno a su nacimiento, modificación y extinción, para adelantar los procesos jurídicos que correspondan al caso.
A7: Identifica los elementos característicos de la negociación y resolución de conflictos para caracterizar la información y argumentación requerida en los procesos de acuerdos, transacciones o laudos arbitrales que den por terminados los conflictos puestos a su conocimiento.
A8: Aplica las acciones administrativas y judiciales procedentes del derecho público para proyectar procesos jurídicos que garanticen el reconocimiento y la protección de los derechos de las personas.
A9: Aplica el derecho penal en el procedimiento y la acción procedente en atención al tipo penal identificado para adelantar los procesos jurídicos que correspondan al caso.
A10: Aplica habilidades de negociación y resolución de conflictos para atender las necesidades de los ciudadanos y la consolidación de acuerdos que den por termino los conflictos puestos a su conocimiento.
A11: Aplica los diferentes regímenes laborales para proyectar soluciones, en el marco jurídico, a las controversias que se originan de estas relaciones.
A12: Reconoce los fundamentos del derecho penal, comercial, público, laboral y privado para determinar el procedimiento a seguir en la resolución de conflictos o de actos jurídicos, observando los principios rectores de cada actividad y atendiendo a la legislación y normatividad vigente, que permitan generar acciones positivas y acordes a las necesidades de los individuos o las organizaciones, según sea el caso. | B12: Preparatorios (prueba estandarizada) | C12: Los estudiantes que hayan culminado su plan de estudios y no tengan un promedio igual o superior a 4,3 en el acumulado de la carrera, deberán presentar los exámenes preparatorios que miden la suficiencia de conocimientos en cada especialidad del derecho, esto mediante la preparación y posterior sustentación de un caso con base en las diferentes fuentes del derecho. | D12: Número de estudiantes que participan de la estrategia. | E12: Informar y formar a los estudiantes en la preparación y sustentación de un caso jurídico, evaluando su suficiencia disciplinar y acompañando su proceso de cierre académico. | F12: Listados de participación.
A13: Aplica el derecho privado, atendiendo la legislación y normatividad vigente, para dar solución a casos concretos. | D13: Número de veces que se desarrolla la estrategia en un periodo de tiempo determinado por el programa. | F13: Reporte.
A14: Reconoce los principios éticos del derecho para implementarlos en su conducta y ejercicio profesional, atendiendo a los casos que llegan a su conocimiento en escenarios nacionales e internacionales. | D14: Valoración de la contribución de la estrategia a los resultados de aprendizaje del programa en una escala de Likert. | F14: Encuesta.
A15: Aplica el régimen de las obligaciones y los contratos comerciales de cualquier tipología, nacional e internacional, atendiendo a las necesidades que se derivan de las relaciones comerciales entorno a su nacimiento, modificación y extinción, para adelantar los procesos jurídicos que correspondan al caso.
A16: Identifica los elementos característicos de la negociación y resolución de conflictos para caracterizar la información y argumentación requerida en los procesos de acuerdos, transacciones o laudos arbitrales que den por terminados los conflictos puestos a su conocimiento.
A17: Aplica las acciones administrativas y judiciales procedentes del derecho público para proyectar procesos jurídicos que garanticen el reconocimiento y la protección de los derechos de las personas.
A18: Aplica el derecho penal en el procedimiento y la acción procedente en atención al tipo penal identificado para adelantar los procesos jurídicos que correspondan al caso.
A19: Aplica habilidades de negociación y resolución de conflictos para atender las necesidades de los ciudadanos y la consolidación de acuerdos que den por termino los conflictos puestos a su conocimiento.
A20: Aplica los diferentes regímenes laborales para proyectar soluciones, en el marco jurídico, a las controversias que se originan de estas relaciones.
A21: Reconoce los fundamentos del derecho penal, comercial, público, laboral y privado para determinar el procedimiento a seguir en la resolución de conflictos o de actos jurídicos, observando los principios rectores de cada actividad y atendiendo a la legislación y normatividad vigente, que permitan generar acciones positivas y acordes a las necesidades de los individuos o las organizaciones, según sea el caso. | B21: Clases espejo nacional e internacional | C21: Tanto profesores como estudiantes participan en clases activamente, en una o doble vía, con grupos de otras universidades nacionales e internacionales, con la finalidad de reforzar sus conocimientos en derecho sustancial de las diferentes disciplinas y conocer los postulados internacionales en mismo sentido. | D21: Número de estudiantes que participan de la estrategia. | E21: Informar y formar sobre los temas abordados en las clases de manera que se contribuya al desarrollo formativo de los estudiantes. | F21: Listados de participación.
A22: Aplica el derecho privado, atendiendo la legislación y normatividad vigente, para dar solución a casos concretos. | D22: Número de veces que se desarrolla la estrategia en un periodo de tiempo determinado por el programa. | F22: Reporte.
A23: Reconoce los principios éticos del derecho para implementarlos en su conducta y ejercicio profesional, atendiendo a los casos que llegan a su conocimiento en escenarios nacionales e internacionales. | D23: Valora la contribución de la estrategia a los resultados de aprendizaje del programa en una escala de Likert. | F23: Encuesta.
A24: Aplica el régimen de las obligaciones y los contratos comerciales de cualquier tipología, nacional e internacional, atendiendo a las necesidades que se derivan de las relaciones comerciales entorno a su nacimiento, modificación y extinción, para adelantar los procesos jurídicos que correspondan al caso.
A25: Identifica los elementos característicos de la negociación y resolución de conflictos para caracterizar la información y argumentación requerida en los procesos de acuerdos, transacciones o laudos arbitrales que den por terminados los conflictos puestos a su conocimiento.
A26: Aplica las acciones administrativas y judiciales procedentes del derecho público para proyectar procesos jurídicos que garanticen el reconocimiento y la protección de los derechos de las personas.
A27: Aplica el derecho penal en el procedimiento y la acción procedente en atención al tipo penal identificado para adelantar los procesos jurídicos que correspondan al caso.
A28: Aplica habilidades de negociación y resolución de conflictos para atender las necesidades de los ciudadanos y la consolidación de acuerdos que den por termino los conflictos puestos a su conocimiento.
A29: Aplica los diferentes regímenes laborales para proyectar soluciones, en el marco jurídico, a las controversias que se originan de estas relaciones.
A30: Reconoce los fundamentos del derecho penal, comercial, público, laboral y privado para determinar el procedimiento a seguir en la resolución de conflictos o de actos jurídicos, observando los principios rectores de cada actividad y atendiendo a la legislación y normatividad vigente, que permitan generar acciones positivas y acordes a las necesidades de los individuos o las organizaciones, según sea el caso. | B30: Divulgación de los trabajos desarrollados en las opciones de grado | C30: Publicación de los trabajos en el Repositorio de Alejandría. | D30: Número de trabajos publicados en los periodos de tiempo que establezca el programa. | E30: Informar y formar sobre los temas abordados en los trabajos como medio de apropiación social del conocimiento. | F30: Reporte.
A31: Aplica el derecho privado, atendiendo la legislación y normatividad vigente, para dar solución a casos concretos. | D31: Número de estudiantes que participan de la estrategia. | F31: Listados de participación.
A32: Reconoce los principios éticos del derecho para implementarlos en su conducta y ejercicio profesional, atendiendo a los casos que llegan a su conocimiento en escenarios nacionales e internacionales.
A33: Aplica el régimen de las obligaciones y los contratos comerciales de cualquier tipología, nacional e internacional, atendiendo a las necesidades que se derivan de las relaciones comerciales entorno a su nacimiento, modificación y extinción, para adelantar los procesos jurídicos que correspondan al caso.
A34: Identifica los elementos característicos de la negociación y resolución de conflictos para caracterizar la información y argumentación requerida en los procesos de acuerdos, transacciones o laudos arbitrales que den por terminados los conflictos puestos a su conocimiento.
A35: Aplica las acciones administrativas y judiciales procedentes del derecho público para proyectar procesos jurídicos que garanticen el reconocimiento y la protección de los derechos de las personas.
A36: Aplica el derecho penal en el procedimiento y la acción procedente en atención al tipo penal identificado para adelantar los procesos jurídicos que correspondan al caso.
A37: Aplica habilidades de negociación y resolución de conflictos para atender las necesidades de los ciudadanos y la consolidación de acuerdos que den por termino los conflictos puestos a su conocimiento.
A38: Aplica los diferentes regímenes laborales para proyectar soluciones, en el marco jurídico, a las controversias que se originan de estas relaciones.
A39: Reconoce los fundamentos del derecho penal, comercial, público, laboral y privado para determinar el procedimiento a seguir en la resolución de conflictos o de actos jurídicos, observando los principios rectores de cada actividad y atendiendo a la legislación y normatividad vigente, que permitan generar acciones positivas y acordes a las necesidades de los individuos o las organizaciones, según sea el caso. | B39: Curso de preparación para el Saber Pro | C39: Los estudiantes al finalizar su plan de estudios, para optar por el grado de abogados, deben presentar un examen de Estado que evalúa sus conocimientos generales y específicos, para esto, desde el programa se genera un MOOCS de preparación para el examen de Estado, con acompañamiento de tutor en el desarrollo del mismo. | D39: Número de estudiantes que participan de la estrategia. | E39: Formar, prevenir y ayudar a tomar decisiones para el desarrollo formativo de los estudiantes. | F39: Listados de participación.
A40: Aplica el derecho privado, atendiendo la legislación y normatividad vigente, para dar solución a casos concretos. | D40: Número de veces que se desarrolla la estrategia en un periodo de tiempo determinado por el programa. | F40: Reporte.
A41: Reconoce los principios éticos del derecho para implementarlos en su conducta y ejercicio profesional, atendiendo a los casos que llegan a su conocimiento en escenarios nacionales e internacionales. | D41: Valoración de la contribución de la estrategia a los resultados de aprendizaje del programa en una escala de Likert. | F41: Encuesta.
A42: Aplica el régimen de las obligaciones y los contratos comerciales de cualquier tipología, nacional e internacional, atendiendo a las necesidades que se derivan de las relaciones comerciales entorno a su nacimiento, modificación y extinción, para adelantar los procesos jurídicos que correspondan al caso.
A43: Identifica los elementos característicos de la negociación y resolución de conflictos para caracterizar la información y argumentación requerida en los procesos de acuerdos, transacciones o laudos arbitrales que den por terminados los conflictos puestos a su conocimiento.
A44: Aplica las acciones administrativas y judiciales procedentes del derecho público para proyectar procesos jurídicos que garanticen el reconocimiento y la protección de los derechos de las personas.
A45: Aplica el derecho penal en el procedimiento y la acción procedente en atención al tipo penal identificado para adelantar los procesos jurídicos que correspondan al caso.
A46: Aplica habilidades de negociación y resolución de conflictos para atender las necesidades de los ciudadanos y la consolidación de acuerdos que den por termino los conflictos puestos a su conocimiento.
A47: Aplica los diferentes regímenes laborales para proyectar soluciones, en el marco jurídico, a las controversias que se originan de estas relaciones.
A48: Reconoce los fundamentos del derecho penal, comercial, público, laboral y privado para determinar el procedimiento a seguir en la resolución de conflictos o de actos jurídicos, observando los principios rectores de cada actividad y atendiendo a la legislación y normatividad vigente, que permitan generar acciones positivas y acordes a las necesidades de los individuos o las organizaciones, según sea el caso. | B48: Semilleros de investigación | C48: Es un espacio dirigido a los estudiantes, para concientizar sobre la importancia de su formación como investigadores y el compromiso que tienen con la sociedad en la generación de nuevo conocimiento. | D48: Número de estudiantes que participan de la estrategia. | E48: Informar y formar sobre los temas abordados en los proyectos del semillero como medio de apropiación social del conocimiento. | F48: Listados de participación.
A49: Aplica el derecho privado, atendiendo la legislación y normatividad vigente, para dar solución a casos concretos. | D49: Número de proyectos desarrollados en la estrategia, en un periodo de tiempo determinado por el programa. | F49: Reporte.
A50: Reconoce los principios éticos del derecho para implementarlos en su conducta y ejercicio profesional, atendiendo a los casos que llegan a su conocimiento en escenarios nacionales e internacionales. | D50: Valora la contribución de la estrategia a los resultados de aprendizaje del programa en una escala de Likert. | F50: Encuesta.
A51: Aplica el régimen de las obligaciones y los contratos comerciales de cualquier tipología, nacional e internacional, atendiendo a las necesidades que se derivan de las relaciones comerciales entorno a su nacimiento, modificación y extinción, para adelantar los procesos jurídicos que correspondan al caso.
A52: Identifica los elementos característicos de la negociación y resolución de conflictos para caracterizar la información y argumentación requerida en los procesos de acuerdos, transacciones o laudos arbitrales que den por terminados los conflictos puestos a su conocimiento.
A53: Aplica las acciones administrativas y judiciales procedentes del derecho público para proyectar procesos jurídicos que garanticen el reconocimiento y la protección de los derechos de las personas.
A54: Aplica el derecho penal en el procedimiento y la acción procedente en atención al tipo penal identificado para adelantar los procesos jurídicos que correspondan al caso.
A55: Aplica habilidades de negociación y resolución de conflictos para atender las necesidades de los ciudadanos y la consolidación de acuerdos que den por termino los conflictos puestos a su conocimiento.
A56: Aplica los diferentes regímenes laborales para proyectar soluciones, en el marco jurídico, a las controversias que se originan de estas relaciones.
A57: Reconoce los fundamentos del derecho penal, comercial, público, laboral y privado para determinar el procedimiento a seguir en la resolución de conflictos o de actos jurídicos, observando los principios rectores de cada actividad y atendiendo a la legislación y normatividad vigente, que permitan generar acciones positivas y acordes a las necesidades de los individuos o las organizaciones, según sea el caso. | B57: Eventos académicos nacionales e internacionales | C57: Son espacios de intercambios académicos y culturales que permiten profundizar, ver nuevas perspectivas, analizar nuevos elementos en cada una de las especialidades del Derecho. | D57: Número de estudiantes que participan de la estrategia. | E57: Informar y formar a los estudiantes en temas de tendencia de la disciplina para fortalecer el desarrollo académico. | F57: Listados de participación.
A58: Aplica el derecho privado, atendiendo la legislación y normatividad vigente, para dar solución a casos concretos. | D58: Número de veces que se desarrolla la estrategia en un periodo de tiempo determinado por el programa. | F58: Reporte o Memorias.
A59: Reconoce los principios éticos del derecho para implementarlos en su conducta y ejercicio profesional, atendiendo a los casos que llegan a su conocimiento en escenarios nacionales e internacionales. | D59: Valora la contribución de la estrategia a los resultados de aprendizaje del programa en una escala de Likert. | F59: Encuesta.
A60: Aplica el régimen de las obligaciones y los contratos comerciales de cualquier tipología, nacional e internacional, atendiendo a las necesidades que se derivan de las relaciones comerciales entorno a su nacimiento, modificación y extinción, para adelantar los procesos jurídicos que correspondan al caso.
A61: Identifica los elementos característicos de la negociación y resolución de conflictos para caracterizar la información y argumentación requerida en los procesos de acuerdos, transacciones o laudos arbitrales que den por terminados los conflictos puestos a su conocimiento.
A62: Aplica las acciones administrativas y judiciales procedentes del derecho público para proyectar procesos jurídicos que garanticen el reconocimiento y la protección de los derechos de las personas.
A63: Aplica el derecho penal en el procedimiento y la acción procedente en atención al tipo penal identificado para adelantar los procesos jurídicos que correspondan al caso.
A64: Aplica habilidades de negociación y resolución de conflictos para atender las necesidades de los ciudadanos y la consolidación de acuerdos que den por termino los conflictos puestos a su conocimiento.
A65: Aplica los diferentes regímenes laborales para proyectar soluciones, en el marco jurídico, a las controversias que se originan de estas relaciones.
A66: Reconoce los fundamentos del derecho penal, comercial, público, laboral y privado para determinar el procedimiento a seguir en la resolución de conflictos o de actos jurídicos, observando los principios rectores de cada actividad y atendiendo a la legislación y normatividad vigente, que permitan generar acciones positivas y acordes a las necesidades de los individuos o las organizaciones, según sea el caso. | B66: Barras jurídicas | C66: Son escenarios extracurriculares dirigidos a los estudiantes de Consultorio Jurídico I, II, III y IV, en los que se cuenta con el acompañamiento de invitados externos bajo la guía del profesor, y se permite el intercambio de experiencias prácticas en casos concretos. | D66: Número de estudiantes que participan de la estrategia. | E66: Informar y formar sobre temas de tendencias de la disciplina para fortalecer el desarrollo académico de los estudiantes. | F66: Listados de participación.
A67: Aplica el derecho privado, atendiendo la legislación y normatividad vigente, para dar solución a casos concretos. | D67: Número de veces que se desarrolla la estrategia en un periodo de tiempo determinado por el programa. | F67: Reporte.
A68: Reconoce los principios éticos del derecho para implementarlos en su conducta y ejercicio profesional, atendiendo a los casos que llegan a su conocimiento en escenarios nacionales e internacionales. | D68: Valoración de la contribución de la estrategia a los resultados de aprendizaje del programa en una escala de Likert. | F68: Encuesta.
A69: Aplica el régimen de las obligaciones y los contratos comerciales de cualquier tipología, nacional e internacional, atendiendo a las necesidades que se derivan de las relaciones comerciales entorno a su nacimiento, modificación y extinción, para adelantar los procesos jurídicos que correspondan al caso.
A70: Identifica los elementos característicos de la negociación y resolución de conflictos para caracterizar la información y argumentación requerida en los procesos de acuerdos, transacciones o laudos arbitrales que den por terminados los conflictos puestos a su conocimiento.
A71: Aplica las acciones administrativas y judiciales procedentes del derecho público para proyectar procesos jurídicos que garanticen el reconocimiento y la protección de los derechos de las personas.
A72: Aplica el derecho penal en el procedimiento y la acción procedente en atención al tipo penal identificado para adelantar los procesos jurídicos que correspondan al caso.
A73: Aplica habilidades de negociación y resolución de conflictos para atender las necesidades de los ciudadanos y la consolidación de acuerdos que den por termino los conflictos puestos a su conocimiento.
A74: Aplica los diferentes regímenes laborales para proyectar soluciones, en el marco jurídico, a las controversias que se originan de estas relaciones.

Sheet Paso 5 Estrategias micro
A1: [Estas celdas se diligencian automáticamente. No ajustar.] | B1: [A partir de la celda A3 despliegue el(los) resultado(s) de aprendizaje y elija aquel (aquellos) al(a los) que se contribuye desde la asignatura o módulo).] | C1: [Escribir el semestre en el que se cursa la asignatura o módulo.] | D1: [Escribir el nombre de la asignatura o módulo que contribuye al logro del resultado de aprendizaje.] | E1: [Redactar los indicadores iniciando con el verbo en presente indicativo, luego el objeto conceptual y finalmente el complemento de oración (que indique una condición o finalidad, con, para, de, entre otros conectores).] | F1: [Escribir la tipología: T (teórico), P (Práctico), TP (Teórico Práctico)] | G1: [Marcar con X el bloque o componente al que pertenece la asignatura o módulo. Por favor ajustar para posgrado, eliminar una columna y ubicar los títulos C.Fundamentación y C.Profundización.] | J1: [Escribir el número de créditos de la asignatura o módulo] | K1: [Escribir el número de horas de trabajo directo: 16*# o 12*#, para presencial o virtual, según sea el caso.] | L1: [Escribir el número de horas de trabajo independiente: 32*# columna J o 36*# columna J, para presencial o virtual, respectivamente.] | M1: [Escribir la suma de los números de horas de las dos celdas anteriores.] | N1: [Escribir el nombre de los cuatro núcleos temáticos que abordará la asignatura o el módulo.] | O1: [Escribir las lecturas, talleres, análisis, referentes, etc., que realiza el estudiante, clasificadas en trabajo directo e independiente.] | P1: [Escribir las actividades de evaluación que se emplean para identificar el alcance del (de los) indicador(es) de logro(s).] | Q1: [Escribir las acciones de retroalimentación que se emplearán en la asignatura o módulo, para retroalimentar a los estudiantes respecto al alcance de los indicadores de logro. Recordar que son cuatro acciones: informar, formar, prevenir y ayudar a tomar decisiones e indique cómo.]
A2: Tipo de Saber | B2: Resultado de aprendizaje | C2: Semestre | D2: Nombre asignatura o módulo | E2: Indicadores de logro asignatura o módulo | F2: Tipología | G2: B.Institucional | H2: B.Disciplinar | I2: B.Electivo | J2: Créditos | K2: Número de horas trabajo directo | L2: Número de horas trabajo independiente | M2: Total de horas | N2: Núcleos temáticos | O2: Actividades de aprendizaje | P2: Actividades de evaluación | Q2: Acciones de retroalimentación
A3: =_xlfn.XLOOKUP(B3,'Paso 3 Redacción RA'!I3:I21,'Paso 3 Redacción RA'!C3:C21,,0,1) -> Saber | B3: Identifica fenómenos contemporáneos y su relación con la profesión, para determinar sus impactos e influencia en la sociedad, de forma responsable y crítica. | C3: 1 | D3: Razonamiento Cuantitativo | E3: Analiza datos numéricos presentados en tablas, gráficos o textos para proponer soluciones informadas a situaciones problema del contexto. | F3: TP | G3: X | J3: 3 | K3: =12*J3 -> 36 | L3: =36*J3 -> 108 | M3: =SUM(K3:L3) -> 144 | N3: 1. Pensamiento numérico. Interpretación y representación de información numérica 2. Pensamiento algebraico. Desde la representación de regularidades y patrones 3. Pensamiento algebraico. Desde las relaciones de comparación entre cantidades o expresiones numéricas 4. Pensamiento geométrico. Propiedades, formas y relaciones espaciales | O3: Trabajo directo: Encuentros sincrónicos Mensajería interna Anuncios Trabajo independiente: Lecturas fundamentales y complementarias Material de trabajo Participación en foros | P3: Evaluación diagnóstica: Cuestionario inicial de, mínimo, cinco preguntas, que recopila información sobre el conocimiento previo y las habilidades del estudiante. Actividad formativa: Foro individual o grupal, creado para que el estudiante participe activamente en la construcción de su conocimiento y desarrollo de habilidades. Varía entre una actividad entregable y la participación en un foro. Actividad de entrega: Actividad individual o grupal, diseñada para evaluar de manera integral el nivel de conocimiento, comprensión y el desempeño de los indicadores de logro. Varía entre entregas independientes o secuenciales. Al ser un módulo teórico, ésta es la única actividad de entrega. Actividad evaluativa: Cuestionario de, mínimo, cinco preguntas, que da cuenta del desarrollo total o parcial de los indicadores de logro y el desarrollo de los temas vistos hasta la unidad 3. Examen final: Cuestionario de, mínimo, quince preguntas, que da cuenta del desarrollo total o parcial de los indicadores de logro y el desarrollo de los temas vistos en el módulo. Autoevaluación: Cuestionario final de, mínimo, cinco preguntas, en el cual el estudiante reflexiona sobre su propio desempeño, habilidades y resultados en un contexto específico. | Q3: Informar oportunamente a través de la plataforma institucional y sesiones sincrónicas sobre el propósito, el proceso de realización, entrega de la actividad y criterios de evaluación. En las sesiones sincrónicas, atender las inquietudes y dar orientaciones al respecto, así como invitar a tomar asesorías ofrecidas por la Escuela de Ciencia Básicas, como estrategia de prevención y ayuda. Ayudar a tomar decisiones a través de preguntas orientadoras y actividades de refuerzo dentro del trabajo directo y autónomo. Retroalimentación por medio de rúbrica que indica el nivel de alcance del logro obtenido. Retroalimentación general del docente acorde a los resultados alcanzados por el grupo.
A4: =_xlfn.XLOOKUP(B4,'Paso 3 Redacción RA'!I3:I21,'Paso 3 Redacción RA'!C3:C21,,0,1) -> Saber | B4: Identifica fenómenos contemporáneos y su relación con la profesión, para determinar sus impactos e influencia en la sociedad, de forma responsable y crítica. | C4: 1 | D4: Cultura, Política y Sociedad | E4: Reconoce las problemáticas, escenarios y mecanismos de participación ciudadana en el marco de sociedades de información y digitales para abordarlas desde iniciativas investigativas. Identifica los objetivos de desarrollo sostenible para la comprensión de problemáticas sociales, ambientales y culturales. Reflexiona los impactos de avances tecnológicos en su contexto profesional y ciudadano para el análisis de contextos situados. | F4: TP | G4: X | J4: 3 | K4: =12*J4 -> 36 | L4: =36*J4 -> 108 | M4: =SUM(K4:L4) -> 144 | N4: 1. ODS, problemas locales: una mirada a Colombia, territorio en búsqueda de la consolidación de la Paz. 2. Ciudadanía y su lugar: relaciones, dinámicas, construcción, expresión y mecanismos de participación. 3. Ecosistemas digitales: relaciones, dinámicas, construcción, expresión e impactos en el contexto profesional. 4. Narrativas y contenidos digitales: análisis de contextos situados. | O4: Trabajo directo: Encuentros sincrónicos Mensajería interna Anuncios Trabajo independiente: Lecturas fundamentales y complementarias Material de trabajo Participación en foros | P4: 1. Evaluación diagnóstica escenario 1: Cuestionario inicial de mínimo cinco preguntas que recopila información sobre el conocimiento previo y las habilidades del estudiante. 2. Actividad formativa escenario 2: Foro individual o grupal, creado para que el estudiante participe activamente en la construcción de su conocimiento y desarrollo de habilidades. Varía entre una actividad entregable y la participación en un foro. 3. Actividad de entrega 1 escenario 4: Actividad individual o grupal, diseñada para evaluar de manera integral el nivel de conocimiento, comprensión y el desempeño de los indicadores de logro. Varía entre entregas independientes o secuenciales. 4. Actividad formativa escenario 5: Foro individual o grupal, creado para que el estudiante participe activamente en la construcción de su conocimiento y desarrollo de habilidades. Varía entre una actividad entregable y la participación en un foro. 5. Actividad evaluativa escenario 6: Cuestionario de, mínimo, cinco preguntas, que da cuenta del desarrollo total o parcial de los indicadores de logro y el desarrollo de los temas vistos hasta la unidad 3. 6. Actividad de entrega 2 escenario 7: Actividad individual o grupal, diseñada para evaluar de manera integral el nivel de conocimiento, comprensión y el desempeño de los indicadores de logro. Varía entre entregas independientes o secuenciales. 7. Autoevaluación escenario 8: Cuestionario final de mínimo cinco preguntas en el cual el estudiante reflexiona sobre su propio desempeño, habilidades y resultados en un contexto específico. | Q4: Las acciones de retroalimentación giran en torno a las siguientes. Formar: donde se crean las condiciones para que los estudiantes adquieran conocimientos, habilidades, actitudes, aptitudes y destrezas. Además, debe promover su desarrollo integral y debe acompañarlos en las situaciones académicas que enfrenten durante el desarrollo de un módulo o una asignatura. Informar: para que los estudiantes identifiquen los cambios que pueden afectarlos directa o indirectamente tanto en el aula de clase como en otros espacios. Prevenir: con el fin de anticiparse a las situaciones académicas que pueden representar dificultad para los estudiantes. Esto se logra a través de la interacción individual con los estudiantes y del completo conocimiento del contexto educativo en que el tutor se desenvuelve. Ayudar a decidir: donde se orienta a los estudiantes para que tomen la mejor decisión ante una situación concreta. El objetivo es que el estudiante fortalezca su autonomía y la toma de decisiones responsable.
A5: =_xlfn.XLOOKUP(B5,'Paso 3 Redacción RA'!I3:I21,'Paso 3 Redacción RA'!C3:C21,,0,1) -> Saber | B5: Reconoce los fundamentos del derecho penal, comercial, público, laboral y privado para determinar el procedimiento a seguir en la resolución de conflictos o de actos jurídicos, observando los principios rectores de cada actividad y atendiendo a la legislación y normatividad vigente, que permitan generar acciones positivas y acordes a las necesidades de los individuos o las organizaciones, según sea el caso. | C5: 1 | D5: Derecho Civil Personas | E5: Emplea el derecho civil y de personas, las nociones fundamentales, los derechos y obligaciones, para implementar los atributos de la personalidad desde la existencia hasta la extinción, en el análisis de casos. | F5: TP | H5: X | J5: 3 | K5: =12*J5 -> 36 | L5: =36*J5 -> 108 | M5: =SUM(K5:L5) -> 144 | N5: 1. Historia del Derecho Civil. 2. Contenido y estructura del código civil. 3. De las personas. 4. Derechos de las personas. | O5: Trabajo directo: Encuentros sincrónicos Mensajería interna Anuncios Trabajo independiente: Lecturas fundamentales y complementarias Recursos de apoyo Trabajo Colaborativo Foros de discusión grupal | P5: Actividad de puntos evaluables (semana 2 – Cuestionario de 5 preguntas). Entrega previa 1 (semana 3 - Laboratorio, taller, ejercicios, resolución de casos o de problemas, desarrollo de procesos o ejecución de propuestas. Entrega de forma individual o grupal, según indicaciones del profesor). Parcial (semana 4 - Cuestionarios de entre 15 y 20 preguntas). Entrega previa 2 (semana 5 - Laboratorio, taller, ejercicios, resolución de casos o de problemas, desarrollo de procesos o ejecución de propuestas. Entrega de forma individual o grupal, según indicaciones dadas por el profesor). Entrega final (semana 7 - Laboratorio, taller, ejercicios, resolución de casos o de problemas, desarrollo de procesos o ejecución de propuestas. Entrega de forma individual o grupal, según indicaciones dadas por el profesor). Evaluación final (semana 8 - Cuestionario de entre 15 y 20 preguntas). | Q5: Las acciones de retroalimentación giran en torno a las siguientes. Formar: donde se crean las condiciones para que los estudiantes adquieran conocimientos, habilidades, actitudes, aptitudes y destrezas. Además, debe promover su desarrollo integral y debe acompañarlos en las situaciones académicas que enfrenten durante el desarrollo de un módulo o una asignatura. Informar: para que los estudiantes identifiquen los cambios que pueden afectarlos directa o indirectamente tanto en el aula de clase como en otros espacios. Prevenir: con el fin de anticiparse a las situaciones académicas que pueden representar dificultad para los estudiantes. Esto se logra a través de la interacción individual con los estudiantes y del completo conocimiento del contexto educativo en que el tutor se desenvuelve. Ayudar a decidir: donde se orienta a los estudiantes para que tomen la mejor decisión ante una situación concreta. El objetivo es que el estudiante fortalezca su autonomía y la toma de decisiones responsable.
A6: =_xlfn.XLOOKUP(B6,'Paso 3 Redacción RA'!I3:I21,'Paso 3 Redacción RA'!C3:C21,,0,1) -> SaberHacer | B6: Aplica el derecho privado, atendiendo la legislación y normatividad vigente, para dar solución a casos concretos.
A7: =_xlfn.XLOOKUP(B7,'Paso 3 Redacción RA'!I3:I21,'Paso 3 Redacción RA'!C3:C21,,0,1) -> SaberSer | B7: Reconoce los principios éticos del derecho para implementarlos en su conducta y ejercicio profesional, atendiendo a los casos que llegan a su conocimiento en escenarios nacionales e internacionales.
A8: =_xlfn.XLOOKUP(B8,'Paso 3 Redacción RA'!I3:I21,'Paso 3 Redacción RA'!C3:C21,,0,1) -> Saber | B8: Identifica los elementos característicos de la negociación y resolución de conflictos para caracterizar la información y argumentación requerida en los procesos de acuerdos, transacciones o laudos arbitrales que den por terminados los conflictos puestos a su conocimiento.
A9: =_xlfn.XLOOKUP(B9,'Paso 3 Redacción RA'!I3:I21,'Paso 3 Redacción RA'!C3:C21,,0,1) -> SaberHacer | B9: Aplica habilidades de negociación y resolución de conflictos para atender las necesidades de los ciudadanos y la consolidación de acuerdos que den por termino los conflictos puestos a su conocimiento.
A10: =_xlfn.XLOOKUP(B10,'Paso 3 Redacción RA'!I3:I21,'Paso 3 Redacción RA'!C3:C21,,0,1) -> Saber | B10: Reconoce los fundamentos del derecho penal, comercial, público, laboral y privado para determinar el procedimiento a seguir en la resolución de conflictos o de actos jurídicos, observando los principios rectores de cada actividad y atendiendo a la legislación y normatividad vigente, que permitan generar acciones positivas y acordes a las necesidades de los individuos o las organizaciones, según sea el caso. | C10: I | D10: Acto Jurídico | E10: Explica los efectos que pueden surgir de los hechos, actos jurídicos, y los negocios jurídicos, para diferenciar los elementos de existencia y validez del negocio jurídico los eventos de su simulación y sus efectos jurídicos. | F10: T | H10: X | J10: 3 | K10: =12*J10 -> 36 | L10: =36*J10 -> 108 | M10: =SUM(K10:L10) -> 144 | N10: 1. Teoría de los actos jurídicos. 2. Estructura de los actos jurídicos. 3. Efectos y eficacia de los actos jurídicos. 4. Nulidad, anulabilidad y mecanismos de resolución de los actos jurídicos. | O10: Trabajo directo: Encuentros sincrónicos Mensajería interna Anuncios Trabajo independiente: Lecturas fundamentales y complementarias Recursos de apoyo Trabajo Colaborativo Foros de discusión grupal | P10: Quiz (semana 2 - Cuestionario de 5 preguntas). Entrega inicial (semana 3 – Ensayo, artículo, cuadro comparativo, revisión documental, entre otros). Foro analítico o argumentativo (semanas 5 y 6 – Participación en el espacio correspondiente del aula). Entrega final (semana 7 – Ensayo, artículo, cuadro comparativo, revisión documental, entre otros). Evaluación final (semana 8 – Cuestionario de entre 15 y 20 preguntas). | Q10: Las acciones de retroalimentación giran en torno a las siguientes. Formar: donde se crean las condiciones para que los estudiantes adquieran conocimientos, habilidades, actitudes, aptitudes y destrezas. Además, debe promover su desarrollo integral y debe acompañarlos en las situaciones académicas que enfrenten durante el desarrollo de un módulo o una asignatura. Informar: para que los estudiantes identifiquen los cambios que pueden afectarlos directa o indirectamente tanto en el aula de clase como en otros espacios. Prevenir: con el fin de anticiparse a las situaciones académicas que pueden representar dificultad para los estudiantes. Esto se logra a través de la interacción individual con los estudiantes y del completo conocimiento del contexto educativo en que el tutor se desenvuelve. Ayudar a decidir: donde se orienta a los estudiantes para que tomen la mejor decisión ante una situación concreta. El objetivo es que el estudiante fortalezca su autonomía y la toma de decisiones responsable.
A11: =_xlfn.XLOOKUP(B11,'Paso 3 Redacción RA'!I3:I21,'Paso 3 Redacción RA'!C3:C21,,0,1) -> SaberHacer | B11: Aplica el derecho privado, atendiendo la legislación y normatividad vigente, para dar solución a casos concretos.
A12: =_xlfn.XLOOKUP(B12,'Paso 3 Redacción RA'!I3:I21,'Paso 3 Redacción RA'!C3:C21,,0,1) -> SaberSer | B12: Reconoce los principios éticos del derecho para implementarlos en su conducta y ejercicio profesional, atendiendo a los casos que llegan a su conocimiento en escenarios nacionales e internacionales.
A13: =_xlfn.XLOOKUP(B13,'Paso 3 Redacción RA'!I3:I21,'Paso 3 Redacción RA'!C3:C21,,0,1) -> Saber | B13: Identifica los elementos característicos de la negociación y resolución de conflictos para caracterizar la información y argumentación requerida en los procesos de acuerdos, transacciones o laudos arbitrales que den por terminados los conflictos puestos a su conocimiento.
A14: =_xlfn.XLOOKUP(B14,'Paso 3 Redacción RA'!I3:I21,'Paso 3 Redacción RA'!C3:C21,,0,1) -> SaberHacer | B14: Aplica habilidades de negociación y resolución de conflictos para atender las necesidades de los ciudadanos y la consolidación de acuerdos que den por termino los conflictos puestos a su conocimiento.
A15: =_xlfn.XLOOKUP(B15,'Paso 3 Redacción RA'!I3:I21,'Paso 3 Redacción RA'!C3:C21,,0,1) -> Saber | B15: Reconoce los fundamentos del derecho penal, comercial, público, laboral y privado para determinar el procedimiento a seguir en la resolución de conflictos o de actos jurídicos, observando los principios rectores de cada actividad y atendiendo a la legislación y normatividad vigente, que permitan generar acciones positivas y acordes a las necesidades de los individuos o las organizaciones, según sea el caso. | C15: I | D15: Introducción al Derecho | E15: Analiza las concepciones del derecho, sus escuelas y corrientes, así como los principios y fuentes del derecho para establecer el derecho en la resolución de casos mediante la argumentación. | F15: T | H15: X | J15: 3 | K15: =12*J15 -> 36 | L15: =36*J15 -> 108 | M15: =SUM(K15:L15) -> 144 | N15: 1. Nociones fundamentales de Derecho. 2. Introducción a la filosofía del Derecho. 3. Fuentes del Derecho. 4. Principios generales del Derecho. | O15: Trabajo directo: Encuentros sincrónicos Mensajería interna Anuncios Trabajo independiente: Lecturas fundamentales y complementarias Recursos de apoyo Trabajo Colaborativo Foros de discusión grupal | P15: Quiz (semana 2 - Cuestionario de 5 preguntas). Entrega inicial (semana 3 – Ensayo, artículo, cuadro comparativo, revisión documental, entre otros). Foro analítico o argumentativo (semanas 5 y 6 – Participación en el espacio correspondiente del aula). Entrega final (semana 7 – Ensayo, artículo, cuadro comparativo, revisión documental, entre otros). Evaluación final (semana 8 – Cuestionario de entre 15 y 20 preguntas). | Q15: Las acciones de retroalimentación giran en torno a las siguientes. Formar: donde se crean las condiciones para que los estudiantes adquieran conocimientos, habilidades, actitudes, aptitudes y destrezas. Además, debe promover su desarrollo integral y debe acompañarlos en las situaciones académicas que enfrenten durante el desarrollo de un módulo o una asignatura. Informar: para que los estudiantes identifiquen los cambios que pueden afectarlos directa o indirectamente tanto en el aula de clase como en otros espacios. Prevenir: con el fin de anticiparse a las situaciones académicas que pueden representar dificultad para los estudiantes. Esto se logra a través de la interacción individual con los estudiantes y del completo conocimiento del contexto educativo en que el tutor se desenvuelve. Ayudar a decidir: donde se orienta a los estudiantes para que tomen la mejor decisión ante una situación concreta. El objetivo es que el estudiante fortalezca su autonomía y la toma de decisiones responsable.
A16: =_xlfn.XLOOKUP(B16,'Paso 3 Redacción RA'!I3:I21,'Paso 3 Redacción RA'!C3:C21,,0,1) -> SaberSer | B16: Reconoce los principios éticos del derecho para implementarlos en su conducta y ejercicio profesional, atendiendo a los casos que llegan a su conocimiento en escenarios nacionales e internacionales.
A17: =_xlfn.XLOOKUP(B17,'Paso 3 Redacción RA'!I3:I21,'Paso 3 Redacción RA'!C3:C21,,0,1) -> Saber | B17: Identifica los elementos característicos de la negociación y resolución de conflictos para caracterizar la información y argumentación requerida en los procesos de acuerdos, transacciones o laudos arbitrales que den por terminados los conflictos puestos a su conocimiento.
A18: =_xlfn.XLOOKUP(B18,'Paso 3 Redacción RA'!I3:I21,'Paso 3 Redacción RA'!C3:C21,,0,1) -> SaberHacer | B18: Aplica habilidades de negociación y resolución de conflictos para atender las necesidades de los ciudadanos y la consolidación de acuerdos que den por termino los conflictos puestos a su conocimiento.
A19: =_xlfn.XLOOKUP(B19,'Paso 3 Redacción RA'!I3:I21,'Paso 3 Redacción RA'!C3:C21,,0,1) -> Saber | B19: Identifica fenómenos contemporáneos y su relación con la profesión, para determinar sus impactos e influencia en la sociedad, de forma responsable y crítica. | C19: 2 | D19: Análisis y Visualización de Datos | E19: Identifica conceptos básicos relacionados con el análisis y visualización de datos con el propósito de comunicar información relevante de manera efectiva en diversos contextos. Utiliza herramientas para realizar análisis y transformación de datos que garanticen una visualización sencilla y eficiente. Utiliza asistentes virtuales para realizar tareas prácticas y resolver problemas en su campo de estudio. Evalúa la presencia de sesgos y cuestiones éticas en el análisis y tratamiento de dato para garantizar que su uso esté desprovisto de efectos negativos en el entorno. | F19: TP | G19: X | J19: 3 | K19: =12*J19 -> 36 | L19: =36*J19 -> 108 | M19: =SUM(K19:L19) -> 144 | N19: 1. Contextualización 2. Análisis de Datos y Visualización 3. Usos de la Inteligencia Artificial 4. Casos de Estudio | O19: Trabajo directo: Encuentros sincrónicos Mensajería interna Anuncios Trabajo independiente: Lecturas fundamentales y complementarias Material de trabajo Participación en foros | P19: 1. Evaluación diagnóstica escenario 1: Cuestionario inicial de mínimo cinco preguntas que recopila información sobre el conocimiento previo y las habilidades del estudiante. 2. Actividad formativa escenario 2: Foro individual o grupal, creado para que el estudiante participe activamente en la construcción de su conocimiento y desarrollo de habilidades. Varía entre una actividad entregable y la participación en un foro. 3. Actividad de entrega 1 escenario 4: Actividad individual o grupal, diseñada para evaluar de manera integral el nivel de conocimiento, comprensión y el desempeño de los indicadores de logro. Varía entre entregas independientes o secuenciales. 4. Actividad formativa escenario 5: Foro individual o grupal, creado para que el estudiante participe activamente en la construcción de su conocimiento y desarrollo de habilidades. Varía entre una actividad entregable y la participación en un foro. 5. Actividad evaluativa escenario 6: Cuestionario de, mínimo, cinco preguntas, que da cuenta del desarrollo total o parcial de los indicadores de logro y el desarrollo de los temas vistos hasta la unidad 3. 6. Actividad de entrega 2 escenario 7: Actividad individual o grupal, diseñada para evaluar de manera integral el nivel de conocimiento, comprensión y el desempeño de los indicadores de logro. Varía entre entregas independientes o secuenciales. 7. Autoevaluación escenario 8: Cuestionario final de mínimo cinco preguntas en el cual el estudiante reflexiona sobre su propio desempeño, habilidades y resultados en un contexto específico. | Q19: Las acciones de retroalimentación giran en torno a las siguientes. Formar: donde se crean las condiciones para que los estudiantes adquieran conocimientos, habilidades, actitudes, aptitudes y destrezas. Además, debe promover su desarrollo integral y debe acompañarlos en las situaciones académicas que enfrenten durante el desarrollo de un módulo o una asignatura. Informar: para que los estudiantes identifiquen los cambios que pueden afectarlos directa o indirectamente tanto en el aula de clase como en otros espacios. Prevenir: con el fin de anticiparse a las situaciones académicas que pueden representar dificultad para los estudiantes. Esto se logra a través de la interacción individual con los estudiantes y del completo conocimiento del contexto educativo en que el tutor se desenvuelve. Ayudar a decidir: donde se orienta a los estudiantes para que tomen la mejor decisión ante una situación concreta. El objetivo es que el estudiante fortalezca su autonomía y la toma de decisiones responsable.
A20: =_xlfn.XLOOKUP(B20,'Paso 3 Redacción RA'!I3:I21,'Paso 3 Redacción RA'!C3:C21,,0,1) -> Saber | B20: Reconoce los fundamentos del derecho penal, comercial, público, laboral y privado para determinar el procedimiento a seguir en la resolución de conflictos o de actos jurídicos, observando los principios rectores de cada actividad y atendiendo a la legislación y normatividad vigente, que permitan generar acciones positivas y acordes a las necesidades de los individuos o las organizaciones, según sea el caso. | C20: 2 | D20: Fundamentación Jurídica | E20: Analiza el contexto histórico del origen del derecho, los conceptos de validez, justicia y eficacia, su relación con el derecho, la cientificidad, la moral y la ética dentro de las corrientes del derecho para explicar las razones de justificación, existencia y dinámica del ordenamiento jurídico actual. | F20: T | H20: X | J20: 3 | K20: =12*J20 -> 36 | L20: =36*J20 -> 108 | M20: =SUM(K20:L20) -> 144 | N20: 1. Derecho Romano y devenir histórico del Derecho hasta el siglo XIX. 2. Devenir histórico del Derecho en los siglos XX y XXI. 3. La Filosofía del Derecho. 4. Introducción a la sociología jurídica. | O20: Trabajo directo: Encuentros sincrónicos Mensajería interna Anuncios Trabajo independiente: Lecturas fundamentales y complementarias Recursos de apoyo Trabajo Colaborativo Foros de discusión grupal | P20: Quiz (semana 2 - Cuestionario de 5 preguntas). Entrega inicial (semana 3 – Ensayo, artículo, cuadro comparativo, revisión documental, entre otros). Foro analítico o argumentativo (semanas 5 y 6 – Participación en el espacio correspondiente del aula). Entrega final (semana 7 – Ensayo, artículo, cuadro comparativo, revisión documental, entre otros). Evaluación final (semana 8 – Cuestionario de entre 15 y 20 preguntas). | Q20: Las acciones de retroalimentación giran en torno a las siguientes. Formar: donde se crean las condiciones para que los estudiantes adquieran conocimientos, habilidades, actitudes, aptitudes y destrezas. Además, debe promover su desarrollo integral y debe acompañarlos en las situaciones académicas que enfrenten durante el desarrollo de un módulo o una asignatura. Informar: para que los estudiantes identifiquen los cambios que pueden afectarlos directa o indirectamente tanto en el aula de clase como en otros espacios. Prevenir: con el fin de anticiparse a las situaciones académicas que pueden representar dificultad para los estudiantes. Esto se logra a través de la interacción individual con los estudiantes y del completo conocimiento del contexto educativo en que el tutor se desenvuelve. Ayudar a decidir: donde se orienta a los estudiantes para que tomen la mejor decisión ante una situación concreta. El objetivo es que el estudiante fortalezca su autonomía y la toma de decisiones responsable.
A21: =_xlfn.XLOOKUP(B21,'Paso 3 Redacción RA'!I3:I21,'Paso 3 Redacción RA'!C3:C21,,0,1) -> SaberSer | B21: Reconoce los principios éticos del derecho para implementarlos en su conducta y ejercicio profesional, atendiendo a los casos que llegan a su conocimiento en escenarios nacionales e internacionales.
A22: =_xlfn.XLOOKUP(B22,'Paso 3 Redacción RA'!I3:I21,'Paso 3 Redacción RA'!C3:C21,,0,1) -> Saber | B22: Identifica los elementos característicos de la negociación y resolución de conflictos para caracterizar la información y argumentación requerida en los procesos de acuerdos, transacciones o laudos arbitrales que den por terminados los conflictos puestos a su conocimiento.
A23: =_xlfn.XLOOKUP(B23,'Paso 3 Redacción RA'!I3:I21,'Paso 3 Redacción RA'!C3:C21,,0,1) -> SaberHacer | B23: Aplica habilidades de negociación y resolución de conflictos para atender las necesidades de los ciudadanos y la consolidación de acuerdos que den por termino los conflictos puestos a su conocimiento.
A24: =_xlfn.XLOOKUP(B24,'Paso 3 Redacción RA'!I3:I21,'Paso 3 Redacción RA'!C3:C21,,0,1) -> Saber | B24: Reconoce los fundamentos del derecho penal, comercial, público, laboral y privado para determinar el procedimiento a seguir en la resolución de conflictos o de actos jurídicos, observando los principios rectores de cada actividad y atendiendo a la legislación y normatividad vigente, que permitan generar acciones positivas y acordes a las necesidades de los individuos o las organizaciones, según sea el caso. | C24: 2 | D24: Derecho Constitucional | E24: Identifica la estructura del poder público en Colombia en atención a las tareas específicas del Estado, así como el régimen económico y de hacienda pública para determinar las responsabilidades del Estado como garante de derechos fundamentales. Reconoce los mecanismos de exigibilidad de derechos, e instrumentos de participación ciudadana para proyectar soluciones en el ejercicio de la protección de derechos. | F24: TP | H24: X | J24: 3 | K24: =12*J24 -> 36 | L24: =36*J24 -> 108 | M24: =SUM(K24:L24) -> 144 | N24: 1. Supremacía constitucional en la Constitución de 1991, mecanismos de control constitucional. Configuración y alcance del catálogo de derechos fundamentales, económicos, sociales y culturales, e instrumentos para su exigibilidad y protección. Mecanismos de participación ciudadana como manifestación del principio democrático en el Estado Social de Derecho. 2. Mecanismos de control constitucional, alcance del catálogo de derechos fundamentales, económicos, sociales y culturales, e instrumentos para su exigibilidad y protección. Mecanismos de participación ciudadana como manifestación del principio democrático en el Estado Social de Derecho. 3. Rasgos distintivos del modelo de Estado derivado del proceso de constitucionalización en Colombia, considerando sus causas y efectos jurídico-políticos. Configuración conceptual y estructural de la forma de Estado vigente, así como las características del sistema de gobierno, organización territorial, régimen político, y el modelo electoral consagrado en la Constitución de 1991. 4. Organización del poder público en la Constitución de 1991, a partir de la distribución funcional y orgánica de sus ramas y competencias. Régimen económico y de Hacienda Pública. Mecanismos y límites de la reforma constitucional y el concepto de sustitución de la Constitución. | O24: Trabajo directo: Encuentros sincrónicos Mensajería interna Anuncios Trabajo independiente: Lecturas fundamentales y complementarias Recursos de apoyo Trabajo Colaborativo Foros de discusión grupal | P24: Evaluación diagnóstica (semana 1- Cuestionario inicial de, mínimo, cinco preguntas, que recopila información sobre el conocimiento previo o las habilidades del estudiante). Actividad formativa (semana 2 - Foro individual o grupal, creado para que el estudiante participe activamente en la construcción de su conocimiento y desarrollo de habilidades. Varía entre una actividad entregable y la participación en un foro). Actividad de entrega 1 (semana 4 - Actividad individual o grupal, diseñada para evaluar de manera integral el nivel de conocimiento, comprensión y el desempeño de los indicadores de logro. Varía entre entregas independientes o secuenciales). Actividad formativa (semana 5 - Foro individual o grupal, creado para que el estudiante participe activamente en la construcción de su conocimiento y desarrollo de habilidades. Varía entre una actividad entregable y la participación en un foro). Actividad evaluativa (semana 6 - Cuestionario de mínimo cinco preguntas, que da cuenta del desarrollo total o parcial de los indicadores de logro y el desarrollo de los temas vistos hasta la unidad 3). Actividad de entrega 2 (semana 7 - Actividad individual o grupal, diseñada para evaluar de manera integral el nivel de conocimiento, comprensión y el desempeño de los indicadores de logro. Varía entre entregas independientes o secuenciales). Autoevaluación (semana 8 - Cuestionario final de, mínimo, cinco preguntas, en el cual el estudiante reflexiona sobre su propio desempeño, habilidades y resultados en un contexto específico). | Q24: Las acciones de retroalimentación giran en torno a las siguientes. Formar: donde se crean las condiciones para que los estudiantes adquieran conocimientos, habilidades, actitudes, aptitudes y destrezas. Además, debe promover su desarrollo integral y debe acompañarlos en las situaciones académicas que enfrenten durante el desarrollo de un módulo o una asignatura. Informar: para que los estudiantes identifiquen los cambios que pueden afectarlos directa o indirectamente tanto en el aula de clase como en otros espacios. Prevenir: con el fin de anticiparse a las situaciones académicas que pueden representar dificultad para los estudiantes. Esto se logra a través de la interacción individual con los estudiantes y del completo conocimiento del contexto educativo en que el tutor se desenvuelve. Ayudar a decidir: donde se orienta a los estudiantes para que tomen la mejor decisión ante una situación concreta. El objetivo es que el estudiante fortalezca su autonomía y la toma de decisiones responsable.
A25: =_xlfn.XLOOKUP(B25,'Paso 3 Redacción RA'!I4:I22,'Paso 3 Redacción RA'!C4:C22,,0,1) -> SaberSer | B25: Reconoce los principios éticos del derecho para implementarlos en su conducta y ejercicio profesional, atendiendo a los casos que llegan a su conocimiento en escenarios nacionales e internacionales.
A26: =_xlfn.XLOOKUP(B26,'Paso 3 Redacción RA'!I5:I23,'Paso 3 Redacción RA'!C5:C23,,0,1) -> Saber | B26: Identifica los elementos característicos de la negociación y resolución de conflictos para caracterizar la información y argumentación requerida en los procesos de acuerdos, transacciones o laudos arbitrales que den por terminados los conflictos puestos a su conocimiento.
A27: =_xlfn.XLOOKUP(B27,'Paso 3 Redacción RA'!I3:I21,'Paso 3 Redacción RA'!C3:C21,,0,1) -> SaberHacer | B27: Aplica las acciones administrativas y judiciales procedentes del derecho público para proyectar procesos jurídicos que garanticen el reconocimiento y la protección de los derechos de las personas.
A28: =_xlfn.XLOOKUP(B28,'Paso 3 Redacción RA'!I3:I21,'Paso 3 Redacción RA'!C3:C21,,0,1) -> SaberHacer | B28: Aplica habilidades de negociación y resolución de conflictos para atender las necesidades de los ciudadanos y la consolidación de acuerdos que den por termino los conflictos puestos a su conocimiento.
A29: =_xlfn.XLOOKUP(B29,'Paso 3 Redacción RA'!I3:I21,'Paso 3 Redacción RA'!C3:C21,,0,1) -> SaberHacer | B29: Aplica los diferentes regímenes laborales para proyectar soluciones, en el marco jurídico, a las controversias que se originan de estas relaciones.
A30: =_xlfn.XLOOKUP(B30,'Paso 3 Redacción RA'!I3:I21,'Paso 3 Redacción RA'!C3:C21,,0,1) -> Saber | B30: Reconoce los fundamentos del derecho penal, comercial, público, laboral y privado para determinar el procedimiento a seguir en la resolución de conflictos o de actos jurídicos, observando los principios rectores de cada actividad y atendiendo a la legislación y normatividad vigente, que permitan generar acciones positivas y acordes a las necesidades de los individuos o las organizaciones, según sea el caso. | C30: 2 | D30: Argumentación y Lógica Jurídica | E30: Analiza los principales conceptos de la argumentación lógica y las teorías del derecho para establecer diferentes puntos de vista de sus contendientes y propios comunicando de manera efectiva sus argumentos. | F30: TP | H30: X | J30: 3 | K30: =12*J30 -> 36 | L30: =36*J30 -> 108 | M30: =SUM(K30:L30) -> 144 | N30: 1. Teoría de la argumentación jurídica. 2. Hermenéutica y teoría interpretativa de los derechos. 3. Introducción a la lógica jurídica. 4. Tipos de argumentos. | O30: Trabajo directo: Encuentros sincrónicos Mensajería interna Anuncios Trabajo independiente: Lecturas fundamentales y complementarias Recursos de apoyo Trabajo Colaborativo Foros de discusión grupal | P30: Actividad de puntos evaluables (semana 2 – Cuestionario de 5 preguntas). Entrega previa 1 (semana 3 - Laboratorio, taller, ejercicios, resolución de casos o de problemas, desarrollo de procesos o ejecución de propuestas. Entrega de forma individual o grupal, según indicaciones del profesor). Parcial (semana 4 - Cuestionarios de entre 15 y 20 preguntas). Entrega previa 2 (semana 5 - Laboratorio, taller, ejercicios, resolución de casos o de problemas, desarrollo de procesos o ejecución de propuestas. Entrega de forma individual o grupal, según indicaciones dadas por el profesor). Entrega final (semana 7 - Laboratorio, taller, ejercicios, resolución de casos o de problemas, desarrollo de procesos o ejecución de propuestas. Entrega de forma individual o grupal, según indicaciones dadas por el profesor). Evaluación final (semana 8 - Cuestionario de entre 15 y 20 preguntas). | Q30: Las acciones de retroalimentación giran en torno a las siguientes. Formar: donde se crean las condiciones para que los estudiantes adquieran conocimientos, habilidades, actitudes, aptitudes y destrezas. Además, debe promover su desarrollo integral y debe acompañarlos en las situaciones académicas que enfrenten durante el desarrollo de un módulo o una asignatura. Informar: para que los estudiantes identifiquen los cambios que pueden afectarlos directa o indirectamente tanto en el aula de clase como en otros espacios. Prevenir: con el fin de anticiparse a las situaciones académicas que pueden representar dificultad para los estudiantes. Esto se logra a través de la interacción individual con los estudiantes y del completo conocimiento del contexto educativo en que el tutor se desenvuelve. Ayudar a decidir: donde se orienta a los estudiantes para que tomen la mejor decisión ante una situación concreta. El objetivo es que el estudiante fortalezca su autonomía y la toma de decisiones responsable.
A31: =_xlfn.XLOOKUP(B31,'Paso 3 Redacción RA'!I3:I21,'Paso 3 Redacción RA'!C3:C21,,0,1) -> SaberSer | B31: Reconoce los principios éticos del derecho para implementarlos en su conducta y ejercicio profesional, atendiendo a los casos que llegan a su conocimiento en escenarios nacionales e internacionales.
A32: =_xlfn.XLOOKUP(B32,'Paso 3 Redacción RA'!I3:I21,'Paso 3 Redacción RA'!C3:C21,,0,1) -> Saber | B32: Identifica los elementos característicos de la negociación y resolución de conflictos para caracterizar la información y argumentación requerida en los procesos de acuerdos, transacciones o laudos arbitrales que den por terminados los conflictos puestos a su conocimiento.
A33: =_xlfn.XLOOKUP(B33,'Paso 3 Redacción RA'!I3:I21,'Paso 3 Redacción RA'!C3:C21,,0,1) -> SaberHacer | B33: Aplica habilidades de negociación y resolución de conflictos para atender las necesidades de los ciudadanos y la consolidación de acuerdos que den por termino los conflictos puestos a su conocimiento.
A34: =_xlfn.XLOOKUP(B34,'Paso 3 Redacción RA'!I3:I21,'Paso 3 Redacción RA'!C3:C21,,0,1) -> Saber | B34: Reconoce los fundamentos del derecho penal, comercial, público, laboral y privado para determinar el procedimiento a seguir en la resolución de conflictos o de actos jurídicos, observando los principios rectores de cada actividad y atendiendo a la legislación y normatividad vigente, que permitan generar acciones positivas y acordes a las necesidades de los individuos o las organizaciones, según sea el caso. | C34: 2 | D34: Bienes Civiles y Mercantiles | E34: Distingue los bienes corporales e incorporales para establecer los modos de adquirir el dominio civiles y comerciales en atención a las condiciones de la ejecución del acto. | F34: TP | H34: X | J34: 3 | K34: =12*J34 -> 36 | L34: =36*J34 -> 108 | M34: =SUM(K34:L34) -> 144 | N34: 1. Noción de bienes y clasificación en bienes corporales e incorporales. 2. Modos de adquirir el dominio. 3. Limitaciones al ejercicio del derecho de dominio. 4. Bienes mercantiles y títulos valores. | O34: Trabajo directo: Encuentros sincrónicos Mensajería interna Anuncios Trabajo independiente: Lecturas fundamentales y complementarias Recursos de apoyo Trabajo Colaborativo Foros de discusión grupal | P34: Actividad de puntos evaluables (semana 2 – Cuestionario de 5 preguntas). Entrega previa 1 (semana 3 - Laboratorio, taller, ejercicios, resolución de casos o de problemas, desarrollo de procesos o ejecución de propuestas. Entrega de forma individual o grupal, según indicaciones del profesor). Parcial (semana 4 - Cuestionarios de entre 15 y 20 preguntas). Entrega previa 2 (semana 5 - Laboratorio, taller, ejercicios, resolución de casos o de problemas, desarrollo de procesos o ejecución de propuestas. Entrega de forma individual o grupal, según indicaciones dadas por el profesor). Entrega final (semana 7 - Laboratorio, taller, ejercicios, resolución de casos o de problemas, desarrollo de procesos o ejecución de propuestas. Entrega de forma individual o grupal, según indicaciones dadas por el profesor). Evaluación final (semana 8 - Cuestionario de entre 15 y 20 preguntas). | Q34: Las acciones de retroalimentación giran en torno a las siguientes. Formar: donde se crean las condiciones para que los estudiantes adquieran conocimientos, habilidades, actitudes, aptitudes y destrezas. Además, debe promover su desarrollo integral y debe acompañarlos en las situaciones académicas que enfrenten durante el desarrollo de un módulo o una asignatura. Informar: para que los estudiantes identifiquen los cambios que pueden afectarlos directa o indirectamente tanto en el aula de clase como en otros espacios. Prevenir: con el fin de anticiparse a las situaciones académicas que pueden representar dificultad para los estudiantes. Esto se logra a través de la interacción individual con los estudiantes y del completo conocimiento del contexto educativo en que el tutor se desenvuelve. Ayudar a decidir: donde se orienta a los estudiantes para que tomen la mejor decisión ante una situación concreta. El objetivo es que el estudiante fortalezca su autonomía y la toma de decisiones responsable.
A35: =_xlfn.XLOOKUP(B35,'Paso 3 Redacción RA'!I3:I21,'Paso 3 Redacción RA'!C3:C21,,0,1) -> #N/A | B35: Aplica el derecho privado, atendiendo la legislación y normatividad vigente, para dar solución a casos concretos.
A36: =_xlfn.XLOOKUP(B36,'Paso 3 Redacción RA'!I3:I21,'Paso 3 Redacción RA'!C3:C21,,0,1) -> SaberSer | B36: Reconoce los principios éticos del derecho para implementarlos en su conducta y ejercicio profesional, atendiendo a los casos que llegan a su conocimiento en escenarios nacionales e internacionales.
A37: =_xlfn.XLOOKUP(B37,'Paso 3 Redacción RA'!I3:I21,'Paso 3 Redacción RA'!C3:C21,,0,1) -> SaberHacer | B37: Aplica el régimen de las obligaciones y los contratos comerciales de cualquier tipología, nacional e internacional, atendiendo a las necesidades que se derivan de las relaciones comerciales entorno a su nacimiento, modificación y extinción, para adelantar los procesos jurídicos que correspondan al caso.
A38: =_xlfn.XLOOKUP(B38,'Paso 3 Redacción RA'!I3:I21,'Paso 3 Redacción RA'!C3:C21,,0,1) -> Saber | B38: Identifica los elementos característicos de la negociación y resolución de conflictos para caracterizar la información y argumentación requerida en los procesos de acuerdos, transacciones o laudos arbitrales que den por terminados los conflictos puestos a su conocimiento.
A39: =_xlfn.XLOOKUP(B39,'Paso 3 Redacción RA'!I3:I21,'Paso 3 Redacción RA'!C3:C21,,0,1) -> SaberHacer | B39: Aplica las acciones administrativas y judiciales procedentes del derecho público para proyectar procesos jurídicos que garanticen el reconocimiento y la protección de los derechos de las personas.
A40: =_xlfn.XLOOKUP(B40,'Paso 3 Redacción RA'!I3:I21,'Paso 3 Redacción RA'!C3:C21,,0,1) -> SaberHacer | B40: Aplica el derecho penal en el procedimiento y la acción procedente en atención al tipo penal identificado para adelantar los procesos jurídicos que correspondan al caso.
A41: =_xlfn.XLOOKUP(B41,'Paso 3 Redacción RA'!I3:I21,'Paso 3 Redacción RA'!C3:C21,,0,1) -> SaberHacer | B41: Aplica habilidades de negociación y resolución de conflictos para atender las necesidades de los ciudadanos y la consolidación de acuerdos que den por termino los conflictos puestos a su conocimiento.
A42: =_xlfn.XLOOKUP(B42,'Paso 3 Redacción RA'!I3:I21,'Paso 3 Redacción RA'!C3:C21,,0,1) -> Saber | B42: Identifica fenómenos contemporáneos y su relación con la profesión, para determinar sus impactos e influencia en la sociedad, de forma responsable y crítica. | C42: 3 | D42: Oportunidades para Emprender | E42: Propone soluciones a los problemas, frustraciones y expectativas de un grupo de personas en su comunidad para idear productos o servicios con valor agregado dentro de su campo de acción profesional. Diseña una idea de negocio que represente una oportunidad de mercado teniendo en cuenta sus habilidades para emprender y el análisis del entorno. | F42: TP | G42: X | J42: 3 | K42: =12*J42 -> 36 | L42: =36*J42 -> 108 | M42: =SUM(K42:L42) -> 144 | N42: 1. Empatía y Comprensión del Usuario 2. Co-creación con los Usuarios 3. Enfoque en la Experiencia del Usuario 4. Diseño del modelo de negocio | O42: Trabajo directo: Encuentros sincrónicos Mensajería interna Anuncios Trabajo independiente: Lecturas fundamentales y complementarias Material de trabajo Participación en foros | P42: Evaluación diagnóstica: Cuestionario inicial de mínimo cinco preguntas que recopila información sobre el conocimiento previo y las habilidades del estudiante. Actividad formativa: Foro individual o grupal, creado para que el estudiante participe activamente en la construcción de su conocimiento y desarrollo de habilidades. Varía entre una actividad entregable y la participación en un foro. Actividad de entrega 1 y 2: Actividad individual o grupal, diseñada para evaluar de manera integral el nivel de conocimiento, comprensión y el desempeño de los indicadores de logro. Varía entre entregas independientes o secuenciales. Actividad evaluativa: Cuestionario de, mínimo, cinco preguntas, que da cuenta del desarrollo total o parcial de los indicadores de logro y el desarrollo de los temas vistos hasta la unidad 3. Autoevaluación: Cuestionario final de mínimo cinco preguntas en el cual el estudiante reflexiona sobre su propio desempeño, habilidades y resultados en un contexto específico. | Q42: Las acciones de retroalimentación giran en torno a las siguientes. Formar: donde se crean las condiciones para que los estudiantes adquieran conocimientos, habilidades, actitudes, aptitudes y destrezas. Además, debe promover su desarrollo integral y debe acompañarlos en las situaciones académicas que enfrenten durante el desarrollo de un módulo o una asignatura. Informar: para que los estudiantes identifiquen los cambios que pueden afectarlos directa o indirectamente tanto en el aula de clase como en otros espacios. Prevenir: con el fin de anticiparse a las situaciones académicas que pueden representar dificultad para los estudiantes. Esto se logra a través de la interacción individual con los estudiantes y del completo conocimiento del contexto educativo en que el tutor se desenvuelve. Ayudar a decidir: donde se orienta a los estudiantes para que tomen la mejor decisión ante una situación concreta. El objetivo es que el estudiante fortalezca su autonomía y la toma de decisiones responsable.
A43: =_xlfn.XLOOKUP(B43,'Paso 3 Redacción RA'!I3:I21,'Paso 3 Redacción RA'!C3:C21,,0,1) -> Saber | B43: Identifica fenómenos contemporáneos y su relación con la profesión, para determinar sus impactos e influencia en la sociedad, de forma responsable y crítica. | C43: 3 | D43: Pensamiento Crítico y Ciudadanías Activas | E43: Identifica los Derechos y Deberes consignados en la Constitución 1991 en relación con la ciudadanía de manera local y global para la comprensión de inmersiones sociales éticas. Reflexiona los impactos de la investigación- acción sin daño en los espacios académicos y los territorios para el abordaje desde proyectos de investigación formativa. Elabora el diseño de planes detallados desde abordajes investigativos e inmersiones creativas para divulgar hallazgos en el ámbito académico. | F43: TP | G43: X | J43: 3 | K43: =12*J43 -> 36 | L43: =36*J43 -> 108 | M43: =SUM(K43:L43) -> 144 | N43: 1. Pacto social colombiano y marco de referencias de DDHH internacionales 2. Planes detallados e inmersiones sociales desde procesos participativos, acciones sociales e iniciativas ciudadanas como respuesta a problemas glocales 3. Perspectivas para la participación ciudadana en los territorios 4. Los avances tecnológicos y su impacto en lo social, cultural y ambiental en el marco de las sociedades de información | O43: Trabajo directo: Encuentros sincrónicos Mensajería interna Anuncios Trabajo independiente: Lecturas fundamentales y complementarias Material de trabajo Participación en foros | P43: 1. Actividad de puntos evaluables escenario 1 (diagnóstica) - Cuestionario de 5 preguntas. 2. Entrega escenario 2 (formativa) 3. Entrega escenario 4 (formativa) 4. Entrega escenario 5 (formativa) 5. Quiz escenario 6 (sumativa) | Q43: Las acciones de retroalimentación giran en torno a las siguientes. Formar: donde se crean las condiciones para que los estudiantes adquieran conocimientos, habilidades, actitudes, aptitudes y destrezas. Además, debe promover su desarrollo integral y debe acompañarlos en las situaciones académicas que enfrenten durante el desarrollo de un módulo o una asignatura. Informar: para que los estudiantes identifiquen los cambios que pueden afectarlos directa o indirectamente tanto en el aula de clase como en otros espacios. Prevenir: con el fin de anticiparse a las situaciones académicas que pueden representar dificultad para los estudiantes. Esto se logra a través de la interacción individual con los estudiantes y del completo conocimiento del contexto educativo en que el tutor se desenvuelve. Ayudar a decidir: donde se orienta a los estudiantes para que tomen la mejor decisión ante una situación concreta. El objetivo es que el estudiante fortalezca su autonomía y la toma de decisiones responsable.
A44: =_xlfn.XLOOKUP(B44,'Paso 3 Redacción RA'!I3:I21,'Paso 3 Redacción RA'!C3:C21,,0,1) -> Saber | B44: Reconoce los fundamentos del derecho penal, comercial, público, laboral y privado para determinar el procedimiento a seguir en la resolución de conflictos o de actos jurídicos, observando los principios rectores de cada actividad y atendiendo a la legislación y normatividad vigente, que permitan generar acciones positivas y acordes a las necesidades de los individuos o las organizaciones, según sea el caso. | C44: 3 | D44: Fundamentos de Derecho Procesal | E44: Analiza el requisito de procedibilidad, la jurisdicción, la competencia, los sujetos y presupuestos procesales para estructurar el procedimiento, la demanda, contestación de la demanda y audiencias propias de una actuación judicial. | F44: TP | H44: X | J44: 3 | K44: =12*J44 -> 36 | L44: =36*J44 -> 108 | M44: =SUM(K44:L44) -> 144 | N44: 1. Temas introductorios, contextualización del Derecho Procesal. 2. Mecanismos alternativos de resolución de conflictos, actos, presupuestos y sujetos. 3. La demanda, su admisión, reforma y adición. 4. La contestación de la demanda y audiencias. | O44: Trabajo directo: Encuentros sincrónicos Mensajería interna Anuncios Trabajo independiente: Lecturas fundamentales y complementarias Recursos de apoyo Trabajo Colaborativo Foros de discusión grupal | P44: Actividad de puntos evaluables (semana 2 – Cuestionario de 5 preguntas). Entrega previa 1 (semana 3 - Laboratorio, taller, ejercicios, resolución de casos o de problemas, desarrollo de procesos o ejecución de propuestas. Entrega de forma individual o grupal, según indicaciones del profesor). Parcial (semana 4 - Cuestionarios de entre 15 y 20 preguntas). Entrega previa 2 (semana 5 - Laboratorio, taller, ejercicios, resolución de casos o de problemas, desarrollo de procesos o ejecución de propuestas. Entrega de forma individual o grupal, según indicaciones dadas por el profesor). Entrega final (semana 7 - Laboratorio, taller, ejercicios, resolución de casos o de problemas, desarrollo de procesos o ejecución de propuestas. Entrega de forma individual o grupal, según indicaciones dadas por el profesor). Evaluación final (semana 8 - Cuestionario de entre 15 y 20 preguntas). | Q44: Las acciones de retroalimentación giran en torno a las siguientes. Formar: donde se crean las condiciones para que los estudiantes adquieran conocimientos, habilidades, actitudes, aptitudes y destrezas. Además, debe promover su desarrollo integral y debe acompañarlos en las situaciones académicas que enfrenten durante el desarrollo de un módulo o una asignatura. Informar: para que los estudiantes identifiquen los cambios que pueden afectarlos directa o indirectamente tanto en el aula de clase como en otros espacios. Prevenir: con el fin de anticiparse a las situaciones académicas que pueden representar dificultad para los estudiantes. Esto se logra a través de la interacción individual con los estudiantes y del completo conocimiento del contexto educativo en que el tutor se desenvuelve. Ayudar a decidir: donde se orienta a los estudiantes para que tomen la mejor decisión ante una situación concreta. El objetivo es que el estudiante fortalezca su autonomía y la toma de decisiones responsable.
A45: =_xlfn.XLOOKUP(B45,'Paso 3 Redacción RA'!I3:I21,'Paso 3 Redacción RA'!C3:C21,,0,1) -> SaberHacer | B45: Aplica el derecho privado, atendiendo la legislación y normatividad vigente, para dar solución a casos concretos.
A46: =_xlfn.XLOOKUP(B46,'Paso 3 Redacción RA'!I3:I21,'Paso 3 Redacción RA'!C3:C21,,0,1) -> SaberSer | B46: Reconoce los principios éticos del derecho para implementarlos en su conducta y ejercicio profesional, atendiendo a los casos que llegan a su conocimiento en escenarios nacionales e internacionales.
A47: =_xlfn.XLOOKUP(B47,'Paso 3 Redacción RA'!I3:I21,'Paso 3 Redacción RA'!C3:C21,,0,1) -> SaberHacer | B47: Aplica el régimen de las obligaciones y los contratos comerciales de cualquier tipología, nacional e internacional, atendiendo a las necesidades que se derivan de las relaciones comerciales entorno a su nacimiento, modificación y extinción, para adelantar los procesos jurídicos que correspondan al caso.
A48: =_xlfn.XLOOKUP(B48,'Paso 3 Redacción RA'!I3:I21,'Paso 3 Redacción RA'!C3:C21,,0,1) -> Saber | B48: Identifica los elementos característicos de la negociación y resolución de conflictos para caracterizar la información y argumentación requerida en los procesos de acuerdos, transacciones o laudos arbitrales que den por terminados los conflictos puestos a su conocimiento.
A49: =_xlfn.XLOOKUP(B49,'Paso 3 Redacción RA'!I3:I21,'Paso 3 Redacción RA'!C3:C21,,0,1) -> SaberHacer | B49: Aplica las acciones administrativas y judiciales procedentes del derecho público para proyectar procesos jurídicos que garanticen el reconocimiento y la protección de los derechos de las personas.
A50: =_xlfn.XLOOKUP(B50,'Paso 3 Redacción RA'!I3:I21,'Paso 3 Redacción RA'!C3:C21,,0,1) -> SaberHacer | B50: Aplica el derecho penal en el procedimiento y la acción procedente en atención al tipo penal identificado para adelantar los procesos jurídicos que correspondan al caso.
A51: =_xlfn.XLOOKUP(B51,'Paso 3 Redacción RA'!I3:I21,'Paso 3 Redacción RA'!C3:C21,,0,1) -> SaberHacer | B51: Aplica habilidades de negociación y resolución de conflictos para atender las necesidades de los ciudadanos y la consolidación de acuerdos que den por termino los conflictos puestos a su conocimiento.
A52: =_xlfn.XLOOKUP(B52,'Paso 3 Redacción RA'!I3:I21,'Paso 3 Redacción RA'!C3:C21,,0,1) -> SaberHacer | B52: Aplica los diferentes regímenes laborales para proyectar soluciones, en el marco jurídico, a las controversias que se originan de estas relaciones.
A53: =_xlfn.XLOOKUP(B53,'Paso 3 Redacción RA'!I3:I21,'Paso 3 Redacción RA'!C3:C21,,0,1) -> Saber | B53: Reconoce los fundamentos del derecho penal, comercial, público, laboral y privado para determinar el procedimiento a seguir en la resolución de conflictos o de actos jurídicos, observando los principios rectores de cada actividad y atendiendo a la legislación y normatividad vigente, que permitan generar acciones positivas y acordes a las necesidades de los individuos o las organizaciones, según sea el caso. | C53: 3 | D53: Obligaciones | E53: Diferencia las clases de obligaciones y los efectos que cada obligación produce en el derecho privado como base delos negocios jurídicos para exponer con criterio y argumentos las diferentes formas de extinguir las obligaciones y los vínculos jurídicos que nacen entre los intervinientes de una relación obligacional. | F53: TP | H53: X | J53: 3 | K53: =12*J53 -> 36 | L53: =36*J53 -> 108 | M53: =SUM(K53:L53) -> 144 | N53: 1. Concepto de las obligaciones y sus elementos esenciales. 2. Clasificación de las obligaciones. 3. Incumplimiento de las obligaciones. 4. La extinción de las obligaciones. | O53: Trabajo directo: Encuentros sincrónicos Mensajería interna Anuncios Trabajo independiente: Lecturas fundamentales y complementarias Recursos de apoyo Trabajo Colaborativo Foros de discusión grupal | P53: Actividad de puntos evaluables (semana 2 – Cuestionario de 5 preguntas). Entrega previa 1 (semana 3 - Laboratorio, taller, ejercicios, resolución de casos o de problemas, desarrollo de procesos o ejecución de propuestas. Entrega de forma individual o grupal, según indicaciones del profesor). Parcial (semana 4 - Cuestionarios de entre 15 y 20 preguntas). Entrega previa 2 (semana 5 - Laboratorio, taller, ejercicios, resolución de casos o de problemas, desarrollo de procesos o ejecución de propuestas. Entrega de forma individual o grupal, según indicaciones dadas por el profesor). Entrega final (semana 7 - Laboratorio, taller, ejercicios, resolución de casos o de problemas, desarrollo de procesos o ejecución de propuestas. Entrega de forma individual o grupal, según indicaciones dadas por el profesor). Evaluación final (semana 8 - Cuestionario de entre 15 y 20 preguntas). | Q53: Las acciones de retroalimentación giran en torno a las siguientes. Formar: donde se crean las condiciones para que los estudiantes adquieran conocimientos, habilidades, actitudes, aptitudes y destrezas. Además, debe promover su desarrollo integral y debe acompañarlos en las situaciones académicas que enfrenten durante el desarrollo de un módulo o una asignatura. Informar: para que los estudiantes identifiquen los cambios que pueden afectarlos directa o indirectamente tanto en el aula de clase como en otros espacios. Prevenir: con el fin de anticiparse a las situaciones académicas que pueden representar dificultad para los estudiantes. Esto se logra a través de la interacción individual con los estudiantes y del completo conocimiento del contexto educativo en que el tutor se desenvuelve. Ayudar a decidir: donde se orienta a los estudiantes para que tomen la mejor decisión ante una situación concreta. El objetivo es que el estudiante fortalezca su autonomía y la toma de decisiones responsable.
A54: =_xlfn.XLOOKUP(B54,'Paso 3 Redacción RA'!I4:I22,'Paso 3 Redacción RA'!C4:C22,,0,1) -> SaberHacer | B54: Aplica el derecho privado, atendiendo la legislación y normatividad vigente, para dar solución a casos concretos.
A55: =_xlfn.XLOOKUP(B55,'Paso 3 Redacción RA'!I5:I23,'Paso 3 Redacción RA'!C5:C23,,0,1) -> SaberSer | B55: Reconoce los principios éticos del derecho para implementarlos en su conducta y ejercicio profesional, atendiendo a los casos que llegan a su conocimiento en escenarios nacionales e internacionales.
A56: =_xlfn.XLOOKUP(B56,'Paso 3 Redacción RA'!I6:I24,'Paso 3 Redacción RA'!C6:C24,,0,1) -> SaberHacer | B56: Aplica el régimen de las obligaciones y los contratos comerciales de cualquier tipología, nacional e internacional, atendiendo a las necesidades que se derivan de las relaciones comerciales entorno a su nacimiento, modificación y extinción, para adelantar los procesos jurídicos que correspondan al caso.
A57: =_xlfn.XLOOKUP(B57,'Paso 3 Redacción RA'!I7:I25,'Paso 3 Redacción RA'!C7:C25,,0,1) -> Saber | B57: Identifica los elementos característicos de la negociación y resolución de conflictos para caracterizar la información y argumentación requerida en los procesos de acuerdos, transacciones o laudos arbitrales que den por terminados los conflictos puestos a su conocimiento.
A58: =_xlfn.XLOOKUP(B58,'Paso 3 Redacción RA'!I8:I26,'Paso 3 Redacción RA'!C8:C26,,0,1) -> SaberHacer | B58: Aplica las acciones administrativas y judiciales procedentes del derecho público para proyectar procesos jurídicos que garanticen el reconocimiento y la protección de los derechos de las personas.
A59: =_xlfn.XLOOKUP(B59,'Paso 3 Redacción RA'!I3:I21,'Paso 3 Redacción RA'!C3:C21,,0,1) -> SaberHacer | B59: Aplica el derecho penal en el procedimiento y la acción procedente en atención al tipo penal identificado para adelantar los procesos jurídicos que correspondan al caso.
A60: =_xlfn.XLOOKUP(B60,'Paso 3 Redacción RA'!I3:I21,'Paso 3 Redacción RA'!C3:C21,,0,1) -> SaberHacer | B60: Aplica habilidades de negociación y resolución de conflictos para atender las necesidades de los ciudadanos y la consolidación de acuerdos que den por termino los conflictos puestos a su conocimiento.
A61: =_xlfn.XLOOKUP(B61,'Paso 3 Redacción RA'!I3:I21,'Paso 3 Redacción RA'!C3:C21,,0,1) -> Saber | B61: Reconoce los fundamentos del derecho penal, comercial, público, laboral y privado para determinar el procedimiento a seguir en la resolución de conflictos o de actos jurídicos, observando los principios rectores de cada actividad y atendiendo a la legislación y normatividad vigente, que permitan generar acciones positivas y acordes a las necesidades de los individuos o las organizaciones, según sea el caso. | C61: 3 | D61: Penal General | E61: Analiza los elementos y conceptos básicos del derecho penal general considerando el modelo constitucional y las teorías adoptas por la legislación colombiana para explicar los conceptos de conducta, tipicidad, antijuricidad, culpabilidad y concursos. | F61: TP | H61: X | J61: 3 | K61: =12*J61 -> 36 | L61: =36*J61 -> 108 | M61: =SUM(K61:L61) -> 144 | N61: 1. Principios y nociones generales del Derecho Penal. 2. La conducta punible. 3. Tipicidad, antijuridicidad, culpabilidad y punibilidad. 4. Dispositivos amplificadores del tipo penal. | O61: Trabajo directo: Encuentros sincrónicos Mensajería interna Anuncios Trabajo independiente: Lecturas fundamentales y complementarias Recursos de apoyo Trabajo Colaborativo Foros de discusión grupal | P61: Actividad de puntos evaluables (semana 2 – Cuestionario de 5 preguntas). Entrega previa 1 (semana 3 - Laboratorio, taller, ejercicios, resolución de casos o de problemas, desarrollo de procesos o ejecución de propuestas. Entrega de forma individual o grupal, según indicaciones del profesor). Parcial (semana 4 - Cuestionarios de entre 15 y 20 preguntas). Entrega previa 2 (semana 5 - Laboratorio, taller, ejercicios, resolución de casos o de problemas, desarrollo de procesos o ejecución de propuestas. Entrega de forma individual o grupal, según indicaciones dadas por el profesor). Entrega final (semana 7 - Laboratorio, taller, ejercicios, resolución de casos o de problemas, desarrollo de procesos o ejecución de propuestas. Entrega de forma individual o grupal, según indicaciones dadas por el profesor). Evaluación final (semana 8 - Cuestionario de entre 15 y 20 preguntas). | Q61: Las acciones de retroalimentación giran en torno a las siguientes. Formar: donde se crean las condiciones para que los estudiantes adquieran conocimientos, habilidades, actitudes, aptitudes y destrezas. Además, debe promover su desarrollo integral y debe acompañarlos en las situaciones académicas que enfrenten durante el desarrollo de un módulo o una asignatura. Informar: para que los estudiantes identifiquen los cambios que pueden afectarlos directa o indirectamente tanto en el aula de clase como en otros espacios. Prevenir: con el fin de anticiparse a las situaciones académicas que pueden representar dificultad para los estudiantes. Esto se logra a través de la interacción individual con los estudiantes y del completo conocimiento del contexto educativo en que el tutor se desenvuelve. Ayudar a decidir: donde se orienta a los estudiantes para que tomen la mejor decisión ante una situación concreta. El objetivo es que el estudiante fortalezca su autonomía y la toma de decisiones responsable.
B62: Reconoce los principios éticos del derecho para implementarlos en su conducta y ejercicio profesional, atendiendo a los casos que llegan a su conocimiento en escenarios nacionales e internacionales.
B63: Aplica el régimen de las obligaciones y los contratos comerciales de cualquier tipología, nacional e internacional, atendiendo a las necesidades que se derivan de las relaciones comerciales entorno a su nacimiento, modificación y extinción, para adelantar los procesos jurídicos que correspondan al caso.
B64: Identifica los elementos característicos de la negociación y resolución de conflictos para caracterizar la información y argumentación requerida en los procesos de acuerdos, transacciones o laudos arbitrales que den por terminados los conflictos puestos a su conocimiento.
B65: Aplica las acciones administrativas y judiciales procedentes del derecho público para proyectar procesos jurídicos que garanticen el reconocimiento y la protección de los derechos de las personas.
A66: =_xlfn.XLOOKUP(B66,'Paso 3 Redacción RA'!I3:I21,'Paso 3 Redacción RA'!C3:C21,,0,1) -> SaberHacer | B66: Aplica el derecho penal en el procedimiento y la acción procedente en atención al tipo penal identificado para adelantar los procesos jurídicos que correspondan al caso.
A67: =_xlfn.XLOOKUP(B67,'Paso 3 Redacción RA'!I3:I21,'Paso 3 Redacción RA'!C3:C21,,0,1) -> SaberHacer | B67: Aplica habilidades de negociación y resolución de conflictos para atender las necesidades de los ciudadanos y la consolidación de acuerdos que den por termino los conflictos puestos a su conocimiento.
A68: =_xlfn.XLOOKUP(B68,'Paso 3 Redacción RA'!I3:I21,'Paso 3 Redacción RA'!C3:C21,,0,1) -> Saber | B68: Reconoce los fundamentos del derecho penal, comercial, público, laboral y privado para determinar el procedimiento a seguir en la resolución de conflictos o de actos jurídicos, observando los principios rectores de cada actividad y atendiendo a la legislación y normatividad vigente, que permitan generar acciones positivas y acordes a las necesidades de los individuos o las organizaciones, según sea el caso. | C68: 3 | D68: Derecho Laboral Individual y Seguridad Social | E68: Reconoce los elementos y conceptos básicos del derecho laboral individual y seguridad social desde los fundamentos normativos y constitucionales (Código Sustantivo del Trabajo y la Constitución Política de Colombia), para aplicarlos en la resolución de contextos con problemáticas laborales. Explica los requisitos que debe reunir un contrato de trabajo para determinar los derechos ciertos e indiscutibles que surgen de esa relación jurídica. | F68: TP | H68: X | J68: 3 | K68: =12*J68 -> 36 | L68: =36*J68 -> 108 | M68: =SUM(K68:L68) -> 144 | N68: 1. Historia, principios generales y fuentes del Derecho Laboral. 2. Contrato de trabajo, jornada laboral, salario y prestaciones sociales. 3. Reglamento interno de trabajo y fueros laborales. 4. Seguridad Social. | O68: Trabajo directo: Encuentros sincrónicos Mensajería interna Anuncios Trabajo independiente: Lecturas fundamentales y complementarias Recursos de apoyo Trabajo Colaborativo Foros de discusión grupal | P68: Actividad de puntos evaluables (semana 2 – Cuestionario de 5 preguntas). Entrega previa 1 (semana 3 - Laboratorio, taller, ejercicios, resolución de casos o de problemas, desarrollo de procesos o ejecución de propuestas. Entrega de forma individual o grupal, según indicaciones del profesor). Parcial (semana 4 - Cuestionarios de entre 15 y 20 preguntas). Entrega previa 2 (semana 5 - Laboratorio, taller, ejercicios, resolución de casos o de problemas, desarrollo de procesos o ejecución de propuestas. Entrega de forma individual o grupal, según indicaciones dadas por el profesor). Entrega final (semana 7 - Laboratorio, taller, ejercicios, resolución de casos o de problemas, desarrollo de procesos o ejecución de propuestas. Entrega de forma individual o grupal, según indicaciones dadas por el profesor). Evaluación final (semana 8 - Cuestionario de entre 15 y 20 preguntas). | Q68: Las acciones de retroalimentación giran en torno a las siguientes. Formar: donde se crean las condiciones para que los estudiantes adquieran conocimientos, habilidades, actitudes, aptitudes y destrezas. Además, debe promover su desarrollo integral y debe acompañarlos en las situaciones académicas que enfrenten durante el desarrollo de un módulo o una asignatura. Informar: para que los estudiantes identifiquen los cambios que pueden afectarlos directa o indirectamente tanto en el aula de clase como en otros espacios. Prevenir: con el fin de anticiparse a las situaciones académicas que pueden representar dificultad para los estudiantes. Esto se logra a través de la interacción individual con los estudiantes y del completo conocimiento del contexto educativo en que el tutor se desenvuelve. Ayudar a decidir: donde se orienta a los estudiantes para que tomen la mejor decisión ante una situación concreta. El objetivo es que el estudiante fortalezca su autonomía y la toma de decisiones responsable.
A69: =_xlfn.XLOOKUP(B69,'Paso 3 Redacción RA'!I4:I22,'Paso 3 Redacción RA'!C4:C22,,0,1) -> SaberSer | B69: Reconoce los principios éticos del derecho para implementarlos en su conducta y ejercicio profesional, atendiendo a los casos que llegan a su conocimiento en escenarios nacionales e internacionales.
A70: =_xlfn.XLOOKUP(B70,'Paso 3 Redacción RA'!I5:I23,'Paso 3 Redacción RA'!C5:C23,,0,1) -> SaberHacer | B70: Aplica el régimen de las obligaciones y los contratos comerciales de cualquier tipología, nacional e internacional, atendiendo a las necesidades que se derivan de las relaciones comerciales entorno a su nacimiento, modificación y extinción, para adelantar los procesos jurídicos que correspondan al caso.
A71: =_xlfn.XLOOKUP(B71,'Paso 3 Redacción RA'!I6:I24,'Paso 3 Redacción RA'!C6:C24,,0,1) -> Saber | B71: Identifica los elementos característicos de la negociación y resolución de conflictos para caracterizar la información y argumentación requerida en los procesos de acuerdos, transacciones o laudos arbitrales que den por terminados los conflictos puestos a su conocimiento.
A72: =_xlfn.XLOOKUP(B72,'Paso 3 Redacción RA'!I7:I25,'Paso 3 Redacción RA'!C7:C25,,0,1) -> SaberHacer | B72: Aplica las acciones administrativas y judiciales procedentes del derecho público para proyectar procesos jurídicos que garanticen el reconocimiento y la protección de los derechos de las personas.
A73: =_xlfn.XLOOKUP(B73,'Paso 3 Redacción RA'!I3:I21,'Paso 3 Redacción RA'!C3:C21,,0,1) -> SaberHacer | B73: Aplica habilidades de negociación y resolución de conflictos para atender las necesidades de los ciudadanos y la consolidación de acuerdos que den por termino los conflictos puestos a su conocimiento.
A74: =_xlfn.XLOOKUP(B74,'Paso 3 Redacción RA'!I3:I21,'Paso 3 Redacción RA'!C3:C21,,0,1) -> SaberHacer | B74: Aplica los diferentes regímenes laborales para proyectar soluciones, en el marco jurídico, a las controversias que se originan de estas relaciones.
A75: =_xlfn.XLOOKUP(B75,'Paso 3 Redacción RA'!I3:I21,'Paso 3 Redacción RA'!C3:C21,,0,1) -> Saber | B75: Identifica fenómenos contemporáneos y su relación con la profesión, para determinar sus impactos e influencia en la sociedad, de forma responsable y crítica. | C75: 4 | D75: Desarrollo Sostenible | E75: Identifica ejemplos de problemas ambientales, sociales y económicos en la sociedad contemporánea para analizar sus causas y efectos desde el enfoque del desarrollo sostenible a escala local y global. Compara enfoques y aproximaciones tanto privados como público/colectivos desde la sostenibilidad y otras visiones alternativas para proponer ideas de solución que respondan a los desafíos contemporáneos. | F75: TP | G75: X | J75: 3 | K75: =12*J75 -> 36 | L75: =36*J75 -> 108 | M75: =SUM(K75:L75) -> 144 | N75: 1. Análisis de la Era del Antropoceno 2. Otras Alternativas al Desarrollo Sostenible 3. Ciudadanía y Políticas Públicas para el Desarrollo Sostenible 4. El aporte de Negocios para la Búsqueda del Desarrollo Sostenible | O75: Trabajo directo: Encuentros sincrónicos Mensajería interna Anuncios Trabajo independiente: Lecturas fundamentales y complementarias Material de trabajo Participación en foros | P75: Evaluación diagnóstica: Cuestionario inicial de mínimo cinco preguntas que recopila información sobre el conocimiento previo y las habilidades del estudiante. Actividad formativa: Foro individual o grupal, creado para que el estudiante participe activamente en la construcción de su conocimiento y desarrollo de habilidades. Varía entre una actividad entregable y la participación en un foro. Actividad de entrega 1 y 2: Actividad individual o grupal, diseñada para evaluar de manera integral el nivel de conocimiento, comprensión y el desempeño de los indicadores de logro. Varía entre entregas independientes o secuenciales. Actividad evaluativa: Cuestionario de, mínimo, cinco preguntas, que da cuenta del desarrollo total o parcial de los indicadores de logro y el desarrollo de los temas vistos hasta la unidad 3. Autoevaluación: Cuestionario final de mínimo cinco preguntas en el cual el estudiante reflexiona sobre su propio desempeño, habilidades y resultados en un contexto específico. | Q75: Las acciones de retroalimentación giran en torno a las siguientes. Formar: donde se crean las condiciones para que los estudiantes adquieran conocimientos, habilidades, actitudes, aptitudes y destrezas. Además, debe promover su desarrollo integral y debe acompañarlos en las situaciones académicas que enfrenten durante el desarrollo de un módulo o una asignatura. Informar: para que los estudiantes identifiquen los cambios que pueden afectarlos directa o indirectamente tanto en el aula de clase como en otros espacios. Prevenir: con el fin de anticiparse a las situaciones académicas que pueden representar dificultad para los estudiantes. Esto se logra a través de la interacción individual con los estudiantes y del completo conocimiento del contexto educativo en que el tutor se desenvuelve. Ayudar a decidir: donde se orienta a los estudiantes para que tomen la mejor decisión ante una situación concreta. El objetivo es que el estudiante fortalezca su autonomía y la toma de decisiones responsable.
A76: =_xlfn.XLOOKUP(B76,'Paso 3 Redacción RA'!I3:I21,'Paso 3 Redacción RA'!C3:C21,,0,1) -> Saber | B76: Reconoce los fundamentos del derecho penal, comercial, público, laboral y privado para determinar el procedimiento a seguir en la resolución de conflictos o de actos jurídicos, observando los principios rectores de cada actividad y atendiendo a la legislación y normatividad vigente, que permitan generar acciones positivas y acordes a las necesidades de los individuos o las organizaciones, según sea el caso. | C76: 4 | D76: Administrativo General | E76: Explica la función administrativa y la función pública, en la organización del estado desde su fundamentación normativa, para diferenciar los procedimientos contenciosos administrativos, así como los conceptos básicos de la contratación estatal a partir del estatuto de la contratación pública. | F76: TP | H76: X | J76: 3 | K76: =12*J76 -> 36 | L76: =36*J76 -> 108 | M76: =SUM(K76:L76) -> 144 | N76: 1. Fundamentos constitucionales y administrativos del derecho administrativo. 2. Función administrativa y función pública, su noción y fundamentación normativa. 3. Teoría del acto administrativo, y actuaciones administrativas. 4. Procedimientos contenciosos administrativos y conceptos básicos de la contratación estatal. | O76: Trabajo directo: Encuentros sincrónicos Mensajería interna Anuncios Trabajo independiente: Lecturas fundamentales y complementarias Recursos de apoyo Trabajo Colaborativo Foros de discusión grupal | P76: Actividad de puntos evaluables (semana 2 – Cuestionario de 5 preguntas). Entrega previa 1 (semana 3 - Laboratorio, taller, ejercicios, resolución de casos o de problemas, desarrollo de procesos o ejecución de propuestas. Entrega de forma individual o grupal, según indicaciones del profesor). Parcial (semana 4 - Cuestionarios de entre 15 y 20 preguntas). Entrega previa 2 (semana 5 - Laboratorio, taller, ejercicios, resolución de casos o de problemas, desarrollo de procesos o ejecución de propuestas. Entrega de forma individual o grupal, según indicaciones dadas por el profesor). Entrega final (semana 7 - Laboratorio, taller, ejercicios, resolución de casos o de problemas, desarrollo de procesos o ejecución de propuestas. Entrega de forma individual o grupal, según indicaciones dadas por el profesor). Evaluación final (semana 8 - Cuestionario de entre 15 y 20 preguntas). | Q76: Las acciones de retroalimentación giran en torno a las siguientes. Formar: donde se crean las condiciones para que los estudiantes adquieran conocimientos, habilidades, actitudes, aptitudes y destrezas. Además, debe promover su desarrollo integral y debe acompañarlos en las situaciones académicas que enfrenten durante el desarrollo de un módulo o una asignatura. Informar: para que los estudiantes identifiquen los cambios que pueden afectarlos directa o indirectamente tanto en el aula de clase como en otros espacios. Prevenir: con el fin de anticiparse a las situaciones académicas que pueden representar dificultad para los estudiantes. Esto se logra a través de la interacción individual con los estudiantes y del completo conocimiento del contexto educativo en que el tutor se desenvuelve. Ayudar a decidir: donde se orienta a los estudiantes para que tomen la mejor decisión ante una situación concreta. El objetivo es que el estudiante fortalezca su autonomía y la toma de decisiones responsable.
A77: =_xlfn.XLOOKUP(B77,'Paso 3 Redacción RA'!I4:I22,'Paso 3 Redacción RA'!C4:C22,,0,1) -> SaberSer | B77: Reconoce los principios éticos del derecho para implementarlos en su conducta y ejercicio profesional, atendiendo a los casos que llegan a su conocimiento en escenarios nacionales e internacionales.
A78: =_xlfn.XLOOKUP(B78,'Paso 3 Redacción RA'!I5:I23,'Paso 3 Redacción RA'!C5:C23,,0,1) -> SaberHacer | B78: Aplica el régimen de las obligaciones y los contratos comerciales de cualquier tipología, nacional e internacional, atendiendo a las necesidades que se derivan de las relaciones comerciales entorno a su nacimiento, modificación y extinción, para adelantar los procesos jurídicos que correspondan al caso.
A79: =_xlfn.XLOOKUP(B79,'Paso 3 Redacción RA'!I6:I24,'Paso 3 Redacción RA'!C6:C24,,0,1) -> Saber | B79: Identifica los elementos característicos de la negociación y resolución de conflictos para caracterizar la información y argumentación requerida en los procesos de acuerdos, transacciones o laudos arbitrales que den por terminados los conflictos puestos a su conocimiento.
A80: =_xlfn.XLOOKUP(B80,'Paso 3 Redacción RA'!I7:I25,'Paso 3 Redacción RA'!C7:C25,,0,1) -> SaberHacer | B80: Aplica las acciones administrativas y judiciales procedentes del derecho público para proyectar procesos jurídicos que garanticen el reconocimiento y la protección de los derechos de las personas.
A81: =_xlfn.XLOOKUP(B81,'Paso 3 Redacción RA'!I8:I26,'Paso 3 Redacción RA'!C8:C26,,0,1) -> SaberHacer | B81: Aplica el derecho penal en el procedimiento y la acción procedente en atención al tipo penal identificado para adelantar los procesos jurídicos que correspondan al caso.
A82: =_xlfn.XLOOKUP(B82,'Paso 3 Redacción RA'!I3:I21,'Paso 3 Redacción RA'!C3:C21,,0,1) -> SaberHacer | B82: Aplica habilidades de negociación y resolución de conflictos para atender las necesidades de los ciudadanos y la consolidación de acuerdos que den por termino los conflictos puestos a su conocimiento.
A83: =_xlfn.XLOOKUP(B83,'Paso 3 Redacción RA'!I3:I21,'Paso 3 Redacción RA'!C3:C21,,0,1) -> SaberHacer | B83: Aplica los diferentes regímenes laborales para proyectar soluciones, en el marco jurídico, a las controversias que se originan de estas relaciones.
A84: =_xlfn.XLOOKUP(B84,'Paso 3 Redacción RA'!I3:I21,'Paso 3 Redacción RA'!C3:C21,,0,1) -> Saber | B84: Reconoce los fundamentos del derecho penal, comercial, público, laboral y privado para determinar el procedimiento a seguir en la resolución de conflictos o de actos jurídicos, observando los principios rectores de cada actividad y atendiendo a la legislación y normatividad vigente, que permitan generar acciones positivas y acordes a las necesidades de los individuos o las organizaciones, según sea el caso. | C84: 4 | D84: Probatorio | E84: Conoce los principios de la actividad probatoria y la prevalencia del debido proceso para aplicarlos en las fases de admisibilidad, contradicción y valoración de la prueba en la toma de decisiones. Diferencia los medios probatorios que se emplean en los procedimientos judiciales para encontrar la certeza frente a los hechos sujetos a investigación. | F84: TP | H84: X | J84: 3 | K84: =12*J84 -> 36 | L84: =36*J84 -> 108 | M84: =SUM(K84:L84) -> 144 | N84: 1. Fundamentos del Derecho Probatorio. 2. Admisibilidad, contradicción y valoración de la prueba. 3. Medios probatorios I. 4. Medios probatorios II. | O84: Trabajo directo: Encuentros sincrónicos Mensajería interna Anuncios Trabajo independiente: Lecturas fundamentales y complementarias Recursos de apoyo Trabajo Colaborativo Foros de discusión grupal | P84: Actividad de puntos evaluables (semana 2 – Cuestionario de 5 preguntas). Entrega previa 1 (semana 3 - Laboratorio, taller, ejercicios, resolución de casos o de problemas, desarrollo de procesos o ejecución de propuestas. Entrega de forma individual o grupal, según indicaciones del profesor). Parcial (semana 4 - Cuestionarios de entre 15 y 20 preguntas). Entrega previa 2 (semana 5 - Laboratorio, taller, ejercicios, resolución de casos o de problemas, desarrollo de procesos o ejecución de propuestas. Entrega de forma individual o grupal, según indicaciones dadas por el profesor). Entrega final (semana 7 - Laboratorio, taller, ejercicios, resolución de casos o de problemas, desarrollo de procesos o ejecución de propuestas. Entrega de forma individual o grupal, según indicaciones dadas por el profesor). Evaluación final (semana 8 - Cuestionario de entre 15 y 20 preguntas). | Q84: Las acciones de retroalimentación giran en torno a las siguientes. Formar: donde se crean las condiciones para que los estudiantes adquieran conocimientos, habilidades, actitudes, aptitudes y destrezas. Además, debe promover su desarrollo integral y debe acompañarlos en las situaciones académicas que enfrenten durante el desarrollo de un módulo o una asignatura. Informar: para que los estudiantes identifiquen los cambios que pueden afectarlos directa o indirectamente tanto en el aula de clase como en otros espacios. Prevenir: con el fin de anticiparse a las situaciones académicas que pueden representar dificultad para los estudiantes. Esto se logra a través de la interacción individual con los estudiantes y del completo conocimiento del contexto educativo en que el tutor se desenvuelve. Ayudar a decidir: donde se orienta a los estudiantes para que tomen la mejor decisión ante una situación concreta. El objetivo es que el estudiante fortalezca su autonomía y la toma de decisiones responsable.
A85: =_xlfn.XLOOKUP(B85,'Paso 3 Redacción RA'!I4:I22,'Paso 3 Redacción RA'!C4:C22,,0,1) -> SaberHacer | B85: Aplica el derecho privado, atendiendo la legislación y normatividad vigente, para dar solución a casos concretos.
A86: =_xlfn.XLOOKUP(B86,'Paso 3 Redacción RA'!I5:I23,'Paso 3 Redacción RA'!C5:C23,,0,1) -> SaberSer | B86: Reconoce los principios éticos del derecho para implementarlos en su conducta y ejercicio profesional, atendiendo a los casos que llegan a su conocimiento en escenarios nacionales e internacionales.
A87: =_xlfn.XLOOKUP(B87,'Paso 3 Redacción RA'!I6:I24,'Paso 3 Redacción RA'!C6:C24,,0,1) -> SaberHacer | B87: Aplica el régimen de las obligaciones y los contratos comerciales de cualquier tipología, nacional e internacional, atendiendo a las necesidades que se derivan de las relaciones comerciales entorno a su nacimiento, modificación y extinción, para adelantar los procesos jurídicos que correspondan al caso.
A88: =_xlfn.XLOOKUP(B88,'Paso 3 Redacción RA'!I7:I25,'Paso 3 Redacción RA'!C7:C25,,0,1) -> Saber | B88: Identifica los elementos característicos de la negociación y resolución de conflictos para caracterizar la información y argumentación requerida en los procesos de acuerdos, transacciones o laudos arbitrales que den por terminados los conflictos puestos a su conocimiento.
A89: =_xlfn.XLOOKUP(B89,'Paso 3 Redacción RA'!I8:I26,'Paso 3 Redacción RA'!C8:C26,,0,1) -> SaberHacer | B89: Aplica las acciones administrativas y judiciales procedentes del derecho público para proyectar procesos jurídicos que garanticen el reconocimiento y la protección de los derechos de las personas.
A90: =_xlfn.XLOOKUP(B90,'Paso 3 Redacción RA'!I9:I27,'Paso 3 Redacción RA'!C9:C27,,0,1) -> SaberHacer | B90: Aplica el derecho penal en el procedimiento y la acción procedente en atención al tipo penal identificado para adelantar los procesos jurídicos que correspondan al caso.
A91: =_xlfn.XLOOKUP(B91,'Paso 3 Redacción RA'!I3:I21,'Paso 3 Redacción RA'!C3:C21,,0,1) -> SaberHacer | B91: Aplica habilidades de negociación y resolución de conflictos para atender las necesidades de los ciudadanos y la consolidación de acuerdos que den por termino los conflictos puestos a su conocimiento.
A92: =_xlfn.XLOOKUP(B92,'Paso 3 Redacción RA'!I3:I21,'Paso 3 Redacción RA'!C3:C21,,0,1) -> SaberHacer | B92: Aplica los diferentes regímenes laborales para proyectar soluciones, en el marco jurídico, a las controversias que se originan de estas relaciones.
A93: =_xlfn.XLOOKUP(B93,'Paso 3 Redacción RA'!I3:I21,'Paso 3 Redacción RA'!C3:C21,,0,1) -> Saber | B93: Reconoce los fundamentos del derecho penal, comercial, público, laboral y privado para determinar el procedimiento a seguir en la resolución de conflictos o de actos jurídicos, observando los principios rectores de cada actividad y atendiendo a la legislación y normatividad vigente, que permitan generar acciones positivas y acordes a las necesidades de los individuos o las organizaciones, según sea el caso. | C93: 4 | D93: Penal Especial | E93: Explica con argumentos teóricos los fundamentos del derecho penal y sus desarrollos doctrinales y jurisprudenciales para resolver casos con los tipos penales materia de estudio de manera precisa y clara. | F93: TP | H93: X | J93: 3 | K93: =12*J93 -> 36 | L93: =36*J93 -> 108 | M93: =SUM(K93:L93) -> 144 | N93: 1. Delitos contra la vida y la integridad personal. 2. Delitos contra la libertad individual y la familia. 3. Delitos contra la libertad, integridad y formación sexuales. 4. Delitos contra la fe pública, la administración pública, el patrimonio económico y el orden económico. | O93: Trabajo directo: Encuentros sincrónicos Mensajería interna Anuncios Trabajo independiente: Lecturas fundamentales y complementarias Recursos de apoyo Trabajo Colaborativo Foros de discusión grupal | P93: Actividad de puntos evaluables (semana 2 – Cuestionario de 5 preguntas). Entrega previa 1 (semana 3 - Laboratorio, taller, ejercicios, resolución de casos o de problemas, desarrollo de procesos o ejecución de propuestas. Entrega de forma individual o grupal, según indicaciones del profesor). Parcial (semana 4 - Cuestionarios de entre 15 y 20 preguntas). Entrega previa 2 (semana 5 - Laboratorio, taller, ejercicios, resolución de casos o de problemas, desarrollo de procesos o ejecución de propuestas. Entrega de forma individual o grupal, según indicaciones dadas por el profesor). Entrega final (semana 7 - Laboratorio, taller, ejercicios, resolución de casos o de problemas, desarrollo de procesos o ejecución de propuestas. Entrega de forma individual o grupal, según indicaciones dadas por el profesor). Evaluación final (semana 8 - Cuestionario de entre 15 y 20 preguntas). | Q93: Las acciones de retroalimentación giran en torno a las siguientes. Formar: donde se crean las condiciones para que los estudiantes adquieran conocimientos, habilidades, actitudes, aptitudes y destrezas. Además, debe promover su desarrollo integral y debe acompañarlos en las situaciones académicas que enfrenten durante el desarrollo de un módulo o una asignatura. Informar: para que los estudiantes identifiquen los cambios que pueden afectarlos directa o indirectamente tanto en el aula de clase como en otros espacios. Prevenir: con el fin de anticiparse a las situaciones académicas que pueden representar dificultad para los estudiantes. Esto se logra a través de la interacción individual con los estudiantes y del completo conocimiento del contexto educativo en que el tutor se desenvuelve. Ayudar a decidir: donde se orienta a los estudiantes para que tomen la mejor decisión ante una situación concreta. El objetivo es que el estudiante fortalezca su autonomía y la toma de decisiones responsable.
A94: =_xlfn.XLOOKUP(B94,'Paso 3 Redacción RA'!I4:I22,'Paso 3 Redacción RA'!C4:C22,,0,1) -> SaberSer | B94: Reconoce los principios éticos del derecho para implementarlos en su conducta y ejercicio profesional, atendiendo a los casos que llegan a su conocimiento en escenarios nacionales e internacionales.
A95: =_xlfn.XLOOKUP(B95,'Paso 3 Redacción RA'!I5:I23,'Paso 3 Redacción RA'!C5:C23,,0,1) -> SaberHacer | B95: Aplica el régimen de las obligaciones y los contratos comerciales de cualquier tipología, nacional e internacional, atendiendo a las necesidades que se derivan de las relaciones comerciales entorno a su nacimiento, modificación y extinción, para adelantar los procesos jurídicos que correspondan al caso.
A96: =_xlfn.XLOOKUP(B96,'Paso 3 Redacción RA'!I6:I24,'Paso 3 Redacción RA'!C6:C24,,0,1) -> Saber | B96: Identifica los elementos característicos de la negociación y resolución de conflictos para caracterizar la información y argumentación requerida en los procesos de acuerdos, transacciones o laudos arbitrales que den por terminados los conflictos puestos a su conocimiento.
A97: =_xlfn.XLOOKUP(B97,'Paso 3 Redacción RA'!I7:I25,'Paso 3 Redacción RA'!C7:C25,,0,1) -> SaberHacer | B97: Aplica las acciones administrativas y judiciales procedentes del derecho público para proyectar procesos jurídicos que garanticen el reconocimiento y la protección de los derechos de las personas.
A98: =_xlfn.XLOOKUP(B98,'Paso 3 Redacción RA'!I3:I21,'Paso 3 Redacción RA'!C3:C21,,0,1) -> SaberHacer | B98: Aplica el derecho penal en el procedimiento y la acción procedente en atención al tipo penal identificado para adelantar los procesos jurídicos que correspondan al caso.
A99: =_xlfn.XLOOKUP(B99,'Paso 3 Redacción RA'!I3:I21,'Paso 3 Redacción RA'!C3:C21,,0,1) -> SaberHacer | B99: Aplica habilidades de negociación y resolución de conflictos para atender las necesidades de los ciudadanos y la consolidación de acuerdos que den por termino los conflictos puestos a su conocimiento.
A100: =_xlfn.XLOOKUP(B100,'Paso 3 Redacción RA'!I3:I21,'Paso 3 Redacción RA'!C3:C21,,0,1) -> Saber | B100: Reconoce los fundamentos del derecho penal, comercial, público, laboral y privado para determinar el procedimiento a seguir en la resolución de conflictos o de actos jurídicos, observando los principios rectores de cada actividad y atendiendo a la legislación y normatividad vigente, que permitan generar acciones positivas y acordes a las necesidades de los individuos o las organizaciones, según sea el caso. | C100: 4 | D100: Contratos | E100: Clasifica los contratos civiles y mercantiles según sus características y la función económica que cumplen para resolver casos en contextos del derecho privado. | F100: TP | H100: X | J100: 3 | K100: =12*J100 -> 36 | L100: =36*J100 -> 108 | M100: =SUM(K100:L100) -> 144 | N100: 1. Principios Generales del Derecho de Contratos. 2. Contratos civiles – Definición, partes y características. 3. Formación de los contratos mercantiles, responsabilidad y grupos empresariales. 4. Contratos típicos y atípicos más comunes en materia mercantil. | O100: Trabajo directo: Encuentros sincrónicos Mensajería interna Anuncios Trabajo independiente: Lecturas fundamentales y complementarias Recursos de apoyo Trabajo Colaborativo Foros de discusión grupal | P100: Actividad de puntos evaluables (semana 2 – Cuestionario de 5 preguntas). Entrega previa 1 (semana 3 - Laboratorio, taller, ejercicios, resolución de casos o de problemas, desarrollo de procesos o ejecución de propuestas. Entrega de forma individual o grupal, según indicaciones del profesor). Parcial (semana 4 - Cuestionarios de entre 15 y 20 preguntas). Entrega previa 2 (semana 5 - Laboratorio, taller, ejercicios, resolución de casos o de problemas, desarrollo de procesos o ejecución de propuestas. Entrega de forma individual o grupal, según indicaciones dadas por el profesor). Entrega final (semana 7 - Laboratorio, taller, ejercicios, resolución de casos o de problemas, desarrollo de procesos o ejecución de propuestas. Entrega de forma individual o grupal, según indicaciones dadas por el profesor). Evaluación final (semana 8 - Cuestionario de entre 15 y 20 preguntas). | Q100: Las acciones de retroalimentación giran en torno a las siguientes. Formar: donde se crean las condiciones para que los estudiantes adquieran conocimientos, habilidades, actitudes, aptitudes y destrezas. Además, debe promover su desarrollo integral y debe acompañarlos en las situaciones académicas que enfrenten durante el desarrollo de un módulo o una asignatura. Informar: para que los estudiantes identifiquen los cambios que pueden afectarlos directa o indirectamente tanto en el aula de clase como en otros espacios. Prevenir: con el fin de anticiparse a las situaciones académicas que pueden representar dificultad para los estudiantes. Esto se logra a través de la interacción individual con los estudiantes y del completo conocimiento del contexto educativo en que el tutor se desenvuelve. Ayudar a decidir: donde se orienta a los estudiantes para que tomen la mejor decisión ante una situación concreta. El objetivo es que el estudiante fortalezca su autonomía y la toma de decisiones responsable.
...

Sheet Taxonomía para competencias
B1: Verbos Competencias
B2: Actualizar
B3: Administrar
B4: Asegurar
B5: Asesorar
B6: Auditar
B7: Comunicar
B8: Conducir
B9: Conocer
B10: Coordinar
B11: Definir
B12: Desarrollar
... B39: Aplicar

Sheet Taxonomias para RA
S1: Taxonomía de Bloom Adaptada bajo las ideas de Anderson y Krathwohl | AL1: Taxonomía de Bloom adaptada bajo las ideas de Lorin y Krathwohl (LK) | AT1: Taxonomía de Bloom adaptada bajo las ideas de Anderson y Kendal (AK)
L2: Taxonomía de Bloom | S2: Cognitivo(BAK) | Y2: Procedimental(BAK) | AC2: Actitudinal(BAK)
A3: Taxonomías | C3: BAK | D3: LK | E3: AK | G3: CognitivoB | H3: ProcedimentalB | I3: ActitudinalB | L3: ConocimientoB | M3: ComprensiónB | N3: AplicaciónB | O3: AnálisisB | P3: SíntesisB | Q3: EvaluaciónB | S3: ConocimientoBAK | T3: ComprensiónBAK | U3: AplicaciónBAK | V3: AnálisisBAK | W3: SíntesisBAK | X3: EvaluaciónBAK | Y3: ImitaciónBAK | Z3: ManipulaciónBAK | AA3: PrecisiónBAK | AB3: ControlBAK | AC3: PercepciónBAK | AD3: ResponderBAK | AE3: ValorarBAK | AF3: OrganizarBAK | AG3: CaracterizarBAK | AL3: Procesos cognitivos de orden inferior | AO3: Procesos cognitivos de orden superior
A4: Bloom | C4: CognitivoBAK | D4: HechosLK | E4: InformaciónAK | G4: ConocimientoB | H4: ConocimientoB | I4: ConocimientoB | L4: Adquirir | M4: Auditar | N4: Aplicar | O4: Aislar | P4: Adaptar | Q4: Aconsejar | S4: Adquirir | T4: Auditar | U4: Aplicar | V4: Aislar | W4: Adaptar | X4: Aconsejar | Y4: Acordar | Z4: Acceder | AA4: Abrir | AB4: Arreglar | AC4: Aceptar | AD4: Acordar | AE4: Aceptar | AF4: Adelantar | AG4: Acabar | AL4: RecordarLK | AM4: ComprenderLK | AN4: AplicarLK | AO4: AnalizarLK | AP4: EvaluarLK | AQ4: CrearLK | AT4: RecuperaciónAK | AU4: ComprensiónAK | AV4: AnálisisAK | AW4: UsoConocimientoAK | AX4: MetacogniciónAK | AY4: SistemadelYoAK
A5: BAK | C5: ProcedimentalBAK | D5: ConceptosLK | E5: ProcesosMentalesAK | G5: ComprensiónB | H5: ComprensiónB | I5: ComprensiónB | L5: Buscar | M5: Bosquejar | N5: Calisificar | O5: Analizar | P5: Administrar | Q5: Adjuntar | S5: Buscar | T5: Bosquejar | U5: Calisificar | V5: Analizar | W5: Administrar | X5: Adjuntar | Y5: Adaptar | Z5: Aislar | AA5: Actuar | AB5: Balancear | AC5: Admitir | AD5: Actuar recíprocamente | AE5: Adoptar | AF5: Anticipar | AG5: Afinar | AL5: Afirmar | AM5: Clasificar | AN5: Actuar | AO5: Agrupar | AP5: Adaptar | AQ5: Desarrollar | AT5: Afirmar | AU5: Auditar | AV5: Agrupar | AW5: Actuar | AX5: Aceptar | AY5: Aceptar
A6: LK | C6: ActitudinalBAK | D6: ProcedimientoslLK | E6: PsicomotorAK | G6: AplicaciónB | H6: AplicaciónB | I6: AplicaciónB | L6: Citar | M6: Comentar | N6: Combinar | O6: Calcular | P6: Arreglar | Q6: Agregar | S6: Citar | T6: Comentar | U6: Combinar | V6: Calcular | W6: Arreglar | X6: Agregar | Y6: Ajustar | Z6: Ajustar | AA6: Adaptar | AB6: Clasificar | AC6: Anotar | AD6: Afirmar | AE6: Afirmar | AF6: Arreglar | AG6: Apoyar | AL6: Citar | AM6: Comparar | AN6: Agrupar | AO6: Aislar | AP6: Añadir | AQ6: Elaborar | AT6: Citar | AU6: Bosquejar | AV6: Aislar | AW6: Agrupar | AX6: Adelantar | AY6: Adoptar
A7: AK | D7: MetacogniciónLK | G7: AnálisisB | H7: AnálisisB | I7: AnálisisB | L7: Consignar | M7: Comunicar | N7: Componer | O7: Categorizar | P7: Arreglar | Q7: Alinear | S7: Consignar | T7: Comunicar | U7: Componer | V7: Categorizar | W7: Arreglar | X7: Alinear | Y7: Alinear | Z7: Ampliar | AA7: Ajustar | AB7: Codificar | AC7: Aplicar | AD7: Aprobar | AE7: Agradecer | AF7: Conectar | AG7: Atender | AL7: Copiar | AM7: Contrastar | AN7: Calcular | AO7: Asumir | AP7: Apoyar | AQ7: Maximizar | AT7: Copiar | AU7: Clasificar | AV7: Analizar | AW7: Aplicar | AX7: Adoptar | AY7: Afinar
G8: SíntesisB | H8: SíntesisB | I8: SíntesisB | L8: Decir | M8: Convertir | N8: Conducir | O8: Comparar | P8: Articular | Q8: Arbitrar | S8: Decir | T8: Convertir | U8: Conducir | V8: Comparar | W8: Articular | X8: Arbitrar | Y8: Analizar | Z8: Aplicar | AA8: Apalancar | AB8: Colocar | AC8: Apreciar | AD8: Asegurar | AE8: Ambicionar | AF8: Considerar | AG8: Categorizar | AL8: Decir | AM8: Demostrar | AN8: Categorizar | AO8: Buscar similitudes | AP8: Argumentar | AQ8: Mejorar | AT8: Decir | AU8: Comentar | AV8: Aplicar | AW8: Calcular | AX8: Afinar | AY8: Agradecer
G9: EvaluaciónB | H9: EvaluaciónB | I9: EvaluaciónB | L9: Definir | M9: Criticar | N9: Construir | O9: Considerar | P9: Aumentar | Q9: Asegurar | S9: Definir | T9: Criticar | U9: Construir | V9: Considerar | W9: Aumentar | X9: Asegurar | Y9: Aplicar | Z9: Arreglar | AA9: Bajar | AB9: Componer | AC9: Apreciar | AD9: Autorizar | AE9: Anhelar | AF9: Cuestionar | AG9: Colaborar | AL9: Definir | AM9: Discutir | AN9: Conectar | AO9: Categorizar | AP9: Cambiar | AQ9: Minimizar | AT9: Definir | AU9: Comparar | AV9: Asumir | AW9: Calisificar | AX9: Afirmar | AY9: Ambicionar
L10: Deletrear | M10: Dar ejemplos | N10: Demostrar | O10: Contrastar | P10: Calcular | Q10: Asesorar | S10: Deletrear | T10: Dar ejemplos | U10: Demostrar | V10: Contrastar | W10: Calcular | X10: Asesorar | Y10: Armar | Z10: Colocar | AA10: Colocar | AB10: Conducir | AC10: Asisitir | AD10: Clasificar | AE10: Apoyar | AF10: Defender | AG10: Completar | AL10: Deletrear | AM10: Ejemplificar | AN10: Construir | AO10: Centrarse | AP10: Combinar | AQ10: Modelar | AT10: Deletrear | AU10: Comunicar | AV10: Buscar similitudes | AW10: Categorizar | AX10: Agradecer | AY10: Anhelar
G11: HechosLK | H11: ConceptosLK | I11: ProcedimientosLK | J11: MetacogniciónLK | L11: Demostrar | M11: Debatir | N11: Determinar | O11: Criticar | P11: Componer | Q11: Atar | S11: Demostrar | T11: Debatir | U11: Determinar | V11: Criticar | W11: Componer | X11: Atar | Y11: Arreglar | Z11: Conducir | AA11: Comenzar | AB11: Correr | AC11: Atender | AD11: Colaborar | AE11: Apreciar | AF11: Definir | AG11: Comportarse bajo condiciones | AL11: Duplicar | AM11: Esquematizar | AN11: Demostrar | AO11: Comparar | AP11: Comparar | AQ11: Pensar | AT11: Duplicar | AU11: Contrastar | AV11: Calcular | AW11: Combinar | AX11: Ambicionar | AY11: Anticipar
G12: RecordarLK | H12: RecordarLK | I12: RecordarLK | J12: RecordarLK | L12: Describir | M12: Describir | N12: Dibujar | O12: Cuestionar | P12: Computar | Q12: Calcular | S12: Describir | T12: Describir | U12: Dibujar | V12: Cuestionar | W12: Computar | X12: Calcular | Y12: Asegurar | Z12: Desmontar | AA12: Cortar | AB12: Coser | AC12: Clasificar | AD12: Comunicar | AE12: Aprobar | AF12: Desplegar | AG12: Conducir | AL12: Elegir | AM12: Explicar | AN12: Desarrollar | AO12: Correlacionar | AP12: Compilar | AQ12: Planear | AT12: Elegir | AU12: Convertir | AV12: Calisificar | AW12: Componer | AX12: Anhelar | AY12: Apreciar
G13: ComprenderLK | H13: ComprenderLK | I13: ComprenderLK | J13: ComprenderLK | L13: Elegir | M13: Desplegar | N13: Discriminar | O13: Debatir | P13: Concluir | Q13: Calificar | S13: Elegir | T13: Desplegar | U13: Discriminar | V13: Debatir | W13: Concluir | X13: Calificar | Y13: Bailar | Z13: Dibujar | AA13: Cumplir | AB13: Difundir | AC13: Conducir | AD13: Conocer | AE13: Asistir | AF13: Determinar | AG13: Constatar | AL13: Escribir | AM13: Expresar | AN13: Dramatizar | AO13: Descomponer | AP13: Componer | AQ13: Proponer | AT13: Escribir | AU13: Criticar | AV13: Categorizar | AW13: Conducir | AX13: Anticipar | AY13: Aprobar
G14: AplicarLK | H14: AplicarLK | I14: AplicarLK | J14: AplicarLK | L14: Enseñar | M14: Dibujar | N14: Diseñar | O14: Deducir | P14: Conectar | Q14: Censurar | S14: Enseñar | T14: Dibujar | U14: Diseñar | V14: Deducir | W14: Conectar | X14: Censurar | Y14: Cambiar | Z14: Direccionar | AA14: Destapar | AB14: Direccionar | AC14: Cumplir | AD14: Contar | AE14: Aspirar | AF14: Discernir | AG14: Contextualizar | AL14: Leer | AM14: Generalizar | AN14: Elegir | AO14: Diferenciar | AP14: Construir | AQ14: Reescribir | AT14: Leer | AU14: Dar ejemplos | AV14: Centrarse | AW14: Conectar | AX14: Apoyar | AY14: Asistir
G15: AnalizarLK | H15: AnalizarLK | I15: AnalizarLK | J15: AnalizarLK | L15: Escribir | M15: Discutir | N15: Dramatizar | O15: Desarrollar | P15: Construir | Q15: Clasificar | S15: Escribir | T15: Discutir | U15: Dramatizar | V15: Desarrollar | W15: Construir | X15: Clasificar | Y15: Comparar | Z15: Dirigir | AA15: Dirigir | AB15: Diseñar | AC15: Decir | AD15: Cooperar | AE15: Atender | AF15: Exteriorizar | AG15: Controlar | AL15: Listar | AM15: Ilustrar | AN15: Emplear | AO15: Distinguir | AP15: Convencer | AQ15: Simplificar | AT15: Listar | AU15: Debatir | AV15: Combinar | AW15: Construir | AX15: Apreciar | AY15: Aspirar
G16: EvaluarLK | H16: EvaluarLK | I16: EvaluarLK | J16: EvaluarLK | L16: Establecer | M16: Diseñar | N16: Duplicar | O16: Detectar | P16: Crear | Q16: Computar | S16: Establecer | T16: Diseñar | U16: Duplicar | V16: Detectar | W16: Crear | X16: Computar | Y16: Comprobar | Z16: Docificar | AA16: Disponer | AB16: Disipar | AC16: Detectar | AD16: Decir | AE16: Aunar | AF16: Extraer | AG16: Cooperar | AL16: Localizar | AM16: Inferir | AN16: Enseñar | AO16: Dividir | AP16: Crear | AQ16: Suponer | AT16: Localizar | AU16: Demostrar | AV16: Comparar | AW16: Demostrar | AX16: Aprobar | AY16: Atender
G17: CrearLK | H17: CrearLK | I17: CrearLK | J17: CrearLK | L17: Etiquetar | M17: Establecer | N17: Elegir | O17: Diagramar | P17: Decidir | Q17: Concluir | S17: Etiquetar | T17: Establecer | U17: Elegir | V17: Diagramar | W17: Decidir | X17: Concluir | Y17: Concretar | Z17: Dramatizar | AA17: Dividir | AB17: Ejecutar | AC17: Direccionar | AD17: Demostrar | AE17: Clasificar | AF17: Fomentar | AG17: Cumplir | AL17: Memorizar | AM17: Informar | AN17: Entrevistar | AO17: Elegir | AP17: Criticar | AQ17: Sustituir | AT17: Memorizar | AU17: Describir | AV17: Componer | AW17: Desarrollar | AX17: Arreglar | AY17: Categorizar
L18: Examinar | M18: Examinar | N18: Emparejar | O18: Diferenciar | P18: Deducir | Q18: Conformar | S18: Examinar | T18: Examinar | U18: Emparejar | V18: Diferenciar | W18: Deducir | X18: Conformar | Y18: Conducir | Z18: Ejecutar | AA18: Ejecutar | AB18: Eliminar | AC18: Dirigir | AD18: Discutir | AE18: Compartir | AF18: Formular | AG18: Discriminar | AL18: Mostrar | AM18: Interpretar | AN18: Hacer uso | AO18: Encontrar | AP18: Debatir | AQ18: Teorizar | AT18: Mostrar | AU18: Desplegar | AV18: Conducir | AW18: Determinar | AX18: Asistir | AY18: Clasificar
G19: InformaciónAK | H19: ProcesosAK | I19: PsicomotorAK | L19: Examinar | M19: Explicar | N19: Emplear | O19: Discernir | P19: Derivar | Q19: Constrastar | S19: Examinar | T19: Explicar | U19: Emplear | V19: Discernir | W19: Derivar | X19: Constrastar | Y19: Construir | Z19: Ejercitar | AA19: Ejercer | AB19: Emplear | AC19: Distinguir | AD19: Distinguir | AE19: Comprender | AF19: Identificar | AG19: Distinguir | AL19: Nombrar | AM19: Mostrar | AN19: Identificar | AO19: Encuestar | AP19: Decidir | AQ19: Testar | AT19: Nombrar | AU19: Dibujar | AV19: Considerar | AW19: Dibujar | AX19: Aspirar | AY19: Completar
G20: RecuperaciónAK | H20: RecuperaciónAK | I20: RecuperaciónAK | L20: Grabar | M20: Exponer | N20: Esquematizar | O20: Discriminar | P20: Desarrollar | Q20: Contabilizar | S20: Grabar | T20: Exponer | U20: Esquematizar | V20: Discriminar | W20: Desarrollar | X20: Contabilizar | Y20: Contar | Z20: Encajar | AA20: Emitir | AB20: Ensanchar | AC20: Elegir | AD20: Elegir | AE20: Contribuir | AF20: Percibir | AG20: Ejercer | AL20: Observar | AM20: Observar | AN20: Interpretar | AO20: Establecer | AP20: Deducir | AQ20: Transformar | AT20: Observar | AU20: Discutir | AV20: Construir | AW20: Discriminar | AX20: Atender | AY20: Comprender
G21: ComprensiónAK | H21: ComprensiónAK | I21: ComprensiónAK | L21: Hacer | M21: Expresar | N21: Estimar | O21: Distinguir | P21: Describir | Q21: Controlar | S21: Hacer | T21: Expresar | U21: Estimar | V21: Distinguir | W21: Describir | X21: Controlar | Y21: Contrastar | Z21: Enseñar | AA21: Emitir | AB21: Entallar | AC21: Emplear | AD21: Enumerar | AE21: Convocar | AF21: Preguntar | AG21: Entregar | AL21: Omitir | AM21: Parafrasear | AN21: Manipular | AO21: Examinar | AP21: Defender | AQ21: Visualizar | AT21: Omitir | AU21: Diseñar | AV21: Contrastar | AW21: Diseñar | AX21: Aunar | AY21: Conducir
G22: AnálisisAK | H22: AnálisisAK | I22: AnálisisAK | L22: Identificar | M22: Extraer | N22: Estructurar | O22: Estructurar | P22: Desempeñar | Q22: Corregir | S22: Identificar | T22: Extraer | U22: Estructurar | V22: Estructurar | W22: Desempeñar | X22: Corregir | Y22: Controlar | Z22: Examinar | AA22: Empaquetar | AB22: Entregar | AC22: Escoger | AD22: Escoger | AE22: Creer | AF22: Promover | AG22: Juzgar | AL22: Rastrear | AM22: Predecir | AN22: Organizar | AO22: Inferir | AP22: Demostrar | AT22: Parafrasear | AU22: Ejemplificar | AV22: Correlacionar | AW22: Dramatizar | AX22: Categorizar | AY22: Conectar
G23: UsoConocimientoAK | H23: UsoConocimientoAK | I23: UsoConocimientoAK | L23: Ilustrar | M23: Generalizar | N23: Estructurar | O23: Examinar | P23: Dirigir | Q23: Criticar | S23: Ilustrar | T23: Generalizar | U23: Estructurar | V23: Examinar | W23: Dirigir | X23: Criticar | Y23: Coordinar | Z23: Explorar | AA23: Encontrar | AB23: Esculpir | AC23: Escuchar | AD23: Hablar | AE23: Cuidar | AF23: Proponer | AG23: Negociar | AL23: Recitar | AM23: Preguntar | AN23: Planear | AO23: Inspeccionar | AP23: Descubrir | AT23: Rastrear | AU23: Esquematizar | AV23: Criticar | AW23: Duplicar | AX23: Clasificar | AY23: Considerar
G24: MetacogniciónAK | H24: MetacogniciónAK | I24: MetacogniciónAK | L24: Listar | M24: Hacer | N24: Evaluar | O24: Experimentar | P24: Diseñar | Q24: Cuestionar | S24: Listar | T24: Hacer | U24: Evaluar | V24: Experimentar | W24: Diseñar | X24: Cuestionar | Y24: Cortar | Z24: Expresar | AA24: Entrenar | AB24: Extender | AC24: Estimar | AD24: Hacer | AE24: Elegir | AF24: Proteger | AG24: Ofrecer | AL24: Reconocer | AM24: Relacionar | AN24: Practicar | AO24: Investigar | AP24: Diseñar | AT24: Recitar | AU24: Establecer | AV24: Cuestionar | AW24: Elegir | AX24: Colaborar | AY24: Constatar
G25: AutoSistemaAK | H25: AutoSistemaAK | I25: AutoSistemaAK | L25: Mostar | M25: Identificar | N25: Experimentar | O25: Inspeccionar | P25: Ejercer | Q25: Culminar | S25: Mostar | T25: Identificar | U25: Experimentar | V25: Inspeccionar | W25: Ejercer | X25: Culminar | Y25: Cotejar | Z25: Extraer | AA25: Envasar | AB25: Extirpar | AC25: Evaluar | AD25: Indicar | AE25: Emplear | AF25: Reconocer | AG25: Participar | AL25: Relacionar | AM25: Resumir | AN25: Resolver | AO25: Motivar | AP25: Estimar | AT25: Reconocer | AU25: Examinar | AV25: Debatir | AW25: Emparejar | AX25: Compartir | AY25: Contextualizar
L26: Nombrar | M26: Indicar | N26: Ilustrar | O26: Inventariar | P26: Ensamblar | Q26: Debatir | S26: Nombrar | T26: Indicar | U26: Ilustrar | V26: Inventariar | W26: Ensamblar | X26: Debatir | Y26: Demostrar | Z26: Guiar | AA26: Establecer | AB26: Hacer | AC26: Examinar | AD26: Informar | AE26: Ensamblar | AF26: Relacionar | AG26: Servir | AL26: Relacionar | AM26: Revisar | AN26: Resumir | AO26: Observar | AP26: Evaluar | AT26: Relacionar | AU26: Explicar | AV26: Deducir | AW26: Emplear | AX26: Completar | AY26: Cuestionar
L27: Numerar | M27: Inferir | N27: Indicar | O27: Investigar | P27: Escribir | Q27: Decidir | S27: Numerar | T27: Inferir | U27: Indicar | V27: Investigar | W27: Escribir | X27: Decidir | Y27: Detectar | Z27: Hacer | AA27: Estampar | AB27: Implementar | AC27: Guiar | AD27: Narrar | AE27: Escoger | AF27: Relatar | AG27: Soportar | AL27: Repetir | AM27: Traducir | AN27: Seleccionar | AO27: Ordenar | AP27: Experimentar | AT27: Repetir | AU27: Exponer | AV27: Demostrar | AW27: Enseñar | AX27: Comportarse bajo condiciones | AY27: Cuidar
L28: Observar | M28: Interpretar | N28: Interpretar | O28: Listar | P28: Establecer | Q28: Deducir | S28: Observar | T28: Interpretar | U28: Interpretar | V28: Listar | W28: Establecer | X28: Deducir | Y28: Direccionar | Z28: Identificar | AA28: Estimular | AB28: Industrializar | AC28: Hacer | AD28: Obrar recíprocamente | AE28: Estimar | AF28: Resumir | AG28: Terminar | AN28: Simular | AO28: Preguntar | AP28: Explicar | AU28: Expresar | AV28: Desarrollar | AW28: Entrevistar | AX28: Comprender | AY28: Cumplir
L29: Obtener | M29: Inventariar | N29: Investigar | O29: Medir | P29: Estudiar | Q29: Defender | S29: Obtener | T29: Inventariar | U29: Investigar | V29: Medir | W29: Estudiar | X29: Defender | Y29: Disponer | Z29: Inspeccionar | AA29: Extraer | AB29: Inspeccionar | AC29: Interrogar | AD29: Recitar | AE29: Estimular | AF29: Revelar | AG29: Verificar | AN29: Transferir | AO29: Priorizar | AP29: Extender | AU29: Extraer | AV29: Descomponer | AW29: Esquematizar | AX29: Conducir | AY29: Defender
L30: Ordenar | M30: Localizar | N30: Listar | O30: Planear | P30: Figurar | Q30: Defender | S30: Ordenar | T30: Localizar | U30: Listar | V30: Planear | W30: Figurar | X30: Defender | Y30: Edificar | Z30: Instalar | AA30: Fabricar | AB30: Llevar | AC30: Manejar | AD30: Referir | AE30: Participar | AG30: Examinar | AN30: Unir | AO30: Probar | AP30: Formular | AU30: Generalizar | AV30: Detectar | AW30: Estimar | AX30: Conectar | AY30: Determinar
L31: Organizar | M31: Narrar | N31: Manipular | O31: Preguntar | P31: Formular | Q31: Determinar | S31: Organizar | T31: Narrar | U31: Manipular | V31: Preguntar | W31: Formular | X31: Determinar | Y31: Ensamblar | Z31: Inventariar | AA31: Gestionar | AB31: Manejar | AC31: Observar | AD31: Relatar | AE31: Preocuparse de o por | AN31: Usar | AO31: Razonar | AP31: Hipotetizar | AU31: Hacer | AV31: Determinar | AW31: Estructurar | AX31: Considerar | AY31: Discernir
L32: Preguntar | M32: Parafrasear | N32: Modelar | O32: Probar | P32: Generar | Q32: Discutir | S32: Preguntar | T32: Parafrasear | U32: Modelar | V32: Probar | W32: Generar | X32: Discutir | Y32: Escoger | Z32: Manejar | AA32: Grabar | AB32: Mecanizar | AC32: Ocupar | AD32: Resolver | AE32: Proporcionar | AO32: Reorganizar | AP32: Influir | AU32: Identificar | AV32: Diagramar | AW32: Evaluar | AX32: Constatar | AY32: Discriminar
L33: Presentar | M33: Presentar | N33: Operar | O33: Reconocer | P33: Gestionar | Q33: Elegir | S33: Presentar | T33: Presentar | U33: Operar | V33: Reconocer | W33: Gestionar | X33: Elegir | Y33: Filtrar | Z33: Maniobrar | AA33: Hacer | AB33: Mover | AC33: Preguntar | AD33: Seleccionar | AE33: Provocar | AO33: Resaltar | AP33: Innovar | AU33: Ilustrar | AV33: Dibujar | AW33: Experimentar | AX33: Contextualizar | AY33: Distinguir
L34: Probar | M34: Relatar | N34: Organizar | O34: Relacionar | P34: Hacer | Q34: Ensamblar | S34: Probar | T34: Relatar | U34: Organizar | V34: Relacionar | W34: Hacer | X34: Ensamblar | Y34: Gestionar | Z34: Manipular | AA34: Hallar | AB34: Ordenar | AC34: Publicar | AE34: Ratificar | AO34: Separar | AP34: Justificar | AU34: Indicar | AV34: Diferenciar | AW34: Hacer uso | AX34: Contribuir | AY34: Ejercer
L35: Realizar | M35: Reportar | N35: Patronar | O35: Separar | P35: Inferir | Q35: Escoger | S35: Realizar | T35: Reportar | U35: Patronar | V35: Separar | W35: Inferir | X35: Escoger | Y35: Hacer | Z35: Mejorar | AA35: Imprimir | AB35: Ponderar | AC35: Realizar | AE35: Seleccionar | AO35: Simplificar | AP35: Juzgar | AU35: Inferir | AV35: Discernir | AW35: Identificar | AX35: Controlar | AY35: Elegir
L36: Reconocer | M36: Resumir | N36: Practicar | O36: Subdividir | P36: Instalar | Q36: Establecer | S36: Reconocer | T36: Resumir | U36: Practicar | V36: Subdividir | W36: Instalar | X36: Establecer | Y36: Inspeccionar | Z36: Perforar | AA36: Impulsar | AB36: Preguntar | AC36: Seleccionar | AE36: Ser partidario de | AP36: Medir | AU36: Informar | AV36: Discriminar | AW36: Ilustrar | AX36: Convocar | AY36: Escoger
L37: Recordar | M37: Revisar | N37: Recoger | P37: Interpretar | Q37: Estimar | S37: Recordar | T37: Revisar | U37: Recoger | W37: Interpretar | X37: Estimar | Y37: Juntar | Z37: Poner | AA37: Interpretar | AB37: Probar | AC37: Servir | AE37: Soportar | AP37: Opinar | AU37: Interpretar | AV37: Diseñar | AW37: Indicar | AX37: Cooperar | AY37: Estimar
L38: Registrar | M38: Seleccionar | N38: Relacionar | P38: Introducir | Q38: Evaluar | S38: Registrar | T38: Seleccionar | U38: Relacionar | W38: Introducir | X38: Evaluar | Y38: Limpiar | Z38: Reconocer | AA38: Levantar | AB38: Quitar | AC38: Tasar | AE38: Tasar | AP38: Originar | AU38: Inventariar | AV38: Distinguir | AW38: Interpretar | AX38: Creer | AY38: Estimular
L39: Relacionar | M39: Separar | N39: Reportar | P39: Inventar | Q39: Evaluar | S39: Relacionar | T39: Separar | U39: Reportar | W39: Inventar | X39: Evaluar | Y39: Modificar | Z39: Registrar | AA39: Localizar | AB39: Reconocer | AC39: Usar | AE39: Unir | AP39: Percibir | AU39: Localizar | AV39: Dividir | AW39: Investigar | AX39: Cuestionar | AY39: Exteriorizar
L40: Relatar | M40: Traducir | N40: Resolver | P40: Juntar | Q40: Finalizar | S40: Relatar | T40: Traducir | U40: Resolver | W40: Juntar | X40: Finalizar | Y40: Modificar | Z40: Revisar | AA40: Manejar | AB40: Reemplazar | AC40: Valorar | AP40: Persuadir | AU40: Mostrar | AV40: Dramatizar | AW40: Listar | AX40: Cuidar | AY40: Extraer
L41: Reproducir | M41: Transformar | N41: Transferir | P41: Manipular | Q41: Formar | S41: Reproducir | T41: Transformar | U41: Transferir | W41: Manipular | X41: Formar | Y41: Ordenar | Z41: Trazar | AA41: Maniobrar | AB41: Remover | AP41: Premiar | AU41: Narrar | AV41: Duplicar | AW41: Manipular | AX41: Cumplir | AY41: Formular
L42: Revisar | M42: Ubicar | N42: Usar | P42: Mejorar | Q42: Justificar | S42: Revisar | T42: Ubicar | U42: Usar | W42: Mejorar | X42: Justificar | Y42: Organizar | AA42: Manipular | AB42: Reparar | AP42: Probar | AU42: Observar | AV42: Elegir | AW42: Modelar | AX42: Defender | AY42: Identificar
L43: Rotular | N43: Valorar | P43: Modificar | Q43: Juzgar | S43: Rotular | U43: Valorar | W43: Modificar | X43: Juzgar | Y43: Preparar | AA43: Medir | AB43: Reponer | AP43: Recomendar | AU43: Predecir | AV43: Emparejar | AW43: Operar | AX43: Definir | AY43: Juzgar
L44: Seleccionar | P44: Numerar | Q44: Marcar | S44: Seleccionar | W44: Numerar | X44: Marcar | Y44: Probar | AA44: Mezclar | AB44: Reproducir | AP44: Seleccionar | AU44: Preguntar | AV44: Emplear | AW44: Organizar | AX44: Desplegar | AY44: Negociar
L45: Subrayar | P45: Obtener | Q45: Marcar | S45: Subrayar | W45: Obtener | X45: Marcar | Y45: Recaudar | AA45: Mitigar | AB45: Resolver | AP45: Testar | AU45: Presentar | AV45: Encontrar | AW45: Patronar | AX45: Determinar | AY45: Ofrecer
P46: Ordenar | Q46: Medir | W46: Ordenar | X46: Medir | Y46: Recoger | AA46: Modificar | AB46: Retirar | AP46: Valorar | AU46: Relacionar | AV46: Encuestar | AW46: Planear | AX46: Discernir | AY46: Participar
P47: Organizar | Q47: Modificar | W47: Organizar | X47: Modificar | Y47: Recortar | AA47: Mover | AB47: Revisar | AU47: Relatar | AV47: Esquematizar | AW47: Practicar | AX47: Discriminar | AY47: Percibir
P48: Organizar | Q48: Numerar | W48: Organizar | X48: Numerar | Y48: Reunir | AA48: Negociar | AB48: Seguir | AU48: Reportar | AV48: Establecer | AW48: Recoger | AX48: Distinguir | AY48: Preguntar
P49: Perfeccionar | Q49: Peritar | W49: Perfeccionar | X49: Peritar | Y49: Señalar | AA49: Operar | AB49: Servir | AU49: Resumir | AV49: Estimar | AW49: Relacionar | AX49: Ejercer | AY49: Promover
P50: Planear | Q50: Predecir | W50: Planear | X50: Predecir | Y50: Transformar | AA50: Ordenar | AB50: Sincronizar | AU50: Revisar | AV50: Estructurar | AW50: Reportar | AX50: Elegir | AY50: Proponer
P51: Planificar | Q51: Pronosticar | W51: Planificar | X51: Pronosticar | Y51: Trazar | AA51: Organizar | AB51: Soldar | AU51: Seleccionar | AV51: Evaluar | AW51: Resolver | AX51: Ensamblar | AY51: Proporcionar
P52: Poner | Q52: Recomendar | W52: Poner | X52: Recomendar | Y52: Verificar | AA52: Pintar | AB52: Suprimir | AU52: Separar | AV52: Examinar | AW52: Resumir | AX52: Entregar | AY52: Provocar
P53: Predecir | Q53: Repartir | W53: Predecir | X53: Repartir | AA53: Planear | AB53: Sustituir | AU53: Traducir | AV53: Experimentar | AW53: Seleccionar | AX53: Escoger | AY53: Reconocer
P54: Preparar | Q54: Resolver | W54: Preparar | X54: Resolver | AA54: Porcionar | AB54: Tapizar | AU54: Transformar | AV54: Ilustrar | AW54: Simular | AX54: Estimar | AY54: Relacionar
P55: Producir | Q55: Reunir | W55: Producir | X55: Reunir | AA55: Practicar | AB55: Traducir | AU55: Ubicar | AV55: Indicar | AW55: Transferir | AX55: Estimular | AY55: Resumir
P56: Proponer | Q56: Revisar | W56: Proponer | X56: Revisar | AA56: Presentar | AB56: Transmitir | AV56: Inferir | AW56: Unir | AX56: Exteriorizar | AY56: Seleccionar
P57: Proyectar | Q57: Seleccionar | W57: Proyectar | X57: Seleccionar | AA57: Producir | AB57: Trasladar | AV57: Inspeccionar | AW57: Usar | AX57: Extraer | AY57: Ser partidario de
P58: Resolver | Q58: Sistematizar | W58: Resolver | X58: Sistematizar | AA58: Racionar | AB58: Ubicar | AV58: Interpretar | AX58: Fomentar | AY58: Unir
P59: Reunir | Q59: Sugerir | W59: Reunir | X59: Sugerir | AA59: Realizar | AB59: Usar | AV59: Inventariar | AX59: Formular | AY59: Valorar
P60: Señalar | Q60: Tasar | W60: Señalar | X60: Tasar | AA60: Reducir | AB60: Utilizar | AV60: Investigar | AX60: Identificar
P61: Simplificar | Q61: Terminar | W61: Simplificar | X61: Terminar | AA61: Repartir | AB61: Validar | AV61: Listar | AX61: Juzgar
P62: Subdividir | Q62: Unir | W62: Subdividir | X62: Unir | AA62: Repasar | AB62: Verificar | AV62: Manipular | AX62: Negociar
P63: Suponer | Q63: Validar | W63: Suponer | X63: Validar | AA63: Representar | AV63: Medir | AX63: Ofrecer
Q64: Valorar | X64: Valorar | AA64: Revisar | AV64: Modelar | AX64: Participar
Q65: Verificar | X65: Verificar | AA65: Sacar | AV65: Motivar | AX65: Percibir
Q66: Vincular | X66: Vincular | AA66: Separer | AV66: Observar | AX66: Preguntar
AA67: Situar | AV67: Operar | AX67: Preocuparse de o por
AA68: Tocar | AV68: Ordenar | AX68: Promover
AA69: Ubicar | AV69: Organizar | AX69: Proponer
AV70: Patronar | AX70: Proporcionar
AV71: Planear | AX71: Proteger
AV72: Practicar | AX72: Provocar
AV73: Preguntar | AX73: Ratificar
AV74: Priorizar | AX74: Reconocer
AV75: Probar | AX75: Relacionar
AV76: Razonar | AX76: Relatar
AV77: Recoger | AX77: Resumir
AV78: Reconocer | AX78: Revelar
AV79: Relacionar | AX79: Seleccionar
AV80: Reorganizar | AX80: Ser partidario de
AV81: Reportar | AX81: Servir
... AV87: Transferir | AX87: Verificar
AV88: Usar
