Workbook
Name actitudinalB: Tabla5785[ActitudinalB]
Name actitudinalB: Tabla5785[ActitudinalB]
Name ActitudinalBAK: 'Taxonomias para RA'!$AC$3:$AG$3
Name AK: Tabla6088[AK]
Name AK: Tabla6088[AK]
Name AnálisisAK: Tabla99[AnálisisAK]
Name AnálisisAK: Tabla99[AnálisisAK]
Name AnálisisB: Tabla385280[AnálisisB]
Name AnálisisB: Tabla385280[AnálisisB]
Name AnálisisBAK: Tabla3865[AnálisisBAK]
Name AnálisisBAK: Tabla3865[AnálisisBAK]
Name AnalizarLK: Tabla2129[AnalizarLK]
Name AnalizarLK: Tabla2129[AnalizarLK]
Name AplicaciónB: Tabla375179[AplicaciónB]
Name AplicaciónB: Tabla375179[AplicaciónB]
Name AplicaciónBAK: Tabla3764[AplicaciónBAK]
Name AplicaciónBAK: Tabla3764[AplicaciónBAK]
Name AplicarLK: Tabla2028[AplicarLK]
Name AplicarLK: Tabla2028[AplicarLK]
Name áreasprofesionales: 'Paso1 Analisis perfil egreso'!$H$3:$H$14
Name áreasprofesionales: 'Paso1 Analisis perfil egreso'!$H$3:$H$14
Name BAK: Tabla5886[BAK]
Name BAK: Tabla5886[BAK]
Name Bloom: 'Taxonomias para RA'!$G$3:$I$3
Name CaracterizarBAK: Tabla4776[CaracterizarBAK]
Name CaracterizarBAK: Tabla4776[CaracterizarBAK]
Name Cognitivo: 'Paso1 Analisis perfil egreso'!$E$3:$E$15
Name Cognitivo: 'Paso1 Analisis perfil egreso'!$E$3:$E$15
Name cognitivoB: Tabla5583[CognitivoB]
Name cognitivoB: Tabla5583[CognitivoB]
Name CognitivoBAK: 'Taxonomias para RA'!$S$3:$X$3
Name competencias: 'Paso 2 Redacción competen'!$F$4:$F$13
Name ComponentesCompetencias: '[1]Paso1 Analisis perfil egreso'!$E$2:$G$2
Name ComprenderLK: 'Taxonomias para RA'!$AM$5:$AM$27
Name ComprensiónAK: Tabla98[ComprensiónAK]
Name ComprensiónAK: Tabla98[ComprensiónAK]
Name ComprensiónB: Tabla365078[ComprensiónB]
Name ComprensiónB: Tabla365078[ComprensiónB]
Name ComprensiónBAK: Tabla3663[ComprensiónBAK]
Name ComprensiónBAK: Tabla3663[ComprensiónBAK]
Name ConceptosLK: Tabla91[ConceptosLK]
Name ConceptosLK: Tabla91[ConceptosLK]
Name ConocimientoB: Tabla354977[ConocimientoB]
Name ConocimientoB: Tabla354977[ConocimientoB]
Name ConocimientoBAK: Tabla3555[ConocimientoBAK]
Name ConocimientoBAK: Tabla3555[ConocimientoBAK]
Name Conocimientos: 'Paso1 Analisis perfil egreso'!$E$3:$E$15
Name Conocimientos: 'Paso1 Analisis perfil egreso'!$E$3:$E$15
Name ControlBAK: Tabla4271[ControlBAK]
Name ControlBAK: Tabla4271[ControlBAK]
Name CrearLK: Tabla2333[CrearLK]
Name CrearLK: Tabla2333[CrearLK]
Name dominios: 'Paso1 Analisis perfil egreso'!$E$2:$G$2
Name EvaluaciónB: Tabla405482[EvaluaciónB]
Name EvaluaciónB: Tabla405482[EvaluaciónB]
Name EvaluaciónBAK: Tabla4067[EvaluaciónBAK]
Name EvaluaciónBAK: Tabla4067[EvaluaciónBAK]
Name EvaluarLK: 'Taxonomias para RA'!$AP$5:$AP$46
Name HechosLK: Tabla90[HechosLK]
Name HechosLK: Tabla90[HechosLK]

Sheet Paso1 Analisis perfil egreso
A1: [Escribir el nombre del programa] | B1: [Escribir la modalidad: presencial o virtual] | C1: [Escribir el perfil profesional del egresado.] | D1: [Escribir el perfil ocupacional del egresado.] | E1: Componentes fundamentales para definir competencias [Listar las palabras clave, no armar oraciones, respecto qué debe saber el egresado en las categorías de Saber -conocimientos, hechos, teorías-, Saber hacer -técnicas, procedimientos, metodologías-, y Saber ser -valores, condiciones. Esta información se estructura a partir del perfil profesional y cada saber hacer depende del saber ubicado a su izquierda, lo mismo ocurre con el saber ser.] | H1: Componentes fundamentales de la ocupación laboral del profesional [Listar, según lo escrito en el perfil ocupacional, en qué áreas, qué tareas potenciales y en qué poblaciones o contextos podrá laborar el profesional. Esta información es un listado general no requiere dependencia horizontal] | K1: Diferencial (valor agregado) del profesional [Listar, según lo escrito en los perfiles, los elementos que son diferenciales y generan un valor agregado al egresado. Debe ser disciplinar, asociado al perfil, ¿qué es lo que lo hace diferente a otros perfiles similares.]
A2: Programa | B2: Modalidad | C2: Perfil profesional | D2: Perfil ocupacional | E2: Saber | F2: Saberhacer | G2: Saberser | H2: ÁreasProfesionales | I2: TareasProfesionales | J2: PoblacionesActuacion | K2: ValorAgregado
A3: Contaduría Pública | B3: Virtual | C3: El profesional en Contaduría Pública del Politécnico Grancolombiano conoce los principios contables, las normas tributarias, los estándares internacionales de información financiera, los procedimientos de auditoría y los sistemas de control interno. Con este saber, analiza la información contable, gestiona obligaciones fiscales, ejecuta auditorías y evalúa la calidad y consistencia técnica de la información financiera de personas naturales, jurídicas y organizaciones, con el propósito de garantizar el cumplimiento normativo y dar soporte a la toma de decisiones informadas. Ejerce su rol con responsabilidad frente a la fe pública y con una perspectiva contable orientada a contextos nacionales e internacionales en distintos entornos organizacionales. | D3: El profesional en Contaduría Pública del Politécnico Grancolombiano analiza y valida la información contable de las organizaciones, asegurando su conformidad con los principios contables nacionales e internacionales, y ejerciendo su rol como garante de la fe pública sobre la calidad y legalidad de los registros contables. Asesora a los usuarios de la información contable y financiera mediante la interpretación de datos, el análisis de riesgos y la verificación de la coherencia técnica y normativa de la información contable que sustenta los estados financieros. Gestiona las obligaciones fiscales de personas naturales, jurídicas u organizaciones en cumplimiento de la normatividad tributaria vigente, y ejecuta auditorías aplicando técnicas y procedimientos especializados para evaluar la fiabilidad de la información contable y el cumplimiento de disposiciones regulatorias. Utiliza herramientas tecnológicas y métodos cuantitativos para generar análisis que respalden procesos de aseguramiento, control y proyección financiera en diversos contextos organizacionales. | E3: Normas contables, financieras y procedimientos de registro | F3: sustentar técnicamente los estados financieros y respaldar su conformidad legal | G3: con responsabilidad frente a la fe pública y compromiso con la transparencia. | H3: Área de Contabilidad o Dirección Financiera/Gerencia de Contabilidad / Subdirección Financiera/Dirección Financiera / Planeación Financiera y Control/Dirección de Contabilidad / Finanzas Corporativas/Unidad de Registro Financiero/ Direcció u Oficina de Control Interno / Auditoría Gubernamental/ Gerencia General / Consultoría/Departamento Tributario /Consultoría Fiscal /Departamento de Cumplimiento / Riesgo Operativo/Auditoría Interna Cumplimiento y Riesgos/Oficina de Revisoría Fiscal / Junta Directiva/Firmas de Auditoría Externa / Contratista Independiente | I3: Preparar y analizar estados financieros (balance, estado de resultados, flujos de efectivo)/Gestionar registros contables, conciliaciones y ciclos contables/Supervisar procesos de cierre contable, presupuestación, proyecciones financieras y control de flujo de efectivo/Coordinar auditorías internas y externas/Registrar, ordenar y respaldar transacciones financieras/Gestionar requerimientos y plazos, aplicando procedimientos establecidos de control interno/Organizar y mantener actualizada la información financiera/Analizar informes financieros para evaluar el rendimiento y rentabilidad organizacional/Realizar proyecciones y evaluaciones de inversiones, identificando oportunidades de mejora/Elaborar recomendaciones estratégicas para optimizar recursos y maximizar resultados financieros/Gestionar obligaciones fiscales, preparar declaraciones de impuestos y cumplir con normativas tributarias vigentes/Optimizar cargas fiscales mediante planificación y aprovechamiento de incentivos legales/Evaluar sistemas de control interno y riesgo operativo, proponiendo mejoras sistemáticas/Aplicar análisis detallados para sustentar evidencias legales y formular recomendaciones de control/Investigar irregularidades contables, fraudes o incumplimientos mediante técnicas de auditoría forense/Verificar el cumplimiento legal y fiduciario de la información financiera/Emitir dictámenes independientes sobre la integridad y veracidad de los estados contables. | J3: Micro, pequeñas, medianas y grandes empresas de todos los sectores económicos (comercial, industrial, financiero, agroindustrial, servicios, etc.)/Alcaldías, gobernaciones, ministerios, superintendencias, entidades descentralizadas/Empresas especializadas en servicios contables, fiscales, financieros y de aseguramiento de la información/Empresas multinacionales y grupos empresariales/Organizaciones no gubernamentales (ONG) y fundaciones/Personas naturales y pequeños contribuyentes/Empresas del sector solidario y cooperativo/Organismos de control | K3: El egresado del programa de Contaduría Pública del Politécnico Grancolombiano articula la formación contable, financiera, tributaria y de aseguramiento con el uso de tecnologías y la analítica de datos para fortalecer procesos integrales en la adecuada gestión de las organizaciones. Su formación en control, auditoría forense, gestión de riesgos y cumplimiento normativo orienta su ejercicio profesional hacia la toma de decisiones basada en información confiable.
E4: Normativa tributaria y procedimientos fiscales | F4: gestionar el cumplimiento tributario en distintos tipos de contribuyentes | G4: con rigurosidad técnica y sentido ético.
E5: Auditoría, aseguramiento y control de la información | F5: verificar la confiabilidad técnica de la información financiera y su alineación con las disposiciones regulatorias | G5: con criterio profesional y enfoque en la consistencia normativa.
E6: Herramientas tecnológicas, métodos cuantitativos y análisis financiero | F6: preparar informes contables y estados financieros de personas naturales, jurídicas u organizaciones, | G6: que sirvan de base en la toma de decisiones, con visión estratégica y adaptación a entornos globales.
E7: Fenómenos contemporáneos | F7: reconocer sus afectaciones o contribuciones en el marco de las ciudadanías globales y de una sociedad responsable y sostenible. | G7: desde una perspectiva glocal, soportada en datos, con una mirada ética y crítica

Sheet Paso 2 Redacción competen
A1: Elementos para redactar las competencias que desarrollará el programa
A2: [Enumerar las competencias que se van a declarar.] | B2: [A partir de la celda B2 dar clic sobre el ícono de lista desplegable y elegir el verbo que considere adecuado.] | C2: [A partir de la celda C2 dar clic sobre la lista desplegable y elegir el saber extraído del perfil de egreso.] | D2: [Escribir para qué se abordará el saber elegido. Se sugiere apoyarse en el saber hacer.] | E2: [Escribir la condición describiendo los referentes, parámetros, principios, requerimientos o retos que se necesitan para alcanzar las características del perfil en el contexto donde el egresado se desenvolverá.] | F2: [Articular los componentes. Iniciar con el verbo, continuar con el objeto conceptual, luego la finalidad y condición de contexto o referencia; estos últimos no requieren un orden particular.] | G2: [Escribir el tipo de competencia del perfil: Específica (si es del bloque Disciplinar para pregrado o de los componentes para el caso de posgrado) o Genérica (si aplica bloque institucional pregrado)]
A3: No. | B3: Verbo competencia | C3: Objeto conceptual | D3: Finalidad | E3: Condición de contexto o referencia | F3: Redacción competencia | G3: Tipo competencia
A4: 1 | B4: Validar | C4: Normas contables, financieras y procedimientos de registro | D4: sustentar técnicamente los estados financieros y respaldar su conformidad legal | E4: con responsabilidad frente a la fe pública y compromiso con la transparencia. | F4: Validar la información contable y financiera con base en normas contables, financieras y procedimientos de registro para sustentar técnicamente los estados financieros y respaldar su conformidad legal, con responsabilidad frente a la fe pública y compromiso con la transparencia. | G4: Específica
A5: 2 | B5: Dominar | C5: Normativa tributaria y procedimientos fiscales | D5: gestionar el cumplimiento tributario en distintos tipos de contribuyentes | E5: con rigurosidad técnica, sentido ético y adaptación a entornos globales. | F5: Dominar la normativa tributaria y los procedimientos fiscales para gestionar el cumplimiento de las obligaciones tributarias en distintos tipos de contribuyentes, con rigurosidad técnica, sentido ético y adaptación a entornos globales. | G5: Específica
A6: 3 | B6: Desarrollar | C6: Auditoría, aseguramiento y control de la información | D6: verificar la confiabilidad técnica de la información financiera y su alineación con las disposiciones regulatorias | E6: con criterio profesional y enfoque en la consistencia normativa. | F6: Desarrollar procesos de auditoría, aseguramiento y control de la información para verificar la confiabilidad técnica de la información financiera y su alineación con las disposiciones regulatorias, con criterio profesional y enfoque en la consistencia normativa. | G6: Específica
A7: 4 | B7: Aplicar | C7: Herramientas tecnológicas, métodos cuantitativos y análisis financiero | D7: preparar informes contables y estados financieros de personas naturales, jurídicas u organizaciones, | E7: que sirvan de base en la toma de decisiones, con visión estratégica . | F7: Aplicar herramientas tecnológicas, métodos cuantitativos y análisis financiero para preparar informes contables y estados financieros de personas naturales, jurídicas u organizaciones que sirvan de base en la toma de decisiones, con visión estratégica. | G7: Específica
A8: 5 | B8: Analizar | C8: Fenómenos contemporáneos | D8: reconocer sus afectaciones o contribuciones en el marco de las ciudadanías globales y de una sociedad responsable y sostenible. | E8: desde una perspectiva glocal, soportada en datos, con una mirada ética y crítica | F8: Analizar los fenómenos contemporáneos desde una perspectiva glocal, soportada en datos, con una mirada ética y crítica, para reconocer sus afectaciones o contribuciones en el marco de las ciudadanías globales y de una sociedad responsable y sostenible. | G8: Genérica

Sheet Paso 3 Redacción RA 
A1: [A partir de la celda A2 dar clic en la lista desplegable y seleccionar la competencia redactada en el paso 2.] | B1: [Enumerar los resultados de aprendizaje que se van a declarar.] | C1: [A partir de la celda C2, dar clic en la lista desplegable y elegir el tipo de dominio a tratar en el resultado de aprendizaje.] | D1: [A partir de la cela D2, dar clic en la lista desplegable y elegir el saber correspondiente al dominio.] | E1: [A partir de la celda E2, dar clic en la lista desplegable y elegir la taxonomía que se considere adecuada, solo se elige una para todos los saberes.] | F1: [A partir de la celda F2, dar clic en la lista desplegable y elegir el dominio que se considera adecuado.] | G1: [A partir de la celda G2, dar clic en la lista desplegable y elegir el nivel del dominio que se considera adecuado.] | H1: [A partir de la celda H2, dar clic en la lista desplegable y elegir el verbo que se considera adecuado.] | I1: [Iniciar con el verbo elegido (columna H), en infinitivo, luego el objeto sobre el cual recae la acción (columna D) y finalmente la condición de contexto (académico, disciplinar, social u otro).]
A2: Competencia por desarrollar | B2: Número de resultado | C2: TipoSaber | D2: SaberAsociado | E2: Taxonomía | F2: Dominio Asociado | G2: Nivel Dominio | H2: Verbo RA | I2: Resultados Aprendizaje
A3: Dominar la normativa tributaria y los procedimientos fiscales para gestionar el cumplimiento de las obligaciones tributarias en distintos tipos de contribuyentes, con rigurosidad técnica, sentido ético y adaptación a entornos globales. | B3: 1 | C3: Saber | D3: Normativa tributaria y procedimientos fiscales | E3: Bloom | F3: CognitivoB | G3: AnálisisB | H3: Analizar | I3: Analiza la normativa vigentes en la preparación y revisión de información contable, financiera y tributaria para identificar criterios técnicos y legales que permitan abordar situaciones contables y fiscales, según el contexto de aplicación.
A4: Dominar la normativa tributaria y los procedimientos fiscales para gestionar el cumplimiento de las obligaciones tributarias en distintos tipos de contribuyentes, con rigurosidad técnica, sentido ético y adaptación a entornos globales. | B4: 5 | C4: Saberhacer | D4: gestionar el cumplimiento tributario en distintos tipos de contribuyentes | E4: Bloom | F4: ProcedimentalB | G4: AnálisisB | H4: Desarrollar | I4: Desarrolla procedimientos contables y tributarios para construir estados financieros conforme a la normativa aplicable, integrando el cumplimiento de obligaciones fiscales de personas naturales y jurídicas.
A5: Dominar la normativa tributaria y los procedimientos fiscales para gestionar el cumplimiento de las obligaciones tributarias en distintos tipos de contribuyentes, con rigurosidad técnica, sentido ético y adaptación a entornos globales. | B5: 8 | C5: Saberser | D5: con rigurosidad técnica y sentido ético. | E5: Bloom | F5: ActitudinalB | G5: AnálisisB | H5: Reconocer | I5: Reconoce criterios éticos, legales, sociales y estratégicos del saber contable, tributario, financiero y de auditoría para aplicarlos con rigor técnico en la preparación de información de personas naturales y jurídicas, según el contexto o situación.
A6: Validar la información contable y financiera con base en normas contables, financieras y procedimientos de registro para sustentar técnicamente los estados financieros y respaldar su conformidad legal, con responsabilidad frente a la fe pública y compromiso con la transparencia. | B6: 1 | C6: Saber | D6: Normas contables, financieras y procedimientos de registro | E6: Bloom | F6: CognitivoB | G6: AnálisisB | H6: Analizar | I6: Analiza la normativa vigentes en la preparación y revisión de información contable, financiera y tributaria para identificar criterios técnicos y legales que permitan abordar situaciones contables y fiscales, según el contexto de aplicación.
A7: Validar la información contable y financiera con base en normas contables, financieras y procedimientos de registro para sustentar técnicamente los estados financieros y respaldar su conformidad legal, con responsabilidad frente a la fe pública y compromiso con la transparencia. | B7: 5 | C7: Saberhacer | D7: sustentar técnicamente los estados financieros y respaldar su conformidad legal | E7: Bloom | F7: ProcedimentalB | G7: AnálisisB | H7: Desarrollar | I7: Desarrolla procedimientos contables y tributarios para construir estados financieros conforme a la normativa aplicable, integrando el cumplimiento de obligaciones fiscales de personas naturales y jurídicas.
A8: Validar la información contable y financiera con base en normas contables, financieras y procedimientos de registro para sustentar técnicamente los estados financieros y respaldar su conformidad legal, con responsabilidad frente a la fe pública y compromiso con la transparencia. | B8: 8 | C8: Saberser | D8: con responsabilidad frente a la fe pública y compromiso con la transparencia. | E8: Bloom | F8: ActitudinalB | G8: AnálisisB | H8: Reconocer | I8: Reconoce criterios éticos, legales, sociales y estratégicos del saber contable, tributario, financiero y de auditoría para aplicarlos con rigor técnico en la preparación de información de personas naturales y jurídicas, según el contexto o situación.
A9: Desarrollar procesos de auditoría, aseguramiento y control de la información para verificar la confiabilidad técnica de la información financiera y su alineación con las disposiciones regulatorias, con criterio profesional y enfoque en la consistencia normativa. | B9: 2 | C9: Saber | D9: Auditoría, aseguramiento y control de la información | E9: Bloom | F9: CognitivoB | G9: ComprensiónB | H9: Interpretar | I9: Interpreta la información contable, financiera y tributaria en contextos de aseguramiento y control para establecer su pertinencia y confiabilidad en la resolución de situaciones contables organizacionales.
A10: Desarrollar procesos de auditoría, aseguramiento y control de la información para verificar la confiabilidad técnica de la información financiera y su alineación con las disposiciones regulatorias, con criterio profesional y enfoque en la consistencia normativa. | B10: 6 | C10: Saberhacer | D10: verificar la confiabilidad técnica de la información financiera y su alineación con las disposiciones regulatorias | E10: Bloom | F10: ProcedimentalB | G10: AplicaciónB | H10: Utilizar | I10: Utiliza información contable, financiera, tributaria y de auditoría para elaborar reportes, y proyecciones que faciliten la toma de decisiones de distintos tipos de usuarios, considerando sus necesidades y características.
A11: Desarrollar procesos de auditoría, aseguramiento y control de la información para verificar la confiabilidad técnica de la información financiera y su alineación con las disposiciones regulatorias, con criterio profesional y enfoque en la consistencia normativa. | B11: 8 | C11: Saberser | D11: con criterio profesional y enfoque en la consistencia normativa. | E11: Bloom | F11: ActitudinalB | G11: AnálisisB | H11: Reconocer | I11: Reconoce criterios éticos, legales, sociales y estratégicos del saber contable, tributario, financiero y de auditoría para aplicarlos con rigor técnico en la preparación de información de personas naturales y jurídicas, según el contexto o situación.
A12: Aplicar herramientas tecnológicas, métodos cuantitativos y análisis financiero para preparar informes contables y estados financieros de personas naturales, jurídicas u organizaciones que sirvan de base en la toma de decisiones, con visión estratégica. | B12: 3 | C12: Saber | D12: Herramientas tecnológicas, métodos cuantitativos y análisis financiero | E12: Bloom | F12: CognitivoB | G12: ComprensiónB | H12: Relacionar | I12: Relaciona métodos cuantitativos y modelos de planeación financiera para explicar dinámicas contables y financieras según el contexto analizado, usando herramientas tecnológicas.
A13: Aplicar herramientas tecnológicas, métodos cuantitativos y análisis financiero para preparar informes contables y estados financieros de personas naturales, jurídicas u organizaciones que sirvan de base en la toma de decisiones, con visión estratégica. | B13: 7 | C13: Saberhacer | D13: preparar informes contables y estados financieros de personas naturales, jurídicas u organizaciones, | E13: Bloom | F13: ProcedimentalB | G13: AplicaciónB | H13: Utilizar | I13: Utiliza métodos cuantitativos y herramientas tecnológicas para elaborar reportes sobre la situación contable y financiera de personas naturales, personas jurídicas y organizaciones, a partir de datos y contextos definidos.
A14: Aplicar herramientas tecnológicas, métodos cuantitativos y análisis financiero para preparar informes contables y estados financieros de personas naturales, jurídicas u organizaciones que sirvan de base en la toma de decisiones, con visión estratégica. | B14: 8 | C14: Saberser | D14: que sirvan de base en la toma de decisiones, con visión estratégica y adaptación a entornos globales. | E14: Bloom | F14: ActitudinalB | G14: AnálisisB | H14: Reconocer | I14: Reconoce criterios éticos, legales, sociales y estratégicos del saber contable, tributario, financiero y de auditoría para aplicarlos con rigor técnico en la preparación de información de personas naturales y jurídicas, según el contexto o situación.
A15: Analizar los fenómenos contemporáneos desde una perspectiva glocal, soportada en datos, con una mirada ética y crítica, para reconocer sus afectaciones o contribuciones en el marco de las ciudadanías globales y de una sociedad responsable y sostenible. | B15: 4 | C15: Saber | D15: Fenómenos contemporáneos | E15: Bloom | F15: CognitivoB | G15: ComprensiónB | H15: Identificar | I15: Identifica fenómenos contemporáneos y su relación con la profesión, para determinar sus impactos e influencia en la sociedad, de forma responsable y crítica.

Sheet Paso 4 Estrategias mesocurricu
A1: [A partir de la celda A3 despliegue el(los) resultado(s) de aprendizaje y elegir aquel (aquellos) al(a los) que se contribuye desde la estrategia.] | B1: [Escribir el nombre de la estrategia a desarrollar. Participación de los estudiantes en cursos, talleres, seminarios, conferencias, pruebas estandarizadas, investigaciones, actividades o experiencias, cuerpos académicos, redes, comunidades, la elaboración de textos y materiales, así como las publicaciones, entre otros.] | C1: [Describir la(s) estrategia(s) definidas por el programa.] | D1: [Escribir los indicadores de impacto de la estrategia. Se sugieren indicadores como: Valora el nivel de contribución de la estrategia a los resultados de aprendizaje; Número de estudiantes que participan en la estrategia; Número de veces que se realiza la estrategia, entre otros.] | E1: [Escribir las acciones de retroalimentación que usará el programa para comunicar a los estudiantes sobre el alcance de sus resultados de aprendizaje.] | F1: [Escribir, para cada indicador con qué instrumento se recogerá información para evidenciar el (los) impacto (s) declarados. Encuesta, lista de asistencia, informe, entre otros.]
A2: Resultado de aprendizaje | B2: Estrategia del programa | C2: Descripción | D2: Indicador de Impacto de la Estrategia | E2: Acciones de retroalimentación para los estudiantes | F2: Instrumentos de medición
A3: Analiza la normativa vigentes en la preparación y revisión de información contable, financiera y tributaria para identificar criterios técnicos y legales que permitan abordar situaciones contables y fiscales, según el contexto de aplicación. | B3: Congresos, conversatorios, capacitaciones seminarios y workshoop | C3: Estrategia que promueve la participación activa de la comunidad académica en eventos nacionales e internacionales que fortalecen el conocimiento disciplinar, fomentan el pensamiento crítico y permiten el intercambio de experiencias académicas y profesionales. | D3: Número de veces que se realiza la estrategia por periodo académico. | E3: Formar: para ampliar los saberes disciplinares, fortaleciendo conocimientos técnicos, habilidades comunicativas y pensamiento crítico. Informar: para mantener a la comunidad académica actualizada sobre avances normativos, tecnológicos y tendencias del entorno profesional. Ayudar a decidir: a través de la exposición a diversos enfoques y experiencias que permiten perfilar intereses académicos y profesionales. | F3: Informe o Reporte.
A4: Interpreta la información contable, financiera y tributaria en contextos de aseguramiento y control para establecer su pertinencia y confiabilidad en la resolución de situaciones contables organizacionales. | D4: Número de estudiantes que participan en la estrategia por periodo académico. | F4: Listados de participación.
A5: Relaciona métodos cuantitativos y modelos de planeación financiera para explicar dinámicas contables y financieras según el contexto analizado, usando herramientas tecnológicas. | D5: Valoración del nivel de aporte de la estrategia a los resultados de aprendizaje del programa. | F5: Encuesta de valoración.
A6: Reconoce criterios éticos, legales, sociales y estratégicos del saber contable, tributario, financiero y de auditoría para aplicarlos con rigor técnico en la preparación de información de personas naturales y jurídicas, según el contexto o situación.
A7: Analiza la normativa vigentes en la preparación y revisión de información contable, financiera y tributaria para identificar criterios técnicos y legales que permitan abordar situaciones contables y fiscales, según el contexto de aplicación. | B7: Semilleros de investigación | C7: Espacios extracurriculares orientados al aprendizaje colectivo, donde estudiantes y docentes desarrollan procesos investigativos que permiten profundizar en temas clave del saber contable, tributario, financiero y de aseguramiento. | D7: Número de estudiantes que participan en la estrategia por periodo académico. | E7: Formar: para fortalecer habilidades investigativas, el trabajo colaborativo y el pensamiento analítico. Prevenir: a través de la profundización temática que permite anticipar vacíos de conocimiento o dificultades académicas. Ayudar a decidir: para orientar la elección de líneas de investigación, temas de trabajo de grado o proyección académica. | F7: Listados de participación.
A8: Interpreta la información contable, financiera y tributaria en contextos de aseguramiento y control para establecer su pertinencia y confiabilidad en la resolución de situaciones contables organizacionales. | D8: Número de veces que se realiza la estrategia por periodo académico. | F8: Informe o Reporte.
A9: Relaciona métodos cuantitativos y modelos de planeación financiera para explicar dinámicas contables y financieras según el contexto analizado, usando herramientas tecnológicas. | D9: Valoración del nivel de aporte de la estrategia a los resultados de aprendizaje del programa. | F9: Encuesta de valoración.
A10: Desarrolla procedimientos contables y tributarios para construir estados financieros conforme a la normativa aplicable, integrando el cumplimiento de obligaciones fiscales de personas naturales y jurídicas.
A11: Reconoce criterios éticos, legales, sociales y estratégicos del saber contable, tributario, financiero y de auditoría para aplicarlos con rigor técnico en la preparación de información de personas naturales y jurídicas, según el contexto o situación.
A12: Analiza la normativa vigentes en la preparación y revisión de información contable, financiera y tributaria para identificar criterios técnicos y legales que permitan abordar situaciones contables y fiscales, según el contexto de aplicación. | B12: Consultorio tributario | C12: Servicio de consultoría presencial y virtual liderado por estudiantes y profesionales expertos, que brinda orientación gratuita en temas tributarios y empresariales a diferentes poblaciones, como parte de la proyección social de la Facultad de Negocios, Gestión y Sostenibilidad. | D12: Número de estudiantes que participan en la estrategia. | E12: Formar: a través de la aplicación práctica del saber contable y tributario en contextos reales. Informar: para evidenciar la normativa vigente y su aplicación en escenarios empresariales y sociales. Ayudar a decidir: mediante el análisis de casos reales que aportan elementos éticos y técnicos en la toma de decisiones. | F12: Listados de participación.
A13: Desarrolla procedimientos contables y tributarios para construir estados financieros conforme a la normativa aplicable, integrando el cumplimiento de obligaciones fiscales de personas naturales y jurídicas. | D13: Número de oportunidades de consultoría, auditoría e interventoría desarrolladas con medición semestral. | F13: Informe o Reporte.
A14: Reconoce criterios éticos, legales, sociales y estratégicos del saber contable, tributario, financiero y de auditoría para aplicarlos con rigor técnico en la preparación de información de personas naturales y jurídicas, según el contexto o situación. | D14: Valoración del nivel de aporte de la estrategia a los resultados de aprendizaje del programa. | F14: Encuesta de valoración.
A15: Interpreta la información contable, financiera y tributaria en contextos de aseguramiento y control para establecer su pertinencia y confiabilidad en la resolución de situaciones contables organizacionales.
A16: Utiliza información contable, financiera, tributaria y de auditoría para elaborar reportes, y proyecciones que faciliten la toma de decisiones de distintos tipos de usuarios, considerando sus necesidades y características.
A17: Relaciona métodos cuantitativos y modelos de planeación financiera para explicar dinámicas contables y financieras según el contexto analizado, usando herramientas tecnológicas.
A18: Utiliza métodos cuantitativos y herramientas tecnológicas para elaborar reportes sobre la situación contable y financiera de personas naturales, personas jurídicas y organizaciones, a partir de datos y contextos definidos.
A19: Analiza la normativa vigentes en la preparación y revisión de información contable, financiera y tributaria para identificar criterios técnicos y legales que permitan abordar situaciones contables y fiscales, según el contexto de aplicación. | B19: Proyección social y extensión (Diplomados -MOOC - Videos de reforzamiento curricular) | C19: Iniciativas que articulan la academia con el entorno social a través de programas de formación continua, difusión del conocimiento y actividades orientadas al bienestar de la comunidad y al fortalecimiento del aprendizaje a lo largo de la vida. | D19: Número de estudiantes que participan en la estrategia por periodo académico. | E19: Formar: para complementar el proceso académico formal, promoviendo el aprendizaje autónomo y continuo. Informar: a través de la difusión de contenidos actualizados y pertinentes sobre el ejercicio profesional. Prevenir: para reforzar áreas de bajo rendimiento y anticipar dificultades académicas. | F19: Listados de participación.
A20: Desarrolla procedimientos contables y tributarios para construir estados financieros conforme a la normativa aplicable, integrando el cumplimiento de obligaciones fiscales de personas naturales y jurídicas. | D20: Relación de actividades desarrolladas en el grupo de interés con actividades del perfil ocupacional del programa. | F20: Informe o Reporte.
A21: Interpreta la información contable, financiera y tributaria en contextos de aseguramiento y control para establecer su pertinencia y confiabilidad en la resolución de situaciones contables organizacionales. | D21: Valoración del nivel de aporte de la estrategia a los resultados de aprendizaje del programa. | F21: Encuesta de valoración.
A22: Utiliza información contable, financiera, tributaria y de auditoría para elaborar reportes, y proyecciones que faciliten la toma de decisiones de distintos tipos de usuarios, considerando sus necesidades y características.
A23: Analiza la normativa vigentes en la preparación y revisión de información contable, financiera y tributaria para identificar criterios técnicos y legales que permitan abordar situaciones contables y fiscales, según el contexto de aplicación. | B23: Clases espejo | C23: Estrategia de internacionalización del currículo que conecta a estudiantes y docentes con tendencias académicas globales, promoviendo el intercambio de saberes y el diálogo académico con instituciones aliadas en diferentes países. | D23: Número de estudiantes que participan en la estrategia por periodo académico. | E23: Formar: para fomentar la comprensión intercultural y el pensamiento global aplicado al saber contable. Informar: a través de la exposición a metodologías y enfoques internacionales. Ayudar a decidir: para apoyar decisiones sobre internacionalización del currículo y orientación profesional. | F23: Listados de participación.
A24: Desarrolla procedimientos contables y tributarios para construir estados financieros conforme a la normativa aplicable, integrando el cumplimiento de obligaciones fiscales de personas naturales y jurídicas. | D24: Número de veces que se realiza la estrategia por periodo académico. | F24: Informe o Reporte.
A25: Interpreta la información contable, financiera y tributaria en contextos de aseguramiento y control para establecer su pertinencia y confiabilidad en la resolución de situaciones contables organizacionales. | D25: Valoración del nivel de aporte de la estrategia a los resultados de aprendizaje del programa. | F25: Encuesta de valoración.
A26: Utiliza información contable, financiera, tributaria y de auditoría para elaborar reportes, y proyecciones que faciliten la toma de decisiones de distintos tipos de usuarios, considerando sus necesidades y características.
A27: Analiza la normativa vigentes en la preparación y revisión de información contable, financiera y tributaria para identificar criterios técnicos y legales que permitan abordar situaciones contables y fiscales, según el contexto de aplicación. | B27: Participación en Centros de Emprendimiento, Liderazgo y Empresa Simulada | C27: Iniciativa que vincula a los estudiantes con espacios de formación práctica en emprendimiento, liderazgo y habilidades para la gestión, fortaleciendo su rol como agentes de cambio con impacto en sus comunidades y en el entorno empresarial. | D27: Número de estudiantes que participan en la estrategia en el periodo de su realización. | E27: Formar: para desarrollar habilidades gerenciales, de liderazgo y toma de decisiones empresariales. Prevenir: mediante la preparación para enfrentar escenarios organizacionales complejos desde la academia. Ayudar a decidir: para orientar la creación de iniciativas propias o el fortalecimiento del perfil emprendedor. | F27: Listas de participación.
A28: Desarrolla procedimientos contables y tributarios para construir estados financieros conforme a la normativa aplicable, integrando el cumplimiento de obligaciones fiscales de personas naturales y jurídicas. | D28: Número de veces que se realiza la estrategia por periodo académico. | F28: Informe o Reporte.
A29: Reconoce criterios éticos, legales, sociales y estratégicos del saber contable, tributario, financiero y de auditoría para aplicarlos con rigor técnico en la preparación de información de personas naturales y jurídicas, según el contexto o situación. | D29: Valoración del nivel de aporte de la estrategia a los resultados de aprendizaje del programa. | F29: Encuesta de valoración.
A30: Interpreta la información contable, financiera y tributaria en contextos de aseguramiento y control para establecer su pertinencia y confiabilidad en la resolución de situaciones contables organizacionales.
A31: Utiliza información contable, financiera, tributaria y de auditoría para elaborar reportes, y proyecciones que faciliten la toma de decisiones de distintos tipos de usuarios, considerando sus necesidades y características.
A32: Analiza la normativa vigentes en la preparación y revisión de información contable, financiera y tributaria para identificar criterios técnicos y legales que permitan abordar situaciones contables y fiscales, según el contexto de aplicación. | B32: Programa radial | C32: Estrategia de divulgación del conocimiento, a través de Poliradio, que amplía el alcance de los contenidos académicos y promueve el acceso abierto a la información de valor formativo. | D32: Número de estudiantes que participan en la estrategia por periodo académico. | E32: Informar: para facilitar el acceso a contenidos relevantes y actualizados del área contable y financiera. Formar: a través del estímulo al aprendizaje autónomo y el interés por la divulgación académica. | F32: Listas de participación.
A33: Reconoce criterios éticos, legales, sociales y estratégicos del saber contable, tributario, financiero y de auditoría para aplicarlos con rigor técnico en la preparación de información de personas naturales y jurídicas, según el contexto o situación. | D33: Número de veces que se realiza la estrategia por periodo académico. | F33: Informe o Reporte.
A34: Interpreta la información contable, financiera y tributaria en contextos de aseguramiento y control para establecer su pertinencia y confiabilidad en la resolución de situaciones contables organizacionales. | D34: Valoración del nivel de aporte de la estrategia a los resultados de aprendizaje del programa. | F34: Encuesta de valoración.
A35: Analiza la normativa vigentes en la preparación y revisión de información contable, financiera y tributaria para identificar criterios técnicos y legales que permitan abordar situaciones contables y fiscales, según el contexto de aplicación. | B35: Redes | C35: Participación en redes académicas y profesionales a nivel nacional e internacional, que ofrecen acceso a cursos, conferencias, proyectos y comunidades interdisciplinares, fortaleciendo la formación continua y las competencias investigativas. | D35: Número de estudiantes que participan en la estrategia por periodo académico. | E35: Formar: para enriquecer la experiencia académica mediante el contacto con comunidades de práctica nacionales e internacionales. Informar: a través del acceso a oportunidades formativas y eventos de interés académico. Ayudar a decidir: para brindar referentes que orienten decisiones sobre especialización o vinculación profesional. | F35: Listas de participación.
A36: Desarrolla procedimientos contables y tributarios para construir estados financieros conforme a la normativa aplicable, integrando el cumplimiento de obligaciones fiscales de personas naturales y jurídicas. | D36: Número de veces que se realiza la estrategia por periodo académico. | F36: Informe o Reporte.
A37: Reconoce criterios éticos, legales, sociales y estratégicos del saber contable, tributario, financiero y de auditoría para aplicarlos con rigor técnico en la preparación de información de personas naturales y jurídicas, según el contexto o situación. | D37: Valoración del nivel de aporte de la estrategia a los resultados de aprendizaje del programa. | F37: Encuesta de valoración.
A38: Interpreta la información contable, financiera y tributaria en contextos de aseguramiento y control para establecer su pertinencia y confiabilidad en la resolución de situaciones contables organizacionales.
A39: Utiliza información contable, financiera, tributaria y de auditoría para elaborar reportes, y proyecciones que faciliten la toma de decisiones de distintos tipos de usuarios, considerando sus necesidades y características.
A40: Relaciona métodos cuantitativos y modelos de planeación financiera para explicar dinámicas contables y financieras según el contexto analizado, usando herramientas tecnológicas.
A41: Utiliza métodos cuantitativos y herramientas tecnológicas para elaborar reportes sobre la situación contable y financiera de personas naturales, personas jurídicas y organizaciones, a partir de datos y contextos definidos.
A42: Analiza la normativa vigentes en la preparación y revisión de información contable, financiera y tributaria para identificar criterios técnicos y legales que permitan abordar situaciones contables y fiscales, según el contexto de aplicación. | B42: Tutorias | C42: Acompañamiento académico personalizado que apoya el fortalecimiento del saber de los estudiantes, favoreciendo el logro de los resultados de aprendizaje en diferentes momentos del proceso formativo. | D42: Número de estudiantes que participan en la estrategia por periodo académico. | E42: Formar: para fortalecer el desarrollo de competencias específicas mediante acompañamiento académico personalizado. Prevenir: a través de la detección y atención oportuna de dificultades académicas. Ayudar a decidir: para orientar la elección de rutas académicas o estrategias de mejora. | F42: Listas de participación.
A43: Desarrolla procedimientos contables y tributarios para construir estados financieros conforme a la normativa aplicable, integrando el cumplimiento de obligaciones fiscales de personas naturales y jurídicas. | D43: Número de veces que se realiza la estrategia por periodo académico. | F43: Informe o Reporte.
A44: Interpreta la información contable, financiera y tributaria en contextos de aseguramiento y control para establecer su pertinencia y confiabilidad en la resolución de situaciones contables organizacionales. | D44: Valoración del nivel de aporte de la estrategia a los resultados de aprendizaje del programa. | F44: Encuesta de valoración.
A45: Utiliza información contable, financiera, tributaria y de auditoría para elaborar reportes, y proyecciones que faciliten la toma de decisiones de distintos tipos de usuarios, considerando sus necesidades y características.
A46: Relaciona métodos cuantitativos y modelos de planeación financiera para explicar dinámicas contables y financieras según el contexto analizado, usando herramientas tecnológicas.
A47: Utiliza métodos cuantitativos y herramientas tecnológicas para elaborar reportes sobre la situación contable y financiera de personas naturales, personas jurídicas y organizaciones, a partir de datos y contextos definidos.
A48: Analiza la normativa vigentes en la preparación y revisión de información contable, financiera y tributaria para identificar criterios técnicos y legales que permitan abordar situaciones contables y fiscales, según el contexto de aplicación. | B48: Concurso de conocimientos | C48: Estrategia que promueve la evaluación y reflexión sobre los saberes técnicos adquiridos, al tiempo que incentiva el uso de una segunda lengua como herramienta para la proyección profesional y el desempeño en contextos globales. | D48: Número de estudiantes que participan en la estrategia por periodo académico. | E48: Formar: para reforzar conocimientos técnicos en un contexto de evaluación lúdica y competitiva. Informar: a través de la retroalimentación sobre el nivel de apropiación de saberes fundamentales. Ayudar a decidir: para identificar fortalezas y áreas de mejora que permitan proyectar su formación. | F48: Listas de participación.
A49: Desarrolla procedimientos contables y tributarios para construir estados financieros conforme a la normativa aplicable, integrando el cumplimiento de obligaciones fiscales de personas naturales y jurídicas. | D49: Número de veces que se realiza la estrategia por periodo académico. | F49: Informe o Reporte.
A50: Interpreta la información contable, financiera y tributaria en contextos de aseguramiento y control para establecer su pertinencia y confiabilidad en la resolución de situaciones contables organizacionales. | D50: Valoración del nivel de aporte de la estrategia a los resultados de aprendizaje del programa. | F50: Encuesta de valoración.
A51: Utiliza información contable, financiera, tributaria y de auditoría para elaborar reportes, y proyecciones que faciliten la toma de decisiones de distintos tipos de usuarios, considerando sus necesidades y características.
A52: Reconoce criterios éticos, legales, sociales y estratégicos del saber contable, tributario, financiero y de auditoría para aplicarlos con rigor técnico en la preparación de información de personas naturales y jurídicas, según el contexto o situación.

Sheet Paso 5 Estrategias micro
A1: [Estas celdas se diligencian automáticamente. No ajustar.] | B1: [A partir de la celda A3 despliegue el(los) resultado(s) de aprendizaje y elija aquel (aquellos) al(a los) que se contribuye desde la asignatura o módulo).] | C1: [Escribir el semestre en el que se cursa la asignatura o módulo.] | D1: [Escribir el nombre de la asignatura o módulo que contribuye al logro del resultado de aprendizaje.] | E1: [Redactar los indicadores iniciando con el verbo en presente indicativo, luego el objeto conceptual y finalmente el complemento de oración (que indique una condición o finalidad, con, para, de, entre otros conectores).] | F1: [Escribir la tipología: T (teórico), P (Práctico), TP (Teórico Práctico)] | G1: [Marcar con X el bloque o componente al que pertenece la asignatura o módulo. Por favor ajustar para posgrado, eliminar una columna y ubicar los títulos C.Fundamentación y C.Profundización.] | J1: [Escribir el número de créditos de la asignatura o módulo] | K1: [Escribir el número de horas de trabajo directo: 16*# o 12*#, para presencial o virtual, según sea el caso.] | L1: [Escribir el número de horas de trabajo independiente: 32*# columna J o 36*# columna J, para presencial o virtual, respectivamente.] | M1: [Escribir la suma de los números de horas de las dos celdas anteriores.] | N1: [Escribir el nombre de los cuatro núcleos temáticos que abordará la asignatura o el módulo.] | O1: [Escribir las lecturas, talleres, análisis, referentes, etc., que realiza el estudiante, clasificadas en trabajo directo e independiente.] | P1: [Escribir las actividades de evaluación que se emplean para identificar el alcance del (de los) indicador(es) de logro(s).] | Q1: [Escribir las acciones de retroalimentación que se emplearán en la asignatura o módulo, para retroalimentar a los estudiantes respecto al alcance de los indicadores de logro. Recordar que son cuatro acciones: informar, formar, prevenir y ayudar a tomar decisiones e indique cómo.]
A2: Tipo de Saber | B2: Resultado de aprendizaje | C2: Semestre | D2: Nombre asignatura o módulo | E2: Indicadores de logro asignatura o módulo | F2: Tipología | G2: B.Institucional | H2: B.Disciplinar | I2: B.Electivo | J2: Créditos | K2: Número de horas trabajo directo | L2: Número de horas trabajo independiente | M2: Total de horas | N2: Núcleos temáticos | O2: Actividades de aprendizaje | P2: Actividades de evaluación | Q2: Acciones de retroalimentación
A3: =_xlfn.XLOOKUP(B3,'Paso 3 Redacción RA '!I$3:I$15,'Paso 3 Redacción RA '!C$3:C$15,,0,1) -> Saber | B3: Identifica fenómenos contemporáneos y su relación con la profesión, para determinar sus impactos e influencia en la sociedad, de forma responsable y crítica. | C3: 1 | D3: Razonamiento Cuantitativo | E3: Analiza datos numéricos presentados en tablas, gráficos o textos para proponer soluciones informadas a situaciones problema del contexto. | F3: TP | G3: X | J3: 3 | K3: =12*J3 -> 36 | L3: =36*J3 -> 108 | M3: =SUM(K3:L3) -> 144 | N3: 1. Pensamiento numérico. Interpretación y representación de información numérica 2. Pensamiento algebraico. Desde la representación de regularidades y patrones 3. Pensamiento algebraico. Desde las relaciones de comparación entre cantidades o expresiones numéricas 4. Pensamiento geométrico. Propiedades, formas y relaciones espaciales | O3: Trabajo directo: Ecuentros sincrónicos Mensajería interna Anuncios Trabajo independiente: Lecturas fundamentales y complementarias Material de trabajo Participación en foros | P3: Evaluación diagnóstica: Cuestionario inicial de, mínimo, cinco preguntas, que recopila información sobre el conocimiento previo y las habilidades del estudiante. Actividad formativa: Foro individual o grupal, creado para que el estudiante participe activamente en la construcción de su conocimiento y desarrollo de habilidades. Varía entre una actividad entregable y la participación en un foro. Actividad de entrega: Actividad individual o grupal, diseñada para evaluar de manera integral el nivel de conocimiento, comprensión y el desempeño de los indicadores de logro. Varía entre entregas independientes o secuenciales. Al ser un módulo teórico, ésta es la única actividad de entrega. Actividad evaluativa: Cuestionario de, mínimo, cinco preguntas, que da cuenta del desarrollo total o parcial de los indicadores de logro y el desarrollo de los temas vistos hasta la unidad 3. Examen final: Cuestionario de, mínimo, quince preguntas, que da cuenta del desarrollo total o parcial de los indicadores de logro y el desarrollo de los temas vistos en el módulo. Autoevaluación: Cuestionario final de, mínimo, cinco preguntas, en el cual el estudiante reflexiona sobre su propio desempeño, habilidades y resultados en un contexto específico. | Q3: Informar oportunamente a través de la plataforma institucional y sesiones sincrónicas sobre el propósito, el proceso de realización, entrega de la actividad y criterios de evaluación. En las sesiones sincrónicas, atender las inquietudes y dar orientaciones al respecto, así como invitar a tomar asesorías ofrecidas por la Escuela de Ciencia Básicas, como estrategia de prevención y ayuda. Ayudar a tomar decisiones a través de preguntas orientadoras y actividades de refuerzo dentro del trabajo directo y autónomo. Retroalimentación por medio de rúbrica que indica el nivel de alcance del logro obtenido. Retroalimentación general del docente acorde a los resultados alcanzados por el grupo
A4: =_xlfn.XLOOKUP(B4,'Paso 3 Redacción RA '!I$3:I$15,'Paso 3 Redacción RA '!C$3:C$15,,0,1) -> Saber | B4: Identifica fenómenos contemporáneos y su relación con la profesión, para determinar sus impactos e influencia en la sociedad, de forma responsable y crítica. | C4: 1 | D4: Cultura, Política y Sociedad | E4: Reconoce las problemáticas, escenarios y mecanismos de participación ciudadana en el marco de sociedades de información y digitales para abordarlas desde iniciativas investigativas. Identifica los objetivos de desarrollo sostenible para la comprensión de problemáticas sociales, ambientales y culturales. Reflexiona sobre los impactos de los avances tecnológicos en el ámbito profesional y ciudadano para generar análisis alrededor de estos en contextos situados. | F4: TP | G4: X | J4: 3 | K4: =12*J4 -> 36 | L4: =36*J4 -> 108 | M4: =SUM(K4:L4) -> 144 | N4: 1. ODS, problemas locales: una mirada a Colombia, territorio en búsqueda de la consolidación de la Paz. 2. Ciudadanía y su lugar: relaciones, dinámicas, construcción, expresión y mecanismos de participación. 3. Ecosistemas digitales: relaciones, dinámicas, construcción, expresión e impactos en el contexto profesional. 4. Narrativas y contenidos digitales: análisis de contextos situados. | O4: Trabajo directo: Ecuentros sincrónicos Mensajería interna Anuncios Trabajo independiente: Lecturas fundamentales y complementarias Material de trabajo Participación en foros | P4: Evaluación diagnóstica escenario 1: Cuestionario inicial de mínimo cinco preguntas que recopila información sobre el conocimiento previo y las habilidades del estudiante. Actividad formativa escenario 2: Foro individual o grupal, creado para que el estudiante participe activamente en la construcción de su conocimiento y desarrollo de habilidades. Varía entre una actividad entregable y la participación en un foro. Actividad de entrega 1 escenario 4: Actividad individual o grupal, diseñada para evaluar de manera integral el nivel de conocimiento, comprensión y el desempeño de los indicadores de logro. Varía entre entregas independientes o secuenciales. Actividad formativa escenario 5: Foro individual o grupal, creado para que el estudiante participe activamente en la construcción de su conocimiento y desarrollo de habilidades. Varía entre una actividad entregable y la participación en un foro. Actividad evaluativa escenario 6: Cuestionario de, mínimo, cinco preguntas, que da cuenta del desarrollo total o parcial de los indicadores de logro y el desarrollo de los temas vistos hasta la unidad 3. Actividad de entrega 2 escenario 7: Actividad individual o grupal, diseñada para evaluar de manera integral el nivel de conocimiento, comprensión y el desempeño de los indicadores de logro. Varía entre entregas independientes o secuenciales. Autoevaluación escenario 8: Cuestionario final de mínimo cinco preguntas en el cual el estudiante reflexiona sobre su propio desempeño, habilidades y resultados en un contexto específico. | Q4: Las acciones de retroalimentación giran en torno a las siguientes. Formar: donde se crean las condiciones para que los estudiantes adquieran conocimientos, habilidades, actitudes, aptitudes y destrezas. Además, debe promover su desarrollo integral y debe acompañarlos en las situaciones académicas que enfrenten durante el desarrollo de un módulo o una asignatura. Informar: para que los estudiantes identifiquen los cambios que pueden afectarlos directa o indirectamente tanto en el aula de clase como en otros espacios. Prevenir: con el fin de anticiparse a las situaciones académicas que pueden representar dificultad para los estudiantes. Esto se logra a través de la interacción individual con los estudiantes y del completo conocimiento del contexto educativo en que el tutor se desenvuelve. Ayudar a decidir: donde se orienta a los estudiantes para que tomen la mejor decisión ante una situación concreta. El objetivo es que el estudiante fortalezca su autonomía y la toma de decisiones responsable.
A5: =_xlfn.XLOOKUP(B5,'Paso 3 Redacción RA '!I$3:I$15,'Paso 3 Redacción RA '!C$3:C$15,,0,1) -> Saber | B5: Analiza la normativa vigentes en la preparación y revisión de información contable, financiera y tributaria para identificar criterios técnicos y legales que permitan abordar situaciones contables y fiscales, según el contexto de aplicación. | C5: 1 | D5: Contabilidad General | E5: Elabora el registro de las operaciones, conforme a la normatividad vigente y la técnica contable a partir del objeto social de una organización, teniendo en cuenta el marco conceptual de las normas internacionales de información financiera para elaborar los estados financieros. | F5: TP | H5: X | J5: 3 | K5: =12*J5 -> 36 | L5: =36*J5 -> 108 | M5: =SUM(K5:L5) -> 144 | N5: 1. Fundamentación teórica y técnica contable 2. Elementos de los Estados Financieros y sus características 3. Transacciones comerciales y operaciones con cuentas de resultado 4. Estructura de los Estados Financieros | O5: Las estrategias pueden variar entre estas u otras: Trabajo directo Clase magistral activa/Análisis o Estudio de casos/Resolución de problemas/Talleres prácticos Trabajo independiente Lecturas relacionadas o de materiales complementarios/Resolución de problemas/Ejercicios aplicados/Desarrollo de proyectos/Talleres grupales o individuales/Análisis o Estudio de casos/Elaboración de informes o documentos técnicos | P5: Actividad de puntos evaluables (semana 2 – Cuestionario de 5 preguntas). Entrega previa 1 (semana 3 - Laboratorio, taller, ejercicios, resolución de casos o de problemas, desarrollo de procesos o ejecución de propuestas. Entrega de forma individual o grupal, según indicaciones del profesor). Parcial (semana 4 - Cuestionarios de entre 15 y 20 preguntas). Entrega previa 2 (semana 5 - Laboratorio, taller, ejercicios, resolución de casos o de problemas, desarrollo de procesos o ejecución de propuestas. Entrega de forma individual o grupal, según indicaciones dadas por el profesor). Entrega final (semana 7 - Laboratorio, taller, ejercicios, resolución de casos o de problemas, desarrollo de procesos o ejecución de propuestas. Entrega de forma individual o grupal, según indicaciones dadas por el profesor). Evaluación final (semana 8 - Cuestionario de entre 15 y 20 preguntas). | Q5: Las acciones de retroalimentación giran en torno a las siguientes. Formar: donde se crean las condiciones para que los estudiantes adquieran conocimientos, habilidades, actitudes, aptitudes y destrezas. Además, debe promover su desarrollo integral y debe acompañarlos en las situaciones académicas que enfrenten durante el desarrollo de un módulo o una asignatura. Informar: para que los estudiantes identifiquen los cambios que pueden afectarlos directa o indirectamente tanto en el aula de clase como en otros espacios. Prevenir: con el fin de anticiparse a las situaciones académicas que pueden representar dificultad para los estudiantes. Esto se logra a través de la interacción individual con los estudiantes y del completo conocimiento del contexto educativo en que el tutor se desenvuelve. Ayudar a decidir: donde se orienta a los estudiantes para que tomen la mejor decisión ante una situación concreta. El objetivo es que el estudiante fortalezca su autonomía y la toma de decisiones responsable.
A6: =_xlfn.XLOOKUP(B6,'Paso 3 Redacción RA '!I$3:I$15,'Paso 3 Redacción RA '!C$3:C$15,,0,1) -> Saberhacer | B6: Desarrolla procedimientos contables y tributarios para construir estados financieros conforme a la normativa aplicable, integrando el cumplimiento de obligaciones fiscales de personas naturales y jurídicas.
A7: =_xlfn.XLOOKUP(B7,'Paso 3 Redacción RA '!I$3:I$15,'Paso 3 Redacción RA '!C$3:C$15,,0,1) -> Saber | B7: Interpreta la información contable, financiera y tributaria en contextos de aseguramiento y control para establecer su pertinencia y confiabilidad en la resolución de situaciones contables organizacionales.
A8: =_xlfn.XLOOKUP(B8,'Paso 3 Redacción RA '!I$3:I$15,'Paso 3 Redacción RA '!C$3:C$15,,0,1) -> Saberhacer | B8: Utiliza información contable, financiera, tributaria y de auditoría para elaborar reportes, y proyecciones que faciliten la toma de decisiones de distintos tipos de usuarios, considerando sus necesidades y características.
A9: =_xlfn.XLOOKUP(B9,'Paso 3 Redacción RA '!I$3:I$15,'Paso 3 Redacción RA '!C$3:C$15,,0,1) -> Saberser | B9: Reconoce criterios éticos, legales, sociales y estratégicos del saber contable, tributario, financiero y de auditoría para aplicarlos con rigor técnico en la preparación de información de personas naturales y jurídicas, según el contexto o situación. | C9: 1 | D9: Epistemología Contable | E9: Identifica los desarrollos epistemológicos de la contabilidad y la incidencia de estos en el pensamiento contable y las prácticas profesionales, con el fin de analizar la relación que existe entre teoría contable, el desarrollo histórico del pensamiento contable, las perspectivas contemporáneas y su problematización en el contexto global. | F9: T | H9: X | J9: 3 | K9: =12*J9 -> 36 | L9: =36*J9 -> 108 | M9: =SUM(K9:L9) -> 144 | N9: 1. Fundamentos de epistemología y el saber contable. 2. Construcción de pensamiento y teoría contable. 3. Contexto actual de la teoría contable. 4. Contexto contemporáneo del campo contable. | O9: Las estrategias pueden variar entre estas u otras: Trabajo directo Clase magistral activa/Análisis o Estudio de casos/Resolución de problemas/Talleres prácticos Trabajo independiente Lecturas relacionadas o de materiales complementarios/Resolución de problemas/Ejercicios aplicados/Desarrollo de proyectos/Talleres grupales o individuales/Análisis o Estudio de casos/Elaboración de informes o documentos técnicos | P9: Quiz (semana 2 - Cuestionario de 5 preguntas). Entrega inicial (semana 3 – Ensayo, artículo, cuadro comparativo, revisión documental, entre otros). Foro analítico o argumentativo (semanas 5 y 6 – Participación en el espacio correspondiente del aula). Entrega final (semana 7 – Ensayo, artículo, cuadro comparativo, revisión documental, entre otros). Evaluación final (semana 8 – Cuestionario de entre 15 y 20 preguntas). | Q9: Las acciones de retroalimentación giran en torno a las siguientes. Formar: donde se crean las condiciones para que los estudiantes adquieran conocimientos, habilidades, actitudes, aptitudes y destrezas. Además, debe promover su desarrollo integral y debe acompañarlos en las situaciones académicas que enfrenten durante el desarrollo de un módulo o una asignatura. Informar: para que los estudiantes identifiquen los cambios que pueden afectarlos directa o indirectamente tanto en el aula de clase como en otros espacios. Prevenir: con el fin de anticiparse a las situaciones académicas que pueden representar dificultad para los estudiantes. Esto se logra a través de la interacción individual con los estudiantes y del completo conocimiento del contexto educativo en que el tutor se desenvuelve. Ayudar a decidir: donde se orienta a los estudiantes para que tomen la mejor decisión ante una situación concreta. El objetivo es que el estudiante fortalezca su autonomía y la toma de decisiones responsable.
A10: =_xlfn.XLOOKUP(B10,'Paso 3 Redacción RA '!I$3:I$15,'Paso 3 Redacción RA '!C$3:C$15,,0,1) -> Saber | B10: Interpreta la información contable, financiera y tributaria en contextos de aseguramiento y control para establecer su pertinencia y confiabilidad en la resolución de situaciones contables organizacionales.
A11: =_xlfn.XLOOKUP(B11,'Paso 3 Redacción RA '!I$3:I$15,'Paso 3 Redacción RA '!C$3:C$15,,0,1) -> Saberhacer | B11: Utiliza información contable, financiera, tributaria y de auditoría para elaborar reportes, y proyecciones que faciliten la toma de decisiones de distintos tipos de usuarios, considerando sus necesidades y características.
A12: =_xlfn.XLOOKUP(B12,'Paso 3 Redacción RA '!I$3:I$15,'Paso 3 Redacción RA '!C$3:C$15,,0,1) -> Saber | B12: Relaciona métodos cuantitativos y modelos de planeación financiera para explicar dinámicas contables y financieras según el contexto analizado, usando herramientas tecnológicas.
A13: =_xlfn.XLOOKUP(B13,'Paso 3 Redacción RA '!I$3:I$15,'Paso 3 Redacción RA '!C$3:C$15,,0,1) -> Saber | B13: Analiza la normativa vigentes en la preparación y revisión de información contable, financiera y tributaria para identificar criterios técnicos y legales que permitan abordar situaciones contables y fiscales, según el contexto de aplicación. | C13: 1 | D13: Derecho Comercial y Laboral | E13: Caracteriza los negocios jurídicos tanto en los actos de comercio como en las relaciones laborales en atención a la legislación vigente para crear modelos de empresas o contratos civiles, comerciales y laborales. | F13: TP | H13: X | J13: 3 | K13: =12*J13 -> 36 | L13: =36*J13 -> 108 | M13: =SUM(K13:L13) -> 144 | N13: 1. Acercamiento al derecho comercial 2. Costumbre mercantil 3. Historia, principios generales y fuentes del derecho laboral 4. Contrato de trabajo, jornada laboral, salario y prestaciones sociales | O13: Las estrategias pueden variar entre estas u otras: Trabajo directo Clase magistral activa/Análisis o Estudio de casos/Resolución de problemas/Talleres prácticos Trabajo independiente Lecturas relacionadas o de materiales complementarios/Resolución de problemas/Ejercicios aplicados/Desarrollo de proyectos/Talleres grupales o individuales/Análisis o Estudio de casos/Elaboración de informes o documentos técnicos | P13: Actividad de puntos evaluables (semana 2 – Cuestionario de 5 preguntas). Entrega previa 1 (semana 3 - Laboratorio, taller, ejercicios, resolución de casos o de problemas, desarrollo de procesos o ejecución de propuestas. Entrega de forma individual o grupal, según indicaciones del profesor). Parcial (semana 4 - Cuestionarios de entre 15 y 20 preguntas). Entrega previa 2 (semana 5 - Laboratorio, taller, ejercicios, resolución de casos o de problemas, desarrollo de procesos o ejecución de propuestas. Entrega de forma individual o grupal, según indicaciones dadas por el profesor). Entrega final (semana 7 - Laboratorio, taller, ejercicios, resolución de casos o de problemas, desarrollo de procesos o ejecución de propuestas. Entrega de forma individual o grupal, según indicaciones dadas por el profesor). Evaluación final (semana 8 - Cuestionario de entre 15 y 20 preguntas). | Q13: Las acciones de retroalimentación giran en torno a las siguientes. Formar: donde se crean las condiciones para que los estudiantes adquieran conocimientos, habilidades, actitudes, aptitudes y destrezas. Además, debe promover su desarrollo integral y debe acompañarlos en las situaciones académicas que enfrenten durante el desarrollo de un módulo o una asignatura. Informar: para que los estudiantes identifiquen los cambios que pueden afectarlos directa o indirectamente tanto en el aula de clase como en otros espacios. Prevenir: con el fin de anticiparse a las situaciones académicas que pueden representar dificultad para los estudiantes. Esto se logra a través de la interacción individual con los estudiantes y del completo conocimiento del contexto educativo en que el tutor se desenvuelve. Ayudar a decidir: donde se orienta a los estudiantes para que tomen la mejor decisión ante una situación concreta. El objetivo es que el estudiante fortalezca su autonomía y la toma de decisiones responsable.
A14: =_xlfn.XLOOKUP(B14,'Paso 3 Redacción RA '!I$3:I$15,'Paso 3 Redacción RA '!C$3:C$15,,0,1) -> Saberser | B14: Reconoce criterios éticos, legales, sociales y estratégicos del saber contable, tributario, financiero y de auditoría para aplicarlos con rigor técnico en la preparación de información de personas naturales y jurídicas, según el contexto o situación.
A15: =_xlfn.XLOOKUP(B15,'Paso 3 Redacción RA '!I$3:I$15,'Paso 3 Redacción RA '!C$3:C$15,,0,1) -> Saber | B15: Interpreta la información contable, financiera y tributaria en contextos de aseguramiento y control para establecer su pertinencia y confiabilidad en la resolución de situaciones contables organizacionales.
A16: =_xlfn.XLOOKUP(B16,'Paso 3 Redacción RA '!I$3:I$15,'Paso 3 Redacción RA '!C$3:C$15,,0,1) -> Saber | B16: Relaciona métodos cuantitativos y modelos de planeación financiera para explicar dinámicas contables y financieras según el contexto analizado, usando herramientas tecnológicas. | R16: =SUM(J3:J16) -> 15
A17: =_xlfn.XLOOKUP(B17,'Paso 3 Redacción RA '!I$3:I$15,'Paso 3 Redacción RA '!C$3:C$15,,0,1) -> Saber | B17: Identifica fenómenos contemporáneos y su relación con la profesión, para determinar sus impactos e influencia en la sociedad, de forma responsable y crítica. | C17: 2 | D17: Análisis y Visualización de Datos | E17: Identifica conceptos básicos relacionados con el análisis y visualización de datos con el propósito de comunicar información relevante de manera efectiva en diversos contextos. Utiliza herramientas para realizar análisis y transformación de datos que garanticen una visualización sencilla y eficiente. Utiliza asistentes virtuales para realizar tareas prácticas y resolver problemas en su campo de estudio. Evalúa la presencia de sesgos y cuestiones éticas en el análisis y tratamiento de dato para garantizar que su uso esté desprovisto de efectos negativos en el entorno. | F17: TP | G17: X | J17: 3 | K17: =12*J17 -> 36 | L17: =36*J17 -> 108 | M17: =SUM(K17:L17) -> 144 | N17: 1. Contextualización 2. Análisis de Datos y Visualización 3. Usos de la Inteligencia Artificial 4. Casos de Estudio | O17: Trabajo directo: Ecuentros sincrónicos Mensajería interna Anuncios Trabajo independiente: Lecturas fundamentales y complementarias Material de trabajo Participación en foros | P17: 1. Evaluación diagnóstica escenario 1: Cuestionario inicial de mínimo cinco preguntas que recopila información sobre el conocimiento previo y las habilidades del estudiante. 2. Actividad formativa escenario 2: Foro individual o grupal, creado para que el estudiante participe activamente en la construcción de su conocimiento y desarrollo de habilidades. Varía entre una actividad entregable y la participación en un foro. 3. Actividad de entrega 1 escenario 4: Actividad individual o grupal, diseñada para evaluar de manera integral el nivel de conocimiento, comprensión y el desempeño de los indicadores de logro. Varía entre entregas independientes o secuenciales. 4. Actividad formativa escenario 5: Foro individual o grupal, creado para que el estudiante participe activamente en la construcción de su conocimiento y desarrollo de habilidades. Varía entre una actividad entregable y la participación en un foro. 5. Actividad evaluativa escenario 6: Cuestionario de, mínimo, cinco preguntas, que da cuenta del desarrollo total o parcial de los indicadores de logro y el desarrollo de los temas vistos hasta la unidad 3. 6. Actividad de entrega 2 escenario 7: Actividad individual o grupal, diseñada para evaluar de manera integral el nivel de conocimiento, comprensión y el desempeño de los indicadores de logro. Varía entre entregas independientes o secuenciales. 7. Autoevaluación escenario 8: Cuestionario final de mínimo cinco preguntas en el cual el estudiante reflexiona sobre su propio desempeño, habilidades y resultados en un contexto específico. | Q17: Las acciones de retroalimentación giran en torno a las siguientes. Formar: donde se crean las condiciones para que los estudiantes adquieran conocimientos, habilidades, actitudes, aptitudes y destrezas. Además, debe promover su desarrollo integral y debe acompañarlos en las situaciones académicas que enfrenten durante el desarrollo de un módulo o una asignatura. Informar: para que los estudiantes identifiquen los cambios que pueden afectarlos directa o indirectamente tanto en el aula de clase como en otros espacios. Prevenir: con el fin de anticiparse a las situaciones académicas que pueden representar dificultad para los estudiantes. Esto se logra a través de la interacción individual con los estudiantes y del completo conocimiento del contexto educativo en que el tutor se desenvuelve. Ayudar a decidir: donde se orienta a los estudiantes para que tomen la mejor decisión ante una situación concreta. El objetivo es que el estudiante fortalezca su autonomía y la toma de decisiones responsable.
A18: =_xlfn.XLOOKUP(B18,'Paso 3 Redacción RA '!I$3:I$15,'Paso 3 Redacción RA '!C$3:C$15,,0,1) -> Saber | B18: Analiza la normativa vigentes en la preparación y revisión de información contable, financiera y tributaria para identificar criterios técnicos y legales que permitan abordar situaciones contables y fiscales, según el contexto de aplicación. | C18: 2 | D18: Contabilidad de Pasivos y Patrimonio | E18: Prepara reportes asociados a los pasivos y patrimonio que permitan el análisis de la información financiera y tributaria, conforme con la normatividad vigente, aplicando técnicas y procedimientos para la clasificación, medición, reconocimiento y revelación de las cuentas correspondientes, considerando las políticas contables asociadas a estas partidas. | F18: TP | H18: X | J18: 3 | K18: =12*J18 -> 36 | L18: =36*J18 -> 108 | M18: =SUM(K18:L18) -> 144 | N18: 1. Generalidades y pasivos financieros 2. Proveedores, cuentas por pagar y Tributos 3. Beneficios a empleados, pasivos estimados y otros pasivos 4. Reconocimiento, medición y valoración de bonos y patrimonio | O18: Trabajo directo: Ecuentros sincrónicos Mensajería interna Anuncios Trabajo independiente: Lecturas fundamentales y complementarias Material de trabajo Participación en foros | P18: Actividad de puntos evaluables (semana 2 – Cuestionario de 5 preguntas). Entrega previa 1 (semana 3 - Laboratorio, taller, ejercicios, resolución de casos o de problemas, desarrollo de procesos o ejecución de propuestas. Entrega de forma individual o grupal, según indicaciones del profesor). Parcial (semana 4 - Cuestionarios de entre 15 y 20 preguntas). Entrega previa 2 (semana 5 - Laboratorio, taller, ejercicios, resolución de casos o de problemas, desarrollo de procesos o ejecución de propuestas. Entrega de forma individual o grupal, según indicaciones dadas por el profesor). Entrega final (semana 7 - Laboratorio, taller, ejercicios, resolución de casos o de problemas, desarrollo de procesos o ejecución de propuestas. Entrega de forma individual o grupal, según indicaciones dadas por el profesor). Evaluación final (semana 8 - Cuestionario de entre 15 y 20 preguntas). | Q18: Las acciones de retroalimentación giran en torno a las siguientes. Formar: donde se crean las condiciones para que los estudiantes adquieran conocimientos, habilidades, actitudes, aptitudes y destrezas. Además, debe promover su desarrollo integral y debe acompañarlos en las situaciones académicas que enfrenten durante el desarrollo de un módulo o una asignatura. Informar: para que los estudiantes identifiquen los cambios que pueden afectarlos directa o indirectamente tanto en el aula de clase como en otros espacios. Prevenir: con el fin de anticiparse a las situaciones académicas que pueden representar dificultad para los estudiantes. Esto se logra a través de la interacción individual con los estudiantes y del completo conocimiento del contexto educativo en que el tutor se desenvuelve. Ayudar a decidir: donde se orienta a los estudiantes para que tomen la mejor decisión ante una situación concreta. El objetivo es que el estudiante fortalezca su autonomía y la toma de decisiones responsable.
A19: =_xlfn.XLOOKUP(B19,'Paso 3 Redacción RA '!I$3:I$15,'Paso 3 Redacción RA '!C$3:C$15,,0,1) -> Saberhacer | B19: Desarrolla procedimientos contables y tributarios para construir estados financieros conforme a la normativa aplicable, integrando el cumplimiento de obligaciones fiscales de personas naturales y jurídicas.
A20: =_xlfn.XLOOKUP(B20,'Paso 3 Redacción RA '!I$3:I$15,'Paso 3 Redacción RA '!C$3:C$15,,0,1) -> Saber | B20: Interpreta la información contable, financiera y tributaria en contextos de aseguramiento y control para establecer su pertinencia y confiabilidad en la resolución de situaciones contables organizacionales.
A21: =_xlfn.XLOOKUP(B21,'Paso 3 Redacción RA '!I$3:I$15,'Paso 3 Redacción RA '!C$3:C$15,,0,1) -> Saber | B21: Relaciona métodos cuantitativos y modelos de planeación financiera para explicar dinámicas contables y financieras según el contexto analizado, usando herramientas tecnológicas.
A22: =_xlfn.XLOOKUP(B22,'Paso 3 Redacción RA '!I$3:I$15,'Paso 3 Redacción RA '!C$3:C$15,,0,1) -> Saberhacer | B22: Utiliza métodos cuantitativos y herramientas tecnológicas para elaborar reportes sobre la situación contable y financiera de personas naturales, personas jurídicas y organizaciones, a partir de datos y contextos definidos.
A23: =_xlfn.XLOOKUP(B23,'Paso 3 Redacción RA '!I$3:I$15,'Paso 3 Redacción RA '!C$3:C$15,,0,1) -> Saber | B23: Interpreta la información contable, financiera y tributaria en contextos de aseguramiento y control para establecer su pertinencia y confiabilidad en la resolución de situaciones contables organizacionales. | C23: 2 | D23: Razonamiento Variacional | E23: Aplica el pensamiento variacional y acumulativo para interpretar, modelar y resolver problemas de cambio y acumulación, relacionados con su contexto profesional y personal, mediante el uso reflexivo de las propiedades y aplicaciones de las derivadas e integrales. | F23: TP | H23: X | J23: 3 | K23: =12*J23 -> 36 | L23: =36*J23 -> 108 | M23: =SUM(K23:L23) -> 144 | N23: 1. Fundamentos del Pensamiento Variacional 2. Análisis del Cambio y Dinámica 3. Acumulación y Modelado Integral 4. Aplicaciones Avanzadas y Modelización | O23: Trabajo directo: Ecuentros sincrónicos Mensajería interna Anuncios Trabajo independiente: Lecturas fundamentales y complementarias Material de trabajo Participación en foros | P23: Actividad de puntos evaluables (semana 2 – Cuestionario de 5 preguntas). Entrega previa 1 (semana 3 - Laboratorio, taller, ejercicios, resolución de casos o de problemas, desarrollo de procesos o ejecución de propuestas. Entrega de forma individual o grupal, según indicaciones del profesor). Parcial (semana 4 - Cuestionarios de entre 15 y 20 preguntas). Entrega previa 2 (semana 5 - Laboratorio, taller, ejercicios, resolución de casos o de problemas, desarrollo de procesos o ejecución de propuestas. Entrega de forma individual o grupal, según indicaciones dadas por el profesor). Entrega final (semana 7 - Laboratorio, taller, ejercicios, resolución de casos o de problemas, desarrollo de procesos o ejecución de propuestas. Entrega de forma individual o grupal, según indicaciones dadas por el profesor). Evaluación final (semana 8 - Cuestionario de entre 15 y 20 preguntas). | Q23: Las acciones de retroalimentación giran en torno a las siguientes. Formar: donde se crean las condiciones para que los estudiantes adquieran conocimientos, habilidades, actitudes, aptitudes y destrezas. Además, debe promover su desarrollo integral y debe acompañarlos en las situaciones académicas que enfrenten durante el desarrollo de un módulo o una asignatura. Informar: para que los estudiantes identifiquen los cambios que pueden afectarlos directa o indirectamente tanto en el aula de clase como en otros espacios. Prevenir: con el fin de anticiparse a las situaciones académicas que pueden representar dificultad para los estudiantes. Esto se logra a través de la interacción individual con los estudiantes y del completo conocimiento del contexto educativo en que el tutor se desenvuelve. Ayudar a decidir: donde se orienta a los estudiantes para que tomen la mejor decisión ante una situación concreta. El objetivo es que el estudiante fortalezca su autonomía y la toma de decisiones responsable.
A24: =_xlfn.XLOOKUP(B24,'Paso 3 Redacción RA '!I$3:I$15,'Paso 3 Redacción RA '!C$3:C$15,,0,1) -> Saber | B24: Relaciona métodos cuantitativos y modelos de planeación financiera para explicar dinámicas contables y financieras según el contexto analizado, usando herramientas tecnológicas.
A25: =_xlfn.XLOOKUP(B25,'Paso 3 Redacción RA '!I$3:I$15,'Paso 3 Redacción RA '!C$3:C$15,,0,1) -> Saberhacer | B25: Utiliza métodos cuantitativos y herramientas tecnológicas para elaborar reportes sobre la situación contable y financiera de personas naturales, personas jurídicas y organizaciones, a partir de datos y contextos definidos.
A26: =_xlfn.XLOOKUP(B26,'Paso 3 Redacción RA '!I$3:I$15,'Paso 3 Redacción RA '!C$3:C$15,,0,1) -> Saber | B26: Analiza la normativa vigentes en la preparación y revisión de información contable, financiera y tributaria para identificar criterios técnicos y legales que permitan abordar situaciones contables y fiscales, según el contexto de aplicación. | C26: 2 | D26: Contabilidad de Activos | E26: Aplica las técnicas, procedimientos y políticas contables para la clasificación, medición, reconocimiento y revelación de las cuentas del grupo de activos, garantizando un registro adecuado de las operaciones contables y de la preparación de información financiera conforme a la normatividad vigente. | F26: TP | H26: X | J26: 3 | K26: =12*J26 -> 36 | L26: =36*J26 -> 108 | M26: =SUM(K26:L26) -> 144 | N26: 1. Generalidades del reconocimiento, medición y presentación de los Activos 2. Efectivo y equivalentes al efectivo; Inversiones (instrumentos financieros); Deudores comerciales y cuentas por cobrar 3. Inventarios; Propiedad planta y Equipo 4. Intangibles; Propiedades de inversión | O26: Trabajo directo: Ecuentros sincrónicos Mensajería interna Anuncios Trabajo independiente: Lecturas fundamentales y complementarias Material de trabajo Participación en foros | P26: Actividad de puntos evaluables (semana 2 – Cuestionario de 5 preguntas). Entrega previa 1 (semana 3 - Laboratorio, taller, ejercicios, resolución de casos o de problemas, desarrollo de procesos o ejecución de propuestas. Entrega de forma individual o grupal, según indicaciones del profesor). Parcial (semana 4 - Cuestionarios de entre 15 y 20 preguntas). Entrega previa 2 (semana 5 - Laboratorio, taller, ejercicios, resolución de casos o de problemas, desarrollo de procesos o ejecución de propuestas. Entrega de forma individual o grupal, según indicaciones dadas por el profesor). Entrega final (semana 7 - Laboratorio, taller, ejercicios, resolución de casos o de problemas, desarrollo de procesos o ejecución de propuestas. Entrega de forma individual o grupal, según indicaciones dadas por el profesor). Evaluación final (semana 8 - Cuestionario de entre 15 y 20 preguntas). | Q26: Las acciones de retroalimentación giran en torno a las siguientes. Formar: donde se crean las condiciones para que los estudiantes adquieran conocimientos, habilidades, actitudes, aptitudes y destrezas. Además, debe promover su desarrollo integral y debe acompañarlos en las situaciones académicas que enfrenten durante el desarrollo de un módulo o una asignatura. Informar: para que los estudiantes identifiquen los cambios que pueden afectarlos directa o indirectamente tanto en el aula de clase como en otros espacios. Prevenir: con el fin de anticiparse a las situaciones académicas que pueden representar dificultad para los estudiantes. Esto se logra a través de la interacción individual con los estudiantes y del completo conocimiento del contexto educativo en que el tutor se desenvuelve. Ayudar a decidir: donde se orienta a los estudiantes para que tomen la mejor decisión ante una situación concreta. El objetivo es que el estudiante fortalezca su autonomía y la toma de decisiones responsable.
A27: =_xlfn.XLOOKUP(B27,'Paso 3 Redacción RA '!I$3:I$15,'Paso 3 Redacción RA '!C$3:C$15,,0,1) -> Saberhacer | B27: Desarrolla procedimientos contables y tributarios para construir estados financieros conforme a la normativa aplicable, integrando el cumplimiento de obligaciones fiscales de personas naturales y jurídicas.
A28: =_xlfn.XLOOKUP(B28,'Paso 3 Redacción RA '!I$3:I$15,'Paso 3 Redacción RA '!C$3:C$15,,0,1) -> Saber | B28: Analiza la normativa vigentes en la preparación y revisión de información contable, financiera y tributaria para identificar criterios técnicos y legales que permitan abordar situaciones contables y fiscales, según el contexto de aplicación.
A29: =_xlfn.XLOOKUP(B29,'Paso 3 Redacción RA '!I$3:I$15,'Paso 3 Redacción RA '!C$3:C$15,,0,1) -> Saberhacer | B29: Utiliza información contable, financiera, tributaria y de auditoría para elaborar reportes, y proyecciones que faciliten la toma de decisiones de distintos tipos de usuarios, considerando sus necesidades y características.
A30: =_xlfn.XLOOKUP(B30,'Paso 3 Redacción RA '!I$3:I$15,'Paso 3 Redacción RA '!C$3:C$15,,0,1) -> Saberser | B30: Reconoce criterios éticos, legales, sociales y estratégicos del saber contable, tributario, financiero y de auditoría para aplicarlos con rigor técnico en la preparación de información de personas naturales y jurídicas, según el contexto o situación. | C30: 2 | D30: Gestión del Talento Humano | E30: Identifica las características y evolución en el tiempo de la gestión del talento humano, para, a partir de casos concretos, proponer soluciones en un contexto organizacional. | F30: TP | H30: X | J30: 3 | K30: =12*J30 -> 36 | L30: =36*J30 -> 108 | M30: =SUM(K30:L30) -> 144 | N30: 1. Importancia del Talento humano en las organizaciones 2. Análisis, descripción y diseño de cargos dentro de la incorporación de las personas en las organizaciones 3. Desarrollo, formación y retribución de las personas en las organizaciones 4. Impacto en las organizaciones, mediante la generación de valor, a través de la evaluación desempeño y el proceso de Seguridad y Salud en el Trabajo | O30: Trabajo directo: Ecuentros sincrónicos Mensajería interna Anuncios Trabajo independiente: Lecturas fundamentales y complementarias Material de trabajo Participación en foros | P30: Actividad de puntos evaluables (semana 2 – Cuestionario de 5 preguntas). Entrega previa 1 (semana 3 - Laboratorio, taller, ejercicios, resolución de casos o de problemas, desarrollo de procesos o ejecución de propuestas. Entrega de forma individual o grupal, según indicaciones del profesor). Parcial (semana 4 - Cuestionarios de entre 15 y 20 preguntas). Entrega previa 2 (semana 5 - Laboratorio, taller, ejercicios, resolución de casos o de problemas, desarrollo de procesos o ejecución de propuestas. Entrega de forma individual o grupal, según indicaciones dadas por el profesor). Entrega final (semana 7 - Laboratorio, taller, ejercicios, resolución de casos o de problemas, desarrollo de procesos o ejecución de propuestas. Entrega de forma individual o grupal, según indicaciones dadas por el profesor). Evaluación final (semana 8 - Cuestionario de entre 15 y 20 preguntas). | Q30: Las acciones de retroalimentación giran en torno a las siguientes. Formar: donde se crean las condiciones para que los estudiantes adquieran conocimientos, habilidades, actitudes, aptitudes y destrezas. Además, debe promover su desarrollo integral y debe acompañarlos en las situaciones académicas que enfrenten durante el desarrollo de un módulo o una asignatura. Informar: para que los estudiantes identifiquen los cambios que pueden afectarlos directa o indirectamente tanto en el aula de clase como en otros espacios. Prevenir: con el fin de anticiparse a las situaciones académicas que pueden representar dificultad para los estudiantes. Esto se logra a través de la interacción individual con los estudiantes y del completo conocimiento del contexto educativo en que el tutor se desenvuelve. Ayudar a decidir: donde se orienta a los estudiantes para que tomen la mejor decisión ante una situación concreta. El objetivo es que el estudiante fortalezca su autonomía y la toma de decisiones responsable.
A31: =_xlfn.XLOOKUP(B31,'Paso 3 Redacción RA '!I$3:I$15,'Paso 3 Redacción RA '!C$3:C$15,,0,1) -> Saberhacer | B31: Utiliza información contable, financiera, tributaria y de auditoría para elaborar reportes, y proyecciones que faciliten la toma de decisiones de distintos tipos de usuarios, considerando sus necesidades y características.
A32: =_xlfn.XLOOKUP(B32,'Paso 3 Redacción RA '!I$3:I$15,'Paso 3 Redacción RA '!C$3:C$15,,0,1) -> Saber | B32: Relaciona métodos cuantitativos y modelos de planeación financiera para explicar dinámicas contables y financieras según el contexto analizado, usando herramientas tecnológicas.
A33: =_xlfn.XLOOKUP(B33,'Paso 3 Redacción RA '!I$3:I$15,'Paso 3 Redacción RA '!C$3:C$15,,0,1) -> Saberser | B33: Reconoce criterios éticos, legales, sociales y estratégicos del saber contable, tributario, financiero y de auditoría para aplicarlos con rigor técnico en la preparación de información de personas naturales y jurídicas, según el contexto o situación. | C33: 2 | D33: Proceso Administrativo | E33: Reconoce las etapas del proceso administrativo (planeación, organización, dirección y control) para aplicarlas en situaciones organizacionales. | F33: TP | H33: X | J33: 3 | K33: =12*J33 -> 36 | L33: =36*J33 -> 108 | M33: =SUM(K33:L33) -> 144 | N33: 1. Planeación 2. Organización 3. Dirección: Integración de Personal - Motivación – liderazgo y comunicación 4. Control | O33: Trabajo directo: Ecuentros sincrónicos Mensajería interna Anuncios Trabajo independiente: Lecturas fundamentales y complementarias Material de trabajo Participación en foros | P33: Actividad de puntos evaluables (semana 2 – Cuestionario de 5 preguntas). Entrega previa 1 (semana 3 - Laboratorio, taller, ejercicios, resolución de casos o de problemas, desarrollo de procesos o ejecución de propuestas. Entrega de forma individual o grupal, según indicaciones del profesor). Parcial (semana 4 - Cuestionarios de entre 15 y 20 preguntas). Entrega previa 2 (semana 5 - Laboratorio, taller, ejercicios, resolución de casos o de problemas, desarrollo de procesos o ejecución de propuestas. Entrega de forma individual o grupal, según indicaciones dadas por el profesor). Entrega final (semana 7 - Laboratorio, taller, ejercicios, resolución de casos o de problemas, desarrollo de procesos o ejecución de propuestas. Entrega de forma individual o grupal, según indicaciones dadas por el profesor). Evaluación final (semana 8 - Cuestionario de entre 15 y 20 preguntas). | Q33: Las acciones de retroalimentación giran en torno a las siguientes. Formar: donde se crean las condiciones para que los estudiantes adquieran conocimientos, habilidades, actitudes, aptitudes y destrezas. Además, debe promover su desarrollo integral y debe acompañarlos en las situaciones académicas que enfrenten durante el desarrollo de un módulo o una asignatura. Informar: para que los estudiantes identifiquen los cambios que pueden afectarlos directa o indirectamente tanto en el aula de clase como en otros espacios. Prevenir: con el fin de anticiparse a las situaciones académicas que pueden representar dificultad para los estudiantes. Esto se logra a través de la interacción individual con los estudiantes y del completo conocimiento del contexto educativo en que el tutor se desenvuelve. Ayudar a decidir: donde se orienta a los estudiantes para que tomen la mejor decisión ante una situación concreta. El objetivo es que el estudiante fortalezca su autonomía y la toma de decisiones responsable.
A34: =_xlfn.XLOOKUP(B34,'Paso 3 Redacción RA '!I$3:I$15,'Paso 3 Redacción RA '!C$3:C$15,,0,1) -> Saberhacer | B34: Utiliza información contable, financiera, tributaria y de auditoría para elaborar reportes, y proyecciones que faciliten la toma de decisiones de distintos tipos de usuarios, considerando sus necesidades y características.
A35: =_xlfn.XLOOKUP(B35,'Paso 3 Redacción RA '!I$3:I$15,'Paso 3 Redacción RA '!C$3:C$15,,0,1) -> Saber | B35: Relaciona métodos cuantitativos y modelos de planeación financiera para explicar dinámicas contables y financieras según el contexto analizado, usando herramientas tecnológicas.
A36: =_xlfn.XLOOKUP(B36,'Paso 3 Redacción RA '!I$3:I$15,'Paso 3 Redacción RA '!C$3:C$15,,0,1) -> Saberhacer | B36: Utiliza métodos cuantitativos y herramientas tecnológicas para elaborar reportes sobre la situación contable y financiera de personas naturales, personas jurídicas y organizaciones, a partir de datos y contextos definidos. | R36: =SUM(J17:J36) -> 18
A37: =_xlfn.XLOOKUP(B37,'Paso 3 Redacción RA '!I$3:I$15,'Paso 3 Redacción RA '!C$3:C$15,,0,1) -> Saber | B37: Identifica fenómenos contemporáneos y su relación con la profesión, para determinar sus impactos e influencia en la sociedad, de forma responsable y crítica. | C37: 3 | D37: Oportunidades para Emprender | E37: Propone soluciones a los problemas, frustraciones y expectativas de un grupo de personas en su comunidad para idear productos o servicios con valor agregado dentro de su campo de acción profesional. Diseña una idea de negocio que represente una oportunidad de mercado teniendo en cuenta sus habilidades para emprender y el análisis del entorno. | F37: TP | G37: X | J37: 3 | K37: =12*J37 -> 36 | L37: =36*J37 -> 108 | M37: =SUM(K37:L37) -> 144 | N37: 1. Empatía y Comprensión del Usuario 2. Co-creación con los Usuarios 3. Enfoque en la Experiencia del Usuario 4. Diseño del modelo de negocio | O37: Trabajo directo: Ecuentros sincrónicos Mensajería interna Anuncios Trabajo independiente: Lecturas fundamentales y complementarias Material de trabajo Participación en foros | P37: Evaluación diagnóstica: Cuestionario inicial de mínimo cinco preguntas que recopila información sobre el conocimiento previo y las habilidades del estudiante. Actividad formativa: Foro individual o grupal, creado para que el estudiante participe activamente en la construcción de su conocimiento y desarrollo de habilidades. Varía entre una actividad entregable y la participación en un foro. Actividad de entrega 1 y 2: Actividad individual o grupal, diseñada para evaluar de manera integral el nivel de conocimiento, comprensión y el desempeño de los indicadores de logro. Varía entre entregas independientes o secuenciales. Actividad evaluativa: Cuestionario de, mínimo, cinco preguntas, que da cuenta del desarrollo total o parcial de los indicadores de logro y el desarrollo de los temas vistos hasta la unidad 3. Autoevaluación: Cuestionario final de mínimo cinco preguntas en el cual el estudiante reflexiona sobre su propio desempeño, habilidades y resultados en un contexto específico. | Q37: Las acciones de retroalimentación giran en torno a las siguientes. Formar: donde se crean las condiciones para que los estudiantes adquieran conocimientos, habilidades, actitudes, aptitudes y destrezas. Además, debe promover su desarrollo integral y debe acompañarlos en las situaciones académicas que enfrenten durante el desarrollo de un módulo o una asignatura. Informar: para que los estudiantes identifiquen los cambios que pueden afectarlos directa o indirectamente tanto en el aula de clase como en otros espacios. Prevenir: con el fin de anticiparse a las situaciones académicas que pueden representar dificultad para los estudiantes. Esto se logra a través de la interacción individual con los estudiantes y del completo conocimiento del contexto educativo en que el tutor se desenvuelve. Ayudar a decidir: donde se orienta a los estudiantes para que tomen la mejor decisión ante una situación concreta. El objetivo es que el estudiante fortalezca su autonomía y la toma de decisiones responsable.
A38: =_xlfn.XLOOKUP(B38,'Paso 3 Redacción RA '!I$3:I$15,'Paso 3 Redacción RA '!C$3:C$15,,0,1) -> Saber | B38: Identifica fenómenos contemporáneos y su relación con la profesión, para determinar sus impactos e influencia en la sociedad, de forma responsable y crítica. | C38: 3 | D38: Pensamiento Crítico y Ciudadanías Activas | E38: Identifica los Derechos y Deberes consignados en la Constitución 1991 en relación con la ciudadanía de manera local y global para la comprensión de inmersiones sociales éticas. Reflexiona sobre los impactos de la investigación- acción sin daño en los espacios académicos y los territorios para el abordaje desde proyectos de investigación formativa. Elabora el diseño de planes detallados desde abordajes investigativos e inmersiones creativas para divulgar hallazgos en el ámbito académico. | F38: TP | G38: X | J38: 3 | K38: =12*J38 -> 36 | L38: =36*J38 -> 108 | M38: =SUM(K38:L38) -> 144 | N38: 1. Pacto social colombiano y marco de referencias de DDHH internacionales 2. Planes detallados e inmersiones sociales desde procesos participativos, acciones sociales e iniciativas ciudadanas como respuesta a problemas glocales 3. Perspectivas para la participación ciudadana en los territorios 4. Los avances tecnológicos y su impacto en lo social, cultural y ambiental en el marco de las sociedades de información | O38: Trabajo directo: Ecuentros sincrónicos Mensajería interna Anuncios Trabajo independiente: Lecturas fundamentales y complementarias Material de trabajo Participación en foros | P38: 1. Actividad de puntos evaluables escenario 1 (diagnóstica) - Cuestionario de 5 preguntas. 2. Entrega escenario 2 (formativa) 3. Entrega escenario 4 (formativa) 4. Entrega escenario 5 (formativa) 5. Quiz escenario 6 (sumativa.) | Q38: Las acciones de retroalimentación giran en torno a las siguientes. Formar: donde se crean las condiciones para que los estudiantes adquieran conocimientos, habilidades, actitudes, aptitudes y destrezas. Además, debe promover su desarrollo integral y debe acompañarlos en las situaciones académicas que enfrenten durante el desarrollo de un módulo o una asignatura. Informar: para que los estudiantes identifiquen los cambios que pueden afectarlos directa o indirectamente tanto en el aula de clase como en otros espacios. Prevenir: con el fin de anticiparse a las situaciones académicas que pueden representar dificultad para los estudiantes. Esto se logra a través de la interacción individual con los estudiantes y del completo conocimiento del contexto educativo en que el tutor se desenvuelve. Ayudar a decidir: donde se orienta a los estudiantes para que tomen la mejor decisión ante una situación concreta. El objetivo es que el estudiante fortalezca su autonomía y la toma de decisiones responsable.
A39: =_xlfn.XLOOKUP(B39,'Paso 3 Redacción RA '!I$3:I$15,'Paso 3 Redacción RA '!C$3:C$15,,0,1) -> Saber | B39: Interpreta la información contable, financiera y tributaria en contextos de aseguramiento y control para establecer su pertinencia y confiabilidad en la resolución de situaciones contables organizacionales. | C39: 3 | D39: Análisis Descriptivo de Datos | E39: Aplica herramientas tecnológicas y modelos probabilístico, para representar procesos, aleatorios y determinar valores de probabilidad en diferentes escenarios. Aplica conceptos de probabilidad elemental y distribuciones como la normal y la binomial, para sustentar decisiones en diversos contextos. | F39: TP | H39: X | J39: 3 | K39: =12*J39 -> 36 | L39: =36*J39 -> 108 | M39: =SUM(K39:L39) -> 144 | N39: 1. Estadística descriptiva 2. Teoría de la probabilidad 3. Variables aleatorias y distribuciones de probabilidad 4. Distribuciones de probabilidad discretas y continuas | O39: Trabajo directo: Ecuentros sincrónicos Mensajería interna Anuncios Trabajo independiente: Lecturas fundamentales y complementarias Material de trabajo Participación en foros | P39: Actividad de puntos evaluables (semana 2 – Cuestionario de 5 preguntas). Entrega previa 1 (semana 3 - Laboratorio, taller, ejercicios, resolución de casos o de problemas, desarrollo de procesos o ejecución de propuestas. Entrega de forma individual o grupal, según indicaciones del profesor). Parcial (semana 4 - Cuestionarios de entre 15 y 20 preguntas). Entrega previa 2 (semana 5 - Laboratorio, taller, ejercicios, resolución de casos o de problemas, desarrollo de procesos o ejecución de propuestas. Entrega de forma individual o grupal, según indicaciones dadas por el profesor). Entrega final (semana 7 - Laboratorio, taller, ejercicios, resolución de casos o de problemas, desarrollo de procesos o ejecución de propuestas. Entrega de forma individual o grupal, según indicaciones dadas por el profesor). Evaluación final (semana 8 - Cuestionario de entre 15 y 20 preguntas). | Q39: Las acciones de retroalimentación giran en torno a las siguientes. Formar: donde se crean las condiciones para que los estudiantes adquieran conocimientos, habilidades, actitudes, aptitudes y destrezas. Además, debe promover su desarrollo integral y debe acompañarlos en las situaciones académicas que enfrenten durante el desarrollo de un módulo o una asignatura. Informar: para que los estudiantes identifiquen los cambios que pueden afectarlos directa o indirectamente tanto en el aula de clase como en otros espacios. Prevenir: con el fin de anticiparse a las situaciones académicas que pueden representar dificultad para los estudiantes. Esto se logra a través de la interacción individual con los estudiantes y del completo conocimiento del contexto educativo en que el tutor se desenvuelve. Ayudar a decidir: donde se orienta a los estudiantes para que tomen la mejor decisión ante una situación concreta. El objetivo es que el estudiante fortalezca su autonomía y la toma de decisiones responsable.
A40: =_xlfn.XLOOKUP(B40,'Paso 3 Redacción RA '!I$3:I$15,'Paso 3 Redacción RA '!C$3:C$15,,0,1) -> Saber | B40: Relaciona métodos cuantitativos y modelos de planeación financiera para explicar dinámicas contables y financieras según el contexto analizado, usando herramientas tecnológicas.
A41: =_xlfn.XLOOKUP(B41,'Paso 3 Redacción RA '!I$3:I$15,'Paso 3 Redacción RA '!C$3:C$15,,0,1) -> Saberhacer | B41: Utiliza información contable, financiera, tributaria y de auditoría para elaborar reportes, y proyecciones que faciliten la toma de decisiones de distintos tipos de usuarios, considerando sus necesidades y características.
A42: =_xlfn.XLOOKUP(B42,'Paso 3 Redacción RA '!I$3:I$15,'Paso 3 Redacción RA '!C$3:C$15,,0,1) -> Saberhacer | B42: Desarrolla procedimientos contables y tributarios para construir estados financieros conforme a la normativa aplicable, integrando el cumplimiento de obligaciones fiscales de personas naturales y jurídicas. | C42: 3 | D42: Estados Financieros | E42: Presenta los estados financieros de una empresa según el sector económico al que pertenece, para proveer información necesaria a los usuarios de la información financiera que permita orientar la toma decisiones respecto a operaciones, inversión y financiación. | F42: TP | H42: X | J42: 3 | K42: =12*J42 -> 36 | L42: =36*J42 -> 108 | M42: =SUM(K42:L42) -> 144 | N42: 1. Fundamentos y Estado de situación financiera 2. Estado de resultados, estados de resultados integral y estado de cambios en el patrimonio. 3. Estado de flujo de efectivo 4. Interpretación gerencial y toma de decisiones | O42: Trabajo directo: Ecuentros sincrónicos Mensajería interna Anuncios Trabajo independiente: Lecturas fundamentales y complementarias Material de trabajo Participación en foros | P42: Actividad de puntos evaluables (semana 2 – Cuestionario de 5 preguntas). Entrega previa 1 (semana 3 - Laboratorio, taller, ejercicios, resolución de casos o de problemas, desarrollo de procesos o ejecución de propuestas. Entrega de forma individual o grupal, según indicaciones del profesor). Parcial (semana 4 - Cuestionarios de entre 15 y 20 preguntas). Entrega previa 2 (semana 5 - Laboratorio, taller, ejercicios, resolución de casos o de problemas, desarrollo de procesos o ejecución de propuestas. Entrega de forma individual o grupal, según indicaciones dadas por el profesor). Entrega final (semana 7 - Laboratorio, taller, ejercicios, resolución de casos o de problemas, desarrollo de procesos o ejecución de propuestas. Entrega de forma individual o grupal, según indicaciones dadas por el profesor). Evaluación final (semana 8 - Cuestionario de entre 15 y 20 preguntas). | Q42: Las acciones de retroalimentación giran en torno a las siguientes. Formar: donde se crean las condiciones para que los estudiantes adquieran conocimientos, habilidades, actitudes, aptitudes y destrezas. Además, debe promover su desarrollo integral y debe acompañarlos en las situaciones académicas que enfrenten durante el desarrollo de un módulo o una asignatura. Informar: para que los estudiantes identifiquen los cambios que pueden afectarlos directa o indirectamente tanto en el aula de clase como en otros espacios. Prevenir: con el fin de anticiparse a las situaciones académicas que pueden representar dificultad para los estudiantes. Esto se logra a través de la interacción individual con los estudiantes y del completo conocimiento del contexto educativo en que el tutor se desenvuelve. Ayudar a decidir: donde se orienta a los estudiantes para que tomen la mejor decisión ante una situación concreta. El objetivo es que el estudiante fortalezca su autonomía y la toma de decisiones responsable.
A43: =_xlfn.XLOOKUP(B43,'Paso 3 Redacción RA '!I$3:I$15,'Paso 3 Redacción RA '!C$3:C$15,,0,1) -> Saber | B43: Interpreta la información contable, financiera y tributaria en contextos de aseguramiento y control para establecer su pertinencia y confiabilidad en la resolución de situaciones contables organizacionales.
A44: =_xlfn.XLOOKUP(B44,'Paso 3 Redacción RA '!I$3:I$15,'Paso 3 Redacción RA '!C$3:C$15,,0,1) -> Saberhacer | B44: Utiliza información contable, financiera, tributaria y de auditoría para elaborar reportes, y proyecciones que faciliten la toma de decisiones de distintos tipos de usuarios, considerando sus necesidades y características.
A45: =_xlfn.XLOOKUP(B45,'Paso 3 Redacción RA '!I$3:I$15,'Paso 3 Redacción RA '!C$3:C$15,,0,1) -> Saber | B45: Relaciona métodos cuantitativos y modelos de planeación financiera para explicar dinámicas contables y financieras según el contexto analizado, usando herramientas tecnológicas.
A46: =_xlfn.XLOOKUP(B46,'Paso 3 Redacción RA '!I$3:I$15,'Paso 3 Redacción RA '!C$3:C$15,,0,1) -> Saber | B46: Interpreta la información contable, financiera y tributaria en contextos de aseguramiento y control para establecer su pertinencia y confiabilidad en la resolución de situaciones contables organizacionales. | C46: 3 | D46: Microeconomía | E46: Calcula el equilibrio de mercado a partir de los cambios generados en la oferta y la demanda y su implicación en los agentes económicos individuales familias y empresas para soportar la toma de decisiones. | F46: TP | H46: X | J46: 3 | K46: =12*J46 -> 36 | L46: =36*J46 -> 108 | M46: =SUM(K46:L46) -> 144 | N46: 1. Conceptos básicos de la ciencia económica. Frontera de posibilidades de producción y circuito económico 2. Análisis microeconómico, funciones, demanda y oferta 3. Estudio de la conducta del consumidor y del productor 4. Análisis de los costos de producción y de los mercados de competencia perfecta e imperfecta | O46: Trabajo directo: Ecuentros sincrónicos Mensajería interna Anuncios Trabajo independiente: Lecturas fundamentales y complementarias Material de trabajo Participación en foros | P46: Actividad de puntos evaluables (semana 2 – Cuestionario de 5 preguntas). Entrega previa 1 (semana 3 - Laboratorio, taller, ejercicios, resolución de casos o de problemas, desarrollo de procesos o ejecución de propuestas. Entrega de forma individual o grupal, según indicaciones del profesor). Parcial (semana 4 - Cuestionarios de entre 15 y 20 preguntas). Entrega previa 2 (semana 5 - Laboratorio, taller, ejercicios, resolución de casos o de problemas, desarrollo de procesos o ejecución de propuestas. Entrega de forma individual o grupal, según indicaciones dadas por el profesor). Entrega final (semana 7 - Laboratorio, taller, ejercicios, resolución de casos o de problemas, desarrollo de procesos o ejecución de propuestas. Entrega de forma individual o grupal, según indicaciones dadas por el profesor). Evaluación final (semana 8 - Cuestionario de entre 15 y 20 preguntas). | Q46: Las acciones de retroalimentación giran en torno a las siguientes. Formar: donde se crean las condiciones para que los estudiantes adquieran conocimientos, habilidades, actitudes, aptitudes y destrezas. Además, debe promover su desarrollo integral y debe acompañarlos en las situaciones académicas que enfrenten durante el desarrollo de un módulo o una asignatura. Informar: para que los estudiantes identifiquen los cambios que pueden afectarlos directa o indirectamente tanto en el aula de clase como en otros espacios. Prevenir: con el fin de anticiparse a las situaciones académicas que pueden representar dificultad para los estudiantes. Esto se logra a través de la interacción individual con los estudiantes y del completo conocimiento del contexto educativo en que el tutor se desenvuelve. Ayudar a decidir: donde se orienta a los estudiantes para que tomen la mejor decisión ante una situación concreta. El objetivo es que el estudiante fortalezca su autonomía y la toma de decisiones responsable.
A47: =_xlfn.XLOOKUP(B47,'Paso 3 Redacción RA '!I$3:I$15,'Paso 3 Redacción RA '!C$3:C$15,,0,1) -> Saberhacer | B47: Utiliza información contable, financiera, tributaria y de auditoría para elaborar reportes, y proyecciones que faciliten la toma de decisiones de distintos tipos de usuarios, considerando sus necesidades y características.
A48: =_xlfn.XLOOKUP(B48,'Paso 3 Redacción RA '!I$3:I$15,'Paso 3 Redacción RA '!C$3:C$15,,0,1) -> Saber | B48: Relaciona métodos cuantitativos y modelos de planeación financiera para explicar dinámicas contables y financieras según el contexto analizado, usando herramientas tecnológicas.
A49: =_xlfn.XLOOKUP(B49,'Paso 3 Redacción RA '!I$3:I$15,'Paso 3 Redacción RA '!C$3:C$15,,0,1) -> Saberhacer | B49: Desarrolla procedimientos contables y tributarios para construir estados financieros conforme a la normativa aplicable, integrando el cumplimiento de obligaciones fiscales de personas naturales y jurídicas. | C49: 3 | D49: Costos de Gestión | E49: Reconoce el sistema de costos como herramienta indispensable en el control y gestión de los recursos económicos, tecnológicos, y humanos, inmersos en los costos de producción de bienes y servicios, para construir información financiera que oriente la toma de decisiones. | F49: TP | H49: X | J49: 3 | K49: =12*J49 -> 36 | L49: =36*J49 -> 108 | M49: =SUM(K49:L49) -> 144 | N49: 1. El Sistema de Costos como Herramienta Estratégica de Gestión 2. Impacto de los costos en el resultado organizacional 3. Estrategia Financiera y Generación de Valor Empresarial 4. Transformación Digital y Sostenibilidad en la Gestión de Costos | O49: Trabajo directo: Ecuentros sincrónicos Mensajería interna Anuncios Trabajo independiente: Lecturas fundamentales y complementarias Material de trabajo Participación en foros | P49: Actividad de puntos evaluables (semana 2 – Cuestionario de 5 preguntas). Entrega previa 1 (semana 3 - Laboratorio, taller, ejercicios, resolución de casos o de problemas, desarrollo de procesos o ejecución de propuestas. Entrega de forma individual o grupal, según indicaciones del profesor). Parcial (semana 4 - Cuestionarios de entre 15 y 20 preguntas). Entrega previa 2 (semana 5 - Laboratorio, taller, ejercicios, resolución de casos o de problemas, desarrollo de procesos o ejecución de propuestas. Entrega de forma individual o grupal, según indicaciones dadas por el profesor). Entrega final (semana 7 - Laboratorio, taller, ejercicios, resolución de casos o de problemas, desarrollo de procesos o ejecución de propuestas. Entrega de forma individual o grupal, según indicaciones dadas por el profesor). Evaluación final (semana 8 - Cuestionario de entre 15 y 20 preguntas). | Q49: Las acciones de retroalimentación giran en torno a las siguientes. Formar: donde se crean las condiciones para que los estudiantes adquieran conocimientos, habilidades, actitudes, aptitudes y destrezas. Además, debe promover su desarrollo integral y debe acompañarlos en las situaciones académicas que enfrenten durante el desarrollo de un módulo o una asignatura. Informar: para que los estudiantes identifiquen los cambios que pueden afectarlos directa o indirectamente tanto en el aula de clase como en otros espacios. Prevenir: con el fin de anticiparse a las situaciones académicas que pueden representar dificultad para los estudiantes. Esto se logra a través de la interacción individual con los estudiantes y del completo conocimiento del contexto educativo en que el tutor se desenvuelve. Ayudar a decidir: donde se orienta a los estudiantes para que tomen la mejor decisión ante una situación concreta. El objetivo es que el estudiante fortalezca su autonomía y la toma de decisiones responsable.
A50: =_xlfn.XLOOKUP(B50,'Paso 3 Redacción RA '!I$3:I$15,'Paso 3 Redacción RA '!C$3:C$15,,0,1) -> Saber | B50: Interpreta la información contable, financiera y tributaria en contextos de aseguramiento y control para establecer su pertinencia y confiabilidad en la resolución de situaciones contables organizacionales.
A51: =_xlfn.XLOOKUP(B51,'Paso 3 Redacción RA '!I$3:I$15,'Paso 3 Redacción RA '!C$3:C$15,,0,1) -> Saberhacer | B51: Utiliza información contable, financiera, tributaria y de auditoría para elaborar reportes, y proyecciones que faciliten la toma de decisiones de distintos tipos de usuarios, considerando sus necesidades y características.
A52: =_xlfn.XLOOKUP(B52,'Paso 3 Redacción RA '!I$3:I$15,'Paso 3 Redacción RA '!C$3:C$15,,0,1) -> Saber | B52: Relaciona métodos cuantitativos y modelos de planeación financiera para explicar dinámicas contables y financieras según el contexto analizado, usando herramientas tecnológicas. | R52: =SUM(J37:J52) -> 18
A53: =_xlfn.XLOOKUP(B53,'Paso 3 Redacción RA '!I$3:I$15,'Paso 3 Redacción RA '!C$3:C$15,,0,1) -> Saber | B53: Identifica fenómenos contemporáneos y su relación con la profesión, para determinar sus impactos e influencia en la sociedad, de forma responsable y crítica. | C53: 4 | D53: Desarrollo Sostenible | E53: Identifica ejemplos de problemas ambientales, sociales y económicos en la sociedad contemporánea para analizar sus causas y efectos desde el enfoque del desarrollo sostenible a escala local y global. Compara enfoques y aproximaciones tanto privados como público/colectivos desde la sostenibilidad y otras visiones alternativas para proponer ideas de solución que respondan a los desafíos contemporáneos. | F53: TP | G53: X | J53: 3 | K53: =12*J53 -> 36 | L53: =36*J53 -> 108 | M53: =SUM(K53:L53) -> 144 | N53: 1. Análisis de la Era del Antropoceno 2. Otras Alternativas al Desarrollo Sostenible 3. Ciudadanía y Políticas Públicas para el Desarrollo Sostenible 4. El aporte de Negocios para la Búsqueda del Desarrollo Sostenible | O53: Trabajo directo: Ecuentros sincrónicos Mensajería interna Anuncios Trabajo independiente: Lecturas fundamentales y complementarias Material de trabajo Participación en foros | P53: Evaluación diagnóstica: Cuestionario inicial de mínimo cinco preguntas que recopila información sobre el conocimiento previo y las habilidades del estudiante. Actividad formativa: Foro individual o grupal, creado para que el estudiante participe activamente en la construcción de su conocimiento y desarrollo de habilidades. Varía entre una actividad entregable y la participación en un foro. Actividad de entrega 1 y 2: Actividad individual o grupal, diseñada para evaluar de manera integral el nivel de conocimiento, comprensión y el desempeño de los indicadores de logro. Varía entre entregas independientes o secuenciales. Actividad evaluativa: Cuestionario de, mínimo, cinco preguntas, que da cuenta del desarrollo total o parcial de los indicadores de logro y el desarrollo de los temas vistos hasta la unidad 3. Autoevaluación: Cuestionario final de mínimo cinco preguntas en el cual el estudiante reflexiona sobre su propio desempeño, habilidades y resultados en un contexto específico. | Q53: Las acciones de retroalimentación giran en torno a las siguientes. Formar: donde se crean las condiciones para que los estudiantes adquieran conocimientos, habilidades, actitudes, aptitudes y destrezas. Además, debe promover su desarrollo integral y debe acompañarlos en las situaciones académicas que enfrenten durante el desarrollo de un módulo o una asignatura. Informar: para que los estudiantes identifiquen los cambios que pueden afectarlos directa o indirectamente tanto en el aula de clase como en otros espacios. Prevenir: con el fin de anticiparse a las situaciones académicas que pueden representar dificultad para los estudiantes. Esto se logra a través de la interacción individual con los estudiantes y del completo conocimiento del contexto educativo en que el tutor se desenvuelve. Ayudar a decidir: donde se orienta a los estudiantes para que tomen la mejor decisión ante una situación concreta. El objetivo es que el estudiante fortalezca su autonomía y la toma de decisiones responsable.
A54: =_xlfn.XLOOKUP(B54,'Paso 3 Redacción RA '!I$3:I$15,'Paso 3 Redacción RA '!C$3:C$15,,0,1) -> Saber | B54: Interpreta la información contable, financiera y tributaria en contextos de aseguramiento y control para establecer su pertinencia y confiabilidad en la resolución de situaciones contables organizacionales. | C54: 4 | D54: Estadística Predictiva | E54: Aplica conceptos de distribuciones muestrales, intervalos de confianza, pruebas de hipótesis y modelos de regresión lineal para estimar parámetros poblacionales orientados a la predicción del comportamiento de una variable en diferentes escenarios. | F54: TP | H54: X | J54: 3 | K54: =12*J54 -> 36 | L54: =36*J54 -> 108 | M54: =SUM(K54:L54) -> 144 | N54: 1. Muestreo y distribuciones muestrales 2. Teoría de la estimación. Estimación de parámetros 3. Pruebas de hipótesis 4. Regresión lineal simple | O54: Trabajo directo: Ecuentros sincrónicos Mensajería interna Anuncios Trabajo independiente: Lecturas fundamentales y complementarias Material de trabajo Participación en foros | P54: Actividad de puntos evaluables (semana 2 – Cuestionario de 5 preguntas). Entrega previa 1 (semana 3 - Laboratorio, taller, ejercicios, resolución de casos o de problemas, desarrollo de procesos o ejecución de propuestas. Entrega de forma individual o grupal, según indicaciones del profesor). Parcial (semana 4 - Cuestionarios de entre 15 y 20 preguntas). Entrega previa 2 (semana 5 - Laboratorio, taller, ejercicios, resolución de casos o de problemas, desarrollo de procesos o ejecución de propuestas. Entrega de forma individual o grupal, según indicaciones dadas por el profesor). Entrega final (semana 7 - Laboratorio, taller, ejercicios, resolución de casos o de problemas, desarrollo de procesos o ejecución de propuestas. Entrega de forma individual o grupal, según indicaciones dadas por el profesor). Evaluación final (semana 8 - Cuestionario de entre 15 y 20 preguntas). | Q54: Las acciones de retroalimentación giran en torno a las siguientes. Formar: donde se crean las condiciones para que los estudiantes adquieran conocimientos, habilidades, actitudes, aptitudes y destrezas. Además, debe promover su desarrollo integral y debe acompañarlos en las situaciones académicas que enfrenten durante el desarrollo de un módulo o una asignatura. Informar: para que los estudiantes identifiquen los cambios que pueden afectarlos directa o indirectamente tanto en el aula de clase como en otros espacios. Prevenir: con el fin de anticiparse a las situaciones académicas que pueden representar dificultad para los estudiantes. Esto se logra a través de la interacción individual con los estudiantes y del completo conocimiento del contexto educativo en que el tutor se desenvuelve. Ayudar a decidir: donde se orienta a los estudiantes para que tomen la mejor decisión ante una situación concreta. El objetivo es que el estudiante fortalezca su autonomía y la toma de decisiones responsable.
A55: =_xlfn.XLOOKUP(B55,'Paso 3 Redacción RA '!I$3:I$15,'Paso 3 Redacción RA '!C$3:C$15,,0,1) -> Saber | B55: Relaciona métodos cuantitativos y modelos de planeación financiera para explicar dinámicas contables y financieras según el contexto analizado, usando herramientas tecnológicas.
A56: =_xlfn.XLOOKUP(B56,'Paso 3 Redacción RA '!I$3:I$15,'Paso 3 Redacción RA '!C$3:C$15,,0,1) -> Saberhacer | B56: Utiliza métodos cuantitativos y herramientas tecnológicas para elaborar reportes sobre la situación contable y financiera de personas naturales, personas jurídicas y organizaciones, a partir de datos y contextos definidos.
A57: =_xlfn.XLOOKUP(B57,'Paso 3 Redacción RA '!I$3:I$15,'Paso 3 Redacción RA '!C$3:C$15,,0,1) -> Saberhacer | B57: Utiliza información contable, financiera, tributaria y de auditoría para elaborar reportes, y proyecciones que faciliten la toma de decisiones de distintos tipos de usuarios, considerando sus necesidades y características. | C57: 4 | D57: Taller Financiero Aplicado a BI | E57: Utiliza la minería de datos, visualización de datos y tableros de control para realizar reportes financieros que permiten orientar la tomar decisiones y eliminar las ineficiencias basadas en una visión integral en los datos. | F57: TP | H57: X | J57: 4 | K57: =12*J57 -> 48 | L57: =36*J57 -> 144 | M57: =SUM(K57:L57) -> 192 | N57: 1. Principales Herramientas de Matemáticas Financieras 2. Diagnóstico Financiero y análisis de la información 3. Introducción a herramientas BI 4. Análisis de información financiera con herramientas BI | O57: Trabajo directo: Ecuentros sincrónicos Mensajería interna Anuncios Trabajo independiente: Lecturas fundamentales y complementarias Material de trabajo Participación en foros | P57: Actividad de puntos evaluables (semana 2 – Cuestionario de 5 preguntas). Entrega previa 1 (semana 3 - Laboratorio, taller, ejercicios, resolución de casos o de problemas, desarrollo de procesos o ejecución de propuestas. Entrega de forma individual o grupal, según indicaciones del profesor). Parcial (semana 4 - Cuestionarios de entre 15 y 20 preguntas). Entrega previa 2 (semana 5 - Laboratorio, taller, ejercicios, resolución de casos o de problemas, desarrollo de procesos o ejecución de propuestas. Entrega de forma individual o grupal, según indicaciones dadas por el profesor). Entrega final (semana 7 - Laboratorio, taller, ejercicios, resolución de casos o de problemas, desarrollo de procesos o ejecución de propuestas. Entrega de forma individual o grupal, según indicaciones dadas por el profesor). Evaluación final (semana 8 - Cuestionario de entre 15 y 20 preguntas). | Q57: Las acciones de retroalimentación giran en torno a las siguientes. Formar: donde se crean las condiciones para que los estudiantes adquieran conocimientos, habilidades, actitudes, aptitudes y destrezas. Además, debe promover su desarrollo integral y debe acompañarlos en las situaciones académicas que enfrenten durante el desarrollo de un módulo o una asignatura. Informar: para que los estudiantes identifiquen los cambios que pueden afectarlos directa o indirectamente tanto en el aula de clase como en otros espacios. Prevenir: con el fin de anticiparse a las situaciones académicas que pueden representar dificultad para los estudiantes. Esto se logra a través de la interacción individual con los estudiantes y del completo conocimiento del contexto educativo en que el tutor se desenvuelve. Ayudar a decidir: donde se orienta a los estudiantes para que tomen la mejor decisión ante una situación concreta. El objetivo es que el estudiante fortalezca su autonomía y la toma de decisiones responsable.
A58: =_xlfn.XLOOKUP(B58,'Paso 3 Redacción RA '!I$3:I$15,'Paso 3 Redacción RA '!C$3:C$15,,0,1) -> Saber | B58: Relaciona métodos cuantitativos y modelos de planeación financiera para explicar dinámicas contables y financieras según el contexto analizado, usando herramientas tecnológicas.
A59: =_xlfn.XLOOKUP(B59,'Paso 3 Redacción RA '!I$3:I$15,'Paso 3 Redacción RA '!C$3:C$15,,0,1) -> Saberhacer | B59: Utiliza métodos cuantitativos y herramientas tecnológicas para elaborar reportes sobre la situación contable y financiera de personas naturales, personas jurídicas y organizaciones, a partir de datos y contextos definidos.
A60: =_xlfn.XLOOKUP(B60,'Paso 3 Redacción RA '!I$3:I$15,'Paso 3 Redacción RA '!C$3:C$15,,0,1) -> Saber | B60: Analiza la normativa vigentes en la preparación y revisión de información contable, financiera y tributaria para identificar criterios técnicos y legales que permitan abordar situaciones contables y fiscales, según el contexto de aplicación. | C60: 4 | D60: Impuesto sobre la Renta Personas Naturales | E60: Aplica la normatividad vigente del impuesto sobre la renta en personas naturales, para preparar declaraciones que respondan a criterios técnicos, éticos y legales en la gestión tributaria. | F60: TP | H60: X | J60: 3 | K60: =12*J60 -> 36 | L60: =36*J60 -> 108 | M60: =SUM(K60:L60) -> 144 | N60: 1. Principios del derecho tributario, obligatoriedad del impuesto de renta y complementarios en personas naturales y anticipo de retención laboral 2. Determinación del patrimonio en personas naturales e impuesto al patrimonio 3. Sistema cedular 4. Ganancias ocasionales y liquidación privada en personas naturales | O60: Trabajo directo: Ecuentros sincrónicos Mensajería interna Anuncios Trabajo independiente: Lecturas fundamentales y complementarias Material de trabajo Participación en foros | P60: Actividad de puntos evaluables (semana 2 – Cuestionario de 5 preguntas). Entrega previa 1 (semana 3 - Laboratorio, taller, ejercicios, resolución de casos o de problemas, desarrollo de procesos o ejecución de propuestas. Entrega de forma individual o grupal, según indicaciones del profesor). Parcial (semana 4 - Cuestionarios de entre 15 y 20 preguntas). Entrega previa 2 (semana 5 - Laboratorio, taller, ejercicios, resolución de casos o de problemas, desarrollo de procesos o ejecución de propuestas. Entrega de forma individual o grupal, según indicaciones dadas por el profesor). Entrega final (semana 7 - Laboratorio, taller, ejercicios, resolución de casos o de problemas, desarrollo de procesos o ejecución de propuestas. Entrega de forma individual o grupal, según indicaciones dadas por el profesor). Evaluación final (semana 8 - Cuestionario de entre 15 y 20 preguntas). | Q60: Las acciones de retroalimentación giran en torno a las siguientes. Formar: donde se crean las condiciones para que los estudiantes adquieran conocimientos, habilidades, actitudes, aptitudes y destrezas. Además, debe promover su desarrollo integral y debe acompañarlos en las situaciones académicas que enfrenten durante el desarrollo de un módulo o una asignatura. Informar: para que los estudiantes identifiquen los cambios que pueden afectarlos directa o indirectamente tanto en el aula de clase como en otros espacios. Prevenir: con el fin de anticiparse a las situaciones académicas que pueden representar dificultad para los estudiantes. Esto se logra a través de la interacción individual con los estudiantes y del completo conocimiento del contexto educativo en que el tutor se desenvuelve. Ayudar a decidir: donde se orienta a los estudiantes para que tomen la mejor decisión ante una situación concreta. El objetivo es que el estudiante fortalezca su autonomía y la toma de decisiones responsable.
A61: =_xlfn.XLOOKUP(B61,'Paso 3 Redacción RA '!I$3:I$15,'Paso 3 Redacción RA '!C$3:C$15,,0,1) -> Saberhacer | B61: Desarrolla procedimientos contables y tributarios para construir estados financieros conforme a la normativa aplicable, integrando el cumplimiento de obligaciones fiscales de personas naturales y jurídicas.
A62: =_xlfn.XLOOKUP(B62,'Paso 3 Redacción RA '!I$3:I$15,'Paso 3 Redacción RA '!C$3:C$15,,0,1) -> Saberser | B62: Reconoce criterios éticos, legales, sociales y estratégicos del saber contable, tributario, financiero y de auditoría para aplicarlos con rigor técnico en la preparación de información de personas naturales y jurídicas, según el contexto o situación.
A63: =_xlfn.XLOOKUP(B63,'Paso 3 Redacción RA '!I$3:I$15,'Paso 3 Redacción RA '!C$3:C$15,,0,1) -> Saberhacer | B63: Utiliza información contable, financiera, tributaria y de auditoría para elaborar reportes, y proyecciones que faciliten la toma de decisiones de distintos tipos de usuarios, considerando sus necesidades y características.
A64: =_xlfn.XLOOKUP(B64,'Paso 3 Redacción RA '!I$3:I$15,'Paso 3 Redacción RA '!C$3:C$15,,0,1) -> Saber | B64: Relaciona métodos cuantitativos y modelos de planeación financiera para explicar dinámicas contables y financieras según el contexto analizado, usando herramientas tecnológicas.
A65: =_xlfn.XLOOKUP(B65,'Paso 3 Redacción RA '!I$3:I$15,'Paso 3 Redacción RA '!C$3:C$15,,0,1) -> Saberser | B65: Reconoce criterios éticos, legales, sociales y estratégicos del saber contable, tributario, financiero y de auditoría para aplicarlos con rigor técnico en la preparación de información de personas naturales y jurídicas, según el contexto o situación. | C65: 4 | D65: Riesgo Operativo y LA/FT | E65: Identifica las características del Sistema de administración de riesgo operativo (SARO)y riesgo de LA y FT en contextos organizacionales para determinar el impacto en el logro de los objetivos estratégicos, tácticos, de proyectos, productos y servicios. | F65: T | H65: X | J65: 4 | K65: =12*J65 -> 48 | L65: =36*J65 -> 144 | M65: =SUM(K65:L65) -> 192 | N65: 1. Generalidades del Riesgo y Sistema de administración de riesgo operativo 2. Medición y tratamiento del riesgo operativo 3. Continuidad de negocio y SARLAFT 4. SaRLAFT y otros sistemas de administración de riesgo de lavado de activos | O65: Trabajo directo: Ecuentros sincrónicos Mensajería interna Anuncios Trabajo independiente: Lecturas fundamentales y complementarias Material de trabajo Participación en foros | P65: Quiz (semana 2 - Cuestionario de 5 preguntas). Entrega inicial (semana 3 – Ensayo, artículo, cuadro comparativo, revisión documental, entre otros). Foro analítico o argumentativo (semanas 5 y 6 – Participación en el espacio correspondiente del aula). Entrega final (semana 7 – Ensayo, artículo, cuadro comparativo, revisión documental, entre otros). Evaluación final (semana 8 – Cuestionario de entre 15 y 20 preguntas). | Q65: Las acciones de retroalimentación giran en torno a las siguientes. Formar: donde se crean las condiciones para que los estudiantes adquieran conocimientos, habilidades, actitudes, aptitudes y destrezas. Además, debe promover su desarrollo integral y debe acompañarlos en las situaciones académicas que enfrenten durante el desarrollo de un módulo o una asignatura. Informar: para que los estudiantes identifiquen los cambios que pueden afectarlos directa o indirectamente tanto en el aula de clase como en otros espacios. Prevenir: con el fin de anticiparse a las situaciones académicas que pueden representar dificultad para los estudiantes. Esto se logra a través de la interacción individual con los estudiantes y del completo conocimiento del contexto educativo en que el tutor se desenvuelve. Ayudar a decidir: donde se orienta a los estudiantes para que tomen la mejor decisión ante una situación concreta. El objetivo es que el estudiante fortalezca su autonomía y la toma de decisiones responsable.
A66: =_xlfn.XLOOKUP(B66,'Paso 3 Redacción RA '!I$3:I$15,'Paso 3 Redacción RA '!C$3:C$15,,0,1) -> Saber | B66: Interpreta la información contable, financiera y tributaria en contextos de aseguramiento y control para establecer su pertinencia y confiabilidad en la resolución de situaciones contables organizacionales.
A67: =_xlfn.XLOOKUP(B67,'Paso 3 Redacción RA '!I$3:I$15,'Paso 3 Redacción RA '!C$3:C$15,,0,1) -> Saberhacer | B67: Utiliza información contable, financiera, tributaria y de auditoría para elaborar reportes, y proyecciones que faciliten la toma de decisiones de distintos tipos de usuarios, considerando sus necesidades y características. | R67: =SUM(J53:J67) -> 17
A68: =_xlfn.XLOOKUP(B68,'Paso 3 Redacción RA '!I$3:I$15,'Paso 3 Redacción RA '!C$3:C$15,,0,1) -> Saber | B68: Interpreta la información contable, financiera y tributaria en contextos de aseguramiento y control para establecer su pertinencia y confiabilidad en la resolución de situaciones contables organizacionales. | C68: 5 | D68: Macroeconomía | E68: Interpreta las variables macroeconómicas y su impacto en el equilibrio, para desarrollar análisis del comportamiento del mercado de bienes y servicios y de las políticas fiscal, monetaria y cambiaria. | F68: TP | H68: X | J68: 3 | K68: =12*J68 -> 36 | L68: =36*J68 -> 108 | M68: =SUM(K68:L68) -> 144 | N68: 1. Generalidades de la macroeconomía, funcionamiento del sistema económico y de las cuentas nacionales 2. Mercado de bienes y servicios y estabilidad macroeconómica 3. Modelo IS-LM 4. La balanza de pagos y el equilibrio general | O68: Trabajo directo: Ecuentros sincrónicos Mensajería interna Anuncios Trabajo independiente: Lecturas fundamentales y complementarias Material de trabajo Participación en foros | P68: Actividad de puntos evaluables (semana 2 – Cuestionario de 5 preguntas). Entrega previa 1 (semana 3 - Laboratorio, taller, ejercicios, resolución de casos o de problemas, desarrollo de procesos o ejecución de propuestas. Entrega de forma individual o grupal, según indicaciones del profesor). Parcial (semana 4 - Cuestionarios de entre 15 y 20 preguntas). Entrega previa 2 (semana 5 - Laboratorio, taller, ejercicios, resolución de casos o de problemas, desarrollo de procesos o ejecución de propuestas. Entrega de forma individual o grupal, según indicaciones dadas por el profesor). Entrega final (semana 7 - Laboratorio, taller, ejercicios, resolución de casos o de problemas, desarrollo de procesos o ejecución de propuestas. Entrega de forma individual o grupal, según indicaciones dadas por el profesor). Evaluación final (semana 8 - Cuestionario de entre 15 y 20 preguntas). | Q68: Las acciones de retroalimentación giran en torno a las siguientes. Formar: donde se crean las condiciones para que los estudiantes adquieran conocimientos, habilidades, actitudes, aptitudes y destrezas. Además, debe promover su desarrollo integral y debe acompañarlos en las situaciones académicas que enfrenten durante el desarrollo de un módulo o una asignatura. Informar: para que los estudiantes identifiquen los cambios que pueden afectarlos directa o indirectamente tanto en el aula de clase como en otros espacios. Prevenir: con el fin de anticiparse a las situaciones académicas que pueden representar dificultad para los estudiantes. Esto se logra a través de la interacción individual con los estudiantes y del completo conocimiento del contexto educativo en que el tutor se desenvuelve. Ayudar a decidir: donde se orienta a los estudiantes para que tomen la mejor decisión ante una situación concreta. El objetivo es que el estudiante fortalezca su autonomía y la toma de decisiones responsable.
A69: =_xlfn.XLOOKUP(B69,'Paso 3 Redacción RA '!I$3:I$15,'Paso 3 Redacción RA '!C$3:C$15,,0,1) -> Saberhacer | B69: Utiliza información contable, financiera, tributaria y de auditoría para elaborar reportes, y proyecciones que faciliten la toma de decisiones de distintos tipos de usuarios, considerando sus necesidades y características.
A70: =_xlfn.XLOOKUP(B70,'Paso 3 Redacción RA '!I$3:I$15,'Paso 3 Redacción RA '!C$3:C$15,,0,1) -> Saber | B70: Relaciona métodos cuantitativos y modelos de planeación financiera para explicar dinámicas contables y financieras según el contexto analizado, usando herramientas tecnológicas.
A71: =_xlfn.XLOOKUP(B71,'Paso 3 Redacción RA '!I$3:I$15,'Paso 3 Redacción RA '!C$3:C$15,,0,1) -> Saber | B71: Analiza la normativa vigentes en la preparación y revisión de información contable, financiera y tributaria para identificar criterios técnicos y legales que permitan abordar situaciones contables y fiscales, según el contexto de aplicación. | C71: 5 | D71: Contabilidades Especiales | E71: Analiza los principios, políticas y procedimientos de la contabilidad y el presupuesto público, para determinar la responsabilidad que tienen los servidores públicos en la gestión y el control financiero conforme al marco legal vigente. | F71: T | H71: X | J71: 3 | K71: =12*J71 -> 36 | L71: =36*J71 -> 108 | M71: =SUM(K71:L71) -> 144 | N71: 1. Conceptualización sobre contabilidad y presupuesto públicos y su relación con la contabilidad privada. 2. Estructura Administrativa del Estado Colombiano. 3. Planeación y Presupuesto Público. 4. Sistema de Contabilidad Pública y Control del Estado. | O71: Trabajo directo: Ecuentros sincrónicos Mensajería interna Anuncios Trabajo independiente: Lecturas fundamentales y complementarias Material de trabajo Participación en foros | P71: Quiz (semana 2 - Cuestionario de 5 preguntas). Entrega inicial (semana 3 – Ensayo, artículo, cuadro comparativo, revisión documental, entre otros). Foro analítico o argumentativo (semanas 5 y 6 – Participación en el espacio correspondiente del aula). Entrega final (semana 7 – Ensayo, artículo, cuadro comparativo, revisión documental, entre otros). Evaluación final (semana 8 – Cuestionario de entre 15 y 20 preguntas). | Q71: Las acciones de retroalimentación giran en torno a las siguientes. Formar: donde se crean las condiciones para que los estudiantes adquieran conocimientos, habilidades, actitudes, aptitudes y destrezas. Además, debe promover su desarrollo integral y debe acompañarlos en las situaciones académicas que enfrenten durante el desarrollo de un módulo o una asignatura. Informar: para que los estudiantes identifiquen los cambios que pueden afectarlos directa o indirectamente tanto en el aula de clase como en otros espacios. Prevenir: con el fin de anticiparse a las situaciones académicas que pueden representar dificultad para los estudiantes. Esto se logra a través de la interacción individual con los estudiantes y del completo conocimiento del contexto educativo en que el tutor se desenvuelve. Ayudar a decidir: donde se orienta a los estudiantes para que tomen la mejor decisión ante una situación concreta. El objetivo es que el estudiante fortalezca su autonomía y la toma de decisiones responsable.
A72: =_xlfn.XLOOKUP(B72,'Paso 3 Redacción RA '!I$3:I$15,'Paso 3 Redacción RA '!C$3:C$15,,0,1) -> Saberhacer | B72: Desarrolla procedimientos contables y tributarios para construir estados financieros conforme a la normativa aplicable, integrando el cumplimiento de obligaciones fiscales de personas naturales y jurídicas.
A73: =_xlfn.XLOOKUP(B73,'Paso 3 Redacción RA '!I$3:I$15,'Paso 3 Redacción RA '!C$3:C$15,,0,1) -> Saberser | B73: Reconoce criterios éticos, legales, sociales y estratégicos del saber contable, tributario, financiero y de auditoría para aplicarlos con rigor técnico en la preparación de información de personas naturales y jurídicas, según el contexto o situación.
A74: =_xlfn.XLOOKUP(B74,'Paso 3 Redacción RA '!I$3:I$15,'Paso 3 Redacción RA '!C$3:C$15,,0,1) -> Saber | B74: Interpreta la información contable, financiera y tributaria en contextos de aseguramiento y control para establecer su pertinencia y confiabilidad en la resolución de situaciones contables organizacionales.
A75: =_xlfn.XLOOKUP(B75,'Paso 3 Redacción RA '!I$3:I$15,'Paso 3 Redacción RA '!C$3:C$15,,0,1) -> Saberhacer | B75: Utiliza información contable, financiera, tributaria y de auditoría para elaborar reportes, y proyecciones que faciliten la toma de decisiones de distintos tipos de usuarios, considerando sus necesidades y características.
A76: =_xlfn.XLOOKUP(B76,'Paso 3 Redacción RA '!I$3:I$15,'Paso 3 Redacción RA '!C$3:C$15,,0,1) -> Saberser | B76: Reconoce criterios éticos, legales, sociales y estratégicos del saber contable, tributario, financiero y de auditoría para aplicarlos con rigor técnico en la preparación de información de personas naturales y jurídicas, según el contexto o situación. | C76: 5 | D76: Comercio Internacional | E76: Describe los principales elementos del comercio internacional, incluyendo el concepto y la aplicación de teorías económicas, la gestión logística y documental, el desarrollo de estrategias de marketing, la selección de opciones de financiación y medios de pago y la implementación de las principales herramientas tecnológicas y prácticas sostenibles para explicar una transacción de intercambio comercial internacional segura y eficiente, cumpliendo con las normativas, la entrada exitosa a nuevos mercados y la sostenibilidad en el comercio internacional. | F76: T | H76: X | J76: 3 | K76: =12*J76 -> 36 | L76: =36*J76 -> 108 | M76: =SUM(K76:L76) -> 144 | N76: 1. Definición y conceptos básicos del comercio internacional 2. Logística, Documentación y Estrategias de Mercado 3. Conceptualización de mercadeo internacional, Financiación y Gestión de Riesgos 4. Herramientas, practicas, innovación y sostenibilidad en el comercio internacional | O76: Trabajo directo: Ecuentros sincrónicos Mensajería interna Anuncios Trabajo independiente: Lecturas fundamentales y complementarias Material de trabajo Participación en foros | P76: Quiz (semana 2 - Cuestionario de 5 preguntas). Entrega inicial (semana 3 – Ensayo, artículo, cuadro comparativo, revisión documental, entre otros). Foro analítico o argumentativo (semanas 5 y 6 – Participación en el espacio correspondiente del aula). Entrega final (semana 7 – Ensayo, artículo, cuadro comparativo, revisión documental, entre otros). Evaluación final (semana 8 – Cuestionario de entre 15 y 20 preguntas). | Q76: Las acciones de retroalimentación giran en torno a las siguientes. Formar: donde se crean las condiciones para que los estudiantes adquieran conocimientos, habilidades, actitudes, aptitudes y destrezas. Además, debe promover su desarrollo integral y debe acompañarlos en las situaciones académicas que enfrenten durante el desarrollo de un módulo o una asignatura. Informar: para que los estudiantes identifiquen los cambios que pueden afectarlos directa o indirectamente tanto en el aula de clase como en otros espacios. Prevenir: con el fin de anticiparse a las situaciones académicas que pueden representar dificultad para los estudiantes. Esto se logra a través de la interacción individual con los estudiantes y del completo conocimiento del contexto educativo en que el tutor se desenvuelve. Ayudar a decidir: donde se orienta a los estudiantes para que tomen la mejor decisión ante una situación concreta. El objetivo es que el estudiante fortalezca su autonomía y la toma de decisiones responsable.
A77: =_xlfn.XLOOKUP(B77,'Paso 3 Redacción RA '!I$3:I$15,'Paso 3 Redacción RA '!C$3:C$15,,0,1) -> Saber | B77: Interpreta la información contable, financiera y tributaria en contextos de aseguramiento y control para establecer su pertinencia y confiabilidad en la resolución de situaciones contables organizacionales.
A78: =_xlfn.XLOOKUP(B78,'Paso 3 Redacción RA '!I$3:I$15,'Paso 3 Redacción RA '!C$3:C$15,,0,1) -> Saberhacer | B78: Utiliza información contable, financiera, tributaria y de auditoría para elaborar reportes, y proyecciones que faciliten la toma de decisiones de distintos tipos de usuarios, considerando sus necesidades y características.
A79: =_xlfn.XLOOKUP(B79,'Paso 3 Redacción RA '!I$3:I$15,'Paso 3 Redacción RA '!C$3:C$15,,0,1) -> Saber | B79: Relaciona métodos cuantitativos y modelos de planeación financiera para explicar dinámicas contables y financieras según el contexto analizado, usando herramientas tecnológicas.
A80: =_xlfn.XLOOKUP(B80,'Paso 3 Redacción RA '!I$3:I$15,'Paso 3 Redacción RA '!C$3:C$15,,0,1) -> Saber | B80: Analiza la normativa vigentes en la preparación y revisión de información contable, financiera y tributaria para identificar criterios técnicos y legales que permitan abordar situaciones contables y fiscales, según el contexto de aplicación. | C80: 5 | D80: Impuesto sobre la Renta Personas Jurídicas | E80: Aplica la normatividad vigente del impuesto sobre la renta en personas jurídicas, para elaborar la declaración tributaria con base en la clasificación, medición y depuración de los elementos que conforman la base gravable. | F80: TP | H80: X | J80: 3 | K80: =12*J80 -> 36 | L80: =36*J80 -> 108 | M80: =SUM(K80:L80) -> 144 | N80: 1. Obligatoriedad del impuesto sobre la renta en personas jurídicas 2. Determinación del patrimonio 3. Depuración de la base gravable 4. Ganancias ocasionales y liquidación privada | O80: Trabajo directo: Ecuentros sincrónicos Mensajería interna Anuncios Trabajo independiente: Lecturas fundamentales y complementarias Material de trabajo Participación en foros | P80: Actividad de puntos evaluables (semana 2 – Cuestionario de 5 preguntas). Entrega previa 1 (semana 3 - Laboratorio, taller, ejercicios, resolución de casos o de problemas, desarrollo de procesos o ejecución de propuestas. Entrega de forma individual o grupal, según indicaciones del profesor). Parcial (semana 4 - Cuestionarios de entre 15 y 20 preguntas). Entrega previa 2 (semana 5 - Laboratorio, taller, ejercicios, resolución de casos o de problemas, desarrollo de procesos o ejecución de propuestas. Entrega de forma individual o grupal, según indicaciones dadas por el profesor). Entrega final (semana 7 - Laboratorio, taller, ejercicios, resolución de casos o de problemas, desarrollo de procesos o ejecución de propuestas. Entrega de forma individual o grupal, según indicaciones dadas por el profesor). Evaluación final (semana 8 - Cuestionario de entre 15 y 20 preguntas). | Q80: Las acciones de retroalimentación giran en torno a las siguientes. Formar: donde se crean las condiciones para que los estudiantes adquieran conocimientos, habilidades, actitudes, aptitudes y destrezas. Además, debe promover su desarrollo integral y debe acompañarlos en las situaciones académicas que enfrenten durante el desarrollo de un módulo o una asignatura. Informar: para que los estudiantes identifiquen los cambios que pueden afectarlos directa o indirectamente tanto en el aula de clase como en otros espacios. Prevenir: con el fin de anticiparse a las situaciones académicas que pueden representar dificultad para los estudiantes. Esto se logra a través de la interacción individual con los estudiantes y del completo conocimiento del contexto educativo en que el tutor se desenvuelve. Ayudar a decidir: donde se orienta a los estudiantes para que tomen la mejor decisión ante una situación concreta. El objetivo es que el estudiante fortalezca su autonomía y la toma de decisiones responsable.
A81: =_xlfn.XLOOKUP(B81,'Paso 3 Redacción RA '!I$3:I$15,'Paso 3 Redacción RA '!C$3:C$15,,0,1) -> Saberhacer | B81: Desarrolla procedimientos contables y tributarios para construir estados financieros conforme a la normativa aplicable, integrando el cumplimiento de obligaciones fiscales de personas naturales y jurídicas.
A82: =_xlfn.XLOOKUP(B82,'Paso 3 Redacción RA '!I$3:I$15,'Paso 3 Redacción RA '!C$3:C$15,,0,1) -> Saberser | B82: Reconoce criterios éticos, legales, sociales y estratégicos del saber contable, tributario, financiero y de auditoría para aplicarlos con rigor técnico en la preparación de información de personas naturales y jurídicas, según el contexto o situación.
A83: =_xlfn.XLOOKUP(B83,'Paso 3 Redacción RA '!I$3:I$15,'Paso 3 Redacción RA '!C$3:C$15,,0,1) -> Saber | B83: Interpreta la información contable, financiera y tributaria en contextos de aseguramiento y control para establecer su pertinencia y confiabilidad en la resolución de situaciones contables organizacionales.
A84: =_xlfn.XLOOKUP(B84,'Paso 3 Redacción RA '!I$3:I$15,'Paso 3 Redacción RA '!C$3:C$15,,0,1) -> Saber | B84: Relaciona métodos cuantitativos y modelos de planeación financiera para explicar dinámicas contables y financieras según el contexto analizado, usando herramientas tecnológicas.
A85: =_xlfn.XLOOKUP(B85,'Paso 3 Redacción RA '!I$3:I$15,'Paso 3 Redacción RA '!C$3:C$15,,0,1) -> Saberser | B85: Reconoce criterios éticos, legales, sociales y estratégicos del saber contable, tributario, financiero y de auditoría para aplicarlos con rigor técnico en la preparación de información de personas naturales y jurídicas, según el contexto o situación. | C85: 5 | D85: Sistemas de Control Interno | E85: Analiza contextos organizacionales a partir de los conceptos, características, procesos administrativos y procedimientos, identificando las necesidades organizacionales para proponer mejoras fundamentadas en la implementación y evaluación de sistemas de control interno como herramientas clave para la sostenibilidad y eficiencia empresarial. | F85: TP | H85: X | J85: 3 | K85: =12*J85 -> 36 | L85: =36*J85 -> 108 | M85: =SUM(K85:L85) -> 144 | N85: 1. Fundamentos de control interno 2. Diseño y planeación del sistema de control interno 3. Implementación del sistema de control interno 4. Evaluación y mejora del sistema de control interno | O85: Trabajo directo: Ecuentros sincrónicos Mensajería interna Anuncios Trabajo independiente: Lecturas fundamentales y complementarias Material de trabajo Participación en foros | P85: Actividad de puntos evaluables (semana 2 – Cuestionario de 5 preguntas). Entrega previa 1 (semana 3 - Laboratorio, taller, ejercicios, resolución de casos o de problemas, desarrollo de procesos o ejecución de propuestas. Entrega de forma individual o grupal, según indicaciones del profesor). Parcial (semana 4 - Cuestionarios de entre 15 y 20 preguntas). Entrega previa 2 (semana 5 - Laboratorio, taller, ejercicios, resolución de casos o de problemas, desarrollo de procesos o ejecución de propuestas. Entrega de forma individual o grupal, según indicaciones dadas por el profesor). Entrega final (semana 7 - Laboratorio, taller, ejercicios, resolución de casos o de problemas, desarrollo de procesos o ejecución de propuestas. Entrega de forma individual o grupal, según indicaciones dadas por el profesor). Evaluación final (semana 8 - Cuestionario de entre 15 y 20 preguntas). | Q85: Las acciones de retroalimentación giran en torno a las siguientes. Formar: donde se crean las condiciones para que los estudiantes adquieran conocimientos, habilidades, actitudes, aptitudes y destrezas. Además, debe promover su desarrollo integral y debe acompañarlos en las situaciones académicas que enfrenten durante el desarrollo de un módulo o una asignatura. Informar: para que los estudiantes identifiquen los cambios que pueden afectarlos directa o indirectamente tanto en el aula de clase como en otros espacios. Prevenir: con el fin de anticiparse a las situaciones académicas que pueden representar dificultad para los estudiantes. Esto se logra a través de la interacción individual con los estudiantes y del completo conocimiento del contexto educativo en que el tutor se desenvuelve. Ayudar a decidir: donde se orienta a los estudiantes para que tomen la mejor decisión ante una situación concreta. El objetivo es que el estudiante fortalezca su autonomía y la toma de decisiones responsable.
A86: =_xlfn.XLOOKUP(B86,'Paso 3 Redacción RA '!I$3:I$15,'Paso 3 Redacción RA '!C$3:C$15,,0,1) -> Saber | B86: Interpreta la información contable, financiera y tributaria en contextos de aseguramiento y control para establecer su pertinencia y confiabilidad en la resolución de situaciones contables organizacionales.
A87: =_xlfn.XLOOKUP(B87,'Paso 3 Redacción RA '!I$3:I$15,'Paso 3 Redacción RA '!C$3:C$15,,0,1) -> Saberhacer | B87: Utiliza información contable, financiera, tributaria y de auditoría para elaborar reportes, y proyecciones que faciliten la toma de decisiones de distintos tipos de usuarios, considerando sus necesidades y características.
A88: =_xlfn.XLOOKUP(B88,'Paso 3 Redacción RA '!I$3:I$15,'Paso 3 Redacción RA '!C$3:C$15,,0,1) -> Saberhacer | B88: Utiliza información contable, financiera, tributaria y de auditoría para elaborar reportes, y proyecciones que faciliten la toma de decisiones de distintos tipos de usuarios, considerando sus necesidades y características. | C88: 5 | D88: Evaluación de Proyectos | E88: Evalúa la factibilidad financiera de un proyecto de inversión mediante la formulación de supuestos, la proyección de estados financieros y la aplicación de métodos de decisión, para determinar su viabilidad y apoyar la toma de decisiones en contextos empresariales. | F88: TP | H88: X | J88: 3 | K88: =12*J88 -> 36 | L88: =36*J88 -> 108 | M88: =SUM(K88:L88) -> 144 | N88: 1. Conceptos básicos contables y financieros para la evaluación de proyectos 2. Flujos de caja en proyectos de inversión 3. Métodos de decisión financiera 4. Análisis de sensibilidad en los proyectos | O88: Trabajo directo: Ecuentros sincrónicos Mensajería interna Anuncios Trabajo independiente: Lecturas fundamentales y complementarias Material de trabajo Participación en foros | P88: Actividad de puntos evaluables (semana 2 – Cuestionario de 5 preguntas). Entrega previa 1 (semana 3 - Laboratorio, taller, ejercicios, resolución de casos o de problemas, desarrollo de procesos o ejecución de propuestas. Entrega de forma individual o grupal, según indicaciones del profesor). Parcial (semana 4 - Cuestionarios de entre 15 y 20 preguntas). Entrega previa 2 (semana 5 - Laboratorio, taller, ejercicios, resolución de casos o de problemas, desarrollo de procesos o ejecución de propuestas. Entrega de forma individual o grupal, según indicaciones dadas por el profesor). Entrega final (semana 7 - Laboratorio, taller, ejercicios, resolución de casos o de problemas, desarrollo de procesos o ejecución de propuestas. Entrega de forma individual o grupal, según indicaciones dadas por el profesor). Evaluación final (semana 8 - Cuestionario de entre 15 y 20 preguntas). | Q88: Las acciones de retroalimentación giran en torno a las siguientes. Formar: donde se crean las condiciones para que los estudiantes adquieran conocimientos, habilidades, actitudes, aptitudes y destrezas. Además, debe promover su desarrollo integral y debe acompañarlos en las situaciones académicas que enfrenten durante el desarrollo de un módulo o una asignatura. Informar: para que los estudiantes identifiquen los cambios que pueden afectarlos directa o indirectamente tanto en el aula de clase como en otros espacios. Prevenir: con el fin de anticiparse a las situaciones académicas que pueden representar dificultad para los estudiantes. Esto se logra a través de la interacción individual con los estudiantes y del completo conocimiento del contexto educativo en que el tutor se desenvuelve. Ayudar a decidir: donde se orienta a los estudiantes para que tomen la mejor decisión ante una situación concreta. El objetivo es que el estudiante fortalezca su autonomía y la toma de decisiones responsable.
A89: =_xlfn.XLOOKUP(B89,'Paso 3 Redacción RA '!I$3:I$15,'Paso 3 Redacción RA '!C$3:C$15,,0,1) -> Saber | B89: Relaciona métodos cuantitativos y modelos de planeación financiera para explicar dinámicas contables y financieras según el contexto analizado, usando herramientas tecnológicas.
A90: =_xlfn.XLOOKUP(B90,'Paso 3 Redacción RA '!I$3:I$15,'Paso 3 Redacción RA '!C$3:C$15,,0,1) -> Saberhacer | B90: Utiliza métodos cuantitativos y herramientas tecnológicas para elaborar reportes sobre la situación contable y financiera de personas naturales, personas jurídicas y organizaciones, a partir de datos y contextos definidos. | R90: =SUM(J68:J90) -> 18
A91: =_xlfn.XLOOKUP(B91,'Paso 3 Redacción RA '!I$3:I$15,'Paso 3 Redacción RA '!C$3:C$15,,0,1) -> Saber | B91: Analiza la normativa vigentes en la preparación y revisión de información contable, financiera y tributaria para identificar criterios técnicos y legales que permitan abordar situaciones contables y fiscales, según el contexto de aplicación. | C91: 6 | D91: Auditoría y Aseguramiento de la Información Financiera | E91: Aplica las normas de aseguramiento de la información y los principios éticos de la profesión, para desarrollar procesos de auditoría y aseguramiento que permitan sustentar la razonabilidad de los informes financieros. | F91: TP | H91: X | J91: 4 | K91: =12*J91 -> 48 | L91: =36*J91 -> 144 | M91: =SUM(K91:L91) -> 192 | N91: 1. Normas de Aseguramiento de la Información 2. Fundamentos y Planeación General de la Auditoria Financiera 3. Ejecución de la Auditoria Financiera 4. Informe y conclusión de la Auditoria Financiera | O91: Trabajo directo: Ecuentros sincrónicos Mensajería interna Anuncios Trabajo independiente: Lecturas fundamentales y complementarias Material de trabajo Participación en foros | P91: Actividad de puntos evaluables (semana 2 – Cuestionario de 5 preguntas). Entrega previa 1 (semana 3 - Laboratorio, taller, ejercicios, resolución de casos o de problemas, desarrollo de procesos o ejecución de propuestas. Entrega de forma individual o grupal, según indicaciones del profesor). Parcial (semana 4 - Cuestionarios de entre 15 y 20 preguntas). Entrega previa 2 (semana 5 - Laboratorio, taller, ejercicios, resolución de casos o de problemas, desarrollo de procesos o ejecución de propuestas. Entrega de forma individual o grupal, según indicaciones dadas por el profesor). Entrega final (semana 7 - Laboratorio, taller, ejercicios, resolución de casos o de problemas, desarrollo de procesos o ejecución de propuestas. Entrega de forma individual o grupal, según indicaciones dadas por el profesor). Evaluación final (semana 8 - Cuestionario de entre 15 y 20 preguntas). | Q91: Las acciones de retroalimentación giran en torno a las siguientes. Formar: donde se crean las condiciones para que los estudiantes adquieran conocimientos, habilidades, actitudes, aptitudes y destrezas. Además, debe promover su desarrollo integral y debe acompañarlos en las situaciones académicas que enfrenten durante el desarrollo de un módulo o una asignatura. Informar: para que los estudiantes identifiquen los cambios que pueden afectarlos directa o indirectamente tanto en el aula de clase como en otros espacios. Prevenir: con el fin de anticiparse a las situaciones académicas que pueden representar dificultad para los estudiantes. Esto se logra a través de la interacción individual con los estudiantes y del completo conocimiento del contexto educativo en que el tutor se desenvuelve. Ayudar a decidir: donde se orienta a los estudiantes para que tomen la mejor decisión ante una situación concreta. El objetivo es que el estudiante fortalezca su autonomía y la toma de decisiones responsable.
A92: =_xlfn.XLOOKUP(B92,'Paso 3 Redacción RA '!I$3:I$15,'Paso 3 Redacción RA '!C$3:C$15,,0,1) -> Saberser | B92: Reconoce criterios éticos, legales, sociales y estratégicos del saber contable, tributario, financiero y de auditoría para aplicarlos con rigor técnico en la preparación de información de personas naturales y jurídicas, según el contexto o situación.
A93: =_xlfn.XLOOKUP(B93,'Paso 3 Redacción RA '!I$3:I$15,'Paso 3 Redacción RA '!C$3:C$15,,0,1) -> Saber | B93: Interpreta la información contable, financiera y tributaria en contextos de aseguramiento y control para establecer su pertinencia y confiabilidad en la resolución de situaciones contables organizacionales.
A94: =_xlfn.XLOOKUP(B94,'Paso 3 Redacción RA '!I$3:I$15,'Paso 3 Redacción RA '!C$3:C$15,,0,1) -> Saberhacer | B94: Utiliza información contable, financiera, tributaria y de auditoría para elaborar reportes, y proyecciones que faciliten la toma de decisiones de distintos tipos de usuarios, considerando sus necesidades y características.
A95: =_xlfn.XLOOKUP(B95,'Paso 3 Redacción RA '!I$3:I$15,'Paso 3 Redacción RA '!C$3:C$15,,0,1) -> Saber | B95: Analiza la normativa vigentes en la preparación y revisión de información contable, financiera y tributaria para identificar criterios técnicos y legales que permitan abordar situaciones contables y fiscales, según el contexto de aplicación. | C95: 6 | D95: Impuestos sobre las Ventas e Impuestos Territoriales | E95: Aplica la normatividad tributaria vigente sobre impuestos nacionales y territoriales de las empresas, para sustentar el cumplimiento de las obligaciones formales y sustanciales según el sector y la actividad económica desarrollada, y su relación con la retención en la fuente. | F95: TP | H95: X | J95: 3 | K95: =12*J95 -> 36 | L95: =36*J95 -> 108 | M95: =SUM(K95:L95) -> 144 | N95: 1. Retención en la Fuente 2. Impuesto al Valor Agregado IVA 3. Impuesto Nacional al consumo 4. Impuestos territoriales | O95: Trabajo directo: Ecuentros sincrónicos Mensajería interna Anuncios Trabajo independiente: Lecturas fundamentales y complementarias Material de trabajo Participación en foros | P95: Actividad de puntos evaluables (semana 2 – Cuestionario de 5 preguntas). Entrega previa 1 (semana 3 - Laboratorio, taller, ejercicios, resolución de casos o de problemas, desarrollo de procesos o ejecución de propuestas. Entrega de forma individual o grupal, según indicaciones del profesor). Parcial (semana 4 - Cuestionarios de entre 15 y 20 preguntas). Entrega previa 2 (semana 5 - Laboratorio, taller, ejercicios, resolución de casos o de problemas, desarrollo de procesos o ejecución de propuestas. Entrega de forma individual o grupal, según indicaciones dadas por el profesor). Entrega final (semana 7 - Laboratorio, taller, ejercicios, resolución de casos o de problemas, desarrollo de procesos o ejecución de propuestas. Entrega de forma individual o grupal, según indicaciones dadas por el profesor). Evaluación final (semana 8 - Cuestionario de entre 15 y 20 preguntas). | Q95: Las acciones de retroalimentación giran en torno a las siguientes. Formar: donde se crean las condiciones para que los estudiantes adquieran conocimientos, habilidades, actitudes, aptitudes y destrezas. Además, debe promover su desarrollo integral y debe acompañarlos en las situaciones académicas que enfrenten durante el desarrollo de un módulo o una asignatura. Informar: para que los estudiantes identifiquen los cambios que pueden afectarlos directa o indirectamente tanto en el aula de clase como en otros espacios. Prevenir: con el fin de anticiparse a las situaciones académicas que pueden representar dificultad para los estudiantes. Esto se logra a través de la interacción individual con los estudiantes y del completo conocimiento del contexto educativo en que el tutor se desenvuelve. Ayudar a decidir: donde se orienta a los estudiantes para que tomen la mejor decisión ante una situación concreta. El objetivo es que el estudiante fortalezca su autonomía y la toma de decisiones responsable.
A96: =_xlfn.XLOOKUP(B96,'Paso 3 Redacción RA '!I$3:I$15,'Paso 3 Redacción RA '!C$3:C$15,,0,1) -> Saberhacer | B96: Desarrolla procedimientos contables y tributarios para construir estados financieros conforme a la normativa aplicable, integrando el cumplimiento de obligaciones fiscales de personas naturales y jurídicas.
A97: =_xlfn.XLOOKUP(B97,'Paso 3 Redacción RA '!I$3:I$15,'Paso 3 Redacción RA '!C$3:C$15,,0,1) -> Saberser | B97: Reconoce criterios éticos, legales, sociales y estratégicos del saber contable, tributario, financiero y de auditoría para aplicarlos con rigor técnico en la preparación de información de personas naturales y jurídicas, según el contexto o situación.
A98: =_xlfn.XLOOKUP(B98,'Paso 3 Redacción RA '!I$3:I$15,'Paso 3 Redacción RA '!C$3:C$15,,0,1) -> Saber | B98: Interpreta la información contable, financiera y tributaria en contextos de aseguramiento y control para establecer su pertinencia y confiabilidad en la resolución de situaciones contables organizacionales.
A99: =_xlfn.XLOOKUP(B99,'Paso 3 Redacción RA '!I$3:I$15,'Paso 3 Redacción RA '!C$3:C$15,,0,1) -> Saberhacer | B99: Utiliza información contable, financiera, tributaria y de auditoría para elaborar reportes, y proyecciones que faciliten la toma de decisiones de distintos tipos de usuarios, considerando sus necesidades y características.
A100: =_xlfn.XLOOKUP(B100,'Paso 3 Redacción RA '!I$3:I$15,'Paso 3 Redacción RA '!C$3:C$15,,0,1) -> Saberhacer | B100: Desarrolla procedimientos contables y tributarios para construir estados financieros conforme a la normativa aplicable, integrando el cumplimiento de obligaciones fiscales de personas naturales y jurídicas. | C100: 6 | D100: Contabilidad Estratégica de Costos | E100: Analiza estrategias y técnicas de gestión de costos de acuerdo con las necesidades de las organizaciones en contextos nacional e internacional, para elaborar la estructura de costos idónea que permita orientar la toma de decisiones. | F100: TP | H100: X | J100: 3 | K100: =12*J100 -> 36 | L100: =36*J100 -> 108 | M100: =SUM(K100:L100) -> 144 | N100: 1. Costos Estándar 2. Costos Basados en Actividades (Activity Based Cost System – ABC) 3. Costos Estratégicos y Modelos de Valor Empresarial 4. Costos ambientales | O100: Trabajo directo: Ecuentros sincrónicos Mensajería interna Anuncios Trabajo independiente: Lecturas fundamentales y complementarias Material de trabajo Participación en foros | P100: Actividad de puntos evaluables (semana 2 – Cuestionario de 5 preguntas). Entrega previa 1 (semana 3 - Laboratorio, taller, ejercicios, resolución de casos o de problemas, desarrollo de procesos o ejecución de propuestas. Entrega de forma individual o grupal, según indicaciones del profesor). Parcial (semana 4 - Cuestionarios de entre 15 y 20 preguntas). Entrega previa 2 (semana 5 - Laboratorio, taller, ejercicios, resolución de casos o de problemas, desarrollo de procesos o ejecución de propuestas. Entrega de forma individual o grupal, según indicaciones dadas por el profesor). Entrega final (semana 7 - Laboratorio, taller, ejercicios, resolución de casos o de problemas, desarrollo de procesos o ejecución de propuestas. Entrega de forma individual o grupal, según indicaciones dadas por el profesor). Evaluación final (semana 8 - Cuestionario de entre 15 y 20 preguntas). | Q100: Las acciones de retroalimentación giran en torno a las siguientes. Formar: donde se crean las condiciones para que los estudiantes adquieran conocimientos, habilidades, actitudes, aptitudes y destrezas. Además, debe promover su desarrollo integral y debe acompañarlos en las situaciones académicas que enfrenten durante el desarrollo de un módulo o una asignatura. Informar: para que los estudiantes identifiquen los cambios que pueden afectarlos directa o indirectamente tanto en el aula de clase como en otros espacios. Prevenir: con el fin de anticiparse a las situaciones académicas que pueden representar dificultad para los estudiantes. Esto se logra a través de la interacción individual con los estudiantes y del completo conocimiento del contexto educativo en que el tutor se desenvuelve. Ayudar a decidir: donde se orienta a los estudiantes para que tomen la mejor decisión ante una situación concreta. El objetivo es que el estudiante fortalezca su autonomía y la toma de decisiones responsable.
...

Sheet Taxonomia para Competencias
B1: Verbos Competencias
B2: Actualizar
B3: Administrar
B4: Analizar
B5: Aplicar
B6: Asegurar
B7: Asesorar
B8: Auditar
B9: Comunicar
B10: Conducir
B11: Conocer
B12: Coordinar
... B38: Verificar

Sheet Taxonomias para RA
S1: Taxonomía de Bloom Adaptada bajo las ideas de Anderson y Krathwohl | AL1: Taxonomía de Bloom adaptada bajo las ideas de Lorin y Krathwohl (LK) | AT1: Taxonomía de Bloom adaptada bajo las ideas de Anderson y Kendal (AK)
L2: Taxonomía de Bloom | S2: Cognitivo(BAK) | Y2: Procedimental(BAK) | AC2: Actitudinal(BAK)
A3: Taxonomías | C3: BAK | D3: LK | E3: AK | G3: CognitivoB | H3: ProcedimentalB | I3: ActitudinalB | L3: ConocimientoB | M3: ComprensiónB | N3: AplicaciónB | O3: AnálisisB | P3: SíntesisB | Q3: EvaluaciónB | S3: ConocimientoBAK | T3: ComprensiónBAK | U3: AplicaciónBAK | V3: AnálisisBAK | W3: SíntesisBAK | X3: EvaluaciónBAK | Y3: ImitaciónBAK | Z3: ManipulaciónBAK | AA3: PrecisiónBAK | AB3: ControlBAK | AC3: PercepciónBAK | AD3: ResponderBAK | AE3: ValorarBAK | AF3: OrganizarBAK | AG3: CaracterizarBAK | AL3: Procesos cognitivos de orden inferior | AO3: Procesos cognitivos de orden superior
A4: Bloom | C4: CognitivoBAK | D4: HechosLK | E4: InformaciónAK | G4: ConocimientoB | H4: ConocimientoB | I4: ConocimientoB | L4: Adquirir | M4: Auditar | N4: Aplicar | O4: Aislar | P4: Adaptar | Q4: Aconsejar | S4: Adquirir | T4: Auditar | U4: Aplicar | V4: Aislar | W4: Adaptar | X4: Aconsejar | Y4: Ajustar | Z4: Direccionar | AA4: Disponer | AB4: Remover | AC4: Hacer | AD4: Aprobar | AE4: Adoptar | AF4: Extraer | AG4: Negociar | AL4: RecordarLK | AM4: ComprenderLK | AN4: AplicarLK | AO4: AnalizarLK | AP4: EvaluarLK | AQ4: CrearLK | AT4: RecuperaciónAK | AU4: ComprensiónAK | AV4: AnálisisAK | AW4: UsoConocimientoAK | AX4: MetacogniciónAK | AY4: SistemadelYoAK
A5: BAK | C5: ProcedimentalBAK | D5: ConceptosLK | E5: ProcesosMentalesAK | G5: ComprensiónB | H5: ComprensiónB | I5: ComprensiónB | L5: Buscar | M5: Bosquejar | N5: Calisificar | O5: Analizar | P5: Administrar | Q5: Adjuntar | S5: Buscar | T5: Bosquejar | U5: Calisificar | V5: Analizar | W5: Administrar | X5: Adjuntar | Y5: Adaptar | Z5: Desmontar | AA5: Planear | AB5: Quitar | AC5: Conducir | AD5: Autorizar | AE5: Aprobar | AF5: Resumir | AG5: Ofrecer | AL5: Afirmar | AM5: Clasificar | AN5: Actuar | AO5: Agrupar | AP5: Adaptar | AQ5: Desarrollar | AT5: Afirmar | AU5: Auditar | AV5: Agrupar | AW5: Actuar | AX5: Aceptar | AY5: Aceptar
A6: LK | C6: ActitudinalBAK | D6: ProcedimientoslLK | E6: PsicomotorAK | G6: AplicaciónB | H6: AplicaciónB | I6: AplicaciónB | L6: Citar | M6: Comentar | N6: Combinar | O6: Calcular | P6: Arreglar | Q6: Agregar | S6: Citar | T6: Comentar | U6: Combinar | V6: Calcular | W6: Arreglar | X6: Agregar | Y6: Modificar | Z6: Dramatizar | AA6: Apalancar | AB6: Suprimir | AC6: Dirigir | AD6: Demostrar | AE6: Aceptar | AF6: Promover | AG6: Conducir | AL6: Citar | AM6: Comparar | AN6: Agrupar | AO6: Aislar | AP6: Añadir | AQ6: Elaborar | AT6: Citar | AU6: Bosquejar | AV6: Aislar | AW6: Agrupar | AX6: Adelantar | AY6: Adoptar
A7: AK | D7: MetacogniciónLK | G7: AnálisisB | H7: AnálisisB | I7: AnálisisB | L7: Consignar | M7: Comunicar | N7: Componer | O7: Categorizar | P7: Arreglar | Q7: Alinear | S7: Consignar | T7: Comunicar | U7: Componer | V7: Categorizar | W7: Arreglar | X7: Alinear | Y7: Concretar | Z7: Docificar | AA7: Levantar | AB7: Eliminar | AC7: Direccionar | AD7: Afirmar | AE7: Afirmar | AF7: Adelantar | AG7: Comportarse bajo condiciones | AL7: Copiar | AM7: Contrastar | AN7: Calcular | AO7: Asumir | AP7: Apoyar | AQ7: Maximizar | AT7: Copiar | AU7: Clasificar | AV7: Analizar | AW7: Aplicar | AX7: Adoptar | AY7: Afinar
G8: SíntesisB | H8: SíntesisB | I8: SíntesisB | L8: Decir | M8: Convertir | N8: Conducir | O8: Comparar | P8: Articular | Q8: Arbitrar | S8: Decir | T8: Convertir | U8: Conducir | V8: Comparar | W8: Articular | X8: Arbitrar | Y8: Asegurar | Z8: Dibujar | AA8: Estimular | AB8: Retirar | AC8: Aplicar | AD8: Asegurar | AE8: Ratificar | AF8: Fomentar | AG8: Completar | AL8: Decir | AM8: Demostrar | AN8: Categorizar | AO8: Buscar similitudes | AP8: Argumentar | AQ8: Mejorar | AT8: Decir | AU8: Comentar | AV8: Aplicar | AW8: Calcular | AX8: Afinar | AY8: Agradecer
G9: EvaluaciónB | H9: EvaluaciónB | I9: EvaluaciónB | L9: Definir | M9: Criticar | N9: Construir | O9: Considerar | P9: Aumentar | Q9: Asegurar | S9: Definir | T9: Criticar | U9: Construir | V9: Considerar | W9: Aumentar | X9: Asegurar | Y9: Alinear | Z9: Trazar | AA9: Localizar | AB9: Extirpar | AC9: Manejar | AD9: Hacer | AE9: Apreciar | AF9: Anticipar | AG9: Afinar | AL9: Definir | AM9: Discutir | AN9: Conectar | AO9: Categorizar | AP9: Cambiar | AQ9: Minimizar | AT9: Definir | AU9: Comparar | AV9: Asumir | AW9: Calisificar | AX9: Afirmar | AY9: Ambicionar
L10: Deletrear | M10: Dar ejemplos | N10: Demostrar | O10: Contrastar | P10: Calcular | Q10: Asesorar | S10: Deletrear | T10: Dar ejemplos | U10: Demostrar | V10: Contrastar | W10: Calcular | X10: Asesorar | Y10: Analizar | Z10: Hacer | AA10: Ubicar | AB10: Disipar | AC10: Guiar | AD10: Comunicar | AE10: Comprender | AF10: Proponer | AG10: Acabar | AL10: Deletrear | AM10: Ejemplificar | AN10: Construir | AO10: Centrarse | AP10: Combinar | AQ10: Modelar | AT10: Deletrear | AU10: Comunicar | AV10: Buscar similitudes | AW10: Categorizar | AX10: Agradecer | AY10: Anhelar
G11: HechosLK | H11: ConceptosLK | I11: ProcedimientosLK | J11: MetacogniciónLK | L11: Demostrar | M11: Debatir | N11: Determinar | O11: Criticar | P11: Componer | Q11: Atar | S11: Demostrar | T11: Debatir | U11: Determinar | V11: Criticar | W11: Componer | X11: Atar | Y11: Aplicar | Z11: Extraer | AA11: Encontrar | AB11: Hacer | AC11: Realizar | AD11: Hablar | AE11: Agradecer | AF11: Defender | AG11: Terminar | AL11: Duplicar | AM11: Esquematizar | AN11: Demostrar | AO11: Comparar | AP11: Comparar | AQ11: Pensar | AT11: Duplicar | AU11: Contrastar | AV11: Calcular | AW11: Combinar | AX11: Ambicionar | AY11: Anticipar
G12: RecordarLK | H12: RecordarLK | I12: RecordarLK | J12: RecordarLK | L12: Describir | M12: Describir | N12: Dibujar | O12: Cuestionar | P12: Computar | Q12: Calcular | S12: Describir | T12: Describir | U12: Dibujar | V12: Cuestionar | W12: Computar | X12: Calcular | Y12: Arreglar | Z12: Perforar | AA12: Colocar | AB12: Reproducir | AC12: Emplear | AD12: Discutir | AE12: Estimar | AF12: Proteger | AG12: Contextualizar | AL12: Elegir | AM12: Explicar | AN12: Desarrollar | AO12: Correlacionar | AP12: Compilar | AQ12: Planear | AT12: Elegir | AU12: Convertir | AV12: Calisificar | AW12: Componer | AX12: Anhelar | AY12: Apreciar
G13: ComprenderLK | H13: ComprenderLK | I13: ComprenderLK | J13: ComprenderLK | L13: Elegir | M13: Desplegar | N13: Discriminar | O13: Debatir | P13: Concluir | Q13: Calificar | S13: Elegir | T13: Desplegar | U13: Discriminar | V13: Debatir | W13: Concluir | X13: Calificar | Y13: Organizar | Z13: Ejercitar | AA13: Establecer | AB13: Traducir | AC13: Aceptar | AD13: Cooperar | AE13: Tasar | AF13: Definir | AG13: Cooperar | AL13: Escribir | AM13: Expresar | AN13: Dramatizar | AO13: Descomponer | AP13: Componer | AQ13: Proponer | AT13: Escribir | AU13: Criticar | AV13: Categorizar | AW13: Conducir | AX13: Anticipar | AY13: Aprobar
G14: AplicarLK | H14: AplicarLK | I14: AplicarLK | J14: AplicarLK | L14: Enseñar | M14: Dibujar | N14: Diseñar | O14: Deducir | P14: Conectar | Q14: Censurar | S14: Enseñar | T14: Dibujar | U14: Diseñar | V14: Deducir | W14: Conectar | X14: Censurar | Y14: Ordenar | Z14: Enseñar | AA14: Hallar | AB14: Entregar | AC14: Admitir | AD14: Colaborar | AE14: Aspirar | AF14: Determinar | AG14: Colaborar | AL14: Leer | AM14: Generalizar | AN14: Elegir | AO14: Diferenciar | AP14: Construir | AQ14: Reescribir | AT14: Leer | AU14: Dar ejemplos | AV14: Centrarse | AW14: Conectar | AX14: Apoyar | AY14: Asistir
G15: AnalizarLK | H15: AnalizarLK | I15: AnalizarLK | J15: AnalizarLK | L15: Escribir | M15: Discutir | N15: Dramatizar | O15: Desarrollar | P15: Construir | Q15: Clasificar | S15: Escribir | T15: Discutir | U15: Dramatizar | V15: Desarrollar | W15: Construir | X15: Clasificar | Y15: Disponer | Z15: Conducir | AA15: Situar | AB15: Conducir | AC15: Evaluar | AD15: Actuar recíprocamente | AE15: Ambicionar | AF15: Considerar | AG15: Discriminar | AL15: Listar | AM15: Ilustrar | AN15: Emplear | AO15: Distinguir | AP15: Convencer | AQ15: Simplificar | AT15: Listar | AU15: Debatir | AV15: Combinar | AW15: Construir | AX15: Apreciar | AY15: Aspirar
G16: EvaluarLK | H16: EvaluarLK | I16: EvaluarLK | J16: EvaluarLK | L16: Establecer | M16: Diseñar | N16: Duplicar | O16: Detectar | P16: Crear | Q16: Computar | S16: Establecer | T16: Diseñar | U16: Duplicar | V16: Detectar | W16: Crear | X16: Computar | Y16: Acordar | Z16: Dirigir | AA16: Bajar | AB16: Direccionar | AC16: Valorar | AD16: Obrar recíprocamente | AE16: Anhelar | AF16: Discernir | AG16: Distinguir | AL16: Localizar | AM16: Inferir | AN16: Enseñar | AO16: Dividir | AP16: Crear | AQ16: Suponer | AT16: Localizar | AU16: Demostrar | AV16: Comparar | AW16: Demostrar | AX16: Aprobar | AY16: Atender
G17: CrearLK | H17: CrearLK | I17: CrearLK | J17: CrearLK | L17: Etiquetar | M17: Establecer | N17: Elegir | O17: Diagramar | P17: Decidir | Q17: Concluir | S17: Etiquetar | T17: Establecer | U17: Elegir | V17: Diagramar | W17: Decidir | X17: Concluir | Y17: Gestionar | Z17: Manejar | AA17: Manipular | AB17: Reparar | AC17: Apreciar | AD17: Recitar | AE17: Creer | AF17: Percibir | AG17: Categorizar | AL17: Memorizar | AM17: Informar | AN17: Entrevistar | AO17: Elegir | AP17: Criticar | AQ17: Sustituir | AT17: Memorizar | AU17: Describir | AV17: Componer | AW17: Desarrollar | AX17: Arreglar | AY17: Categorizar
L18: Examinar | M18: Examinar | N18: Emparejar | O18: Diferenciar | P18: Deducir | Q18: Conformar | S18: Examinar | T18: Examinar | U18: Emparejar | V18: Diferenciar | W18: Deducir | X18: Conformar | Y18: Armar | Z18: Guiar | AA18: Manejar | AB18: Componer | AC18: Tasar | AD18: Decir | AE18: Ser partidario de | AF18: Identificar | AG18: Juzgar | AL18: Mostrar | AM18: Interpretar | AN18: Hacer uso | AO18: Encontrar | AP18: Debatir | AQ18: Teorizar | AT18: Mostrar | AU18: Desplegar | AV18: Conducir | AW18: Determinar | AX18: Asistir | AY18: Clasificar
G19: InformaciónAK | H19: ProcesosAK | I19: PsicomotorAK | L19: Examinar | M19: Explicar | N19: Emplear | O19: Discernir | P19: Derivar | Q19: Constrastar | S19: Examinar | T19: Explicar | U19: Emplear | V19: Discernir | W19: Derivar | X19: Constrastar | Y19: Ensamblar | Z19: Examinar | AA19: Medir | AB19: Reemplazar | AC19: Estimar | AD19: Enumerar | AE19: Cuidar | AF19: Reconocer | AG19: Participar | AL19: Nombrar | AM19: Mostrar | AN19: Identificar | AO19: Encuestar | AP19: Decidir | AQ19: Testar | AT19: Nombrar | AU19: Dibujar | AV19: Considerar | AW19: Dibujar | AX19: Aspirar | AY19: Completar
G20: RecuperaciónAK | H20: RecuperaciónAK | I20: RecuperaciónAK | L20: Grabar | M20: Exponer | N20: Esquematizar | O20: Discriminar | P20: Desarrollar | Q20: Contabilizar | S20: Grabar | T20: Exponer | U20: Esquematizar | V20: Discriminar | W20: Desarrollar | X20: Contabilizar | Y20: Reunir | Z20: Ejecutar | AA20: Racionar | AB20: Sustituir | AC20: Preguntar | AD20: Narrar | AE20: Atender | AF20: Formular | AG20: Atender | AL20: Observar | AM20: Observar | AN20: Interpretar | AO20: Establecer | AP20: Deducir | AQ20: Transformar | AT20: Observar | AU20: Discutir | AV20: Construir | AW20: Discriminar | AX20: Atender | AY20: Comprender
G21: ComprensiónAK | H21: ComprensiónAK | I21: ComprensiónAK | L21: Hacer | M21: Expresar | N21: Estimar | O21: Distinguir | P21: Describir | Q21: Controlar | S21: Hacer | T21: Expresar | U21: Estimar | V21: Distinguir | W21: Describir | X21: Controlar | Y21: Construir | Z21: Explorar | AA21: Separer | AB21: Reponer | AC21: Interrogar | AD21: Referir | AE21: Asistir | AF21: Arreglar | AG21: Servir | AL21: Omitir | AM21: Parafrasear | AN21: Manipular | AO21: Examinar | AP21: Defender | AQ21: Visualizar | AT21: Omitir | AU21: Diseñar | AV21: Contrastar | AW21: Diseñar | AX21: Aunar | AY21: Conducir
G22: AnálisisAK | H22: AnálisisAK | I22: AnálisisAK | L22: Identificar | M22: Extraer | N22: Estructurar | O22: Estructurar | P22: Desempeñar | Q22: Corregir | S22: Identificar | T22: Extraer | U22: Estructurar | V22: Estructurar | W22: Desempeñar | X22: Corregir | Y22: Edificar | Z22: Expresar | AA22: Dividir | AB22: Colocar | AC22: Publicar | AD22: Resolver | AE22: Preocuparse de o por | AF22: Preguntar | AG22: Cumplir | AL22: Rastrear | AM22: Predecir | AN22: Organizar | AO22: Inferir | AP22: Demostrar | AT22: Parafrasear | AU22: Ejemplificar | AV22: Correlacionar | AW22: Dramatizar | AX22: Categorizar | AY22: Conectar
G23: UsoConocimientoAK | H23: UsoConocimientoAK | I23: UsoConocimientoAK | L23: Ilustrar | M23: Generalizar | N23: Estructurar | O23: Examinar | P23: Dirigir | Q23: Criticar | S23: Ilustrar | T23: Generalizar | U23: Estructurar | V23: Examinar | W23: Dirigir | X23: Criticar | Y23: Hacer | Z23: Encajar | AA23: Repartir | AB23: Ubicar | AC23: Asisitir | AD23: Acordar | AE23: Elegir | AF23: Cuestionar | AG23: Ejercer | AL23: Recitar | AM23: Preguntar | AN23: Planear | AO23: Inspeccionar | AP23: Descubrir | AT23: Rastrear | AU23: Esquematizar | AV23: Criticar | AW23: Duplicar | AX23: Clasificar | AY23: Considerar
G24: MetacogniciónAK | H24: MetacogniciónAK | I24: MetacogniciónAK | L24: Listar | M24: Hacer | N24: Evaluar | O24: Experimentar | P24: Diseñar | Q24: Cuestionar | S24: Listar | T24: Hacer | U24: Evaluar | V24: Experimentar | W24: Diseñar | X24: Cuestionar | Y24: Trazar | Z24: Ajustar | AA24: Mezclar | AB24: Ejecutar | AC24: Atender | AD24: Seleccionar | AE24: Seleccionar | AF24: Relacionar | AG24: Entregar | AL24: Reconocer | AM24: Relacionar | AN24: Practicar | AO24: Investigar | AP24: Diseñar | AT24: Recitar | AU24: Establecer | AV24: Cuestionar | AW24: Elegir | AX24: Colaborar | AY24: Constatar
G25: AutoSistemaAK | H25: AutoSistemaAK | I25: AutoSistemaAK | L25: Mostar | M25: Identificar | N25: Experimentar | O25: Inspeccionar | P25: Ejercer | Q25: Culminar | S25: Mostar | T25: Identificar | U25: Experimentar | V25: Inspeccionar | W25: Ejercer | X25: Culminar | Y25: Preparar | Z25: Acceder | AA25: Porcionar | AB25: Correr | AC25: Servir | AD25: Elegir | AE25: Escoger | AF25: Conectar | AG25: Apoyar | AL25: Relacionar | AM25: Resumir | AN25: Resolver | AO25: Motivar | AP25: Estimar | AT25: Reconocer | AU25: Examinar | AV25: Debatir | AW25: Emparejar | AX25: Compartir | AY25: Contextualizar
L26: Nombrar | M26: Indicar | N26: Ilustrar | O26: Inventariar | P26: Ensamblar | Q26: Debatir | S26: Nombrar | T26: Indicar | U26: Ilustrar | V26: Inventariar | W26: Ensamblar | X26: Debatir | Y26: Cambiar | Z26: Arreglar | AA26: Modificar | AB26: Llevar | AC26: Ocupar | AD26: Escoger | AE26: Clasificar | AF26: Relatar | AG26: Soportar | AL26: Relacionar | AM26: Revisar | AN26: Resumir | AO26: Observar | AP26: Evaluar | AT26: Relacionar | AU26: Explicar | AV26: Deducir | AW26: Emplear | AX26: Completar | AY26: Cuestionar
L27: Numerar | M27: Inferir | N27: Indicar | O27: Investigar | P27: Escribir | Q27: Decidir | S27: Numerar | T27: Inferir | U27: Indicar | V27: Investigar | W27: Escribir | X27: Decidir | Y27: Modificar | Z27: Mejorar | AA27: Ajustar | AB27: Manejar | AC27: Elegir | AD27: Clasificar | AE27: Convocar | AF27: Revelar | AG27: Verificar | AL27: Repetir | AM27: Traducir | AN27: Seleccionar | AO27: Ordenar | AP27: Experimentar | AT27: Repetir | AU27: Exponer | AV27: Demostrar | AW27: Enseñar | AX27: Comportarse bajo condiciones | AY27: Cuidar
L28: Observar | M28: Interpretar | N28: Interpretar | O28: Listar | P28: Establecer | Q28: Deducir | S28: Observar | T28: Interpretar | U28: Interpretar | V28: Listar | W28: Establecer | X28: Deducir | Y28: Transformar | Z28: Manipular | AA28: Mover | AB28: Seguir | AC28: Escoger | AD28: Contar | AE28: Unir | AF28: Exteriorizar | AG28: Constatar | AN28: Simular | AO28: Preguntar | AP28: Explicar | AU28: Expresar | AV28: Desarrollar | AW28: Entrevistar | AX28: Comprender | AY28: Cumplir
L29: Obtener | M29: Inventariar | N29: Investigar | O29: Medir | P29: Estudiar | Q29: Defender | S29: Obtener | T29: Inventariar | U29: Investigar | V29: Medir | W29: Estudiar | X29: Defender | Y29: Comprobar | Z29: Maniobrar | AA29: Maniobrar | AB29: Trasladar | AC29: Seleccionar | AD29: Informar | AE29: Ensamblar | AF29: Desplegar | AG29: Controlar | AN29: Transferir | AO29: Priorizar | AP29: Extender | AU29: Extraer | AV29: Descomponer | AW29: Esquematizar | AX29: Conducir | AY29: Defender
L30: Ordenar | M30: Localizar | N30: Listar | O30: Planear | P30: Figurar | Q30: Defender | S30: Ordenar | T30: Localizar | U30: Listar | V30: Planear | W30: Figurar | X30: Defender | Y30: Verificar | Z30: Identificar | AA30: Gestionar | AB30: Implementar | AC30: Escuchar | AD30: Indicar | AE30: Participar | AN30: Unir | AO30: Probar | AP30: Formular | AU30: Generalizar | AV30: Detectar | AW30: Estimar | AX30: Conectar | AY30: Determinar
L31: Organizar | M31: Narrar | N31: Manipular | O31: Preguntar | P31: Formular | Q31: Determinar | S31: Organizar | T31: Narrar | U31: Manipular | V31: Preguntar | W31: Formular | X31: Determinar | Y31: Controlar | Z31: Inspeccionar | AA31: Negociar | AB31: Esculpir | AC31: Anotar | AD31: Distinguir | AE31: Aunar | AN31: Usar | AO31: Razonar | AP31: Hipotetizar | AU31: Hacer | AV31: Determinar | AW31: Estructurar | AX31: Considerar | AY31: Discernir
L32: Preguntar | M32: Parafrasear | N32: Modelar | O32: Probar | P32: Generar | Q32: Discutir | S32: Preguntar | T32: Parafrasear | U32: Modelar | V32: Probar | W32: Generar | X32: Discutir | Y32: Contrastar | Z32: Revisar | AA32: Emitir | AB32: Entallar | AC32: Observar | AD32: Relatar | AE32: Proporcionar | AO32: Reorganizar | AP32: Influir | AU32: Identificar | AV32: Diagramar | AW32: Evaluar | AX32: Constatar | AY32: Discriminar
L33: Presentar | M33: Presentar | N33: Operar | O33: Reconocer | P33: Gestionar | Q33: Elegir | S33: Presentar | T33: Presentar | U33: Operar | V33: Reconocer | W33: Gestionar | X33: Elegir | Y33: Contar | Z33: Registrar | AA33: Abrir | AB33: Servir | AC33: Cumplir | AD33: Conocer | AE33: Estimular | AO33: Resaltar | AP33: Innovar | AU33: Ilustrar | AV33: Dibujar | AW33: Experimentar | AX33: Contextualizar | AY33: Distinguir
L34: Probar | M34: Relatar | N34: Organizar | O34: Relacionar | P34: Hacer | Q34: Ensamblar | S34: Probar | T34: Relatar | U34: Organizar | V34: Relacionar | W34: Hacer | X34: Ensamblar | Y34: Limpiar | Z34: Reconocer | AA34: Destapar | AB34: Coser | AC34: Examinar | AD34: Aplicar | AE34: Contribuir | AO34: Separar | AP34: Justificar | AU34: Indicar | AV34: Diferenciar | AW34: Hacer uso | AX34: Contribuir | AY34: Ejercer
L35: Realizar | M35: Reportar | N35: Patronar | O35: Separar | P35: Inferir | Q35: Escoger | S35: Realizar | T35: Reportar | U35: Patronar | V35: Separar | W35: Inferir | X35: Escoger | Y35: Filtrar | Z35: Instalar | AA35: Comenzar | AB35: Soldar | AC35: Usar | AE35: Provocar | AO35: Simplificar | AP35: Juzgar | AU35: Inferir | AV35: Discernir | AW35: Identificar | AX35: Controlar | AY35: Elegir
L36: Reconocer | M36: Resumir | N36: Practicar | O36: Subdividir | P36: Instalar | Q36: Establecer | S36: Reconocer | T36: Resumir | U36: Practicar | V36: Subdividir | W36: Instalar | X36: Establecer | Y36: Escoger | Z36: Poner | AA36: Operar | AB36: Clasificar | AC36: Decir | AE36: Compartir | AP36: Medir | AU36: Informar | AV36: Discriminar | AW36: Ilustrar | AX36: Convocar | AY36: Escoger
L37: Recordar | M37: Revisar | N37: Recoger | P37: Interpretar | Q37: Estimar | S37: Recordar | T37: Revisar | U37: Recoger | W37: Interpretar | X37: Estimar | Y37: Recoger | Z37: Colocar | AA37: Dirigir | AB37: Ordenar | AC37: Apreciar | AE37: Apoyar | AP37: Opinar | AU37: Interpretar | AV37: Diseñar | AW37: Indicar | AX37: Cooperar | AY37: Estimar
L38: Registrar | M38: Seleccionar | N38: Relacionar | P38: Introducir | Q38: Evaluar | S38: Registrar | T38: Seleccionar | U38: Relacionar | W38: Introducir | X38: Evaluar | Y38: Recaudar | Z38: Inventariar | AA38: Impulsar | AB38: Arreglar | AC38: Distinguir | AE38: Soportar | AP38: Originar | AU38: Inventariar | AV38: Distinguir | AW38: Interpretar | AX38: Creer | AY38: Estimular
L39: Relacionar | M39: Separar | N39: Reportar | P39: Inventar | Q39: Evaluar | S39: Relacionar | T39: Separar | U39: Reportar | W39: Inventar | X39: Evaluar | Y39: Juntar | Z39: Aislar | AA39: Organizar | AB39: Extender | AC39: Detectar | AP39: Percibir | AU39: Localizar | AV39: Dividir | AW39: Investigar | AX39: Cuestionar | AY39: Exteriorizar
L40: Relatar | M40: Traducir | N40: Resolver | P40: Juntar | Q40: Finalizar | S40: Relatar | T40: Traducir | U40: Resolver | W40: Juntar | X40: Finalizar | Y40: Comparar | Z40: Ampliar | AA40: Ordenar | AB40: Ensanchar | AC40: Clasificar | AP40: Persuadir | AU40: Mostrar | AV40: Dramatizar | AW40: Listar | AX40: Cuidar | AY40: Extraer
L41: Reproducir | M41: Transformar | N41: Transferir | P41: Manipular | Q41: Formar | S41: Reproducir | T41: Transformar | U41: Transferir | W41: Manipular | X41: Formar | Y41: Cotejar | AA41: Revisar | AB41: Preguntar | AP41: Premiar | AU41: Narrar | AV41: Duplicar | AW41: Manipular | AX41: Cumplir | AY41: Formular
L42: Revisar | M42: Ubicar | N42: Usar | P42: Mejorar | Q42: Justificar | S42: Revisar | T42: Ubicar | U42: Usar | W42: Mejorar | X42: Justificar | Y42: Conducir | AA42: Repasar | AB42: Mover | AP42: Probar | AU42: Observar | AV42: Elegir | AW42: Modelar | AX42: Defender | AY42: Identificar
L43: Rotular | M43: Relacionar | N43: Valorar | P43: Modificar | Q43: Juzgar | S43: Rotular | U43: Valorar | W43: Modificar | X43: Juzgar | Y43: Direccionar | AA43: Empaquetar | AB43: Balancear | AP43: Recomendar | AU43: Predecir | AV43: Emparejar | AW43: Operar | AX43: Definir | AY43: Juzgar
L44: Seleccionar | N44: Utilizar | P44: Numerar | Q44: Marcar | S44: Seleccionar | W44: Numerar | X44: Marcar | Y44: Inspeccionar | AA44: Envasar | AB44: Reconocer | AP44: Seleccionar | AU44: Preguntar | AV44: Emplear | AW44: Organizar | AX44: Desplegar | AY44: Negociar
L45: Subrayar | P45: Obtener | Q45: Marcar | S45: Subrayar | W45: Obtener | X45: Marcar | Y45: Coordinar | AA45: Pintar | AB45: Inspeccionar | AP45: Testar | AU45: Presentar | AV45: Encontrar | AW45: Patronar | AX45: Determinar | AY45: Ofrecer
P46: Ordenar | Q46: Medir | W46: Ordenar | X46: Medir | Y46: Cortar | AA46: Realizar | AB46: Diseñar | AP46: Valorar | AU46: Relacionar | AV46: Encuestar | AW46: Planear | AX46: Discernir | AY46: Participar
P47: Organizar | Q47: Modificar | W47: Organizar | X47: Modificar | Y47: Recortar | AA47: Hacer | AB47: Sincronizar | AU47: Relatar | AV47: Esquematizar | AW47: Practicar | AX47: Discriminar | AY47: Percibir
P48: Organizar | Q48: Numerar | W48: Organizar | X48: Numerar | Y48: Bailar | AA48: Ejecutar | AB48: Verificar | AU48: Reportar | AV48: Establecer | AW48: Recoger | AX48: Distinguir | AY48: Preguntar
P49: Perfeccionar | Q49: Peritar | W49: Perfeccionar | X49: Peritar | Y49: Demostrar | AA49: Cumplir | AB49: Validar | AU49: Resumir | AV49: Estimar | AW49: Relacionar | AX49: Ejercer | AY49: Promover
P50: Planear | Q50: Predecir | W50: Planear | X50: Predecir | Y50: Detectar | AA50: Actuar | AB50: Revisar | AU50: Revisar | AV50: Estructurar | AW50: Reportar | AX50: Elegir | AY50: Proponer
P51: Planificar | Q51: Pronosticar | W51: Planificar | X51: Pronosticar | Y51: Señalar | AA51: Ejercer | AB51: Probar | AU51: Seleccionar | AV51: Evaluar | AW51: Resolver | AX51: Ensamblar | AY51: Proporcionar
P52: Poner | Q52: Recomendar | W52: Poner | X52: Recomendar | Y52: Probar | AA52: Interpretar | AB52: Difundir | AU52: Separar | AV52: Examinar | AW52: Resumir | AX52: Entregar | AY52: Provocar
P53: Predecir | Q53: Repartir | W53: Predecir | X53: Repartir | AA53: Tocar | AB53: Transmitir | AU53: Traducir | AV53: Experimentar | AW53: Seleccionar | AX53: Escoger | AY53: Reconocer
P54: Preparar | Q54: Resolver | W54: Preparar | X54: Resolver | AA54: Representar | AB54: Resolver | AU54: Transformar | AV54: Ilustrar | AW54: Simular | AX54: Estimar | AY54: Relacionar
P55: Producir | Q55: Reunir | W55: Producir | X55: Reunir | AA55: Practicar | AB55: Tapizar | AU55: Ubicar | AV55: Indicar | AW55: Transferir | AX55: Estimular | AY55: Resumir
P56: Proponer | Q56: Revisar | W56: Proponer | X56: Revisar | AA56: Entrenar | AB56: Usar | AV56: Inferir | AW56: Unir | AX56: Exteriorizar | AY56: Seleccionar
P57: Proyectar | Q57: Seleccionar | W57: Proyectar | X57: Seleccionar | AA57: Grabar | AB57: Emplear | AV57: Inspeccionar | AW57: Usar | AX57: Extraer | AY57: Ser partidario de
P58: Resolver | Q58: Sistematizar | W58: Resolver | X58: Sistematizar | AA58: Sacar | AB58: Utilizar | AV58: Interpretar | AX58: Fomentar | AY58: Unir
P59: Reunir | Q59: Sugerir | W59: Reunir | X59: Sugerir | AA59: Imprimir | AB59: Ponderar | AV59: Inventariar | AX59: Formular | AY59: Valorar
P60: Señalar | Q60: Tasar | W60: Señalar | X60: Tasar | AA60: Estampar | AB60: Mecanizar | AV60: Investigar | AX60: Identificar
P61: Simplificar | Q61: Terminar | W61: Simplificar | X61: Terminar | AA61: Extraer | AB61: Industrializar | AV61: Listar | AX61: Juzgar
P62: Subdividir | Q62: Unir | W62: Subdividir | X62: Unir | AA62: Producir | AB62: Codificar | AV62: Manipular | AX62: Negociar
P63: Suponer | Q63: Validar | W63: Suponer | X63: Validar | AA63: Fabricar | AV63: Medir | AX63: Ofrecer
Q64: Valorar | X64: Valorar | AA64: Presentar | AV64: Modelar | AX64: Participar
Q65: Verificar | X65: Verificar | AA65: Cortar | AV65: Motivar | AX65: Percibir
Q66: Vincular | X66: Vincular | AA66: Reducir | AV66: Observar | AX66: Preguntar
AA67: Mitigar | AV67: Operar | AX67: Preocuparse de o por
AA68: Emitir | AV68: Ordenar | AX68: Promover
AA69: Proponer | AV69: Organizar | AX69: Proponer
AA70: Evaluar | AV70: Patronar | AX70: Proporcionar
AV71: Planear | AX71: Proteger
AV72: Practicar | AX72: Provocar
AV73: Preguntar | AX73: Ratificar
AV74: Priorizar | AX74: Reconocer
AV75: Probar | AX75: Relacionar
AV76: Razonar | AX76: Relatar
AV77: Recoger | AX77: Resumir
AV78: Reconocer | AX78: Revelar
AV79: Relacionar | AX79: Seleccionar
AV80: Reorganizar | AX80: Ser partidario de
AV81: Reportar | AX81: Servir
AV82: Resaltar | AX82: Soportar
... AV87: Transferir | AX87: Verificar
AV88: Usar
